[
  {
    "category": "Galaxy Watch",
    "title": "Samsung L705 Galaxy Watch Ultra Titanium White",
    "price": 1199.0,
    "link": "https://zoommer.ge/smart-saatebi/samsung-l705-galaxy-watch-ultra-titanium-white-p43711",
    "image": "/_next/image?url=https%3A%2F%2Fs3.zoommer.ge%2Fsite%2F7170c76d-cc49-4170-9ac6-331819b1a00d_Thumb.jpeg&w=384&q=50",
    "product_title_detail": "Samsung L705 Galaxy Watch Ultra Titanium White",
    "description": "*7007 / +995 (32) 2 60 30 60\nსავაჭრო პოლიტიკა\nგანვადება\nკარიერა\nTrade In\nფილიალები\nნავიგაცია\nკალათა\nშესვლა\n%\nმთავარი\nსმარტ საათები\nSamsung\n#ZOOM-034257\nSamsung L705 Galaxy Watch Ultra Titanium White\nეკრანის ზომა\n47 mm\nრეზოლუცია\n480 x 480 pixels\nსამუშაო დრო\n-\nეკრანის ტიპი\nSuper Amoled\nშიდა მეხსიერება\n32 GB\nBluetooth\n5.3\nოპერატიული მეხსიერება\n2 GB\nელემენტი\n590 mAh\nფერი: Titanium White\nერთად იაფია\nდაამატე ნივთი\nSamsung L705 Galaxy Watch Ultra Titanium White\n1199 ₾\nSamsung Travel Adapter 25W EP-T2510 White\n52.25 ₾\n55 ₾\nჯამური ფასი (1)\n1251.25 ₾\n1254 ₾\nყიდვა\nაღწერა\nმსგავსი\nმახასიათებლები\nფილიალები\nაღწერა\nმსგავსი\nმახასიათებლები\nფილიალები\nპროდუქტის შესახებ\n\nSamsung L705 Galaxy Watch Ultra Titanium White - ფლაგმანური სმარტ საათი, შექმნილი მათთვის, ვინც აქტიურ დღის რეჟიმს აერთიანებს ტექნოლოგიურ სიზუსტესთან. მისი ძირითადი მიზანია, დაგეხმაროთ მუდმივად კავშირ...\n\nმეტის ნახვა\nმსგავსი პროდუქტები\n399 ₾\n\nთვეში: 11 ₾ -დან\n\nSamsung Galaxy Watch FE Pink Gold\nდამატება\n1199 ₾\n1299 ₾\n\nთვეში: 33 ₾ -დან\n\nSamsung L705 Galaxy Watch Ultra Titanium Grey\nდამატება\n1199 ₾\n1299 ₾\n\nთვეში: 33 ₾ -დან\n\nSamsung L705 Galaxy Watch Ultra Titanium Silver\nდამატება\n549 ₾\n669 ₾\n\nთვეში: 15 ₾ -დან\n\nSamsung SM-R950 43mm Galaxy Watch 6 Classic Silver\nდამატება\n499 ₾\n\nთვეში: 13 ₾ -დან\n\nSamsung SM-R940 44mm Galaxy Watch 6 Silver\nდამატება\n569 ₾\n649 ₾\n\nთვეში: 15 ₾ -დან\n\nSamsung SM-R960 47mm Galaxy Watch 6 Classic Silver\nდამატება\n449 ₾\n499 ₾\n\nთვეში: 12 ₾ -დან\n\nSamsung L300 40mm Galaxy Watch 7 Cream\nდამატება\n449 ₾\n499 ₾\n\nთვეში: 12 ₾ -დან\n\nSamsung L300 40mm Galaxy Watch 7 Green\nდამატება\n549 ₾\n\nთვეში: 15 ₾ -დან\n\nSamsung L310 44mm Galaxy Watch 7 Green\nდამატება\n549 ₾\n\nთვეში: 15 ₾ -დან\n\nSamsung L310 44mm Galaxy Watch 7 Silver\nდამატება\n139 ₾\n\nთვეში: 3 ₾ -დან\n\nSamsung Galaxy Fit 3 R390 Silver\nდამატება\nდამატებითი მახასიათებლები\nბრენდი\nბრენდი:\n\t\nSamsung\nტექნიკური მახასიათებლები\nკავშირის სტანდარტი:\n\t\nNo\n\n\nSIM ბარათი:\n\t\n-\n\n\nკორპუსი:\n\t\nტიტანიუმი\n\n\nIP დაცვა :\n\t\nIP68, 10 ATM\n\n\nოპერაციული სისტემა:\n\t\nWear OS\n\n\nჩიპსეტი:\n\t\nExynos W1000\n\n\nNFC:\n\t\nYes\n\n\nBluetooth:\n\t\n5.3\n\n\nსენსორი:\n\t\nAccelerometer, Gyro, Heart Rate, Barometer, Altimeter, Compass, SpO2, Temperature (body), Temperature (water), BioActive\n\n\nსპიკერი:\n\t\nYes\n\n\nქართული ენის მხარდაჭერა:\n\t\nYes\n\n\nგადახდის ფუნქცია (Pay):\n\t\nYes\n\n\nკამერა:\n\t\nNo\nეკრანი\nეკრანის ზომა:\n\t\n47 mm\n\n\nეკრანის ტიპი:\n\t\nSuper Amoled\n\n\nPPI:\n\t\n327 ppi\n\n\nრეზოლუცია:\n\t\n480 x 480 pixels\n\n\nეკრანის სიკაშკაშე:\n\t\n-\n\n\nAlways on Display:\n\t\nYes\nდამატებითი მახასიათებლები\nWi-Fi:\n\t\nYes\n\n\nGPS:\n\t\nYes\nმეხსიერება\nშიდა მეხსიერება:\n\t\n32 GB\n\n\nოპერატიული მეხსიერება:\n\t\n2 GB\nთავსებადობა\nთავსებადობა (Android; iOS):\n\t\nAndroid\nელემენტი\nელემენტი:\n\t\n590 mAh\n\n\nელემენტი დამუხტვის სიჩქარე:\n\t\n10 W\n\n\nელემენტის ტიპი:\n\t\nLi-Ion\n\n\nWireless დამუხტვა:\n\t\nYes\n\n\nსამუშაო დრო:\n\t\n-\nზომა/წონა\nწონა:\n\t\n60.5 g\nფერი\nფერი:\n\t\nTitanium White\nმეტის ნახვა\nგაეცანი საგარანტიო პირობებს\nსაგარანტიო პირობები\nგაეცანი პროდუქტის სახელმძღვანელოს\nპროდუქტის სახელმძღვანელო\nგაეცანი სერტიფიკატს\nსერტიფიკატი\nფილიალები\nმარაგშია\nშეკვეთიდან 2-5 დღეში\nზუმერის წერეთლის ფილიალი\n\nთბილისი - წერეთლის გამზირი, N1.\n\nმარაგშია\n+995 591 967 601\nორშ-შაბ: 10:00:00 - 20:00:00\nკვირა: 10:00:00 - 19:00:00\nზუმერის \"თბილისი ცენტრალის\" ფილიალი\n\nთბილისი - \"თბილისი ცენტრალი\"- lll სართული\n\nმარაგშია\n+995 599 862 449\nორშ-შაბ: 10:00:00 - 20:00:00\nკვირა: 10:00:00 - 19:00:00\nზუმერის თბილისი მოლის ფილიალი\n\nთბილისი - „თბილისი მოლი\" - I სართული. აღმაშენებლის ხეივანი მე-16 კმ\n\nმარაგშია\n+995 591 967 608\nორშ-შაბ: 10:00:00 - 22:00:00\nკვირა: 10:00:00 - 22:00:00\nზუმერის \"გლდანი მოლის\" ფილიალი\n\nთბილისი - \"გლდანი მოლი\" - I სართული, M-ახმეტელის მიმდებარე\n\nმარაგშია\n+995 591 967 673\nორშ-შაბ: 10:00:00 - 21:00:00\nკვირა: 10:00:00 - 21:00:00\nზუმერის ისთ ფოინთის ფილიალი\n\nთბილისი - \"ისთ ფოინთი\" - ალ. თვალჭრელიძე N2\n\nმარაგშია\n+995 591 340 476\nორშ-შაბ: 10:00:00 - 22:00:00\nკვირა: 10:00:00 - 22:00:00\nზუმერი რუსთავი მოლის ფილიალი\n\nრუსთავი - შარტავას და ლომოურის კვეთა\n\nმარაგშია\n+995 591 441 082\nორშ-შაბ: 10:00:00 - 22:00:00\nკვირა: 10:00:00 - 22:00:00\nბათუმი ჭავჭავაძის ფილიალი\n\nბათუმი - ბათუმი, ჭავჭავაძის N21\n\nმარაგშია\n+995 591 967 606\nორშ-შაბ: 10:00:00 - 20:00:00\nკვირა: 10:00:00 - 19:00:00\nბათუმის \"Black Sea Mall\"-ის ფილიალი\n\nბათუმი - \"Black Sea Mall\" - ტბელ აბუსერიძის N22\n\nმარაგშია\n+995 591 310 257\nორშ-შაბ: 10:00:00 - 21:00:00\nკვირა: 10:00:00 - 21:00:00\nბათუმის გრანდ მოლის ფილიალი\n\nბათუმი - \"გრანდ მოლი\" - შერიფ ხიმშიაშვილის 29\n\nმარაგშია\n+995 591 022 872\nორშ-შაბ: 10:00:00 - 22:00:00\nკვირა: 10:00:00 - 22:00:00\nქუთაისის ფილიალი\n\nქუთაისი - თამარ მეფის ქ. N3 , ქუთაისის ცენტრალური მოედანი\n\nმარაგშია\n+955 591 967 605\nორშ-შაბ: 10:00:00 - 20:00:00\nკვირა: 10:00:00 - 19:00:00\nქუთაისი ვესთ მოლი\n\nქუთაისი - \"ვესთ მოლი\" - შარტავას N2\n\nმარაგშია\n+995 595 306 765\nორშ-შაბ: 10:00:00 - 22:00:00\nკვირა: 10:00:00 - 22:00:00\nზუგდიდი მოლის ფილიალი\n\nზუგდიდი - ზუგდიდი მოლი, კოსტავას ქუჩა №28\n\nმარაგშია\n+995 591 676 489\nორშ-შაბ: 10:00:00 - 22:00:00\nკვირა: 10:00:00 - 22:00:00\nგორი მოლის ფილიალი\n\nგორი - გორი, ცხინვალის გზატკეცილი 14-14ამ, გორი მოლი\n\nმარაგშია\n+995 591 198 248\nორშ-შაბ: 10:00:00 - 22:00:00\nკვირა: 10:00:00 - 22:00:00\nახალციხის ფილიალი\n\nახალციხე - ახალციხე, თამარ მეფის ქ. N9\n\nმარაგშია\n+995 598 088 659\nორშ-შაბ: 10:00:00 - 19:00:00\nკვირა: 10:00:00 - 19:00:00\nთელავი მოლის ფილიალი\n\nთელავი - \"თელავი მოლი\" - ალაზნის ქ.N77\n\nმარაგშია\n+995 595 069 853\nორშ-შაბ: 10:00:00 - 20:00:00\nკვირა: 10:00:00 - 19:00:00\nმეტის ნახვა\n1199 ₾\n1299 ₾\n\nთვეში: 33.3 ₾ -დან\n\nმარაგი ფილიალებში\nფასის დაზღვევა\nფასის კონტროლი\nფასის დაჯავშნა\nყიდვა\nშედარება\nდამატება\nნავიგაცია\n\nპერსონალურ მონაცემთა დაცვის პოლიტიკა\n\nჩვენ შესახებ\n\nწესები და პირობები\n\nმიწოდების სერვისი\n\nკარიერა\n\nგადახდები\n\nSetanta Sports\n\nგადახდის მეთოდები\n\nგარანტია\n\nგანვადება\n\nნივთის დაბრუნება\n\nნივთის ონლაინ ყიდვის ინსტრუქცია\n\nგამოგვყევი\n\nFacebook\n\nYoutube\n\nInstagram\n\nTik Tok\n\nკონტაქტი\n\nInfo@zoommer.ge\n\n+995 (32) 2 60 30 60 / *7007\n\nფილიალები\n\nკორპორატიული გაყიდვები\n\nZoommer App\n\nCopyright © 2023 Zoommer.ge. All rights reserved.\n\nCookie პოლიტიკა\n\nსაიტით სარგებლობის გაგრძელებით, შენ ეთანხმები Cookie ჩანაწერების გამოყენებას. მეტი ინფორმაცისათვის იხილეთ კონფიდენციალურობის პოლიტიკა\n\nგასაგებია",
    "specs": {
      "ბრენდი:": "Samsung",
      "კავშირის სტანდარტი:": "No",
      "SIM ბარათი:": "-",
      "კორპუსი:": "ტიტანიუმი",
      "IP დაცვა :": "IP68, 10 ATM",
      "ოპერაციული სისტემა:": "Wear OS",
      "ჩიპსეტი:": "Exynos W1000",
      "NFC:": "Yes",
      "Bluetooth:": "5.3",
      "სენსორი:": "Accelerometer, Gyro, Heart Rate, Barometer, Altimeter, Compass, SpO2, Temperature (body), Temperature (water), BioActive",
      "სპიკერი:": "Yes",
      "ქართული ენის მხარდაჭერა:": "Yes",
      "გადახდის ფუნქცია (Pay):": "Yes",
      "კამერა:": "No",
      "ეკრანის ზომა:": "47 mm",
      "ეკრანის ტიპი:": "Super Amoled",
      "PPI:": "327 ppi",
      "რეზოლუცია:": "480 x 480 pixels",
      "ეკრანის სიკაშკაშე:": "-",
      "Always on Display:": "Yes",
      "Wi-Fi:": "Yes",
      "GPS:": "Yes",
      "შიდა მეხსიერება:": "32 GB",
      "ოპერატიული მეხსიერება:": "2 GB",
      "თავსებადობა (Android; iOS):": "Android",
      "ელემენტი:": "590 mAh",
      "ელემენტი დამუხტვის სიჩქარე:": "10 W",
      "ელემენტის ტიპი:": "Li-Ion",
      "Wireless დამუხტვა:": "Yes",
      "სამუშაო დრო:": "-",
      "წონა:": "60.5 g",
      "ფერი:": "Titanium White"
    }
  },
  {
    "category": "Galaxy Watch",
    "title": "Samsung L705 Galaxy Watch Ultra Titanium Silver",
    "price": 1199.0,
    "link": "https://zoommer.ge/smart-saatebi/samsung-l705-galaxy-watch-ultra-titanium-silver-p43710",
    "image": "/_next/image?url=https%3A%2F%2Fs3.zoommer.ge%2Fsite%2Fc6f4e55c-6f81-42ea-b456-fc82f1053320_Thumb.jpeg&w=384&q=50",
    "product_title_detail": "Samsung L705 Galaxy Watch Ultra Titanium Silver",
    "description": "*7007 / +995 (32) 2 60 30 60\nსავაჭრო პოლიტიკა\nგანვადება\nკარიერა\nTrade In\nფილიალები\nნავიგაცია\nკალათა\nშესვლა\n%\nმთავარი\nსმარტ საათები\nSamsung\n#ZOOM-034257\nSamsung L705 Galaxy Watch Ultra Titanium Silver\nეკრანის ზომა\n47 mm\nრეზოლუცია\n480 x 480 pixels\nსამუშაო დრო\n-\nეკრანის ტიპი\nSuper Amoled\nშიდა მეხსიერება\n32 GB\nBluetooth\n5.3\nოპერატიული მეხსიერება\n2 GB\nელემენტი\n590 mAh\nფერი: Titanium Silver\nერთად იაფია\nდაამატე ნივთი\nSamsung L705 Galaxy Watch Ultra Titanium Silver\n1199 ₾\nSamsung Travel Adapter 25W EP-T2510 White\n52.25 ₾\n55 ₾\nჯამური ფასი (1)\n1251.25 ₾\n1254 ₾\nყიდვა\nაქსესუარები\nაღწერა\nმსგავსი\nმახასიათებლები\nფილიალები\nაქსესუარები\nაღწერა\nმსგავსი\nმახასიათებლები\nფილიალები\n99 ₾\n\nთვეში: 2 ₾ -დან\n\nXiaomi Redmi Fast Charge Power Bank 20000 mAh 18W PB2 ...\nდამატება\n89 ₾\n\nთვეში: 2 ₾ -დან\n\nXiaomi 22.5W Power Bank 10000mAh BHR5884GL Blue\nდამატება\n139 ₾\n\nთვეში: 3 ₾ -დან\n\nAnker 324 Powerbank 10.000mAh A1237 Black\nდამატება\n189 ₾\n\nთვეში: 5 ₾ -დან\n\nAnker 325 Powerbank 20000mAh A1286G11 Black\nდამატება\n89 ₾\n\nთვეში: 2 ₾ -დან\n\nXiaomi Power Bank 10000mAh BHR9072GL White\nდამატება\n89 ₾\n\nთვეში: 2 ₾ -დან\n\nXiaomi Power Bank 10000mAh BHR9072GL Blue\nდამატება\n129 ₾\n\nთვეში: 3 ₾ -დან\n\nXiaomi 33W Integrated Cable Power Bank 20000mAh Blue\nდამატება\n129 ₾\n\nთვეში: 3 ₾ -დან\n\nXiaomi 33W Integrated Cable Power Bank 20000mAh White\nდამატება\n89 ₾\n\nთვეში: 2 ₾ -დან\n\nUgreen 10000mAh USB-C Two-way Power Bank 25742 Black\nდამატება\n199 ₾\n\nთვეში: 5 ₾ -დან\n\nUgreen 20000mAh USB Type-C Two-way Power Bank 25188 G ...\nდამატება\n199 ₾\n\nთვეში: 5 ₾ -დან\n\nUgreen Nexode with Smart Digital Display 20000mAh Typ ...\nდამატება\n129 ₾\n\nთვეში: 3 ₾ -დან\n\nUgreen 20000mAh USB Type-C Two-way Power Bank 25683 B ...\nდამატება\n249 ₾\n\nთვეში: 6 ₾ -დან\n\nUgreen 25000mAh Type-C Power Bank 90597A Grey\nდამატება\n109 ₾\n\nთვეში: 3 ₾ -დან\n\nUgreen 5000mAh USB Type-C Power Bank 35338 Grey\nდამატება\n299 ₾\n\nთვეში: 8 ₾ -დან\n\nUgreen Nexode with Smart Digital Display 25000mAh Typ ...\nდამატება\n199 ₾\n\nთვეში: 5 ₾ -დან\n\nXiaomi 165W Power Bank 10000mAh Integrated Cable Gray\nდამატება\n349 ₾\n\nთვეში: 9 ₾ -დან\n\nLenovo Go USB-C Laptop Power Bank 20000 mAh Grey\nდამატება\n179 ₾\n\nთვეში: 4 ₾ -დან\n\nAnker Powerbank 10000mAh 30W C-L A1680 Black\nდამატება\n159 ₾\n\nთვეში: 4 ₾ -დან\n\nAnker Powerbank 10000mAh 30W USB-C A1688 Black\nდამატება\n219 ₾\n\nთვეში: 6 ₾ -დან\n\nAnker Powerbank 20000mAh 30W C-L A1681 Black\nდამატება\n149 ₾\n\nთვეში: 4 ₾ -დან\n\nXiaomi 18W Power Bank 30000mAh BHR9126GL Black\nდამატება\n199 ₾\n\nთვეში: 5 ₾ -დან\n\nEcoflow Rapid Wireless Power Bank 5000mAh Grey\nდამატება\n249 ₾\n\nთვეში: 6 ₾ -დან\n\nAnker MagGo PowerBank 10000mAh For Apple Watch A1657 ...\nდამატება\nპროდუქტის შესახებ\n\nSamsung L705 Galaxy Watch Ultra Titanium Silver - ფლაგმანური სმარტ საათი, შექმნილი მათთვის, ვინც აქტიურ დღის რეჟიმს აერთიანებს ტექნოლოგიურ სიზუსტესთან. მისი ძირითადი მიზანია, დაგეხმაროთ მუდმივად კავში...\n\nმეტის ნახვა\nმსგავსი პროდუქტები\n399 ₾\n\nთვეში: 11 ₾ -დან\n\nSamsung Galaxy Watch FE Pink Gold\nდამატება\n1199 ₾\n1299 ₾\n\nთვეში: 33 ₾ -დან\n\nSamsung L705 Galaxy Watch Ultra Titanium Grey\nდამატება\n1199 ₾\n1299 ₾\n\nთვეში: 33 ₾ -დან\n\nSamsung L705 Galaxy Watch Ultra Titanium White\nდამატება\n549 ₾\n669 ₾\n\nთვეში: 15 ₾ -დან\n\nSamsung SM-R950 43mm Galaxy Watch 6 Classic Silver\nდამატება\n499 ₾\n\nთვეში: 13 ₾ -დან\n\nSamsung SM-R940 44mm Galaxy Watch 6 Silver\nდამატება\n569 ₾\n649 ₾\n\nთვეში: 15 ₾ -დან\n\nSamsung SM-R960 47mm Galaxy Watch 6 Classic Silver\nდამატება\n449 ₾\n499 ₾\n\nთვეში: 12 ₾ -დან\n\nSamsung L300 40mm Galaxy Watch 7 Cream\nდამატება\n449 ₾\n499 ₾\n\nთვეში: 12 ₾ -დან\n\nSamsung L300 40mm Galaxy Watch 7 Green\nდამატება\n549 ₾\n\nთვეში: 15 ₾ -დან\n\nSamsung L310 44mm Galaxy Watch 7 Green\nდამატება\n549 ₾\n\nთვეში: 15 ₾ -დან\n\nSamsung L310 44mm Galaxy Watch 7 Silver\nდამატება\n139 ₾\n\nთვეში: 3 ₾ -დან\n\nSamsung Galaxy Fit 3 R390 Silver\nდამატება\nდამატებითი მახასიათებლები\nბრენდი\nბრენდი:\n\t\nSamsung\nტექნიკური მახასიათებლები\nკავშირის სტანდარტი:\n\t\nNo\n\n\nSIM ბარათი:\n\t\n-\n\n\nკორპუსი:\n\t\nტიტანიუმი\n\n\nIP დაცვა :\n\t\nIP68, 10 ATM\n\n\nოპერაციული სისტემა:\n\t\nWear OS\n\n\nჩიპსეტი:\n\t\nExynos W1000\n\n\nNFC:\n\t\nYes\n\n\nBluetooth:\n\t\n5.3\n\n\nსენსორი:\n\t\nAccelerometer, Gyro, Heart Rate, Barometer, Altimeter, Compass, SpO2, Temperature (body), Temperature (water), BioActive\n\n\nსპიკერი:\n\t\nYes\n\n\nქართული ენის მხარდაჭერა:\n\t\nYes\n\n\nგადახდის ფუნქცია (Pay):\n\t\nYes\n\n\nკამერა:\n\t\nNo\nეკრანი\nეკრანის ზომა:\n\t\n47 mm\n\n\nეკრანის ტიპი:\n\t\nSuper Amoled\n\n\nPPI:\n\t\n327 ppi\n\n\nრეზოლუცია:\n\t\n480 x 480 pixels\n\n\nეკრანის სიკაშკაშე:\n\t\n-\n\n\nAlways on Display:\n\t\nYes\nდამატებითი მახასიათებლები\nWi-Fi:\n\t\nYes\n\n\nGPS:\n\t\nYes\nმეხსიერება\nშიდა მეხსიერება:\n\t\n32 GB\n\n\nოპერატიული მეხსიერება:\n\t\n2 GB\nთავსებადობა\nთავსებადობა (Android; iOS):\n\t\nAndroid\nელემენტი\nელემენტი:\n\t\n590 mAh\n\n\nელემენტი დამუხტვის სიჩქარე:\n\t\n10 W\n\n\nელემენტის ტიპი:\n\t\nLi-Ion\n\n\nWireless დამუხტვა:\n\t\nYes\n\n\nსამუშაო დრო:\n\t\n-\nზომა/წონა\nწონა:\n\t\n60.5 g\nფერი\nფერი:\n\t\nTitanium Silver\nმეტის ნახვა\nგაეცანი საგარანტიო პირობებს\nსაგარანტიო პირობები\nფილიალები\nმარაგშია\nშეკვეთიდან 2-5 დღეში\nზუმერის წერეთლის ფილიალი\n\nთბილისი - წერეთლის გამზირი, N1.\n\nმარაგშია\n+995 591 967 601\nორშ-შაბ: 10:00:00 - 20:00:00\nკვირა: 10:00:00 - 19:00:00\nზუმერის \"თბილისი ცენტრალის\" ფილიალი\n\nთბილისი - \"თბილისი ცენტრალი\"- lll სართული\n\nმარაგშია\n+995 599 862 449\nორშ-შაბ: 10:00:00 - 20:00:00\nკვირა: 10:00:00 - 19:00:00\nზუმერის City Mall საბურთალო-ს ფილიალი\n\nთბილისი - \"სითი მოლი\" - პეტრე ქავთარაძის N1\n\nმარაგშია\n+995 591 971 962\nორშ-შაბ: 10:00:00 - 22:00:00\nკვირა: 10:00:00 - 22:00:00\nზუმერის თბილისი მოლის ფილიალი\n\nთბილისი - „თბილისი მოლი\" - I სართული. აღმაშენებლის ხეივანი მე-16 კმ\n\nმარაგშია\n+995 591 967 608\nორშ-შაბ: 10:00:00 - 22:00:00\nკვირა: 10:00:00 - 22:00:00\nზუმერის \"გლდანი მოლის\" ფილიალი\n\nთბილისი - \"გლდანი მოლი\" - I სართული, M-ახმეტელის მიმდებარე\n\nმარაგშია\n+995 591 967 673\nორშ-შაბ: 10:00:00 - 21:00:00\nკვირა: 10:00:00 - 21:00:00\nზუმერის ისთ ფოინთის ფილიალი\n\nთბილისი - \"ისთ ფოინთი\" - ალ. თვალჭრელიძე N2\n\nმარაგშია\n+995 591 340 476\nორშ-შაბ: 10:00:00 - 22:00:00\nკვირა: 10:00:00 - 22:00:00\nზუმერი რუსთავი მოლის ფილიალი\n\nრუსთავი - შარტავას და ლომოურის კვეთა\n\nმარაგშია\n+995 591 441 082\nორშ-შაბ: 10:00:00 - 22:00:00\nკვირა: 10:00:00 - 22:00:00\nბათუმი ჭავჭავაძის ფილიალი\n\nბათუმი - ბათუმი, ჭავჭავაძის N21\n\nმარაგშია\n+995 591 967 606\nორშ-შაბ: 10:00:00 - 20:00:00\nკვირა: 10:00:00 - 19:00:00\nბათუმის \"Black Sea Mall\"-ის ფილიალი\n\nბათუმი - \"Black Sea Mall\" - ტბელ აბუსერიძის N22\n\nმარაგშია\n+995 591 310 257\nორშ-შაბ: 10:00:00 - 21:00:00\nკვირა: 10:00:00 - 21:00:00\nბათუმის გრანდ მოლის ფილიალი\n\nბათუმი - \"გრანდ მოლი\" - შერიფ ხიმშიაშვილის 29\n\nმარაგშია\n+995 591 022 872\nორშ-შაბ: 10:00:00 - 22:00:00\nკვირა: 10:00:00 - 22:00:00\nქუთაისის ფილიალი\n\nქუთაისი - თამარ მეფის ქ. N3 , ქუთაისის ცენტრალური მოედანი\n\nმარაგშია\n+955 591 967 605\nორშ-შაბ: 10:00:00 - 20:00:00\nკვირა: 10:00:00 - 19:00:00\nქუთაისი ვესთ მოლი\n\nქუთაისი - \"ვესთ მოლი\" - შარტავას N2\n\nმარაგშია\n+995 595 306 765\nორშ-შაბ: 10:00:00 - 22:00:00\nკვირა: 10:00:00 - 22:00:00\nზუგდიდი მოლის ფილიალი\n\nზუგდიდი - ზუგდიდი მოლი, კოსტავას ქუჩა №28\n\nმარაგშია\n+995 591 676 489\nორშ-შაბ: 10:00:00 - 22:00:00\nკვირა: 10:00:00 - 22:00:00\nგორი მოლის ფილიალი\n\nგორი - გორი, ცხინვალის გზატკეცილი 14-14ამ, გორი მოლი\n\nმარაგშია\n+995 591 198 248\nორშ-შაბ: 10:00:00 - 22:00:00\nკვირა: 10:00:00 - 22:00:00\nახალციხის ფილიალი\n\nახალციხე - ახალციხე, თამარ მეფის ქ. N9\n\nმარაგშია\n+995 598 088 659\nორშ-შაბ: 10:00:00 - 19:00:00\nკვირა: 10:00:00 - 19:00:00\nზუმერის საბითუმო საწყობი\n\nთბილისი - აკაკი წერეთლის გამზირი 1, საბითუმო საწყობი, -1 სართული\n\nმარაგშია\n+995 (32) 2 60 30 60\nორშ-შაბ: 10:00:00 - 19:00:00\nკვირა: 10:00:00 - 19:00:00\nმეტის ნახვა\n1199 ₾\n1299 ₾\n\nთვეში: 33.3 ₾ -დან\n\nმარაგი ფილიალებში\nფასის დაზღვევა\nფასის კონტროლი\nფასის დაჯავშნა\nყიდვა\nშედარება\nდამატება\nნავიგაცია\n\nპერსონალურ მონაცემთა დაცვის პოლიტიკა\n\nჩვენ შესახებ\n\nწესები და პირობები\n\nმიწოდების სერვისი\n\nკარიერა\n\nგადახდები\n\nSetanta Sports\n\nგადახდის მეთოდები\n\nგარანტია\n\nგანვადება\n\nნივთის დაბრუნება\n\nნივთის ონლაინ ყიდვის ინსტრუქცია\n\nგამოგვყევი\n\nFacebook\n\nYoutube\n\nInstagram\n\nTik Tok\n\nკონტაქტი\n\nInfo@zoommer.ge\n\n+995 (32) 2 60 30 60 / *7007\n\nფილიალები\n\nკორპორატიული გაყიდვები\n\nZoommer App\n\nCopyright © 2023 Zoommer.ge. All rights reserved.\n\nCookie პოლიტიკა\n\nსაიტით სარგებლობის გაგრძელებით, შენ ეთანხმები Cookie ჩანაწერების გამოყენებას. მეტი ინფორმაცისათვის იხილეთ კონფიდენციალურობის პოლიტიკა\n\nგასაგებია",
    "specs": {
      "ბრენდი:": "Samsung",
      "კავშირის სტანდარტი:": "No",
      "SIM ბარათი:": "-",
      "კორპუსი:": "ტიტანიუმი",
      "IP დაცვა :": "IP68, 10 ATM",
      "ოპერაციული სისტემა:": "Wear OS",
      "ჩიპსეტი:": "Exynos W1000",
      "NFC:": "Yes",
      "Bluetooth:": "5.3",
      "სენსორი:": "Accelerometer, Gyro, Heart Rate, Barometer, Altimeter, Compass, SpO2, Temperature (body), Temperature (water), BioActive",
      "სპიკერი:": "Yes",
      "ქართული ენის მხარდაჭერა:": "Yes",
      "გადახდის ფუნქცია (Pay):": "Yes",
      "კამერა:": "No",
      "ეკრანის ზომა:": "47 mm",
      "ეკრანის ტიპი:": "Super Amoled",
      "PPI:": "327 ppi",
      "რეზოლუცია:": "480 x 480 pixels",
      "ეკრანის სიკაშკაშე:": "-",
      "Always on Display:": "Yes",
      "Wi-Fi:": "Yes",
      "GPS:": "Yes",
      "შიდა მეხსიერება:": "32 GB",
      "ოპერატიული მეხსიერება:": "2 GB",
      "თავსებადობა (Android; iOS):": "Android",
      "ელემენტი:": "590 mAh",
      "ელემენტი დამუხტვის სიჩქარე:": "10 W",
      "ელემენტის ტიპი:": "Li-Ion",
      "Wireless დამუხტვა:": "Yes",
      "სამუშაო დრო:": "-",
      "წონა:": "60.5 g",
      "ფერი:": "Titanium Silver"
    }
  },
  {
    "category": "Galaxy Watch",
    "title": "Samsung L705 Galaxy Watch Ultra Titanium Grey",
    "price": 1199.0,
    "link": "https://zoommer.ge/smart-saatebi/samsung-l705-galaxy-watch-ultra-titanium-grey-p43684",
    "image": "/_next/image?url=https%3A%2F%2Fs3.zoommer.ge%2Fsite%2F438974f4-face-411e-8912-5808c50ea6be_Thumb.jpeg&w=384&q=50",
    "product_title_detail": "Samsung L705 Galaxy Watch Ultra Titanium Grey",
    "description": "*7007 / +995 (32) 2 60 30 60\nსავაჭრო პოლიტიკა\nგანვადება\nკარიერა\nTrade In\nფილიალები\nნავიგაცია\nკალათა\nშესვლა\n%\nმთავარი\nსმარტ საათები\nSamsung\n#ZOOM-034257\nSamsung L705 Galaxy Watch Ultra Titanium Grey\nეკრანის ზომა\n47 mm\nრეზოლუცია\n480 x 480 pixels\nსამუშაო დრო\n-\nეკრანის ტიპი\nSuper Amoled\nშიდა მეხსიერება\n32 GB\nBluetooth\n5.3\nოპერატიული მეხსიერება\n2 GB\nელემენტი\n590 mAh\nფერი: Titanium Gray\nერთად იაფია\nდაამატე ნივთი\nSamsung L705 Galaxy Watch Ultra Titanium Grey\n1199 ₾\nSamsung Travel Adapter 25W EP-T2510 White\n52.25 ₾\n55 ₾\nჯამური ფასი (1)\n1251.25 ₾\n1254 ₾\nყიდვა\nაქსესუარები\nაღწერა\nმსგავსი\nმახასიათებლები\nფილიალები\nაქსესუარები\nაღწერა\nმსგავსი\nმახასიათებლები\nფილიალები\n99 ₾\n\nთვეში: 2 ₾ -დან\n\nXiaomi Redmi Fast Charge Power Bank 20000 mAh 18W PB2 ...\nდამატება\n49 ₾\n\nთვეში: 1 ₾ -დან\n\nXiaomi Redmi Buds 6 Lite Blue\nდამატება\n199 ₾\n\nთვეში: 5 ₾ -დან\n\nOnePlus Nord Buds 3 Pro Green\nდამატება\n119 ₾\n\nთვეში: 3 ₾ -დან\n\nNothing CMF Buds Pro Dark Grey\nდამატება\n149 ₾\n\nთვეში: 4 ₾ -დან\n\nRealme Buds Air 6 Silver\nდამატება\n89 ₾\n\nთვეში: 2 ₾ -დან\n\nXiaomi 22.5W Power Bank 10000mAh BHR5884GL Blue\nდამატება\n129 ₾\n\nთვეში: 3 ₾ -დან\n\nNothing Buds CMF Neckband Pro Light Grey\nდამატება\n59 ₾\n\nთვეში: 1 ₾ -დან\n\nRealme Buds T01 Black\nდამატება\n139 ₾\n\nთვეში: 3 ₾ -დან\n\nAnker 324 Powerbank 10.000mAh A1237 Black\nდამატება\n139 ₾\n\nთვეში: 3 ₾ -დან\n\nNothing CMF Buds Pro 2 Blue\nდამატება\n299 ₾\n\nთვეში: 8 ₾ -დან\n\nRealme Buds Air 7 Pro Green\nდამატება\n189 ₾\n\nთვეში: 5 ₾ -დან\n\nAnker 325 Powerbank 20000mAh A1286G11 Black\nდამატება\n299 ₾\n\nთვეში: 8 ₾ -დან\n\nRealme Buds Air 7 Pro Grey\nდამატება\n89 ₾\n\nთვეში: 2 ₾ -დან\n\nXiaomi Power Bank 10000mAh BHR9072GL White\nდამატება\n299 ₾\n\nთვეში: 8 ₾ -დან\n\nRealme Buds Air 7 Pro Red\nდამატება\n89 ₾\n\nთვეში: 2 ₾ -დან\n\nXiaomi Power Bank 10000mAh BHR9072GL Blue\nდამატება\n299 ₾\n\nთვეში: 8 ₾ -დან\n\nRealme Buds Air 7 Pro White\nდამატება\n129 ₾\n\nთვეში: 3 ₾ -დან\n\nXiaomi 33W Integrated Cable Power Bank 20000mAh Blue\nდამატება\n129 ₾\n\nთვეში: 3 ₾ -დან\n\nXiaomi 33W Integrated Cable Power Bank 20000mAh White\nდამატება\n89 ₾\n\nთვეში: 2 ₾ -დან\n\nUgreen 10000mAh USB-C Two-way Power Bank 25742 Black\nდამატება\n199 ₾\n\nთვეში: 5 ₾ -დან\n\nUgreen 20000mAh USB Type-C Two-way Power Bank 25188 G ...\nდამატება\n199 ₾\n\nთვეში: 5 ₾ -დან\n\nUgreen Nexode with Smart Digital Display 20000mAh Typ ...\nდამატება\n129 ₾\n\nთვეში: 3 ₾ -დან\n\nUgreen 20000mAh USB Type-C Two-way Power Bank 25683 B ...\nდამატება\n249 ₾\n\nთვეში: 6 ₾ -დან\n\nUgreen 25000mAh Type-C Power Bank 90597A Grey\nდამატება\n109 ₾\n\nთვეში: 3 ₾ -დან\n\nUgreen 5000mAh USB Type-C Power Bank 35338 Grey\nდამატება\n299 ₾\n\nთვეში: 8 ₾ -დან\n\nUgreen Nexode with Smart Digital Display 25000mAh Typ ...\nდამატება\n199 ₾\n\nთვეში: 5 ₾ -დან\n\nXiaomi 165W Power Bank 10000mAh Integrated Cable Gray\nდამატება\n349 ₾\n\nთვეში: 9 ₾ -დან\n\nLenovo Go USB-C Laptop Power Bank 20000 mAh Grey\nდამატება\n179 ₾\n\nთვეში: 4 ₾ -დან\n\nAnker Powerbank 10000mAh 30W C-L A1680 Black\nდამატება\n159 ₾\n\nთვეში: 4 ₾ -დან\n\nAnker Powerbank 10000mAh 30W USB-C A1688 Black\nდამატება\n219 ₾\n\nთვეში: 6 ₾ -დან\n\nAnker Powerbank 20000mAh 30W C-L A1681 Black\nდამატება\n149 ₾\n\nთვეში: 4 ₾ -დან\n\nXiaomi 18W Power Bank 30000mAh BHR9126GL Black\nდამატება\n199 ₾\n\nთვეში: 5 ₾ -დან\n\nEcoflow Rapid Wireless Power Bank 5000mAh Grey\nდამატება\n249 ₾\n\nთვეში: 6 ₾ -დან\n\nAnker MagGo PowerBank 10000mAh For Apple Watch A1657 ...\nდამატება\nპროდუქტის შესახებ\n\nSamsung L705 Galaxy Watch Ultra Titanium Grey - ფლაგმანური სმარტ საათი, შექმნილი მათთვის, ვინც აქტიურ დღის რეჟიმს აერთიანებს ტექნოლოგიურ სიზუსტესთან. მისი ძირითადი მიზანია, დაგეხმაროთ მუდმივად კავშირზ...\n\nმეტის ნახვა\nმსგავსი პროდუქტები\n399 ₾\n\nთვეში: 11 ₾ -დან\n\nSamsung Galaxy Watch FE Pink Gold\nდამატება\n1199 ₾\n1299 ₾\n\nთვეში: 33 ₾ -დან\n\nSamsung L705 Galaxy Watch Ultra Titanium Silver\nდამატება\n1199 ₾\n1299 ₾\n\nთვეში: 33 ₾ -დან\n\nSamsung L705 Galaxy Watch Ultra Titanium White\nდამატება\n549 ₾\n669 ₾\n\nთვეში: 15 ₾ -დან\n\nSamsung SM-R950 43mm Galaxy Watch 6 Classic Silver\nდამატება\n499 ₾\n\nთვეში: 13 ₾ -დან\n\nSamsung SM-R940 44mm Galaxy Watch 6 Silver\nდამატება\n569 ₾\n649 ₾\n\nთვეში: 15 ₾ -დან\n\nSamsung SM-R960 47mm Galaxy Watch 6 Classic Silver\nდამატება\n449 ₾\n499 ₾\n\nთვეში: 12 ₾ -დან\n\nSamsung L300 40mm Galaxy Watch 7 Cream\nდამატება\n449 ₾\n499 ₾\n\nთვეში: 12 ₾ -დან\n\nSamsung L300 40mm Galaxy Watch 7 Green\nდამატება\n549 ₾\n\nთვეში: 15 ₾ -დან\n\nSamsung L310 44mm Galaxy Watch 7 Green\nდამატება\n549 ₾\n\nთვეში: 15 ₾ -დან\n\nSamsung L310 44mm Galaxy Watch 7 Silver\nდამატება\n139 ₾\n\nთვეში: 3 ₾ -დან\n\nSamsung Galaxy Fit 3 R390 Silver\nდამატება\nდამატებითი მახასიათებლები\nბრენდი\nბრენდი:\n\t\nSamsung\nტექნიკური მახასიათებლები\nკავშირის სტანდარტი:\n\t\nNo\n\n\nSIM ბარათი:\n\t\n-\n\n\nკორპუსი:\n\t\nტიტანიუმი\n\n\nIP დაცვა :\n\t\nIP68, 10 ATM\n\n\nოპერაციული სისტემა:\n\t\nWear OS\n\n\nჩიპსეტი:\n\t\nExynos W1000\n\n\nNFC:\n\t\nYes\n\n\nBluetooth:\n\t\n5.3\n\n\nსენსორი:\n\t\nAccelerometer, Gyro, Heart Rate, Barometer, Altimeter, Compass, SpO2, Temperature (body), Temperature (water), BioActive\n\n\nსპიკერი:\n\t\nYes\n\n\nქართული ენის მხარდაჭერა:\n\t\nYes\n\n\nგადახდის ფუნქცია (Pay):\n\t\nYes\n\n\nკამერა:\n\t\nNo\nეკრანი\nეკრანის ზომა:\n\t\n47 mm\n\n\nეკრანის ტიპი:\n\t\nSuper Amoled\n\n\nPPI:\n\t\n327 ppi\n\n\nრეზოლუცია:\n\t\n480 x 480 pixels\n\n\nეკრანის სიკაშკაშე:\n\t\n-\n\n\nAlways on Display:\n\t\nYes\nდამატებითი მახასიათებლები\nWi-Fi:\n\t\nYes\n\n\nGPS:\n\t\nYes\nმეხსიერება\nშიდა მეხსიერება:\n\t\n32 GB\n\n\nოპერატიული მეხსიერება:\n\t\n2 GB\nთავსებადობა\nთავსებადობა (Android; iOS):\n\t\nAndroid\nელემენტი\nელემენტი:\n\t\n590 mAh\n\n\nელემენტი დამუხტვის სიჩქარე:\n\t\n10 W\n\n\nელემენტის ტიპი:\n\t\nLi-Ion\n\n\nWireless დამუხტვა:\n\t\nYes\n\n\nსამუშაო დრო:\n\t\n-\nზომა/წონა\nწონა:\n\t\n60.5 g\nფერი\nფერი:\n\t\nTitanium Gray\nმეტის ნახვა\nგაეცანი საგარანტიო პირობებს\nსაგარანტიო პირობები\nფილიალები\nმარაგშია\nშეკვეთიდან 2-5 დღეში\nზუმერის პეკინის ფილიალი\n\nთბილისი - კ.გამსახურდიას (პეკინის) გამზირი N14ა\n\nმარაგშია\n+995 591 967 671\nორშ-შაბ: 10:00:00 - 21:00:00\nკვირა: 10:00:00 - 20:00:00\nზუმერის \"თბილისი ცენტრალის\" ფილიალი\n\nთბილისი - \"თბილისი ცენტრალი\"- lll სართული\n\nმარაგშია\n+995 599 862 449\nორშ-შაბ: 10:00:00 - 20:00:00\nკვირა: 10:00:00 - 19:00:00\nზუმერის City Mall საბურთალო-ს ფილიალი\n\nთბილისი - \"სითი მოლი\" - პეტრე ქავთარაძის N1\n\nმარაგშია\n+995 591 971 962\nორშ-შაბ: 10:00:00 - 22:00:00\nკვირა: 10:00:00 - 22:00:00\nზუმერის თბილისი მოლის ფილიალი\n\nთბილისი - „თბილისი მოლი\" - I სართული. აღმაშენებლის ხეივანი მე-16 კმ\n\nმარაგშია\n+995 591 967 608\nორშ-შაბ: 10:00:00 - 22:00:00\nკვირა: 10:00:00 - 22:00:00\nზუმერის ისთ ფოინთის ფილიალი\n\nთბილისი - \"ისთ ფოინთი\" - ალ. თვალჭრელიძე N2\n\nმარაგშია\n+995 591 340 476\nორშ-შაბ: 10:00:00 - 22:00:00\nკვირა: 10:00:00 - 22:00:00\nზუმერი რუსთავი მოლის ფილიალი\n\nრუსთავი - შარტავას და ლომოურის კვეთა\n\nმარაგშია\n+995 591 441 082\nორშ-შაბ: 10:00:00 - 22:00:00\nკვირა: 10:00:00 - 22:00:00\nბათუმი ჭავჭავაძის ფილიალი\n\nბათუმი - ბათუმი, ჭავჭავაძის N21\n\nმარაგშია\n+995 591 967 606\nორშ-შაბ: 10:00:00 - 20:00:00\nკვირა: 10:00:00 - 19:00:00\nბათუმის გრანდ მოლის ფილიალი\n\nბათუმი - \"გრანდ მოლი\" - შერიფ ხიმშიაშვილის 29\n\nმარაგშია\n+995 591 022 872\nორშ-შაბ: 10:00:00 - 22:00:00\nკვირა: 10:00:00 - 22:00:00\nქუთაისის ფილიალი\n\nქუთაისი - თამარ მეფის ქ. N3 , ქუთაისის ცენტრალური მოედანი\n\nმარაგშია\n+955 591 967 605\nორშ-შაბ: 10:00:00 - 20:00:00\nკვირა: 10:00:00 - 19:00:00\nქუთაისი ვესთ მოლი\n\nქუთაისი - \"ვესთ მოლი\" - შარტავას N2\n\nმარაგშია\n+995 595 306 765\nორშ-შაბ: 10:00:00 - 22:00:00\nკვირა: 10:00:00 - 22:00:00\nზუგდიდი მოლის ფილიალი\n\nზუგდიდი - ზუგდიდი მოლი, კოსტავას ქუჩა №28\n\nმარაგშია\n+995 591 676 489\nორშ-შაბ: 10:00:00 - 22:00:00\nკვირა: 10:00:00 - 22:00:00\nგორი მოლის ფილიალი\n\nგორი - გორი, ცხინვალის გზატკეცილი 14-14ამ, გორი მოლი\n\nმარაგშია\n+995 591 198 248\nორშ-შაბ: 10:00:00 - 22:00:00\nკვირა: 10:00:00 - 22:00:00\nახალციხის ფილიალი\n\nახალციხე - ახალციხე, თამარ მეფის ქ. N9\n\nმარაგშია\n+995 598 088 659\nორშ-შაბ: 10:00:00 - 19:00:00\nკვირა: 10:00:00 - 19:00:00\nთელავი მოლის ფილიალი\n\nთელავი - \"თელავი მოლი\" - ალაზნის ქ.N77\n\nმარაგშია\n+995 595 069 853\nორშ-შაბ: 10:00:00 - 20:00:00\nკვირა: 10:00:00 - 19:00:00\nმეტის ნახვა\n1199 ₾\n1299 ₾\n\nთვეში: 33.3 ₾ -დან\n\nმარაგი ფილიალებში\nფასის დაზღვევა\nფასის კონტროლი\nფასის დაჯავშნა\nყიდვა\nშედარება\nდამატება\nნავიგაცია\n\nპერსონალურ მონაცემთა დაცვის პოლიტიკა\n\nჩვენ შესახებ\n\nწესები და პირობები\n\nმიწოდების სერვისი\n\nკარიერა\n\nგადახდები\n\nSetanta Sports\n\nგადახდის მეთოდები\n\nგარანტია\n\nგანვადება\n\nნივთის დაბრუნება\n\nნივთის ონლაინ ყიდვის ინსტრუქცია\n\nგამოგვყევი\n\nFacebook\n\nYoutube\n\nInstagram\n\nTik Tok\n\nკონტაქტი\n\nInfo@zoommer.ge\n\n+995 (32) 2 60 30 60 / *7007\n\nფილიალები\n\nკორპორატიული გაყიდვები\n\nZoommer App\n\nCopyright © 2023 Zoommer.ge. All rights reserved.\n\nCookie პოლიტიკა\n\nსაიტით სარგებლობის გაგრძელებით, შენ ეთანხმები Cookie ჩანაწერების გამოყენებას. მეტი ინფორმაცისათვის იხილეთ კონფიდენციალურობის პოლიტიკა\n\nგასაგებია",
    "specs": {
      "ბრენდი:": "Samsung",
      "კავშირის სტანდარტი:": "No",
      "SIM ბარათი:": "-",
      "კორპუსი:": "ტიტანიუმი",
      "IP დაცვა :": "IP68, 10 ATM",
      "ოპერაციული სისტემა:": "Wear OS",
      "ჩიპსეტი:": "Exynos W1000",
      "NFC:": "Yes",
      "Bluetooth:": "5.3",
      "სენსორი:": "Accelerometer, Gyro, Heart Rate, Barometer, Altimeter, Compass, SpO2, Temperature (body), Temperature (water), BioActive",
      "სპიკერი:": "Yes",
      "ქართული ენის მხარდაჭერა:": "Yes",
      "გადახდის ფუნქცია (Pay):": "Yes",
      "კამერა:": "No",
      "ეკრანის ზომა:": "47 mm",
      "ეკრანის ტიპი:": "Super Amoled",
      "PPI:": "327 ppi",
      "რეზოლუცია:": "480 x 480 pixels",
      "ეკრანის სიკაშკაშე:": "-",
      "Always on Display:": "Yes",
      "Wi-Fi:": "Yes",
      "GPS:": "Yes",
      "შიდა მეხსიერება:": "32 GB",
      "ოპერატიული მეხსიერება:": "2 GB",
      "თავსებადობა (Android; iOS):": "Android",
      "ელემენტი:": "590 mAh",
      "ელემენტი დამუხტვის სიჩქარე:": "10 W",
      "ელემენტის ტიპი:": "Li-Ion",
      "Wireless დამუხტვა:": "Yes",
      "სამუშაო დრო:": "-",
      "წონა:": "60.5 g",
      "ფერი:": "Titanium Gray"
    }
  },
  {
    "category": "Galaxy Watch",
    "title": "Samsung Galaxy Watch FE Pink Gold",
    "price": 399.0,
    "link": "https://zoommer.ge/smart-saatebi/samsung-galaxy-watch-fe-pink-gold-p43298",
    "image": "/_next/image?url=https%3A%2F%2Fs3.zoommer.ge%2Fsite%2Fa0f66d7b-f48f-4d64-85cc-ea5bbc78665b_Thumb.jpeg&w=384&q=50",
    "product_title_detail": "Samsung Galaxy Watch FE Pink Gold",
    "description": "*7007 / +995 (32) 2 60 30 60\nსავაჭრო პოლიტიკა\nგანვადება\nკარიერა\nTrade In\nფილიალები\nნავიგაცია\nკალათა\nშესვლა\n%\nმთავარი\nსმარტ საათები\nSamsung\n#ZOOM-034081\nSamsung Galaxy Watch FE Pink Gold\nეკრანის ზომა\n44 mm\nრეზოლუცია\n396 x 396 pixels\nსამუშაო დრო\nUp To 40 hrs\nეკრანის ტიპი\nSuper Amoled\nშიდა მეხსიერება\n16 GB\nBluetooth\n5.0\nოპერატიული მეხსიერება\n1.5 GB\nელემენტი\n247 mAh\nერთად იაფია\nდაამატე ნივთი\nSamsung Galaxy Watch FE Pink Gold\n399 ₾\nXiaomi Mi 20W charger Type-C BHR4927GL White\n33.25 ₾\n35 ₾\nჯამური ფასი (1)\n432.25 ₾\n434 ₾\nყიდვა\nაქსესუარები\nაღწერა\nმსგავსი\nმახასიათებლები\nფილიალები\nაქსესუარები\nაღწერა\nმსგავსი\nმახასიათებლები\nფილიალები\n49 ₾\n\nთვეში: 1 ₾ -დან\n\nXiaomi Redmi Buds 6 Lite Blue\nდამატება\n199 ₾\n\nთვეში: 5 ₾ -დან\n\nOnePlus Nord Buds 3 Pro Green\nდამატება\n119 ₾\n\nთვეში: 3 ₾ -დან\n\nNothing CMF Buds Pro Dark Grey\nდამატება\n149 ₾\n\nთვეში: 4 ₾ -დან\n\nRealme Buds Air 6 Silver\nდამატება\n129 ₾\n\nთვეში: 3 ₾ -დან\n\nNothing Buds CMF Neckband Pro Light Grey\nდამატება\n59 ₾\n\nთვეში: 1 ₾ -დან\n\nRealme Buds T01 Black\nდამატება\n139 ₾\n\nთვეში: 3 ₾ -დან\n\nNothing CMF Buds Pro 2 Blue\nდამატება\n299 ₾\n\nთვეში: 8 ₾ -დან\n\nRealme Buds Air 7 Pro Green\nდამატება\n299 ₾\n\nთვეში: 8 ₾ -დან\n\nRealme Buds Air 7 Pro Grey\nდამატება\n299 ₾\n\nთვეში: 8 ₾ -დან\n\nRealme Buds Air 7 Pro Red\nდამატება\n299 ₾\n\nთვეში: 8 ₾ -დან\n\nRealme Buds Air 7 Pro White\nდამატება\nპროდუქტის შესახებ\n\nSamsung Galaxy Watch FE Pink Gold - ქმნის სასიამოვნო ბალანსს, სტილსა და ფუნქციონალს. საათი იდეალურია მათთვის, ვინც აფასებს მარტივად სამართავ ტექნოლოგიას და სურს მუდმივად აკონტროლოს ყოველდღიური აქტივობ...\n\nმეტის ნახვა\nმსგავსი პროდუქტები\n1199 ₾\n1299 ₾\n\nთვეში: 33 ₾ -დან\n\nSamsung L705 Galaxy Watch Ultra Titanium Grey\nდამატება\n1199 ₾\n1299 ₾\n\nთვეში: 33 ₾ -დან\n\nSamsung L705 Galaxy Watch Ultra Titanium Silver\nდამატება\n1199 ₾\n1299 ₾\n\nთვეში: 33 ₾ -დან\n\nSamsung L705 Galaxy Watch Ultra Titanium White\nდამატება\n549 ₾\n669 ₾\n\nთვეში: 15 ₾ -დან\n\nSamsung SM-R950 43mm Galaxy Watch 6 Classic Silver\nდამატება\n499 ₾\n\nთვეში: 13 ₾ -დან\n\nSamsung SM-R940 44mm Galaxy Watch 6 Silver\nდამატება\n569 ₾\n649 ₾\n\nთვეში: 15 ₾ -დან\n\nSamsung SM-R960 47mm Galaxy Watch 6 Classic Silver\nდამატება\n449 ₾\n499 ₾\n\nთვეში: 12 ₾ -დან\n\nSamsung L300 40mm Galaxy Watch 7 Cream\nდამატება\n449 ₾\n499 ₾\n\nთვეში: 12 ₾ -დან\n\nSamsung L300 40mm Galaxy Watch 7 Green\nდამატება\n549 ₾\n\nთვეში: 15 ₾ -დან\n\nSamsung L310 44mm Galaxy Watch 7 Green\nდამატება\n549 ₾\n\nთვეში: 15 ₾ -დან\n\nSamsung L310 44mm Galaxy Watch 7 Silver\nდამატება\n139 ₾\n\nთვეში: 3 ₾ -დან\n\nSamsung Galaxy Fit 3 R390 Silver\nდამატება\nდამატებითი მახასიათებლები\nბრენდი\nბრენდი:\n\t\nSamsung\nტექნიკური მახასიათებლები\nკავშირის სტანდარტი:\n\t\nNo\n\n\nSIM ბარათი:\n\t\nNo\n\n\nკორპუსი:\n\t\nალუმინი\n\n\nIP დაცვა :\n\t\n5 ATM, IP68\n\n\nოპერაციული სისტემა:\n\t\nWear OS\n\n\nჩიპსეტი:\n\t\nExynos W920\n\n\nNFC:\n\t\nYes\n\n\nBluetooth:\n\t\n5.0\n\n\nსენსორი:\n\t\nAccelerometer, Gyroscope, Barometer, Altimeter, Geomagnetic, Bioelectrical Impedance Analysis Sensor, Optical Heart Rate Sensor, Compass, Electrocardiogram Sensor\n\n\nსპიკერი:\n\t\nYes\n\n\nქართული ენის მხარდაჭერა:\n\t\nYes\n\n\nგადახდის ფუნქცია (Pay):\n\t\nYes\n\n\nკამერა:\n\t\nNo\nეკრანი\nეკრანის ზომა:\n\t\n44 mm\n\n\nეკრანის ტიპი:\n\t\nSuper Amoled\n\n\nPPI:\n\t\n330 ppi\n\n\nრეზოლუცია:\n\t\n396 x 396 pixels\n\n\nეკრანის სიკაშკაშე:\n\t\n-\n\n\nAlways on Display:\n\t\nYes\nდამატებითი მახასიათებლები\nWi-Fi:\n\t\nYes\n\n\nGPS:\n\t\nYes\nმეხსიერება\nშიდა მეხსიერება:\n\t\n16 GB\n\n\nოპერატიული მეხსიერება:\n\t\n1.5 GB\nთავსებადობა\nთავსებადობა (Android; iOS):\n\t\nAndroid\nელემენტი\nელემენტი:\n\t\n247 mAh\n\n\nელემენტი დამუხტვის სიჩქარე:\n\t\n5 W\n\n\nელემენტის ტიპი:\n\t\nLi - Ion\n\n\nWireless დამუხტვა:\n\t\nYes\n\n\nსამუშაო დრო:\n\t\nUp To 40 hrs\nზომა/წონა\nწონა:\n\t\n26.6 g\nფერი\nფერი:\n\t\nPink Gold\nმეტის ნახვა\nგაეცანი საგარანტიო პირობებს\nსაგარანტიო პირობები\nგაეცანი პროდუქტის სახელმძღვანელოს\nპროდუქტის სახელმძღვანელო\nგაეცანი სერტიფიკატს\nსერტიფიკატი\nფილიალები\nმარაგშია\nშეკვეთიდან 2-5 დღეში\nზუმერის City Mall საბურთალო-ს ფილიალი\n\nთბილისი - \"სითი მოლი\" - პეტრე ქავთარაძის N1\n\nმარაგშია\n+995 591 971 962\nორშ-შაბ: 10:00:00 - 22:00:00\nკვირა: 10:00:00 - 22:00:00\nზუმერის ისთ ფოინთის ფილიალი\n\nთბილისი - \"ისთ ფოინთი\" - ალ. თვალჭრელიძე N2\n\nმარაგშია\n+995 591 340 476\nორშ-შაბ: 10:00:00 - 22:00:00\nკვირა: 10:00:00 - 22:00:00\nბათუმი ჭავჭავაძის ფილიალი\n\nბათუმი - ბათუმი, ჭავჭავაძის N21\n\nმარაგშია\n+995 591 967 606\nორშ-შაბ: 10:00:00 - 20:00:00\nკვირა: 10:00:00 - 19:00:00\nბათუმის \"Black Sea Mall\"-ის ფილიალი\n\nბათუმი - \"Black Sea Mall\" - ტბელ აბუსერიძის N22\n\nმარაგშია\n+995 591 310 257\nორშ-შაბ: 10:00:00 - 21:00:00\nკვირა: 10:00:00 - 21:00:00\nზუგდიდი მოლის ფილიალი\n\nზუგდიდი - ზუგდიდი მოლი, კოსტავას ქუჩა №28\n\nმარაგშია\n+995 591 676 489\nორშ-შაბ: 10:00:00 - 22:00:00\nკვირა: 10:00:00 - 22:00:00\nმეტის ნახვა\n399 ₾\n\nთვეში: 11.1 ₾ -დან\n\nმარაგი ფილიალებში\nფასის დაზღვევა\nფასის კონტროლი\nფასის დაჯავშნა\nყიდვა\nშედარება\nდამატება\nნავიგაცია\n\nპერსონალურ მონაცემთა დაცვის პოლიტიკა\n\nჩვენ შესახებ\n\nწესები და პირობები\n\nმიწოდების სერვისი\n\nკარიერა\n\nგადახდები\n\nSetanta Sports\n\nგადახდის მეთოდები\n\nგარანტია\n\nგანვადება\n\nნივთის დაბრუნება\n\nნივთის ონლაინ ყიდვის ინსტრუქცია\n\nგამოგვყევი\n\nFacebook\n\nYoutube\n\nInstagram\n\nTik Tok\n\nკონტაქტი\n\nInfo@zoommer.ge\n\n+995 (32) 2 60 30 60 / *7007\n\nფილიალები\n\nკორპორატიული გაყიდვები\n\nZoommer App\n\nCopyright © 2023 Zoommer.ge. All rights reserved.\n\nCookie პოლიტიკა\n\nსაიტით სარგებლობის გაგრძელებით, შენ ეთანხმები Cookie ჩანაწერების გამოყენებას. მეტი ინფორმაცისათვის იხილეთ კონფიდენციალურობის პოლიტიკა\n\nგასაგებია",
    "specs": {
      "ბრენდი:": "Samsung",
      "კავშირის სტანდარტი:": "No",
      "SIM ბარათი:": "No",
      "კორპუსი:": "ალუმინი",
      "IP დაცვა :": "5 ATM, IP68",
      "ოპერაციული სისტემა:": "Wear OS",
      "ჩიპსეტი:": "Exynos W920",
      "NFC:": "Yes",
      "Bluetooth:": "5.0",
      "სენსორი:": "Accelerometer, Gyroscope, Barometer, Altimeter, Geomagnetic, Bioelectrical Impedance Analysis Sensor, Optical Heart Rate Sensor, Compass, Electrocardiogram Sensor",
      "სპიკერი:": "Yes",
      "ქართული ენის მხარდაჭერა:": "Yes",
      "გადახდის ფუნქცია (Pay):": "Yes",
      "კამერა:": "No",
      "ეკრანის ზომა:": "44 mm",
      "ეკრანის ტიპი:": "Super Amoled",
      "PPI:": "330 ppi",
      "რეზოლუცია:": "396 x 396 pixels",
      "ეკრანის სიკაშკაშე:": "-",
      "Always on Display:": "Yes",
      "Wi-Fi:": "Yes",
      "GPS:": "Yes",
      "შიდა მეხსიერება:": "16 GB",
      "ოპერატიული მეხსიერება:": "1.5 GB",
      "თავსებადობა (Android; iOS):": "Android",
      "ელემენტი:": "247 mAh",
      "ელემენტი დამუხტვის სიჩქარე:": "5 W",
      "ელემენტის ტიპი:": "Li - Ion",
      "Wireless დამუხტვა:": "Yes",
      "სამუშაო დრო:": "Up To 40 hrs",
      "წონა:": "26.6 g",
      "ფერი:": "Pink Gold"
    }
  },
  {
    "category": "Galaxy Watch",
    "title": "Samsung L310 44mm Galaxy Watch 7 Silver",
    "price": 549.0,
    "link": "https://zoommer.ge/smart-saatebi/samsung-l310-44mm-galaxy-watch-7-silver-p43728",
    "image": "/_next/image?url=https%3A%2F%2Fs3.zoommer.ge%2Fsite%2F3a925ad6-d30a-4d6b-a074-901be0b9d9f0_Thumb.jpeg&w=384&q=50",
    "product_title_detail": "Samsung L310 44mm Galaxy Watch 7 Silver",
    "description": "*7007 / +995 (32) 2 60 30 60\nფილიალები\nნავიგაცია\nკალათა\nშესვლა\n%\nმთავარი\nსმარტ საათები\nSamsung\n#ZOOM-034267\nSamsung L310 44mm Galaxy Watch 7 Silver\nეკრანის ზომა\n44 mm\nრეზოლუცია\n480 x 480 pixels\nსამუშაო დრო\nUp To 40 hrs\nეკრანის ტიპი\nSuper Amoled\nშიდა მეხსიერება\n32 GB\nBluetooth\n5.3\nოპერატიული მეხსიერება\n2 GB\nელემენტი\n425 mAh\nფერი: Silver\nერთად იაფია\nდაამატე ნივთი\nSamsung L310 44mm Galaxy Watch 7 Silver\n549 ₾\nSamsung Travel Adapter 25W EP-T2510 White\n52.25 ₾\n55 ₾\nჯამური ფასი (1)\n601.25 ₾\n604 ₾\nყიდვა\nაქსესუარები\nაღწერა\nმსგავსი\nმახასიათებლები\nფილიალები\nაქსესუარები\nაღწერა\nმსგავსი\nმახასიათებლები\nფილიალები\n49 ₾\n\nთვეში: 1 ₾ -დან\n\nXiaomi Redmi Buds 6 Lite Blue\nდამატება\n199 ₾\n\nთვეში: 5 ₾ -დან\n\nOnePlus Nord Buds 3 Pro Green\nდამატება\n119 ₾\n\nთვეში: 3 ₾ -დან\n\nNothing CMF Buds Pro Dark Grey\nდამატება\n149 ₾\n\nთვეში: 4 ₾ -დან\n\nRealme Buds Air 6 Silver\nდამატება\n129 ₾\n\nთვეში: 3 ₾ -დან\n\nNothing Buds CMF Neckband Pro Light Grey\nდამატება\n59 ₾\n\nთვეში: 1 ₾ -დან\n\nRealme Buds T01 Black\nდამატება\n139 ₾\n\nთვეში: 3 ₾ -დან\n\nNothing CMF Buds Pro 2 Blue\nდამატება\n299 ₾\n\nთვეში: 8 ₾ -დან\n\nRealme Buds Air 7 Pro Green\nდამატება\n299 ₾\n\nთვეში: 8 ₾ -დან\n\nRealme Buds Air 7 Pro Grey\nდამატება\n299 ₾\n\nთვეში: 8 ₾ -დან\n\nRealme Buds Air 7 Pro Red\nდამატება\n299 ₾\n\nთვეში: 8 ₾ -დან\n\nRealme Buds Air 7 Pro White\nდამატება\nპროდუქტის შესახებ\n\nSamsung L310 44mm Galaxy Watch 7 Silver - ფლაგმანური სმარტ საათი, შექმნილი მათთვის, ვინც აქტიურ დღის რეჟიმს აერთიანებს ტექნოლოგიურ სიზუსტესთან. მისი ძირითადი მიზანია, დაგეხმაროთ მუდმივად კავშირზე იყოთ...\n\nმეტის ნახვა\nმსგავსი პროდუქტები\n399 ₾\n\nთვეში: 11 ₾ -დან\n\nSamsung Galaxy Watch FE Pink Gold\nდამატება\n1199 ₾\n1299 ₾\n\nთვეში: 33 ₾ -დან\n\nSamsung L705 Galaxy Watch Ultra Titanium Grey\nდამატება\n1199 ₾\n1299 ₾\n\nთვეში: 33 ₾ -დან\n\nSamsung L705 Galaxy Watch Ultra Titanium Silver\nდამატება\n1199 ₾\n1299 ₾\n\nთვეში: 33 ₾ -დან\n\nSamsung L705 Galaxy Watch Ultra Titanium White\nდამატება\n549 ₾\n669 ₾\n\nთვეში: 15 ₾ -დან\n\nSamsung SM-R950 43mm Galaxy Watch 6 Classic Silver\nდამატება\n499 ₾\n\nთვეში: 13 ₾ -დან\n\nSamsung SM-R940 44mm Galaxy Watch 6 Silver\nდამატება\n569 ₾\n649 ₾\n\nთვეში: 15 ₾ -დან\n\nSamsung SM-R960 47mm Galaxy Watch 6 Classic Silver\nდამატება\n449 ₾\n499 ₾\n\nთვეში: 12 ₾ -დან\n\nSamsung L300 40mm Galaxy Watch 7 Cream\nდამატება\n449 ₾\n499 ₾\n\nთვეში: 12 ₾ -დან\n\nSamsung L300 40mm Galaxy Watch 7 Green\nდამატება\n549 ₾\n\nთვეში: 15 ₾ -დან\n\nSamsung L310 44mm Galaxy Watch 7 Green\nდამატება\n139 ₾\n\nთვეში: 3 ₾ -დან\n\nSamsung Galaxy Fit 3 R390 Silver\nდამატება\nდამატებითი მახასიათებლები\nბრენდი\nბრენდი:\n\t\nSamsung\nტექნიკური მახასიათებლები\nკავშირის სტანდარტი:\n\t\nNo\n\n\nSIM ბარათი:\n\t\nNo\n\n\nკორპუსი:\n\t\nალუმინი\n\n\nIP დაცვა :\n\t\n5 ATM, IP68\n\n\nოპერაციული სისტემა:\n\t\nWear OS\n\n\nჩიპსეტი:\n\t\nExynos W1000\n\n\nNFC:\n\t\nYes\n\n\nBluetooth:\n\t\n5.3\n\n\nსენსორი:\n\t\nAccelerometer, Barometer, Light Sensor, Bioelectrical Impedance Analysis Sensor, Electrical Heart Sensor, Gyro Sensor, Geomagnetic Sensor, Optical Heart Rate Sensor, Infrared Temperature Sensor\n\n\nსპიკერი:\n\t\nYes\n\n\nქართული ენის მხარდაჭერა:\n\t\nYes\n\n\nგადახდის ფუნქცია (Pay):\n\t\nYes\n\n\nკამერა:\n\t\nNo\nეკრანი\nეკრანის ზომა:\n\t\n44 mm\n\n\nეკრანის ტიპი:\n\t\nSuper Amoled\n\n\nPPI:\n\t\n453 ppi\n\n\nრეზოლუცია:\n\t\n480 x 480 pixels\n\n\nეკრანის სიკაშკაშე:\n\t\n3000 nits\n\n\nAlways on Display:\n\t\nYes\nდამატებითი მახასიათებლები\nWi-Fi:\n\t\nYes\n\n\nGPS:\n\t\nYes\nმეხსიერება\nშიდა მეხსიერება:\n\t\n32 GB\n\n\nოპერატიული მეხსიერება:\n\t\n2 GB\nთავსებადობა\nთავსებადობა (Android; iOS):\n\t\nAndroid\nელემენტი\nელემენტი:\n\t\n425 mAh\n\n\nელემენტი დამუხტვის სიჩქარე:\n\t\n15 W\n\n\nელემენტის ტიპი:\n\t\nLi - Ion\n\n\nWireless დამუხტვა:\n\t\nYes\n\n\nსამუშაო დრო:\n\t\nUp To 40 hrs\nზომა/წონა\nწონა:\n\t\n34.0 g\nმეტის ნახვა\nგაეცანი საგარანტიო პირობებს\nსაგარანტიო პირობები\nგაეცანი პროდუქტის სახელმძღვანელოს\nპროდუქტის სახელმძღვანელო\nგაეცანი სერტიფიკატს\nსერტიფიკატი\nფილიალები\nმარაგშია\nშეკვეთიდან 2-5 დღეში\nზუმერის წერეთლის ფილიალი\n\nთბილისი - წერეთლის გამზირი, N1.\n\nმარაგშია\n+995 591 967 601\nორშ-შაბ: 10:00:00 - 20:00:00\nკვირა: 10:00:00 - 19:00:00\nზუმერის პეკინის ფილიალი\n\nთბილისი - კ.გამსახურდიას (პეკინის) გამზირი N14ა\n\nმარაგშია\n+995 591 967 671\nორშ-შაბ: 10:00:00 - 21:00:00\nკვირა: 10:00:00 - 20:00:00\nზუმერის \"თბილისი ცენტრალის\" ფილიალი\n\nთბილისი - \"თბილისი ცენტრალი\"- lll სართული\n\nმარაგშია\n+995 599 862 449\nორშ-შაბ: 10:00:00 - 20:00:00\nკვირა: 10:00:00 - 19:00:00\nზუმერის City Mall საბურთალო-ს ფილიალი\n\nთბილისი - \"სითი მოლი\" - პეტრე ქავთარაძის N1\n\nმარაგშია\n+995 591 971 962\nორშ-შაბ: 10:00:00 - 22:00:00\nკვირა: 10:00:00 - 22:00:00\nზუმერის თბილისი მოლის ფილიალი\n\nთბილისი - „თბილისი მოლი\" - I სართული. აღმაშენებლის ხეივანი მე-16 კმ\n\nმარაგშია\n+995 591 967 608\nორშ-შაბ: 10:00:00 - 22:00:00\nკვირა: 10:00:00 - 22:00:00\nზუმერის \"გლდანი მოლის\" ფილიალი\n\nთბილისი - \"გლდანი მოლი\" - I სართული, M-ახმეტელის მიმდებარე\n\nმარაგშია\n+995 591 967 673\nორშ-შაბ: 10:00:00 - 21:00:00\nკვირა: 10:00:00 - 21:00:00\nზუმერის ისთ ფოინთის ფილიალი\n\nთბილისი - \"ისთ ფოინთი\" - ალ. თვალჭრელიძე N2\n\nმარაგშია\n+995 591 340 476\nორშ-შაბ: 10:00:00 - 22:00:00\nკვირა: 10:00:00 - 22:00:00\nზუმერი რუსთავი მოლის ფილიალი\n\nრუსთავი - შარტავას და ლომოურის კვეთა\n\nმარაგშია\n+995 591 441 082\nორშ-შაბ: 10:00:00 - 22:00:00\nკვირა: 10:00:00 - 22:00:00\nბათუმი ჭავჭავაძის ფილიალი\n\nბათუმი - ბათუმი, ჭავჭავაძის N21\n\nმარაგშია\n+995 591 967 606\nორშ-შაბ: 10:00:00 - 20:00:00\nკვირა: 10:00:00 - 19:00:00\nბათუმის \"Black Sea Mall\"-ის ფილიალი\n\nბათუმი - \"Black Sea Mall\" - ტბელ აბუსერიძის N22\n\nმარაგშია\n+995 591 310 257\nორშ-შაბ: 10:00:00 - 21:00:00\nკვირა: 10:00:00 - 21:00:00\nბათუმის გრანდ მოლის ფილიალი\n\nბათუმი - \"გრანდ მოლი\" - შერიფ ხიმშიაშვილის 29\n\nმარაგშია\n+995 591 022 872\nორშ-შაბ: 10:00:00 - 22:00:00\nკვირა: 10:00:00 - 22:00:00\nქუთაისი ვესთ მოლი\n\nქუთაისი - \"ვესთ მოლი\" - შარტავას N2\n\nმარაგშია\n+995 595 306 765\nორშ-შაბ: 10:00:00 - 22:00:00\nკვირა: 10:00:00 - 22:00:00\nზუგდიდი მოლის ფილიალი\n\nზუგდიდი - ზუგდიდი მოლი, კოსტავას ქუჩა №28\n\nმარაგშია\n+995 591 676 489\nორშ-შაბ: 10:00:00 - 22:00:00\nკვირა: 10:00:00 - 22:00:00\nგორი მოლის ფილიალი\n\nგორი - გორი, ცხინვალის გზატკეცილი 14-14ამ, გორი მოლი\n\nმარაგშია\n+995 591 198 248\nორშ-შაბ: 10:00:00 - 22:00:00\nკვირა: 10:00:00 - 22:00:00\nზუმერის საბითუმო საწყობი\n\nთბილისი - აკაკი წერეთლის გამზირი 1, საბითუმო საწყობი, -1 სართული\n\nმარაგშია\n+995 (32) 2 60 30 60\nორშ-შაბ: 10:00:00 - 19:00:00\nკვირა: 10:00:00 - 19:00:00\nმეტის ნახვა\n549 ₾\n\nთვეში: 15.3 ₾ -დან\n\nმარაგი ფილიალებში\nფასის დაზღვევა\nფასის კონტროლი\nფასის დაჯავშნა\nყიდვა\nშედარება\nდამატება\nნავიგაცია\nგადახდები\nგამოგვყევი\n\nFacebook\n\nYoutube\n\nInstagram\n\nTik Tok\n\nკონტაქტი\n\nInfo@zoommer.ge\n\n+995 (32) 2 60 30 60 / *7007\n\nფილიალები\n\nკორპორატიული გაყიდვები\n\nZoommer App\n\nCopyright © 2023 Zoommer.ge. All rights reserved.\n\nCookie პოლიტიკა\n\nსაიტით სარგებლობის გაგრძელებით, შენ ეთანხმები Cookie ჩანაწერების გამოყენებას. მეტი ინფორმაცისათვის იხილეთ კონფიდენციალურობის პოლიტიკა\n\nგასაგებია",
    "specs": {
      "ბრენდი:": "Samsung",
      "კავშირის სტანდარტი:": "No",
      "SIM ბარათი:": "No",
      "კორპუსი:": "ალუმინი",
      "IP დაცვა :": "5 ATM, IP68",
      "ოპერაციული სისტემა:": "Wear OS",
      "ჩიპსეტი:": "Exynos W1000",
      "NFC:": "Yes",
      "Bluetooth:": "5.3",
      "სენსორი:": "Accelerometer, Barometer, Light Sensor, Bioelectrical Impedance Analysis Sensor, Electrical Heart Sensor, Gyro Sensor, Geomagnetic Sensor, Optical Heart Rate Sensor, Infrared Temperature Sensor",
      "სპიკერი:": "Yes",
      "ქართული ენის მხარდაჭერა:": "Yes",
      "გადახდის ფუნქცია (Pay):": "Yes",
      "კამერა:": "No",
      "ეკრანის ზომა:": "44 mm",
      "ეკრანის ტიპი:": "Super Amoled",
      "PPI:": "453 ppi",
      "რეზოლუცია:": "480 x 480 pixels",
      "ეკრანის სიკაშკაშე:": "3000 nits",
      "Always on Display:": "Yes",
      "Wi-Fi:": "Yes",
      "GPS:": "Yes",
      "შიდა მეხსიერება:": "32 GB",
      "ოპერატიული მეხსიერება:": "2 GB",
      "თავსებადობა (Android; iOS):": "Android",
      "ელემენტი:": "425 mAh",
      "ელემენტი დამუხტვის სიჩქარე:": "15 W",
      "ელემენტის ტიპი:": "Li - Ion",
      "Wireless დამუხტვა:": "Yes",
      "სამუშაო დრო:": "Up To 40 hrs",
      "წონა:": "34.0 g"
    }
  },
  {
    "category": "Galaxy Watch",
    "title": "Samsung L310 44mm Galaxy Watch 7 Green",
    "price": 549.0,
    "link": "https://zoommer.ge/smart-saatebi/samsung-l310-44mm-galaxy-watch-7-green-p43727",
    "image": "/_next/image?url=https%3A%2F%2Fs3.zoommer.ge%2Fsite%2F5b784e5e-d8f6-4099-ae57-3b7bf4268b3c_Thumb.jpeg&w=384&q=50",
    "product_title_detail": "Samsung L310 44mm Galaxy Watch 7 Green",
    "description": "*7007 / +995 (32) 2 60 30 60\nფილიალები\nნავიგაცია\nკალათა\nშესვლა\n%\nმთავარი\nსმარტ საათები\nSamsung\n#ZOOM-034267\nSamsung L310 44mm Galaxy Watch 7 Green\nეკრანის ზომა\n44 mm\nრეზოლუცია\n480 x 480 pixels\nსამუშაო დრო\nUp To 40 hrs\nეკრანის ტიპი\nSuper Amoled\nშიდა მეხსიერება\n32 GB\nBluetooth\n5.3\nოპერატიული მეხსიერება\n2 GB\nელემენტი\n425 mAh\nფერი: Dark Green\nერთად იაფია\nდაამატე ნივთი\nSamsung L310 44mm Galaxy Watch 7 Green\n549 ₾\nSamsung Travel Adapter 25W EP-T2510 White\n52.25 ₾\n55 ₾\nჯამური ფასი (1)\n601.25 ₾\n604 ₾\nყიდვა\nაქსესუარები\nაღწერა\nმსგავსი\nმახასიათებლები\nფილიალები\nაქსესუარები\nაღწერა\nმსგავსი\nმახასიათებლები\nფილიალები\n49 ₾\n\nთვეში: 1 ₾ -დან\n\nXiaomi Redmi Buds 6 Lite Blue\nდამატება\n199 ₾\n\nთვეში: 5 ₾ -დან\n\nOnePlus Nord Buds 3 Pro Green\nდამატება\n119 ₾\n\nთვეში: 3 ₾ -დან\n\nNothing CMF Buds Pro Dark Grey\nდამატება\n149 ₾\n\nთვეში: 4 ₾ -დან\n\nRealme Buds Air 6 Silver\nდამატება\n129 ₾\n\nთვეში: 3 ₾ -დან\n\nNothing Buds CMF Neckband Pro Light Grey\nდამატება\n59 ₾\n\nთვეში: 1 ₾ -დან\n\nRealme Buds T01 Black\nდამატება\n139 ₾\n\nთვეში: 3 ₾ -დან\n\nNothing CMF Buds Pro 2 Blue\nდამატება\n299 ₾\n\nთვეში: 8 ₾ -დან\n\nRealme Buds Air 7 Pro Green\nდამატება\n299 ₾\n\nთვეში: 8 ₾ -დან\n\nRealme Buds Air 7 Pro Grey\nდამატება\n299 ₾\n\nთვეში: 8 ₾ -დან\n\nRealme Buds Air 7 Pro Red\nდამატება\n299 ₾\n\nთვეში: 8 ₾ -დან\n\nRealme Buds Air 7 Pro White\nდამატება\nპროდუქტის შესახებ\n\nSamsung L310 44mm Galaxy Watch 7 Green - ფლაგმანური სმარტ საათი, შექმნილი მათთვის, ვინც აქტიურ დღის რეჟიმს აერთიანებს ტექნოლოგიურ სიზუსტესთან. მისი ძირითადი მიზანია, დაგეხმაროთ მუდმივად კავშირზე იყოთ ...\n\nმეტის ნახვა\nმსგავსი პროდუქტები\n399 ₾\n\nთვეში: 11 ₾ -დან\n\nSamsung Galaxy Watch FE Pink Gold\nდამატება\n1199 ₾\n1299 ₾\n\nთვეში: 33 ₾ -დან\n\nSamsung L705 Galaxy Watch Ultra Titanium Grey\nდამატება\n1199 ₾\n1299 ₾\n\nთვეში: 33 ₾ -დან\n\nSamsung L705 Galaxy Watch Ultra Titanium Silver\nდამატება\n1199 ₾\n1299 ₾\n\nთვეში: 33 ₾ -დან\n\nSamsung L705 Galaxy Watch Ultra Titanium White\nდამატება\n549 ₾\n669 ₾\n\nთვეში: 15 ₾ -დან\n\nSamsung SM-R950 43mm Galaxy Watch 6 Classic Silver\nდამატება\n499 ₾\n\nთვეში: 13 ₾ -დან\n\nSamsung SM-R940 44mm Galaxy Watch 6 Silver\nდამატება\n569 ₾\n649 ₾\n\nთვეში: 15 ₾ -დან\n\nSamsung SM-R960 47mm Galaxy Watch 6 Classic Silver\nდამატება\n449 ₾\n499 ₾\n\nთვეში: 12 ₾ -დან\n\nSamsung L300 40mm Galaxy Watch 7 Cream\nდამატება\n449 ₾\n499 ₾\n\nთვეში: 12 ₾ -დან\n\nSamsung L300 40mm Galaxy Watch 7 Green\nდამატება\n549 ₾\n\nთვეში: 15 ₾ -დან\n\nSamsung L310 44mm Galaxy Watch 7 Silver\nდამატება\n139 ₾\n\nთვეში: 3 ₾ -დან\n\nSamsung Galaxy Fit 3 R390 Silver\nდამატება\nდამატებითი მახასიათებლები\nბრენდი\nბრენდი:\n\t\nSamsung\nტექნიკური მახასიათებლები\nკავშირის სტანდარტი:\n\t\nNo\n\n\nSIM ბარათი:\n\t\nNo\n\n\nკორპუსი:\n\t\nალუმინი\n\n\nIP დაცვა :\n\t\n5 ATM, IP68\n\n\nოპერაციული სისტემა:\n\t\nWear OS\n\n\nჩიპსეტი:\n\t\nExynos W1000\n\n\nNFC:\n\t\nYes\n\n\nBluetooth:\n\t\n5.3\n\n\nსენსორი:\n\t\nAccelerometer, Barometer, Light Sensor, Bioelectrical Impedance Analysis Sensor, Electrical Heart Sensor, Gyro Sensor, Geomagnetic Sensor, Optical Heart Rate Sensor, Infrared Temperature Sensor\n\n\nსპიკერი:\n\t\nYes\n\n\nქართული ენის მხარდაჭერა:\n\t\nYes\n\n\nგადახდის ფუნქცია (Pay):\n\t\nYes\n\n\nკამერა:\n\t\nNo\nეკრანი\nეკრანის ზომა:\n\t\n44 mm\n\n\nეკრანის ტიპი:\n\t\nSuper Amoled\n\n\nPPI:\n\t\n453 ppi\n\n\nრეზოლუცია:\n\t\n480 x 480 pixels\n\n\nეკრანის სიკაშკაშე:\n\t\n3000 nits\n\n\nAlways on Display:\n\t\nYes\nდამატებითი მახასიათებლები\nWi-Fi:\n\t\nYes\n\n\nGPS:\n\t\nYes\nმეხსიერება\nშიდა მეხსიერება:\n\t\n32 GB\n\n\nოპერატიული მეხსიერება:\n\t\n2 GB\nთავსებადობა\nთავსებადობა (Android; iOS):\n\t\nAndroid\nელემენტი\nელემენტი:\n\t\n425 mAh\n\n\nელემენტი დამუხტვის სიჩქარე:\n\t\n15 W\n\n\nელემენტის ტიპი:\n\t\nLi - Ion\n\n\nWireless დამუხტვა:\n\t\nYes\n\n\nსამუშაო დრო:\n\t\nUp To 40 hrs\nზომა/წონა\nწონა:\n\t\n34.0 g\nმეტის ნახვა\nგაეცანი საგარანტიო პირობებს\nსაგარანტიო პირობები\nგაეცანი პროდუქტის სახელმძღვანელოს\nპროდუქტის სახელმძღვანელო\nგაეცანი სერტიფიკატს\nსერტიფიკატი\nფილიალები\nმარაგშია\nშეკვეთიდან 2-5 დღეში\nზუმერის წერეთლის ფილიალი\n\nთბილისი - წერეთლის გამზირი, N1.\n\nმარაგშია\n+995 591 967 601\nორშ-შაბ: 10:00:00 - 20:00:00\nკვირა: 10:00:00 - 19:00:00\nზუმერის \"თბილისი ცენტრალის\" ფილიალი\n\nთბილისი - \"თბილისი ცენტრალი\"- lll სართული\n\nმარაგშია\n+995 599 862 449\nორშ-შაბ: 10:00:00 - 20:00:00\nკვირა: 10:00:00 - 19:00:00\nზუმერის City Mall საბურთალო-ს ფილიალი\n\nთბილისი - \"სითი მოლი\" - პეტრე ქავთარაძის N1\n\nმარაგშია\n+995 591 971 962\nორშ-შაბ: 10:00:00 - 22:00:00\nკვირა: 10:00:00 - 22:00:00\nზუმერის თბილისი მოლის ფილიალი\n\nთბილისი - „თბილისი მოლი\" - I სართული. აღმაშენებლის ხეივანი მე-16 კმ\n\nმარაგშია\n+995 591 967 608\nორშ-შაბ: 10:00:00 - 22:00:00\nკვირა: 10:00:00 - 22:00:00\nზუმერის \"გლდანი მოლის\" ფილიალი\n\nთბილისი - \"გლდანი მოლი\" - I სართული, M-ახმეტელის მიმდებარე\n\nმარაგშია\n+995 591 967 673\nორშ-შაბ: 10:00:00 - 21:00:00\nკვირა: 10:00:00 - 21:00:00\nზუმერის ისთ ფოინთის ფილიალი\n\nთბილისი - \"ისთ ფოინთი\" - ალ. თვალჭრელიძე N2\n\nმარაგშია\n+995 591 340 476\nორშ-შაბ: 10:00:00 - 22:00:00\nკვირა: 10:00:00 - 22:00:00\nზუმერი რუსთავი მოლის ფილიალი\n\nრუსთავი - შარტავას და ლომოურის კვეთა\n\nმარაგშია\n+995 591 441 082\nორშ-შაბ: 10:00:00 - 22:00:00\nკვირა: 10:00:00 - 22:00:00\nბათუმი ჭავჭავაძის ფილიალი\n\nბათუმი - ბათუმი, ჭავჭავაძის N21\n\nმარაგშია\n+995 591 967 606\nორშ-შაბ: 10:00:00 - 20:00:00\nკვირა: 10:00:00 - 19:00:00\nბათუმის \"Black Sea Mall\"-ის ფილიალი\n\nბათუმი - \"Black Sea Mall\" - ტბელ აბუსერიძის N22\n\nმარაგშია\n+995 591 310 257\nორშ-შაბ: 10:00:00 - 21:00:00\nკვირა: 10:00:00 - 21:00:00\nბათუმის გრანდ მოლის ფილიალი\n\nბათუმი - \"გრანდ მოლი\" - შერიფ ხიმშიაშვილის 29\n\nმარაგშია\n+995 591 022 872\nორშ-შაბ: 10:00:00 - 22:00:00\nკვირა: 10:00:00 - 22:00:00\nქუთაისი ვესთ მოლი\n\nქუთაისი - \"ვესთ მოლი\" - შარტავას N2\n\nმარაგშია\n+995 595 306 765\nორშ-შაბ: 10:00:00 - 22:00:00\nკვირა: 10:00:00 - 22:00:00\nზუგდიდი მოლის ფილიალი\n\nზუგდიდი - ზუგდიდი მოლი, კოსტავას ქუჩა №28\n\nმარაგშია\n+995 591 676 489\nორშ-შაბ: 10:00:00 - 22:00:00\nკვირა: 10:00:00 - 22:00:00\nგორი მოლის ფილიალი\n\nგორი - გორი, ცხინვალის გზატკეცილი 14-14ამ, გორი მოლი\n\nმარაგშია\n+995 591 198 248\nორშ-შაბ: 10:00:00 - 22:00:00\nკვირა: 10:00:00 - 22:00:00\nახალციხის ფილიალი\n\nახალციხე - ახალციხე, თამარ მეფის ქ. N9\n\nმარაგშია\n+995 598 088 659\nორშ-შაბ: 10:00:00 - 19:00:00\nკვირა: 10:00:00 - 19:00:00\nთელავი მოლის ფილიალი\n\nთელავი - \"თელავი მოლი\" - ალაზნის ქ.N77\n\nმარაგშია\n+995 595 069 853\nორშ-შაბ: 10:00:00 - 20:00:00\nკვირა: 10:00:00 - 19:00:00\nზუმერის საბითუმო საწყობი\n\nთბილისი - აკაკი წერეთლის გამზირი 1, საბითუმო საწყობი, -1 სართული\n\nმარაგშია\n+995 (32) 2 60 30 60\nორშ-შაბ: 10:00:00 - 19:00:00\nკვირა: 10:00:00 - 19:00:00\nმეტის ნახვა\n549 ₾\n\nთვეში: 15.3 ₾ -დან\n\nმარაგი ფილიალებში\nფასის დაზღვევა\nფასის კონტროლი\nფასის დაჯავშნა\nყიდვა\nშედარება\nდამატება\nნავიგაცია\nგადახდები\nგამოგვყევი\n\nFacebook\n\nYoutube\n\nInstagram\n\nTik Tok\n\nკონტაქტი\n\nInfo@zoommer.ge\n\n+995 (32) 2 60 30 60 / *7007\n\nფილიალები\n\nკორპორატიული გაყიდვები\n\nZoommer App\n\nCopyright © 2023 Zoommer.ge. All rights reserved.\n\nCookie პოლიტიკა\n\nსაიტით სარგებლობის გაგრძელებით, შენ ეთანხმები Cookie ჩანაწერების გამოყენებას. მეტი ინფორმაცისათვის იხილეთ კონფიდენციალურობის პოლიტიკა\n\nგასაგებია",
    "specs": {
      "ბრენდი:": "Samsung",
      "კავშირის სტანდარტი:": "No",
      "SIM ბარათი:": "No",
      "კორპუსი:": "ალუმინი",
      "IP დაცვა :": "5 ATM, IP68",
      "ოპერაციული სისტემა:": "Wear OS",
      "ჩიპსეტი:": "Exynos W1000",
      "NFC:": "Yes",
      "Bluetooth:": "5.3",
      "სენსორი:": "Accelerometer, Barometer, Light Sensor, Bioelectrical Impedance Analysis Sensor, Electrical Heart Sensor, Gyro Sensor, Geomagnetic Sensor, Optical Heart Rate Sensor, Infrared Temperature Sensor",
      "სპიკერი:": "Yes",
      "ქართული ენის მხარდაჭერა:": "Yes",
      "გადახდის ფუნქცია (Pay):": "Yes",
      "კამერა:": "No",
      "ეკრანის ზომა:": "44 mm",
      "ეკრანის ტიპი:": "Super Amoled",
      "PPI:": "453 ppi",
      "რეზოლუცია:": "480 x 480 pixels",
      "ეკრანის სიკაშკაშე:": "3000 nits",
      "Always on Display:": "Yes",
      "Wi-Fi:": "Yes",
      "GPS:": "Yes",
      "შიდა მეხსიერება:": "32 GB",
      "ოპერატიული მეხსიერება:": "2 GB",
      "თავსებადობა (Android; iOS):": "Android",
      "ელემენტი:": "425 mAh",
      "ელემენტი დამუხტვის სიჩქარე:": "15 W",
      "ელემენტის ტიპი:": "Li - Ion",
      "Wireless დამუხტვა:": "Yes",
      "სამუშაო დრო:": "Up To 40 hrs",
      "წონა:": "34.0 g"
    }
  },
  {
    "category": "Galaxy Watch",
    "title": "Samsung L300 40mm Galaxy Watch 7 Green",
    "price": 449.0,
    "link": "https://zoommer.ge/smart-saatebi/samsung-l300-40mm-galaxy-watch-7-green-p43534",
    "image": "/_next/image?url=https%3A%2F%2Fs3.zoommer.ge%2Fsite%2Fa89105b3-1bb6-4d29-9caa-afa42fdd9b06_Thumb.jpeg&w=384&q=50",
    "product_title_detail": "Samsung L300 40mm Galaxy Watch 7 Green",
    "description": "*7007 / +995 (32) 2 60 30 60\nფილიალები\nნავიგაცია\nკალათა\nშესვლა\n%\nმთავარი\nსმარტ საათები\nSamsung\n#ZOOM-034124\nSamsung L300 40mm Galaxy Watch 7 Green\nეკრანის ზომა\n40 mm\nრეზოლუცია\n432 x 432 pixels\nსამუშაო დრო\nUp To 40 hrs\nეკრანის ტიპი\nSuper Amoled\nშიდა მეხსიერება\n32 GB\nBluetooth\n5.3\nოპერატიული მეხსიერება\n2 GB\nელემენტი\n300 mAh\nფერი: Dark Green\nერთად იაფია\nდაამატე ნივთი\nSamsung L300 40mm Galaxy Watch 7 Green\n449 ₾\nGlass Pro+ Full Screen Film Samsung Watch 7 40MM Black\n19 ₾\nSamsung Travel Adapter 25W EP-T2510 White\n52.25 ₾\n55 ₾\nჯამური ფასი (2)\n520.25 ₾\n523 ₾\nყიდვა\nაქსესუარები\nაღწერა\nმსგავსი\nმახასიათებლები\nფილიალები\nაქსესუარები\nაღწერა\nმსგავსი\nმახასიათებლები\nფილიალები\n49 ₾\n\nთვეში: 1 ₾ -დან\n\nXiaomi Redmi Buds 6 Lite Blue\nდამატება\n199 ₾\n\nთვეში: 5 ₾ -დან\n\nOnePlus Nord Buds 3 Pro Green\nდამატება\n119 ₾\n\nთვეში: 3 ₾ -დან\n\nNothing CMF Buds Pro Dark Grey\nდამატება\n149 ₾\n\nთვეში: 4 ₾ -დან\n\nRealme Buds Air 6 Silver\nდამატება\n129 ₾\n\nთვეში: 3 ₾ -დან\n\nNothing Buds CMF Neckband Pro Light Grey\nდამატება\n59 ₾\n\nთვეში: 1 ₾ -დან\n\nRealme Buds T01 Black\nდამატება\n139 ₾\n\nთვეში: 3 ₾ -დან\n\nNothing CMF Buds Pro 2 Blue\nდამატება\n299 ₾\n\nთვეში: 8 ₾ -დან\n\nRealme Buds Air 7 Pro Green\nდამატება\n299 ₾\n\nთვეში: 8 ₾ -დან\n\nRealme Buds Air 7 Pro Grey\nდამატება\n299 ₾\n\nთვეში: 8 ₾ -დან\n\nRealme Buds Air 7 Pro Red\nდამატება\n299 ₾\n\nთვეში: 8 ₾ -დან\n\nRealme Buds Air 7 Pro White\nდამატება\nპროდუქტის შესახებ\n\nSamsung L300 40mm Galaxy Watch 7 Green - ფლაგმანური სმარტ საათი, შექმნილი მათთვის, ვინც აქტიურ დღის რეჟიმს აერთიანებს ტექნოლოგიურ სიზუსტესთან. მისი ძირითადი მიზანია, დაგეხმაროთ მუდმივად კავშირზე იყოთ ...\n\nმეტის ნახვა\nმსგავსი პროდუქტები\n399 ₾\n\nთვეში: 11 ₾ -დან\n\nSamsung Galaxy Watch FE Pink Gold\nდამატება\n1199 ₾\n1299 ₾\n\nთვეში: 33 ₾ -დან\n\nSamsung L705 Galaxy Watch Ultra Titanium Grey\nდამატება\n1199 ₾\n1299 ₾\n\nთვეში: 33 ₾ -დან\n\nSamsung L705 Galaxy Watch Ultra Titanium Silver\nდამატება\n1199 ₾\n1299 ₾\n\nთვეში: 33 ₾ -დან\n\nSamsung L705 Galaxy Watch Ultra Titanium White\nდამატება\n549 ₾\n669 ₾\n\nთვეში: 15 ₾ -დან\n\nSamsung SM-R950 43mm Galaxy Watch 6 Classic Silver\nდამატება\n499 ₾\n\nთვეში: 13 ₾ -დან\n\nSamsung SM-R940 44mm Galaxy Watch 6 Silver\nდამატება\n569 ₾\n649 ₾\n\nთვეში: 15 ₾ -დან\n\nSamsung SM-R960 47mm Galaxy Watch 6 Classic Silver\nდამატება\n449 ₾\n499 ₾\n\nთვეში: 12 ₾ -დან\n\nSamsung L300 40mm Galaxy Watch 7 Cream\nდამატება\n549 ₾\n\nთვეში: 15 ₾ -დან\n\nSamsung L310 44mm Galaxy Watch 7 Green\nდამატება\n549 ₾\n\nთვეში: 15 ₾ -დან\n\nSamsung L310 44mm Galaxy Watch 7 Silver\nდამატება\n139 ₾\n\nთვეში: 3 ₾ -დან\n\nSamsung Galaxy Fit 3 R390 Silver\nდამატება\nდამატებითი მახასიათებლები\nბრენდი\nბრენდი:\n\t\nSamsung\nტექნიკური მახასიათებლები\nკავშირის სტანდარტი:\n\t\nNo\n\n\nSIM ბარათი:\n\t\nNo\n\n\nკორპუსი:\n\t\nალუმინი\n\n\nIP დაცვა :\n\t\n5 ATM, IP68\n\n\nოპერაციული სისტემა:\n\t\nWear OS\n\n\nჩიპსეტი:\n\t\nExynos W1000\n\n\nNFC:\n\t\nYes\n\n\nBluetooth:\n\t\n5.3\n\n\nსენსორი:\n\t\nAccelerometer, Barometer, Light Sensor, Bioelectrical Impedance Analysis Sensor, Electrical Heart Sensor, Gyro Sensor, Geomagnetic Sensor, Optical Heart Rate Sensor, Infrared Temperature Sensor\n\n\nსპიკერი:\n\t\nYes\n\n\nქართული ენის მხარდაჭერა:\n\t\nYes\n\n\nგადახდის ფუნქცია (Pay):\n\t\nYes\n\n\nკამერა:\n\t\nNo\nეკრანი\nეკრანის ზომა:\n\t\n40 mm\n\n\nეკრანის ტიპი:\n\t\nSuper Amoled\n\n\nPPI:\n\t\n330 ppi\n\n\nრეზოლუცია:\n\t\n432 x 432 pixels\n\n\nეკრანის სიკაშკაშე:\n\t\n3000 nits\n\n\nAlways on Display:\n\t\nYes\nდამატებითი მახასიათებლები\nWi-Fi:\n\t\nYes\n\n\nGPS:\n\t\nYes\nმეხსიერება\nშიდა მეხსიერება:\n\t\n32 GB\n\n\nოპერატიული მეხსიერება:\n\t\n2 GB\nთავსებადობა\nთავსებადობა (Android; iOS):\n\t\nAndroid\nელემენტი\nელემენტი:\n\t\n300 mAh\n\n\nელემენტი დამუხტვის სიჩქარე:\n\t\n15 W\n\n\nელემენტის ტიპი:\n\t\nLi - Ion\n\n\nWireless დამუხტვა:\n\t\nYes\n\n\nსამუშაო დრო:\n\t\nUp To 40 hrs\nზომა/წონა\nწონა:\n\t\n28.7 g\nმეტის ნახვა\nგაეცანი საგარანტიო პირობებს\nსაგარანტიო პირობები\nგაეცანი პროდუქტის სახელმძღვანელოს\nპროდუქტის სახელმძღვანელო\nგაეცანი სერტიფიკატს\nსერტიფიკატი\nფილიალები\nმარაგშია\nშეკვეთიდან 2-5 დღეში\nზუმერის წერეთლის ფილიალი\n\nთბილისი - წერეთლის გამზირი, N1.\n\nმარაგშია\n+995 591 967 601\nორშ-შაბ: 10:00:00 - 20:00:00\nკვირა: 10:00:00 - 19:00:00\nზუმერის პეკინის ფილიალი\n\nთბილისი - კ.გამსახურდიას (პეკინის) გამზირი N14ა\n\nმარაგშია\n+995 591 967 671\nორშ-შაბ: 10:00:00 - 21:00:00\nკვირა: 10:00:00 - 20:00:00\nზუმერის \"თბილისი ცენტრალის\" ფილიალი\n\nთბილისი - \"თბილისი ცენტრალი\"- lll სართული\n\nმარაგშია\n+995 599 862 449\nორშ-შაბ: 10:00:00 - 20:00:00\nკვირა: 10:00:00 - 19:00:00\nზუმერის City Mall საბურთალო-ს ფილიალი\n\nთბილისი - \"სითი მოლი\" - პეტრე ქავთარაძის N1\n\nმარაგშია\n+995 591 971 962\nორშ-შაბ: 10:00:00 - 22:00:00\nკვირა: 10:00:00 - 22:00:00\nზუმერის თბილისი მოლის ფილიალი\n\nთბილისი - „თბილისი მოლი\" - I სართული. აღმაშენებლის ხეივანი მე-16 კმ\n\nმარაგშია\n+995 591 967 608\nორშ-შაბ: 10:00:00 - 22:00:00\nკვირა: 10:00:00 - 22:00:00\nზუმერის \"გლდანი მოლის\" ფილიალი\n\nთბილისი - \"გლდანი მოლი\" - I სართული, M-ახმეტელის მიმდებარე\n\nმარაგშია\n+995 591 967 673\nორშ-შაბ: 10:00:00 - 21:00:00\nკვირა: 10:00:00 - 21:00:00\nზუმერის ისთ ფოინთის ფილიალი\n\nთბილისი - \"ისთ ფოინთი\" - ალ. თვალჭრელიძე N2\n\nმარაგშია\n+995 591 340 476\nორშ-შაბ: 10:00:00 - 22:00:00\nკვირა: 10:00:00 - 22:00:00\nზუმერი რუსთავი მოლის ფილიალი\n\nრუსთავი - შარტავას და ლომოურის კვეთა\n\nმარაგშია\n+995 591 441 082\nორშ-შაბ: 10:00:00 - 22:00:00\nკვირა: 10:00:00 - 22:00:00\nბათუმი ჭავჭავაძის ფილიალი\n\nბათუმი - ბათუმი, ჭავჭავაძის N21\n\nმარაგშია\n+995 591 967 606\nორშ-შაბ: 10:00:00 - 20:00:00\nკვირა: 10:00:00 - 19:00:00\nბათუმის \"Black Sea Mall\"-ის ფილიალი\n\nბათუმი - \"Black Sea Mall\" - ტბელ აბუსერიძის N22\n\nმარაგშია\n+995 591 310 257\nორშ-შაბ: 10:00:00 - 21:00:00\nკვირა: 10:00:00 - 21:00:00\nბათუმის გრანდ მოლის ფილიალი\n\nბათუმი - \"გრანდ მოლი\" - შერიფ ხიმშიაშვილის 29\n\nმარაგშია\n+995 591 022 872\nორშ-შაბ: 10:00:00 - 22:00:00\nკვირა: 10:00:00 - 22:00:00\nქუთაისის ფილიალი\n\nქუთაისი - თამარ მეფის ქ. N3 , ქუთაისის ცენტრალური მოედანი\n\nმარაგშია\n+955 591 967 605\nორშ-შაბ: 10:00:00 - 20:00:00\nკვირა: 10:00:00 - 19:00:00\nქუთაისი ვესთ მოლი\n\nქუთაისი - \"ვესთ მოლი\" - შარტავას N2\n\nმარაგშია\n+995 595 306 765\nორშ-შაბ: 10:00:00 - 22:00:00\nკვირა: 10:00:00 - 22:00:00\nზუგდიდი მოლის ფილიალი\n\nზუგდიდი - ზუგდიდი მოლი, კოსტავას ქუჩა №28\n\nმარაგშია\n+995 591 676 489\nორშ-შაბ: 10:00:00 - 22:00:00\nკვირა: 10:00:00 - 22:00:00\nახალციხის ფილიალი\n\nახალციხე - ახალციხე, თამარ მეფის ქ. N9\n\nმარაგშია\n+995 598 088 659\nორშ-შაბ: 10:00:00 - 19:00:00\nკვირა: 10:00:00 - 19:00:00\nთელავი მოლის ფილიალი\n\nთელავი - \"თელავი მოლი\" - ალაზნის ქ.N77\n\nმარაგშია\n+995 595 069 853\nორშ-შაბ: 10:00:00 - 20:00:00\nკვირა: 10:00:00 - 19:00:00\nზუმერის საბითუმო საწყობი\n\nთბილისი - აკაკი წერეთლის გამზირი 1, საბითუმო საწყობი, -1 სართული\n\nმარაგშია\n+995 (32) 2 60 30 60\nორშ-შაბ: 10:00:00 - 19:00:00\nკვირა: 10:00:00 - 19:00:00\nმეტის ნახვა\n449 ₾\n499 ₾\n\nთვეში: 12.5 ₾ -დან\n\nმარაგი ფილიალებში\nფასის დაზღვევა\nფასის კონტროლი\nფასის დაჯავშნა\nყიდვა\nშედარება\nდამატება\nნავიგაცია\nგადახდები\nგამოგვყევი\n\nFacebook\n\nYoutube\n\nInstagram\n\nTik Tok\n\nკონტაქტი\n\nInfo@zoommer.ge\n\n+995 (32) 2 60 30 60 / *7007\n\nფილიალები\n\nკორპორატიული გაყიდვები\n\nZoommer App\n\nCopyright © 2023 Zoommer.ge. All rights reserved.\n\nCookie პოლიტიკა\n\nსაიტით სარგებლობის გაგრძელებით, შენ ეთანხმები Cookie ჩანაწერების გამოყენებას. მეტი ინფორმაცისათვის იხილეთ კონფიდენციალურობის პოლიტიკა\n\nგასაგებია",
    "specs": {
      "ბრენდი:": "Samsung",
      "კავშირის სტანდარტი:": "No",
      "SIM ბარათი:": "No",
      "კორპუსი:": "ალუმინი",
      "IP დაცვა :": "5 ATM, IP68",
      "ოპერაციული სისტემა:": "Wear OS",
      "ჩიპსეტი:": "Exynos W1000",
      "NFC:": "Yes",
      "Bluetooth:": "5.3",
      "სენსორი:": "Accelerometer, Barometer, Light Sensor, Bioelectrical Impedance Analysis Sensor, Electrical Heart Sensor, Gyro Sensor, Geomagnetic Sensor, Optical Heart Rate Sensor, Infrared Temperature Sensor",
      "სპიკერი:": "Yes",
      "ქართული ენის მხარდაჭერა:": "Yes",
      "გადახდის ფუნქცია (Pay):": "Yes",
      "კამერა:": "No",
      "ეკრანის ზომა:": "40 mm",
      "ეკრანის ტიპი:": "Super Amoled",
      "PPI:": "330 ppi",
      "რეზოლუცია:": "432 x 432 pixels",
      "ეკრანის სიკაშკაშე:": "3000 nits",
      "Always on Display:": "Yes",
      "Wi-Fi:": "Yes",
      "GPS:": "Yes",
      "შიდა მეხსიერება:": "32 GB",
      "ოპერატიული მეხსიერება:": "2 GB",
      "თავსებადობა (Android; iOS):": "Android",
      "ელემენტი:": "300 mAh",
      "ელემენტი დამუხტვის სიჩქარე:": "15 W",
      "ელემენტის ტიპი:": "Li - Ion",
      "Wireless დამუხტვა:": "Yes",
      "სამუშაო დრო:": "Up To 40 hrs",
      "წონა:": "28.7 g"
    }
  },
  {
    "category": "Galaxy Watch",
    "title": "Samsung L300 40mm Galaxy Watch 7 Cream",
    "price": 449.0,
    "link": "https://zoommer.ge/smart-saatebi/samsung-l300-40mm-galaxy-watch-7-cream-p43533",
    "image": "/_next/image?url=https%3A%2F%2Fs3.zoommer.ge%2Fsite%2F90fed208-4e7d-4c58-bff9-1bef07e24d99_Thumb.jpeg&w=384&q=50",
    "product_title_detail": "Samsung L300 40mm Galaxy Watch 7 Cream",
    "description": "*7007 / +995 (32) 2 60 30 60\nსავაჭრო პოლიტიკა\nგანვადება\nკარიერა\nTrade In\nფილიალები\nნავიგაცია\nკალათა\nშესვლა\n%\nმთავარი\nსმარტ საათები\nSamsung\n#ZOOM-034124\nSamsung L300 40mm Galaxy Watch 7 Cream\nეკრანის ზომა\n40 mm\nრეზოლუცია\n432 x 432 pixels\nსამუშაო დრო\nUp To 40 hrs\nეკრანის ტიპი\nSuper Amoled\nშიდა მეხსიერება\n32 GB\nBluetooth\n5.3\nოპერატიული მეხსიერება\n2 GB\nელემენტი\n300 mAh\nფერი: Cream\nერთად იაფია\nდაამატე ნივთი\nSamsung L300 40mm Galaxy Watch 7 Cream\n449 ₾\nGlass Pro+ Full Screen Film Samsung Watch 7 40MM Black\n19 ₾\nSamsung Travel Adapter 25W EP-T2510 White\n52.25 ₾\n55 ₾\nჯამური ფასი (2)\n520.25 ₾\n523 ₾\nყიდვა\nაქსესუარები\nაღწერა\nმსგავსი\nმახასიათებლები\nფილიალები\nაქსესუარები\nაღწერა\nმსგავსი\nმახასიათებლები\nფილიალები\n49 ₾\n\nთვეში: 1 ₾ -დან\n\nXiaomi Redmi Buds 6 Lite Blue\nდამატება\n199 ₾\n\nთვეში: 5 ₾ -დან\n\nOnePlus Nord Buds 3 Pro Green\nდამატება\n119 ₾\n\nთვეში: 3 ₾ -დან\n\nNothing CMF Buds Pro Dark Grey\nდამატება\n149 ₾\n\nთვეში: 4 ₾ -დან\n\nRealme Buds Air 6 Silver\nდამატება\n129 ₾\n\nთვეში: 3 ₾ -დან\n\nNothing Buds CMF Neckband Pro Light Grey\nდამატება\n59 ₾\n\nთვეში: 1 ₾ -დან\n\nRealme Buds T01 Black\nდამატება\n139 ₾\n\nთვეში: 3 ₾ -დან\n\nNothing CMF Buds Pro 2 Blue\nდამატება\n299 ₾\n\nთვეში: 8 ₾ -დან\n\nRealme Buds Air 7 Pro Green\nდამატება\n299 ₾\n\nთვეში: 8 ₾ -დან\n\nRealme Buds Air 7 Pro Grey\nდამატება\n299 ₾\n\nთვეში: 8 ₾ -დან\n\nRealme Buds Air 7 Pro Red\nდამატება\n299 ₾\n\nთვეში: 8 ₾ -დან\n\nRealme Buds Air 7 Pro White\nდამატება\nპროდუქტის შესახებ\n\nSamsung L300 40mm Galaxy Watch 7 Cream - ფლაგმანური სმარტ საათი, შექმნილი მათთვის, ვინც აქტიურ დღის რეჟიმს აერთიანებს ტექნოლოგიურ სიზუსტესთან. მისი ძირითადი მიზანია, დაგეხმაროთ მუდმივად კავშირზე იყოთ ...\n\nმეტის ნახვა\nმსგავსი პროდუქტები\n399 ₾\n\nთვეში: 11 ₾ -დან\n\nSamsung Galaxy Watch FE Pink Gold\nდამატება\n1199 ₾\n1299 ₾\n\nთვეში: 33 ₾ -დან\n\nSamsung L705 Galaxy Watch Ultra Titanium Grey\nდამატება\n1199 ₾\n1299 ₾\n\nთვეში: 33 ₾ -დან\n\nSamsung L705 Galaxy Watch Ultra Titanium Silver\nდამატება\n1199 ₾\n1299 ₾\n\nთვეში: 33 ₾ -დან\n\nSamsung L705 Galaxy Watch Ultra Titanium White\nდამატება\n549 ₾\n669 ₾\n\nთვეში: 15 ₾ -დან\n\nSamsung SM-R950 43mm Galaxy Watch 6 Classic Silver\nდამატება\n499 ₾\n\nთვეში: 13 ₾ -დან\n\nSamsung SM-R940 44mm Galaxy Watch 6 Silver\nდამატება\n569 ₾\n649 ₾\n\nთვეში: 15 ₾ -დან\n\nSamsung SM-R960 47mm Galaxy Watch 6 Classic Silver\nდამატება\n449 ₾\n499 ₾\n\nთვეში: 12 ₾ -დან\n\nSamsung L300 40mm Galaxy Watch 7 Green\nდამატება\n549 ₾\n\nთვეში: 15 ₾ -დან\n\nSamsung L310 44mm Galaxy Watch 7 Green\nდამატება\n549 ₾\n\nთვეში: 15 ₾ -დან\n\nSamsung L310 44mm Galaxy Watch 7 Silver\nდამატება\n139 ₾\n\nთვეში: 3 ₾ -დან\n\nSamsung Galaxy Fit 3 R390 Silver\nდამატება\nდამატებითი მახასიათებლები\nბრენდი\nბრენდი:\n\t\nSamsung\nტექნიკური მახასიათებლები\nკავშირის სტანდარტი:\n\t\nNo\n\n\nSIM ბარათი:\n\t\nNo\n\n\nკორპუსი:\n\t\nალუმინი\n\n\nIP დაცვა :\n\t\n5 ATM, IP68\n\n\nოპერაციული სისტემა:\n\t\nWear OS\n\n\nჩიპსეტი:\n\t\nExynos W1000\n\n\nNFC:\n\t\nYes\n\n\nBluetooth:\n\t\n5.3\n\n\nსენსორი:\n\t\nAccelerometer, Barometer, Light Sensor, Bioelectrical Impedance Analysis Sensor, Electrical Heart Sensor, Gyro Sensor, Geomagnetic Sensor, Optical Heart Rate Sensor, Infrared Temperature Sensor\n\n\nსპიკერი:\n\t\nYes\n\n\nქართული ენის მხარდაჭერა:\n\t\nYes\n\n\nგადახდის ფუნქცია (Pay):\n\t\nYes\n\n\nკამერა:\n\t\nNo\nეკრანი\nეკრანის ზომა:\n\t\n40 mm\n\n\nეკრანის ტიპი:\n\t\nSuper Amoled\n\n\nPPI:\n\t\n330 ppi\n\n\nრეზოლუცია:\n\t\n432 x 432 pixels\n\n\nეკრანის სიკაშკაშე:\n\t\n3000 nits\n\n\nAlways on Display:\n\t\nYes\nდამატებითი მახასიათებლები\nWi-Fi:\n\t\nYes\n\n\nGPS:\n\t\nYes\nმეხსიერება\nშიდა მეხსიერება:\n\t\n32 GB\n\n\nოპერატიული მეხსიერება:\n\t\n2 GB\nთავსებადობა\nთავსებადობა (Android; iOS):\n\t\nAndroid\nელემენტი\nელემენტი:\n\t\n300 mAh\n\n\nელემენტი დამუხტვის სიჩქარე:\n\t\n15 W\n\n\nელემენტის ტიპი:\n\t\nLi - Ion\n\n\nWireless დამუხტვა:\n\t\nYes\n\n\nსამუშაო დრო:\n\t\nUp To 40 hrs\nზომა/წონა\nწონა:\n\t\n28.7 g\nმეტის ნახვა\nგაეცანი საგარანტიო პირობებს\nსაგარანტიო პირობები\nფილიალები\nმარაგშია\nშეკვეთიდან 2-5 დღეში\nზუმერის წერეთლის ფილიალი\n\nთბილისი - წერეთლის გამზირი, N1.\n\nმარაგშია\n+995 591 967 601\nორშ-შაბ: 10:00:00 - 20:00:00\nკვირა: 10:00:00 - 19:00:00\nზუმერის პეკინის ფილიალი\n\nთბილისი - კ.გამსახურდიას (პეკინის) გამზირი N14ა\n\nმარაგშია\n+995 591 967 671\nორშ-შაბ: 10:00:00 - 21:00:00\nკვირა: 10:00:00 - 20:00:00\nზუმერის \"თბილისი ცენტრალის\" ფილიალი\n\nთბილისი - \"თბილისი ცენტრალი\"- lll სართული\n\nმარაგშია\n+995 599 862 449\nორშ-შაბ: 10:00:00 - 20:00:00\nკვირა: 10:00:00 - 19:00:00\nზუმერის City Mall საბურთალო-ს ფილიალი\n\nთბილისი - \"სითი მოლი\" - პეტრე ქავთარაძის N1\n\nმარაგშია\n+995 591 971 962\nორშ-შაბ: 10:00:00 - 22:00:00\nკვირა: 10:00:00 - 22:00:00\nზუმერის თბილისი მოლის ფილიალი\n\nთბილისი - „თბილისი მოლი\" - I სართული. აღმაშენებლის ხეივანი მე-16 კმ\n\nმარაგშია\n+995 591 967 608\nორშ-შაბ: 10:00:00 - 22:00:00\nკვირა: 10:00:00 - 22:00:00\nზუმერის \"გლდანი მოლის\" ფილიალი\n\nთბილისი - \"გლდანი მოლი\" - I სართული, M-ახმეტელის მიმდებარე\n\nმარაგშია\n+995 591 967 673\nორშ-შაბ: 10:00:00 - 21:00:00\nკვირა: 10:00:00 - 21:00:00\nზუმერის ისთ ფოინთის ფილიალი\n\nთბილისი - \"ისთ ფოინთი\" - ალ. თვალჭრელიძე N2\n\nმარაგშია\n+995 591 340 476\nორშ-შაბ: 10:00:00 - 22:00:00\nკვირა: 10:00:00 - 22:00:00\nზუმერი რუსთავი მოლის ფილიალი\n\nრუსთავი - შარტავას და ლომოურის კვეთა\n\nმარაგშია\n+995 591 441 082\nორშ-შაბ: 10:00:00 - 22:00:00\nკვირა: 10:00:00 - 22:00:00\nბათუმი ჭავჭავაძის ფილიალი\n\nბათუმი - ბათუმი, ჭავჭავაძის N21\n\nმარაგშია\n+995 591 967 606\nორშ-შაბ: 10:00:00 - 20:00:00\nკვირა: 10:00:00 - 19:00:00\nბათუმის \"Black Sea Mall\"-ის ფილიალი\n\nბათუმი - \"Black Sea Mall\" - ტბელ აბუსერიძის N22\n\nმარაგშია\n+995 591 310 257\nორშ-შაბ: 10:00:00 - 21:00:00\nკვირა: 10:00:00 - 21:00:00\nბათუმის გრანდ მოლის ფილიალი\n\nბათუმი - \"გრანდ მოლი\" - შერიფ ხიმშიაშვილის 29\n\nმარაგშია\n+995 591 022 872\nორშ-შაბ: 10:00:00 - 22:00:00\nკვირა: 10:00:00 - 22:00:00\nქუთაისის ფილიალი\n\nქუთაისი - თამარ მეფის ქ. N3 , ქუთაისის ცენტრალური მოედანი\n\nმარაგშია\n+955 591 967 605\nორშ-შაბ: 10:00:00 - 20:00:00\nკვირა: 10:00:00 - 19:00:00\nქუთაისი ვესთ მოლი\n\nქუთაისი - \"ვესთ მოლი\" - შარტავას N2\n\nმარაგშია\n+995 595 306 765\nორშ-შაბ: 10:00:00 - 22:00:00\nკვირა: 10:00:00 - 22:00:00\nზუგდიდი მოლის ფილიალი\n\nზუგდიდი - ზუგდიდი მოლი, კოსტავას ქუჩა №28\n\nმარაგშია\n+995 591 676 489\nორშ-შაბ: 10:00:00 - 22:00:00\nკვირა: 10:00:00 - 22:00:00\nგორი მოლის ფილიალი\n\nგორი - გორი, ცხინვალის გზატკეცილი 14-14ამ, გორი მოლი\n\nმარაგშია\n+995 591 198 248\nორშ-შაბ: 10:00:00 - 22:00:00\nკვირა: 10:00:00 - 22:00:00\nახალციხის ფილიალი\n\nახალციხე - ახალციხე, თამარ მეფის ქ. N9\n\nმარაგშია\n+995 598 088 659\nორშ-შაბ: 10:00:00 - 19:00:00\nკვირა: 10:00:00 - 19:00:00\nთელავი მოლის ფილიალი\n\nთელავი - \"თელავი მოლი\" - ალაზნის ქ.N77\n\nმარაგშია\n+995 595 069 853\nორშ-შაბ: 10:00:00 - 20:00:00\nკვირა: 10:00:00 - 19:00:00\nზუმერის საბითუმო საწყობი\n\nთბილისი - აკაკი წერეთლის გამზირი 1, საბითუმო საწყობი, -1 სართული\n\nმარაგშია\n+995 (32) 2 60 30 60\nორშ-შაბ: 10:00:00 - 19:00:00\nკვირა: 10:00:00 - 19:00:00\nმეტის ნახვა\n449 ₾\n499 ₾\n\nთვეში: 12.5 ₾ -დან\n\nმარაგი ფილიალებში\nფასის დაზღვევა\nფასის კონტროლი\nფასის დაჯავშნა\nყიდვა\nშედარება\nდამატება\nნავიგაცია\n\nპერსონალურ მონაცემთა დაცვის პოლიტიკა\n\nჩვენ შესახებ\n\nწესები და პირობები\n\nმიწოდების სერვისი\n\nკარიერა\n\nგადახდები\n\nSetanta Sports\n\nგადახდის მეთოდები\n\nგარანტია\n\nგანვადება\n\nნივთის დაბრუნება\n\nნივთის ონლაინ ყიდვის ინსტრუქცია\n\nგამოგვყევი\n\nFacebook\n\nYoutube\n\nInstagram\n\nTik Tok\n\nკონტაქტი\n\nInfo@zoommer.ge\n\n+995 (32) 2 60 30 60 / *7007\n\nფილიალები\n\nკორპორატიული გაყიდვები\n\nZoommer App\n\nCopyright © 2023 Zoommer.ge. All rights reserved.\n\nCookie პოლიტიკა\n\nსაიტით სარგებლობის გაგრძელებით, შენ ეთანხმები Cookie ჩანაწერების გამოყენებას. მეტი ინფორმაცისათვის იხილეთ კონფიდენციალურობის პოლიტიკა\n\nგასაგებია",
    "specs": {
      "ბრენდი:": "Samsung",
      "კავშირის სტანდარტი:": "No",
      "SIM ბარათი:": "No",
      "კორპუსი:": "ალუმინი",
      "IP დაცვა :": "5 ATM, IP68",
      "ოპერაციული სისტემა:": "Wear OS",
      "ჩიპსეტი:": "Exynos W1000",
      "NFC:": "Yes",
      "Bluetooth:": "5.3",
      "სენსორი:": "Accelerometer, Barometer, Light Sensor, Bioelectrical Impedance Analysis Sensor, Electrical Heart Sensor, Gyro Sensor, Geomagnetic Sensor, Optical Heart Rate Sensor, Infrared Temperature Sensor",
      "სპიკერი:": "Yes",
      "ქართული ენის მხარდაჭერა:": "Yes",
      "გადახდის ფუნქცია (Pay):": "Yes",
      "კამერა:": "No",
      "ეკრანის ზომა:": "40 mm",
      "ეკრანის ტიპი:": "Super Amoled",
      "PPI:": "330 ppi",
      "რეზოლუცია:": "432 x 432 pixels",
      "ეკრანის სიკაშკაშე:": "3000 nits",
      "Always on Display:": "Yes",
      "Wi-Fi:": "Yes",
      "GPS:": "Yes",
      "შიდა მეხსიერება:": "32 GB",
      "ოპერატიული მეხსიერება:": "2 GB",
      "თავსებადობა (Android; iOS):": "Android",
      "ელემენტი:": "300 mAh",
      "ელემენტი დამუხტვის სიჩქარე:": "15 W",
      "ელემენტის ტიპი:": "Li - Ion",
      "Wireless დამუხტვა:": "Yes",
      "სამუშაო დრო:": "Up To 40 hrs",
      "წონა:": "28.7 g"
    }
  },
  {
    "category": "Galaxy Watch",
    "title": "Samsung SM-R960 47mm Galaxy Watch 6 Classic Silver",
    "price": 569.0,
    "link": "https://zoommer.ge/smart-saatebi/samsung-sm-r960-47mm-galaxy-watch-6-classic-silver-p36901",
    "image": "/_next/image?url=https%3A%2F%2Fs3.zoommer.ge%2Fzoommer-images%2Fthumbs%2F0196205_samsung-sm-r960-47mm-galaxy-watch-6-classic-silver_550.jpeg&w=384&q=50",
    "product_title_detail": "Samsung SM-R960 47mm Galaxy Watch 6 Classic Silver",
    "description": "*7007 / +995 (32) 2 60 30 60\nსავაჭრო პოლიტიკა\nგანვადება\nკარიერა\nTrade In\nფილიალები\nნავიგაცია\nკალათა\nშესვლა\n%\nმთავარი\nსმარტ საათები\nSamsung\n#ZOOM-030986\nSamsung SM-R960 47mm Galaxy Watch 6 Classic Silver\nეკრანის ზომა\n47 mm\nრეზოლუცია\n480 x 480 pixels\nსამუშაო დრო\nUp To 40 hrs\nეკრანის ტიპი\nSuper Amoled\nშიდა მეხსიერება\n16 GB\nBluetooth\n5.3\nოპერატიული მეხსიერება\n2 GB\nელემენტი\n425 mAh\nფერი: Silver\nერთად იაფია\nდაამატე ნივთი\nSamsung SM-R960 47mm Galaxy Watch 6 Classic Silver\n569 ₾\nGlass Pro+ Full Screen Film Samsung SM-R960 Watch 6 Classic 47MM Black\n19 ₾\nSamsung Travel Adapter 25W EP-T2510 White\n52.25 ₾\n55 ₾\nჯამური ფასი (2)\n640.25 ₾\n643 ₾\nყიდვა\nაქსესუარები\nაღწერა\nმსგავსი\nმახასიათებლები\nფილიალები\nაქსესუარები\nაღწერა\nმსგავსი\nმახასიათებლები\nფილიალები\n49 ₾\n\nთვეში: 1 ₾ -დან\n\nXiaomi Redmi Buds 6 Lite Blue\nდამატება\n199 ₾\n\nთვეში: 5 ₾ -დან\n\nOnePlus Nord Buds 3 Pro Green\nდამატება\n119 ₾\n\nთვეში: 3 ₾ -დან\n\nNothing CMF Buds Pro Dark Grey\nდამატება\n149 ₾\n\nთვეში: 4 ₾ -დან\n\nRealme Buds Air 6 Silver\nდამატება\n129 ₾\n\nთვეში: 3 ₾ -დან\n\nNothing Buds CMF Neckband Pro Light Grey\nდამატება\n59 ₾\n\nთვეში: 1 ₾ -დან\n\nRealme Buds T01 Black\nდამატება\n139 ₾\n\nთვეში: 3 ₾ -დან\n\nNothing CMF Buds Pro 2 Blue\nდამატება\n299 ₾\n\nთვეში: 8 ₾ -დან\n\nRealme Buds Air 7 Pro Green\nდამატება\n299 ₾\n\nთვეში: 8 ₾ -დან\n\nRealme Buds Air 7 Pro Grey\nდამატება\n299 ₾\n\nთვეში: 8 ₾ -დან\n\nRealme Buds Air 7 Pro Red\nდამატება\n299 ₾\n\nთვეში: 8 ₾ -დან\n\nRealme Buds Air 7 Pro White\nდამატება\nპროდუქტის შესახებ\n\nSamsung SM-R960 47mm Galaxy Watch 6 Classic Silver - ფლაგმანური სმარტ საათი, შექმნილი მათთვის, ვინც აქტიურ დღის რეჟიმს აერთიანებს ტექნოლოგიურ სიზუსტესთან. მისი ძირითადი მიზანია, დაგეხმაროთ მუდმივად კა...\n\nმეტის ნახვა\nმსგავსი პროდუქტები\n399 ₾\n\nთვეში: 11 ₾ -დან\n\nSamsung Galaxy Watch FE Pink Gold\nდამატება\n1199 ₾\n1299 ₾\n\nთვეში: 33 ₾ -დან\n\nSamsung L705 Galaxy Watch Ultra Titanium Grey\nდამატება\n1199 ₾\n1299 ₾\n\nთვეში: 33 ₾ -დან\n\nSamsung L705 Galaxy Watch Ultra Titanium Silver\nდამატება\n1199 ₾\n1299 ₾\n\nთვეში: 33 ₾ -დან\n\nSamsung L705 Galaxy Watch Ultra Titanium White\nდამატება\n549 ₾\n669 ₾\n\nთვეში: 15 ₾ -დან\n\nSamsung SM-R950 43mm Galaxy Watch 6 Classic Silver\nდამატება\n499 ₾\n\nთვეში: 13 ₾ -დან\n\nSamsung SM-R940 44mm Galaxy Watch 6 Silver\nდამატება\n449 ₾\n499 ₾\n\nთვეში: 12 ₾ -დან\n\nSamsung L300 40mm Galaxy Watch 7 Cream\nდამატება\n449 ₾\n499 ₾\n\nთვეში: 12 ₾ -დან\n\nSamsung L300 40mm Galaxy Watch 7 Green\nდამატება\n549 ₾\n\nთვეში: 15 ₾ -დან\n\nSamsung L310 44mm Galaxy Watch 7 Green\nდამატება\n549 ₾\n\nთვეში: 15 ₾ -დან\n\nSamsung L310 44mm Galaxy Watch 7 Silver\nდამატება\n139 ₾\n\nთვეში: 3 ₾ -დან\n\nSamsung Galaxy Fit 3 R390 Silver\nდამატება\nდამატებითი მახასიათებლები\nბრენდი\nბრენდი:\n\t\nSamsung\nტექნიკური მახასიათებლები\nკავშირის სტანდარტი:\n\t\nNo\n\n\nSIM ბარათი:\n\t\nNo\n\n\nკორპუსი:\n\t\nუჟანგავი ფოლადი\n\n\nIP დაცვა :\n\t\n5 ATM, IP68\n\n\nოპერაციული სისტემა:\n\t\nWear OS\n\n\nჩიპსეტი:\n\t\nExynos W930\n\n\nNFC:\n\t\nYes\n\n\nBluetooth:\n\t\n5.3\n\n\nსენსორი:\n\t\nAccelerometer, Barometer, Light Sensor, Bioelectrical Impedance Analysis Sensor, Electrical Heart Sensor, Gyro Sensor, Geomagnetic Sensor, Optical Heart Rate Sensor, Infrared Temperature Sensor, Hall Sensor\n\n\nსპიკერი:\n\t\nYes\n\n\nქართული ენის მხარდაჭერა:\n\t\nYes\n\n\nგადახდის ფუნქცია (Pay):\n\t\nYes\n\n\nკამერა:\n\t\nNo\nეკრანი\nეკრანის ზომა:\n\t\n47 mm\n\n\nეკრანის ტიპი:\n\t\nSuper Amoled\n\n\nPPI:\n\t\n453 ppi\n\n\nრეზოლუცია:\n\t\n480 x 480 pixels\n\n\nეკრანის სიკაშკაშე:\n\t\n2000 nits\n\n\nAlways on Display:\n\t\nYes\nდამატებითი მახასიათებლები\nWi-Fi:\n\t\nYes\n\n\nGPS:\n\t\nYes\nმეხსიერება\nშიდა მეხსიერება:\n\t\n16 GB\n\n\nოპერატიული მეხსიერება:\n\t\n2 GB\nთავსებადობა\nთავსებადობა (Android; iOS):\n\t\nAndroid\nელემენტი\nელემენტი:\n\t\n425 mAh\n\n\nელემენტი დამუხტვის სიჩქარე:\n\t\n10 W\n\n\nელემენტის ტიპი:\n\t\nLi - Ion\n\n\nWireless დამუხტვა:\n\t\nYes\n\n\nსამუშაო დრო:\n\t\nUp To 40 hrs\nზომა/წონა\nწონა:\n\t\n59.0 g\nფერი\nფერი:\n\t\nSilver\nმეტის ნახვა\nგაეცანი საგარანტიო პირობებს\nსაგარანტიო პირობები\nგაეცანი პროდუქტის სახელმძღვანელოს\nპროდუქტის სახელმძღვანელო\nგაეცანი სერტიფიკატს\nსერტიფიკატი\nფილიალები\nმარაგშია\nშეკვეთიდან 2-5 დღეში\nბათუმი ჭავჭავაძის ფილიალი\n\nბათუმი - ბათუმი, ჭავჭავაძის N21\n\nმარაგშია\n+995 591 967 606\nორშ-შაბ: 10:00:00 - 20:00:00\nკვირა: 10:00:00 - 19:00:00\n569 ₾\n649 ₾\n\nთვეში: 15.8 ₾ -დან\n\nმარაგი ფილიალებში\nფასის დაზღვევა\nფასის კონტროლი\nფასის დაჯავშნა\nყიდვა\nშედარება\nდამატება\nნავიგაცია\n\nპერსონალურ მონაცემთა დაცვის პოლიტიკა\n\nჩვენ შესახებ\n\nწესები და პირობები\n\nმიწოდების სერვისი\n\nკარიერა\n\nგადახდები\n\nSetanta Sports\n\nგადახდის მეთოდები\n\nგარანტია\n\nგანვადება\n\nნივთის დაბრუნება\n\nნივთის ონლაინ ყიდვის ინსტრუქცია\n\nგამოგვყევი\n\nFacebook\n\nYoutube\n\nInstagram\n\nTik Tok\n\nკონტაქტი\n\nInfo@zoommer.ge\n\n+995 (32) 2 60 30 60 / *7007\n\nფილიალები\n\nკორპორატიული გაყიდვები\n\nZoommer App\n\nCopyright © 2023 Zoommer.ge. All rights reserved.\n\nCookie პოლიტიკა\n\nსაიტით სარგებლობის გაგრძელებით, შენ ეთანხმები Cookie ჩანაწერების გამოყენებას. მეტი ინფორმაცისათვის იხილეთ კონფიდენციალურობის პოლიტიკა\n\nგასაგებია",
    "specs": {
      "ბრენდი:": "Samsung",
      "კავშირის სტანდარტი:": "No",
      "SIM ბარათი:": "No",
      "კორპუსი:": "უჟანგავი ფოლადი",
      "IP დაცვა :": "5 ATM, IP68",
      "ოპერაციული სისტემა:": "Wear OS",
      "ჩიპსეტი:": "Exynos W930",
      "NFC:": "Yes",
      "Bluetooth:": "5.3",
      "სენსორი:": "Accelerometer, Barometer, Light Sensor, Bioelectrical Impedance Analysis Sensor, Electrical Heart Sensor, Gyro Sensor, Geomagnetic Sensor, Optical Heart Rate Sensor, Infrared Temperature Sensor, Hall Sensor",
      "სპიკერი:": "Yes",
      "ქართული ენის მხარდაჭერა:": "Yes",
      "გადახდის ფუნქცია (Pay):": "Yes",
      "კამერა:": "No",
      "ეკრანის ზომა:": "47 mm",
      "ეკრანის ტიპი:": "Super Amoled",
      "PPI:": "453 ppi",
      "რეზოლუცია:": "480 x 480 pixels",
      "ეკრანის სიკაშკაშე:": "2000 nits",
      "Always on Display:": "Yes",
      "Wi-Fi:": "Yes",
      "GPS:": "Yes",
      "შიდა მეხსიერება:": "16 GB",
      "ოპერატიული მეხსიერება:": "2 GB",
      "თავსებადობა (Android; iOS):": "Android",
      "ელემენტი:": "425 mAh",
      "ელემენტი დამუხტვის სიჩქარე:": "10 W",
      "ელემენტის ტიპი:": "Li - Ion",
      "Wireless დამუხტვა:": "Yes",
      "სამუშაო დრო:": "Up To 40 hrs",
      "წონა:": "59.0 g",
      "ფერი:": "Silver"
    }
  },
  {
    "category": "Galaxy Watch",
    "title": "Samsung SM-R940 44mm Galaxy Watch 6 Silver",
    "price": 499.0,
    "link": "https://zoommer.ge/smart-saatebi/samsung-sm-r940-44mm-galaxy-watch-6-silver-p36895",
    "image": "/_next/image?url=https%3A%2F%2Fs3.zoommer.ge%2Fzoommer-images%2Fthumbs%2F0196234_samsung-sm-r940-44mm-galaxy-watch-6-silver_550.jpeg&w=384&q=50",
    "product_title_detail": "Samsung SM-R940 44mm Galaxy Watch 6 Silver",
    "description": "*7007 / +995 (32) 2 60 30 60\nფილიალები\nნავიგაცია\nკალათა\nშესვლა\n%\nმთავარი\nსმარტ საათები\nSamsung\n#ZOOM-030985\nSamsung SM-R940 44mm Galaxy Watch 6 Silver\nეკრანის ზომა\n44 mm\nრეზოლუცია\n480 x 480 pixels\nსამუშაო დრო\nUp To 40 hrs\nეკრანის ტიპი\nSuper Amoled\nშიდა მეხსიერება\n16 GB\nBluetooth\n5.3\nოპერატიული მეხსიერება\n2 GB\nელემენტი\n425 mAh\nფერი: Silver\nერთად იაფია\nდაამატე ნივთი\nSamsung SM-R940 44mm Galaxy Watch 6 Silver\n499 ₾\nSamsung Travel Adapter 25W EP-T2510 White\n52.25 ₾\n55 ₾\nჯამური ფასი (1)\n551.25 ₾\n554 ₾\nყიდვა\nაქსესუარები\nაღწერა\nმსგავსი\nმახასიათებლები\nფილიალები\nაქსესუარები\nაღწერა\nმსგავსი\nმახასიათებლები\nფილიალები\n49 ₾\n\nთვეში: 1 ₾ -დან\n\nXiaomi Redmi Buds 6 Lite Blue\nდამატება\n199 ₾\n\nთვეში: 5 ₾ -დან\n\nOnePlus Nord Buds 3 Pro Green\nდამატება\n119 ₾\n\nთვეში: 3 ₾ -დან\n\nNothing CMF Buds Pro Dark Grey\nდამატება\n149 ₾\n\nთვეში: 4 ₾ -დან\n\nRealme Buds Air 6 Silver\nდამატება\n129 ₾\n\nთვეში: 3 ₾ -დან\n\nNothing Buds CMF Neckband Pro Light Grey\nდამატება\n59 ₾\n\nთვეში: 1 ₾ -დან\n\nRealme Buds T01 Black\nდამატება\n139 ₾\n\nთვეში: 3 ₾ -დან\n\nNothing CMF Buds Pro 2 Blue\nდამატება\n299 ₾\n\nთვეში: 8 ₾ -დან\n\nRealme Buds Air 7 Pro Green\nდამატება\n299 ₾\n\nთვეში: 8 ₾ -დან\n\nRealme Buds Air 7 Pro Grey\nდამატება\n299 ₾\n\nთვეში: 8 ₾ -დან\n\nRealme Buds Air 7 Pro Red\nდამატება\n299 ₾\n\nთვეში: 8 ₾ -დან\n\nRealme Buds Air 7 Pro White\nდამატება\nპროდუქტის შესახებ\n\nSamsung SM-R940 44mm Galaxy Watch 6 Silver - ფლაგმანური სმარტ საათი, შექმნილი მათთვის, ვინც აქტიურ დღის რეჟიმს აერთიანებს ტექნოლოგიურ სიზუსტესთან. მისი ძირითადი მიზანია, დაგეხმაროთ მუდმივად კავშირზე ი...\n\nმეტის ნახვა\nმსგავსი პროდუქტები\n399 ₾\n\nთვეში: 11 ₾ -დან\n\nSamsung Galaxy Watch FE Pink Gold\nდამატება\n1199 ₾\n1299 ₾\n\nთვეში: 33 ₾ -დან\n\nSamsung L705 Galaxy Watch Ultra Titanium Grey\nდამატება\n1199 ₾\n1299 ₾\n\nთვეში: 33 ₾ -დან\n\nSamsung L705 Galaxy Watch Ultra Titanium Silver\nდამატება\n1199 ₾\n1299 ₾\n\nთვეში: 33 ₾ -დან\n\nSamsung L705 Galaxy Watch Ultra Titanium White\nდამატება\n549 ₾\n669 ₾\n\nთვეში: 15 ₾ -დან\n\nSamsung SM-R950 43mm Galaxy Watch 6 Classic Silver\nდამატება\n569 ₾\n649 ₾\n\nთვეში: 15 ₾ -დან\n\nSamsung SM-R960 47mm Galaxy Watch 6 Classic Silver\nდამატება\n449 ₾\n499 ₾\n\nთვეში: 12 ₾ -დან\n\nSamsung L300 40mm Galaxy Watch 7 Cream\nდამატება\n449 ₾\n499 ₾\n\nთვეში: 12 ₾ -დან\n\nSamsung L300 40mm Galaxy Watch 7 Green\nდამატება\n549 ₾\n\nთვეში: 15 ₾ -დან\n\nSamsung L310 44mm Galaxy Watch 7 Green\nდამატება\n549 ₾\n\nთვეში: 15 ₾ -დან\n\nSamsung L310 44mm Galaxy Watch 7 Silver\nდამატება\n139 ₾\n\nთვეში: 3 ₾ -დან\n\nSamsung Galaxy Fit 3 R390 Silver\nდამატება\nდამატებითი მახასიათებლები\nბრენდი\nბრენდი:\n\t\nSamsung\nტექნიკური მახასიათებლები\nკავშირის სტანდარტი:\n\t\nNo\n\n\nSIM ბარათი:\n\t\nNo\n\n\nკორპუსი:\n\t\nალუმინი\n\n\nIP დაცვა :\n\t\n5 ATM, IP68\n\n\nოპერაციული სისტემა:\n\t\nWear OS\n\n\nჩიპსეტი:\n\t\nExynos W930\n\n\nNFC:\n\t\nYes\n\n\nBluetooth:\n\t\n5.3\n\n\nსენსორი:\n\t\nAccelerometer, Barometer, Light Sensor, Bioelectrical Impedance Analysis Sensor, Electrical Heart Sensor, Gyro Sensor, Geomagnetic Sensor, Optical Heart Rate Sensor, Infrared Temperature Sensor\n\n\nსპიკერი:\n\t\nYes\n\n\nქართული ენის მხარდაჭერა:\n\t\nYes\n\n\nგადახდის ფუნქცია (Pay):\n\t\nYes\n\n\nკამერა:\n\t\nNo\nეკრანი\nეკრანის ზომა:\n\t\n44 mm\n\n\nეკრანის ტიპი:\n\t\nSuper Amoled\n\n\nPPI:\n\t\n453 ppi\n\n\nრეზოლუცია:\n\t\n480 x 480 pixels\n\n\nეკრანის სიკაშკაშე:\n\t\n2000 nits\n\n\nAlways on Display:\n\t\nYes\nდამატებითი მახასიათებლები\nWi-Fi:\n\t\nYes\n\n\nGPS:\n\t\nYes\nმეხსიერება\nშიდა მეხსიერება:\n\t\n16 GB\n\n\nოპერატიული მეხსიერება:\n\t\n2 GB\nთავსებადობა\nთავსებადობა (Android; iOS):\n\t\nAndroid\nელემენტი\nელემენტი:\n\t\n425 mAh\n\n\nელემენტი დამუხტვის სიჩქარე:\n\t\n10 W\n\n\nელემენტის ტიპი:\n\t\nLi - Ion\n\n\nWireless დამუხტვა:\n\t\nYes\n\n\nსამუშაო დრო:\n\t\nUp To 40 hrs\nზომა/წონა\nწონა:\n\t\n33.3 g\nფერი\nფერი:\n\t\nSilver\nმეტის ნახვა\nგაეცანი საგარანტიო პირობებს\nსაგარანტიო პირობები\nგაეცანი პროდუქტის სახელმძღვანელოს\nპროდუქტის სახელმძღვანელო\nგაეცანი სერტიფიკატს\nსერტიფიკატი\nფილიალები\nმარაგშია\nშეკვეთიდან 2-5 დღეში\nბათუმი ჭავჭავაძის ფილიალი\n\nბათუმი - ბათუმი, ჭავჭავაძის N21\n\nმარაგშია\n+995 591 967 606\nორშ-შაბ: 10:00:00 - 20:00:00\nკვირა: 10:00:00 - 19:00:00\n499 ₾\n\nთვეში: 13.9 ₾ -დან\n\nმარაგი ფილიალებში\nფასის დაზღვევა\nფასის კონტროლი\nფასის დაჯავშნა\nყიდვა\nშედარება\nდამატება\nნავიგაცია\nგადახდები\nგამოგვყევი\n\nFacebook\n\nYoutube\n\nInstagram\n\nTik Tok\n\nკონტაქტი\n\nInfo@zoommer.ge\n\n+995 (32) 2 60 30 60 / *7007\n\nფილიალები\n\nკორპორატიული გაყიდვები\n\nZoommer App\n\nCopyright © 2023 Zoommer.ge. All rights reserved.\n\nCookie პოლიტიკა\n\nსაიტით სარგებლობის გაგრძელებით, შენ ეთანხმები Cookie ჩანაწერების გამოყენებას. მეტი ინფორმაცისათვის იხილეთ კონფიდენციალურობის პოლიტიკა\n\nგასაგებია",
    "specs": {
      "ბრენდი:": "Samsung",
      "კავშირის სტანდარტი:": "No",
      "SIM ბარათი:": "No",
      "კორპუსი:": "ალუმინი",
      "IP დაცვა :": "5 ATM, IP68",
      "ოპერაციული სისტემა:": "Wear OS",
      "ჩიპსეტი:": "Exynos W930",
      "NFC:": "Yes",
      "Bluetooth:": "5.3",
      "სენსორი:": "Accelerometer, Barometer, Light Sensor, Bioelectrical Impedance Analysis Sensor, Electrical Heart Sensor, Gyro Sensor, Geomagnetic Sensor, Optical Heart Rate Sensor, Infrared Temperature Sensor",
      "სპიკერი:": "Yes",
      "ქართული ენის მხარდაჭერა:": "Yes",
      "გადახდის ფუნქცია (Pay):": "Yes",
      "კამერა:": "No",
      "ეკრანის ზომა:": "44 mm",
      "ეკრანის ტიპი:": "Super Amoled",
      "PPI:": "453 ppi",
      "რეზოლუცია:": "480 x 480 pixels",
      "ეკრანის სიკაშკაშე:": "2000 nits",
      "Always on Display:": "Yes",
      "Wi-Fi:": "Yes",
      "GPS:": "Yes",
      "შიდა მეხსიერება:": "16 GB",
      "ოპერატიული მეხსიერება:": "2 GB",
      "თავსებადობა (Android; iOS):": "Android",
      "ელემენტი:": "425 mAh",
      "ელემენტი დამუხტვის სიჩქარე:": "10 W",
      "ელემენტის ტიპი:": "Li - Ion",
      "Wireless დამუხტვა:": "Yes",
      "სამუშაო დრო:": "Up To 40 hrs",
      "წონა:": "33.3 g",
      "ფერი:": "Silver"
    }
  },
  {
    "category": "Galaxy Watch",
    "title": "Samsung SM-R950 43mm Galaxy Watch 6 Classic Silver",
    "price": 549.0,
    "link": "https://zoommer.ge/smart-saatebi/samsung-sm-r950-43mm-galaxy-watch-6-classic-silver-p36888",
    "image": "/_next/image?url=https%3A%2F%2Fs3.zoommer.ge%2Fzoommer-images%2Fthumbs%2F0196198_samsung-sm-r950-43mm-galaxy-watch-6-classic-silver_550.jpeg&w=384&q=50",
    "product_title_detail": "Samsung SM-R950 43mm Galaxy Watch 6 Classic Silver",
    "description": "*7007 / +995 (32) 2 60 30 60\nსავაჭრო პოლიტიკა\nგანვადება\nკარიერა\nTrade In\nფილიალები\nნავიგაცია\nკალათა\nშესვლა\n%\nმთავარი\nსმარტ საათები\nSamsung\n#ZOOM-030983\nSamsung SM-R950 43mm Galaxy Watch 6 Classic Silver\nეკრანის ზომა\n43 mm\nრეზოლუცია\n432 x 432 pixels\nსამუშაო დრო\nUp To 40 hrs\nეკრანის ტიპი\nSuper Amoled\nშიდა მეხსიერება\n16 GB\nBluetooth\n5.3\nოპერატიული მეხსიერება\n2 GB\nელემენტი\n300 mAh\nერთად იაფია\nდაამატე ნივთი\nSamsung SM-R950 43mm Galaxy Watch 6 Classic Silver\n549 ₾\nGlass Pro+ Full Screen Film Samsung SM-R950 Watch 6 Classic 43MM Black\n19 ₾\nSamsung Travel Adapter 25W EP-T2510 White\n52.25 ₾\n55 ₾\nჯამური ფასი (2)\n620.25 ₾\n623 ₾\nყიდვა\nაქსესუარები\nაღწერა\nმსგავსი\nმახასიათებლები\nფილიალები\nაქსესუარები\nაღწერა\nმსგავსი\nმახასიათებლები\nფილიალები\n49 ₾\n\nთვეში: 1 ₾ -დან\n\nXiaomi Redmi Buds 6 Lite Blue\nდამატება\n199 ₾\n\nთვეში: 5 ₾ -დან\n\nOnePlus Nord Buds 3 Pro Green\nდამატება\n119 ₾\n\nთვეში: 3 ₾ -დან\n\nNothing CMF Buds Pro Dark Grey\nდამატება\n149 ₾\n\nთვეში: 4 ₾ -დან\n\nRealme Buds Air 6 Silver\nდამატება\n129 ₾\n\nთვეში: 3 ₾ -დან\n\nNothing Buds CMF Neckband Pro Light Grey\nდამატება\n59 ₾\n\nთვეში: 1 ₾ -დან\n\nRealme Buds T01 Black\nდამატება\n139 ₾\n\nთვეში: 3 ₾ -დან\n\nNothing CMF Buds Pro 2 Blue\nდამატება\n299 ₾\n\nთვეში: 8 ₾ -დან\n\nRealme Buds Air 7 Pro Green\nდამატება\n299 ₾\n\nთვეში: 8 ₾ -დან\n\nRealme Buds Air 7 Pro Grey\nდამატება\n299 ₾\n\nთვეში: 8 ₾ -დან\n\nRealme Buds Air 7 Pro Red\nდამატება\n299 ₾\n\nთვეში: 8 ₾ -დან\n\nRealme Buds Air 7 Pro White\nდამატება\nპროდუქტის შესახებ\n\nSamsung SM-R950 43mm Galaxy Watch 6 Classic Silver - ფლაგმანური სმარტ საათი, შექმნილი მათთვის, ვინც აქტიურ დღის რეჟიმს აერთიანებს ტექნოლოგიურ სიზუსტესთან. მისი ძირითადი მიზანია, დაგეხმაროთ მუდმივად კა...\n\nმეტის ნახვა\nმსგავსი პროდუქტები\n399 ₾\n\nთვეში: 11 ₾ -დან\n\nSamsung Galaxy Watch FE Pink Gold\nდამატება\n1199 ₾\n1299 ₾\n\nთვეში: 33 ₾ -დან\n\nSamsung L705 Galaxy Watch Ultra Titanium Grey\nდამატება\n1199 ₾\n1299 ₾\n\nთვეში: 33 ₾ -დან\n\nSamsung L705 Galaxy Watch Ultra Titanium Silver\nდამატება\n1199 ₾\n1299 ₾\n\nთვეში: 33 ₾ -დან\n\nSamsung L705 Galaxy Watch Ultra Titanium White\nდამატება\n499 ₾\n\nთვეში: 13 ₾ -დან\n\nSamsung SM-R940 44mm Galaxy Watch 6 Silver\nდამატება\n569 ₾\n649 ₾\n\nთვეში: 15 ₾ -დან\n\nSamsung SM-R960 47mm Galaxy Watch 6 Classic Silver\nდამატება\n449 ₾\n499 ₾\n\nთვეში: 12 ₾ -დან\n\nSamsung L300 40mm Galaxy Watch 7 Cream\nდამატება\n449 ₾\n499 ₾\n\nთვეში: 12 ₾ -დან\n\nSamsung L300 40mm Galaxy Watch 7 Green\nდამატება\n549 ₾\n\nთვეში: 15 ₾ -დან\n\nSamsung L310 44mm Galaxy Watch 7 Green\nდამატება\n549 ₾\n\nთვეში: 15 ₾ -დან\n\nSamsung L310 44mm Galaxy Watch 7 Silver\nდამატება\n139 ₾\n\nთვეში: 3 ₾ -დან\n\nSamsung Galaxy Fit 3 R390 Silver\nდამატება\nდამატებითი მახასიათებლები\nბრენდი\nბრენდი:\n\t\nSamsung\nტექნიკური მახასიათებლები\nკავშირის სტანდარტი:\n\t\nNo\n\n\nSIM ბარათი:\n\t\nNo\n\n\nკორპუსი:\n\t\nუჟანგავი ფოლადი\n\n\nIP დაცვა :\n\t\n5 ATM, IP68\n\n\nოპერაციული სისტემა:\n\t\nWear OS\n\n\nჩიპსეტი:\n\t\nExynos W930\n\n\nNFC:\n\t\nYes\n\n\nBluetooth:\n\t\n5.3\n\n\nსენსორი:\n\t\nAccelerometer, Barometer, Light Sensor, Bioelectrical Impedance Analysis Sensor, Electrical Heart Sensor, Gyro Sensor, Geomagnetic Sensor, Optical Heart Rate Sensor, Infrared Temperature Sensor, Hall Sensor\n\n\nსპიკერი:\n\t\nYes\n\n\nქართული ენის მხარდაჭერა:\n\t\nYes\n\n\nგადახდის ფუნქცია (Pay):\n\t\nYes\n\n\nკამერა:\n\t\nNo\nეკრანი\nეკრანის ზომა:\n\t\n43 mm\n\n\nეკრანის ტიპი:\n\t\nSuper Amoled\n\n\nPPI:\n\t\n453 ppi\n\n\nრეზოლუცია:\n\t\n432 x 432 pixels\n\n\nეკრანის სიკაშკაშე:\n\t\n2000 nits\n\n\nAlways on Display:\n\t\nYes\nდამატებითი მახასიათებლები\nWi-Fi:\n\t\nYes\n\n\nGPS:\n\t\nYes\nმეხსიერება\nშიდა მეხსიერება:\n\t\n16 GB\n\n\nოპერატიული მეხსიერება:\n\t\n2 GB\nთავსებადობა\nთავსებადობა (Android; iOS):\n\t\nAndroid\nელემენტი\nელემენტი:\n\t\n300 mAh\n\n\nელემენტი დამუხტვის სიჩქარე:\n\t\n10 W\n\n\nელემენტის ტიპი:\n\t\nLi - Ion\n\n\nWireless დამუხტვა:\n\t\nYes\n\n\nსამუშაო დრო:\n\t\nUp To 40 hrs\nზომა/წონა\nწონა:\n\t\n52.0 g\nფერი\nფერი:\n\t\nSilver\nმეტის ნახვა\nგაეცანი საგარანტიო პირობებს\nსაგარანტიო პირობები\nგაეცანი პროდუქტის სახელმძღვანელოს\nპროდუქტის სახელმძღვანელო\nგაეცანი სერტიფიკატს\nსერტიფიკატი\nფილიალები\nმარაგშია\nშეკვეთიდან 2-5 დღეში\nზუმერის City Mall საბურთალო-ს ფილიალი\n\nთბილისი - \"სითი მოლი\" - პეტრე ქავთარაძის N1\n\nმარაგშია\n+995 591 971 962\nორშ-შაბ: 10:00:00 - 22:00:00\nკვირა: 10:00:00 - 22:00:00\nზუმერის ისთ ფოინთის ფილიალი\n\nთბილისი - \"ისთ ფოინთი\" - ალ. თვალჭრელიძე N2\n\nმარაგშია\n+995 591 340 476\nორშ-შაბ: 10:00:00 - 22:00:00\nკვირა: 10:00:00 - 22:00:00\nბათუმი ჭავჭავაძის ფილიალი\n\nბათუმი - ბათუმი, ჭავჭავაძის N21\n\nმარაგშია\n+995 591 967 606\nორშ-შაბ: 10:00:00 - 20:00:00\nკვირა: 10:00:00 - 19:00:00\n549 ₾\n669 ₾\n\nთვეში: 15.3 ₾ -დან\n\nმარაგი ფილიალებში\nფასის დაზღვევა\nფასის კონტროლი\nფასის დაჯავშნა\nყიდვა\nშედარება\nდამატება\nნავიგაცია\n\nპერსონალურ მონაცემთა დაცვის პოლიტიკა\n\nჩვენ შესახებ\n\nწესები და პირობები\n\nმიწოდების სერვისი\n\nკარიერა\n\nგადახდები\n\nSetanta Sports\n\nგადახდის მეთოდები\n\nგარანტია\n\nგანვადება\n\nნივთის დაბრუნება\n\nნივთის ონლაინ ყიდვის ინსტრუქცია\n\nგამოგვყევი\n\nFacebook\n\nYoutube\n\nInstagram\n\nTik Tok\n\nკონტაქტი\n\nInfo@zoommer.ge\n\n+995 (32) 2 60 30 60 / *7007\n\nფილიალები\n\nკორპორატიული გაყიდვები\n\nZoommer App\n\nCopyright © 2023 Zoommer.ge. All rights reserved.\n\nCookie პოლიტიკა\n\nსაიტით სარგებლობის გაგრძელებით, შენ ეთანხმები Cookie ჩანაწერების გამოყენებას. მეტი ინფორმაცისათვის იხილეთ კონფიდენციალურობის პოლიტიკა\n\nგასაგებია",
    "specs": {
      "ბრენდი:": "Samsung",
      "კავშირის სტანდარტი:": "No",
      "SIM ბარათი:": "No",
      "კორპუსი:": "უჟანგავი ფოლადი",
      "IP დაცვა :": "5 ATM, IP68",
      "ოპერაციული სისტემა:": "Wear OS",
      "ჩიპსეტი:": "Exynos W930",
      "NFC:": "Yes",
      "Bluetooth:": "5.3",
      "სენსორი:": "Accelerometer, Barometer, Light Sensor, Bioelectrical Impedance Analysis Sensor, Electrical Heart Sensor, Gyro Sensor, Geomagnetic Sensor, Optical Heart Rate Sensor, Infrared Temperature Sensor, Hall Sensor",
      "სპიკერი:": "Yes",
      "ქართული ენის მხარდაჭერა:": "Yes",
      "გადახდის ფუნქცია (Pay):": "Yes",
      "კამერა:": "No",
      "ეკრანის ზომა:": "43 mm",
      "ეკრანის ტიპი:": "Super Amoled",
      "PPI:": "453 ppi",
      "რეზოლუცია:": "432 x 432 pixels",
      "ეკრანის სიკაშკაშე:": "2000 nits",
      "Always on Display:": "Yes",
      "Wi-Fi:": "Yes",
      "GPS:": "Yes",
      "შიდა მეხსიერება:": "16 GB",
      "ოპერატიული მეხსიერება:": "2 GB",
      "თავსებადობა (Android; iOS):": "Android",
      "ელემენტი:": "300 mAh",
      "ელემენტი დამუხტვის სიჩქარე:": "10 W",
      "ელემენტის ტიპი:": "Li - Ion",
      "Wireless დამუხტვა:": "Yes",
      "სამუშაო დრო:": "Up To 40 hrs",
      "წონა:": "52.0 g",
      "ფერი:": "Silver"
    }
  },
  {
    "category": "Galaxy Watch",
    "title": "Samsung Galaxy Fit 3 R390 Silver",
    "price": 139.0,
    "link": "https://zoommer.ge/smart-saatebi/samsung-galaxy-fit-3-r390-silver-p47147",
    "image": "/_next/image?url=https%3A%2F%2Fs3.zoommer.ge%2Fsite%2Fb54ebfac-2c71-484a-bcba-31e18b2be22f_Thumb.jpeg&w=384&q=50",
    "product_title_detail": "Samsung Galaxy Fit 3 R390 Silver",
    "description": "*7007 / +995 (32) 2 60 30 60\nსავაჭრო პოლიტიკა\nგანვადება\nკარიერა\nTrade In\nფილიალები\nნავიგაცია\nკალათა\nშესვლა\n%\nმთავარი\nსმარტ საათები\nSamsung\n#ZOOM-036343\nSamsung Galaxy Fit 3 R390 Silver\nეკრანის ზომა\n1.6 Inches\nრეზოლუცია\n256 x 402 pixels\nსამუშაო დრო\nUp To 13 Days\nეკრანის ტიპი\nAmoled\nშიდა მეხსიერება\n256 MB\nBluetooth\n5.3\nოპერატიული მეხსიერება\n16 MB\nელემენტი\n208 mAh\nერთად იაფია\nდაამატე ნივთი\nSamsung Galaxy Fit 3 R390 Silver\n139 ₾\nXiaomi Mi 20W charger Type-C BHR4927GL White\n33.25 ₾\n35 ₾\nჯამური ფასი (1)\n172.25 ₾\n174 ₾\nყიდვა\nაქსესუარები\nაღწერა\nმსგავსი\nმახასიათებლები\nფილიალები\nაქსესუარები\nაღწერა\nმსგავსი\nმახასიათებლები\nფილიალები\n49 ₾\n\nთვეში: 1 ₾ -დან\n\nXiaomi Redmi Buds 6 Lite Blue\nდამატება\n199 ₾\n\nთვეში: 5 ₾ -დან\n\nOnePlus Nord Buds 3 Pro Green\nდამატება\n119 ₾\n\nთვეში: 3 ₾ -დან\n\nNothing CMF Buds Pro Dark Grey\nდამატება\n149 ₾\n\nთვეში: 4 ₾ -დან\n\nRealme Buds Air 6 Silver\nდამატება\n129 ₾\n\nთვეში: 3 ₾ -დან\n\nNothing Buds CMF Neckband Pro Light Grey\nდამატება\n59 ₾\n\nთვეში: 1 ₾ -დან\n\nRealme Buds T01 Black\nდამატება\n139 ₾\n\nთვეში: 3 ₾ -დან\n\nNothing CMF Buds Pro 2 Blue\nდამატება\n299 ₾\n\nთვეში: 8 ₾ -დან\n\nRealme Buds Air 7 Pro Green\nდამატება\n299 ₾\n\nთვეში: 8 ₾ -დან\n\nRealme Buds Air 7 Pro Grey\nდამატება\n299 ₾\n\nთვეში: 8 ₾ -დან\n\nRealme Buds Air 7 Pro Red\nდამატება\n299 ₾\n\nთვეში: 8 ₾ -დან\n\nRealme Buds Air 7 Pro White\nდამატება\nპროდუქტის შესახებ\n\nSamsung Galaxy Fit 3 R390 Silver - თანამედროვე და მრავალფუნქციური ფიტნეს ტრეკერი მათთვის, ვინც აქტიურ და ჯანსაღ ცხოვრებას აფასებს. მოდელი იდეალურია როგორც სპორტული ვარჯიშისთვის, ისე ყოველდღიური მონაცე...\n\nმეტის ნახვა\nმსგავსი პროდუქტები\n399 ₾\n\nთვეში: 11 ₾ -დან\n\nSamsung Galaxy Watch FE Pink Gold\nდამატება\n1199 ₾\n1299 ₾\n\nთვეში: 33 ₾ -დან\n\nSamsung L705 Galaxy Watch Ultra Titanium Grey\nდამატება\n1199 ₾\n1299 ₾\n\nთვეში: 33 ₾ -დან\n\nSamsung L705 Galaxy Watch Ultra Titanium Silver\nდამატება\n1199 ₾\n1299 ₾\n\nთვეში: 33 ₾ -დან\n\nSamsung L705 Galaxy Watch Ultra Titanium White\nდამატება\n549 ₾\n669 ₾\n\nთვეში: 15 ₾ -დან\n\nSamsung SM-R950 43mm Galaxy Watch 6 Classic Silver\nდამატება\n499 ₾\n\nთვეში: 13 ₾ -დან\n\nSamsung SM-R940 44mm Galaxy Watch 6 Silver\nდამატება\n569 ₾\n649 ₾\n\nთვეში: 15 ₾ -დან\n\nSamsung SM-R960 47mm Galaxy Watch 6 Classic Silver\nდამატება\n449 ₾\n499 ₾\n\nთვეში: 12 ₾ -დან\n\nSamsung L300 40mm Galaxy Watch 7 Cream\nდამატება\n449 ₾\n499 ₾\n\nთვეში: 12 ₾ -დან\n\nSamsung L300 40mm Galaxy Watch 7 Green\nდამატება\n549 ₾\n\nთვეში: 15 ₾ -დან\n\nSamsung L310 44mm Galaxy Watch 7 Green\nდამატება\n549 ₾\n\nთვეში: 15 ₾ -დან\n\nSamsung L310 44mm Galaxy Watch 7 Silver\nდამატება\nდამატებითი მახასიათებლები\nბრენდი\nბრენდი:\n\t\nSamsung\nტექნიკური მახასიათებლები\nკავშირის სტანდარტი:\n\t\nNo\n\n\nSIM ბარათი:\n\t\nNo\n\n\nკორპუსი:\n\t\nალუმინი\n\n\nIP დაცვა :\n\t\nIP68\n\n\nოპერაციული სისტემა:\n\t\nFreeRTOS\n\n\nჩიპსეტი:\n\t\n-\n\n\nNFC:\n\t\n-\n\n\nBluetooth:\n\t\n5.3\n\n\nსენსორი:\n\t\nAccelerometer, Barometer, Light Sensor, Gyro Sensor, Optical Heart Rate Sensor\n\n\nსპიკერი:\n\t\n-\n\n\nქართული ენის მხარდაჭერა:\n\t\nYes\n\n\nგადახდის ფუნქცია (Pay):\n\t\nNo\n\n\nკამერა:\n\t\nNo\nეკრანი\nეკრანის ზომა:\n\t\n1.6 Inches\n\n\nეკრანის ტიპი:\n\t\nAmoled\n\n\nPPI:\n\t\n-\n\n\nრეზოლუცია:\n\t\n256 x 402 pixels\n\n\nეკრანის სიკაშკაშე:\n\t\n-\n\n\nAlways on Display:\n\t\nYes\nდამატებითი მახასიათებლები\nWi-Fi:\n\t\n-\n\n\nGPS:\n\t\nYes\nმეხსიერება\nშიდა მეხსიერება:\n\t\n256 MB\n\n\nოპერატიული მეხსიერება:\n\t\n16 MB\nთავსებადობა\nთავსებადობა (Android; iOS):\n\t\nAndroid\nელემენტი\nელემენტი:\n\t\n208 mAh\n\n\nელემენტი დამუხტვის სიჩქარე:\n\t\n-\n\n\nელემენტის ტიპი:\n\t\n-\n\n\nWireless დამუხტვა:\n\t\nNo\n\n\nსამუშაო დრო:\n\t\nUp To 13 Days\nზომა/წონა\nწონა:\n\t\n36.8 g\nფერი\nფერი:\n\t\nSilver\nმეტის ნახვა\nგაეცანი საგარანტიო პირობებს\nსაგარანტიო პირობები\nფილიალები\nმარაგშია\nშეკვეთიდან 2-5 დღეში\nზუმერის წერეთლის ფილიალი\n\nთბილისი - წერეთლის გამზირი, N1.\n\nმარაგშია\n+995 591 967 601\nორშ-შაბ: 10:00:00 - 20:00:00\nკვირა: 10:00:00 - 19:00:00\nზუმერის პეკინის ფილიალი\n\nთბილისი - კ.გამსახურდიას (პეკინის) გამზირი N14ა\n\nმარაგშია\n+995 591 967 671\nორშ-შაბ: 10:00:00 - 21:00:00\nკვირა: 10:00:00 - 20:00:00\nზუმერის City Mall საბურთალო-ს ფილიალი\n\nთბილისი - \"სითი მოლი\" - პეტრე ქავთარაძის N1\n\nმარაგშია\n+995 591 971 962\nორშ-შაბ: 10:00:00 - 22:00:00\nკვირა: 10:00:00 - 22:00:00\nზუმერის თბილისი მოლის ფილიალი\n\nთბილისი - „თბილისი მოლი\" - I სართული. აღმაშენებლის ხეივანი მე-16 კმ\n\nმარაგშია\n+995 591 967 608\nორშ-შაბ: 10:00:00 - 22:00:00\nკვირა: 10:00:00 - 22:00:00\nზუმერის \"გლდანი მოლის\" ფილიალი\n\nთბილისი - \"გლდანი მოლი\" - I სართული, M-ახმეტელის მიმდებარე\n\nმარაგშია\n+995 591 967 673\nორშ-შაბ: 10:00:00 - 21:00:00\nკვირა: 10:00:00 - 21:00:00\nზუმერის ისთ ფოინთის ფილიალი\n\nთბილისი - \"ისთ ფოინთი\" - ალ. თვალჭრელიძე N2\n\nმარაგშია\n+995 591 340 476\nორშ-შაბ: 10:00:00 - 22:00:00\nკვირა: 10:00:00 - 22:00:00\nბათუმი ჭავჭავაძის ფილიალი\n\nბათუმი - ბათუმი, ჭავჭავაძის N21\n\nმარაგშია\n+995 591 967 606\nორშ-შაბ: 10:00:00 - 20:00:00\nკვირა: 10:00:00 - 19:00:00\nბათუმის \"Black Sea Mall\"-ის ფილიალი\n\nბათუმი - \"Black Sea Mall\" - ტბელ აბუსერიძის N22\n\nმარაგშია\n+995 591 310 257\nორშ-შაბ: 10:00:00 - 21:00:00\nკვირა: 10:00:00 - 21:00:00\nბათუმის გრანდ მოლის ფილიალი\n\nბათუმი - \"გრანდ მოლი\" - შერიფ ხიმშიაშვილის 29\n\nმარაგშია\n+995 591 022 872\nორშ-შაბ: 10:00:00 - 22:00:00\nკვირა: 10:00:00 - 22:00:00\nქუთაისის ფილიალი\n\nქუთაისი - თამარ მეფის ქ. N3 , ქუთაისის ცენტრალური მოედანი\n\nმარაგშია\n+955 591 967 605\nორშ-შაბ: 10:00:00 - 20:00:00\nკვირა: 10:00:00 - 19:00:00\nქუთაისი ვესთ მოლი\n\nქუთაისი - \"ვესთ მოლი\" - შარტავას N2\n\nმარაგშია\n+995 595 306 765\nორშ-შაბ: 10:00:00 - 22:00:00\nკვირა: 10:00:00 - 22:00:00\nზუგდიდი მოლის ფილიალი\n\nზუგდიდი - ზუგდიდი მოლი, კოსტავას ქუჩა №28\n\nმარაგშია\n+995 591 676 489\nორშ-შაბ: 10:00:00 - 22:00:00\nკვირა: 10:00:00 - 22:00:00\nგორი მოლის ფილიალი\n\nგორი - გორი, ცხინვალის გზატკეცილი 14-14ამ, გორი მოლი\n\nმარაგშია\n+995 591 198 248\nორშ-შაბ: 10:00:00 - 22:00:00\nკვირა: 10:00:00 - 22:00:00\nახალციხის ფილიალი\n\nახალციხე - ახალციხე, თამარ მეფის ქ. N9\n\nმარაგშია\n+995 598 088 659\nორშ-შაბ: 10:00:00 - 19:00:00\nკვირა: 10:00:00 - 19:00:00\nთელავი მოლის ფილიალი\n\nთელავი - \"თელავი მოლი\" - ალაზნის ქ.N77\n\nმარაგშია\n+995 595 069 853\nორშ-შაბ: 10:00:00 - 20:00:00\nკვირა: 10:00:00 - 19:00:00\nმეტის ნახვა\n139 ₾\n\nთვეში: 3.9 ₾ -დან\n\nმარაგი ფილიალებში\nფასის დაზღვევა\nფასის კონტროლი\nფასის დაჯავშნა\nყიდვა\nშედარება\nდამატება\nნავიგაცია\n\nპერსონალურ მონაცემთა დაცვის პოლიტიკა\n\nჩვენ შესახებ\n\nწესები და პირობები\n\nმიწოდების სერვისი\n\nკარიერა\n\nგადახდები\n\nSetanta Sports\n\nგადახდის მეთოდები\n\nგარანტია\n\nგანვადება\n\nნივთის დაბრუნება\n\nნივთის ონლაინ ყიდვის ინსტრუქცია\n\nგამოგვყევი\n\nFacebook\n\nYoutube\n\nInstagram\n\nTik Tok\n\nკონტაქტი\n\nInfo@zoommer.ge\n\n+995 (32) 2 60 30 60 / *7007\n\nფილიალები\n\nკორპორატიული გაყიდვები\n\nZoommer App\n\nCopyright © 2023 Zoommer.ge. All rights reserved.\n\nCookie პოლიტიკა\n\nსაიტით სარგებლობის გაგრძელებით, შენ ეთანხმები Cookie ჩანაწერების გამოყენებას. მეტი ინფორმაცისათვის იხილეთ კონფიდენციალურობის პოლიტიკა\n\nგასაგებია",
    "specs": {
      "ბრენდი:": "Samsung",
      "კავშირის სტანდარტი:": "No",
      "SIM ბარათი:": "No",
      "კორპუსი:": "ალუმინი",
      "IP დაცვა :": "IP68",
      "ოპერაციული სისტემა:": "FreeRTOS",
      "ჩიპსეტი:": "-",
      "NFC:": "-",
      "Bluetooth:": "5.3",
      "სენსორი:": "Accelerometer, Barometer, Light Sensor, Gyro Sensor, Optical Heart Rate Sensor",
      "სპიკერი:": "-",
      "ქართული ენის მხარდაჭერა:": "Yes",
      "გადახდის ფუნქცია (Pay):": "No",
      "კამერა:": "No",
      "ეკრანის ზომა:": "1.6 Inches",
      "ეკრანის ტიპი:": "Amoled",
      "PPI:": "-",
      "რეზოლუცია:": "256 x 402 pixels",
      "ეკრანის სიკაშკაშე:": "-",
      "Always on Display:": "Yes",
      "Wi-Fi:": "-",
      "GPS:": "Yes",
      "შიდა მეხსიერება:": "256 MB",
      "ოპერატიული მეხსიერება:": "16 MB",
      "თავსებადობა (Android; iOS):": "Android",
      "ელემენტი:": "208 mAh",
      "ელემენტი დამუხტვის სიჩქარე:": "-",
      "ელემენტის ტიპი:": "-",
      "Wireless დამუხტვა:": "No",
      "სამუშაო დრო:": "Up To 13 Days",
      "წონა:": "36.8 g",
      "ფერი:": "Silver"
    }
  },
  {
    "category": "Gaming ლეპტოპები",
    "title": "Asus TUF F16 FX608JHR-RV035, Intel core i7-14650HX 16 ...",
    "price": 4199.0,
    "link": "https://zoommer.ge/leptopebi/asus-tuf-f16-fx608jhr-rv035-intel-core-i7-14650hx-16c-nvidia-geforce-rtx-5050-8-p48881",
    "image": "/_next/image?url=https%3A%2F%2Fs3.zoommer.ge%2Fsite%2F5130b483-82a5-498f-b438-c145a5cbe221_Thumb.jpeg&w=384&q=50",
    "product_title_detail": "Asus TUF F16 FX608JHR-RV035, Intel core i7-14650HX 16C, Nvidia GeForce RTX 5050 8GB, 16GB RAM SSD 512GB, Free Dos, ლეპტოპი",
    "description": "",
    "specs": {
      "ბრენდი:": "Asus",
      "მოდელი:": "TUF 16",
      "ცენტრალური პროცესორი:": "Intel Core i7-14650HX",
      "პროცესორის თაობა:": "Intel i7 14th Gen",
      "პროცესორის სიხშირე:": "3.7 GHz ~ 5.2 GHz",
      "ბირთვების რაოდენობა:": "16",
      "ნაკადების რაოდენობა:": "24",
      "გრაფიკული პროცესორი:": "Nvidia GeForce RTX 5050",
      "გრაფიკული პროცესორის მეხსიერება:": "8 GB",
      "გრაფიკული პროცესორის ტიპი:": "არა ინტეგრირებული",
      "ოპერაციული სისტემა:": "No",
      "Bluetooth:": "5.3",
      "ეკრანის ზომა:": "16 Inches",
      "რეზოლუცია:": "WUXGA",
      "ეკრანის ტიპი:": "IPS",
      "სენსორული ეკრანი:": "No",
      "განახლების სიხშირე:": "165 Hz",
      "კლავიატურის განათება:": "Yes",
      "Numpad:": "Yes",
      "დისკის წამკითხველი:": "No",
      "ვებ კამერა:": "Yes",
      "ლეპტოპის ტიპი:": "გეიმინგი",
      "შიდა მეხსიერება:": "512 GB",
      "შიდა მეხსიერების ტიპი:": "SSD",
      "შიდა მეხსიერების ინტერფეისი:": "M.2",
      "ოპერატიული მეხსიერება:": "16 GB",
      "ოპერატიული მეხსიერების ტიპი:": "DDR5",
      "ოპერატიული მეხსიერების სიხშირე:": "5600 MHz",
      "USB:": "3 x USB-A",
      "Type-C:": "1x",
      "Type-C პორტით დამუხტვა:": "No",
      "HDMI:": "Yes",
      "ლან პორტი:": "Yes",
      "3.5mm:": "Yes",
      "წონა:": "2.40 kg",
      "ფერი:": "titan grey"
    }
  },
  {
    "category": "Gaming ლეპტოპები",
    "title": "Asus TUF 16 FX607VJ-RL005, Intel Core 5-210H, Nvidia ...",
    "price": 2699.0,
    "link": "https://zoommer.ge/leptopebi/asus-tuf-16-fx607vj-rl005-intel-core-5-210h-nvidia-geforce-rtx-3050-6gb-16gb-r-p48879",
    "image": "/_next/image?url=https%3A%2F%2Fs3.zoommer.ge%2Fsite%2F1f21f53c-d74b-4124-a89f-d71e2022fbd8_Thumb.jpeg&w=384&q=50",
    "product_title_detail": "Asus TUF 16 FX607VJ-RL005, Intel Core 5-210H, Nvidia GeForce RTX 3050 6GB, 16GB RAM SSD 1TB, Free Dos, ლეპტოპი",
    "description": "*7007 / +995 (32) 2 60 30 60\nსავაჭრო პოლიტიკა\nგანვადება\nკარიერა\nTrade In\nფილიალები\nნავიგაცია\nკალათა\nშესვლა\n%\nმთავარი\nლეპტოპები\nAsus\n#ZOOM-037016\nAsus TUF 16 FX607VJ-RL005, Intel Core 5-210H, Nvidia GeForce RTX 3050 6GB, 16GB RAM SSD 1TB, Free Dos, ლეპტოპი\nეკრანის ზომა\n16 Inches\nრეზოლუცია\nWUXGA\nეკრანის ტიპი\nIPS\nგანახლების სიხშირე\n144 Hz\nშიდა მეხსიერება\n1 TB\nBluetooth\n5.3\nType-C\n1x\nოპერატიული მეხსიერება\n16 GB\nერთად იაფია\nდაამატე ნივთი\nAsus TUF 16 FX607VJ-RL005, Intel Core 5-210H, Nvidia GeForce RTX 3050 6GB, 16GB RAM SSD 1TB, Free Dos, ლეპტოპი\n2699 ₾\nRivacase 8057 Laptop Bag 16 Black\n58.65 ₾\n69 ₾\nRazer Gaming Mouse DeathAdder Essential USB White\n52 ₾\n65 ₾\nHavit Gaming Cooling Pad HV-F2083 Black\n75.65 ₾\n89 ₾\nჯამური ფასი (3)\n2885.3 ₾\n2922 ₾\nყიდვა\nაქსესუარები\nაღწერა\nმსგავსი\nმახასიათებლები\nფილიალები\nაქსესუარები\nაღწერა\nმსგავსი\nმახასიათებლები\nფილიალები\n89 ₾\n\nთვეში: 2 ₾ -დან\n\nHavit Gaming Cooling Pad HV-F2083 Black\nდამატება\n69 ₾\n\nთვეში: 1 ₾ -დან\n\nRivacase 8057 Laptop Bag 16 Black\nდამატება\n219 ₾\n\nთვეში: 6 ₾ -დან\n\nRazer Gaming Mouse Orochi V2 WL Black\nდამატება\n9 ₾\n\nHavit Gaming mouse Pad HV-MP838\nდამატება\n69 ₾\n\nთვეში: 1 ₾ -დან\n\nXiaomi Mi Router 4A DVB4230GL White\nდამატება\n79 ₾\n\nთვეში: 2 ₾ -დან\n\nRivacase 7531 Eco Laptop Bag 15 Black\nდამატება\n219 ₾\n\nთვეში: 6 ₾ -დან\n\nRazer Gaming Mouse Orochi V2 WL White\nდამატება\n29 ₾\n\nRazer Mouse Pad Goliathus Mobile Black/Green\nდამატება\n85 ₾\n\nთვეში: 2 ₾ -დან\n\nTP-Link Archer C50 AC1200 White\nდამატება\n89 ₾\n\nთვეში: 2 ₾ -დან\n\nTomtoc Defender A13 Laptop Sleeve Kit 16 A13F2DV Blac ...\nდამატება\n209 ₾\n\nთვეში: 5 ₾ -დან\n\nRazer Gaming Mouse DeathAdder V2 X Hyperspeed WL/BT/U ...\nდამატება\n29 ₾\n\nRazer Mouse Pad Goliathus Mobile Stealth Edition Blac ...\nდამატება\n119 ₾\n\nთვეში: 3 ₾ -დან\n\nTP-Link Archer C6 AC1200 Black\nდამატება\n119 ₾\n\nთვეში: 3 ₾ -დან\n\nTomtoc Defender A42 Laptop Briefcase 16 A42F2B1 Navy ...\nდამატება\n139 ₾\n\nთვეში: 3 ₾ -დან\n\nLogitech Gaming Mouse G402 Hyperion Fury black\nდამატება\n59 ₾\n\nთვეში: 1 ₾ -დან\n\nRazer Mouse Pad Gigantus V2 Large Black\nდამატება\n159 ₾\n\nთვეში: 4 ₾ -დან\n\nXiaomi Router AX1500 White\nდამატება\n119 ₾\n\nთვეში: 3 ₾ -დან\n\nTomtoc Defender A42 Laptop Briefcase 16 A42F2D1 Black\nდამატება\n29 ₾\n\nHavit Gaming Mouse HV-MS1010 Black\nდამატება\n49 ₾\n\nთვეში: 1 ₾ -დან\n\nRazer Mouse Pad Gigantus V2 Medium Black\nდამატება\n179 ₾\n\nთვეში: 4 ₾ -დან\n\nXiaomi Mesh System AX3000 NE 1 pack White\nდამატება\n89 ₾\n\nთვეში: 2 ₾ -დან\n\nUniq Dfender Tough Laptop Sleeve 16 Inch Marl Grey\nდამატება\n79 ₾\n\nთვეში: 2 ₾ -დან\n\nRazer Gaming Mouse DeathAdder Essential USB Black\nდამატება\n49 ₾\n\nთვეში: 1 ₾ -დან\n\nHyperX Pulsefire Mat M Black\nდამატება\n299 ₾\n\nთვეში: 8 ₾ -დან\n\nXiaomi Mesh System AX3000 NE 2 pack White\nდამატება\n89 ₾\n\nთვეში: 2 ₾ -დან\n\nUniq Dfender Tough Laptop Sleeve 16 Inch Black\nდამატება\n119 ₾\n\nთვეში: 3 ₾ -დან\n\nHyperX Pulsefire Surge Mouse Black\nდამატება\n59 ₾\n\nთვეში: 1 ₾ -დან\n\nHyperX Pulsefire Mat L Black\nდამატება\n249 ₾\n\nთვეში: 6 ₾ -დან\n\nXiaomi Router BE3600 White\nდამატება\n99 ₾\n\nთვეში: 2 ₾ -დან\n\nDell EcoLoop Essential Backpack 14-16 460-BDSS Black\nდამატება\n469 ₾\n\nთვეში: 13 ₾ -დან\n\nHP OMEN PHOTON Wireless Mouse 6CL96AA Black\nდამატება\n39 ₾\n\nთვეში: 1 ₾ -დან\n\nRazer Mouse Pad Sphex V3 S Black\nდამატება\n79 ₾\n\nთვეში: 2 ₾ -დან\n\nTomtoc Defender A13 Laptop Sleeve 16 A13F2D1 Black\nდამატება\n65 ₾\n\nთვეში: 1 ₾ -დან\n\nRazer Gaming Mouse DeathAdder Essential USB White\nდამატება\n89 ₾\n\nთვეში: 2 ₾ -დან\n\nRazer Mouse Pad Sphex V3 L Black\nდამატება\n89 ₾\n\nთვეში: 2 ₾ -დან\n\nTomtoc Defender A14 Laptop Briefcase 16 A14F2D1 Black\nდამატება\n239 ₾\n\nთვეში: 6 ₾ -დან\n\nRazer Gaming Mouse Basilisk V3 Black\nდამატება\n25 ₾\n\nHavit Gaming mouse Pad HV-MP861\nდამატება\n299 ₾\n\nთვეში: 8 ₾ -დან\n\nRazer Gaming Mouse Naga V2 HyperSpeed WL Black\nდამატება\n99 ₾\n\nთვეში: 2 ₾ -დან\n\nSpigen Desk Pad Black with Magnetic Cable Holder LD30 ...\nდამატება\n229 ₾\n\nთვეში: 6 ₾ -დან\n\nRazer Gaming Mouse Basilisk V3 X HyperSpeed WL Black\nდამატება\n129 ₾\n\nთვეში: 3 ₾ -დან\n\nRazer Gaming Mouse Cobra Black\nდამატება\n19 ₾\n\nHavit Gaming Mouse HV-MS989GT Black/Red\nდამატება\n19 ₾\n\nHavit Gaming Mouse HV-MS626GT Black\nდამატება\n19 ₾\n\nHavit Gaming Mouse HV-MS66GT White/Blue\nდამატება\n149 ₾\n\nთვეში: 4 ₾ -დან\n\nHyperX Gaming Mouse Pulsefire Haste 2 Black\nდამატება\n19 ₾\n\nHavit Wireless Mouse HV-MS66GT Black\nდამატება\n179 ₾\n\nთვეში: 4 ₾ -დან\n\nLogitech Gaming Mouse G305 LIGHTSPEED WL L910-005282 ...\nდამატება\n259 ₾\n\nთვეში: 7 ₾ -დან\n\nLogitech Gaming Mouse G502 X L910-006138 Black\nდამატება\n259 ₾\n\nთვეში: 7 ₾ -დან\n\nLogitech Gaming Mouse G502 X L910-006138 White\nდამატება\n19 ₾\n\nHavit Gaming Mouse HV-MS626GT Black/Red\nდამატება\n19 ₾\n\nHavit Gaming Mouse HV-MS626GT Black/Blue\nდამატება\n349 ₾\n\nთვეში: 9 ₾ -დან\n\nLogitech Gaming Mouse G703 LIGHTSPEED WL L910-005640 ...\nდამატება\n89 ₾\n\nთვეში: 2 ₾ -დან\n\nLogitech Gaming Mouse G102 LIGHTSYNC L910-005823 Blac ...\nდამატება\n89 ₾\n\nთვეში: 2 ₾ -დან\n\nLogitech Gaming Mouse G102 LIGHTSYNC L910-005824 Whit ...\nდამატება\n89 ₾\n\nთვეში: 2 ₾ -დან\n\nLogitech Gaming Mouse G102 LIGHTSYNC L910-005801 Blue\nდამატება\n239 ₾\n\nთვეში: 6 ₾ -დან\n\nLogitech Gaming Mouse G502 HERO L910-005470 Black\nდამატება\n199 ₾\n\nთვეში: 5 ₾ -დან\n\nHyperX Pulsefire Haste 2 core Wireless Black\nდამატება\n199 ₾\n\nთვეში: 5 ₾ -დან\n\nHyperX Pulsefire Haste 2 core Wireless White\nდამატება\n59 ₾\n\nთვეში: 1 ₾ -დან\n\nHavit Gaming Mouse HV-MS954 Black\nდამატება\n39 ₾\n\nთვეში: 1 ₾ -დან\n\nHavit Gaming Mouse HV-MS1033 White\nდამატება\n39 ₾\n\nთვეში: 1 ₾ -დან\n\nHavit Gaming Mouse HV-MS1029 Pink\nდამატება\n59 ₾\n\nთვეში: 1 ₾ -დან\n\nHavit Gaming Mouse HV-MS966 Black/Green\nდამატება\n49 ₾\n\nთვეში: 1 ₾ -დან\n\nHavit Wireless Mouse HV-MS1039W Black/White\nდამატება\n79 ₾\n\nთვეში: 2 ₾ -დან\n\nHavit Wireless Mouse HV-MS970WB Pro Black\nდამატება\n79 ₾\n\nთვეში: 2 ₾ -დან\n\nHavit Wireless Mouse HV-MS970WB Pro Transparent White\nდამატება\n219 ₾\n\nთვეში: 6 ₾ -დან\n\nRazer Gaming Mouse Orochi V2 WL Pink\nდამატება\nპროდუქტის შესახებ\n\n თუ ეძებთ ლეპტოპს, რომელიც მარტივად გაუმკლავდება ყველაზე მოთხოვნად თამაშებს —  Asus TUF 16 FX607VJ-RL005 Grey შექმნილია სწორედ თქვენთვის. ეს მოდელი აერთიანებს მაღალ წარმადობას, გამძლე კონ...\n\nმეტის ნახვა\nმსგავსი პროდუქტები\n2599 ₾\n2799 ₾\n\nთვეში: 72 ₾ -დან\n\nAsus TUF 15 FX507ZC4-HN009 Black\nდამატება\n2249 ₾\n2499 ₾\n\nთვეში: 62 ₾ -დან\n\nAsus TUF 15 FA506NF-HN018, AMD Ryzen 5-7535HS, NVIDIA ...\nდამატება\n2999 ₾\n3699 ₾\n\nთვეში: 83 ₾ -დან\n\nAsus TUF 15 FA507NUR-LP044 Mercha Grey\nდამატება\n3299 ₾\n3499 ₾\n\nთვეში: 91 ₾ -დან\n\nAsus TUF 14 FA401UU-RG013 Jaeger Grey\nდამატება\n4179 ₾\n\nთვეში: 116 ₾ -დან\n\nAsus TUF A16 FA608WV-QT053 Grey\nდამატება\n2179 ₾\n2279 ₾\n\nთვეში: 60 ₾ -დან\n\nAsus TUF 15 FA506NFR-HN021, AMD Ryzen 7 7435HS, Nvidi ...\nდამატება\n5599 ₾\n5899 ₾\n\nთვეში: 155 ₾ -დან\n\nAsus TUF 18 FA808UP-S8030 Grey\nდამატება\n7299 ₾\n\nთვეში: 202 ₾ -დან\n\nAsus ROG Strix 16 G615JPR-S5101 Grey\nდამატება\n10399 ₾\n10499 ₾\n\nთვეში: 288 ₾ -დან\n\nAsus ROG Strix 18 G835LR-SA005 Black\nდამატება\n15999 ₾\n\nთვეში: 444 ₾ -დან\n\nAsus ROG Strix 18 G835LX-SA034W Black\nდამატება\n6499 ₾\n\nთვეში: 180 ₾ -დან\n\nAsus ROG Strix 16 G614PR-RV007, AMD Ryzen 9-7940HX, N ...\nდამატება\n6699 ₾\n\nთვეში: 186 ₾ -დან\n\nAsus ROG Strix G16 G615JPR-RV113, Intel core i7-14650 ...\nდამატება\n8499 ₾\n\nთვეში: 236 ₾ -დან\n\nAsus ROG Strix G18 G815LR-S9085, Intel Core Ultra 9 2 ...\nდამატება\n4999 ₾\n\nთვეში: 138 ₾ -დან\n\nAsus TUF F16 FX608JMR-RV073, Intel core i7-14650HX 16 ...\nდამატება\n4199 ₾\n\nთვეში: 116 ₾ -დან\n\nAsus TUF F16 FX608JHR-RV035, Intel core i7-14650HX 16 ...\nდამატება\nდამატებითი მახასიათებლები\nბრენდი\nბრენდი:\n\t\nAsus\nმოდელი\nმოდელი:\n\t\nTUF 16\nტექნიკური მახასიათებლები\nცენტრალური პროცესორი:\n\t\nIntel Core 5-210H\n\n\nპროცესორის თაობა:\n\t\nIntel 5 Series 2\n\n\nპროცესორის სიხშირე:\n\t\n2.2 GHz ~ 4.8 GHz\n\n\nბირთვების რაოდენობა:\n\t\n8\n\n\nნაკადების რაოდენობა:\n\t\n12\n\n\nგრაფიკული პროცესორი:\n\t\nNvidia GeForce RTX 3050\n\n\nგრაფიკული პროცესორის მეხსიერება:\n\t\n6 GB\n\n\nგრაფიკული პროცესორის ტიპი:\n\t\nარა ინტეგრირებული\n\n\nოპერაციული სისტემა:\n\t\nNo\n\n\nBluetooth:\n\t\n5.3\nეკრანი\nეკრანის ზომა:\n\t\n16 Inches\n\n\nრეზოლუცია:\n\t\nWUXGA\n\n\nეკრანის ტიპი:\n\t\nIPS\n\n\nსენსორული ეკრანი:\n\t\nNo\n\n\nგანახლების სიხშირე:\n\t\n144 Hz\nდამატებითი მახასიათებლები\nკლავიატურის განათება:\n\t\nYes\n\n\nNumpad:\n\t\nYes\n\n\nდისკის წამკითხველი:\n\t\nNo\n\n\nვებ კამერა:\n\t\nYes\n\n\nლეპტოპის ტიპი:\n\t\nგეიმინგი\nმეხსიერება\nშიდა მეხსიერება:\n\t\n1 TB\n\n\nშიდა მეხსიერების ტიპი:\n\t\nSSD\n\n\nშიდა მეხსიერების ინტერფეისი:\n\t\nM.2\n\n\nოპერატიული მეხსიერება:\n\t\n16 GB\n\n\nოპერატიული მეხსიერების ტიპი:\n\t\nDDR4\n\n\nოპერატიული მეხსიერების სიხშირე:\n\t\n3200 MHz\nპორტები\nUSB:\n\t\n2 x USB-A\n\n\nType-C:\n\t\n1x\n\n\nType-C პორტით დამუხტვა:\n\t\nNo\n\n\nHDMI:\n\t\nYes\n\n\nლან პორტი:\n\t\nYes\n\n\n3.5mm:\n\t\nYes\nზომა/წონა\nწონა:\n\t\n2.40 kg\nფერი\nფერი:\n\t\ntitan grey\nმეტის ნახვა\nგაეცანი საგარანტიო პირობებს\nსაგარანტიო პირობები\nფილიალები\nმარაგშია\nშეკვეთიდან 2-5 დღეში\nზუმერის \"თბილისი ცენტრალის\" ფილიალი\n\nთბილისი - \"თბილისი ცენტრალი\"- lll სართული\n\nმარაგშია\n+995 599 862 449\nორშ-შაბ: 10:00:00 - 20:00:00\nკვირა: 10:00:00 - 19:00:00\nზუმერის City Mall საბურთალო-ს ფილიალი\n\nთბილისი - \"სითი მოლი\" - პეტრე ქავთარაძის N1\n\nმარაგშია\n+995 591 971 962\nორშ-შაბ: 10:00:00 - 22:00:00\nკვირა: 10:00:00 - 22:00:00\nზუმერის თბილისი მოლის ფილიალი\n\nთბილისი - „თბილისი მოლი\" - I სართული. აღმაშენებლის ხეივანი მე-16 კმ\n\nმარაგშია\n+995 591 967 608\nორშ-შაბ: 10:00:00 - 22:00:00\nკვირა: 10:00:00 - 22:00:00\nზუმერის \"გლდანი მოლის\" ფილიალი\n\nთბილისი - \"გლდანი მოლი\" - I სართული, M-ახმეტელის მიმდებარე\n\nმარაგშია\n+995 591 967 673\nორშ-შაბ: 10:00:00 - 21:00:00\nკვირა: 10:00:00 - 21:00:00\nზუმერის ისთ ფოინთის ფილიალი\n\nთბილისი - \"ისთ ფოინთი\" - ალ. თვალჭრელიძე N2\n\nმარაგშია\n+995 591 340 476\nორშ-შაბ: 10:00:00 - 22:00:00\nკვირა: 10:00:00 - 22:00:00\nბათუმი ჭავჭავაძის ფილიალი\n\nბათუმი - ბათუმი, ჭავჭავაძის N21\n\nმარაგშია\n+995 591 967 606\nორშ-შაბ: 10:00:00 - 20:00:00\nკვირა: 10:00:00 - 19:00:00\nბათუმის \"Black Sea Mall\"-ის ფილიალი\n\nბათუმი - \"Black Sea Mall\" - ტბელ აბუსერიძის N22\n\nმარაგშია\n+995 591 310 257\nორშ-შაბ: 10:00:00 - 21:00:00\nკვირა: 10:00:00 - 21:00:00\nბათუმის გრანდ მოლის ფილიალი\n\nბათუმი - \"გრანდ მოლი\" - შერიფ ხიმშიაშვილის 29\n\nმარაგშია\n+995 591 022 872\nორშ-შაბ: 10:00:00 - 22:00:00\nკვირა: 10:00:00 - 22:00:00\nქუთაისი ვესთ მოლი\n\nქუთაისი - \"ვესთ მოლი\" - შარტავას N2\n\nმარაგშია\n+995 595 306 765\nორშ-შაბ: 10:00:00 - 22:00:00\nკვირა: 10:00:00 - 22:00:00\nმეტის ნახვა\n2699 ₾\n\nთვეში: 75.0 ₾ -დან\n\nმარაგი ფილიალებში\nფასის დაზღვევა\nფასის კონტროლი\nფასის დაჯავშნა\nყიდვა\nშედარება\nდამატება\nნავიგაცია\n\nპერსონალურ მონაცემთა დაცვის პოლიტიკა\n\nჩვენ შესახებ\n\nწესები და პირობები\n\nმიწოდების სერვისი\n\nკარიერა\n\nგადახდები\n\nSetanta Sports\n\nგადახდის მეთოდები\n\nგარანტია\n\nგანვადება\n\nნივთის დაბრუნება\n\nნივთის ონლაინ ყიდვის ინსტრუქცია\n\nგამოგვყევი\n\nFacebook\n\nYoutube\n\nInstagram\n\nTik Tok\n\nკონტაქტი\n\nInfo@zoommer.ge\n\n+995 (32) 2 60 30 60 / *7007\n\nფილიალები\n\nკორპორატიული გაყიდვები\n\nZoommer App\n\nCopyright © 2023 Zoommer.ge. All rights reserved.\n\nCookie პოლიტიკა\n\nსაიტით სარგებლობის გაგრძელებით, შენ ეთანხმები Cookie ჩანაწერების გამოყენებას. მეტი ინფორმაცისათვის იხილეთ კონფიდენციალურობის პოლიტიკა\n\nგასაგებია",
    "specs": {
      "ბრენდი:": "Asus",
      "მოდელი:": "TUF 16",
      "ცენტრალური პროცესორი:": "Intel Core 5-210H",
      "პროცესორის თაობა:": "Intel 5 Series 2",
      "პროცესორის სიხშირე:": "2.2 GHz ~ 4.8 GHz",
      "ბირთვების რაოდენობა:": "8",
      "ნაკადების რაოდენობა:": "12",
      "გრაფიკული პროცესორი:": "Nvidia GeForce RTX 3050",
      "გრაფიკული პროცესორის მეხსიერება:": "6 GB",
      "გრაფიკული პროცესორის ტიპი:": "არა ინტეგრირებული",
      "ოპერაციული სისტემა:": "No",
      "Bluetooth:": "5.3",
      "ეკრანის ზომა:": "16 Inches",
      "რეზოლუცია:": "WUXGA",
      "ეკრანის ტიპი:": "IPS",
      "სენსორული ეკრანი:": "No",
      "განახლების სიხშირე:": "144 Hz",
      "კლავიატურის განათება:": "Yes",
      "Numpad:": "Yes",
      "დისკის წამკითხველი:": "No",
      "ვებ კამერა:": "Yes",
      "ლეპტოპის ტიპი:": "გეიმინგი",
      "შიდა მეხსიერება:": "1 TB",
      "შიდა მეხსიერების ტიპი:": "SSD",
      "შიდა მეხსიერების ინტერფეისი:": "M.2",
      "ოპერატიული მეხსიერება:": "16 GB",
      "ოპერატიული მეხსიერების ტიპი:": "DDR4",
      "ოპერატიული მეხსიერების სიხშირე:": "3200 MHz",
      "USB:": "2 x USB-A",
      "Type-C:": "1x",
      "Type-C პორტით დამუხტვა:": "No",
      "HDMI:": "Yes",
      "ლან პორტი:": "Yes",
      "3.5mm:": "Yes",
      "წონა:": "2.40 kg",
      "ფერი:": "titan grey"
    }
  },
  {
    "category": "Gaming ლეპტოპები",
    "title": "Asus TUF F16 FX608JMR-RV073, Intel core i7-14650HX 16 ...",
    "price": 4999.0,
    "link": "https://zoommer.ge/leptopebi/asus-tuf-f16-fx608jmr-rv073-intel-core-i7-14650hx-16c-nvidia-geforce-rtx-5060-8-p48866",
    "image": "/_next/image?url=https%3A%2F%2Fs3.zoommer.ge%2Fsite%2F6833c0f3-8abf-4a14-8a9e-c5e86de6e1b6_Thumb.jpeg&w=384&q=50",
    "product_title_detail": "Asus TUF F16 FX608JMR-RV073, Intel core i7-14650HX 16C, NVIDIA GeForce RTX 5060 8GB, 32GB RAM SSD 1TB, Free Dos, ლეპტოპი",
    "description": "*7007 / +995 (32) 2 60 30 60\nფილიალები\nნავიგაცია\nკალათა\nშესვლა\n%\nმთავარი\nლეპტოპები\nAsus\n#ZOOM-037008\nAsus TUF F16 FX608JMR-RV073, Intel core i7-14650HX 16C, NVIDIA GeForce RTX 5060 8GB, 32GB RAM SSD 1TB, Free Dos, ლეპტოპი\nეკრანის ზომა\n16 Inches\nრეზოლუცია\nWUXGA\nეკრანის ტიპი\nIPS\nგანახლების სიხშირე\n165 Hz\nშიდა მეხსიერება\n1 TB\nBluetooth\n5.3\nType-C\n1x\nოპერატიული მეხსიერება\n32 GB\nერთად იაფია\nდაამატე ნივთი\nAsus TUF F16 FX608JMR-RV073, Intel core i7-14650HX 16C, NVIDIA GeForce RTX 5060 8GB, 32GB RAM SSD 1TB, Free Dos, ლეპტოპი\n4999 ₾\nRivacase 8057 Laptop Bag 16 Black\n58.65 ₾\n69 ₾\nRazer Gaming Mouse DeathAdder Essential USB White\n52 ₾\n65 ₾\nHavit Gaming Cooling Pad HV-F2083 Black\n75.65 ₾\n89 ₾\nჯამური ფასი (3)\n5185.3 ₾\n5222 ₾\nყიდვა\nაქსესუარები\nაღწერა\nმსგავსი\nმახასიათებლები\nფილიალები\nაქსესუარები\nაღწერა\nმსგავსი\nმახასიათებლები\nფილიალები\n89 ₾\n\nთვეში: 2 ₾ -დან\n\nHavit Gaming Cooling Pad HV-F2083 Black\nდამატება\n69 ₾\n\nთვეში: 1 ₾ -დან\n\nRivacase 8057 Laptop Bag 16 Black\nდამატება\n219 ₾\n\nთვეში: 6 ₾ -დან\n\nRazer Gaming Mouse Orochi V2 WL Black\nდამატება\n59 ₾\n\nთვეში: 1 ₾ -დან\n\nHavit Gaming mouse Pad HV-MP901\nდამატება\n69 ₾\n\nთვეში: 1 ₾ -დან\n\nXiaomi Mi Router 4A DVB4230GL White\nდამატება\n79 ₾\n\nთვეში: 2 ₾ -დან\n\nRivacase 7531 Eco Laptop Bag 15 Black\nდამატება\n219 ₾\n\nთვეში: 6 ₾ -დან\n\nRazer Gaming Mouse Orochi V2 WL White\nდამატება\n9 ₾\n\nHavit Gaming mouse Pad HV-MP838\nდამატება\n85 ₾\n\nთვეში: 2 ₾ -დან\n\nTP-Link Archer C50 AC1200 White\nდამატება\n89 ₾\n\nთვეში: 2 ₾ -დან\n\nTomtoc Defender A13 Laptop Sleeve Kit 16 A13F2DV Blac ...\nდამატება\n209 ₾\n\nთვეში: 5 ₾ -დან\n\nRazer Gaming Mouse DeathAdder V2 X Hyperspeed WL/BT/U ...\nდამატება\n29 ₾\n\nRazer Mouse Pad Goliathus Mobile Black/Green\nდამატება\n119 ₾\n\nთვეში: 3 ₾ -დან\n\nTP-Link Archer C6 AC1200 Black\nდამატება\n119 ₾\n\nთვეში: 3 ₾ -დან\n\nTomtoc Defender A42 Laptop Briefcase 16 A42F2B1 Navy ...\nდამატება\n139 ₾\n\nთვეში: 3 ₾ -დან\n\nLogitech Gaming Mouse G402 Hyperion Fury black\nდამატება\n29 ₾\n\nRazer Mouse Pad Goliathus Mobile Stealth Edition Blac ...\nდამატება\n159 ₾\n\nთვეში: 4 ₾ -დან\n\nXiaomi Router AX1500 White\nდამატება\n119 ₾\n\nთვეში: 3 ₾ -დან\n\nTomtoc Defender A42 Laptop Briefcase 16 A42F2D1 Black\nდამატება\n29 ₾\n\nHavit Gaming Mouse HV-MS1010 Black\nდამატება\n59 ₾\n\nთვეში: 1 ₾ -დან\n\nRazer Mouse Pad Gigantus V2 Large Black\nდამატება\n179 ₾\n\nთვეში: 4 ₾ -დან\n\nXiaomi Mesh System AX3000 NE 1 pack White\nდამატება\n89 ₾\n\nთვეში: 2 ₾ -დან\n\nUniq Dfender Tough Laptop Sleeve 16 Inch Marl Grey\nდამატება\n79 ₾\n\nთვეში: 2 ₾ -დან\n\nRazer Gaming Mouse DeathAdder Essential USB Black\nდამატება\n49 ₾\n\nთვეში: 1 ₾ -დან\n\nRazer Mouse Pad Gigantus V2 Medium Black\nდამატება\n299 ₾\n\nთვეში: 8 ₾ -დან\n\nXiaomi Mesh System AX3000 NE 2 pack White\nდამატება\n89 ₾\n\nთვეში: 2 ₾ -დან\n\nUniq Dfender Tough Laptop Sleeve 16 Inch Black\nდამატება\n119 ₾\n\nთვეში: 3 ₾ -დან\n\nHyperX Pulsefire Surge Mouse Black\nდამატება\n9 ₾\n\nHavit Gaming mouse Pad HV-MP843 Black\nდამატება\n249 ₾\n\nთვეში: 6 ₾ -დან\n\nXiaomi Router BE3600 White\nდამატება\n99 ₾\n\nთვეში: 2 ₾ -დან\n\nDell EcoLoop Essential Backpack 14-16 460-BDSS Black\nდამატება\n469 ₾\n\nთვეში: 13 ₾ -დან\n\nHP OMEN PHOTON Wireless Mouse 6CL96AA Black\nდამატება\n149 ₾\n\nთვეში: 4 ₾ -დან\n\nRazer Mouse Pad Firefly V2 RGB M Black\nდამატება\n79 ₾\n\nთვეში: 2 ₾ -დან\n\nTomtoc Defender A13 Laptop Sleeve 16 A13F2D1 Black\nდამატება\n65 ₾\n\nთვეში: 1 ₾ -დან\n\nRazer Gaming Mouse DeathAdder Essential USB White\nდამატება\n199 ₾\n\nთვეში: 5 ₾ -დან\n\nRazer Mouse Pad Goliathus Extended Chroma XXL Black\nდამატება\n89 ₾\n\nთვეში: 2 ₾ -დან\n\nTomtoc Defender A14 Laptop Briefcase 16 A14F2D1 Black\nდამატება\n239 ₾\n\nთვეში: 6 ₾ -დან\n\nRazer Gaming Mouse Basilisk V3 Black\nდამატება\n149 ₾\n\nთვეში: 4 ₾ -დან\n\nHyperX Pulsefire Mat RGB Black\nდამატება\n299 ₾\n\nთვეში: 8 ₾ -დან\n\nRazer Gaming Mouse Naga V2 HyperSpeed WL Black\nდამატება\n29 ₾\n\nHavit Gaming Mouse Pad HV-MP845 Black\nდამატება\n229 ₾\n\nთვეში: 6 ₾ -დან\n\nRazer Gaming Mouse Basilisk V3 X HyperSpeed WL Black\nდამატება\n29 ₾\n\nHavit Gaming Mouse Pad HV-MP847 Pink\nდამატება\n129 ₾\n\nთვეში: 3 ₾ -დან\n\nRazer Gaming Mouse Cobra Black\nდამატება\n29 ₾\n\nHavit Gaming Mouse Pad HV-MP849 Black\nდამატება\n19 ₾\n\nHavit Gaming Mouse HV-MS989GT Black/Red\nდამატება\n49 ₾\n\nთვეში: 1 ₾ -დან\n\nHyperX Pulsefire Mat M Black\nდამატება\n19 ₾\n\nHavit Gaming Mouse HV-MS626GT Black\nდამატება\n59 ₾\n\nთვეში: 1 ₾ -დან\n\nHyperX Pulsefire Mat L Black\nდამატება\n19 ₾\n\nHavit Gaming Mouse HV-MS66GT White/Blue\nდამატება\n39 ₾\n\nთვეში: 1 ₾ -დან\n\nRazer Mouse Pad Sphex V3 S Black\nდამატება\n149 ₾\n\nთვეში: 4 ₾ -დან\n\nHyperX Gaming Mouse Pulsefire Haste 2 Black\nდამატება\n89 ₾\n\nთვეში: 2 ₾ -დან\n\nRazer Mouse Pad Sphex V3 L Black\nდამატება\n19 ₾\n\nHavit Wireless Mouse HV-MS66GT Black\nდამატება\n29 ₾\n\nHavit Gaming mouse Pad HV-MP860\nდამატება\n179 ₾\n\nთვეში: 4 ₾ -დან\n\nLogitech Gaming Mouse G305 LIGHTSPEED WL L910-005282 ...\nდამატება\n25 ₾\n\nHavit Gaming mouse Pad HV-MP861\nდამატება\n259 ₾\n\nთვეში: 7 ₾ -დან\n\nLogitech Gaming Mouse G502 X L910-006138 Black\nდამატება\n99 ₾\n\nთვეში: 2 ₾ -დან\n\nSpigen Desk Pad Black with Magnetic Cable Holder LD30 ...\nდამატება\n259 ₾\n\nთვეში: 7 ₾ -დან\n\nLogitech Gaming Mouse G502 X L910-006138 White\nდამატება\n19 ₾\n\nHavit Gaming Mouse HV-MS626GT Black/Red\nდამატება\n19 ₾\n\nHavit Gaming Mouse HV-MS626GT Black/Blue\nდამატება\n349 ₾\n\nთვეში: 9 ₾ -დან\n\nLogitech Gaming Mouse G703 LIGHTSPEED WL L910-005640 ...\nდამატება\n89 ₾\n\nთვეში: 2 ₾ -დან\n\nLogitech Gaming Mouse G102 LIGHTSYNC L910-005823 Blac ...\nდამატება\n89 ₾\n\nთვეში: 2 ₾ -დან\n\nLogitech Gaming Mouse G102 LIGHTSYNC L910-005824 Whit ...\nდამატება\n89 ₾\n\nთვეში: 2 ₾ -დან\n\nLogitech Gaming Mouse G102 LIGHTSYNC L910-005801 Blue\nდამატება\n239 ₾\n\nთვეში: 6 ₾ -დან\n\nLogitech Gaming Mouse G502 HERO L910-005470 Black\nდამატება\n199 ₾\n\nთვეში: 5 ₾ -დან\n\nHyperX Pulsefire Haste 2 core Wireless Black\nდამატება\n199 ₾\n\nთვეში: 5 ₾ -დან\n\nHyperX Pulsefire Haste 2 core Wireless White\nდამატება\n59 ₾\n\nთვეში: 1 ₾ -დან\n\nHavit Gaming Mouse HV-MS954 Black\nდამატება\n39 ₾\n\nთვეში: 1 ₾ -დან\n\nHavit Gaming Mouse HV-MS1033 White\nდამატება\n39 ₾\n\nთვეში: 1 ₾ -დან\n\nHavit Gaming Mouse HV-MS1029 Pink\nდამატება\n59 ₾\n\nთვეში: 1 ₾ -დან\n\nHavit Gaming Mouse HV-MS966 Black/Green\nდამატება\n49 ₾\n\nთვეში: 1 ₾ -დან\n\nHavit Wireless Mouse HV-MS1039W Black/White\nდამატება\n79 ₾\n\nთვეში: 2 ₾ -დან\n\nHavit Wireless Mouse HV-MS970WB Pro Black\nდამატება\n79 ₾\n\nთვეში: 2 ₾ -დან\n\nHavit Wireless Mouse HV-MS970WB Pro Transparent White\nდამატება\n219 ₾\n\nთვეში: 6 ₾ -დან\n\nRazer Gaming Mouse Orochi V2 WL Pink\nდამატება\nპროდუქტის შესახებ\n\n თუ ეძებთ ლეპტოპს, რომელიც მარტივად გაუმკლავდება ყველაზე მოთხოვნად თამაშებს —  Asus TUF F16 FX608JMR-RV073 Grey შექმნილია სწორედ თქვენთვის. ეს მოდელი აერთიანებს მაღალ წარმადობას, გამძლე კ...\n\nმეტის ნახვა\nმსგავსი პროდუქტები\n2599 ₾\n2799 ₾\n\nთვეში: 72 ₾ -დან\n\nAsus TUF 15 FX507ZC4-HN009 Black\nდამატება\n2249 ₾\n2499 ₾\n\nთვეში: 62 ₾ -დან\n\nAsus TUF 15 FA506NF-HN018, AMD Ryzen 5-7535HS, NVIDIA ...\nდამატება\n2999 ₾\n3699 ₾\n\nთვეში: 83 ₾ -დან\n\nAsus TUF 15 FA507NUR-LP044 Mercha Grey\nდამატება\n3299 ₾\n3499 ₾\n\nთვეში: 91 ₾ -დან\n\nAsus TUF 14 FA401UU-RG013 Jaeger Grey\nდამატება\n4179 ₾\n\nთვეში: 116 ₾ -დან\n\nAsus TUF A16 FA608WV-QT053 Grey\nდამატება\n2179 ₾\n2279 ₾\n\nთვეში: 60 ₾ -დან\n\nAsus TUF 15 FA506NFR-HN021, AMD Ryzen 7 7435HS, Nvidi ...\nდამატება\n5599 ₾\n5899 ₾\n\nთვეში: 155 ₾ -დან\n\nAsus TUF 18 FA808UP-S8030 Grey\nდამატება\n7299 ₾\n\nთვეში: 202 ₾ -დან\n\nAsus ROG Strix 16 G615JPR-S5101 Grey\nდამატება\n10399 ₾\n10499 ₾\n\nთვეში: 288 ₾ -დან\n\nAsus ROG Strix 18 G835LR-SA005 Black\nდამატება\n15999 ₾\n\nთვეში: 444 ₾ -დან\n\nAsus ROG Strix 18 G835LX-SA034W Black\nდამატება\n6499 ₾\n\nთვეში: 180 ₾ -დან\n\nAsus ROG Strix 16 G614PR-RV007, AMD Ryzen 9-7940HX, N ...\nდამატება\n6699 ₾\n\nთვეში: 186 ₾ -დან\n\nAsus ROG Strix G16 G615JPR-RV113, Intel core i7-14650 ...\nდამატება\n8499 ₾\n\nთვეში: 236 ₾ -დან\n\nAsus ROG Strix G18 G815LR-S9085, Intel Core Ultra 9 2 ...\nდამატება\n2699 ₾\n\nთვეში: 74 ₾ -დან\n\nAsus TUF 16 FX607VJ-RL005, Intel Core 5-210H, Nvidia ...\nდამატება\n4199 ₾\n\nთვეში: 116 ₾ -დან\n\nAsus TUF F16 FX608JHR-RV035, Intel core i7-14650HX 16 ...\nდამატება\nდამატებითი მახასიათებლები\nბრენდი\nბრენდი:\n\t\nAsus\nმოდელი\nმოდელი:\n\t\nTUF 16\nტექნიკური მახასიათებლები\nცენტრალური პროცესორი:\n\t\nIntel Core i7-14650HX\n\n\nპროცესორის თაობა:\n\t\nIntel i7 14th Gen\n\n\nპროცესორის სიხშირე:\n\t\n3.7 GHz ~ 5.2 GHz\n\n\nბირთვების რაოდენობა:\n\t\n16\n\n\nნაკადების რაოდენობა:\n\t\n24\n\n\nგრაფიკული პროცესორი:\n\t\nNvidia GeForce RTX 5060\n\n\nგრაფიკული პროცესორის მეხსიერება:\n\t\n8 GB\n\n\nგრაფიკული პროცესორის ტიპი:\n\t\nარა ინტეგრირებული\n\n\nოპერაციული სისტემა:\n\t\nNo\n\n\nBluetooth:\n\t\n5.3\nეკრანი\nეკრანის ზომა:\n\t\n16 Inches\n\n\nრეზოლუცია:\n\t\nWUXGA\n\n\nეკრანის ტიპი:\n\t\nIPS\n\n\nსენსორული ეკრანი:\n\t\nNo\n\n\nგანახლების სიხშირე:\n\t\n165 Hz\nდამატებითი მახასიათებლები\nკლავიატურის განათება:\n\t\nYes\n\n\nNumpad:\n\t\nYes\n\n\nდისკის წამკითხველი:\n\t\nNo\n\n\nვებ კამერა:\n\t\nYes\n\n\nლეპტოპის ტიპი:\n\t\nგეიმინგი\nმეხსიერება\nშიდა მეხსიერება:\n\t\n1 TB\n\n\nშიდა მეხსიერების ტიპი:\n\t\nSSD\n\n\nშიდა მეხსიერების ინტერფეისი:\n\t\nM.2\n\n\nოპერატიული მეხსიერება:\n\t\n32 GB\n\n\nოპერატიული მეხსიერების ტიპი:\n\t\nDDR5\n\n\nოპერატიული მეხსიერების სიხშირე:\n\t\n5600 MHz\nპორტები\nUSB:\n\t\n3 x USB-A\n\n\nType-C:\n\t\n1x\n\n\nType-C პორტით დამუხტვა:\n\t\nNo\n\n\nHDMI:\n\t\nYes\n\n\nლან პორტი:\n\t\nYes\n\n\n3.5mm:\n\t\nYes\nზომა/წონა\nწონა:\n\t\n2.40 kg\nფერი\nფერი:\n\t\ntitan grey\nმეტის ნახვა\nგაეცანი საგარანტიო პირობებს\nსაგარანტიო პირობები\nფილიალები\nმარაგშია\nშეკვეთიდან 2-5 დღეში\nზუმერის City Mall საბურთალო-ს ფილიალი\n\nთბილისი - \"სითი მოლი\" - პეტრე ქავთარაძის N1\n\nმარაგშია\n+995 591 971 962\nორშ-შაბ: 10:00:00 - 22:00:00\nკვირა: 10:00:00 - 22:00:00\nზუმერის ისთ ფოინთის ფილიალი\n\nთბილისი - \"ისთ ფოინთი\" - ალ. თვალჭრელიძე N2\n\nმარაგშია\n+995 591 340 476\nორშ-შაბ: 10:00:00 - 22:00:00\nკვირა: 10:00:00 - 22:00:00\nბათუმი ჭავჭავაძის ფილიალი\n\nბათუმი - ბათუმი, ჭავჭავაძის N21\n\nმარაგშია\n+995 591 967 606\nორშ-შაბ: 10:00:00 - 20:00:00\nკვირა: 10:00:00 - 19:00:00\nბათუმის გრანდ მოლის ფილიალი\n\nბათუმი - \"გრანდ მოლი\" - შერიფ ხიმშიაშვილის 29\n\nმარაგშია\n+995 591 022 872\nორშ-შაბ: 10:00:00 - 22:00:00\nკვირა: 10:00:00 - 22:00:00\n4999 ₾\n\nთვეში: 138.9 ₾ -დან\n\nმარაგი ფილიალებში\nფასის დაზღვევა\nფასის კონტროლი\nფასის დაჯავშნა\nყიდვა\nშედარება\nდამატება\nნავიგაცია\nგადახდები\nგამოგვყევი\n\nFacebook\n\nYoutube\n\nInstagram\n\nTik Tok\n\nკონტაქტი\n\nInfo@zoommer.ge\n\n+995 (32) 2 60 30 60 / *7007\n\nფილიალები\n\nკორპორატიული გაყიდვები\n\nZoommer App\n\nCopyright © 2023 Zoommer.ge. All rights reserved.\n\nCookie პოლიტიკა\n\nსაიტით სარგებლობის გაგრძელებით, შენ ეთანხმები Cookie ჩანაწერების გამოყენებას. მეტი ინფორმაცისათვის იხილეთ კონფიდენციალურობის პოლიტიკა\n\nგასაგებია",
    "specs": {
      "ბრენდი:": "Asus",
      "მოდელი:": "TUF 16",
      "ცენტრალური პროცესორი:": "Intel Core i7-14650HX",
      "პროცესორის თაობა:": "Intel i7 14th Gen",
      "პროცესორის სიხშირე:": "3.7 GHz ~ 5.2 GHz",
      "ბირთვების რაოდენობა:": "16",
      "ნაკადების რაოდენობა:": "24",
      "გრაფიკული პროცესორი:": "Nvidia GeForce RTX 5060",
      "გრაფიკული პროცესორის მეხსიერება:": "8 GB",
      "გრაფიკული პროცესორის ტიპი:": "არა ინტეგრირებული",
      "ოპერაციული სისტემა:": "No",
      "Bluetooth:": "5.3",
      "ეკრანის ზომა:": "16 Inches",
      "რეზოლუცია:": "WUXGA",
      "ეკრანის ტიპი:": "IPS",
      "სენსორული ეკრანი:": "No",
      "განახლების სიხშირე:": "165 Hz",
      "კლავიატურის განათება:": "Yes",
      "Numpad:": "Yes",
      "დისკის წამკითხველი:": "No",
      "ვებ კამერა:": "Yes",
      "ლეპტოპის ტიპი:": "გეიმინგი",
      "შიდა მეხსიერება:": "1 TB",
      "შიდა მეხსიერების ტიპი:": "SSD",
      "შიდა მეხსიერების ინტერფეისი:": "M.2",
      "ოპერატიული მეხსიერება:": "32 GB",
      "ოპერატიული მეხსიერების ტიპი:": "DDR5",
      "ოპერატიული მეხსიერების სიხშირე:": "5600 MHz",
      "USB:": "3 x USB-A",
      "Type-C:": "1x",
      "Type-C პორტით დამუხტვა:": "No",
      "HDMI:": "Yes",
      "ლან პორტი:": "Yes",
      "3.5mm:": "Yes",
      "წონა:": "2.40 kg",
      "ფერი:": "titan grey"
    }
  },
  {
    "category": "Gaming ლეპტოპები",
    "title": "Asus ROG Strix G18 G815LR-S9085, Intel Core Ultra 9 2 ...",
    "price": 8499.0,
    "link": "https://zoommer.ge/leptopebi/asus-rog-strix-g18-g815lr-s9085-intel-core-ultra-9-275hx-24c-nvidia-geforce-rtx-p48863",
    "image": "/_next/image?url=https%3A%2F%2Fs3.zoommer.ge%2Fsite%2F1fefbe8e-ae19-4fcd-9226-e8c88741219e_Thumb.jpeg&w=384&q=50",
    "product_title_detail": "Asus ROG Strix G18 G815LR-S9085, Intel Core Ultra 9 275HX 24c, Nvidia GeForce RTX 5070 Ti 12GB, 32GB RAM SSD 1TB, Free Dos, ლეპტოპი",
    "description": "*7007 / +995 (32) 2 60 30 60\nსავაჭრო პოლიტიკა\nგანვადება\nკარიერა\nTrade In\nფილიალები\nნავიგაცია\nკალათა\nშესვლა\n%\nმთავარი\nლეპტოპები\nAsus\n#ZOOM-037005\nAsus ROG Strix G18 G815LR-S9085, Intel Core Ultra 9 275HX 24c, Nvidia GeForce RTX 5070 Ti 12GB, 32GB RAM SSD 1TB, Free Dos, ლეპტოპი\nეკრანის ზომა\n18 Inches\nრეზოლუცია\n2.5K\nეკრანის ტიპი\nIPS\nგანახლების სიხშირე\n240 Hz\nშიდა მეხსიერება\n1 TB\nBluetooth\n5.4\nType-C\n2x\nოპერატიული მეხსიერება\n32 GB\nერთად იაფია\nდაამატე ნივთი\nAsus ROG Strix G18 G815LR-S9085, Intel Core Ultra 9 275HX 24c, Nvidia GeForce RTX 5070 Ti 12GB, 32GB RAM SSD 1TB, Free Dos, ლეპტოპი\n8499 ₾\nRazer Gaming Mouse DeathAdder Essential USB White\n52 ₾\n65 ₾\nHavit Gaming Cooling Pad HV-F2083 Black\n75.65 ₾\n89 ₾\nჯამური ფასი (2)\n8626.65 ₾\n8653 ₾\nყიდვა\nაქსესუარები\nაღწერა\nმსგავსი\nმახასიათებლები\nფილიალები\nაქსესუარები\nაღწერა\nმსგავსი\nმახასიათებლები\nფილიალები\n89 ₾\n\nთვეში: 2 ₾ -დან\n\nHavit Gaming Cooling Pad HV-F2083 Black\nდამატება\n219 ₾\n\nთვეში: 6 ₾ -დან\n\nRazer Gaming Mouse Orochi V2 WL Black\nდამატება\n59 ₾\n\nთვეში: 1 ₾ -დან\n\nHavit Gaming mouse Pad HV-MP901\nდამატება\n69 ₾\n\nთვეში: 1 ₾ -დან\n\nXiaomi Mi Router 4A DVB4230GL White\nდამატება\n219 ₾\n\nთვეში: 6 ₾ -დან\n\nRazer Gaming Mouse Orochi V2 WL White\nდამატება\n9 ₾\n\nHavit Gaming mouse Pad HV-MP838\nდამატება\n85 ₾\n\nთვეში: 2 ₾ -დან\n\nTP-Link Archer C50 AC1200 White\nდამატება\n209 ₾\n\nთვეში: 5 ₾ -დან\n\nRazer Gaming Mouse DeathAdder V2 X Hyperspeed WL/BT/U ...\nდამატება\n29 ₾\n\nRazer Mouse Pad Goliathus Mobile Black/Green\nდამატება\n119 ₾\n\nთვეში: 3 ₾ -დან\n\nTP-Link Archer C6 AC1200 Black\nდამატება\n139 ₾\n\nთვეში: 3 ₾ -დან\n\nLogitech Gaming Mouse G402 Hyperion Fury black\nდამატება\n29 ₾\n\nRazer Mouse Pad Goliathus Mobile Stealth Edition Blac ...\nდამატება\n159 ₾\n\nთვეში: 4 ₾ -დან\n\nXiaomi Router AX1500 White\nდამატება\n29 ₾\n\nHavit Gaming Mouse HV-MS1010 Black\nდამატება\n59 ₾\n\nთვეში: 1 ₾ -დან\n\nRazer Mouse Pad Gigantus V2 Large Black\nდამატება\n179 ₾\n\nთვეში: 4 ₾ -დან\n\nXiaomi Mesh System AX3000 NE 1 pack White\nდამატება\n79 ₾\n\nთვეში: 2 ₾ -დან\n\nRazer Gaming Mouse DeathAdder Essential USB Black\nდამატება\n49 ₾\n\nთვეში: 1 ₾ -დან\n\nRazer Mouse Pad Gigantus V2 Medium Black\nდამატება\n299 ₾\n\nთვეში: 8 ₾ -დან\n\nXiaomi Mesh System AX3000 NE 2 pack White\nდამატება\n119 ₾\n\nთვეში: 3 ₾ -დან\n\nHyperX Pulsefire Surge Mouse Black\nდამატება\n9 ₾\n\nHavit Gaming mouse Pad HV-MP843 Black\nდამატება\n249 ₾\n\nთვეში: 6 ₾ -დან\n\nXiaomi Router BE3600 White\nდამატება\n469 ₾\n\nთვეში: 13 ₾ -დან\n\nHP OMEN PHOTON Wireless Mouse 6CL96AA Black\nდამატება\n149 ₾\n\nთვეში: 4 ₾ -დან\n\nRazer Mouse Pad Firefly V2 RGB M Black\nდამატება\n65 ₾\n\nთვეში: 1 ₾ -დან\n\nRazer Gaming Mouse DeathAdder Essential USB White\nდამატება\n199 ₾\n\nთვეში: 5 ₾ -დან\n\nRazer Mouse Pad Goliathus Extended Chroma XXL Black\nდამატება\n239 ₾\n\nთვეში: 6 ₾ -დან\n\nRazer Gaming Mouse Basilisk V3 Black\nდამატება\n149 ₾\n\nთვეში: 4 ₾ -დან\n\nHyperX Pulsefire Mat RGB Black\nდამატება\n299 ₾\n\nთვეში: 8 ₾ -დან\n\nRazer Gaming Mouse Naga V2 HyperSpeed WL Black\nდამატება\n29 ₾\n\nHavit Gaming Mouse Pad HV-MP845 Black\nდამატება\n229 ₾\n\nთვეში: 6 ₾ -დან\n\nRazer Gaming Mouse Basilisk V3 X HyperSpeed WL Black\nდამატება\n29 ₾\n\nHavit Gaming Mouse Pad HV-MP847 Pink\nდამატება\n129 ₾\n\nთვეში: 3 ₾ -დან\n\nRazer Gaming Mouse Cobra Black\nდამატება\n29 ₾\n\nHavit Gaming Mouse Pad HV-MP849 Black\nდამატება\n19 ₾\n\nHavit Gaming Mouse HV-MS989GT Black/Red\nდამატება\n49 ₾\n\nთვეში: 1 ₾ -დან\n\nHyperX Pulsefire Mat M Black\nდამატება\n19 ₾\n\nHavit Gaming Mouse HV-MS626GT Black\nდამატება\n59 ₾\n\nთვეში: 1 ₾ -დან\n\nHyperX Pulsefire Mat L Black\nდამატება\n19 ₾\n\nHavit Gaming Mouse HV-MS66GT White/Blue\nდამატება\n39 ₾\n\nთვეში: 1 ₾ -დან\n\nRazer Mouse Pad Sphex V3 S Black\nდამატება\n149 ₾\n\nთვეში: 4 ₾ -დან\n\nHyperX Gaming Mouse Pulsefire Haste 2 Black\nდამატება\n89 ₾\n\nთვეში: 2 ₾ -დან\n\nRazer Mouse Pad Sphex V3 L Black\nდამატება\n19 ₾\n\nHavit Wireless Mouse HV-MS66GT Black\nდამატება\n29 ₾\n\nHavit Gaming mouse Pad HV-MP860\nდამატება\n179 ₾\n\nთვეში: 4 ₾ -დან\n\nLogitech Gaming Mouse G305 LIGHTSPEED WL L910-005282 ...\nდამატება\n25 ₾\n\nHavit Gaming mouse Pad HV-MP861\nდამატება\n259 ₾\n\nთვეში: 7 ₾ -დან\n\nLogitech Gaming Mouse G502 X L910-006138 Black\nდამატება\n99 ₾\n\nთვეში: 2 ₾ -დან\n\nSpigen Desk Pad Black with Magnetic Cable Holder LD30 ...\nდამატება\n259 ₾\n\nთვეში: 7 ₾ -დან\n\nLogitech Gaming Mouse G502 X L910-006138 White\nდამატება\n19 ₾\n\nHavit Gaming Mouse HV-MS626GT Black/Red\nდამატება\n19 ₾\n\nHavit Gaming Mouse HV-MS626GT Black/Blue\nდამატება\n349 ₾\n\nთვეში: 9 ₾ -დან\n\nLogitech Gaming Mouse G703 LIGHTSPEED WL L910-005640 ...\nდამატება\n89 ₾\n\nთვეში: 2 ₾ -დან\n\nLogitech Gaming Mouse G102 LIGHTSYNC L910-005823 Blac ...\nდამატება\n89 ₾\n\nთვეში: 2 ₾ -დან\n\nLogitech Gaming Mouse G102 LIGHTSYNC L910-005824 Whit ...\nდამატება\n89 ₾\n\nთვეში: 2 ₾ -დან\n\nLogitech Gaming Mouse G102 LIGHTSYNC L910-005801 Blue\nდამატება\n239 ₾\n\nთვეში: 6 ₾ -დან\n\nLogitech Gaming Mouse G502 HERO L910-005470 Black\nდამატება\n199 ₾\n\nთვეში: 5 ₾ -დან\n\nHyperX Pulsefire Haste 2 core Wireless Black\nდამატება\n199 ₾\n\nთვეში: 5 ₾ -დან\n\nHyperX Pulsefire Haste 2 core Wireless White\nდამატება\n59 ₾\n\nთვეში: 1 ₾ -დან\n\nHavit Gaming Mouse HV-MS954 Black\nდამატება\n39 ₾\n\nთვეში: 1 ₾ -დან\n\nHavit Gaming Mouse HV-MS1033 White\nდამატება\n39 ₾\n\nთვეში: 1 ₾ -დან\n\nHavit Gaming Mouse HV-MS1029 Pink\nდამატება\n59 ₾\n\nთვეში: 1 ₾ -დან\n\nHavit Gaming Mouse HV-MS966 Black/Green\nდამატება\n49 ₾\n\nთვეში: 1 ₾ -დან\n\nHavit Wireless Mouse HV-MS1039W Black/White\nდამატება\n79 ₾\n\nთვეში: 2 ₾ -დან\n\nHavit Wireless Mouse HV-MS970WB Pro Black\nდამატება\n79 ₾\n\nთვეში: 2 ₾ -დან\n\nHavit Wireless Mouse HV-MS970WB Pro Transparent White\nდამატება\n219 ₾\n\nთვეში: 6 ₾ -დან\n\nRazer Gaming Mouse Orochi V2 WL Pink\nდამატება\nპროდუქტის შესახებ\n\n თუ ეძებთ ლეპტოპს, რომელიც მარტივად გაუმკლავდება ყველაზე მოთხოვნად თამაშებს —  Asus ROG Strix G18 G815LR-S9085 Grey შექმნილია სწორედ თქვენთვის. ეს მოდელი აერთიანებს მაღალ წარმადობას, გამძ...\n\nმეტის ნახვა\nმსგავსი პროდუქტები\n2599 ₾\n2799 ₾\n\nთვეში: 72 ₾ -დან\n\nAsus TUF 15 FX507ZC4-HN009 Black\nდამატება\n2249 ₾\n2499 ₾\n\nთვეში: 62 ₾ -დან\n\nAsus TUF 15 FA506NF-HN018, AMD Ryzen 5-7535HS, NVIDIA ...\nდამატება\n2999 ₾\n3699 ₾\n\nთვეში: 83 ₾ -დან\n\nAsus TUF 15 FA507NUR-LP044 Mercha Grey\nდამატება\n3299 ₾\n3499 ₾\n\nთვეში: 91 ₾ -დან\n\nAsus TUF 14 FA401UU-RG013 Jaeger Grey\nდამატება\n4179 ₾\n\nთვეში: 116 ₾ -დან\n\nAsus TUF A16 FA608WV-QT053 Grey\nდამატება\n2179 ₾\n2279 ₾\n\nთვეში: 60 ₾ -დან\n\nAsus TUF 15 FA506NFR-HN021, AMD Ryzen 7 7435HS, Nvidi ...\nდამატება\n5599 ₾\n5899 ₾\n\nთვეში: 155 ₾ -დან\n\nAsus TUF 18 FA808UP-S8030 Grey\nდამატება\n7299 ₾\n\nთვეში: 202 ₾ -დან\n\nAsus ROG Strix 16 G615JPR-S5101 Grey\nდამატება\n10399 ₾\n10499 ₾\n\nთვეში: 288 ₾ -დან\n\nAsus ROG Strix 18 G835LR-SA005 Black\nდამატება\n15999 ₾\n\nთვეში: 444 ₾ -დან\n\nAsus ROG Strix 18 G835LX-SA034W Black\nდამატება\n6499 ₾\n\nთვეში: 180 ₾ -დან\n\nAsus ROG Strix 16 G614PR-RV007, AMD Ryzen 9-7940HX, N ...\nდამატება\n6699 ₾\n\nთვეში: 186 ₾ -დან\n\nAsus ROG Strix G16 G615JPR-RV113, Intel core i7-14650 ...\nდამატება\n4999 ₾\n\nთვეში: 138 ₾ -დან\n\nAsus TUF F16 FX608JMR-RV073, Intel core i7-14650HX 16 ...\nდამატება\n2699 ₾\n\nთვეში: 74 ₾ -დან\n\nAsus TUF 16 FX607VJ-RL005, Intel Core 5-210H, Nvidia ...\nდამატება\n4199 ₾\n\nთვეში: 116 ₾ -დან\n\nAsus TUF F16 FX608JHR-RV035, Intel core i7-14650HX 16 ...\nდამატება\nდამატებითი მახასიათებლები\nბრენდი\nბრენდი:\n\t\nAsus\nმოდელი\nმოდელი:\n\t\nROG\nტექნიკური მახასიათებლები\nცენტრალური პროცესორი:\n\t\nIntel Core Ultra 9-275HX\n\n\nპროცესორის თაობა:\n\t\nIntel Ultra 9 Series 2\n\n\nპროცესორის სიხშირე:\n\t\n2.1 GHz ~ 5.4 GHz\n\n\nბირთვების რაოდენობა:\n\t\n24\n\n\nნაკადების რაოდენობა:\n\t\n24\n\n\nგრაფიკული პროცესორი:\n\t\nNvidia GeForce RTX 5070 Ti\n\n\nგრაფიკული პროცესორის მეხსიერება:\n\t\n12 GB\n\n\nგრაფიკული პროცესორის ტიპი:\n\t\nარა ინტეგრირებული\n\n\nოპერაციული სისტემა:\n\t\nNo\n\n\nBluetooth:\n\t\n5.4\nეკრანი\nეკრანის ზომა:\n\t\n18 Inches\n\n\nრეზოლუცია:\n\t\n2.5K\n\n\nეკრანის ტიპი:\n\t\nIPS\n\n\nსენსორული ეკრანი:\n\t\nNo\n\n\nგანახლების სიხშირე:\n\t\n240 Hz\nდამატებითი მახასიათებლები\nკლავიატურის განათება:\n\t\nYes\n\n\nNumpad:\n\t\nYes\n\n\nდისკის წამკითხველი:\n\t\nNo\n\n\nვებ კამერა:\n\t\nYes\n\n\nლეპტოპის ტიპი:\n\t\nგეიმინგი\nმეხსიერება\nშიდა მეხსიერება:\n\t\n1 TB\n\n\nშიდა მეხსიერების ტიპი:\n\t\nSSD\n\n\nშიდა მეხსიერების ინტერფეისი:\n\t\nM.2\n\n\nოპერატიული მეხსიერება:\n\t\n32 GB\n\n\nოპერატიული მეხსიერების ტიპი:\n\t\nDDR5\n\n\nოპერატიული მეხსიერების სიხშირე:\n\t\n5600 MHz\nპორტები\nUSB:\n\t\n2 x USB-A\n\n\nType-C:\n\t\n2x\n\n\nType-C პორტით დამუხტვა:\n\t\nNo\n\n\nHDMI:\n\t\nYes\n\n\nლან პორტი:\n\t\nYes\n\n\n3.5mm:\n\t\nYes\nზომა/წონა\nწონა:\n\t\n3.42 kg\nფერი\nფერი:\n\t\ntitan grey\nმეტის ნახვა\nგაეცანი საგარანტიო პირობებს\nსაგარანტიო პირობები\nფილიალები\nმარაგშია\nშეკვეთიდან 2-5 დღეში\nზუმერის City Mall საბურთალო-ს ფილიალი\n\nთბილისი - \"სითი მოლი\" - პეტრე ქავთარაძის N1\n\nმარაგშია\n+995 591 971 962\nორშ-შაბ: 10:00:00 - 22:00:00\nკვირა: 10:00:00 - 22:00:00\n8499 ₾\n\nთვეში: 236.1 ₾ -დან\n\nმარაგი ფილიალებში\nფასის დაზღვევა\nფასის კონტროლი\nფასის დაჯავშნა\nყიდვა\nშედარება\nდამატება\nნავიგაცია\n\nპერსონალურ მონაცემთა დაცვის პოლიტიკა\n\nჩვენ შესახებ\n\nწესები და პირობები\n\nმიწოდების სერვისი\n\nკარიერა\n\nგადახდები\n\nSetanta Sports\n\nგადახდის მეთოდები\n\nგარანტია\n\nგანვადება\n\nნივთის დაბრუნება\n\nნივთის ონლაინ ყიდვის ინსტრუქცია\n\nგამოგვყევი\n\nFacebook\n\nYoutube\n\nInstagram\n\nTik Tok\n\nკონტაქტი\n\nInfo@zoommer.ge\n\n+995 (32) 2 60 30 60 / *7007\n\nფილიალები\n\nკორპორატიული გაყიდვები\n\nZoommer App\n\nCopyright © 2023 Zoommer.ge. All rights reserved.\n\nCookie პოლიტიკა\n\nსაიტით სარგებლობის გაგრძელებით, შენ ეთანხმები Cookie ჩანაწერების გამოყენებას. მეტი ინფორმაცისათვის იხილეთ კონფიდენციალურობის პოლიტიკა\n\nგასაგებია",
    "specs": {
      "ბრენდი:": "Asus",
      "მოდელი:": "ROG",
      "ცენტრალური პროცესორი:": "Intel Core Ultra 9-275HX",
      "პროცესორის თაობა:": "Intel Ultra 9 Series 2",
      "პროცესორის სიხშირე:": "2.1 GHz ~ 5.4 GHz",
      "ბირთვების რაოდენობა:": "24",
      "ნაკადების რაოდენობა:": "24",
      "გრაფიკული პროცესორი:": "Nvidia GeForce RTX 5070 Ti",
      "გრაფიკული პროცესორის მეხსიერება:": "12 GB",
      "გრაფიკული პროცესორის ტიპი:": "არა ინტეგრირებული",
      "ოპერაციული სისტემა:": "No",
      "Bluetooth:": "5.4",
      "ეკრანის ზომა:": "18 Inches",
      "რეზოლუცია:": "2.5K",
      "ეკრანის ტიპი:": "IPS",
      "სენსორული ეკრანი:": "No",
      "განახლების სიხშირე:": "240 Hz",
      "კლავიატურის განათება:": "Yes",
      "Numpad:": "Yes",
      "დისკის წამკითხველი:": "No",
      "ვებ კამერა:": "Yes",
      "ლეპტოპის ტიპი:": "გეიმინგი",
      "შიდა მეხსიერება:": "1 TB",
      "შიდა მეხსიერების ტიპი:": "SSD",
      "შიდა მეხსიერების ინტერფეისი:": "M.2",
      "ოპერატიული მეხსიერება:": "32 GB",
      "ოპერატიული მეხსიერების ტიპი:": "DDR5",
      "ოპერატიული მეხსიერების სიხშირე:": "5600 MHz",
      "USB:": "2 x USB-A",
      "Type-C:": "2x",
      "Type-C პორტით დამუხტვა:": "No",
      "HDMI:": "Yes",
      "ლან პორტი:": "Yes",
      "3.5mm:": "Yes",
      "წონა:": "3.42 kg",
      "ფერი:": "titan grey"
    }
  },
  {
    "category": "Gaming ლეპტოპები",
    "title": "Asus ROG Strix G16 G615JPR-RV113, Intel core i7-14650 ...",
    "price": 6699.0,
    "link": "https://zoommer.ge/leptopebi/asus-rog-strix-g16-g615jpr-rv113-intel-core-i7-14650hx-16c-nvidia-geforce-rtx-5-p48862",
    "image": "/_next/image?url=https%3A%2F%2Fs3.zoommer.ge%2Fsite%2F04b76f7b-6257-4ab1-a8f1-3868823eeef0_Thumb.jpeg&w=384&q=50",
    "product_title_detail": "Asus ROG Strix G16 G615JPR-RV113, Intel core i7-14650HX 16C, Nvidia GeForce RTX 5070 8GB, 32GB RAM SSD 1TB, Free Dos, ლეპტოპი",
    "description": "*7007 / +995 (32) 2 60 30 60\nსავაჭრო პოლიტიკა\nგანვადება\nკარიერა\nTrade In\nფილიალები\nნავიგაცია\nკალათა\nშესვლა\n%\nმთავარი\nლეპტოპები\nAsus\n#ZOOM-037004\nAsus ROG Strix G16 G615JPR-RV113, Intel core i7-14650HX 16C, Nvidia GeForce RTX 5070 8GB, 32GB RAM SSD 1TB, Free Dos, ლეპტოპი\nეკრანის ზომა\n16 Inches\nრეზოლუცია\nWUXGA\nეკრანის ტიპი\nIPS\nგანახლების სიხშირე\n240 Hz\nშიდა მეხსიერება\n1 TB\nBluetooth\n5.4\nType-C\n1x\nოპერატიული მეხსიერება\n32 GB\nერთად იაფია\nდაამატე ნივთი\nAsus ROG Strix G16 G615JPR-RV113, Intel core i7-14650HX 16C, Nvidia GeForce RTX 5070 8GB, 32GB RAM SSD 1TB, Free Dos, ლეპტოპი\n6699 ₾\nRivacase 8057 Laptop Bag 16 Black\n58.65 ₾\n69 ₾\nRazer Gaming Mouse DeathAdder Essential USB White\n52 ₾\n65 ₾\nHavit Gaming Cooling Pad HV-F2083 Black\n75.65 ₾\n89 ₾\nჯამური ფასი (3)\n6885.3 ₾\n6922 ₾\nყიდვა\nაქსესუარები\nაღწერა\nმსგავსი\nმახასიათებლები\nფილიალები\nაქსესუარები\nაღწერა\nმსგავსი\nმახასიათებლები\nფილიალები\n89 ₾\n\nთვეში: 2 ₾ -დან\n\nHavit Gaming Cooling Pad HV-F2083 Black\nდამატება\n69 ₾\n\nთვეში: 1 ₾ -დან\n\nRivacase 8057 Laptop Bag 16 Black\nდამატება\n219 ₾\n\nთვეში: 6 ₾ -დან\n\nRazer Gaming Mouse Orochi V2 WL Black\nდამატება\n59 ₾\n\nთვეში: 1 ₾ -დან\n\nHavit Gaming mouse Pad HV-MP901\nდამატება\n69 ₾\n\nთვეში: 1 ₾ -დან\n\nXiaomi Mi Router 4A DVB4230GL White\nდამატება\n79 ₾\n\nთვეში: 2 ₾ -დან\n\nRivacase 7531 Eco Laptop Bag 15 Black\nდამატება\n219 ₾\n\nთვეში: 6 ₾ -დან\n\nRazer Gaming Mouse Orochi V2 WL White\nდამატება\n9 ₾\n\nHavit Gaming mouse Pad HV-MP838\nდამატება\n85 ₾\n\nთვეში: 2 ₾ -დან\n\nTP-Link Archer C50 AC1200 White\nდამატება\n89 ₾\n\nთვეში: 2 ₾ -დან\n\nTomtoc Defender A13 Laptop Sleeve Kit 16 A13F2DV Blac ...\nდამატება\n209 ₾\n\nთვეში: 5 ₾ -დან\n\nRazer Gaming Mouse DeathAdder V2 X Hyperspeed WL/BT/U ...\nდამატება\n29 ₾\n\nRazer Mouse Pad Goliathus Mobile Black/Green\nდამატება\n119 ₾\n\nთვეში: 3 ₾ -დან\n\nTP-Link Archer C6 AC1200 Black\nდამატება\n119 ₾\n\nთვეში: 3 ₾ -დან\n\nTomtoc Defender A42 Laptop Briefcase 16 A42F2B1 Navy ...\nდამატება\n139 ₾\n\nთვეში: 3 ₾ -დან\n\nLogitech Gaming Mouse G402 Hyperion Fury black\nდამატება\n29 ₾\n\nRazer Mouse Pad Goliathus Mobile Stealth Edition Blac ...\nდამატება\n159 ₾\n\nთვეში: 4 ₾ -დან\n\nXiaomi Router AX1500 White\nდამატება\n119 ₾\n\nთვეში: 3 ₾ -დან\n\nTomtoc Defender A42 Laptop Briefcase 16 A42F2D1 Black\nდამატება\n29 ₾\n\nHavit Gaming Mouse HV-MS1010 Black\nდამატება\n59 ₾\n\nთვეში: 1 ₾ -დან\n\nRazer Mouse Pad Gigantus V2 Large Black\nდამატება\n179 ₾\n\nთვეში: 4 ₾ -დან\n\nXiaomi Mesh System AX3000 NE 1 pack White\nდამატება\n89 ₾\n\nთვეში: 2 ₾ -დან\n\nUniq Dfender Tough Laptop Sleeve 16 Inch Marl Grey\nდამატება\n79 ₾\n\nთვეში: 2 ₾ -დან\n\nRazer Gaming Mouse DeathAdder Essential USB Black\nდამატება\n49 ₾\n\nთვეში: 1 ₾ -დან\n\nRazer Mouse Pad Gigantus V2 Medium Black\nდამატება\n299 ₾\n\nთვეში: 8 ₾ -დან\n\nXiaomi Mesh System AX3000 NE 2 pack White\nდამატება\n89 ₾\n\nთვეში: 2 ₾ -დან\n\nUniq Dfender Tough Laptop Sleeve 16 Inch Black\nდამატება\n119 ₾\n\nთვეში: 3 ₾ -დან\n\nHyperX Pulsefire Surge Mouse Black\nდამატება\n9 ₾\n\nHavit Gaming mouse Pad HV-MP843 Black\nდამატება\n249 ₾\n\nთვეში: 6 ₾ -დან\n\nXiaomi Router BE3600 White\nდამატება\n99 ₾\n\nთვეში: 2 ₾ -დან\n\nDell EcoLoop Essential Backpack 14-16 460-BDSS Black\nდამატება\n469 ₾\n\nთვეში: 13 ₾ -დან\n\nHP OMEN PHOTON Wireless Mouse 6CL96AA Black\nდამატება\n149 ₾\n\nთვეში: 4 ₾ -დან\n\nRazer Mouse Pad Firefly V2 RGB M Black\nდამატება\n79 ₾\n\nთვეში: 2 ₾ -დან\n\nTomtoc Defender A13 Laptop Sleeve 16 A13F2D1 Black\nდამატება\n65 ₾\n\nთვეში: 1 ₾ -დან\n\nRazer Gaming Mouse DeathAdder Essential USB White\nდამატება\n199 ₾\n\nთვეში: 5 ₾ -დან\n\nRazer Mouse Pad Goliathus Extended Chroma XXL Black\nდამატება\n89 ₾\n\nთვეში: 2 ₾ -დან\n\nTomtoc Defender A14 Laptop Briefcase 16 A14F2D1 Black\nდამატება\n239 ₾\n\nთვეში: 6 ₾ -დან\n\nRazer Gaming Mouse Basilisk V3 Black\nდამატება\n149 ₾\n\nთვეში: 4 ₾ -დან\n\nHyperX Pulsefire Mat RGB Black\nდამატება\n299 ₾\n\nთვეში: 8 ₾ -დან\n\nRazer Gaming Mouse Naga V2 HyperSpeed WL Black\nდამატება\n29 ₾\n\nHavit Gaming Mouse Pad HV-MP845 Black\nდამატება\n229 ₾\n\nთვეში: 6 ₾ -დან\n\nRazer Gaming Mouse Basilisk V3 X HyperSpeed WL Black\nდამატება\n29 ₾\n\nHavit Gaming Mouse Pad HV-MP847 Pink\nდამატება\n129 ₾\n\nთვეში: 3 ₾ -დან\n\nRazer Gaming Mouse Cobra Black\nდამატება\n29 ₾\n\nHavit Gaming Mouse Pad HV-MP849 Black\nდამატება\n19 ₾\n\nHavit Gaming Mouse HV-MS989GT Black/Red\nდამატება\n49 ₾\n\nთვეში: 1 ₾ -დან\n\nHyperX Pulsefire Mat M Black\nდამატება\n19 ₾\n\nHavit Gaming Mouse HV-MS626GT Black\nდამატება\n59 ₾\n\nთვეში: 1 ₾ -დან\n\nHyperX Pulsefire Mat L Black\nდამატება\n19 ₾\n\nHavit Gaming Mouse HV-MS66GT White/Blue\nდამატება\n39 ₾\n\nთვეში: 1 ₾ -დან\n\nRazer Mouse Pad Sphex V3 S Black\nდამატება\n149 ₾\n\nთვეში: 4 ₾ -დან\n\nHyperX Gaming Mouse Pulsefire Haste 2 Black\nდამატება\n89 ₾\n\nთვეში: 2 ₾ -დან\n\nRazer Mouse Pad Sphex V3 L Black\nდამატება\n19 ₾\n\nHavit Wireless Mouse HV-MS66GT Black\nდამატება\n29 ₾\n\nHavit Gaming mouse Pad HV-MP860\nდამატება\n179 ₾\n\nთვეში: 4 ₾ -დან\n\nLogitech Gaming Mouse G305 LIGHTSPEED WL L910-005282 ...\nდამატება\n25 ₾\n\nHavit Gaming mouse Pad HV-MP861\nდამატება\n259 ₾\n\nთვეში: 7 ₾ -დან\n\nLogitech Gaming Mouse G502 X L910-006138 Black\nდამატება\n99 ₾\n\nთვეში: 2 ₾ -დან\n\nSpigen Desk Pad Black with Magnetic Cable Holder LD30 ...\nდამატება\n259 ₾\n\nთვეში: 7 ₾ -დან\n\nLogitech Gaming Mouse G502 X L910-006138 White\nდამატება\n19 ₾\n\nHavit Gaming Mouse HV-MS626GT Black/Red\nდამატება\n19 ₾\n\nHavit Gaming Mouse HV-MS626GT Black/Blue\nდამატება\n349 ₾\n\nთვეში: 9 ₾ -დან\n\nLogitech Gaming Mouse G703 LIGHTSPEED WL L910-005640 ...\nდამატება\n89 ₾\n\nთვეში: 2 ₾ -დან\n\nLogitech Gaming Mouse G102 LIGHTSYNC L910-005823 Blac ...\nდამატება\n89 ₾\n\nთვეში: 2 ₾ -დან\n\nLogitech Gaming Mouse G102 LIGHTSYNC L910-005824 Whit ...\nდამატება\n89 ₾\n\nთვეში: 2 ₾ -დან\n\nLogitech Gaming Mouse G102 LIGHTSYNC L910-005801 Blue\nდამატება\n239 ₾\n\nთვეში: 6 ₾ -დან\n\nLogitech Gaming Mouse G502 HERO L910-005470 Black\nდამატება\n199 ₾\n\nთვეში: 5 ₾ -დან\n\nHyperX Pulsefire Haste 2 core Wireless Black\nდამატება\n199 ₾\n\nთვეში: 5 ₾ -დან\n\nHyperX Pulsefire Haste 2 core Wireless White\nდამატება\n59 ₾\n\nთვეში: 1 ₾ -დან\n\nHavit Gaming Mouse HV-MS954 Black\nდამატება\n39 ₾\n\nთვეში: 1 ₾ -დან\n\nHavit Gaming Mouse HV-MS1033 White\nდამატება\n39 ₾\n\nთვეში: 1 ₾ -დან\n\nHavit Gaming Mouse HV-MS1029 Pink\nდამატება\n59 ₾\n\nთვეში: 1 ₾ -დან\n\nHavit Gaming Mouse HV-MS966 Black/Green\nდამატება\n49 ₾\n\nთვეში: 1 ₾ -დან\n\nHavit Wireless Mouse HV-MS1039W Black/White\nდამატება\n79 ₾\n\nთვეში: 2 ₾ -დან\n\nHavit Wireless Mouse HV-MS970WB Pro Black\nდამატება\n79 ₾\n\nთვეში: 2 ₾ -დან\n\nHavit Wireless Mouse HV-MS970WB Pro Transparent White\nდამატება\n219 ₾\n\nთვეში: 6 ₾ -დან\n\nRazer Gaming Mouse Orochi V2 WL Pink\nდამატება\nპროდუქტის შესახებ\n\n თუ ეძებთ ლეპტოპს, რომელიც მარტივად გაუმკლავდება ყველაზე მოთხოვნად თამაშებს —  Asus ROG Strix G16 G615JPR-RV113 Grey შექმნილია სწორედ თქვენთვის. ეს მოდელი აერთიანებს მაღალ წარმადობას, გამ...\n\nმეტის ნახვა\nმსგავსი პროდუქტები\n2599 ₾\n2799 ₾\n\nთვეში: 72 ₾ -დან\n\nAsus TUF 15 FX507ZC4-HN009 Black\nდამატება\n2249 ₾\n2499 ₾\n\nთვეში: 62 ₾ -დან\n\nAsus TUF 15 FA506NF-HN018, AMD Ryzen 5-7535HS, NVIDIA ...\nდამატება\n2999 ₾\n3699 ₾\n\nთვეში: 83 ₾ -დან\n\nAsus TUF 15 FA507NUR-LP044 Mercha Grey\nდამატება\n3299 ₾\n3499 ₾\n\nთვეში: 91 ₾ -დან\n\nAsus TUF 14 FA401UU-RG013 Jaeger Grey\nდამატება\n4179 ₾\n\nთვეში: 116 ₾ -დან\n\nAsus TUF A16 FA608WV-QT053 Grey\nდამატება\n2179 ₾\n2279 ₾\n\nთვეში: 60 ₾ -დან\n\nAsus TUF 15 FA506NFR-HN021, AMD Ryzen 7 7435HS, Nvidi ...\nდამატება\n5599 ₾\n5899 ₾\n\nთვეში: 155 ₾ -დან\n\nAsus TUF 18 FA808UP-S8030 Grey\nდამატება\n7299 ₾\n\nთვეში: 202 ₾ -დან\n\nAsus ROG Strix 16 G615JPR-S5101 Grey\nდამატება\n10399 ₾\n10499 ₾\n\nთვეში: 288 ₾ -დან\n\nAsus ROG Strix 18 G835LR-SA005 Black\nდამატება\n15999 ₾\n\nთვეში: 444 ₾ -დან\n\nAsus ROG Strix 18 G835LX-SA034W Black\nდამატება\n6499 ₾\n\nთვეში: 180 ₾ -დან\n\nAsus ROG Strix 16 G614PR-RV007, AMD Ryzen 9-7940HX, N ...\nდამატება\n8499 ₾\n\nთვეში: 236 ₾ -დან\n\nAsus ROG Strix G18 G815LR-S9085, Intel Core Ultra 9 2 ...\nდამატება\n4999 ₾\n\nთვეში: 138 ₾ -დან\n\nAsus TUF F16 FX608JMR-RV073, Intel core i7-14650HX 16 ...\nდამატება\n2699 ₾\n\nთვეში: 74 ₾ -დან\n\nAsus TUF 16 FX607VJ-RL005, Intel Core 5-210H, Nvidia ...\nდამატება\n4199 ₾\n\nთვეში: 116 ₾ -დან\n\nAsus TUF F16 FX608JHR-RV035, Intel core i7-14650HX 16 ...\nდამატება\nდამატებითი მახასიათებლები\nბრენდი\nბრენდი:\n\t\nAsus\nმოდელი\nმოდელი:\n\t\nROG\nტექნიკური მახასიათებლები\nცენტრალური პროცესორი:\n\t\nIntel Core i7-14650HX\n\n\nპროცესორის თაობა:\n\t\nIntel i7 14th Gen\n\n\nპროცესორის სიხშირე:\n\t\n3.7 GHz ~ 5.2 GHz\n\n\nბირთვების რაოდენობა:\n\t\n16\n\n\nნაკადების რაოდენობა:\n\t\n24\n\n\nგრაფიკული პროცესორი:\n\t\nNvidia GeForce RTX 5070\n\n\nგრაფიკული პროცესორის მეხსიერება:\n\t\n8 GB\n\n\nგრაფიკული პროცესორის ტიპი:\n\t\nარა ინტეგრირებული\n\n\nოპერაციული სისტემა:\n\t\nNo\n\n\nBluetooth:\n\t\n5.4\nეკრანი\nეკრანის ზომა:\n\t\n16 Inches\n\n\nრეზოლუცია:\n\t\nWUXGA\n\n\nეკრანის ტიპი:\n\t\nIPS\n\n\nსენსორული ეკრანი:\n\t\nNo\n\n\nგანახლების სიხშირე:\n\t\n240 Hz\nდამატებითი მახასიათებლები\nკლავიატურის განათება:\n\t\nYes\n\n\nNumpad:\n\t\nNo\n\n\nდისკის წამკითხველი:\n\t\nNo\n\n\nვებ კამერა:\n\t\nYes\n\n\nლეპტოპის ტიპი:\n\t\nგეიმინგი\nმეხსიერება\nშიდა მეხსიერება:\n\t\n1 TB\n\n\nშიდა მეხსიერების ტიპი:\n\t\nSSD\n\n\nშიდა მეხსიერების ინტერფეისი:\n\t\nM.2\n\n\nოპერატიული მეხსიერება:\n\t\n32 GB\n\n\nოპერატიული მეხსიერების ტიპი:\n\t\n-\n\n\nოპერატიული მეხსიერების სიხშირე:\n\t\n-\nპორტები\nUSB:\n\t\n2 x USB-A\n\n\nType-C:\n\t\n1x\n\n\nType-C პორტით დამუხტვა:\n\t\nNo\n\n\nHDMI:\n\t\nYes\n\n\nლან პორტი:\n\t\nYes\n\n\n3.5mm:\n\t\nYes\nზომა/წონა\nწონა:\n\t\n2.80 kg\nფერი\nფერი:\n\t\ntitan grey\nმეტის ნახვა\nგაეცანი საგარანტიო პირობებს\nსაგარანტიო პირობები\nფილიალები\nმარაგშია\nშეკვეთიდან 2-5 დღეში\nზუმერის ისთ ფოინთის ფილიალი\n\nთბილისი - \"ისთ ფოინთი\" - ალ. თვალჭრელიძე N2\n\nმარაგშია\n+995 591 340 476\nორშ-შაბ: 10:00:00 - 22:00:00\nკვირა: 10:00:00 - 22:00:00\nბათუმის გრანდ მოლის ფილიალი\n\nბათუმი - \"გრანდ მოლი\" - შერიფ ხიმშიაშვილის 29\n\nმარაგშია\n+995 591 022 872\nორშ-შაბ: 10:00:00 - 22:00:00\nკვირა: 10:00:00 - 22:00:00\n6699 ₾\n\nთვეში: 186.1 ₾ -დან\n\nმარაგი ფილიალებში\nფასის დაზღვევა\nფასის კონტროლი\nფასის დაჯავშნა\nყიდვა\nშედარება\nდამატება\nნავიგაცია\n\nპერსონალურ მონაცემთა დაცვის პოლიტიკა\n\nჩვენ შესახებ\n\nწესები და პირობები\n\nმიწოდების სერვისი\n\nკარიერა\n\nგადახდები\n\nSetanta Sports\n\nგადახდის მეთოდები\n\nგარანტია\n\nგანვადება\n\nნივთის დაბრუნება\n\nნივთის ონლაინ ყიდვის ინსტრუქცია\n\nგამოგვყევი\n\nFacebook\n\nYoutube\n\nInstagram\n\nTik Tok\n\nკონტაქტი\n\nInfo@zoommer.ge\n\n+995 (32) 2 60 30 60 / *7007\n\nფილიალები\n\nკორპორატიული გაყიდვები\n\nZoommer App\n\nCopyright © 2023 Zoommer.ge. All rights reserved.\n\nCookie პოლიტიკა\n\nსაიტით სარგებლობის გაგრძელებით, შენ ეთანხმები Cookie ჩანაწერების გამოყენებას. მეტი ინფორმაცისათვის იხილეთ კონფიდენციალურობის პოლიტიკა\n\nგასაგებია",
    "specs": {
      "ბრენდი:": "Asus",
      "მოდელი:": "ROG",
      "ცენტრალური პროცესორი:": "Intel Core i7-14650HX",
      "პროცესორის თაობა:": "Intel i7 14th Gen",
      "პროცესორის სიხშირე:": "3.7 GHz ~ 5.2 GHz",
      "ბირთვების რაოდენობა:": "16",
      "ნაკადების რაოდენობა:": "24",
      "გრაფიკული პროცესორი:": "Nvidia GeForce RTX 5070",
      "გრაფიკული პროცესორის მეხსიერება:": "8 GB",
      "გრაფიკული პროცესორის ტიპი:": "არა ინტეგრირებული",
      "ოპერაციული სისტემა:": "No",
      "Bluetooth:": "5.4",
      "ეკრანის ზომა:": "16 Inches",
      "რეზოლუცია:": "WUXGA",
      "ეკრანის ტიპი:": "IPS",
      "სენსორული ეკრანი:": "No",
      "განახლების სიხშირე:": "240 Hz",
      "კლავიატურის განათება:": "Yes",
      "Numpad:": "No",
      "დისკის წამკითხველი:": "No",
      "ვებ კამერა:": "Yes",
      "ლეპტოპის ტიპი:": "გეიმინგი",
      "შიდა მეხსიერება:": "1 TB",
      "შიდა მეხსიერების ტიპი:": "SSD",
      "შიდა მეხსიერების ინტერფეისი:": "M.2",
      "ოპერატიული მეხსიერება:": "32 GB",
      "ოპერატიული მეხსიერების ტიპი:": "-",
      "ოპერატიული მეხსიერების სიხშირე:": "-",
      "USB:": "2 x USB-A",
      "Type-C:": "1x",
      "Type-C პორტით დამუხტვა:": "No",
      "HDMI:": "Yes",
      "ლან პორტი:": "Yes",
      "3.5mm:": "Yes",
      "წონა:": "2.80 kg",
      "ფერი:": "titan grey"
    }
  },
  {
    "category": "Gaming ლეპტოპები",
    "title": "Asus ROG Strix 16 G614PR-RV007, AMD Ryzen 9-7940HX, N ...",
    "price": 6499.0,
    "link": "https://zoommer.ge/leptopebi/asus-rog-strix-16-g614pr-rv007-amd-ryzen-9-7940hx-nvidia-geforce-rtx-5070-ti-12-p48856",
    "image": "/_next/image?url=https%3A%2F%2Fs3.zoommer.ge%2Fsite%2F7aea0ff0-5ee2-4a8e-aa11-b65ec7f3e35a_Thumb.jpeg&w=384&q=50",
    "product_title_detail": "Asus ROG Strix 16 G614PR-RV007, AMD Ryzen 9-7940HX, Nvidia GeForce RTX 5070 Ti 12GB, 16GB RAM SSD 512GB, Free Dos, ლეპტოპი",
    "description": "*7007 / +995 (32) 2 60 30 60\nსავაჭრო პოლიტიკა\nგანვადება\nკარიერა\nTrade In\nფილიალები\nნავიგაცია\nკალათა\nშესვლა\n%\nმთავარი\nლეპტოპები\nAsus\n#ZOOM-036998\nAsus ROG Strix 16 G614PR-RV007, AMD Ryzen 9-7940HX, Nvidia GeForce RTX 5070 Ti 12GB, 16GB RAM SSD 512GB, Free Dos, ლეპტოპი\nეკრანის ზომა\n16 Inches\nრეზოლუცია\nWUXGA\nეკრანის ტიპი\nIPS\nგანახლების სიხშირე\n165 Hz\nშიდა მეხსიერება\n512 GB\nBluetooth\n5.3\nType-C\n2x\nოპერატიული მეხსიერება\n16 GB\nერთად იაფია\nდაამატე ნივთი\nAsus ROG Strix 16 G614PR-RV007, AMD Ryzen 9-7940HX, Nvidia GeForce RTX 5070 Ti 12GB, 16GB RAM SSD 512GB, Free Dos, ლეპტოპი\n6499 ₾\nRivacase 8057 Laptop Bag 16 Black\n58.65 ₾\n69 ₾\nRazer Gaming Mouse DeathAdder Essential USB White\n52 ₾\n65 ₾\nHavit Gaming Cooling Pad HV-F2083 Black\n75.65 ₾\n89 ₾\nჯამური ფასი (3)\n6685.3 ₾\n6722 ₾\nყიდვა\nაქსესუარები\nაღწერა\nმსგავსი\nმახასიათებლები\nფილიალები\nაქსესუარები\nაღწერა\nმსგავსი\nმახასიათებლები\nფილიალები\n89 ₾\n\nთვეში: 2 ₾ -დან\n\nHavit Gaming Cooling Pad HV-F2083 Black\nდამატება\n69 ₾\n\nთვეში: 1 ₾ -დან\n\nRivacase 8057 Laptop Bag 16 Black\nდამატება\n219 ₾\n\nთვეში: 6 ₾ -დან\n\nRazer Gaming Mouse Orochi V2 WL Black\nდამატება\n59 ₾\n\nთვეში: 1 ₾ -დან\n\nHavit Gaming mouse Pad HV-MP901\nდამატება\n69 ₾\n\nთვეში: 1 ₾ -დან\n\nXiaomi Mi Router 4A DVB4230GL White\nდამატება\n79 ₾\n\nთვეში: 2 ₾ -დან\n\nRivacase 7531 Eco Laptop Bag 15 Black\nდამატება\n219 ₾\n\nთვეში: 6 ₾ -დან\n\nRazer Gaming Mouse Orochi V2 WL White\nდამატება\n9 ₾\n\nHavit Gaming mouse Pad HV-MP838\nდამატება\n85 ₾\n\nთვეში: 2 ₾ -დან\n\nTP-Link Archer C50 AC1200 White\nდამატება\n89 ₾\n\nთვეში: 2 ₾ -დან\n\nTomtoc Defender A13 Laptop Sleeve Kit 16 A13F2DV Blac ...\nდამატება\n209 ₾\n\nთვეში: 5 ₾ -დან\n\nRazer Gaming Mouse DeathAdder V2 X Hyperspeed WL/BT/U ...\nდამატება\n29 ₾\n\nRazer Mouse Pad Goliathus Mobile Black/Green\nდამატება\n119 ₾\n\nთვეში: 3 ₾ -დან\n\nTP-Link Archer C6 AC1200 Black\nდამატება\n119 ₾\n\nთვეში: 3 ₾ -დან\n\nTomtoc Defender A42 Laptop Briefcase 16 A42F2B1 Navy ...\nდამატება\n139 ₾\n\nთვეში: 3 ₾ -დან\n\nLogitech Gaming Mouse G402 Hyperion Fury black\nდამატება\n29 ₾\n\nRazer Mouse Pad Goliathus Mobile Stealth Edition Blac ...\nდამატება\n159 ₾\n\nთვეში: 4 ₾ -დან\n\nXiaomi Router AX1500 White\nდამატება\n119 ₾\n\nთვეში: 3 ₾ -დან\n\nTomtoc Defender A42 Laptop Briefcase 16 A42F2D1 Black\nდამატება\n29 ₾\n\nHavit Gaming Mouse HV-MS1010 Black\nდამატება\n59 ₾\n\nთვეში: 1 ₾ -დან\n\nRazer Mouse Pad Gigantus V2 Large Black\nდამატება\n179 ₾\n\nთვეში: 4 ₾ -დან\n\nXiaomi Mesh System AX3000 NE 1 pack White\nდამატება\n89 ₾\n\nთვეში: 2 ₾ -დან\n\nUniq Dfender Tough Laptop Sleeve 16 Inch Marl Grey\nდამატება\n79 ₾\n\nთვეში: 2 ₾ -დან\n\nRazer Gaming Mouse DeathAdder Essential USB Black\nდამატება\n49 ₾\n\nთვეში: 1 ₾ -დან\n\nRazer Mouse Pad Gigantus V2 Medium Black\nდამატება\n299 ₾\n\nთვეში: 8 ₾ -დან\n\nXiaomi Mesh System AX3000 NE 2 pack White\nდამატება\n89 ₾\n\nთვეში: 2 ₾ -დან\n\nUniq Dfender Tough Laptop Sleeve 16 Inch Black\nდამატება\n119 ₾\n\nთვეში: 3 ₾ -დან\n\nHyperX Pulsefire Surge Mouse Black\nდამატება\n9 ₾\n\nHavit Gaming mouse Pad HV-MP843 Black\nდამატება\n249 ₾\n\nთვეში: 6 ₾ -დან\n\nXiaomi Router BE3600 White\nდამატება\n99 ₾\n\nთვეში: 2 ₾ -დან\n\nDell EcoLoop Essential Backpack 14-16 460-BDSS Black\nდამატება\n469 ₾\n\nთვეში: 13 ₾ -დან\n\nHP OMEN PHOTON Wireless Mouse 6CL96AA Black\nდამატება\n149 ₾\n\nთვეში: 4 ₾ -დან\n\nRazer Mouse Pad Firefly V2 RGB M Black\nდამატება\n79 ₾\n\nთვეში: 2 ₾ -დან\n\nTomtoc Defender A13 Laptop Sleeve 16 A13F2D1 Black\nდამატება\n65 ₾\n\nთვეში: 1 ₾ -დან\n\nRazer Gaming Mouse DeathAdder Essential USB White\nდამატება\n199 ₾\n\nთვეში: 5 ₾ -დან\n\nRazer Mouse Pad Goliathus Extended Chroma XXL Black\nდამატება\n89 ₾\n\nთვეში: 2 ₾ -დან\n\nTomtoc Defender A14 Laptop Briefcase 16 A14F2D1 Black\nდამატება\n239 ₾\n\nთვეში: 6 ₾ -დან\n\nRazer Gaming Mouse Basilisk V3 Black\nდამატება\n149 ₾\n\nთვეში: 4 ₾ -დან\n\nHyperX Pulsefire Mat RGB Black\nდამატება\n299 ₾\n\nთვეში: 8 ₾ -დან\n\nRazer Gaming Mouse Naga V2 HyperSpeed WL Black\nდამატება\n29 ₾\n\nHavit Gaming Mouse Pad HV-MP845 Black\nდამატება\n229 ₾\n\nთვეში: 6 ₾ -დან\n\nRazer Gaming Mouse Basilisk V3 X HyperSpeed WL Black\nდამატება\n29 ₾\n\nHavit Gaming Mouse Pad HV-MP847 Pink\nდამატება\n129 ₾\n\nთვეში: 3 ₾ -დან\n\nRazer Gaming Mouse Cobra Black\nდამატება\n29 ₾\n\nHavit Gaming Mouse Pad HV-MP849 Black\nდამატება\n19 ₾\n\nHavit Gaming Mouse HV-MS989GT Black/Red\nდამატება\n49 ₾\n\nთვეში: 1 ₾ -დან\n\nHyperX Pulsefire Mat M Black\nდამატება\n19 ₾\n\nHavit Gaming Mouse HV-MS626GT Black\nდამატება\n59 ₾\n\nთვეში: 1 ₾ -დან\n\nHyperX Pulsefire Mat L Black\nდამატება\n19 ₾\n\nHavit Gaming Mouse HV-MS66GT White/Blue\nდამატება\n39 ₾\n\nთვეში: 1 ₾ -დან\n\nRazer Mouse Pad Sphex V3 S Black\nდამატება\n149 ₾\n\nთვეში: 4 ₾ -დან\n\nHyperX Gaming Mouse Pulsefire Haste 2 Black\nდამატება\n89 ₾\n\nთვეში: 2 ₾ -დან\n\nRazer Mouse Pad Sphex V3 L Black\nდამატება\n19 ₾\n\nHavit Wireless Mouse HV-MS66GT Black\nდამატება\n29 ₾\n\nHavit Gaming mouse Pad HV-MP860\nდამატება\n179 ₾\n\nთვეში: 4 ₾ -დან\n\nLogitech Gaming Mouse G305 LIGHTSPEED WL L910-005282 ...\nდამატება\n25 ₾\n\nHavit Gaming mouse Pad HV-MP861\nდამატება\n259 ₾\n\nთვეში: 7 ₾ -დან\n\nLogitech Gaming Mouse G502 X L910-006138 Black\nდამატება\n99 ₾\n\nთვეში: 2 ₾ -დან\n\nSpigen Desk Pad Black with Magnetic Cable Holder LD30 ...\nდამატება\n259 ₾\n\nთვეში: 7 ₾ -დან\n\nLogitech Gaming Mouse G502 X L910-006138 White\nდამატება\n19 ₾\n\nHavit Gaming Mouse HV-MS626GT Black/Red\nდამატება\n19 ₾\n\nHavit Gaming Mouse HV-MS626GT Black/Blue\nდამატება\n349 ₾\n\nთვეში: 9 ₾ -დან\n\nLogitech Gaming Mouse G703 LIGHTSPEED WL L910-005640 ...\nდამატება\n89 ₾\n\nთვეში: 2 ₾ -დან\n\nLogitech Gaming Mouse G102 LIGHTSYNC L910-005823 Blac ...\nდამატება\n89 ₾\n\nთვეში: 2 ₾ -დან\n\nLogitech Gaming Mouse G102 LIGHTSYNC L910-005824 Whit ...\nდამატება\n89 ₾\n\nთვეში: 2 ₾ -დან\n\nLogitech Gaming Mouse G102 LIGHTSYNC L910-005801 Blue\nდამატება\n239 ₾\n\nთვეში: 6 ₾ -დან\n\nLogitech Gaming Mouse G502 HERO L910-005470 Black\nდამატება\n199 ₾\n\nთვეში: 5 ₾ -დან\n\nHyperX Pulsefire Haste 2 core Wireless Black\nდამატება\n199 ₾\n\nთვეში: 5 ₾ -დან\n\nHyperX Pulsefire Haste 2 core Wireless White\nდამატება\n59 ₾\n\nთვეში: 1 ₾ -დან\n\nHavit Gaming Mouse HV-MS954 Black\nდამატება\n39 ₾\n\nთვეში: 1 ₾ -დან\n\nHavit Gaming Mouse HV-MS1033 White\nდამატება\n39 ₾\n\nთვეში: 1 ₾ -დან\n\nHavit Gaming Mouse HV-MS1029 Pink\nდამატება\n59 ₾\n\nთვეში: 1 ₾ -დან\n\nHavit Gaming Mouse HV-MS966 Black/Green\nდამატება\n49 ₾\n\nთვეში: 1 ₾ -დან\n\nHavit Wireless Mouse HV-MS1039W Black/White\nდამატება\n79 ₾\n\nთვეში: 2 ₾ -დან\n\nHavit Wireless Mouse HV-MS970WB Pro Black\nდამატება\n79 ₾\n\nთვეში: 2 ₾ -დან\n\nHavit Wireless Mouse HV-MS970WB Pro Transparent White\nდამატება\n219 ₾\n\nთვეში: 6 ₾ -დან\n\nRazer Gaming Mouse Orochi V2 WL Pink\nდამატება\nპროდუქტის შესახებ\n\n თუ ეძებთ ლეპტოპს, რომელიც მარტივად გაუმკლავდება ყველაზე მოთხოვნად თამაშებს —  Asus ROG Strix 16 G614PR-RV007 შექმნილია სწორედ თქვენთვის. ეს მოდელი აერთიანებს მაღალ წარმადობას, გამძლე კონ...\n\nმეტის ნახვა\nმსგავსი პროდუქტები\n2599 ₾\n2799 ₾\n\nთვეში: 72 ₾ -დან\n\nAsus TUF 15 FX507ZC4-HN009 Black\nდამატება\n2249 ₾\n2499 ₾\n\nთვეში: 62 ₾ -დან\n\nAsus TUF 15 FA506NF-HN018, AMD Ryzen 5-7535HS, NVIDIA ...\nდამატება\n2999 ₾\n3699 ₾\n\nთვეში: 83 ₾ -დან\n\nAsus TUF 15 FA507NUR-LP044 Mercha Grey\nდამატება\n3299 ₾\n3499 ₾\n\nთვეში: 91 ₾ -დან\n\nAsus TUF 14 FA401UU-RG013 Jaeger Grey\nდამატება\n4179 ₾\n\nთვეში: 116 ₾ -დან\n\nAsus TUF A16 FA608WV-QT053 Grey\nდამატება\n2179 ₾\n2279 ₾\n\nთვეში: 60 ₾ -დან\n\nAsus TUF 15 FA506NFR-HN021, AMD Ryzen 7 7435HS, Nvidi ...\nდამატება\n5599 ₾\n5899 ₾\n\nთვეში: 155 ₾ -დან\n\nAsus TUF 18 FA808UP-S8030 Grey\nდამატება\n7299 ₾\n\nთვეში: 202 ₾ -დან\n\nAsus ROG Strix 16 G615JPR-S5101 Grey\nდამატება\n10399 ₾\n10499 ₾\n\nთვეში: 288 ₾ -დან\n\nAsus ROG Strix 18 G835LR-SA005 Black\nდამატება\n15999 ₾\n\nთვეში: 444 ₾ -დან\n\nAsus ROG Strix 18 G835LX-SA034W Black\nდამატება\n6699 ₾\n\nთვეში: 186 ₾ -დან\n\nAsus ROG Strix G16 G615JPR-RV113, Intel core i7-14650 ...\nდამატება\n8499 ₾\n\nთვეში: 236 ₾ -დან\n\nAsus ROG Strix G18 G815LR-S9085, Intel Core Ultra 9 2 ...\nდამატება\n4999 ₾\n\nთვეში: 138 ₾ -დან\n\nAsus TUF F16 FX608JMR-RV073, Intel core i7-14650HX 16 ...\nდამატება\n2699 ₾\n\nთვეში: 74 ₾ -დან\n\nAsus TUF 16 FX607VJ-RL005, Intel Core 5-210H, Nvidia ...\nდამატება\n4199 ₾\n\nთვეში: 116 ₾ -დან\n\nAsus TUF F16 FX608JHR-RV035, Intel core i7-14650HX 16 ...\nდამატება\nდამატებითი მახასიათებლები\nბრენდი\nბრენდი:\n\t\nAsus\nმოდელი\nმოდელი:\n\t\nROG\nტექნიკური მახასიათებლები\nცენტრალური პროცესორი:\n\t\nAMD Ryzen 9-7940HX\n\n\nპროცესორის თაობა:\n\t\nRyzen 9 7000 Series\n\n\nპროცესორის სიხშირე:\n\t\n2.4 GHz ~ 5.2 GHz\n\n\nბირთვების რაოდენობა:\n\t\n16\n\n\nნაკადების რაოდენობა:\n\t\n32\n\n\nგრაფიკული პროცესორი:\n\t\nNvidia GeForce RTX 5070 Ti\n\n\nგრაფიკული პროცესორის მეხსიერება:\n\t\n12 GB\n\n\nგრაფიკული პროცესორის ტიპი:\n\t\nარა ინტეგრირებული\n\n\nოპერაციული სისტემა:\n\t\nNo\n\n\nBluetooth:\n\t\n5.3\nეკრანი\nეკრანის ზომა:\n\t\n16 Inches\n\n\nრეზოლუცია:\n\t\nWUXGA\n\n\nეკრანის ტიპი:\n\t\nIPS\n\n\nსენსორული ეკრანი:\n\t\nNo\n\n\nგანახლების სიხშირე:\n\t\n165 Hz\nდამატებითი მახასიათებლები\nკლავიატურის განათება:\n\t\nYes\n\n\nNumpad:\n\t\nNo\n\n\nდისკის წამკითხველი:\n\t\nNo\n\n\nვებ კამერა:\n\t\nYes\n\n\nლეპტოპის ტიპი:\n\t\nგეიმინგი\nმეხსიერება\nშიდა მეხსიერება:\n\t\n512 GB\n\n\nშიდა მეხსიერების ტიპი:\n\t\nSSD\n\n\nშიდა მეხსიერების ინტერფეისი:\n\t\nM.2\n\n\nოპერატიული მეხსიერება:\n\t\n16 GB\n\n\nოპერატიული მეხსიერების ტიპი:\n\t\nDDR5\n\n\nოპერატიული მეხსიერების სიხშირე:\n\t\n-\nპორტები\nUSB:\n\t\n2 x USB-A\n\n\nType-C:\n\t\n2x\n\n\nType-C პორტით დამუხტვა:\n\t\nNo\n\n\nHDMI:\n\t\nYes\n\n\nლან პორტი:\n\t\nYes\n\n\n3.5mm:\n\t\nYes\nზომა/წონა\nწონა:\n\t\n2.80 kg\nფერი\nფერი:\n\t\ntitan grey\nმეტის ნახვა\nგაეცანი საგარანტიო პირობებს\nსაგარანტიო პირობები\nფილიალები\nმარაგშია\nშეკვეთიდან 2-5 დღეში\nზუმერის City Mall საბურთალო-ს ფილიალი\n\nთბილისი - \"სითი მოლი\" - პეტრე ქავთარაძის N1\n\nმარაგშია\n+995 591 971 962\nორშ-შაბ: 10:00:00 - 22:00:00\nკვირა: 10:00:00 - 22:00:00\n6499 ₾\n\nთვეში: 180.5 ₾ -დან\n\nმარაგი ფილიალებში\nფასის დაზღვევა\nფასის კონტროლი\nფასის დაჯავშნა\nყიდვა\nშედარება\nდამატება\nნავიგაცია\n\nპერსონალურ მონაცემთა დაცვის პოლიტიკა\n\nჩვენ შესახებ\n\nწესები და პირობები\n\nმიწოდების სერვისი\n\nკარიერა\n\nგადახდები\n\nSetanta Sports\n\nგადახდის მეთოდები\n\nგარანტია\n\nგანვადება\n\nნივთის დაბრუნება\n\nნივთის ონლაინ ყიდვის ინსტრუქცია\n\nგამოგვყევი\n\nFacebook\n\nYoutube\n\nInstagram\n\nTik Tok\n\nკონტაქტი\n\nInfo@zoommer.ge\n\n+995 (32) 2 60 30 60 / *7007\n\nფილიალები\n\nკორპორატიული გაყიდვები\n\nZoommer App\n\nCopyright © 2023 Zoommer.ge. All rights reserved.\n\nCookie პოლიტიკა\n\nსაიტით სარგებლობის გაგრძელებით, შენ ეთანხმები Cookie ჩანაწერების გამოყენებას. მეტი ინფორმაცისათვის იხილეთ კონფიდენციალურობის პოლიტიკა\n\nგასაგებია",
    "specs": {
      "ბრენდი:": "Asus",
      "მოდელი:": "ROG",
      "ცენტრალური პროცესორი:": "AMD Ryzen 9-7940HX",
      "პროცესორის თაობა:": "Ryzen 9 7000 Series",
      "პროცესორის სიხშირე:": "2.4 GHz ~ 5.2 GHz",
      "ბირთვების რაოდენობა:": "16",
      "ნაკადების რაოდენობა:": "32",
      "გრაფიკული პროცესორი:": "Nvidia GeForce RTX 5070 Ti",
      "გრაფიკული პროცესორის მეხსიერება:": "12 GB",
      "გრაფიკული პროცესორის ტიპი:": "არა ინტეგრირებული",
      "ოპერაციული სისტემა:": "No",
      "Bluetooth:": "5.3",
      "ეკრანის ზომა:": "16 Inches",
      "რეზოლუცია:": "WUXGA",
      "ეკრანის ტიპი:": "IPS",
      "სენსორული ეკრანი:": "No",
      "განახლების სიხშირე:": "165 Hz",
      "კლავიატურის განათება:": "Yes",
      "Numpad:": "No",
      "დისკის წამკითხველი:": "No",
      "ვებ კამერა:": "Yes",
      "ლეპტოპის ტიპი:": "გეიმინგი",
      "შიდა მეხსიერება:": "512 GB",
      "შიდა მეხსიერების ტიპი:": "SSD",
      "შიდა მეხსიერების ინტერფეისი:": "M.2",
      "ოპერატიული მეხსიერება:": "16 GB",
      "ოპერატიული მეხსიერების ტიპი:": "DDR5",
      "ოპერატიული მეხსიერების სიხშირე:": "-",
      "USB:": "2 x USB-A",
      "Type-C:": "2x",
      "Type-C პორტით დამუხტვა:": "No",
      "HDMI:": "Yes",
      "ლან პორტი:": "Yes",
      "3.5mm:": "Yes",
      "წონა:": "2.80 kg",
      "ფერი:": "titan grey"
    }
  },
  {
    "category": "Gaming ლეპტოპები",
    "title": "HP Omen Max 16 BG7J7EA, Intel Core Ultra 7-255HX 20c, ...",
    "price": 5699.0,
    "link": "https://zoommer.ge/leptopebi/hp-omen-max-16-bg7j7ea-intel-core-ultra-7-255hx-20c-nvidia-geforce-rtx-5070-8gb-p48826",
    "image": "/_next/image?url=https%3A%2F%2Fs3.zoommer.ge%2Fsite%2Fefe88bfe-d121-4e34-af02-435a62c2b32f_Thumb.jpeg&w=384&q=50",
    "product_title_detail": "HP Omen Max 16 BG7J7EA, Intel Core Ultra 7-255HX 20c, Nvidia GeForce RTX 5070 8GB, 24GB RAM SSD 1TB, Free Dos, ლეპტოპი",
    "description": "",
    "specs": {
      "ბრენდი:": "HP",
      "მოდელი:": "Omen",
      "ცენტრალური პროცესორი:": "Intel Core Ultra 7-255HX",
      "პროცესორის თაობა:": "Intel Ultra 7 Series 2",
      "პროცესორის სიხშირე:": "1.8 GHz ~ 5.2 GHz",
      "ბირთვების რაოდენობა:": "20",
      "ნაკადების რაოდენობა:": "20",
      "გრაფიკული პროცესორი:": "Nvidia GeForce RTX 5070",
      "გრაფიკული პროცესორის მეხსიერება:": "8 GB",
      "გრაფიკული პროცესორის ტიპი:": "არა ინტეგრირებული",
      "ოპერაციული სისტემა:": "No",
      "Bluetooth:": "5.3",
      "ეკრანის ზომა:": "16 Inches",
      "რეზოლუცია:": "WUXGA",
      "ეკრანის ტიპი:": "IPS",
      "სენსორული ეკრანი:": "No",
      "განახლების სიხშირე:": "165 Hz",
      "კლავიატურის განათება:": "Yes",
      "Numpad:": "Yes",
      "დისკის წამკითხველი:": "No",
      "ვებ კამერა:": "Yes",
      "ლეპტოპის ტიპი:": "გეიმინგი",
      "შიდა მეხსიერება:": "1 TB",
      "შიდა მეხსიერების ტიპი:": "SSD",
      "შიდა მეხსიერების ინტერფეისი:": "M.2",
      "ოპერატიული მეხსიერება:": "24 GB",
      "ოპერატიული მეხსიერების ტიპი:": "DDR5",
      "ოპერატიული მეხსიერების სიხშირე:": "5600 MHz",
      "USB:": "2 x USB-A",
      "Type-C:": "2x",
      "Type-C პორტით დამუხტვა:": "No",
      "HDMI:": "Yes",
      "ლან პორტი:": "Yes",
      "3.5mm:": "Yes",
      "წონა:": "2.40 kg",
      "ფერი:": "Black"
    }
  },
  {
    "category": "Gaming ლეპტოპები",
    "title": "Lenovo Legion 5 Pro 83F30012RK Black",
    "price": 6999.0,
    "link": "https://zoommer.ge/leptopebi/lenovo-legion-5-pro-83f30012rk-black-p48583",
    "image": "/_next/image?url=https%3A%2F%2Fs3.zoommer.ge%2Fsite%2F1615de3b-4bc5-4b73-973e-ea35946fc434_Thumb.jpeg&w=384&q=50",
    "product_title_detail": "Lenovo Legion 5 Pro 83F30012RK Black",
    "description": "*7007 / +995 (32) 2 60 30 60\nსავაჭრო პოლიტიკა\nგანვადება\nკარიერა\nTrade In\nფილიალები\nნავიგაცია\nკალათა\nშესვლა\n%\nმთავარი\nლეპტოპები\nLenovo\n#ZOOM-036833\nLenovo Legion 5 Pro 83F30012RK Black\nეკრანის ზომა\n16 Inches\nრეზოლუცია\nWQXGA\nეკრანის ტიპი\nOled\nგანახლების სიხშირე\n165 Hz\nშიდა მეხსიერება\n1 TB\nBluetooth\n5.4\nType-C\n2x\nოპერატიული მეხსიერება\n32 GB\nერთად იაფია\nდაამატე ნივთი\nLenovo Legion 5 Pro 83F30012RK Black\n6999 ₾\nRivacase 8057 Laptop Bag 16 Black\n58.65 ₾\n69 ₾\nRazer Gaming Mouse DeathAdder Essential USB White\n52 ₾\n65 ₾\nHavit Gaming Cooling Pad HV-F2083 Black\n75.65 ₾\n89 ₾\nჯამური ფასი (3)\n7185.3 ₾\n7222 ₾\nყიდვა\nაქსესუარები\nაღწერა\nმსგავსი\nმახასიათებლები\nფილიალები\nაქსესუარები\nაღწერა\nმსგავსი\nმახასიათებლები\nფილიალები\n89 ₾\n\nთვეში: 2 ₾ -დან\n\nHavit Gaming Cooling Pad HV-F2083 Black\nდამატება\n69 ₾\n\nთვეში: 1 ₾ -დან\n\nRivacase 8057 Laptop Bag 16 Black\nდამატება\n219 ₾\n\nთვეში: 6 ₾ -დან\n\nRazer Gaming Mouse Orochi V2 WL Black\nდამატება\n59 ₾\n\nთვეში: 1 ₾ -დან\n\nHavit Gaming mouse Pad HV-MP901\nდამატება\n69 ₾\n\nთვეში: 1 ₾ -დან\n\nXiaomi Mi Router 4A DVB4230GL White\nდამატება\n79 ₾\n\nთვეში: 2 ₾ -დან\n\nRivacase 7531 Eco Laptop Bag 15 Black\nდამატება\n219 ₾\n\nთვეში: 6 ₾ -დან\n\nRazer Gaming Mouse Orochi V2 WL White\nდამატება\n9 ₾\n\nHavit Gaming mouse Pad HV-MP838\nდამატება\n85 ₾\n\nთვეში: 2 ₾ -დან\n\nTP-Link Archer C50 AC1200 White\nდამატება\n89 ₾\n\nთვეში: 2 ₾ -დან\n\nTomtoc Defender A13 Laptop Sleeve Kit 16 A13F2DV Blac ...\nდამატება\n209 ₾\n\nთვეში: 5 ₾ -დან\n\nRazer Gaming Mouse DeathAdder V2 X Hyperspeed WL/BT/U ...\nდამატება\n9 ₾\n\nHavit Gaming mouse Pad HV-MP843 Black\nდამატება\n119 ₾\n\nთვეში: 3 ₾ -დან\n\nTP-Link Archer C6 AC1200 Black\nდამატება\n119 ₾\n\nთვეში: 3 ₾ -დან\n\nTomtoc Defender A42 Laptop Briefcase 16 A42F2B1 Navy ...\nდამატება\n139 ₾\n\nთვეში: 3 ₾ -დან\n\nLogitech Gaming Mouse G402 Hyperion Fury black\nდამატება\n149 ₾\n\nთვეში: 4 ₾ -დან\n\nRazer Mouse Pad Firefly V2 RGB M Black\nდამატება\n159 ₾\n\nთვეში: 4 ₾ -დან\n\nXiaomi Router AX1500 White\nდამატება\n119 ₾\n\nთვეში: 3 ₾ -დან\n\nTomtoc Defender A42 Laptop Briefcase 16 A42F2D1 Black\nდამატება\n29 ₾\n\nHavit Gaming Mouse HV-MS1010 Black\nდამატება\n199 ₾\n\nთვეში: 5 ₾ -დან\n\nRazer Mouse Pad Goliathus Extended Chroma XXL Black\nდამატება\n179 ₾\n\nთვეში: 4 ₾ -დან\n\nXiaomi Mesh System AX3000 NE 1 pack White\nდამატება\n89 ₾\n\nთვეში: 2 ₾ -დან\n\nUniq Dfender Tough Laptop Sleeve 16 Inch Marl Grey\nდამატება\n79 ₾\n\nთვეში: 2 ₾ -დან\n\nRazer Gaming Mouse DeathAdder Essential USB Black\nდამატება\n149 ₾\n\nთვეში: 4 ₾ -დან\n\nHyperX Pulsefire Mat RGB Black\nდამატება\n299 ₾\n\nთვეში: 8 ₾ -დან\n\nXiaomi Mesh System AX3000 NE 2 pack White\nდამატება\n89 ₾\n\nთვეში: 2 ₾ -დან\n\nUniq Dfender Tough Laptop Sleeve 16 Inch Black\nდამატება\n119 ₾\n\nთვეში: 3 ₾ -დან\n\nHyperX Pulsefire Surge Mouse Black\nდამატება\n29 ₾\n\nHavit Gaming Mouse Pad HV-MP845 Black\nდამატება\n249 ₾\n\nთვეში: 6 ₾ -დან\n\nXiaomi Router BE3600 White\nდამატება\n99 ₾\n\nთვეში: 2 ₾ -დან\n\nDell EcoLoop Essential Backpack 14-16 460-BDSS Black\nდამატება\n469 ₾\n\nთვეში: 13 ₾ -დან\n\nHP OMEN PHOTON Wireless Mouse 6CL96AA Black\nდამატება\n29 ₾\n\nHavit Gaming Mouse Pad HV-MP847 Pink\nდამატება\n79 ₾\n\nთვეში: 2 ₾ -დან\n\nTomtoc Defender A13 Laptop Sleeve 16 A13F2D1 Black\nდამატება\n65 ₾\n\nთვეში: 1 ₾ -დან\n\nRazer Gaming Mouse DeathAdder Essential USB White\nდამატება\n29 ₾\n\nHavit Gaming Mouse Pad HV-MP849 Black\nდამატება\n89 ₾\n\nთვეში: 2 ₾ -დან\n\nTomtoc Defender A14 Laptop Briefcase 16 A14F2D1 Black\nდამატება\n239 ₾\n\nთვეში: 6 ₾ -დან\n\nRazer Gaming Mouse Basilisk V3 Black\nდამატება\n49 ₾\n\nთვეში: 1 ₾ -დან\n\nHyperX Pulsefire Mat M Black\nდამატება\n299 ₾\n\nთვეში: 8 ₾ -დან\n\nRazer Gaming Mouse Naga V2 HyperSpeed WL Black\nდამატება\n59 ₾\n\nთვეში: 1 ₾ -დან\n\nHyperX Pulsefire Mat L Black\nდამატება\n229 ₾\n\nთვეში: 6 ₾ -დან\n\nRazer Gaming Mouse Basilisk V3 X HyperSpeed WL Black\nდამატება\n39 ₾\n\nთვეში: 1 ₾ -დან\n\nRazer Mouse Pad Sphex V3 S Black\nდამატება\n129 ₾\n\nთვეში: 3 ₾ -დან\n\nRazer Gaming Mouse Cobra Black\nდამატება\n89 ₾\n\nთვეში: 2 ₾ -დან\n\nRazer Mouse Pad Sphex V3 L Black\nდამატება\n19 ₾\n\nHavit Gaming Mouse HV-MS989GT Black/Red\nდამატება\n29 ₾\n\nHavit Gaming mouse Pad HV-MP860\nდამატება\n19 ₾\n\nHavit Gaming Mouse HV-MS626GT Black\nდამატება\n19 ₾\n\nHavit Gaming Mouse HV-MS66GT White/Blue\nდამატება\n149 ₾\n\nთვეში: 4 ₾ -დან\n\nHyperX Gaming Mouse Pulsefire Haste 2 Black\nდამატება\n19 ₾\n\nHavit Wireless Mouse HV-MS66GT Black\nდამატება\n179 ₾\n\nთვეში: 4 ₾ -დან\n\nLogitech Gaming Mouse G305 LIGHTSPEED WL L910-005282 ...\nდამატება\n259 ₾\n\nთვეში: 7 ₾ -დან\n\nLogitech Gaming Mouse G502 X L910-006138 Black\nდამატება\n259 ₾\n\nთვეში: 7 ₾ -დან\n\nLogitech Gaming Mouse G502 X L910-006138 White\nდამატება\n19 ₾\n\nHavit Gaming Mouse HV-MS626GT Black/Red\nდამატება\n19 ₾\n\nHavit Gaming Mouse HV-MS626GT Black/Blue\nდამატება\n349 ₾\n\nთვეში: 9 ₾ -დან\n\nLogitech Gaming Mouse G703 LIGHTSPEED WL L910-005640 ...\nდამატება\n89 ₾\n\nთვეში: 2 ₾ -დან\n\nLogitech Gaming Mouse G102 LIGHTSYNC L910-005823 Blac ...\nდამატება\n89 ₾\n\nთვეში: 2 ₾ -დან\n\nLogitech Gaming Mouse G102 LIGHTSYNC L910-005824 Whit ...\nდამატება\n89 ₾\n\nთვეში: 2 ₾ -დან\n\nLogitech Gaming Mouse G102 LIGHTSYNC L910-005801 Blue\nდამატება\n239 ₾\n\nთვეში: 6 ₾ -დან\n\nLogitech Gaming Mouse G502 HERO L910-005470 Black\nდამატება\n199 ₾\n\nთვეში: 5 ₾ -დან\n\nHyperX Pulsefire Haste 2 core Wireless Black\nდამატება\n199 ₾\n\nთვეში: 5 ₾ -დან\n\nHyperX Pulsefire Haste 2 core Wireless White\nდამატება\n59 ₾\n\nთვეში: 1 ₾ -დან\n\nHavit Gaming Mouse HV-MS954 Black\nდამატება\n39 ₾\n\nთვეში: 1 ₾ -დან\n\nHavit Gaming Mouse HV-MS1033 White\nდამატება\n39 ₾\n\nთვეში: 1 ₾ -დან\n\nHavit Gaming Mouse HV-MS1029 Pink\nდამატება\n59 ₾\n\nთვეში: 1 ₾ -დან\n\nHavit Gaming Mouse HV-MS966 Black/Green\nდამატება\n49 ₾\n\nთვეში: 1 ₾ -დან\n\nHavit Wireless Mouse HV-MS1039W Black/White\nდამატება\n79 ₾\n\nთვეში: 2 ₾ -დან\n\nHavit Wireless Mouse HV-MS970WB Pro Black\nდამატება\n79 ₾\n\nთვეში: 2 ₾ -დან\n\nHavit Wireless Mouse HV-MS970WB Pro Transparent White\nდამატება\n219 ₾\n\nთვეში: 6 ₾ -დან\n\nRazer Gaming Mouse Orochi V2 WL Pink\nდამატება\nპროდუქტის შესახებ\n\nთუ ეძებთ ლეპტოპს, რომელიც მარტივად გაუმკლავდება ყველაზე მოთხოვნად თამაშებს — Lenovo Legion 5 Pro 83F30012RK Black შექმნილია სწორედ თქვენთვის. ეს მოდელი აერთიანებს მაღალ წარმადობას, გამძლე კონსტრუქცი...\n\nმეტის ნახვა\nმსგავსი პროდუქტები\n2999 ₾\n3199 ₾\n\nთვეში: 83 ₾ -დან\n\nLenovo LOQ 15 83DV00MPRK Luna Grey\nდამატება\n7999 ₾\n8799 ₾\n\nთვეში: 222 ₾ -დან\n\nLenovo Legion Pro 7 83F50026RK, Intel Core Ultra 9 27 ...\nდამატება\n4299 ₾\n\nთვეში: 119 ₾ -დან\n\nLenovo Legion 5 83LY008MRK Black\nდამატება\n3799 ₾\n\nთვეში: 105 ₾ -დან\n\nLenovo LOQ 15 83JE002DRK Grey\nდამატება\n5999 ₾\n6199 ₾\n\nთვეში: 166 ₾ -დან\n\nLenovo Legion 5 Pro 83F3000XRK Black\nდამატება\nდამატებითი მახასიათებლები\nბრენდი\nბრენდი:\n\t\nLenovo\nმოდელი\nმოდელი:\n\t\nLegion\nტექნიკური მახასიათებლები\nცენტრალური პროცესორი:\n\t\nIntel Core Ultra 9-275HX\n\n\nპროცესორის თაობა:\n\t\nIntel Ultra 9 Series 2\n\n\nპროცესორის სიხშირე:\n\t\n2.1 GHz ~ 5.4 GHz\n\n\nბირთვების რაოდენობა:\n\t\n24\n\n\nნაკადების რაოდენობა:\n\t\n24\n\n\nგრაფიკული პროცესორი:\n\t\nNvidia GeForce RTX 5070\n\n\nგრაფიკული პროცესორის მეხსიერება:\n\t\n8 GB\n\n\nგრაფიკული პროცესორის ტიპი:\n\t\nარა ინტეგრირებული\n\n\nოპერაციული სისტემა:\n\t\nNo\n\n\nBluetooth:\n\t\n5.4\nეკრანი\nეკრანის ზომა:\n\t\n16 Inches\n\n\nრეზოლუცია:\n\t\nWQXGA\n\n\nეკრანის ტიპი:\n\t\nOled\n\n\nსენსორული ეკრანი:\n\t\nNo\n\n\nგანახლების სიხშირე:\n\t\n165 Hz\nდამატებითი მახასიათებლები\nკლავიატურის განათება:\n\t\nYes\n\n\nNumpad:\n\t\nYes\n\n\nდისკის წამკითხველი:\n\t\nNo\n\n\nვებ კამერა:\n\t\nYes\n\n\nლეპტოპის ტიპი:\n\t\nგეიმინგი\nმეხსიერება\nშიდა მეხსიერება:\n\t\n1 TB\n\n\nშიდა მეხსიერების ტიპი:\n\t\nSSD\n\n\nშიდა მეხსიერების ინტერფეისი:\n\t\nM.2\n\n\nოპერატიული მეხსიერება:\n\t\n32 GB\n\n\nოპერატიული მეხსიერების ტიპი:\n\t\nDDR5\n\n\nოპერატიული მეხსიერების სიხშირე:\n\t\n5600 MHz\nპორტები\nUSB:\n\t\n3 x USB-A\n\n\nType-C:\n\t\n2x\n\n\nType-C პორტით დამუხტვა:\n\t\nYes\n\n\nHDMI:\n\t\nYes\n\n\nლან პორტი:\n\t\nYes\n\n\n3.5mm:\n\t\nYes\nზომა/წონა\nწონა:\n\t\n2.43 kg\nფერი\nფერი:\n\t\nBlack\nმეტის ნახვა\nგაეცანი საგარანტიო პირობებს\nსაგარანტიო პირობები\nფილიალები\nმარაგშია\nშეკვეთიდან 2-5 დღეში\nზუმერის City Mall საბურთალო-ს ფილიალი\n\nთბილისი - \"სითი მოლი\" - პეტრე ქავთარაძის N1\n\nმარაგშია\n+995 591 971 962\nორშ-შაბ: 10:00:00 - 22:00:00\nკვირა: 10:00:00 - 22:00:00\nბათუმი ჭავჭავაძის ფილიალი\n\nბათუმი - ბათუმი, ჭავჭავაძის N21\n\nმარაგშია\n+995 591 967 606\nორშ-შაბ: 10:00:00 - 20:00:00\nკვირა: 10:00:00 - 19:00:00\n6999 ₾\n\nთვეში: 194.4 ₾ -დან\n\nმარაგი ფილიალებში\nფასის დაზღვევა\nფასის კონტროლი\nფასის დაჯავშნა\nყიდვა\nშედარება\nდამატება\nნავიგაცია\n\nპერსონალურ მონაცემთა დაცვის პოლიტიკა\n\nჩვენ შესახებ\n\nწესები და პირობები\n\nმიწოდების სერვისი\n\nკარიერა\n\nგადახდები\n\nSetanta Sports\n\nგადახდის მეთოდები\n\nგარანტია\n\nგანვადება\n\nნივთის დაბრუნება\n\nნივთის ონლაინ ყიდვის ინსტრუქცია\n\nგამოგვყევი\n\nFacebook\n\nYoutube\n\nInstagram\n\nTik Tok\n\nკონტაქტი\n\nInfo@zoommer.ge\n\n+995 (32) 2 60 30 60 / *7007\n\nფილიალები\n\nკორპორატიული გაყიდვები\n\nZoommer App\n\nCopyright © 2023 Zoommer.ge. All rights reserved.\n\nCookie პოლიტიკა\n\nსაიტით სარგებლობის გაგრძელებით, შენ ეთანხმები Cookie ჩანაწერების გამოყენებას. მეტი ინფორმაცისათვის იხილეთ კონფიდენციალურობის პოლიტიკა\n\nგასაგებია",
    "specs": {
      "ბრენდი:": "Lenovo",
      "მოდელი:": "Legion",
      "ცენტრალური პროცესორი:": "Intel Core Ultra 9-275HX",
      "პროცესორის თაობა:": "Intel Ultra 9 Series 2",
      "პროცესორის სიხშირე:": "2.1 GHz ~ 5.4 GHz",
      "ბირთვების რაოდენობა:": "24",
      "ნაკადების რაოდენობა:": "24",
      "გრაფიკული პროცესორი:": "Nvidia GeForce RTX 5070",
      "გრაფიკული პროცესორის მეხსიერება:": "8 GB",
      "გრაფიკული პროცესორის ტიპი:": "არა ინტეგრირებული",
      "ოპერაციული სისტემა:": "No",
      "Bluetooth:": "5.4",
      "ეკრანის ზომა:": "16 Inches",
      "რეზოლუცია:": "WQXGA",
      "ეკრანის ტიპი:": "Oled",
      "სენსორული ეკრანი:": "No",
      "განახლების სიხშირე:": "165 Hz",
      "კლავიატურის განათება:": "Yes",
      "Numpad:": "Yes",
      "დისკის წამკითხველი:": "No",
      "ვებ კამერა:": "Yes",
      "ლეპტოპის ტიპი:": "გეიმინგი",
      "შიდა მეხსიერება:": "1 TB",
      "შიდა მეხსიერების ტიპი:": "SSD",
      "შიდა მეხსიერების ინტერფეისი:": "M.2",
      "ოპერატიული მეხსიერება:": "32 GB",
      "ოპერატიული მეხსიერების ტიპი:": "DDR5",
      "ოპერატიული მეხსიერების სიხშირე:": "5600 MHz",
      "USB:": "3 x USB-A",
      "Type-C:": "2x",
      "Type-C პორტით დამუხტვა:": "Yes",
      "HDMI:": "Yes",
      "ლან პორტი:": "Yes",
      "3.5mm:": "Yes",
      "წონა:": "2.43 kg",
      "ფერი:": "Black"
    }
  },
  {
    "category": "Gaming ლეპტოპები",
    "title": "Lenovo Legion 5 Pro 83F3000XRK Black",
    "price": 5999.0,
    "link": "https://zoommer.ge/leptopebi/lenovo-legion-5-pro-83f3000xrk-black-p48582",
    "image": "/_next/image?url=https%3A%2F%2Fs3.zoommer.ge%2Fsite%2Fc8645de3-0b2d-407d-bebe-63d59ecb106d_Thumb.jpeg&w=384&q=50",
    "product_title_detail": "Lenovo Legion 5 Pro 83F3000XRK Black",
    "description": "*7007 / +995 (32) 2 60 30 60\nსავაჭრო პოლიტიკა\nგანვადება\nკარიერა\nTrade In\nფილიალები\nნავიგაცია\nკალათა\nშესვლა\n%\nმთავარი\nლეპტოპები\nLenovo\n#ZOOM-036832\nLenovo Legion 5 Pro 83F3000XRK Black\nეკრანის ზომა\n16 Inches\nრეზოლუცია\nWQXGA\nეკრანის ტიპი\nOled\nგანახლების სიხშირე\n165 Hz\nშიდა მეხსიერება\n1 TB\nBluetooth\n5.4\nType-C\n2x\nოპერატიული მეხსიერება\n32 GB\nერთად იაფია\nდაამატე ნივთი\nLenovo Legion 5 Pro 83F3000XRK Black\n5999 ₾\nRivacase 8057 Laptop Bag 16 Black\n58.65 ₾\n69 ₾\nRazer Gaming Mouse DeathAdder Essential USB White\n52 ₾\n65 ₾\nHavit Gaming Cooling Pad HV-F2083 Black\n75.65 ₾\n89 ₾\nჯამური ფასი (3)\n6185.3 ₾\n6222 ₾\nყიდვა\nაქსესუარები\nაღწერა\nმსგავსი\nმახასიათებლები\nფილიალები\nაქსესუარები\nაღწერა\nმსგავსი\nმახასიათებლები\nფილიალები\n89 ₾\n\nთვეში: 2 ₾ -დან\n\nHavit Gaming Cooling Pad HV-F2083 Black\nდამატება\n69 ₾\n\nთვეში: 1 ₾ -დან\n\nRivacase 8057 Laptop Bag 16 Black\nდამატება\n219 ₾\n\nთვეში: 6 ₾ -დან\n\nRazer Gaming Mouse Orochi V2 WL Black\nდამატება\n59 ₾\n\nთვეში: 1 ₾ -დან\n\nHavit Gaming mouse Pad HV-MP901\nდამატება\n69 ₾\n\nთვეში: 1 ₾ -დან\n\nXiaomi Mi Router 4A DVB4230GL White\nდამატება\n79 ₾\n\nთვეში: 2 ₾ -დან\n\nRivacase 7531 Eco Laptop Bag 15 Black\nდამატება\n219 ₾\n\nთვეში: 6 ₾ -დან\n\nRazer Gaming Mouse Orochi V2 WL White\nდამატება\n9 ₾\n\nHavit Gaming mouse Pad HV-MP838\nდამატება\n85 ₾\n\nთვეში: 2 ₾ -დან\n\nTP-Link Archer C50 AC1200 White\nდამატება\n89 ₾\n\nთვეში: 2 ₾ -დან\n\nTomtoc Defender A13 Laptop Sleeve Kit 16 A13F2DV Blac ...\nდამატება\n209 ₾\n\nთვეში: 5 ₾ -დან\n\nRazer Gaming Mouse DeathAdder V2 X Hyperspeed WL/BT/U ...\nდამატება\n9 ₾\n\nHavit Gaming mouse Pad HV-MP843 Black\nდამატება\n119 ₾\n\nთვეში: 3 ₾ -დან\n\nTP-Link Archer C6 AC1200 Black\nდამატება\n119 ₾\n\nთვეში: 3 ₾ -დან\n\nTomtoc Defender A42 Laptop Briefcase 16 A42F2B1 Navy ...\nდამატება\n139 ₾\n\nთვეში: 3 ₾ -დან\n\nLogitech Gaming Mouse G402 Hyperion Fury black\nდამატება\n149 ₾\n\nთვეში: 4 ₾ -დან\n\nRazer Mouse Pad Firefly V2 RGB M Black\nდამატება\n159 ₾\n\nთვეში: 4 ₾ -დან\n\nXiaomi Router AX1500 White\nდამატება\n119 ₾\n\nთვეში: 3 ₾ -დან\n\nTomtoc Defender A42 Laptop Briefcase 16 A42F2D1 Black\nდამატება\n29 ₾\n\nHavit Gaming Mouse HV-MS1010 Black\nდამატება\n199 ₾\n\nთვეში: 5 ₾ -დან\n\nRazer Mouse Pad Goliathus Extended Chroma XXL Black\nდამატება\n179 ₾\n\nთვეში: 4 ₾ -დან\n\nXiaomi Mesh System AX3000 NE 1 pack White\nდამატება\n89 ₾\n\nთვეში: 2 ₾ -დან\n\nUniq Dfender Tough Laptop Sleeve 16 Inch Marl Grey\nდამატება\n79 ₾\n\nთვეში: 2 ₾ -დან\n\nRazer Gaming Mouse DeathAdder Essential USB Black\nდამატება\n149 ₾\n\nთვეში: 4 ₾ -დან\n\nHyperX Pulsefire Mat RGB Black\nდამატება\n299 ₾\n\nთვეში: 8 ₾ -დან\n\nXiaomi Mesh System AX3000 NE 2 pack White\nდამატება\n89 ₾\n\nთვეში: 2 ₾ -დან\n\nUniq Dfender Tough Laptop Sleeve 16 Inch Black\nდამატება\n119 ₾\n\nთვეში: 3 ₾ -დან\n\nHyperX Pulsefire Surge Mouse Black\nდამატება\n29 ₾\n\nHavit Gaming Mouse Pad HV-MP845 Black\nდამატება\n249 ₾\n\nთვეში: 6 ₾ -დან\n\nXiaomi Router BE3600 White\nდამატება\n99 ₾\n\nთვეში: 2 ₾ -დან\n\nDell EcoLoop Essential Backpack 14-16 460-BDSS Black\nდამატება\n469 ₾\n\nთვეში: 13 ₾ -დან\n\nHP OMEN PHOTON Wireless Mouse 6CL96AA Black\nდამატება\n29 ₾\n\nHavit Gaming Mouse Pad HV-MP847 Pink\nდამატება\n79 ₾\n\nთვეში: 2 ₾ -დან\n\nTomtoc Defender A13 Laptop Sleeve 16 A13F2D1 Black\nდამატება\n65 ₾\n\nთვეში: 1 ₾ -დან\n\nRazer Gaming Mouse DeathAdder Essential USB White\nდამატება\n29 ₾\n\nHavit Gaming Mouse Pad HV-MP849 Black\nდამატება\n89 ₾\n\nთვეში: 2 ₾ -დან\n\nTomtoc Defender A14 Laptop Briefcase 16 A14F2D1 Black\nდამატება\n239 ₾\n\nთვეში: 6 ₾ -დან\n\nRazer Gaming Mouse Basilisk V3 Black\nდამატება\n49 ₾\n\nთვეში: 1 ₾ -დან\n\nHyperX Pulsefire Mat M Black\nდამატება\n299 ₾\n\nთვეში: 8 ₾ -დან\n\nRazer Gaming Mouse Naga V2 HyperSpeed WL Black\nდამატება\n59 ₾\n\nთვეში: 1 ₾ -დან\n\nHyperX Pulsefire Mat L Black\nდამატება\n229 ₾\n\nთვეში: 6 ₾ -დან\n\nRazer Gaming Mouse Basilisk V3 X HyperSpeed WL Black\nდამატება\n39 ₾\n\nთვეში: 1 ₾ -დან\n\nRazer Mouse Pad Sphex V3 S Black\nდამატება\n129 ₾\n\nთვეში: 3 ₾ -დან\n\nRazer Gaming Mouse Cobra Black\nდამატება\n89 ₾\n\nთვეში: 2 ₾ -დან\n\nRazer Mouse Pad Sphex V3 L Black\nდამატება\n19 ₾\n\nHavit Gaming Mouse HV-MS989GT Black/Red\nდამატება\n29 ₾\n\nHavit Gaming mouse Pad HV-MP860\nდამატება\n19 ₾\n\nHavit Gaming Mouse HV-MS626GT Black\nდამატება\n19 ₾\n\nHavit Gaming Mouse HV-MS66GT White/Blue\nდამატება\n149 ₾\n\nთვეში: 4 ₾ -დან\n\nHyperX Gaming Mouse Pulsefire Haste 2 Black\nდამატება\n19 ₾\n\nHavit Wireless Mouse HV-MS66GT Black\nდამატება\n179 ₾\n\nთვეში: 4 ₾ -დან\n\nLogitech Gaming Mouse G305 LIGHTSPEED WL L910-005282 ...\nდამატება\n259 ₾\n\nთვეში: 7 ₾ -დან\n\nLogitech Gaming Mouse G502 X L910-006138 Black\nდამატება\n259 ₾\n\nთვეში: 7 ₾ -დან\n\nLogitech Gaming Mouse G502 X L910-006138 White\nდამატება\n19 ₾\n\nHavit Gaming Mouse HV-MS626GT Black/Red\nდამატება\n19 ₾\n\nHavit Gaming Mouse HV-MS626GT Black/Blue\nდამატება\n349 ₾\n\nთვეში: 9 ₾ -დან\n\nLogitech Gaming Mouse G703 LIGHTSPEED WL L910-005640 ...\nდამატება\n89 ₾\n\nთვეში: 2 ₾ -დან\n\nLogitech Gaming Mouse G102 LIGHTSYNC L910-005823 Blac ...\nდამატება\n89 ₾\n\nთვეში: 2 ₾ -დან\n\nLogitech Gaming Mouse G102 LIGHTSYNC L910-005824 Whit ...\nდამატება\n89 ₾\n\nთვეში: 2 ₾ -დან\n\nLogitech Gaming Mouse G102 LIGHTSYNC L910-005801 Blue\nდამატება\n239 ₾\n\nთვეში: 6 ₾ -დან\n\nLogitech Gaming Mouse G502 HERO L910-005470 Black\nდამატება\n199 ₾\n\nთვეში: 5 ₾ -დან\n\nHyperX Pulsefire Haste 2 core Wireless Black\nდამატება\n199 ₾\n\nთვეში: 5 ₾ -დან\n\nHyperX Pulsefire Haste 2 core Wireless White\nდამატება\n59 ₾\n\nთვეში: 1 ₾ -დან\n\nHavit Gaming Mouse HV-MS954 Black\nდამატება\n39 ₾\n\nთვეში: 1 ₾ -დან\n\nHavit Gaming Mouse HV-MS1033 White\nდამატება\n39 ₾\n\nთვეში: 1 ₾ -დან\n\nHavit Gaming Mouse HV-MS1029 Pink\nდამატება\n59 ₾\n\nთვეში: 1 ₾ -დან\n\nHavit Gaming Mouse HV-MS966 Black/Green\nდამატება\n49 ₾\n\nთვეში: 1 ₾ -დან\n\nHavit Wireless Mouse HV-MS1039W Black/White\nდამატება\n79 ₾\n\nთვეში: 2 ₾ -დან\n\nHavit Wireless Mouse HV-MS970WB Pro Black\nდამატება\n79 ₾\n\nთვეში: 2 ₾ -დან\n\nHavit Wireless Mouse HV-MS970WB Pro Transparent White\nდამატება\n219 ₾\n\nთვეში: 6 ₾ -დან\n\nRazer Gaming Mouse Orochi V2 WL Pink\nდამატება\nპროდუქტის შესახებ\n\nთუ ეძებთ ლეპტოპს, რომელიც მარტივად გაუმკლავდება ყველაზე მოთხოვნად თამაშებს — Lenovo Legion 5 Pro 83F3000XRK Black შექმნილია სწორედ თქვენთვის. ეს მოდელი აერთიანებს მაღალ წარმადობას, გამძლე კონსტრუქცი...\n\nმეტის ნახვა\nმსგავსი პროდუქტები\n2999 ₾\n3199 ₾\n\nთვეში: 83 ₾ -დან\n\nLenovo LOQ 15 83DV00MPRK Luna Grey\nდამატება\n7999 ₾\n8799 ₾\n\nთვეში: 222 ₾ -დან\n\nLenovo Legion Pro 7 83F50026RK, Intel Core Ultra 9 27 ...\nდამატება\n4299 ₾\n\nთვეში: 119 ₾ -დან\n\nLenovo Legion 5 83LY008MRK Black\nდამატება\n3799 ₾\n\nთვეში: 105 ₾ -დან\n\nLenovo LOQ 15 83JE002DRK Grey\nდამატება\n6999 ₾\n\nთვეში: 194 ₾ -დან\n\nLenovo Legion 5 Pro 83F30012RK Black\nდამატება\nდამატებითი მახასიათებლები\nბრენდი\nბრენდი:\n\t\nLenovo\nმოდელი\nმოდელი:\n\t\nLegion\nტექნიკური მახასიათებლები\nცენტრალური პროცესორი:\n\t\nIntel Core Ultra 7-255HX\n\n\nპროცესორის თაობა:\n\t\nIntel Ultra 7 Series 2\n\n\nპროცესორის სიხშირე:\n\t\n1.8 GHz ~ 5.2 GHz\n\n\nბირთვების რაოდენობა:\n\t\n20\n\n\nნაკადების რაოდენობა:\n\t\n20\n\n\nგრაფიკული პროცესორი:\n\t\nNvidia GeForce RTX 5070\n\n\nგრაფიკული პროცესორის მეხსიერება:\n\t\n8 GB\n\n\nგრაფიკული პროცესორის ტიპი:\n\t\nარა ინტეგრირებული\n\n\nოპერაციული სისტემა:\n\t\nNo\n\n\nBluetooth:\n\t\n5.4\nეკრანი\nეკრანის ზომა:\n\t\n16 Inches\n\n\nრეზოლუცია:\n\t\nWQXGA\n\n\nეკრანის ტიპი:\n\t\nOled\n\n\nსენსორული ეკრანი:\n\t\nNo\n\n\nგანახლების სიხშირე:\n\t\n165 Hz\nდამატებითი მახასიათებლები\nკლავიატურის განათება:\n\t\nYes\n\n\nNumpad:\n\t\nYes\n\n\nდისკის წამკითხველი:\n\t\nNo\n\n\nვებ კამერა:\n\t\nYes\n\n\nლეპტოპის ტიპი:\n\t\nგეიმინგი\nმეხსიერება\nშიდა მეხსიერება:\n\t\n1 TB\n\n\nშიდა მეხსიერების ტიპი:\n\t\nSSD\n\n\nშიდა მეხსიერების ინტერფეისი:\n\t\nM.2\n\n\nოპერატიული მეხსიერება:\n\t\n32 GB\n\n\nოპერატიული მეხსიერების ტიპი:\n\t\nDDR5\n\n\nოპერატიული მეხსიერების სიხშირე:\n\t\n5600 MHz\nპორტები\nUSB:\n\t\n3 x USB-A\n\n\nType-C:\n\t\n2x\n\n\nType-C პორტით დამუხტვა:\n\t\nYes\n\n\nHDMI:\n\t\nYes\n\n\nლან პორტი:\n\t\nYes\n\n\n3.5mm:\n\t\nYes\nზომა/წონა\nწონა:\n\t\n2.43 kg\nფერი\nფერი:\n\t\nBlack\nმეტის ნახვა\nგაეცანი საგარანტიო პირობებს\nსაგარანტიო პირობები\nფილიალები\nმარაგშია\nშეკვეთიდან 2-5 დღეში\nზუმერის წერეთლის ფილიალი\n\nთბილისი - წერეთლის გამზირი, N1.\n\nმარაგშია\n+995 591 967 601\nორშ-შაბ: 10:00:00 - 20:00:00\nკვირა: 10:00:00 - 19:00:00\nზუმერის \"თბილისი ცენტრალის\" ფილიალი\n\nთბილისი - \"თბილისი ცენტრალი\"- lll სართული\n\nმარაგშია\n+995 599 862 449\nორშ-შაბ: 10:00:00 - 20:00:00\nკვირა: 10:00:00 - 19:00:00\nზუმერის City Mall საბურთალო-ს ფილიალი\n\nთბილისი - \"სითი მოლი\" - პეტრე ქავთარაძის N1\n\nმარაგშია\n+995 591 971 962\nორშ-შაბ: 10:00:00 - 22:00:00\nკვირა: 10:00:00 - 22:00:00\nზუმერის თბილისი მოლის ფილიალი\n\nთბილისი - „თბილისი მოლი\" - I სართული. აღმაშენებლის ხეივანი მე-16 კმ\n\nმარაგშია\n+995 591 967 608\nორშ-შაბ: 10:00:00 - 22:00:00\nკვირა: 10:00:00 - 22:00:00\nზუმერის ისთ ფოინთის ფილიალი\n\nთბილისი - \"ისთ ფოინთი\" - ალ. თვალჭრელიძე N2\n\nმარაგშია\n+995 591 340 476\nორშ-შაბ: 10:00:00 - 22:00:00\nკვირა: 10:00:00 - 22:00:00\nბათუმი ჭავჭავაძის ფილიალი\n\nბათუმი - ბათუმი, ჭავჭავაძის N21\n\nმარაგშია\n+995 591 967 606\nორშ-შაბ: 10:00:00 - 20:00:00\nკვირა: 10:00:00 - 19:00:00\nბათუმის გრანდ მოლის ფილიალი\n\nბათუმი - \"გრანდ მოლი\" - შერიფ ხიმშიაშვილის 29\n\nმარაგშია\n+995 591 022 872\nორშ-შაბ: 10:00:00 - 22:00:00\nკვირა: 10:00:00 - 22:00:00\nმეტის ნახვა\n5999 ₾\n6199 ₾\n\nთვეში: 166.6 ₾ -დან\n\nმარაგი ფილიალებში\nფასის დაზღვევა\nფასის კონტროლი\nფასის დაჯავშნა\nყიდვა\nშედარება\nდამატება\nნავიგაცია\n\nპერსონალურ მონაცემთა დაცვის პოლიტიკა\n\nჩვენ შესახებ\n\nწესები და პირობები\n\nმიწოდების სერვისი\n\nკარიერა\n\nგადახდები\n\nSetanta Sports\n\nგადახდის მეთოდები\n\nგარანტია\n\nგანვადება\n\nნივთის დაბრუნება\n\nნივთის ონლაინ ყიდვის ინსტრუქცია\n\nგამოგვყევი\n\nFacebook\n\nYoutube\n\nInstagram\n\nTik Tok\n\nკონტაქტი\n\nInfo@zoommer.ge\n\n+995 (32) 2 60 30 60 / *7007\n\nფილიალები\n\nკორპორატიული გაყიდვები\n\nZoommer App\n\nCopyright © 2023 Zoommer.ge. All rights reserved.\n\nCookie პოლიტიკა\n\nსაიტით სარგებლობის გაგრძელებით, შენ ეთანხმები Cookie ჩანაწერების გამოყენებას. მეტი ინფორმაცისათვის იხილეთ კონფიდენციალურობის პოლიტიკა\n\nგასაგებია",
    "specs": {
      "ბრენდი:": "Lenovo",
      "მოდელი:": "Legion",
      "ცენტრალური პროცესორი:": "Intel Core Ultra 7-255HX",
      "პროცესორის თაობა:": "Intel Ultra 7 Series 2",
      "პროცესორის სიხშირე:": "1.8 GHz ~ 5.2 GHz",
      "ბირთვების რაოდენობა:": "20",
      "ნაკადების რაოდენობა:": "20",
      "გრაფიკული პროცესორი:": "Nvidia GeForce RTX 5070",
      "გრაფიკული პროცესორის მეხსიერება:": "8 GB",
      "გრაფიკული პროცესორის ტიპი:": "არა ინტეგრირებული",
      "ოპერაციული სისტემა:": "No",
      "Bluetooth:": "5.4",
      "ეკრანის ზომა:": "16 Inches",
      "რეზოლუცია:": "WQXGA",
      "ეკრანის ტიპი:": "Oled",
      "სენსორული ეკრანი:": "No",
      "განახლების სიხშირე:": "165 Hz",
      "კლავიატურის განათება:": "Yes",
      "Numpad:": "Yes",
      "დისკის წამკითხველი:": "No",
      "ვებ კამერა:": "Yes",
      "ლეპტოპის ტიპი:": "გეიმინგი",
      "შიდა მეხსიერება:": "1 TB",
      "შიდა მეხსიერების ტიპი:": "SSD",
      "შიდა მეხსიერების ინტერფეისი:": "M.2",
      "ოპერატიული მეხსიერება:": "32 GB",
      "ოპერატიული მეხსიერების ტიპი:": "DDR5",
      "ოპერატიული მეხსიერების სიხშირე:": "5600 MHz",
      "USB:": "3 x USB-A",
      "Type-C:": "2x",
      "Type-C პორტით დამუხტვა:": "Yes",
      "HDMI:": "Yes",
      "ლან პორტი:": "Yes",
      "3.5mm:": "Yes",
      "წონა:": "2.43 kg",
      "ფერი:": "Black"
    }
  },
  {
    "category": "Gaming ლეპტოპები",
    "title": "Asus ROG Strix 18 G835LX-SA034W Black",
    "price": 15999.0,
    "link": "https://zoommer.ge/leptopebi/asus-rog-strix-18-g835lx-sa034w-black-p48540",
    "image": "/_next/image?url=https%3A%2F%2Fs3.zoommer.ge%2Fsite%2F5ea31e12-7387-42cd-9874-f99be31a5bbc_Thumb.jpeg&w=384&q=50",
    "product_title_detail": "Asus ROG Strix 18 G835LX-SA034W Black",
    "description": "*7007 / +995 (32) 2 60 30 60\nსავაჭრო პოლიტიკა\nგანვადება\nკარიერა\nTrade In\nფილიალები\nნავიგაცია\nკალათა\nშესვლა\n%\nმთავარი\nლეპტოპები\nAsus\n#ZOOM-036805\nAsus ROG Strix 18 G835LX-SA034W Black\nეკრანის ზომა\n18 Inches\nრეზოლუცია\nWQXGA\nეკრანის ტიპი\nMini LED\nგანახლების სიხშირე\n240 Hz\nშიდა მეხსიერება\n2 TB\nBluetooth\n5.4\nType-C\n2x\nოპერატიული მეხსიერება\n32 GB\nერთად იაფია\nდაამატე ნივთი\nAsus ROG Strix 18 G835LX-SA034W Black\n15999 ₾\nRazer Gaming Mouse DeathAdder Essential USB White\n52 ₾\n65 ₾\nHavit Gaming Cooling Pad HV-F2083 Black\n75.65 ₾\n89 ₾\nჯამური ფასი (2)\n16126.65 ₾\n16153 ₾\nყიდვა\nაქსესუარები\nაღწერა\nმსგავსი\nმახასიათებლები\nფილიალები\nაქსესუარები\nაღწერა\nმსგავსი\nმახასიათებლები\nფილიალები\n89 ₾\n\nთვეში: 2 ₾ -დან\n\nHavit Gaming Cooling Pad HV-F2083 Black\nდამატება\n219 ₾\n\nთვეში: 6 ₾ -დან\n\nRazer Gaming Mouse Orochi V2 WL Black\nდამატება\n59 ₾\n\nთვეში: 1 ₾ -დან\n\nHavit Gaming mouse Pad HV-MP901\nდამატება\n69 ₾\n\nთვეში: 1 ₾ -დან\n\nXiaomi Mi Router 4A DVB4230GL White\nდამატება\n219 ₾\n\nთვეში: 6 ₾ -დან\n\nRazer Gaming Mouse Orochi V2 WL White\nდამატება\n9 ₾\n\nHavit Gaming mouse Pad HV-MP838\nდამატება\n85 ₾\n\nთვეში: 2 ₾ -დან\n\nTP-Link Archer C50 AC1200 White\nდამატება\n209 ₾\n\nთვეში: 5 ₾ -დან\n\nRazer Gaming Mouse DeathAdder V2 X Hyperspeed WL/BT/U ...\nდამატება\n9 ₾\n\nHavit Gaming mouse Pad HV-MP843 Black\nდამატება\n119 ₾\n\nთვეში: 3 ₾ -დან\n\nTP-Link Archer C6 AC1200 Black\nდამატება\n139 ₾\n\nთვეში: 3 ₾ -დან\n\nLogitech Gaming Mouse G402 Hyperion Fury black\nდამატება\n149 ₾\n\nთვეში: 4 ₾ -დან\n\nRazer Mouse Pad Firefly V2 RGB M Black\nდამატება\n159 ₾\n\nთვეში: 4 ₾ -დან\n\nXiaomi Router AX1500 White\nდამატება\n29 ₾\n\nHavit Gaming Mouse HV-MS1010 Black\nდამატება\n199 ₾\n\nთვეში: 5 ₾ -დან\n\nRazer Mouse Pad Goliathus Extended Chroma XXL Black\nდამატება\n179 ₾\n\nთვეში: 4 ₾ -დან\n\nXiaomi Mesh System AX3000 NE 1 pack White\nდამატება\n79 ₾\n\nთვეში: 2 ₾ -დან\n\nRazer Gaming Mouse DeathAdder Essential USB Black\nდამატება\n149 ₾\n\nთვეში: 4 ₾ -დან\n\nHyperX Pulsefire Mat RGB Black\nდამატება\n299 ₾\n\nთვეში: 8 ₾ -დან\n\nXiaomi Mesh System AX3000 NE 2 pack White\nდამატება\n119 ₾\n\nთვეში: 3 ₾ -დან\n\nHyperX Pulsefire Surge Mouse Black\nდამატება\n29 ₾\n\nHavit Gaming Mouse Pad HV-MP845 Black\nდამატება\n249 ₾\n\nთვეში: 6 ₾ -დან\n\nXiaomi Router BE3600 White\nდამატება\n469 ₾\n\nთვეში: 13 ₾ -დან\n\nHP OMEN PHOTON Wireless Mouse 6CL96AA Black\nდამატება\n29 ₾\n\nHavit Gaming Mouse Pad HV-MP847 Pink\nდამატება\n65 ₾\n\nთვეში: 1 ₾ -დან\n\nRazer Gaming Mouse DeathAdder Essential USB White\nდამატება\n29 ₾\n\nHavit Gaming Mouse Pad HV-MP849 Black\nდამატება\n239 ₾\n\nთვეში: 6 ₾ -დან\n\nRazer Gaming Mouse Basilisk V3 Black\nდამატება\n49 ₾\n\nთვეში: 1 ₾ -დან\n\nHyperX Pulsefire Mat M Black\nდამატება\n299 ₾\n\nთვეში: 8 ₾ -დან\n\nRazer Gaming Mouse Naga V2 HyperSpeed WL Black\nდამატება\n59 ₾\n\nთვეში: 1 ₾ -დან\n\nHyperX Pulsefire Mat L Black\nდამატება\n229 ₾\n\nთვეში: 6 ₾ -დან\n\nRazer Gaming Mouse Basilisk V3 X HyperSpeed WL Black\nდამატება\n39 ₾\n\nთვეში: 1 ₾ -დან\n\nRazer Mouse Pad Sphex V3 S Black\nდამატება\n129 ₾\n\nთვეში: 3 ₾ -დან\n\nRazer Gaming Mouse Cobra Black\nდამატება\n89 ₾\n\nთვეში: 2 ₾ -დან\n\nRazer Mouse Pad Sphex V3 L Black\nდამატება\n19 ₾\n\nHavit Gaming Mouse HV-MS989GT Black/Red\nდამატება\n29 ₾\n\nHavit Gaming mouse Pad HV-MP860\nდამატება\n19 ₾\n\nHavit Gaming Mouse HV-MS626GT Black\nდამატება\n19 ₾\n\nHavit Gaming Mouse HV-MS66GT White/Blue\nდამატება\n149 ₾\n\nთვეში: 4 ₾ -დან\n\nHyperX Gaming Mouse Pulsefire Haste 2 Black\nდამატება\n19 ₾\n\nHavit Wireless Mouse HV-MS66GT Black\nდამატება\n179 ₾\n\nთვეში: 4 ₾ -დან\n\nLogitech Gaming Mouse G305 LIGHTSPEED WL L910-005282 ...\nდამატება\n259 ₾\n\nთვეში: 7 ₾ -დან\n\nLogitech Gaming Mouse G502 X L910-006138 Black\nდამატება\n259 ₾\n\nთვეში: 7 ₾ -დან\n\nLogitech Gaming Mouse G502 X L910-006138 White\nდამატება\n19 ₾\n\nHavit Gaming Mouse HV-MS626GT Black/Red\nდამატება\n19 ₾\n\nHavit Gaming Mouse HV-MS626GT Black/Blue\nდამატება\n349 ₾\n\nთვეში: 9 ₾ -დან\n\nLogitech Gaming Mouse G703 LIGHTSPEED WL L910-005640 ...\nდამატება\n89 ₾\n\nთვეში: 2 ₾ -დან\n\nLogitech Gaming Mouse G102 LIGHTSYNC L910-005823 Blac ...\nდამატება\n89 ₾\n\nთვეში: 2 ₾ -დან\n\nLogitech Gaming Mouse G102 LIGHTSYNC L910-005824 Whit ...\nდამატება\n89 ₾\n\nთვეში: 2 ₾ -დან\n\nLogitech Gaming Mouse G102 LIGHTSYNC L910-005801 Blue\nდამატება\n239 ₾\n\nთვეში: 6 ₾ -დან\n\nLogitech Gaming Mouse G502 HERO L910-005470 Black\nდამატება\n199 ₾\n\nთვეში: 5 ₾ -დან\n\nHyperX Pulsefire Haste 2 core Wireless Black\nდამატება\n199 ₾\n\nთვეში: 5 ₾ -დან\n\nHyperX Pulsefire Haste 2 core Wireless White\nდამატება\n59 ₾\n\nთვეში: 1 ₾ -დან\n\nHavit Gaming Mouse HV-MS954 Black\nდამატება\n39 ₾\n\nთვეში: 1 ₾ -დან\n\nHavit Gaming Mouse HV-MS1033 White\nდამატება\n39 ₾\n\nთვეში: 1 ₾ -დან\n\nHavit Gaming Mouse HV-MS1029 Pink\nდამატება\n59 ₾\n\nთვეში: 1 ₾ -დან\n\nHavit Gaming Mouse HV-MS966 Black/Green\nდამატება\n49 ₾\n\nთვეში: 1 ₾ -დან\n\nHavit Wireless Mouse HV-MS1039W Black/White\nდამატება\n79 ₾\n\nთვეში: 2 ₾ -დან\n\nHavit Wireless Mouse HV-MS970WB Pro Black\nდამატება\n79 ₾\n\nთვეში: 2 ₾ -დან\n\nHavit Wireless Mouse HV-MS970WB Pro Transparent White\nდამატება\n219 ₾\n\nთვეში: 6 ₾ -დან\n\nRazer Gaming Mouse Orochi V2 WL Pink\nდამატება\nპროდუქტის შესახებ\n\nთუ ეძებთ ლეპტოპს, რომელიც მარტივად გაუმკლავდება ყველაზე მოთხოვნად თამაშებს — Asus ROG Strix 18 G835LX-SA034W Black შექმნილია სწორედ თქვენთვის. ეს მოდელი აერთიანებს მაღალ წარმადობას, გამძლე კონსტრუქც...\n\nმეტის ნახვა\nმსგავსი პროდუქტები\n2599 ₾\n2799 ₾\n\nთვეში: 72 ₾ -დან\n\nAsus TUF 15 FX507ZC4-HN009 Black\nდამატება\n2249 ₾\n2499 ₾\n\nთვეში: 62 ₾ -დან\n\nAsus TUF 15 FA506NF-HN018, AMD Ryzen 5-7535HS, NVIDIA ...\nდამატება\n2999 ₾\n3699 ₾\n\nთვეში: 83 ₾ -დან\n\nAsus TUF 15 FA507NUR-LP044 Mercha Grey\nდამატება\n3299 ₾\n3499 ₾\n\nთვეში: 91 ₾ -დან\n\nAsus TUF 14 FA401UU-RG013 Jaeger Grey\nდამატება\n4179 ₾\n\nთვეში: 116 ₾ -დან\n\nAsus TUF A16 FA608WV-QT053 Grey\nდამატება\n2179 ₾\n2279 ₾\n\nთვეში: 60 ₾ -დან\n\nAsus TUF 15 FA506NFR-HN021, AMD Ryzen 7 7435HS, Nvidi ...\nდამატება\n5599 ₾\n5899 ₾\n\nთვეში: 155 ₾ -დან\n\nAsus TUF 18 FA808UP-S8030 Grey\nდამატება\n7299 ₾\n\nთვეში: 202 ₾ -დან\n\nAsus ROG Strix 16 G615JPR-S5101 Grey\nდამატება\n10399 ₾\n10499 ₾\n\nთვეში: 288 ₾ -დან\n\nAsus ROG Strix 18 G835LR-SA005 Black\nდამატება\n6499 ₾\n\nთვეში: 180 ₾ -დან\n\nAsus ROG Strix 16 G614PR-RV007, AMD Ryzen 9-7940HX, N ...\nდამატება\n6699 ₾\n\nთვეში: 186 ₾ -დან\n\nAsus ROG Strix G16 G615JPR-RV113, Intel core i7-14650 ...\nდამატება\n8499 ₾\n\nთვეში: 236 ₾ -დან\n\nAsus ROG Strix G18 G815LR-S9085, Intel Core Ultra 9 2 ...\nდამატება\n4999 ₾\n\nთვეში: 138 ₾ -დან\n\nAsus TUF F16 FX608JMR-RV073, Intel core i7-14650HX 16 ...\nდამატება\n2699 ₾\n\nთვეში: 74 ₾ -დან\n\nAsus TUF 16 FX607VJ-RL005, Intel Core 5-210H, Nvidia ...\nდამატება\n4199 ₾\n\nთვეში: 116 ₾ -დან\n\nAsus TUF F16 FX608JHR-RV035, Intel core i7-14650HX 16 ...\nდამატება\nდამატებითი მახასიათებლები\nბრენდი\nბრენდი:\n\t\nAsus\nმოდელი\nმოდელი:\n\t\nROG\nტექნიკური მახასიათებლები\nცენტრალური პროცესორი:\n\t\nIntel Core Ultra 9-285HX\n\n\nპროცესორის თაობა:\n\t\nIntel Ultra 9 Series 2\n\n\nპროცესორის სიხშირე:\n\t\n2.8 GHz ~ 5.5 GHz\n\n\nბირთვების რაოდენობა:\n\t\n16\n\n\nნაკადების რაოდენობა:\n\t\n24\n\n\nგრაფიკული პროცესორი:\n\t\nNvidia GeForce RTX 5090\n\n\nგრაფიკული პროცესორის მეხსიერება:\n\t\n16 GB\n\n\nგრაფიკული პროცესორის ტიპი:\n\t\nარა ინტეგრირებული\n\n\nოპერაციული სისტემა:\n\t\nWindows 11 Home\n\n\nBluetooth:\n\t\n5.4\nეკრანი\nეკრანის ზომა:\n\t\n18 Inches\n\n\nრეზოლუცია:\n\t\nWQXGA\n\n\nეკრანის ტიპი:\n\t\nMini LED\n\n\nსენსორული ეკრანი:\n\t\nNo\n\n\nგანახლების სიხშირე:\n\t\n240 Hz\nდამატებითი მახასიათებლები\nკლავიატურის განათება:\n\t\nYes\n\n\nNumpad:\n\t\nYes\n\n\nდისკის წამკითხველი:\n\t\nNo\n\n\nვებ კამერა:\n\t\nYes\n\n\nლეპტოპის ტიპი:\n\t\nგეიმინგი\nმეხსიერება\nშიდა მეხსიერება:\n\t\n2 TB\n\n\nშიდა მეხსიერების ტიპი:\n\t\nSSD\n\n\nშიდა მეხსიერების ინტერფეისი:\n\t\nM.2\n\n\nოპერატიული მეხსიერება:\n\t\n32 GB\n\n\nოპერატიული მეხსიერების ტიპი:\n\t\nDDR5\n\n\nოპერატიული მეხსიერების სიხშირე:\n\t\n5600 MHz\nპორტები\nUSB:\n\t\n3 x USB-A\n\n\nType-C:\n\t\n2x\n\n\nType-C პორტით დამუხტვა:\n\t\nYes\n\n\nHDMI:\n\t\nYes\n\n\nლან პორტი:\n\t\nYes\n\n\n3.5mm:\n\t\nYes\nზომა/წონა\nწონა:\n\t\n3.48 kg\nფერი\nფერი:\n\t\nBlack\nმეტის ნახვა\nგაეცანი საგარანტიო პირობებს\nსაგარანტიო პირობები\nფილიალები\nმარაგშია\nშეკვეთიდან 2-5 დღეში\nზუმერის City Mall საბურთალო-ს ფილიალი\n\nთბილისი - \"სითი მოლი\" - პეტრე ქავთარაძის N1\n\nმარაგშია\n+995 591 971 962\nორშ-შაბ: 10:00:00 - 22:00:00\nკვირა: 10:00:00 - 22:00:00\n15999 ₾\n\nთვეში: 444.4 ₾ -დან\n\nმარაგი ფილიალებში\nფასის დაზღვევა\nფასის კონტროლი\nფასის დაჯავშნა\nყიდვა\nშედარება\nდამატება\nნავიგაცია\n\nპერსონალურ მონაცემთა დაცვის პოლიტიკა\n\nჩვენ შესახებ\n\nწესები და პირობები\n\nმიწოდების სერვისი\n\nკარიერა\n\nგადახდები\n\nSetanta Sports\n\nგადახდის მეთოდები\n\nგარანტია\n\nგანვადება\n\nნივთის დაბრუნება\n\nნივთის ონლაინ ყიდვის ინსტრუქცია\n\nგამოგვყევი\n\nFacebook\n\nYoutube\n\nInstagram\n\nTik Tok\n\nკონტაქტი\n\nInfo@zoommer.ge\n\n+995 (32) 2 60 30 60 / *7007\n\nფილიალები\n\nკორპორატიული გაყიდვები\n\nZoommer App\n\nCopyright © 2023 Zoommer.ge. All rights reserved.\n\nCookie პოლიტიკა\n\nსაიტით სარგებლობის გაგრძელებით, შენ ეთანხმები Cookie ჩანაწერების გამოყენებას. მეტი ინფორმაცისათვის იხილეთ კონფიდენციალურობის პოლიტიკა\n\nგასაგებია",
    "specs": {
      "ბრენდი:": "Asus",
      "მოდელი:": "ROG",
      "ცენტრალური პროცესორი:": "Intel Core Ultra 9-285HX",
      "პროცესორის თაობა:": "Intel Ultra 9 Series 2",
      "პროცესორის სიხშირე:": "2.8 GHz ~ 5.5 GHz",
      "ბირთვების რაოდენობა:": "16",
      "ნაკადების რაოდენობა:": "24",
      "გრაფიკული პროცესორი:": "Nvidia GeForce RTX 5090",
      "გრაფიკული პროცესორის მეხსიერება:": "16 GB",
      "გრაფიკული პროცესორის ტიპი:": "არა ინტეგრირებული",
      "ოპერაციული სისტემა:": "Windows 11 Home",
      "Bluetooth:": "5.4",
      "ეკრანის ზომა:": "18 Inches",
      "რეზოლუცია:": "WQXGA",
      "ეკრანის ტიპი:": "Mini LED",
      "სენსორული ეკრანი:": "No",
      "განახლების სიხშირე:": "240 Hz",
      "კლავიატურის განათება:": "Yes",
      "Numpad:": "Yes",
      "დისკის წამკითხველი:": "No",
      "ვებ კამერა:": "Yes",
      "ლეპტოპის ტიპი:": "გეიმინგი",
      "შიდა მეხსიერება:": "2 TB",
      "შიდა მეხსიერების ტიპი:": "SSD",
      "შიდა მეხსიერების ინტერფეისი:": "M.2",
      "ოპერატიული მეხსიერება:": "32 GB",
      "ოპერატიული მეხსიერების ტიპი:": "DDR5",
      "ოპერატიული მეხსიერების სიხშირე:": "5600 MHz",
      "USB:": "3 x USB-A",
      "Type-C:": "2x",
      "Type-C პორტით დამუხტვა:": "Yes",
      "HDMI:": "Yes",
      "ლან პორტი:": "Yes",
      "3.5mm:": "Yes",
      "წონა:": "3.48 kg",
      "ფერი:": "Black"
    }
  },
  {
    "category": "Gaming ლეპტოპები",
    "title": "Asus ROG Strix 18 G835LR-SA005 Black",
    "price": 10399.0,
    "link": "https://zoommer.ge/leptopebi/asus-rog-strix-18-g835lr-sa005-black-p48539",
    "image": "/_next/image?url=https%3A%2F%2Fs3.zoommer.ge%2Fsite%2F86eb848f-cf7c-4e4d-8022-eebc64db7416_Thumb.jpeg&w=384&q=50",
    "product_title_detail": "Asus ROG Strix 18 G835LR-SA005 Black",
    "description": "*7007 / +995 (32) 2 60 30 60\nფილიალები\nნავიგაცია\nკალათა\nშესვლა\n%\nმთავარი\nლეპტოპები\nAsus\n#ZOOM-036804\nAsus ROG Strix 18 G835LR-SA005 Black\nეკრანის ზომა\n18 Inches\nრეზოლუცია\nWQXGA\nეკრანის ტიპი\nIPS\nგანახლების სიხშირე\n240 Hz\nშიდა მეხსიერება\n2 TB\nBluetooth\n5.4\nType-C\n2x\nოპერატიული მეხსიერება\n32 GB\nერთად იაფია\nდაამატე ნივთი\nAsus ROG Strix 18 G835LR-SA005 Black\n10399 ₾\nRazer Gaming Mouse DeathAdder Essential USB White\n52 ₾\n65 ₾\nHavit Gaming Cooling Pad HV-F2083 Black\n75.65 ₾\n89 ₾\nჯამური ფასი (2)\n10526.65 ₾\n10553 ₾\nყიდვა\nაქსესუარები\nაღწერა\nმსგავსი\nმახასიათებლები\nფილიალები\nაქსესუარები\nაღწერა\nმსგავსი\nმახასიათებლები\nფილიალები\n89 ₾\n\nთვეში: 2 ₾ -დან\n\nHavit Gaming Cooling Pad HV-F2083 Black\nდამატება\n219 ₾\n\nთვეში: 6 ₾ -დან\n\nRazer Gaming Mouse Orochi V2 WL Black\nდამატება\n59 ₾\n\nთვეში: 1 ₾ -დან\n\nHavit Gaming mouse Pad HV-MP901\nდამატება\n69 ₾\n\nთვეში: 1 ₾ -დან\n\nXiaomi Mi Router 4A DVB4230GL White\nდამატება\n219 ₾\n\nთვეში: 6 ₾ -დან\n\nRazer Gaming Mouse Orochi V2 WL White\nდამატება\n9 ₾\n\nHavit Gaming mouse Pad HV-MP838\nდამატება\n85 ₾\n\nთვეში: 2 ₾ -დან\n\nTP-Link Archer C50 AC1200 White\nდამატება\n209 ₾\n\nთვეში: 5 ₾ -დან\n\nRazer Gaming Mouse DeathAdder V2 X Hyperspeed WL/BT/U ...\nდამატება\n9 ₾\n\nHavit Gaming mouse Pad HV-MP843 Black\nდამატება\n119 ₾\n\nთვეში: 3 ₾ -დან\n\nTP-Link Archer C6 AC1200 Black\nდამატება\n139 ₾\n\nთვეში: 3 ₾ -დან\n\nLogitech Gaming Mouse G402 Hyperion Fury black\nდამატება\n149 ₾\n\nთვეში: 4 ₾ -დან\n\nRazer Mouse Pad Firefly V2 RGB M Black\nდამატება\n159 ₾\n\nთვეში: 4 ₾ -დან\n\nXiaomi Router AX1500 White\nდამატება\n29 ₾\n\nHavit Gaming Mouse HV-MS1010 Black\nდამატება\n199 ₾\n\nთვეში: 5 ₾ -დან\n\nRazer Mouse Pad Goliathus Extended Chroma XXL Black\nდამატება\n179 ₾\n\nთვეში: 4 ₾ -დან\n\nXiaomi Mesh System AX3000 NE 1 pack White\nდამატება\n79 ₾\n\nთვეში: 2 ₾ -დან\n\nRazer Gaming Mouse DeathAdder Essential USB Black\nდამატება\n149 ₾\n\nთვეში: 4 ₾ -დან\n\nHyperX Pulsefire Mat RGB Black\nდამატება\n299 ₾\n\nთვეში: 8 ₾ -დან\n\nXiaomi Mesh System AX3000 NE 2 pack White\nდამატება\n119 ₾\n\nთვეში: 3 ₾ -დან\n\nHyperX Pulsefire Surge Mouse Black\nდამატება\n29 ₾\n\nHavit Gaming Mouse Pad HV-MP845 Black\nდამატება\n249 ₾\n\nთვეში: 6 ₾ -დან\n\nXiaomi Router BE3600 White\nდამატება\n469 ₾\n\nთვეში: 13 ₾ -დან\n\nHP OMEN PHOTON Wireless Mouse 6CL96AA Black\nდამატება\n29 ₾\n\nHavit Gaming Mouse Pad HV-MP847 Pink\nდამატება\n65 ₾\n\nთვეში: 1 ₾ -დან\n\nRazer Gaming Mouse DeathAdder Essential USB White\nდამატება\n29 ₾\n\nHavit Gaming Mouse Pad HV-MP849 Black\nდამატება\n239 ₾\n\nთვეში: 6 ₾ -დან\n\nRazer Gaming Mouse Basilisk V3 Black\nდამატება\n49 ₾\n\nთვეში: 1 ₾ -დან\n\nHyperX Pulsefire Mat M Black\nდამატება\n299 ₾\n\nთვეში: 8 ₾ -დან\n\nRazer Gaming Mouse Naga V2 HyperSpeed WL Black\nდამატება\n59 ₾\n\nთვეში: 1 ₾ -დან\n\nHyperX Pulsefire Mat L Black\nდამატება\n229 ₾\n\nთვეში: 6 ₾ -დან\n\nRazer Gaming Mouse Basilisk V3 X HyperSpeed WL Black\nდამატება\n39 ₾\n\nთვეში: 1 ₾ -დან\n\nRazer Mouse Pad Sphex V3 S Black\nდამატება\n129 ₾\n\nთვეში: 3 ₾ -დან\n\nRazer Gaming Mouse Cobra Black\nდამატება\n89 ₾\n\nთვეში: 2 ₾ -დან\n\nRazer Mouse Pad Sphex V3 L Black\nდამატება\n19 ₾\n\nHavit Gaming Mouse HV-MS989GT Black/Red\nდამატება\n29 ₾\n\nHavit Gaming mouse Pad HV-MP860\nდამატება\n19 ₾\n\nHavit Gaming Mouse HV-MS626GT Black\nდამატება\n19 ₾\n\nHavit Gaming Mouse HV-MS66GT White/Blue\nდამატება\n149 ₾\n\nთვეში: 4 ₾ -დან\n\nHyperX Gaming Mouse Pulsefire Haste 2 Black\nდამატება\n19 ₾\n\nHavit Wireless Mouse HV-MS66GT Black\nდამატება\n179 ₾\n\nთვეში: 4 ₾ -დან\n\nLogitech Gaming Mouse G305 LIGHTSPEED WL L910-005282 ...\nდამატება\n259 ₾\n\nთვეში: 7 ₾ -დან\n\nLogitech Gaming Mouse G502 X L910-006138 Black\nდამატება\n259 ₾\n\nთვეში: 7 ₾ -დან\n\nLogitech Gaming Mouse G502 X L910-006138 White\nდამატება\n19 ₾\n\nHavit Gaming Mouse HV-MS626GT Black/Red\nდამატება\n19 ₾\n\nHavit Gaming Mouse HV-MS626GT Black/Blue\nდამატება\n349 ₾\n\nთვეში: 9 ₾ -დან\n\nLogitech Gaming Mouse G703 LIGHTSPEED WL L910-005640 ...\nდამატება\n89 ₾\n\nთვეში: 2 ₾ -დან\n\nLogitech Gaming Mouse G102 LIGHTSYNC L910-005823 Blac ...\nდამატება\n89 ₾\n\nთვეში: 2 ₾ -დან\n\nLogitech Gaming Mouse G102 LIGHTSYNC L910-005824 Whit ...\nდამატება\n89 ₾\n\nთვეში: 2 ₾ -დან\n\nLogitech Gaming Mouse G102 LIGHTSYNC L910-005801 Blue\nდამატება\n239 ₾\n\nთვეში: 6 ₾ -დან\n\nLogitech Gaming Mouse G502 HERO L910-005470 Black\nდამატება\n199 ₾\n\nთვეში: 5 ₾ -დან\n\nHyperX Pulsefire Haste 2 core Wireless Black\nდამატება\n199 ₾\n\nთვეში: 5 ₾ -დან\n\nHyperX Pulsefire Haste 2 core Wireless White\nდამატება\n59 ₾\n\nთვეში: 1 ₾ -დან\n\nHavit Gaming Mouse HV-MS954 Black\nდამატება\n39 ₾\n\nთვეში: 1 ₾ -დან\n\nHavit Gaming Mouse HV-MS1033 White\nდამატება\n39 ₾\n\nთვეში: 1 ₾ -დან\n\nHavit Gaming Mouse HV-MS1029 Pink\nდამატება\n59 ₾\n\nთვეში: 1 ₾ -დან\n\nHavit Gaming Mouse HV-MS966 Black/Green\nდამატება\n49 ₾\n\nთვეში: 1 ₾ -დან\n\nHavit Wireless Mouse HV-MS1039W Black/White\nდამატება\n79 ₾\n\nთვეში: 2 ₾ -დან\n\nHavit Wireless Mouse HV-MS970WB Pro Black\nდამატება\n79 ₾\n\nთვეში: 2 ₾ -დან\n\nHavit Wireless Mouse HV-MS970WB Pro Transparent White\nდამატება\n219 ₾\n\nთვეში: 6 ₾ -დან\n\nRazer Gaming Mouse Orochi V2 WL Pink\nდამატება\nპროდუქტის შესახებ\n\nთუ ეძებთ ლეპტოპს, რომელიც მარტივად გაუმკლავდება ყველაზე მოთხოვნად თამაშებს — Asus ROG Strix 18 G835LR-SA005 Black შექმნილია სწორედ თქვენთვის. ეს მოდელი აერთიანებს მაღალ წარმადობას, გამძლე კონსტრუქცი...\n\nმეტის ნახვა\nმსგავსი პროდუქტები\n2599 ₾\n2799 ₾\n\nთვეში: 72 ₾ -დან\n\nAsus TUF 15 FX507ZC4-HN009 Black\nდამატება\n2249 ₾\n2499 ₾\n\nთვეში: 62 ₾ -დან\n\nAsus TUF 15 FA506NF-HN018, AMD Ryzen 5-7535HS, NVIDIA ...\nდამატება\n2999 ₾\n3699 ₾\n\nთვეში: 83 ₾ -დან\n\nAsus TUF 15 FA507NUR-LP044 Mercha Grey\nდამატება\n3299 ₾\n3499 ₾\n\nთვეში: 91 ₾ -დან\n\nAsus TUF 14 FA401UU-RG013 Jaeger Grey\nდამატება\n4179 ₾\n\nთვეში: 116 ₾ -დან\n\nAsus TUF A16 FA608WV-QT053 Grey\nდამატება\n2179 ₾\n2279 ₾\n\nთვეში: 60 ₾ -დან\n\nAsus TUF 15 FA506NFR-HN021, AMD Ryzen 7 7435HS, Nvidi ...\nდამატება\n5599 ₾\n5899 ₾\n\nთვეში: 155 ₾ -დან\n\nAsus TUF 18 FA808UP-S8030 Grey\nდამატება\n7299 ₾\n\nთვეში: 202 ₾ -დან\n\nAsus ROG Strix 16 G615JPR-S5101 Grey\nდამატება\n15999 ₾\n\nთვეში: 444 ₾ -დან\n\nAsus ROG Strix 18 G835LX-SA034W Black\nდამატება\n6499 ₾\n\nთვეში: 180 ₾ -დან\n\nAsus ROG Strix 16 G614PR-RV007, AMD Ryzen 9-7940HX, N ...\nდამატება\n6699 ₾\n\nთვეში: 186 ₾ -დან\n\nAsus ROG Strix G16 G615JPR-RV113, Intel core i7-14650 ...\nდამატება\n8499 ₾\n\nთვეში: 236 ₾ -დან\n\nAsus ROG Strix G18 G815LR-S9085, Intel Core Ultra 9 2 ...\nდამატება\n4999 ₾\n\nთვეში: 138 ₾ -დან\n\nAsus TUF F16 FX608JMR-RV073, Intel core i7-14650HX 16 ...\nდამატება\n2699 ₾\n\nთვეში: 74 ₾ -დან\n\nAsus TUF 16 FX607VJ-RL005, Intel Core 5-210H, Nvidia ...\nდამატება\n4199 ₾\n\nთვეში: 116 ₾ -დან\n\nAsus TUF F16 FX608JHR-RV035, Intel core i7-14650HX 16 ...\nდამატება\nდამატებითი მახასიათებლები\nბრენდი\nბრენდი:\n\t\nAsus\nმოდელი\nმოდელი:\n\t\nROG\nტექნიკური მახასიათებლები\nცენტრალური პროცესორი:\n\t\nIntel Core Ultra 9-285HX\n\n\nპროცესორის თაობა:\n\t\nIntel Ultra 9 Series 2\n\n\nპროცესორის სიხშირე:\n\t\n2.8 GHz ~ 5.5 GHz\n\n\nბირთვების რაოდენობა:\n\t\n16\n\n\nნაკადების რაოდენობა:\n\t\n24\n\n\nგრაფიკული პროცესორი:\n\t\nNvidia GeForce RTX 5070 TI\n\n\nგრაფიკული პროცესორის მეხსიერება:\n\t\n12 GB\n\n\nგრაფიკული პროცესორის ტიპი:\n\t\nარა ინტეგრირებული\n\n\nოპერაციული სისტემა:\n\t\n-\n\n\nBluetooth:\n\t\n5.4\nეკრანი\nეკრანის ზომა:\n\t\n18 Inches\n\n\nრეზოლუცია:\n\t\nWQXGA\n\n\nეკრანის ტიპი:\n\t\nIPS\n\n\nსენსორული ეკრანი:\n\t\nNo\n\n\nგანახლების სიხშირე:\n\t\n240 Hz\nდამატებითი მახასიათებლები\nკლავიატურის განათება:\n\t\nYes\n\n\nNumpad:\n\t\nYes\n\n\nდისკის წამკითხველი:\n\t\nNo\n\n\nვებ კამერა:\n\t\nYes\n\n\nლეპტოპის ტიპი:\n\t\nგეიმინგი\nმეხსიერება\nშიდა მეხსიერება:\n\t\n2 TB\n\n\nშიდა მეხსიერების ტიპი:\n\t\nSSD\n\n\nშიდა მეხსიერების ინტერფეისი:\n\t\nM.2\n\n\nოპერატიული მეხსიერება:\n\t\n32 GB\n\n\nოპერატიული მეხსიერების ტიპი:\n\t\nDDR5\n\n\nოპერატიული მეხსიერების სიხშირე:\n\t\n5600 MHz\nპორტები\nUSB:\n\t\n3 x USB-A\n\n\nType-C:\n\t\n2x\n\n\nType-C პორტით დამუხტვა:\n\t\nNo\n\n\nHDMI:\n\t\nYes\n\n\nლან პორტი:\n\t\nYes\n\n\n3.5mm:\n\t\nYes\nზომა/წონა\nწონა:\n\t\n3.3 kg\nფერი\nფერი:\n\t\nBlack\nმეტის ნახვა\nგაეცანი საგარანტიო პირობებს\nსაგარანტიო პირობები\nფილიალები\nმარაგშია\nშეკვეთიდან 2-5 დღეში\nზუმერის წერეთლის ფილიალი\n\nთბილისი - წერეთლის გამზირი, N1.\n\nმარაგშია\n+995 591 967 601\nორშ-შაბ: 10:00:00 - 20:00:00\nკვირა: 10:00:00 - 19:00:00\nზუმერის City Mall საბურთალო-ს ფილიალი\n\nთბილისი - \"სითი მოლი\" - პეტრე ქავთარაძის N1\n\nმარაგშია\n+995 591 971 962\nორშ-შაბ: 10:00:00 - 22:00:00\nკვირა: 10:00:00 - 22:00:00\n10399 ₾\n10499 ₾\n\nთვეში: 288.9 ₾ -დან\n\nმარაგი ფილიალებში\nფასის დაზღვევა\nფასის კონტროლი\nფასის დაჯავშნა\nყიდვა\nშედარება\nდამატება\nნავიგაცია\nგადახდები\nგამოგვყევი\n\nFacebook\n\nYoutube\n\nInstagram\n\nTik Tok\n\nკონტაქტი\n\nInfo@zoommer.ge\n\n+995 (32) 2 60 30 60 / *7007\n\nფილიალები\n\nკორპორატიული გაყიდვები\n\nZoommer App\n\nCopyright © 2023 Zoommer.ge. All rights reserved.\n\nCookie პოლიტიკა\n\nსაიტით სარგებლობის გაგრძელებით, შენ ეთანხმები Cookie ჩანაწერების გამოყენებას. მეტი ინფორმაცისათვის იხილეთ კონფიდენციალურობის პოლიტიკა\n\nგასაგებია",
    "specs": {
      "ბრენდი:": "Asus",
      "მოდელი:": "ROG",
      "ცენტრალური პროცესორი:": "Intel Core Ultra 9-285HX",
      "პროცესორის თაობა:": "Intel Ultra 9 Series 2",
      "პროცესორის სიხშირე:": "2.8 GHz ~ 5.5 GHz",
      "ბირთვების რაოდენობა:": "16",
      "ნაკადების რაოდენობა:": "24",
      "გრაფიკული პროცესორი:": "Nvidia GeForce RTX 5070 TI",
      "გრაფიკული პროცესორის მეხსიერება:": "12 GB",
      "გრაფიკული პროცესორის ტიპი:": "არა ინტეგრირებული",
      "ოპერაციული სისტემა:": "-",
      "Bluetooth:": "5.4",
      "ეკრანის ზომა:": "18 Inches",
      "რეზოლუცია:": "WQXGA",
      "ეკრანის ტიპი:": "IPS",
      "სენსორული ეკრანი:": "No",
      "განახლების სიხშირე:": "240 Hz",
      "კლავიატურის განათება:": "Yes",
      "Numpad:": "Yes",
      "დისკის წამკითხველი:": "No",
      "ვებ კამერა:": "Yes",
      "ლეპტოპის ტიპი:": "გეიმინგი",
      "შიდა მეხსიერება:": "2 TB",
      "შიდა მეხსიერების ტიპი:": "SSD",
      "შიდა მეხსიერების ინტერფეისი:": "M.2",
      "ოპერატიული მეხსიერება:": "32 GB",
      "ოპერატიული მეხსიერების ტიპი:": "DDR5",
      "ოპერატიული მეხსიერების სიხშირე:": "5600 MHz",
      "USB:": "3 x USB-A",
      "Type-C:": "2x",
      "Type-C პორტით დამუხტვა:": "No",
      "HDMI:": "Yes",
      "ლან პორტი:": "Yes",
      "3.5mm:": "Yes",
      "წონა:": "3.3 kg",
      "ფერი:": "Black"
    }
  },
  {
    "category": "Gaming ლეპტოპები",
    "title": "Asus ROG Strix 16 G615JPR-S5101 Grey",
    "price": 7299.0,
    "link": "https://zoommer.ge/leptopebi/asus-rog-strix-16-g615jpr-s5101-grey-p48538",
    "image": "/_next/image?url=https%3A%2F%2Fs3.zoommer.ge%2Fsite%2Fec7d8d0e-ba46-419e-b602-4454fc6a6b44_Thumb.jpeg&w=384&q=50",
    "product_title_detail": "Asus ROG Strix 16 G615JPR-S5101 Grey",
    "description": "*7007 / +995 (32) 2 60 30 60\nფილიალები\nნავიგაცია\nკალათა\nშესვლა\n%\nმთავარი\nლეპტოპები\nAsus\n#ZOOM-036803\nAsus ROG Strix 16 G615JPR-S5101 Grey\nეკრანის ზომა\n16 Inches\nრეზოლუცია\nWQXGA\nეკრანის ტიპი\nIPS\nგანახლების სიხშირე\n240 Hz\nშიდა მეხსიერება\n1 TB\nBluetooth\n5.4\nType-C\n2x\nოპერატიული მეხსიერება\n32 GB\nერთად იაფია\nდაამატე ნივთი\nAsus ROG Strix 16 G615JPR-S5101 Grey\n7299 ₾\nRivacase 8057 Laptop Bag 16 Black\n58.65 ₾\n69 ₾\nRazer Gaming Mouse DeathAdder Essential USB White\n52 ₾\n65 ₾\nHavit Gaming Cooling Pad HV-F2083 Black\n75.65 ₾\n89 ₾\nჯამური ფასი (3)\n7485.3 ₾\n7522 ₾\nყიდვა\nაქსესუარები\nაღწერა\nმსგავსი\nმახასიათებლები\nფილიალები\nაქსესუარები\nაღწერა\nმსგავსი\nმახასიათებლები\nფილიალები\n89 ₾\n\nთვეში: 2 ₾ -დან\n\nHavit Gaming Cooling Pad HV-F2083 Black\nდამატება\n69 ₾\n\nთვეში: 1 ₾ -დან\n\nRivacase 8057 Laptop Bag 16 Black\nდამატება\n219 ₾\n\nთვეში: 6 ₾ -დან\n\nRazer Gaming Mouse Orochi V2 WL Black\nდამატება\n59 ₾\n\nთვეში: 1 ₾ -დან\n\nHavit Gaming mouse Pad HV-MP901\nდამატება\n69 ₾\n\nთვეში: 1 ₾ -დან\n\nXiaomi Mi Router 4A DVB4230GL White\nდამატება\n79 ₾\n\nთვეში: 2 ₾ -დან\n\nRivacase 7531 Eco Laptop Bag 15 Black\nდამატება\n219 ₾\n\nთვეში: 6 ₾ -დან\n\nRazer Gaming Mouse Orochi V2 WL White\nდამატება\n9 ₾\n\nHavit Gaming mouse Pad HV-MP838\nდამატება\n85 ₾\n\nთვეში: 2 ₾ -დან\n\nTP-Link Archer C50 AC1200 White\nდამატება\n89 ₾\n\nთვეში: 2 ₾ -დან\n\nTomtoc Defender A13 Laptop Sleeve Kit 16 A13F2DV Blac ...\nდამატება\n209 ₾\n\nთვეში: 5 ₾ -დან\n\nRazer Gaming Mouse DeathAdder V2 X Hyperspeed WL/BT/U ...\nდამატება\n9 ₾\n\nHavit Gaming mouse Pad HV-MP843 Black\nდამატება\n119 ₾\n\nთვეში: 3 ₾ -დან\n\nTP-Link Archer C6 AC1200 Black\nდამატება\n119 ₾\n\nთვეში: 3 ₾ -დან\n\nTomtoc Defender A42 Laptop Briefcase 16 A42F2B1 Navy ...\nდამატება\n139 ₾\n\nთვეში: 3 ₾ -დან\n\nLogitech Gaming Mouse G402 Hyperion Fury black\nდამატება\n149 ₾\n\nთვეში: 4 ₾ -დან\n\nRazer Mouse Pad Firefly V2 RGB M Black\nდამატება\n159 ₾\n\nთვეში: 4 ₾ -დან\n\nXiaomi Router AX1500 White\nდამატება\n119 ₾\n\nთვეში: 3 ₾ -დან\n\nTomtoc Defender A42 Laptop Briefcase 16 A42F2D1 Black\nდამატება\n29 ₾\n\nHavit Gaming Mouse HV-MS1010 Black\nდამატება\n199 ₾\n\nთვეში: 5 ₾ -დან\n\nRazer Mouse Pad Goliathus Extended Chroma XXL Black\nდამატება\n179 ₾\n\nთვეში: 4 ₾ -დან\n\nXiaomi Mesh System AX3000 NE 1 pack White\nდამატება\n89 ₾\n\nთვეში: 2 ₾ -დან\n\nUniq Dfender Tough Laptop Sleeve 16 Inch Marl Grey\nდამატება\n79 ₾\n\nთვეში: 2 ₾ -დან\n\nRazer Gaming Mouse DeathAdder Essential USB Black\nდამატება\n149 ₾\n\nთვეში: 4 ₾ -დან\n\nHyperX Pulsefire Mat RGB Black\nდამატება\n299 ₾\n\nთვეში: 8 ₾ -დან\n\nXiaomi Mesh System AX3000 NE 2 pack White\nდამატება\n89 ₾\n\nთვეში: 2 ₾ -დან\n\nUniq Dfender Tough Laptop Sleeve 16 Inch Black\nდამატება\n119 ₾\n\nთვეში: 3 ₾ -დან\n\nHyperX Pulsefire Surge Mouse Black\nდამატება\n29 ₾\n\nHavit Gaming Mouse Pad HV-MP845 Black\nდამატება\n249 ₾\n\nთვეში: 6 ₾ -დან\n\nXiaomi Router BE3600 White\nდამატება\n99 ₾\n\nთვეში: 2 ₾ -დან\n\nDell EcoLoop Essential Backpack 14-16 460-BDSS Black\nდამატება\n469 ₾\n\nთვეში: 13 ₾ -დან\n\nHP OMEN PHOTON Wireless Mouse 6CL96AA Black\nდამატება\n29 ₾\n\nHavit Gaming Mouse Pad HV-MP847 Pink\nდამატება\n79 ₾\n\nთვეში: 2 ₾ -დან\n\nTomtoc Defender A13 Laptop Sleeve 16 A13F2D1 Black\nდამატება\n65 ₾\n\nთვეში: 1 ₾ -დან\n\nRazer Gaming Mouse DeathAdder Essential USB White\nდამატება\n29 ₾\n\nHavit Gaming Mouse Pad HV-MP849 Black\nდამატება\n89 ₾\n\nთვეში: 2 ₾ -დან\n\nTomtoc Defender A14 Laptop Briefcase 16 A14F2D1 Black\nდამატება\n239 ₾\n\nთვეში: 6 ₾ -დან\n\nRazer Gaming Mouse Basilisk V3 Black\nდამატება\n49 ₾\n\nთვეში: 1 ₾ -დან\n\nHyperX Pulsefire Mat M Black\nდამატება\n299 ₾\n\nთვეში: 8 ₾ -დან\n\nRazer Gaming Mouse Naga V2 HyperSpeed WL Black\nდამატება\n59 ₾\n\nთვეში: 1 ₾ -დან\n\nHyperX Pulsefire Mat L Black\nდამატება\n229 ₾\n\nთვეში: 6 ₾ -დან\n\nRazer Gaming Mouse Basilisk V3 X HyperSpeed WL Black\nდამატება\n39 ₾\n\nთვეში: 1 ₾ -დან\n\nRazer Mouse Pad Sphex V3 S Black\nდამატება\n129 ₾\n\nთვეში: 3 ₾ -დან\n\nRazer Gaming Mouse Cobra Black\nდამატება\n89 ₾\n\nთვეში: 2 ₾ -დან\n\nRazer Mouse Pad Sphex V3 L Black\nდამატება\n19 ₾\n\nHavit Gaming Mouse HV-MS989GT Black/Red\nდამატება\n29 ₾\n\nHavit Gaming mouse Pad HV-MP860\nდამატება\n19 ₾\n\nHavit Gaming Mouse HV-MS626GT Black\nდამატება\n19 ₾\n\nHavit Gaming Mouse HV-MS66GT White/Blue\nდამატება\n149 ₾\n\nთვეში: 4 ₾ -დან\n\nHyperX Gaming Mouse Pulsefire Haste 2 Black\nდამატება\n19 ₾\n\nHavit Wireless Mouse HV-MS66GT Black\nდამატება\n179 ₾\n\nთვეში: 4 ₾ -დან\n\nLogitech Gaming Mouse G305 LIGHTSPEED WL L910-005282 ...\nდამატება\n259 ₾\n\nთვეში: 7 ₾ -დან\n\nLogitech Gaming Mouse G502 X L910-006138 Black\nდამატება\n259 ₾\n\nთვეში: 7 ₾ -დან\n\nLogitech Gaming Mouse G502 X L910-006138 White\nდამატება\n19 ₾\n\nHavit Gaming Mouse HV-MS626GT Black/Red\nდამატება\n19 ₾\n\nHavit Gaming Mouse HV-MS626GT Black/Blue\nდამატება\n349 ₾\n\nთვეში: 9 ₾ -დან\n\nLogitech Gaming Mouse G703 LIGHTSPEED WL L910-005640 ...\nდამატება\n89 ₾\n\nთვეში: 2 ₾ -დან\n\nLogitech Gaming Mouse G102 LIGHTSYNC L910-005823 Blac ...\nდამატება\n89 ₾\n\nთვეში: 2 ₾ -დან\n\nLogitech Gaming Mouse G102 LIGHTSYNC L910-005824 Whit ...\nდამატება\n89 ₾\n\nთვეში: 2 ₾ -დან\n\nLogitech Gaming Mouse G102 LIGHTSYNC L910-005801 Blue\nდამატება\n239 ₾\n\nთვეში: 6 ₾ -დან\n\nLogitech Gaming Mouse G502 HERO L910-005470 Black\nდამატება\n199 ₾\n\nთვეში: 5 ₾ -დან\n\nHyperX Pulsefire Haste 2 core Wireless Black\nდამატება\n199 ₾\n\nთვეში: 5 ₾ -დან\n\nHyperX Pulsefire Haste 2 core Wireless White\nდამატება\n59 ₾\n\nთვეში: 1 ₾ -დან\n\nHavit Gaming Mouse HV-MS954 Black\nდამატება\n39 ₾\n\nთვეში: 1 ₾ -დან\n\nHavit Gaming Mouse HV-MS1033 White\nდამატება\n39 ₾\n\nთვეში: 1 ₾ -დან\n\nHavit Gaming Mouse HV-MS1029 Pink\nდამატება\n59 ₾\n\nთვეში: 1 ₾ -დან\n\nHavit Gaming Mouse HV-MS966 Black/Green\nდამატება\n49 ₾\n\nთვეში: 1 ₾ -დან\n\nHavit Wireless Mouse HV-MS1039W Black/White\nდამატება\n79 ₾\n\nთვეში: 2 ₾ -დან\n\nHavit Wireless Mouse HV-MS970WB Pro Black\nდამატება\n79 ₾\n\nთვეში: 2 ₾ -დან\n\nHavit Wireless Mouse HV-MS970WB Pro Transparent White\nდამატება\n219 ₾\n\nთვეში: 6 ₾ -დან\n\nRazer Gaming Mouse Orochi V2 WL Pink\nდამატება\nპროდუქტის შესახებ\n\nთუ ეძებთ ლეპტოპს, რომელიც მარტივად გაუმკლავდება ყველაზე მოთხოვნად თამაშებს — Asus ROG Strix 16 G615JPR-S5101 Grey შექმნილია სწორედ თქვენთვის. ეს მოდელი აერთიანებს მაღალ წარმადობას, გამძლე კონსტრუქცი...\n\nმეტის ნახვა\nმსგავსი პროდუქტები\n2599 ₾\n2799 ₾\n\nთვეში: 72 ₾ -დან\n\nAsus TUF 15 FX507ZC4-HN009 Black\nდამატება\n2249 ₾\n2499 ₾\n\nთვეში: 62 ₾ -დან\n\nAsus TUF 15 FA506NF-HN018, AMD Ryzen 5-7535HS, NVIDIA ...\nდამატება\n2999 ₾\n3699 ₾\n\nთვეში: 83 ₾ -დან\n\nAsus TUF 15 FA507NUR-LP044 Mercha Grey\nდამატება\n3299 ₾\n3499 ₾\n\nთვეში: 91 ₾ -დან\n\nAsus TUF 14 FA401UU-RG013 Jaeger Grey\nდამატება\n4179 ₾\n\nთვეში: 116 ₾ -დან\n\nAsus TUF A16 FA608WV-QT053 Grey\nდამატება\n2179 ₾\n2279 ₾\n\nთვეში: 60 ₾ -დან\n\nAsus TUF 15 FA506NFR-HN021, AMD Ryzen 7 7435HS, Nvidi ...\nდამატება\n5599 ₾\n5899 ₾\n\nთვეში: 155 ₾ -დან\n\nAsus TUF 18 FA808UP-S8030 Grey\nდამატება\n10399 ₾\n10499 ₾\n\nთვეში: 288 ₾ -დან\n\nAsus ROG Strix 18 G835LR-SA005 Black\nდამატება\n15999 ₾\n\nთვეში: 444 ₾ -დან\n\nAsus ROG Strix 18 G835LX-SA034W Black\nდამატება\n6499 ₾\n\nთვეში: 180 ₾ -დან\n\nAsus ROG Strix 16 G614PR-RV007, AMD Ryzen 9-7940HX, N ...\nდამატება\n6699 ₾\n\nთვეში: 186 ₾ -დან\n\nAsus ROG Strix G16 G615JPR-RV113, Intel core i7-14650 ...\nდამატება\n8499 ₾\n\nთვეში: 236 ₾ -დან\n\nAsus ROG Strix G18 G815LR-S9085, Intel Core Ultra 9 2 ...\nდამატება\n4999 ₾\n\nთვეში: 138 ₾ -დან\n\nAsus TUF F16 FX608JMR-RV073, Intel core i7-14650HX 16 ...\nდამატება\n2699 ₾\n\nთვეში: 74 ₾ -დან\n\nAsus TUF 16 FX607VJ-RL005, Intel Core 5-210H, Nvidia ...\nდამატება\n4199 ₾\n\nთვეში: 116 ₾ -დან\n\nAsus TUF F16 FX608JHR-RV035, Intel core i7-14650HX 16 ...\nდამატება\nდამატებითი მახასიათებლები\nბრენდი\nბრენდი:\n\t\nAsus\nმოდელი\nმოდელი:\n\t\nROG\nტექნიკური მახასიათებლები\nცენტრალური პროცესორი:\n\t\nIntel Core i9-14900HX\n\n\nპროცესორის თაობა:\n\t\nIntel i9 14th Gen\n\n\nპროცესორის სიხშირე:\n\t\n1.6 GHz ~ 5.8 GHz\n\n\nბირთვების რაოდენობა:\n\t\n24\n\n\nნაკადების რაოდენობა:\n\t\n32\n\n\nგრაფიკული პროცესორი:\n\t\nNvidia GeForce RTX 5070\n\n\nგრაფიკული პროცესორის მეხსიერება:\n\t\n8 GB\n\n\nგრაფიკული პროცესორის ტიპი:\n\t\nარა ინტეგრირებული\n\n\nოპერაციული სისტემა:\n\t\n-\n\n\nBluetooth:\n\t\n5.4\nეკრანი\nეკრანის ზომა:\n\t\n16 Inches\n\n\nრეზოლუცია:\n\t\nWQXGA\n\n\nეკრანის ტიპი:\n\t\nIPS\n\n\nსენსორული ეკრანი:\n\t\nNo\n\n\nგანახლების სიხშირე:\n\t\n240 Hz\nდამატებითი მახასიათებლები\nკლავიატურის განათება:\n\t\nYes\n\n\nNumpad:\n\t\nNo\n\n\nდისკის წამკითხველი:\n\t\nNo\n\n\nვებ კამერა:\n\t\nYes\n\n\nლეპტოპის ტიპი:\n\t\nგეიმინგი\nმეხსიერება\nშიდა მეხსიერება:\n\t\n1 TB\n\n\nშიდა მეხსიერების ტიპი:\n\t\nSSD\n\n\nშიდა მეხსიერების ინტერფეისი:\n\t\nM.2\n\n\nოპერატიული მეხსიერება:\n\t\n32 GB\n\n\nოპერატიული მეხსიერების ტიპი:\n\t\nDDR5\n\n\nოპერატიული მეხსიერების სიხშირე:\n\t\n5600 MHz\nპორტები\nUSB:\n\t\n3 x USB-A\n\n\nType-C:\n\t\n2x\n\n\nType-C პორტით დამუხტვა:\n\t\nNo\n\n\nHDMI:\n\t\nYes\n\n\nლან პორტი:\n\t\nYes\n\n\n3.5mm:\n\t\nYes\nზომა/წონა\nწონა:\n\t\n2.73 kg\nმეტის ნახვა\nგაეცანი საგარანტიო პირობებს\nსაგარანტიო პირობები\nფილიალები\nმარაგშია\nშეკვეთიდან 2-5 დღეში\nზუმერის წერეთლის ფილიალი\n\nთბილისი - წერეთლის გამზირი, N1.\n\nმარაგშია\n+995 591 967 601\nორშ-შაბ: 10:00:00 - 20:00:00\nკვირა: 10:00:00 - 19:00:00\n7299 ₾\n\nთვეში: 202.8 ₾ -დან\n\nმარაგი ფილიალებში\nფასის დაზღვევა\nფასის კონტროლი\nფასის დაჯავშნა\nყიდვა\nშედარება\nდამატება\nნავიგაცია\nგადახდები\nგამოგვყევი\n\nFacebook\n\nYoutube\n\nInstagram\n\nTik Tok\n\nკონტაქტი\n\nInfo@zoommer.ge\n\n+995 (32) 2 60 30 60 / *7007\n\nფილიალები\n\nკორპორატიული გაყიდვები\n\nZoommer App\n\nCopyright © 2023 Zoommer.ge. All rights reserved.\n\nCookie პოლიტიკა\n\nსაიტით სარგებლობის გაგრძელებით, შენ ეთანხმები Cookie ჩანაწერების გამოყენებას. მეტი ინფორმაცისათვის იხილეთ კონფიდენციალურობის პოლიტიკა\n\nგასაგებია",
    "specs": {
      "ბრენდი:": "Asus",
      "მოდელი:": "ROG",
      "ცენტრალური პროცესორი:": "Intel Core i9-14900HX",
      "პროცესორის თაობა:": "Intel i9 14th Gen",
      "პროცესორის სიხშირე:": "1.6 GHz ~ 5.8 GHz",
      "ბირთვების რაოდენობა:": "24",
      "ნაკადების რაოდენობა:": "32",
      "გრაფიკული პროცესორი:": "Nvidia GeForce RTX 5070",
      "გრაფიკული პროცესორის მეხსიერება:": "8 GB",
      "გრაფიკული პროცესორის ტიპი:": "არა ინტეგრირებული",
      "ოპერაციული სისტემა:": "-",
      "Bluetooth:": "5.4",
      "ეკრანის ზომა:": "16 Inches",
      "რეზოლუცია:": "WQXGA",
      "ეკრანის ტიპი:": "IPS",
      "სენსორული ეკრანი:": "No",
      "განახლების სიხშირე:": "240 Hz",
      "კლავიატურის განათება:": "Yes",
      "Numpad:": "No",
      "დისკის წამკითხველი:": "No",
      "ვებ კამერა:": "Yes",
      "ლეპტოპის ტიპი:": "გეიმინგი",
      "შიდა მეხსიერება:": "1 TB",
      "შიდა მეხსიერების ტიპი:": "SSD",
      "შიდა მეხსიერების ინტერფეისი:": "M.2",
      "ოპერატიული მეხსიერება:": "32 GB",
      "ოპერატიული მეხსიერების ტიპი:": "DDR5",
      "ოპერატიული მეხსიერების სიხშირე:": "5600 MHz",
      "USB:": "3 x USB-A",
      "Type-C:": "2x",
      "Type-C პორტით დამუხტვა:": "No",
      "HDMI:": "Yes",
      "ლან პორტი:": "Yes",
      "3.5mm:": "Yes",
      "წონა:": "2.73 kg"
    }
  },
  {
    "category": "Gaming ლეპტოპები",
    "title": "Asus TUF 18 FA808UP-S8030 Grey",
    "price": 5599.0,
    "link": "https://zoommer.ge/leptopebi/asus-tuf-18-fa808up-s8030-grey-p48537",
    "image": "/_next/image?url=https%3A%2F%2Fs3.zoommer.ge%2Fsite%2Fcffdc07c-6527-4a2e-9471-fe97c1b79a49_Thumb.jpeg&w=384&q=50",
    "product_title_detail": "Asus TUF 18 FA808UP-S8030 Grey",
    "description": "*7007 / +995 (32) 2 60 30 60\nსავაჭრო პოლიტიკა\nგანვადება\nკარიერა\nTrade In\nფილიალები\nნავიგაცია\nკალათა\nშესვლა\n%\nმთავარი\nლეპტოპები\nAsus\n#ZOOM-036802\nAsus TUF 18 FA808UP-S8030 Grey\nეკრანის ზომა\n18 Inches\nრეზოლუცია\nWUXGA\nეკრანის ტიპი\nIPS\nგანახლების სიხშირე\n144 Hz\nშიდა მეხსიერება\n1 TB\nBluetooth\n5.3\nType-C\n2x\nოპერატიული მეხსიერება\n32 GB\nერთად იაფია\nდაამატე ნივთი\nAsus TUF 18 FA808UP-S8030 Grey\n5599 ₾\nRazer Gaming Mouse DeathAdder Essential USB White\n52 ₾\n65 ₾\nHavit Gaming Cooling Pad HV-F2083 Black\n75.65 ₾\n89 ₾\nჯამური ფასი (2)\n5726.65 ₾\n5753 ₾\nყიდვა\nაქსესუარები\nაღწერა\nმსგავსი\nმახასიათებლები\nფილიალები\nაქსესუარები\nაღწერა\nმსგავსი\nმახასიათებლები\nფილიალები\n89 ₾\n\nთვეში: 2 ₾ -დან\n\nHavit Gaming Cooling Pad HV-F2083 Black\nდამატება\n219 ₾\n\nთვეში: 6 ₾ -დან\n\nRazer Gaming Mouse Orochi V2 WL Black\nდამატება\n59 ₾\n\nთვეში: 1 ₾ -დან\n\nHavit Gaming mouse Pad HV-MP901\nდამატება\n69 ₾\n\nთვეში: 1 ₾ -დან\n\nXiaomi Mi Router 4A DVB4230GL White\nდამატება\n219 ₾\n\nთვეში: 6 ₾ -დან\n\nRazer Gaming Mouse Orochi V2 WL White\nდამატება\n9 ₾\n\nHavit Gaming mouse Pad HV-MP838\nდამატება\n85 ₾\n\nთვეში: 2 ₾ -დან\n\nTP-Link Archer C50 AC1200 White\nდამატება\n209 ₾\n\nთვეში: 5 ₾ -დან\n\nRazer Gaming Mouse DeathAdder V2 X Hyperspeed WL/BT/U ...\nდამატება\n9 ₾\n\nHavit Gaming mouse Pad HV-MP843 Black\nდამატება\n119 ₾\n\nთვეში: 3 ₾ -დან\n\nTP-Link Archer C6 AC1200 Black\nდამატება\n139 ₾\n\nთვეში: 3 ₾ -დან\n\nLogitech Gaming Mouse G402 Hyperion Fury black\nდამატება\n149 ₾\n\nთვეში: 4 ₾ -დან\n\nRazer Mouse Pad Firefly V2 RGB M Black\nდამატება\n159 ₾\n\nთვეში: 4 ₾ -დან\n\nXiaomi Router AX1500 White\nდამატება\n29 ₾\n\nHavit Gaming Mouse HV-MS1010 Black\nდამატება\n199 ₾\n\nთვეში: 5 ₾ -დან\n\nRazer Mouse Pad Goliathus Extended Chroma XXL Black\nდამატება\n179 ₾\n\nთვეში: 4 ₾ -დან\n\nXiaomi Mesh System AX3000 NE 1 pack White\nდამატება\n79 ₾\n\nთვეში: 2 ₾ -დან\n\nRazer Gaming Mouse DeathAdder Essential USB Black\nდამატება\n149 ₾\n\nთვეში: 4 ₾ -დან\n\nHyperX Pulsefire Mat RGB Black\nდამატება\n299 ₾\n\nთვეში: 8 ₾ -დან\n\nXiaomi Mesh System AX3000 NE 2 pack White\nდამატება\n119 ₾\n\nთვეში: 3 ₾ -დან\n\nHyperX Pulsefire Surge Mouse Black\nდამატება\n29 ₾\n\nHavit Gaming Mouse Pad HV-MP845 Black\nდამატება\n249 ₾\n\nთვეში: 6 ₾ -დან\n\nXiaomi Router BE3600 White\nდამატება\n469 ₾\n\nთვეში: 13 ₾ -დან\n\nHP OMEN PHOTON Wireless Mouse 6CL96AA Black\nდამატება\n29 ₾\n\nHavit Gaming Mouse Pad HV-MP847 Pink\nდამატება\n65 ₾\n\nთვეში: 1 ₾ -დან\n\nRazer Gaming Mouse DeathAdder Essential USB White\nდამატება\n29 ₾\n\nHavit Gaming Mouse Pad HV-MP849 Black\nდამატება\n239 ₾\n\nთვეში: 6 ₾ -დან\n\nRazer Gaming Mouse Basilisk V3 Black\nდამატება\n49 ₾\n\nთვეში: 1 ₾ -დან\n\nHyperX Pulsefire Mat M Black\nდამატება\n299 ₾\n\nთვეში: 8 ₾ -დან\n\nRazer Gaming Mouse Naga V2 HyperSpeed WL Black\nდამატება\n59 ₾\n\nთვეში: 1 ₾ -დან\n\nHyperX Pulsefire Mat L Black\nდამატება\n229 ₾\n\nთვეში: 6 ₾ -დან\n\nRazer Gaming Mouse Basilisk V3 X HyperSpeed WL Black\nდამატება\n39 ₾\n\nთვეში: 1 ₾ -დან\n\nRazer Mouse Pad Sphex V3 S Black\nდამატება\n129 ₾\n\nთვეში: 3 ₾ -დან\n\nRazer Gaming Mouse Cobra Black\nდამატება\n89 ₾\n\nთვეში: 2 ₾ -დან\n\nRazer Mouse Pad Sphex V3 L Black\nდამატება\n19 ₾\n\nHavit Gaming Mouse HV-MS989GT Black/Red\nდამატება\n29 ₾\n\nHavit Gaming mouse Pad HV-MP860\nდამატება\n19 ₾\n\nHavit Gaming Mouse HV-MS626GT Black\nდამატება\n19 ₾\n\nHavit Gaming Mouse HV-MS66GT White/Blue\nდამატება\n149 ₾\n\nთვეში: 4 ₾ -დან\n\nHyperX Gaming Mouse Pulsefire Haste 2 Black\nდამატება\n19 ₾\n\nHavit Wireless Mouse HV-MS66GT Black\nდამატება\n179 ₾\n\nთვეში: 4 ₾ -დან\n\nLogitech Gaming Mouse G305 LIGHTSPEED WL L910-005282 ...\nდამატება\n259 ₾\n\nთვეში: 7 ₾ -დან\n\nLogitech Gaming Mouse G502 X L910-006138 Black\nდამატება\n259 ₾\n\nთვეში: 7 ₾ -დან\n\nLogitech Gaming Mouse G502 X L910-006138 White\nდამატება\n19 ₾\n\nHavit Gaming Mouse HV-MS626GT Black/Red\nდამატება\n19 ₾\n\nHavit Gaming Mouse HV-MS626GT Black/Blue\nდამატება\n349 ₾\n\nთვეში: 9 ₾ -დან\n\nLogitech Gaming Mouse G703 LIGHTSPEED WL L910-005640 ...\nდამატება\n89 ₾\n\nთვეში: 2 ₾ -დან\n\nLogitech Gaming Mouse G102 LIGHTSYNC L910-005823 Blac ...\nდამატება\n89 ₾\n\nთვეში: 2 ₾ -დან\n\nLogitech Gaming Mouse G102 LIGHTSYNC L910-005824 Whit ...\nდამატება\n89 ₾\n\nთვეში: 2 ₾ -დან\n\nLogitech Gaming Mouse G102 LIGHTSYNC L910-005801 Blue\nდამატება\n239 ₾\n\nთვეში: 6 ₾ -დან\n\nLogitech Gaming Mouse G502 HERO L910-005470 Black\nდამატება\n199 ₾\n\nთვეში: 5 ₾ -დან\n\nHyperX Pulsefire Haste 2 core Wireless Black\nდამატება\n199 ₾\n\nთვეში: 5 ₾ -დან\n\nHyperX Pulsefire Haste 2 core Wireless White\nდამატება\n59 ₾\n\nთვეში: 1 ₾ -დან\n\nHavit Gaming Mouse HV-MS954 Black\nდამატება\n39 ₾\n\nთვეში: 1 ₾ -დან\n\nHavit Gaming Mouse HV-MS1033 White\nდამატება\n39 ₾\n\nთვეში: 1 ₾ -დან\n\nHavit Gaming Mouse HV-MS1029 Pink\nდამატება\n59 ₾\n\nთვეში: 1 ₾ -დან\n\nHavit Gaming Mouse HV-MS966 Black/Green\nდამატება\n49 ₾\n\nთვეში: 1 ₾ -დან\n\nHavit Wireless Mouse HV-MS1039W Black/White\nდამატება\n79 ₾\n\nთვეში: 2 ₾ -დან\n\nHavit Wireless Mouse HV-MS970WB Pro Black\nდამატება\n79 ₾\n\nთვეში: 2 ₾ -დან\n\nHavit Wireless Mouse HV-MS970WB Pro Transparent White\nდამატება\n219 ₾\n\nთვეში: 6 ₾ -დან\n\nRazer Gaming Mouse Orochi V2 WL Pink\nდამატება\nპროდუქტის შესახებ\n\nთუ ეძებთ ლეპტოპს, რომელიც მარტივად გაუმკლავდება ყველაზე მოთხოვნად თამაშებს — Asus TUF 18 FA808UP-S8030 Grey შექმნილია სწორედ თქვენთვის. ეს მოდელი აერთიანებს მაღალ წარმადობას, გამძლე კონსტრუქციასა და...\n\nმეტის ნახვა\nმსგავსი პროდუქტები\n2599 ₾\n2799 ₾\n\nთვეში: 72 ₾ -დან\n\nAsus TUF 15 FX507ZC4-HN009 Black\nდამატება\n2249 ₾\n2499 ₾\n\nთვეში: 62 ₾ -დან\n\nAsus TUF 15 FA506NF-HN018, AMD Ryzen 5-7535HS, NVIDIA ...\nდამატება\n2999 ₾\n3699 ₾\n\nთვეში: 83 ₾ -დან\n\nAsus TUF 15 FA507NUR-LP044 Mercha Grey\nდამატება\n3299 ₾\n3499 ₾\n\nთვეში: 91 ₾ -დან\n\nAsus TUF 14 FA401UU-RG013 Jaeger Grey\nდამატება\n4179 ₾\n\nთვეში: 116 ₾ -დან\n\nAsus TUF A16 FA608WV-QT053 Grey\nდამატება\n2179 ₾\n2279 ₾\n\nთვეში: 60 ₾ -დან\n\nAsus TUF 15 FA506NFR-HN021, AMD Ryzen 7 7435HS, Nvidi ...\nდამატება\n7299 ₾\n\nთვეში: 202 ₾ -დან\n\nAsus ROG Strix 16 G615JPR-S5101 Grey\nდამატება\n10399 ₾\n10499 ₾\n\nთვეში: 288 ₾ -დან\n\nAsus ROG Strix 18 G835LR-SA005 Black\nდამატება\n15999 ₾\n\nთვეში: 444 ₾ -დან\n\nAsus ROG Strix 18 G835LX-SA034W Black\nდამატება\n6499 ₾\n\nთვეში: 180 ₾ -დან\n\nAsus ROG Strix 16 G614PR-RV007, AMD Ryzen 9-7940HX, N ...\nდამატება\n6699 ₾\n\nთვეში: 186 ₾ -დან\n\nAsus ROG Strix G16 G615JPR-RV113, Intel core i7-14650 ...\nდამატება\n8499 ₾\n\nთვეში: 236 ₾ -დან\n\nAsus ROG Strix G18 G815LR-S9085, Intel Core Ultra 9 2 ...\nდამატება\n4999 ₾\n\nთვეში: 138 ₾ -დან\n\nAsus TUF F16 FX608JMR-RV073, Intel core i7-14650HX 16 ...\nდამატება\n2699 ₾\n\nთვეში: 74 ₾ -დან\n\nAsus TUF 16 FX607VJ-RL005, Intel Core 5-210H, Nvidia ...\nდამატება\n4199 ₾\n\nთვეში: 116 ₾ -დან\n\nAsus TUF F16 FX608JHR-RV035, Intel core i7-14650HX 16 ...\nდამატება\nდამატებითი მახასიათებლები\nბრენდი\nბრენდი:\n\t\nAsus\nმოდელი\nმოდელი:\n\t\nTUF\nტექნიკური მახასიათებლები\nცენტრალური პროცესორი:\n\t\nAMD Ryzen 7-260\n\n\nპროცესორის თაობა:\n\t\nRyzen 7 200 Series\n\n\nპროცესორის სიხშირე:\n\t\n3.8 GHz ~ 5.1 GHz\n\n\nბირთვების რაოდენობა:\n\t\n8\n\n\nნაკადების რაოდენობა:\n\t\n16\n\n\nგრაფიკული პროცესორი:\n\t\nNvidia GeForce RTX 5070\n\n\nგრაფიკული პროცესორის მეხსიერება:\n\t\n8 GB\n\n\nგრაფიკული პროცესორის ტიპი:\n\t\nარა ინტეგრირებული\n\n\nოპერაციული სისტემა:\n\t\n-\n\n\nBluetooth:\n\t\n5.3\nეკრანი\nეკრანის ზომა:\n\t\n18 Inches\n\n\nრეზოლუცია:\n\t\nWUXGA\n\n\nეკრანის ტიპი:\n\t\nIPS\n\n\nსენსორული ეკრანი:\n\t\nNo\n\n\nგანახლების სიხშირე:\n\t\n144 Hz\nდამატებითი მახასიათებლები\nკლავიატურის განათება:\n\t\nYes\n\n\nNumpad:\n\t\nYes\n\n\nდისკის წამკითხველი:\n\t\nNo\n\n\nვებ კამერა:\n\t\nYes\n\n\nლეპტოპის ტიპი:\n\t\nგეიმინგი\nმეხსიერება\nშიდა მეხსიერება:\n\t\n1 TB\n\n\nშიდა მეხსიერების ტიპი:\n\t\nSSD\n\n\nშიდა მეხსიერების ინტერფეისი:\n\t\nM.2\n\n\nოპერატიული მეხსიერება:\n\t\n32 GB\n\n\nოპერატიული მეხსიერების ტიპი:\n\t\nDDR5\n\n\nოპერატიული მეხსიერების სიხშირე:\n\t\n5600 MHz\nპორტები\nUSB:\n\t\n3 x USB-A\n\n\nType-C:\n\t\n2x\n\n\nType-C პორტით დამუხტვა:\n\t\nNo\n\n\nHDMI:\n\t\nYes\n\n\nლან პორტი:\n\t\nYes\n\n\n3.5mm:\n\t\nYes\nზომა/წონა\nწონა:\n\t\n2.6 kg\nფერი\nფერი:\n\t\nGrey\nმეტის ნახვა\nგაეცანი საგარანტიო პირობებს\nსაგარანტიო პირობები\nფილიალები\nმარაგშია\nშეკვეთიდან 2-5 დღეში\nზუმერის წერეთლის ფილიალი\n\nთბილისი - წერეთლის გამზირი, N1.\n\nმარაგშია\n+995 591 967 601\nორშ-შაბ: 10:00:00 - 20:00:00\nკვირა: 10:00:00 - 19:00:00\n5599 ₾\n5899 ₾\n\nთვეში: 155.5 ₾ -დან\n\nმარაგი ფილიალებში\nფასის დაზღვევა\nფასის კონტროლი\nფასის დაჯავშნა\nყიდვა\nშედარება\nდამატება\nნავიგაცია\n\nპერსონალურ მონაცემთა დაცვის პოლიტიკა\n\nჩვენ შესახებ\n\nწესები და პირობები\n\nმიწოდების სერვისი\n\nკარიერა\n\nგადახდები\n\nSetanta Sports\n\nგადახდის მეთოდები\n\nგარანტია\n\nგანვადება\n\nნივთის დაბრუნება\n\nნივთის ონლაინ ყიდვის ინსტრუქცია\n\nგამოგვყევი\n\nFacebook\n\nYoutube\n\nInstagram\n\nTik Tok\n\nკონტაქტი\n\nInfo@zoommer.ge\n\n+995 (32) 2 60 30 60 / *7007\n\nფილიალები\n\nკორპორატიული გაყიდვები\n\nZoommer App\n\nCopyright © 2023 Zoommer.ge. All rights reserved.\n\nCookie პოლიტიკა\n\nსაიტით სარგებლობის გაგრძელებით, შენ ეთანხმები Cookie ჩანაწერების გამოყენებას. მეტი ინფორმაცისათვის იხილეთ კონფიდენციალურობის პოლიტიკა\n\nგასაგებია",
    "specs": {
      "ბრენდი:": "Asus",
      "მოდელი:": "TUF",
      "ცენტრალური პროცესორი:": "AMD Ryzen 7-260",
      "პროცესორის თაობა:": "Ryzen 7 200 Series",
      "პროცესორის სიხშირე:": "3.8 GHz ~ 5.1 GHz",
      "ბირთვების რაოდენობა:": "8",
      "ნაკადების რაოდენობა:": "16",
      "გრაფიკული პროცესორი:": "Nvidia GeForce RTX 5070",
      "გრაფიკული პროცესორის მეხსიერება:": "8 GB",
      "გრაფიკული პროცესორის ტიპი:": "არა ინტეგრირებული",
      "ოპერაციული სისტემა:": "-",
      "Bluetooth:": "5.3",
      "ეკრანის ზომა:": "18 Inches",
      "რეზოლუცია:": "WUXGA",
      "ეკრანის ტიპი:": "IPS",
      "სენსორული ეკრანი:": "No",
      "განახლების სიხშირე:": "144 Hz",
      "კლავიატურის განათება:": "Yes",
      "Numpad:": "Yes",
      "დისკის წამკითხველი:": "No",
      "ვებ კამერა:": "Yes",
      "ლეპტოპის ტიპი:": "გეიმინგი",
      "შიდა მეხსიერება:": "1 TB",
      "შიდა მეხსიერების ტიპი:": "SSD",
      "შიდა მეხსიერების ინტერფეისი:": "M.2",
      "ოპერატიული მეხსიერება:": "32 GB",
      "ოპერატიული მეხსიერების ტიპი:": "DDR5",
      "ოპერატიული მეხსიერების სიხშირე:": "5600 MHz",
      "USB:": "3 x USB-A",
      "Type-C:": "2x",
      "Type-C პორტით დამუხტვა:": "No",
      "HDMI:": "Yes",
      "ლან პორტი:": "Yes",
      "3.5mm:": "Yes",
      "წონა:": "2.6 kg",
      "ფერი:": "Grey"
    }
  },
  {
    "category": "Gaming ლეპტოპები",
    "title": "MSI Thin A15 B7VE 9S7-16RK11-604 Black",
    "price": 3399.0,
    "link": "https://zoommer.ge/leptopebi/msi-thin-a15-b7ve-9s7-16rk11-604-black-p48519",
    "image": "/_next/image?url=https%3A%2F%2Fs3.zoommer.ge%2Fsite%2F1ec5ff43-cbbb-4da0-93f7-8e0419d1baf4_Thumb.jpeg&w=384&q=50",
    "product_title_detail": "MSI Thin A15 B7VE 9S7-16RK11-604 Black",
    "description": "*7007 / +995 (32) 2 60 30 60\nსავაჭრო პოლიტიკა\nგანვადება\nკარიერა\nTrade In\nფილიალები\nნავიგაცია\nკალათა\nშესვლა\n%\nმთავარი\nლეპტოპები\nMSI\n#ZOOM-036789\nMSI Thin A15 B7VE 9S7-16RK11-604 Black\nეკრანის ზომა\n15.6 Inches\nრეზოლუცია\nFull HD\nეკრანის ტიპი\nIPS\nგანახლების სიხშირე\n144 Hz\nშიდა მეხსიერება\n512 GB\nBluetooth\n5.3\nType-C\n1x\nოპერატიული მეხსიერება\n16 GB\nერთად იაფია\nდაამატე ნივთი\nMSI Thin A15 B7VE 9S7-16RK11-604 Black\n3399 ₾\nRivacase 7562 Anti-Theft Laptop Backpack 15 Grey/Dark blue\n67.15 ₾\n79 ₾\nRazer Gaming Mouse DeathAdder Essential USB White\n52 ₾\n65 ₾\nHavit Gaming Cooling Pad HV-F2035 Black\n41.65 ₾\n49 ₾\nჯამური ფასი (3)\n3559.8 ₾\n3592 ₾\nყიდვა\nაქსესუარები\nაღწერა\nმსგავსი\nმახასიათებლები\nფილიალები\nაქსესუარები\nაღწერა\nმსგავსი\nმახასიათებლები\nფილიალები\n89 ₾\n\nთვეში: 2 ₾ -დან\n\nHavit Gaming Cooling Pad HV-F2083 Black\nდამატება\n39 ₾\n\nთვეში: 1 ₾ -დან\n\nLenovo Casual Backpack B210 Green\nდამატება\n219 ₾\n\nთვეში: 6 ₾ -დან\n\nRazer Gaming Mouse Orochi V2 WL Black\nდამატება\n59 ₾\n\nთვეში: 1 ₾ -დან\n\nHavit Gaming mouse Pad HV-MP901\nდამატება\n69 ₾\n\nთვეში: 1 ₾ -დან\n\nXiaomi Mi Router 4A DVB4230GL White\nდამატება\n129 ₾\n\nთვეში: 3 ₾ -დან\n\nRivacase 7930 Pro 16\nდამატება\n219 ₾\n\nთვეში: 6 ₾ -დან\n\nRazer Gaming Mouse Orochi V2 WL White\nდამატება\n9 ₾\n\nHavit Gaming mouse Pad HV-MP838\nდამატება\n85 ₾\n\nთვეში: 2 ₾ -დან\n\nTP-Link Archer C50 AC1200 White\nდამატება\n59 ₾\n\nთვეში: 1 ₾ -დან\n\nRivacese 8035 Laptop Shoulder Bag 15 Black\nდამატება\n209 ₾\n\nთვეში: 5 ₾ -დან\n\nRazer Gaming Mouse DeathAdder V2 X Hyperspeed WL/BT/U ...\nდამატება\n9 ₾\n\nHavit Gaming mouse Pad HV-MP843 Black\nდამატება\n119 ₾\n\nთვეში: 3 ₾ -დან\n\nTP-Link Archer C6 AC1200 Black\nდამატება\n59 ₾\n\nთვეში: 1 ₾ -დან\n\nRivacase 8037 Laptop Bag 15 Black\nდამატება\n139 ₾\n\nთვეში: 3 ₾ -დან\n\nLogitech Gaming Mouse G402 Hyperion Fury black\nდამატება\n149 ₾\n\nთვეში: 4 ₾ -დან\n\nRazer Mouse Pad Firefly V2 RGB M Black\nდამატება\n159 ₾\n\nთვეში: 4 ₾ -დან\n\nXiaomi Router AX1500 White\nდამატება\n79 ₾\n\nთვეში: 2 ₾ -დან\n\nRivacase 7562 Anti-Theft Laptop Backpack 15 Black\nდამატება\n29 ₾\n\nHavit Gaming Mouse HV-MS1010 Black\nდამატება\n199 ₾\n\nთვეში: 5 ₾ -დან\n\nRazer Mouse Pad Goliathus Extended Chroma XXL Black\nდამატება\n179 ₾\n\nთვეში: 4 ₾ -დან\n\nXiaomi Mesh System AX3000 NE 1 pack White\nდამატება\n79 ₾\n\nთვეში: 2 ₾ -დან\n\nRivacase 7562 Anti-Theft Laptop Backpack 15 Dark grey\nდამატება\n79 ₾\n\nთვეში: 2 ₾ -დან\n\nRazer Gaming Mouse DeathAdder Essential USB Black\nდამატება\n149 ₾\n\nთვეში: 4 ₾ -დან\n\nHyperX Pulsefire Mat RGB Black\nდამატება\n299 ₾\n\nთვეში: 8 ₾ -დან\n\nXiaomi Mesh System AX3000 NE 2 pack White\nდამატება\n79 ₾\n\nთვეში: 2 ₾ -დან\n\nRivacase 7562 Anti-Theft Laptop Backpack 15 Grey/Dark ...\nდამატება\n119 ₾\n\nთვეში: 3 ₾ -დან\n\nHyperX Pulsefire Surge Mouse Black\nდამატება\n29 ₾\n\nHavit Gaming Mouse Pad HV-MP845 Black\nდამატება\n249 ₾\n\nთვეში: 6 ₾ -დან\n\nXiaomi Router BE3600 White\nდამატება\n69 ₾\n\nთვეში: 1 ₾ -დან\n\nRivacase 7532 Anti-Theft Laptop Bag 15 Dark Grey\nდამატება\n469 ₾\n\nთვეში: 13 ₾ -დან\n\nHP OMEN PHOTON Wireless Mouse 6CL96AA Black\nდამატება\n29 ₾\n\nHavit Gaming Mouse Pad HV-MP847 Pink\nდამატება\n69 ₾\n\nთვეში: 1 ₾ -დან\n\nRivacase 7532 Anti-Theft Laptop Bag 15 Grey/Dark Blue ...\nდამატება\n65 ₾\n\nთვეში: 1 ₾ -დან\n\nRazer Gaming Mouse DeathAdder Essential USB White\nდამატება\n29 ₾\n\nHavit Gaming Mouse Pad HV-MP849 Black\nდამატება\n79 ₾\n\nთვეში: 2 ₾ -დან\n\nRivacase 8231 Laptop Bag 15 Black\nდამატება\n239 ₾\n\nთვეში: 6 ₾ -დან\n\nRazer Gaming Mouse Basilisk V3 Black\nდამატება\n49 ₾\n\nთვეში: 1 ₾ -დან\n\nHyperX Pulsefire Mat M Black\nდამატება\n79 ₾\n\nთვეში: 2 ₾ -დან\n\nRivacase 8231 Laptop Bag 15 Star blue\nდამატება\n299 ₾\n\nთვეში: 8 ₾ -დან\n\nRazer Gaming Mouse Naga V2 HyperSpeed WL Black\nდამატება\n59 ₾\n\nთვეში: 1 ₾ -დან\n\nHyperX Pulsefire Mat L Black\nდამატება\n79 ₾\n\nთვეში: 2 ₾ -დან\n\nRivacase 8335 Laptop Bag 15 Black\nდამატება\n229 ₾\n\nთვეში: 6 ₾ -დან\n\nRazer Gaming Mouse Basilisk V3 X HyperSpeed WL Black\nდამატება\n39 ₾\n\nთვეში: 1 ₾ -დან\n\nRazer Mouse Pad Sphex V3 S Black\nდამატება\n79 ₾\n\nთვეში: 2 ₾ -დან\n\nRivacase 8335 Laptop Bag 15 Star blue\nდამატება\n129 ₾\n\nთვეში: 3 ₾ -დან\n\nRazer Gaming Mouse Cobra Black\nდამატება\n89 ₾\n\nთვეში: 2 ₾ -დან\n\nRazer Mouse Pad Sphex V3 L Black\nდამატება\n69 ₾\n\nთვეში: 1 ₾ -დან\n\nRivacase 7730 Eco Laptop Shoulder Bag 15 Black\nდამატება\n19 ₾\n\nHavit Gaming Mouse HV-MS989GT Black/Red\nდამატება\n29 ₾\n\nHavit Gaming mouse Pad HV-MP860\nდამატება\n59 ₾\n\nთვეში: 1 ₾ -დან\n\nRivacase 8035 Laptop Shoulder Bag 15\nდამატება\n19 ₾\n\nHavit Gaming Mouse HV-MS626GT Black\nდამატება\n79 ₾\n\nთვეში: 2 ₾ -დან\n\nTomtoc Defender A13 Laptop Sleeve 15 A13E3D1 Black\nდამატება\n19 ₾\n\nHavit Gaming Mouse HV-MS66GT White/Blue\nდამატება\n119 ₾\n\nთვეში: 3 ₾ -დან\n\nTomtoc Defender A42 Laptop Briefcase 15 A42E1D1 Black\nდამატება\n149 ₾\n\nთვეში: 4 ₾ -დან\n\nHyperX Gaming Mouse Pulsefire Haste 2 Black\nდამატება\n79 ₾\n\nთვეში: 2 ₾ -დან\n\nHP Campus backpack 15.6 7J595AA Green\nდამატება\n19 ₾\n\nHavit Wireless Mouse HV-MS66GT Black\nდამატება\n79 ₾\n\nთვეში: 2 ₾ -დან\n\nHP Campus backpack 15.6 7J597AA Lavender\nდამატება\n179 ₾\n\nთვეში: 4 ₾ -დან\n\nLogitech Gaming Mouse G305 LIGHTSPEED WL L910-005282 ...\nდამატება\n69 ₾\n\nთვეში: 1 ₾ -დან\n\nRivacase 8065 Laptop Backpack 15 Black\nდამატება\n259 ₾\n\nთვეში: 7 ₾ -დან\n\nLogitech Gaming Mouse G502 X L910-006138 Black\nდამატება\n69 ₾\n\nთვეში: 1 ₾ -დან\n\nRivacase 8065 Laptop Backpack 15 Dark Blue\nდამატება\n259 ₾\n\nთვეში: 7 ₾ -დან\n\nLogitech Gaming Mouse G502 X L910-006138 White\nდამატება\n79 ₾\n\nთვეში: 2 ₾ -დან\n\nRivacase 8335 Laptop Bag 15 Purple\nდამატება\n19 ₾\n\nHavit Gaming Mouse HV-MS626GT Black/Red\nდამატება\n19 ₾\n\nHavit Gaming Mouse HV-MS626GT Black/Blue\nდამატება\n349 ₾\n\nთვეში: 9 ₾ -დან\n\nLogitech Gaming Mouse G703 LIGHTSPEED WL L910-005640 ...\nდამატება\n89 ₾\n\nთვეში: 2 ₾ -დან\n\nLogitech Gaming Mouse G102 LIGHTSYNC L910-005823 Blac ...\nდამატება\n89 ₾\n\nთვეში: 2 ₾ -დან\n\nLogitech Gaming Mouse G102 LIGHTSYNC L910-005824 Whit ...\nდამატება\n89 ₾\n\nთვეში: 2 ₾ -დან\n\nLogitech Gaming Mouse G102 LIGHTSYNC L910-005801 Blue\nდამატება\n239 ₾\n\nთვეში: 6 ₾ -დან\n\nLogitech Gaming Mouse G502 HERO L910-005470 Black\nდამატება\n199 ₾\n\nთვეში: 5 ₾ -დან\n\nHyperX Pulsefire Haste 2 core Wireless Black\nდამატება\n199 ₾\n\nთვეში: 5 ₾ -დან\n\nHyperX Pulsefire Haste 2 core Wireless White\nდამატება\n59 ₾\n\nთვეში: 1 ₾ -დან\n\nHavit Gaming Mouse HV-MS954 Black\nდამატება\n39 ₾\n\nთვეში: 1 ₾ -დან\n\nHavit Gaming Mouse HV-MS1033 White\nდამატება\n39 ₾\n\nთვეში: 1 ₾ -დან\n\nHavit Gaming Mouse HV-MS1029 Pink\nდამატება\n59 ₾\n\nთვეში: 1 ₾ -დან\n\nHavit Gaming Mouse HV-MS966 Black/Green\nდამატება\n49 ₾\n\nთვეში: 1 ₾ -დან\n\nHavit Wireless Mouse HV-MS1039W Black/White\nდამატება\n79 ₾\n\nთვეში: 2 ₾ -დან\n\nHavit Wireless Mouse HV-MS970WB Pro Black\nდამატება\n79 ₾\n\nთვეში: 2 ₾ -დან\n\nHavit Wireless Mouse HV-MS970WB Pro Transparent White\nდამატება\n219 ₾\n\nთვეში: 6 ₾ -დან\n\nRazer Gaming Mouse Orochi V2 WL Pink\nდამატება\nპროდუქტის შესახებ\n\nთუ ეძებთ ლეპტოპს, რომელიც მარტივად გაუმკლავდება ყველაზე მოთხოვნად თამაშებს — MSI Thin A15 B7VE 9S7-16RK11-604 Black შექმნილია სწორედ თქვენთვის. ეს მოდელი აერთიანებს მაღალ წარმადობას, გამძლე კონსტრუქ...\n\nმეტის ნახვა\nმსგავსი პროდუქტები\n2599 ₾\n2999 ₾\n\nთვეში: 72 ₾ -დან\n\nMSI Thin A15 B7UC 9S7-16RK11-211, AMD Ryzen 7, Nvidia ...\nდამატება\n5599 ₾\n5999 ₾\n\nთვეში: 155 ₾ -დან\n\nMSI Sword 16 HX B14VGKG 9S7-15P214-262, Intel core i7 ...\nდამატება\n3299 ₾\n3499 ₾\n\nთვეში: 91 ₾ -დან\n\nMSI Thin 15 9S7-16R831-2003 Black\nდამატება\n4499 ₾\n5199 ₾\n\nთვეში: 124 ₾ -დან\n\nMSI Sword 16 HX B14VFKG 9S7-15P214-669, Intel Core i7 ...\nდამატება\n5199 ₾\n5499 ₾\n\nთვეში: 144 ₾ -დან\n\nMSI Crosshair 16 HX D14VFKG 9S7-15P231-670, Intel Cor ...\nდამატება\n2449 ₾\n2549 ₾\n\nთვეში: 68 ₾ -დან\n\nMSI Thin 15 9S7-16R831-2681, Intel Core i5-12450H, Nv ...\nდამატება\n3399 ₾\n3699 ₾\n\nთვეში: 94 ₾ -დან\n\nMSI Katana 15 9S7-158571-2222, Intel Core i5-13420H, ...\nდამატება\n5399 ₾\n5999 ₾\n\nთვეში: 149 ₾ -დან\n\nMSI Crosshair 17 9S7-17T223-270, Intel Core i7-14700H ...\nდამატება\n3999 ₾\n4299 ₾\n\nთვეში: 111 ₾ -დან\n\nMSI Katana 15 9S7-158571-2279, Intel Core i7-13620H, ...\nდამატება\n4499 ₾\n4899 ₾\n\nთვეში: 124 ₾ -დან\n\nMSI Sword 16 9S7-15P214-886, Intel Core i7-14650HX, N ...\nდამატება\n2599 ₾\n\nთვეში: 72 ₾ -დან\n\nMSI Thin A15 B7UC 9S7-16RK11-601 Black\nდამატება\n2599 ₾\n2799 ₾\n\nთვეში: 72 ₾ -დან\n\nMSI Thin A15 B7UC 9S7-16RK11-602 Black\nდამატება\n2999 ₾\n3199 ₾\n\nთვეში: 83 ₾ -დან\n\nMSI Thin A15 B7VE 9S7-16RK11-603 Black\nდამატება\nდამატებითი მახასიათებლები\nბრენდი\nბრენდი:\n\t\nMSI\nმოდელი\nმოდელი:\n\t\nThin\nტექნიკური მახასიათებლები\nცენტრალური პროცესორი:\n\t\nAMD Ryzen 7-7735HS\n\n\nპროცესორის თაობა:\n\t\nRyzen 7 7000 Series\n\n\nპროცესორის სიხშირე:\n\t\n3.2 GHz ~ 4.75 GHz\n\n\nბირთვების რაოდენობა:\n\t\n8\n\n\nნაკადების რაოდენობა:\n\t\n16\n\n\nგრაფიკული პროცესორი:\n\t\nNvidia GeForce RTX 4050\n\n\nგრაფიკული პროცესორის მეხსიერება:\n\t\n6 GB\n\n\nგრაფიკული პროცესორის ტიპი:\n\t\nარა ინტეგრირებული\n\n\nოპერაციული სისტემა:\n\t\nNo\n\n\nBluetooth:\n\t\n5.3\nეკრანი\nეკრანის ზომა:\n\t\n15.6 Inches\n\n\nრეზოლუცია:\n\t\nFull HD\n\n\nეკრანის ტიპი:\n\t\nIPS\n\n\nსენსორული ეკრანი:\n\t\nNo\n\n\nგანახლების სიხშირე:\n\t\n144 Hz\nდამატებითი მახასიათებლები\nკლავიატურის განათება:\n\t\nYes\n\n\nNumpad:\n\t\nNo\n\n\nდისკის წამკითხველი:\n\t\nNo\n\n\nვებ კამერა:\n\t\nYes\n\n\nლეპტოპის ტიპი:\n\t\nგეიმინგი\nმეხსიერება\nშიდა მეხსიერება:\n\t\n512 GB\n\n\nშიდა მეხსიერების ტიპი:\n\t\nSSD\n\n\nშიდა მეხსიერების ინტერფეისი:\n\t\nM.2\n\n\nოპერატიული მეხსიერება:\n\t\n16 GB\n\n\nოპერატიული მეხსიერების ტიპი:\n\t\nDDR5\n\n\nოპერატიული მეხსიერების სიხშირე:\n\t\n-\nპორტები\nUSB:\n\t\n3 x USB-A\n\n\nType-C:\n\t\n1x\n\n\nType-C პორტით დამუხტვა:\n\t\nNo\n\n\nHDMI:\n\t\nYes\n\n\nლან პორტი:\n\t\nYes\n\n\n3.5mm:\n\t\nYes\nზომა/წონა\nწონა:\n\t\n1.86 kg\nფერი\nფერი:\n\t\nBlack\nმეტის ნახვა\nგაეცანი საგარანტიო პირობებს\nსაგარანტიო პირობები\nფილიალები\nმარაგშია\nშეკვეთიდან 2-5 დღეში\nზუმერის წერეთლის ფილიალი\n\nთბილისი - წერეთლის გამზირი, N1.\n\nმარაგშია\n+995 591 967 601\nორშ-შაბ: 10:00:00 - 20:00:00\nკვირა: 10:00:00 - 19:00:00\nზუმერის \"თბილისი ცენტრალის\" ფილიალი\n\nთბილისი - \"თბილისი ცენტრალი\"- lll სართული\n\nმარაგშია\n+995 599 862 449\nორშ-შაბ: 10:00:00 - 20:00:00\nკვირა: 10:00:00 - 19:00:00\nზუმერის City Mall საბურთალო-ს ფილიალი\n\nთბილისი - \"სითი მოლი\" - პეტრე ქავთარაძის N1\n\nმარაგშია\n+995 591 971 962\nორშ-შაბ: 10:00:00 - 22:00:00\nკვირა: 10:00:00 - 22:00:00\nზუმერის თბილისი მოლის ფილიალი\n\nთბილისი - „თბილისი მოლი\" - I სართული. აღმაშენებლის ხეივანი მე-16 კმ\n\nმარაგშია\n+995 591 967 608\nორშ-შაბ: 10:00:00 - 22:00:00\nკვირა: 10:00:00 - 22:00:00\nზუმერის \"გლდანი მოლის\" ფილიალი\n\nთბილისი - \"გლდანი მოლი\" - I სართული, M-ახმეტელის მიმდებარე\n\nმარაგშია\n+995 591 967 673\nორშ-შაბ: 10:00:00 - 21:00:00\nკვირა: 10:00:00 - 21:00:00\nზუმერის ისთ ფოინთის ფილიალი\n\nთბილისი - \"ისთ ფოინთი\" - ალ. თვალჭრელიძე N2\n\nმარაგშია\n+995 591 340 476\nორშ-შაბ: 10:00:00 - 22:00:00\nკვირა: 10:00:00 - 22:00:00\nბათუმი ჭავჭავაძის ფილიალი\n\nბათუმი - ბათუმი, ჭავჭავაძის N21\n\nმარაგშია\n+995 591 967 606\nორშ-შაბ: 10:00:00 - 20:00:00\nკვირა: 10:00:00 - 19:00:00\nმეტის ნახვა\n3399 ₾\n\nთვეში: 94.4 ₾ -დან\n\nმარაგი ფილიალებში\nფასის დაზღვევა\nფასის კონტროლი\nფასის დაჯავშნა\nყიდვა\nშედარება\nდამატება\nნავიგაცია\n\nპერსონალურ მონაცემთა დაცვის პოლიტიკა\n\nჩვენ შესახებ\n\nწესები და პირობები\n\nმიწოდების სერვისი\n\nკარიერა\n\nგადახდები\n\nSetanta Sports\n\nგადახდის მეთოდები\n\nგარანტია\n\nგანვადება\n\nნივთის დაბრუნება\n\nნივთის ონლაინ ყიდვის ინსტრუქცია\n\nგამოგვყევი\n\nFacebook\n\nYoutube\n\nInstagram\n\nTik Tok\n\nკონტაქტი\n\nInfo@zoommer.ge\n\n+995 (32) 2 60 30 60 / *7007\n\nფილიალები\n\nკორპორატიული გაყიდვები\n\nZoommer App\n\nCopyright © 2023 Zoommer.ge. All rights reserved.\n\nCookie პოლიტიკა\n\nსაიტით სარგებლობის გაგრძელებით, შენ ეთანხმები Cookie ჩანაწერების გამოყენებას. მეტი ინფორმაცისათვის იხილეთ კონფიდენციალურობის პოლიტიკა\n\nგასაგებია",
    "specs": {
      "ბრენდი:": "MSI",
      "მოდელი:": "Thin",
      "ცენტრალური პროცესორი:": "AMD Ryzen 7-7735HS",
      "პროცესორის თაობა:": "Ryzen 7 7000 Series",
      "პროცესორის სიხშირე:": "3.2 GHz ~ 4.75 GHz",
      "ბირთვების რაოდენობა:": "8",
      "ნაკადების რაოდენობა:": "16",
      "გრაფიკული პროცესორი:": "Nvidia GeForce RTX 4050",
      "გრაფიკული პროცესორის მეხსიერება:": "6 GB",
      "გრაფიკული პროცესორის ტიპი:": "არა ინტეგრირებული",
      "ოპერაციული სისტემა:": "No",
      "Bluetooth:": "5.3",
      "ეკრანის ზომა:": "15.6 Inches",
      "რეზოლუცია:": "Full HD",
      "ეკრანის ტიპი:": "IPS",
      "სენსორული ეკრანი:": "No",
      "განახლების სიხშირე:": "144 Hz",
      "კლავიატურის განათება:": "Yes",
      "Numpad:": "No",
      "დისკის წამკითხველი:": "No",
      "ვებ კამერა:": "Yes",
      "ლეპტოპის ტიპი:": "გეიმინგი",
      "შიდა მეხსიერება:": "512 GB",
      "შიდა მეხსიერების ტიპი:": "SSD",
      "შიდა მეხსიერების ინტერფეისი:": "M.2",
      "ოპერატიული მეხსიერება:": "16 GB",
      "ოპერატიული მეხსიერების ტიპი:": "DDR5",
      "ოპერატიული მეხსიერების სიხშირე:": "-",
      "USB:": "3 x USB-A",
      "Type-C:": "1x",
      "Type-C პორტით დამუხტვა:": "No",
      "HDMI:": "Yes",
      "ლან პორტი:": "Yes",
      "3.5mm:": "Yes",
      "წონა:": "1.86 kg",
      "ფერი:": "Black"
    }
  },
  {
    "category": "Gaming ლეპტოპები",
    "title": "MSI Thin A15 B7VE 9S7-16RK11-603 Black",
    "price": 2999.0,
    "link": "https://zoommer.ge/leptopebi/msi-thin-a15-b7ve-9s7-16rk11-603-black-p48518",
    "image": "/_next/image?url=https%3A%2F%2Fs3.zoommer.ge%2Fsite%2Fc1891171-3f4b-440e-9fc0-1f7a9b684a8b_Thumb.jpeg&w=384&q=50",
    "product_title_detail": "MSI Thin A15 B7VE 9S7-16RK11-603 Black",
    "description": "*7007 / +995 (32) 2 60 30 60\nფილიალები\nნავიგაცია\nკალათა\nშესვლა\n%\nმთავარი\nლეპტოპები\nMSI\n#ZOOM-036788\nMSI Thin A15 B7VE 9S7-16RK11-603 Black\nეკრანის ზომა\n15.6 Inches\nრეზოლუცია\nFull HD\nეკრანის ტიპი\nIPS\nგანახლების სიხშირე\n144 Hz\nშიდა მეხსიერება\n512 GB\nBluetooth\n5.3\nType-C\n1x\nოპერატიული მეხსიერება\n16 GB\nერთად იაფია\nდაამატე ნივთი\nMSI Thin A15 B7VE 9S7-16RK11-603 Black\n2999 ₾\nRivacase 7562 Anti-Theft Laptop Backpack 15 Grey/Dark blue\n67.15 ₾\n79 ₾\nRazer Gaming Mouse DeathAdder Essential USB White\n52 ₾\n65 ₾\nHavit Gaming Cooling Pad HV-F2035 Black\n41.65 ₾\n49 ₾\nჯამური ფასი (3)\n3159.8 ₾\n3192 ₾\nყიდვა\nაქსესუარები\nაღწერა\nმსგავსი\nმახასიათებლები\nფილიალები\nაქსესუარები\nაღწერა\nმსგავსი\nმახასიათებლები\nფილიალები\n89 ₾\n\nთვეში: 2 ₾ -დან\n\nHavit Gaming Cooling Pad HV-F2083 Black\nდამატება\n39 ₾\n\nთვეში: 1 ₾ -დან\n\nLenovo Casual Backpack B210 Green\nდამატება\n219 ₾\n\nთვეში: 6 ₾ -დან\n\nRazer Gaming Mouse Orochi V2 WL Black\nდამატება\n59 ₾\n\nთვეში: 1 ₾ -დან\n\nHavit Gaming mouse Pad HV-MP901\nდამატება\n69 ₾\n\nთვეში: 1 ₾ -დან\n\nXiaomi Mi Router 4A DVB4230GL White\nდამატება\n129 ₾\n\nთვეში: 3 ₾ -დან\n\nRivacase 7930 Pro 16\nდამატება\n219 ₾\n\nთვეში: 6 ₾ -დან\n\nRazer Gaming Mouse Orochi V2 WL White\nდამატება\n9 ₾\n\nHavit Gaming mouse Pad HV-MP838\nდამატება\n85 ₾\n\nთვეში: 2 ₾ -დან\n\nTP-Link Archer C50 AC1200 White\nდამატება\n59 ₾\n\nთვეში: 1 ₾ -დან\n\nRivacese 8035 Laptop Shoulder Bag 15 Black\nდამატება\n209 ₾\n\nთვეში: 5 ₾ -დან\n\nRazer Gaming Mouse DeathAdder V2 X Hyperspeed WL/BT/U ...\nდამატება\n9 ₾\n\nHavit Gaming mouse Pad HV-MP843 Black\nდამატება\n119 ₾\n\nთვეში: 3 ₾ -დან\n\nTP-Link Archer C6 AC1200 Black\nდამატება\n59 ₾\n\nთვეში: 1 ₾ -დან\n\nRivacase 8037 Laptop Bag 15 Black\nდამატება\n139 ₾\n\nთვეში: 3 ₾ -დან\n\nLogitech Gaming Mouse G402 Hyperion Fury black\nდამატება\n149 ₾\n\nთვეში: 4 ₾ -დან\n\nRazer Mouse Pad Firefly V2 RGB M Black\nდამატება\n159 ₾\n\nთვეში: 4 ₾ -დან\n\nXiaomi Router AX1500 White\nდამატება\n79 ₾\n\nთვეში: 2 ₾ -დან\n\nRivacase 7562 Anti-Theft Laptop Backpack 15 Black\nდამატება\n29 ₾\n\nHavit Gaming Mouse HV-MS1010 Black\nდამატება\n199 ₾\n\nთვეში: 5 ₾ -დან\n\nRazer Mouse Pad Goliathus Extended Chroma XXL Black\nდამატება\n179 ₾\n\nთვეში: 4 ₾ -დან\n\nXiaomi Mesh System AX3000 NE 1 pack White\nდამატება\n79 ₾\n\nთვეში: 2 ₾ -დან\n\nRivacase 7562 Anti-Theft Laptop Backpack 15 Dark grey\nდამატება\n79 ₾\n\nთვეში: 2 ₾ -დან\n\nRazer Gaming Mouse DeathAdder Essential USB Black\nდამატება\n149 ₾\n\nთვეში: 4 ₾ -დან\n\nHyperX Pulsefire Mat RGB Black\nდამატება\n299 ₾\n\nთვეში: 8 ₾ -დან\n\nXiaomi Mesh System AX3000 NE 2 pack White\nდამატება\n79 ₾\n\nთვეში: 2 ₾ -დან\n\nRivacase 7562 Anti-Theft Laptop Backpack 15 Grey/Dark ...\nდამატება\n119 ₾\n\nთვეში: 3 ₾ -დან\n\nHyperX Pulsefire Surge Mouse Black\nდამატება\n29 ₾\n\nHavit Gaming Mouse Pad HV-MP845 Black\nდამატება\n249 ₾\n\nთვეში: 6 ₾ -დან\n\nXiaomi Router BE3600 White\nდამატება\n69 ₾\n\nთვეში: 1 ₾ -დან\n\nRivacase 7532 Anti-Theft Laptop Bag 15 Dark Grey\nდამატება\n469 ₾\n\nთვეში: 13 ₾ -დან\n\nHP OMEN PHOTON Wireless Mouse 6CL96AA Black\nდამატება\n29 ₾\n\nHavit Gaming Mouse Pad HV-MP847 Pink\nდამატება\n69 ₾\n\nთვეში: 1 ₾ -დან\n\nRivacase 7532 Anti-Theft Laptop Bag 15 Grey/Dark Blue ...\nდამატება\n65 ₾\n\nთვეში: 1 ₾ -დან\n\nRazer Gaming Mouse DeathAdder Essential USB White\nდამატება\n29 ₾\n\nHavit Gaming Mouse Pad HV-MP849 Black\nდამატება\n79 ₾\n\nთვეში: 2 ₾ -დან\n\nRivacase 8231 Laptop Bag 15 Black\nდამატება\n239 ₾\n\nთვეში: 6 ₾ -დან\n\nRazer Gaming Mouse Basilisk V3 Black\nდამატება\n49 ₾\n\nთვეში: 1 ₾ -დან\n\nHyperX Pulsefire Mat M Black\nდამატება\n79 ₾\n\nთვეში: 2 ₾ -დან\n\nRivacase 8231 Laptop Bag 15 Star blue\nდამატება\n299 ₾\n\nთვეში: 8 ₾ -დან\n\nRazer Gaming Mouse Naga V2 HyperSpeed WL Black\nდამატება\n59 ₾\n\nთვეში: 1 ₾ -დან\n\nHyperX Pulsefire Mat L Black\nდამატება\n79 ₾\n\nთვეში: 2 ₾ -დან\n\nRivacase 8335 Laptop Bag 15 Black\nდამატება\n229 ₾\n\nთვეში: 6 ₾ -დან\n\nRazer Gaming Mouse Basilisk V3 X HyperSpeed WL Black\nდამატება\n39 ₾\n\nთვეში: 1 ₾ -დან\n\nRazer Mouse Pad Sphex V3 S Black\nდამატება\n79 ₾\n\nთვეში: 2 ₾ -დან\n\nRivacase 8335 Laptop Bag 15 Star blue\nდამატება\n129 ₾\n\nთვეში: 3 ₾ -დან\n\nRazer Gaming Mouse Cobra Black\nდამატება\n89 ₾\n\nთვეში: 2 ₾ -დან\n\nRazer Mouse Pad Sphex V3 L Black\nდამატება\n69 ₾\n\nთვეში: 1 ₾ -დან\n\nRivacase 7730 Eco Laptop Shoulder Bag 15 Black\nდამატება\n19 ₾\n\nHavit Gaming Mouse HV-MS989GT Black/Red\nდამატება\n29 ₾\n\nHavit Gaming mouse Pad HV-MP860\nდამატება\n59 ₾\n\nთვეში: 1 ₾ -დან\n\nRivacase 8035 Laptop Shoulder Bag 15\nდამატება\n19 ₾\n\nHavit Gaming Mouse HV-MS626GT Black\nდამატება\n79 ₾\n\nთვეში: 2 ₾ -დან\n\nTomtoc Defender A13 Laptop Sleeve 15 A13E3D1 Black\nდამატება\n19 ₾\n\nHavit Gaming Mouse HV-MS66GT White/Blue\nდამატება\n119 ₾\n\nთვეში: 3 ₾ -დან\n\nTomtoc Defender A42 Laptop Briefcase 15 A42E1D1 Black\nდამატება\n149 ₾\n\nთვეში: 4 ₾ -დან\n\nHyperX Gaming Mouse Pulsefire Haste 2 Black\nდამატება\n79 ₾\n\nთვეში: 2 ₾ -დან\n\nHP Campus backpack 15.6 7J595AA Green\nდამატება\n19 ₾\n\nHavit Wireless Mouse HV-MS66GT Black\nდამატება\n79 ₾\n\nთვეში: 2 ₾ -დან\n\nHP Campus backpack 15.6 7J597AA Lavender\nდამატება\n179 ₾\n\nთვეში: 4 ₾ -დან\n\nLogitech Gaming Mouse G305 LIGHTSPEED WL L910-005282 ...\nდამატება\n69 ₾\n\nთვეში: 1 ₾ -დან\n\nRivacase 8065 Laptop Backpack 15 Black\nდამატება\n259 ₾\n\nთვეში: 7 ₾ -დან\n\nLogitech Gaming Mouse G502 X L910-006138 Black\nდამატება\n69 ₾\n\nთვეში: 1 ₾ -დან\n\nRivacase 8065 Laptop Backpack 15 Dark Blue\nდამატება\n259 ₾\n\nთვეში: 7 ₾ -დან\n\nLogitech Gaming Mouse G502 X L910-006138 White\nდამატება\n79 ₾\n\nთვეში: 2 ₾ -დან\n\nRivacase 8335 Laptop Bag 15 Purple\nდამატება\n19 ₾\n\nHavit Gaming Mouse HV-MS626GT Black/Red\nდამატება\n19 ₾\n\nHavit Gaming Mouse HV-MS626GT Black/Blue\nდამატება\n349 ₾\n\nთვეში: 9 ₾ -დან\n\nLogitech Gaming Mouse G703 LIGHTSPEED WL L910-005640 ...\nდამატება\n89 ₾\n\nთვეში: 2 ₾ -დან\n\nLogitech Gaming Mouse G102 LIGHTSYNC L910-005823 Blac ...\nდამატება\n89 ₾\n\nთვეში: 2 ₾ -დან\n\nLogitech Gaming Mouse G102 LIGHTSYNC L910-005824 Whit ...\nდამატება\n89 ₾\n\nთვეში: 2 ₾ -დან\n\nLogitech Gaming Mouse G102 LIGHTSYNC L910-005801 Blue\nდამატება\n239 ₾\n\nთვეში: 6 ₾ -დან\n\nLogitech Gaming Mouse G502 HERO L910-005470 Black\nდამატება\n199 ₾\n\nთვეში: 5 ₾ -დან\n\nHyperX Pulsefire Haste 2 core Wireless Black\nდამატება\n199 ₾\n\nთვეში: 5 ₾ -დან\n\nHyperX Pulsefire Haste 2 core Wireless White\nდამატება\n59 ₾\n\nთვეში: 1 ₾ -დან\n\nHavit Gaming Mouse HV-MS954 Black\nდამატება\n39 ₾\n\nთვეში: 1 ₾ -დან\n\nHavit Gaming Mouse HV-MS1033 White\nდამატება\n39 ₾\n\nთვეში: 1 ₾ -დან\n\nHavit Gaming Mouse HV-MS1029 Pink\nდამატება\n59 ₾\n\nთვეში: 1 ₾ -დან\n\nHavit Gaming Mouse HV-MS966 Black/Green\nდამატება\n49 ₾\n\nთვეში: 1 ₾ -დან\n\nHavit Wireless Mouse HV-MS1039W Black/White\nდამატება\n79 ₾\n\nთვეში: 2 ₾ -დან\n\nHavit Wireless Mouse HV-MS970WB Pro Black\nდამატება\n79 ₾\n\nთვეში: 2 ₾ -დან\n\nHavit Wireless Mouse HV-MS970WB Pro Transparent White\nდამატება\n219 ₾\n\nთვეში: 6 ₾ -დან\n\nRazer Gaming Mouse Orochi V2 WL Pink\nდამატება\nპროდუქტის შესახებ\n\nთუ ეძებთ ლეპტოპს, რომელიც მარტივად გაუმკლავდება ყველაზე მოთხოვნად თამაშებს — MSI Thin A15 B7VE 9S7-16RK11-603 Black შექმნილია სწორედ თქვენთვის. ეს მოდელი აერთიანებს მაღალ წარმადობას, გამძლე კონსტრუქ...\n\nმეტის ნახვა\nმსგავსი პროდუქტები\n2599 ₾\n2999 ₾\n\nთვეში: 72 ₾ -დან\n\nMSI Thin A15 B7UC 9S7-16RK11-211, AMD Ryzen 7, Nvidia ...\nდამატება\n5599 ₾\n5999 ₾\n\nთვეში: 155 ₾ -დან\n\nMSI Sword 16 HX B14VGKG 9S7-15P214-262, Intel core i7 ...\nდამატება\n3299 ₾\n3499 ₾\n\nთვეში: 91 ₾ -დან\n\nMSI Thin 15 9S7-16R831-2003 Black\nდამატება\n4499 ₾\n5199 ₾\n\nთვეში: 124 ₾ -დან\n\nMSI Sword 16 HX B14VFKG 9S7-15P214-669, Intel Core i7 ...\nდამატება\n5199 ₾\n5499 ₾\n\nთვეში: 144 ₾ -დან\n\nMSI Crosshair 16 HX D14VFKG 9S7-15P231-670, Intel Cor ...\nდამატება\n2449 ₾\n2549 ₾\n\nთვეში: 68 ₾ -დან\n\nMSI Thin 15 9S7-16R831-2681, Intel Core i5-12450H, Nv ...\nდამატება\n3399 ₾\n3699 ₾\n\nთვეში: 94 ₾ -დან\n\nMSI Katana 15 9S7-158571-2222, Intel Core i5-13420H, ...\nდამატება\n5399 ₾\n5999 ₾\n\nთვეში: 149 ₾ -დან\n\nMSI Crosshair 17 9S7-17T223-270, Intel Core i7-14700H ...\nდამატება\n3999 ₾\n4299 ₾\n\nთვეში: 111 ₾ -დან\n\nMSI Katana 15 9S7-158571-2279, Intel Core i7-13620H, ...\nდამატება\n4499 ₾\n4899 ₾\n\nთვეში: 124 ₾ -დან\n\nMSI Sword 16 9S7-15P214-886, Intel Core i7-14650HX, N ...\nდამატება\n2599 ₾\n\nთვეში: 72 ₾ -დან\n\nMSI Thin A15 B7UC 9S7-16RK11-601 Black\nდამატება\n2599 ₾\n2799 ₾\n\nთვეში: 72 ₾ -დან\n\nMSI Thin A15 B7UC 9S7-16RK11-602 Black\nდამატება\n3399 ₾\n\nთვეში: 94 ₾ -დან\n\nMSI Thin A15 B7VE 9S7-16RK11-604 Black\nდამატება\nდამატებითი მახასიათებლები\nბრენდი\nბრენდი:\n\t\nMSI\nმოდელი\nმოდელი:\n\t\nThin\nტექნიკური მახასიათებლები\nცენტრალური პროცესორი:\n\t\nAMD Ryzen 5-7535HS\n\n\nპროცესორის თაობა:\n\t\nRyzen 5 7000 Series\n\n\nპროცესორის სიხშირე:\n\t\n3.3 GHz ~ 4.55 GHz\n\n\nბირთვების რაოდენობა:\n\t\n6\n\n\nნაკადების რაოდენობა:\n\t\n12\n\n\nგრაფიკული პროცესორი:\n\t\nNvidia GeForce RTX 4050\n\n\nგრაფიკული პროცესორის მეხსიერება:\n\t\n6 GB\n\n\nგრაფიკული პროცესორის ტიპი:\n\t\nარა ინტეგრირებული\n\n\nოპერაციული სისტემა:\n\t\nNo\n\n\nBluetooth:\n\t\n5.3\nეკრანი\nეკრანის ზომა:\n\t\n15.6 Inches\n\n\nრეზოლუცია:\n\t\nFull HD\n\n\nეკრანის ტიპი:\n\t\nIPS\n\n\nსენსორული ეკრანი:\n\t\nNo\n\n\nგანახლების სიხშირე:\n\t\n144 Hz\nდამატებითი მახასიათებლები\nკლავიატურის განათება:\n\t\nYes\n\n\nNumpad:\n\t\nNo\n\n\nდისკის წამკითხველი:\n\t\nNo\n\n\nვებ კამერა:\n\t\nYes\n\n\nლეპტოპის ტიპი:\n\t\nგეიმინგი\nმეხსიერება\nშიდა მეხსიერება:\n\t\n512 GB\n\n\nშიდა მეხსიერების ტიპი:\n\t\nSSD\n\n\nშიდა მეხსიერების ინტერფეისი:\n\t\nM.2\n\n\nოპერატიული მეხსიერება:\n\t\n16 GB\n\n\nოპერატიული მეხსიერების ტიპი:\n\t\nDDR5\n\n\nოპერატიული მეხსიერების სიხშირე:\n\t\n-\nპორტები\nUSB:\n\t\n3 x USB-A\n\n\nType-C:\n\t\n1x\n\n\nType-C პორტით დამუხტვა:\n\t\nNo\n\n\nHDMI:\n\t\nYes\n\n\nლან პორტი:\n\t\nYes\n\n\n3.5mm:\n\t\nYes\nზომა/წონა\nწონა:\n\t\n1.86 kg\nფერი\nფერი:\n\t\nBlack\nმეტის ნახვა\nგაეცანი საგარანტიო პირობებს\nსაგარანტიო პირობები\nფილიალები\nმარაგშია\nშეკვეთიდან 2-5 დღეში\nზუმერის წერეთლის ფილიალი\n\nთბილისი - წერეთლის გამზირი, N1.\n\nმარაგშია\n+995 591 967 601\nორშ-შაბ: 10:00:00 - 20:00:00\nკვირა: 10:00:00 - 19:00:00\nზუმერის \"თბილისი ცენტრალის\" ფილიალი\n\nთბილისი - \"თბილისი ცენტრალი\"- lll სართული\n\nმარაგშია\n+995 599 862 449\nორშ-შაბ: 10:00:00 - 20:00:00\nკვირა: 10:00:00 - 19:00:00\nზუმერის City Mall საბურთალო-ს ფილიალი\n\nთბილისი - \"სითი მოლი\" - პეტრე ქავთარაძის N1\n\nმარაგშია\n+995 591 971 962\nორშ-შაბ: 10:00:00 - 22:00:00\nკვირა: 10:00:00 - 22:00:00\nზუმერის თბილისი მოლის ფილიალი\n\nთბილისი - „თბილისი მოლი\" - I სართული. აღმაშენებლის ხეივანი მე-16 კმ\n\nმარაგშია\n+995 591 967 608\nორშ-შაბ: 10:00:00 - 22:00:00\nკვირა: 10:00:00 - 22:00:00\nზუმერის \"გლდანი მოლის\" ფილიალი\n\nთბილისი - \"გლდანი მოლი\" - I სართული, M-ახმეტელის მიმდებარე\n\nმარაგშია\n+995 591 967 673\nორშ-შაბ: 10:00:00 - 21:00:00\nკვირა: 10:00:00 - 21:00:00\nზუმერის ისთ ფოინთის ფილიალი\n\nთბილისი - \"ისთ ფოინთი\" - ალ. თვალჭრელიძე N2\n\nმარაგშია\n+995 591 340 476\nორშ-შაბ: 10:00:00 - 22:00:00\nკვირა: 10:00:00 - 22:00:00\nზუმერი რუსთავი მოლის ფილიალი\n\nრუსთავი - შარტავას და ლომოურის კვეთა\n\nმარაგშია\n+995 591 441 082\nორშ-შაბ: 10:00:00 - 22:00:00\nკვირა: 10:00:00 - 22:00:00\nბათუმი ჭავჭავაძის ფილიალი\n\nბათუმი - ბათუმი, ჭავჭავაძის N21\n\nმარაგშია\n+995 591 967 606\nორშ-შაბ: 10:00:00 - 20:00:00\nკვირა: 10:00:00 - 19:00:00\nბათუმის \"Black Sea Mall\"-ის ფილიალი\n\nბათუმი - \"Black Sea Mall\" - ტბელ აბუსერიძის N22\n\nმარაგშია\n+995 591 310 257\nორშ-შაბ: 10:00:00 - 21:00:00\nკვირა: 10:00:00 - 21:00:00\nბათუმის გრანდ მოლის ფილიალი\n\nბათუმი - \"გრანდ მოლი\" - შერიფ ხიმშიაშვილის 29\n\nმარაგშია\n+995 591 022 872\nორშ-შაბ: 10:00:00 - 22:00:00\nკვირა: 10:00:00 - 22:00:00\nქუთაისი ვესთ მოლი\n\nქუთაისი - \"ვესთ მოლი\" - შარტავას N2\n\nმარაგშია\n+995 595 306 765\nორშ-შაბ: 10:00:00 - 22:00:00\nკვირა: 10:00:00 - 22:00:00\nზუგდიდი მოლის ფილიალი\n\nზუგდიდი - ზუგდიდი მოლი, კოსტავას ქუჩა №28\n\nმარაგშია\n+995 591 676 489\nორშ-შაბ: 10:00:00 - 22:00:00\nკვირა: 10:00:00 - 22:00:00\nზუმერის საწყობი\n\nთბილისი - თბილისი\n\nმარაგშია\nორშ-შაბ: 10:00:00 - 19:00:00\nკვირა: 10:00:00 - 19:00:00\nმეტის ნახვა\n2999 ₾\n3199 ₾\n\nთვეში: 83.3 ₾ -დან\n\nმარაგი ფილიალებში\nფასის დაზღვევა\nფასის კონტროლი\nფასის დაჯავშნა\nყიდვა\nშედარება\nდამატება\nნავიგაცია\nგადახდები\nგამოგვყევი\n\nFacebook\n\nYoutube\n\nInstagram\n\nTik Tok\n\nკონტაქტი\n\nInfo@zoommer.ge\n\n+995 (32) 2 60 30 60 / *7007\n\nფილიალები\n\nკორპორატიული გაყიდვები\n\nZoommer App\n\nCopyright © 2023 Zoommer.ge. All rights reserved.\n\nCookie პოლიტიკა\n\nსაიტით სარგებლობის გაგრძელებით, შენ ეთანხმები Cookie ჩანაწერების გამოყენებას. მეტი ინფორმაცისათვის იხილეთ კონფიდენციალურობის პოლიტიკა\n\nგასაგებია",
    "specs": {
      "ბრენდი:": "MSI",
      "მოდელი:": "Thin",
      "ცენტრალური პროცესორი:": "AMD Ryzen 5-7535HS",
      "პროცესორის თაობა:": "Ryzen 5 7000 Series",
      "პროცესორის სიხშირე:": "3.3 GHz ~ 4.55 GHz",
      "ბირთვების რაოდენობა:": "6",
      "ნაკადების რაოდენობა:": "12",
      "გრაფიკული პროცესორი:": "Nvidia GeForce RTX 4050",
      "გრაფიკული პროცესორის მეხსიერება:": "6 GB",
      "გრაფიკული პროცესორის ტიპი:": "არა ინტეგრირებული",
      "ოპერაციული სისტემა:": "No",
      "Bluetooth:": "5.3",
      "ეკრანის ზომა:": "15.6 Inches",
      "რეზოლუცია:": "Full HD",
      "ეკრანის ტიპი:": "IPS",
      "სენსორული ეკრანი:": "No",
      "განახლების სიხშირე:": "144 Hz",
      "კლავიატურის განათება:": "Yes",
      "Numpad:": "No",
      "დისკის წამკითხველი:": "No",
      "ვებ კამერა:": "Yes",
      "ლეპტოპის ტიპი:": "გეიმინგი",
      "შიდა მეხსიერება:": "512 GB",
      "შიდა მეხსიერების ტიპი:": "SSD",
      "შიდა მეხსიერების ინტერფეისი:": "M.2",
      "ოპერატიული მეხსიერება:": "16 GB",
      "ოპერატიული მეხსიერების ტიპი:": "DDR5",
      "ოპერატიული მეხსიერების სიხშირე:": "-",
      "USB:": "3 x USB-A",
      "Type-C:": "1x",
      "Type-C პორტით დამუხტვა:": "No",
      "HDMI:": "Yes",
      "ლან პორტი:": "Yes",
      "3.5mm:": "Yes",
      "წონა:": "1.86 kg",
      "ფერი:": "Black"
    }
  },
  {
    "category": "Gaming ლეპტოპები",
    "title": "MSI Thin A15 B7UC 9S7-16RK11-602 Black",
    "price": 2599.0,
    "link": "https://zoommer.ge/leptopebi/msi-thin-a15-b7uc-9s7-16rk11-602-black-p48517",
    "image": "/_next/image?url=https%3A%2F%2Fs3.zoommer.ge%2Fsite%2Fb5710844-1f1a-44a1-829c-ffbcafbc529d_Thumb.jpeg&w=384&q=50",
    "product_title_detail": "MSI Thin A15 B7UC 9S7-16RK11-602 Black",
    "description": "*7007 / +995 (32) 2 60 30 60\nსავაჭრო პოლიტიკა\nგანვადება\nკარიერა\nTrade In\nფილიალები\nნავიგაცია\nკალათა\nშესვლა\n%\nმთავარი\nლეპტოპები\nMSI\n#ZOOM-036787\nMSI Thin A15 B7UC 9S7-16RK11-602 Black\nეკრანის ზომა\n15.6 Inches\nრეზოლუცია\nFull HD\nეკრანის ტიპი\nIPS\nგანახლების სიხშირე\n144 Hz\nშიდა მეხსიერება\n512 GB\nBluetooth\n5.3\nType-C\n1x\nოპერატიული მეხსიერება\n16 GB\nერთად იაფია\nდაამატე ნივთი\nMSI Thin A15 B7UC 9S7-16RK11-602 Black\n2599 ₾\nRivacase 7562 Anti-Theft Laptop Backpack 15 Grey/Dark blue\n67.15 ₾\n79 ₾\nRazer Gaming Mouse DeathAdder Essential USB White\n52 ₾\n65 ₾\nHavit Gaming Cooling Pad HV-F2035 Black\n41.65 ₾\n49 ₾\nჯამური ფასი (3)\n2759.8 ₾\n2792 ₾\nყიდვა\nაქსესუარები\nაღწერა\nმსგავსი\nმახასიათებლები\nფილიალები\nაქსესუარები\nაღწერა\nმსგავსი\nმახასიათებლები\nფილიალები\n89 ₾\n\nთვეში: 2 ₾ -დან\n\nHavit Gaming Cooling Pad HV-F2083 Black\nდამატება\n39 ₾\n\nთვეში: 1 ₾ -დან\n\nLenovo Casual Backpack B210 Green\nდამატება\n219 ₾\n\nთვეში: 6 ₾ -დან\n\nRazer Gaming Mouse Orochi V2 WL Black\nდამატება\n59 ₾\n\nთვეში: 1 ₾ -დან\n\nHavit Gaming mouse Pad HV-MP901\nდამატება\n69 ₾\n\nთვეში: 1 ₾ -დან\n\nXiaomi Mi Router 4A DVB4230GL White\nდამატება\n129 ₾\n\nთვეში: 3 ₾ -დან\n\nRivacase 7930 Pro 16\nდამატება\n219 ₾\n\nთვეში: 6 ₾ -დან\n\nRazer Gaming Mouse Orochi V2 WL White\nდამატება\n9 ₾\n\nHavit Gaming mouse Pad HV-MP838\nდამატება\n85 ₾\n\nთვეში: 2 ₾ -დან\n\nTP-Link Archer C50 AC1200 White\nდამატება\n59 ₾\n\nთვეში: 1 ₾ -დან\n\nRivacese 8035 Laptop Shoulder Bag 15 Black\nდამატება\n209 ₾\n\nთვეში: 5 ₾ -დან\n\nRazer Gaming Mouse DeathAdder V2 X Hyperspeed WL/BT/U ...\nდამატება\n9 ₾\n\nHavit Gaming mouse Pad HV-MP843 Black\nდამატება\n119 ₾\n\nთვეში: 3 ₾ -დან\n\nTP-Link Archer C6 AC1200 Black\nდამატება\n59 ₾\n\nთვეში: 1 ₾ -დან\n\nRivacase 8037 Laptop Bag 15 Black\nდამატება\n139 ₾\n\nთვეში: 3 ₾ -დან\n\nLogitech Gaming Mouse G402 Hyperion Fury black\nდამატება\n149 ₾\n\nთვეში: 4 ₾ -დან\n\nRazer Mouse Pad Firefly V2 RGB M Black\nდამატება\n159 ₾\n\nთვეში: 4 ₾ -დან\n\nXiaomi Router AX1500 White\nდამატება\n79 ₾\n\nთვეში: 2 ₾ -დან\n\nRivacase 7562 Anti-Theft Laptop Backpack 15 Black\nდამატება\n29 ₾\n\nHavit Gaming Mouse HV-MS1010 Black\nდამატება\n199 ₾\n\nთვეში: 5 ₾ -დან\n\nRazer Mouse Pad Goliathus Extended Chroma XXL Black\nდამატება\n179 ₾\n\nთვეში: 4 ₾ -დან\n\nXiaomi Mesh System AX3000 NE 1 pack White\nდამატება\n79 ₾\n\nთვეში: 2 ₾ -დან\n\nRivacase 7562 Anti-Theft Laptop Backpack 15 Dark grey\nდამატება\n79 ₾\n\nთვეში: 2 ₾ -დან\n\nRazer Gaming Mouse DeathAdder Essential USB Black\nდამატება\n149 ₾\n\nთვეში: 4 ₾ -დან\n\nHyperX Pulsefire Mat RGB Black\nდამატება\n299 ₾\n\nთვეში: 8 ₾ -დან\n\nXiaomi Mesh System AX3000 NE 2 pack White\nდამატება\n79 ₾\n\nთვეში: 2 ₾ -დან\n\nRivacase 7562 Anti-Theft Laptop Backpack 15 Grey/Dark ...\nდამატება\n119 ₾\n\nთვეში: 3 ₾ -დან\n\nHyperX Pulsefire Surge Mouse Black\nდამატება\n29 ₾\n\nHavit Gaming Mouse Pad HV-MP845 Black\nდამატება\n249 ₾\n\nთვეში: 6 ₾ -დან\n\nXiaomi Router BE3600 White\nდამატება\n69 ₾\n\nთვეში: 1 ₾ -დან\n\nRivacase 7532 Anti-Theft Laptop Bag 15 Dark Grey\nდამატება\n469 ₾\n\nთვეში: 13 ₾ -დან\n\nHP OMEN PHOTON Wireless Mouse 6CL96AA Black\nდამატება\n29 ₾\n\nHavit Gaming Mouse Pad HV-MP847 Pink\nდამატება\n69 ₾\n\nთვეში: 1 ₾ -დან\n\nRivacase 7532 Anti-Theft Laptop Bag 15 Grey/Dark Blue ...\nდამატება\n65 ₾\n\nთვეში: 1 ₾ -დან\n\nRazer Gaming Mouse DeathAdder Essential USB White\nდამატება\n29 ₾\n\nHavit Gaming Mouse Pad HV-MP849 Black\nდამატება\n79 ₾\n\nთვეში: 2 ₾ -დან\n\nRivacase 8231 Laptop Bag 15 Black\nდამატება\n239 ₾\n\nთვეში: 6 ₾ -დან\n\nRazer Gaming Mouse Basilisk V3 Black\nდამატება\n49 ₾\n\nთვეში: 1 ₾ -დან\n\nHyperX Pulsefire Mat M Black\nდამატება\n79 ₾\n\nთვეში: 2 ₾ -დან\n\nRivacase 8231 Laptop Bag 15 Star blue\nდამატება\n299 ₾\n\nთვეში: 8 ₾ -დან\n\nRazer Gaming Mouse Naga V2 HyperSpeed WL Black\nდამატება\n59 ₾\n\nთვეში: 1 ₾ -დან\n\nHyperX Pulsefire Mat L Black\nდამატება\n79 ₾\n\nთვეში: 2 ₾ -დან\n\nRivacase 8335 Laptop Bag 15 Black\nდამატება\n229 ₾\n\nთვეში: 6 ₾ -დან\n\nRazer Gaming Mouse Basilisk V3 X HyperSpeed WL Black\nდამატება\n39 ₾\n\nთვეში: 1 ₾ -დან\n\nRazer Mouse Pad Sphex V3 S Black\nდამატება\n79 ₾\n\nთვეში: 2 ₾ -დან\n\nRivacase 8335 Laptop Bag 15 Star blue\nდამატება\n129 ₾\n\nთვეში: 3 ₾ -დან\n\nRazer Gaming Mouse Cobra Black\nდამატება\n89 ₾\n\nთვეში: 2 ₾ -დან\n\nRazer Mouse Pad Sphex V3 L Black\nდამატება\n69 ₾\n\nთვეში: 1 ₾ -დან\n\nRivacase 7730 Eco Laptop Shoulder Bag 15 Black\nდამატება\n19 ₾\n\nHavit Gaming Mouse HV-MS989GT Black/Red\nდამატება\n29 ₾\n\nHavit Gaming mouse Pad HV-MP860\nდამატება\n59 ₾\n\nთვეში: 1 ₾ -დან\n\nRivacase 8035 Laptop Shoulder Bag 15\nდამატება\n19 ₾\n\nHavit Gaming Mouse HV-MS626GT Black\nდამატება\n79 ₾\n\nთვეში: 2 ₾ -დან\n\nTomtoc Defender A13 Laptop Sleeve 15 A13E3D1 Black\nდამატება\n19 ₾\n\nHavit Gaming Mouse HV-MS66GT White/Blue\nდამატება\n119 ₾\n\nთვეში: 3 ₾ -დან\n\nTomtoc Defender A42 Laptop Briefcase 15 A42E1D1 Black\nდამატება\n149 ₾\n\nთვეში: 4 ₾ -დან\n\nHyperX Gaming Mouse Pulsefire Haste 2 Black\nდამატება\n79 ₾\n\nთვეში: 2 ₾ -დან\n\nHP Campus backpack 15.6 7J595AA Green\nდამატება\n19 ₾\n\nHavit Wireless Mouse HV-MS66GT Black\nდამატება\n79 ₾\n\nთვეში: 2 ₾ -დან\n\nHP Campus backpack 15.6 7J597AA Lavender\nდამატება\n179 ₾\n\nთვეში: 4 ₾ -დან\n\nLogitech Gaming Mouse G305 LIGHTSPEED WL L910-005282 ...\nდამატება\n69 ₾\n\nთვეში: 1 ₾ -დან\n\nRivacase 8065 Laptop Backpack 15 Black\nდამატება\n259 ₾\n\nთვეში: 7 ₾ -დან\n\nLogitech Gaming Mouse G502 X L910-006138 Black\nდამატება\n69 ₾\n\nთვეში: 1 ₾ -დან\n\nRivacase 8065 Laptop Backpack 15 Dark Blue\nდამატება\n259 ₾\n\nთვეში: 7 ₾ -დან\n\nLogitech Gaming Mouse G502 X L910-006138 White\nდამატება\n79 ₾\n\nთვეში: 2 ₾ -დან\n\nRivacase 8335 Laptop Bag 15 Purple\nდამატება\n19 ₾\n\nHavit Gaming Mouse HV-MS626GT Black/Red\nდამატება\n19 ₾\n\nHavit Gaming Mouse HV-MS626GT Black/Blue\nდამატება\n349 ₾\n\nთვეში: 9 ₾ -დან\n\nLogitech Gaming Mouse G703 LIGHTSPEED WL L910-005640 ...\nდამატება\n89 ₾\n\nთვეში: 2 ₾ -დან\n\nLogitech Gaming Mouse G102 LIGHTSYNC L910-005823 Blac ...\nდამატება\n89 ₾\n\nთვეში: 2 ₾ -დან\n\nLogitech Gaming Mouse G102 LIGHTSYNC L910-005824 Whit ...\nდამატება\n89 ₾\n\nთვეში: 2 ₾ -დან\n\nLogitech Gaming Mouse G102 LIGHTSYNC L910-005801 Blue\nდამატება\n239 ₾\n\nთვეში: 6 ₾ -დან\n\nLogitech Gaming Mouse G502 HERO L910-005470 Black\nდამატება\n199 ₾\n\nთვეში: 5 ₾ -დან\n\nHyperX Pulsefire Haste 2 core Wireless Black\nდამატება\n199 ₾\n\nთვეში: 5 ₾ -დან\n\nHyperX Pulsefire Haste 2 core Wireless White\nდამატება\n59 ₾\n\nთვეში: 1 ₾ -დან\n\nHavit Gaming Mouse HV-MS954 Black\nდამატება\n39 ₾\n\nთვეში: 1 ₾ -დან\n\nHavit Gaming Mouse HV-MS1033 White\nდამატება\n39 ₾\n\nთვეში: 1 ₾ -დან\n\nHavit Gaming Mouse HV-MS1029 Pink\nდამატება\n59 ₾\n\nთვეში: 1 ₾ -დან\n\nHavit Gaming Mouse HV-MS966 Black/Green\nდამატება\n49 ₾\n\nთვეში: 1 ₾ -დან\n\nHavit Wireless Mouse HV-MS1039W Black/White\nდამატება\n79 ₾\n\nთვეში: 2 ₾ -დან\n\nHavit Wireless Mouse HV-MS970WB Pro Black\nდამატება\n79 ₾\n\nთვეში: 2 ₾ -დან\n\nHavit Wireless Mouse HV-MS970WB Pro Transparent White\nდამატება\n219 ₾\n\nთვეში: 6 ₾ -დან\n\nRazer Gaming Mouse Orochi V2 WL Pink\nდამატება\nპროდუქტის შესახებ\n\nთუ ეძებთ ლეპტოპს, რომელიც მარტივად გაუმკლავდება ყველაზე მოთხოვნად თამაშებს — MSI Thin A15 B7UC 9S7-16RK11-602 Black შექმნილია სწორედ თქვენთვის. ეს მოდელი აერთიანებს მაღალ წარმადობას, გამძლე კონსტრუქ...\n\nმეტის ნახვა\nმსგავსი პროდუქტები\n2599 ₾\n2999 ₾\n\nთვეში: 72 ₾ -დან\n\nMSI Thin A15 B7UC 9S7-16RK11-211, AMD Ryzen 7, Nvidia ...\nდამატება\n5599 ₾\n5999 ₾\n\nთვეში: 155 ₾ -დან\n\nMSI Sword 16 HX B14VGKG 9S7-15P214-262, Intel core i7 ...\nდამატება\n3299 ₾\n3499 ₾\n\nთვეში: 91 ₾ -დან\n\nMSI Thin 15 9S7-16R831-2003 Black\nდამატება\n4499 ₾\n5199 ₾\n\nთვეში: 124 ₾ -დან\n\nMSI Sword 16 HX B14VFKG 9S7-15P214-669, Intel Core i7 ...\nდამატება\n5199 ₾\n5499 ₾\n\nთვეში: 144 ₾ -დან\n\nMSI Crosshair 16 HX D14VFKG 9S7-15P231-670, Intel Cor ...\nდამატება\n2449 ₾\n2549 ₾\n\nთვეში: 68 ₾ -დან\n\nMSI Thin 15 9S7-16R831-2681, Intel Core i5-12450H, Nv ...\nდამატება\n3399 ₾\n3699 ₾\n\nთვეში: 94 ₾ -დან\n\nMSI Katana 15 9S7-158571-2222, Intel Core i5-13420H, ...\nდამატება\n5399 ₾\n5999 ₾\n\nთვეში: 149 ₾ -დან\n\nMSI Crosshair 17 9S7-17T223-270, Intel Core i7-14700H ...\nდამატება\n3999 ₾\n4299 ₾\n\nთვეში: 111 ₾ -დან\n\nMSI Katana 15 9S7-158571-2279, Intel Core i7-13620H, ...\nდამატება\n4499 ₾\n4899 ₾\n\nთვეში: 124 ₾ -დან\n\nMSI Sword 16 9S7-15P214-886, Intel Core i7-14650HX, N ...\nდამატება\n2599 ₾\n\nთვეში: 72 ₾ -დან\n\nMSI Thin A15 B7UC 9S7-16RK11-601 Black\nდამატება\n2999 ₾\n3199 ₾\n\nთვეში: 83 ₾ -დან\n\nMSI Thin A15 B7VE 9S7-16RK11-603 Black\nდამატება\n3399 ₾\n\nთვეში: 94 ₾ -დან\n\nMSI Thin A15 B7VE 9S7-16RK11-604 Black\nდამატება\nდამატებითი მახასიათებლები\nბრენდი\nბრენდი:\n\t\nMSI\nმოდელი\nმოდელი:\n\t\nThin\nტექნიკური მახასიათებლები\nცენტრალური პროცესორი:\n\t\nAMD Ryzen 7-7735HS\n\n\nპროცესორის თაობა:\n\t\nRyzen 7 7000 Series\n\n\nპროცესორის სიხშირე:\n\t\n3.2 GHz ~ 4.75 GHz\n\n\nბირთვების რაოდენობა:\n\t\n8\n\n\nნაკადების რაოდენობა:\n\t\n16\n\n\nგრაფიკული პროცესორი:\n\t\nNvidia GeForce RTX 3050\n\n\nგრაფიკული პროცესორის მეხსიერება:\n\t\n4 GB\n\n\nგრაფიკული პროცესორის ტიპი:\n\t\nარა ინტეგრირებული\n\n\nოპერაციული სისტემა:\n\t\nNo\n\n\nBluetooth:\n\t\n5.3\nეკრანი\nეკრანის ზომა:\n\t\n15.6 Inches\n\n\nრეზოლუცია:\n\t\nFull HD\n\n\nეკრანის ტიპი:\n\t\nIPS\n\n\nსენსორული ეკრანი:\n\t\nNo\n\n\nგანახლების სიხშირე:\n\t\n144 Hz\nდამატებითი მახასიათებლები\nკლავიატურის განათება:\n\t\nYes\n\n\nNumpad:\n\t\nNo\n\n\nდისკის წამკითხველი:\n\t\nNo\n\n\nვებ კამერა:\n\t\nYes\n\n\nლეპტოპის ტიპი:\n\t\nგეიმინგი\nმეხსიერება\nშიდა მეხსიერება:\n\t\n512 GB\n\n\nშიდა მეხსიერების ტიპი:\n\t\nSSD\n\n\nშიდა მეხსიერების ინტერფეისი:\n\t\nM.2\n\n\nოპერატიული მეხსიერება:\n\t\n16 GB\n\n\nოპერატიული მეხსიერების ტიპი:\n\t\nDDR5\n\n\nოპერატიული მეხსიერების სიხშირე:\n\t\n-\nპორტები\nUSB:\n\t\n3 x USB-A\n\n\nType-C:\n\t\n1x\n\n\nType-C პორტით დამუხტვა:\n\t\nNo\n\n\nHDMI:\n\t\nYes\n\n\nლან პორტი:\n\t\nYes\n\n\n3.5mm:\n\t\nYes\nზომა/წონა\nწონა:\n\t\n1.86 kg\nფერი\nფერი:\n\t\nBlack\nმეტის ნახვა\nგაეცანი საგარანტიო პირობებს\nსაგარანტიო პირობები\nფილიალები\nმარაგშია\nშეკვეთიდან 2-5 დღეში\nზუმერის წერეთლის ფილიალი\n\nთბილისი - წერეთლის გამზირი, N1.\n\nმარაგშია\n+995 591 967 601\nორშ-შაბ: 10:00:00 - 20:00:00\nკვირა: 10:00:00 - 19:00:00\nზუმერის \"თბილისი ცენტრალის\" ფილიალი\n\nთბილისი - \"თბილისი ცენტრალი\"- lll სართული\n\nმარაგშია\n+995 599 862 449\nორშ-შაბ: 10:00:00 - 20:00:00\nკვირა: 10:00:00 - 19:00:00\nზუმერის City Mall საბურთალო-ს ფილიალი\n\nთბილისი - \"სითი მოლი\" - პეტრე ქავთარაძის N1\n\nმარაგშია\n+995 591 971 962\nორშ-შაბ: 10:00:00 - 22:00:00\nკვირა: 10:00:00 - 22:00:00\nზუმერის თბილისი მოლის ფილიალი\n\nთბილისი - „თბილისი მოლი\" - I სართული. აღმაშენებლის ხეივანი მე-16 კმ\n\nმარაგშია\n+995 591 967 608\nორშ-შაბ: 10:00:00 - 22:00:00\nკვირა: 10:00:00 - 22:00:00\nზუმერის \"გლდანი მოლის\" ფილიალი\n\nთბილისი - \"გლდანი მოლი\" - I სართული, M-ახმეტელის მიმდებარე\n\nმარაგშია\n+995 591 967 673\nორშ-შაბ: 10:00:00 - 21:00:00\nკვირა: 10:00:00 - 21:00:00\nზუმერის ისთ ფოინთის ფილიალი\n\nთბილისი - \"ისთ ფოინთი\" - ალ. თვალჭრელიძე N2\n\nმარაგშია\n+995 591 340 476\nორშ-შაბ: 10:00:00 - 22:00:00\nკვირა: 10:00:00 - 22:00:00\nზუმერი რუსთავი მოლის ფილიალი\n\nრუსთავი - შარტავას და ლომოურის კვეთა\n\nმარაგშია\n+995 591 441 082\nორშ-შაბ: 10:00:00 - 22:00:00\nკვირა: 10:00:00 - 22:00:00\nბათუმი ჭავჭავაძის ფილიალი\n\nბათუმი - ბათუმი, ჭავჭავაძის N21\n\nმარაგშია\n+995 591 967 606\nორშ-შაბ: 10:00:00 - 20:00:00\nკვირა: 10:00:00 - 19:00:00\nბათუმის \"Black Sea Mall\"-ის ფილიალი\n\nბათუმი - \"Black Sea Mall\" - ტბელ აბუსერიძის N22\n\nმარაგშია\n+995 591 310 257\nორშ-შაბ: 10:00:00 - 21:00:00\nკვირა: 10:00:00 - 21:00:00\nბათუმის გრანდ მოლის ფილიალი\n\nბათუმი - \"გრანდ მოლი\" - შერიფ ხიმშიაშვილის 29\n\nმარაგშია\n+995 591 022 872\nორშ-შაბ: 10:00:00 - 22:00:00\nკვირა: 10:00:00 - 22:00:00\nქუთაისი ვესთ მოლი\n\nქუთაისი - \"ვესთ მოლი\" - შარტავას N2\n\nმარაგშია\n+995 595 306 765\nორშ-შაბ: 10:00:00 - 22:00:00\nკვირა: 10:00:00 - 22:00:00\nზუგდიდი მოლის ფილიალი\n\nზუგდიდი - ზუგდიდი მოლი, კოსტავას ქუჩა №28\n\nმარაგშია\n+995 591 676 489\nორშ-შაბ: 10:00:00 - 22:00:00\nკვირა: 10:00:00 - 22:00:00\nგორი მოლის ფილიალი\n\nგორი - გორი, ცხინვალის გზატკეცილი 14-14ამ, გორი მოლი\n\nმარაგშია\n+995 591 198 248\nორშ-შაბ: 10:00:00 - 22:00:00\nკვირა: 10:00:00 - 22:00:00\nზუმერის საწყობი\n\nთბილისი - თბილისი\n\nმარაგშია\nორშ-შაბ: 10:00:00 - 19:00:00\nკვირა: 10:00:00 - 19:00:00\nმეტის ნახვა\n2599 ₾\n2799 ₾\n\nთვეში: 72.2 ₾ -დან\n\nმარაგი ფილიალებში\nფასის დაზღვევა\nფასის კონტროლი\nფასის დაჯავშნა\nყიდვა\nშედარება\nდამატება\nნავიგაცია\n\nპერსონალურ მონაცემთა დაცვის პოლიტიკა\n\nჩვენ შესახებ\n\nწესები და პირობები\n\nმიწოდების სერვისი\n\nკარიერა\n\nგადახდები\n\nSetanta Sports\n\nგადახდის მეთოდები\n\nგარანტია\n\nგანვადება\n\nნივთის დაბრუნება\n\nნივთის ონლაინ ყიდვის ინსტრუქცია\n\nგამოგვყევი\n\nFacebook\n\nYoutube\n\nInstagram\n\nTik Tok\n\nკონტაქტი\n\nInfo@zoommer.ge\n\n+995 (32) 2 60 30 60 / *7007\n\nფილიალები\n\nკორპორატიული გაყიდვები\n\nZoommer App\n\nCopyright © 2023 Zoommer.ge. All rights reserved.\n\nCookie პოლიტიკა\n\nსაიტით სარგებლობის გაგრძელებით, შენ ეთანხმები Cookie ჩანაწერების გამოყენებას. მეტი ინფორმაცისათვის იხილეთ კონფიდენციალურობის პოლიტიკა\n\nგასაგებია",
    "specs": {
      "ბრენდი:": "MSI",
      "მოდელი:": "Thin",
      "ცენტრალური პროცესორი:": "AMD Ryzen 7-7735HS",
      "პროცესორის თაობა:": "Ryzen 7 7000 Series",
      "პროცესორის სიხშირე:": "3.2 GHz ~ 4.75 GHz",
      "ბირთვების რაოდენობა:": "8",
      "ნაკადების რაოდენობა:": "16",
      "გრაფიკული პროცესორი:": "Nvidia GeForce RTX 3050",
      "გრაფიკული პროცესორის მეხსიერება:": "4 GB",
      "გრაფიკული პროცესორის ტიპი:": "არა ინტეგრირებული",
      "ოპერაციული სისტემა:": "No",
      "Bluetooth:": "5.3",
      "ეკრანის ზომა:": "15.6 Inches",
      "რეზოლუცია:": "Full HD",
      "ეკრანის ტიპი:": "IPS",
      "სენსორული ეკრანი:": "No",
      "განახლების სიხშირე:": "144 Hz",
      "კლავიატურის განათება:": "Yes",
      "Numpad:": "No",
      "დისკის წამკითხველი:": "No",
      "ვებ კამერა:": "Yes",
      "ლეპტოპის ტიპი:": "გეიმინგი",
      "შიდა მეხსიერება:": "512 GB",
      "შიდა მეხსიერების ტიპი:": "SSD",
      "შიდა მეხსიერების ინტერფეისი:": "M.2",
      "ოპერატიული მეხსიერება:": "16 GB",
      "ოპერატიული მეხსიერების ტიპი:": "DDR5",
      "ოპერატიული მეხსიერების სიხშირე:": "-",
      "USB:": "3 x USB-A",
      "Type-C:": "1x",
      "Type-C პორტით დამუხტვა:": "No",
      "HDMI:": "Yes",
      "ლან პორტი:": "Yes",
      "3.5mm:": "Yes",
      "წონა:": "1.86 kg",
      "ფერი:": "Black"
    }
  },
  {
    "category": "Gaming ლეპტოპები",
    "title": "MSI Thin A15 B7UC 9S7-16RK11-601 Black",
    "price": 2599.0,
    "link": "https://zoommer.ge/leptopebi/msi-thin-a15-b7uc-9s7-16rk11-601-black-p48516",
    "image": "/_next/image?url=https%3A%2F%2Fs3.zoommer.ge%2Fsite%2F62e59329-0913-4818-ac9e-6f0af01a7a20_Thumb.jpeg&w=384&q=50",
    "product_title_detail": "MSI Thin A15 B7UC 9S7-16RK11-601 Black",
    "description": "*7007 / +995 (32) 2 60 30 60\nსავაჭრო პოლიტიკა\nგანვადება\nკარიერა\nTrade In\nფილიალები\nნავიგაცია\nკალათა\nშესვლა\n%\nმთავარი\nლეპტოპები\nMSI\n#ZOOM-036786\nMSI Thin A15 B7UC 9S7-16RK11-601 Black\nეკრანის ზომა\n15.6 Inches\nრეზოლუცია\nFull HD\nეკრანის ტიპი\nIPS\nგანახლების სიხშირე\n144 Hz\nშიდა მეხსიერება\n512 GB\nBluetooth\n5.3\nType-C\n1x\nოპერატიული მეხსიერება\n16 GB\nერთად იაფია\nდაამატე ნივთი\nMSI Thin A15 B7UC 9S7-16RK11-601 Black\n2599 ₾\nRivacase 7562 Anti-Theft Laptop Backpack 15 Grey/Dark blue\n67.15 ₾\n79 ₾\nRazer Gaming Mouse DeathAdder Essential USB White\n52 ₾\n65 ₾\nHavit Gaming Cooling Pad HV-F2035 Black\n41.65 ₾\n49 ₾\nჯამური ფასი (3)\n2759.8 ₾\n2792 ₾\nყიდვა\nაქსესუარები\nაღწერა\nმსგავსი\nმახასიათებლები\nფილიალები\nაქსესუარები\nაღწერა\nმსგავსი\nმახასიათებლები\nფილიალები\n89 ₾\n\nთვეში: 2 ₾ -დან\n\nHavit Gaming Cooling Pad HV-F2083 Black\nდამატება\n39 ₾\n\nთვეში: 1 ₾ -დან\n\nLenovo Casual Backpack B210 Green\nდამატება\n219 ₾\n\nთვეში: 6 ₾ -დან\n\nRazer Gaming Mouse Orochi V2 WL Black\nდამატება\n59 ₾\n\nთვეში: 1 ₾ -დან\n\nHavit Gaming mouse Pad HV-MP901\nდამატება\n69 ₾\n\nთვეში: 1 ₾ -დან\n\nXiaomi Mi Router 4A DVB4230GL White\nდამატება\n129 ₾\n\nთვეში: 3 ₾ -დან\n\nRivacase 7930 Pro 16\nდამატება\n219 ₾\n\nთვეში: 6 ₾ -დან\n\nRazer Gaming Mouse Orochi V2 WL White\nდამატება\n9 ₾\n\nHavit Gaming mouse Pad HV-MP838\nდამატება\n85 ₾\n\nთვეში: 2 ₾ -დან\n\nTP-Link Archer C50 AC1200 White\nდამატება\n59 ₾\n\nთვეში: 1 ₾ -დან\n\nRivacese 8035 Laptop Shoulder Bag 15 Black\nდამატება\n209 ₾\n\nთვეში: 5 ₾ -დან\n\nRazer Gaming Mouse DeathAdder V2 X Hyperspeed WL/BT/U ...\nდამატება\n9 ₾\n\nHavit Gaming mouse Pad HV-MP843 Black\nდამატება\n119 ₾\n\nთვეში: 3 ₾ -დან\n\nTP-Link Archer C6 AC1200 Black\nდამატება\n59 ₾\n\nთვეში: 1 ₾ -დან\n\nRivacase 8037 Laptop Bag 15 Black\nდამატება\n139 ₾\n\nთვეში: 3 ₾ -დან\n\nLogitech Gaming Mouse G402 Hyperion Fury black\nდამატება\n149 ₾\n\nთვეში: 4 ₾ -დან\n\nRazer Mouse Pad Firefly V2 RGB M Black\nდამატება\n159 ₾\n\nთვეში: 4 ₾ -დან\n\nXiaomi Router AX1500 White\nდამატება\n79 ₾\n\nთვეში: 2 ₾ -დან\n\nRivacase 7562 Anti-Theft Laptop Backpack 15 Black\nდამატება\n29 ₾\n\nHavit Gaming Mouse HV-MS1010 Black\nდამატება\n199 ₾\n\nთვეში: 5 ₾ -დან\n\nRazer Mouse Pad Goliathus Extended Chroma XXL Black\nდამატება\n179 ₾\n\nთვეში: 4 ₾ -დან\n\nXiaomi Mesh System AX3000 NE 1 pack White\nდამატება\n79 ₾\n\nთვეში: 2 ₾ -დან\n\nRivacase 7562 Anti-Theft Laptop Backpack 15 Dark grey\nდამატება\n79 ₾\n\nთვეში: 2 ₾ -დან\n\nRazer Gaming Mouse DeathAdder Essential USB Black\nდამატება\n149 ₾\n\nთვეში: 4 ₾ -დან\n\nHyperX Pulsefire Mat RGB Black\nდამატება\n299 ₾\n\nთვეში: 8 ₾ -დან\n\nXiaomi Mesh System AX3000 NE 2 pack White\nდამატება\n79 ₾\n\nთვეში: 2 ₾ -დან\n\nRivacase 7562 Anti-Theft Laptop Backpack 15 Grey/Dark ...\nდამატება\n119 ₾\n\nთვეში: 3 ₾ -დან\n\nHyperX Pulsefire Surge Mouse Black\nდამატება\n29 ₾\n\nHavit Gaming Mouse Pad HV-MP845 Black\nდამატება\n249 ₾\n\nთვეში: 6 ₾ -დან\n\nXiaomi Router BE3600 White\nდამატება\n69 ₾\n\nთვეში: 1 ₾ -დან\n\nRivacase 7532 Anti-Theft Laptop Bag 15 Dark Grey\nდამატება\n469 ₾\n\nთვეში: 13 ₾ -დან\n\nHP OMEN PHOTON Wireless Mouse 6CL96AA Black\nდამატება\n29 ₾\n\nHavit Gaming Mouse Pad HV-MP847 Pink\nდამატება\n69 ₾\n\nთვეში: 1 ₾ -დან\n\nRivacase 7532 Anti-Theft Laptop Bag 15 Grey/Dark Blue ...\nდამატება\n65 ₾\n\nთვეში: 1 ₾ -დან\n\nRazer Gaming Mouse DeathAdder Essential USB White\nდამატება\n29 ₾\n\nHavit Gaming Mouse Pad HV-MP849 Black\nდამატება\n79 ₾\n\nთვეში: 2 ₾ -დან\n\nRivacase 8231 Laptop Bag 15 Black\nდამატება\n239 ₾\n\nთვეში: 6 ₾ -დან\n\nRazer Gaming Mouse Basilisk V3 Black\nდამატება\n49 ₾\n\nთვეში: 1 ₾ -დან\n\nHyperX Pulsefire Mat M Black\nდამატება\n79 ₾\n\nთვეში: 2 ₾ -დან\n\nRivacase 8231 Laptop Bag 15 Star blue\nდამატება\n299 ₾\n\nთვეში: 8 ₾ -დან\n\nRazer Gaming Mouse Naga V2 HyperSpeed WL Black\nდამატება\n59 ₾\n\nთვეში: 1 ₾ -დან\n\nHyperX Pulsefire Mat L Black\nდამატება\n79 ₾\n\nთვეში: 2 ₾ -დან\n\nRivacase 8335 Laptop Bag 15 Black\nდამატება\n229 ₾\n\nთვეში: 6 ₾ -დან\n\nRazer Gaming Mouse Basilisk V3 X HyperSpeed WL Black\nდამატება\n39 ₾\n\nთვეში: 1 ₾ -დან\n\nRazer Mouse Pad Sphex V3 S Black\nდამატება\n79 ₾\n\nთვეში: 2 ₾ -დან\n\nRivacase 8335 Laptop Bag 15 Star blue\nდამატება\n129 ₾\n\nთვეში: 3 ₾ -დან\n\nRazer Gaming Mouse Cobra Black\nდამატება\n89 ₾\n\nთვეში: 2 ₾ -დან\n\nRazer Mouse Pad Sphex V3 L Black\nდამატება\n69 ₾\n\nთვეში: 1 ₾ -დან\n\nRivacase 7730 Eco Laptop Shoulder Bag 15 Black\nდამატება\n19 ₾\n\nHavit Gaming Mouse HV-MS989GT Black/Red\nდამატება\n29 ₾\n\nHavit Gaming mouse Pad HV-MP860\nდამატება\n59 ₾\n\nთვეში: 1 ₾ -დან\n\nRivacase 8035 Laptop Shoulder Bag 15\nდამატება\n19 ₾\n\nHavit Gaming Mouse HV-MS626GT Black\nდამატება\n79 ₾\n\nთვეში: 2 ₾ -დან\n\nTomtoc Defender A13 Laptop Sleeve 15 A13E3D1 Black\nდამატება\n19 ₾\n\nHavit Gaming Mouse HV-MS66GT White/Blue\nდამატება\n119 ₾\n\nთვეში: 3 ₾ -დან\n\nTomtoc Defender A42 Laptop Briefcase 15 A42E1D1 Black\nდამატება\n149 ₾\n\nთვეში: 4 ₾ -დან\n\nHyperX Gaming Mouse Pulsefire Haste 2 Black\nდამატება\n79 ₾\n\nთვეში: 2 ₾ -დან\n\nHP Campus backpack 15.6 7J595AA Green\nდამატება\n19 ₾\n\nHavit Wireless Mouse HV-MS66GT Black\nდამატება\n79 ₾\n\nთვეში: 2 ₾ -დან\n\nHP Campus backpack 15.6 7J597AA Lavender\nდამატება\n179 ₾\n\nთვეში: 4 ₾ -დან\n\nLogitech Gaming Mouse G305 LIGHTSPEED WL L910-005282 ...\nდამატება\n69 ₾\n\nთვეში: 1 ₾ -დან\n\nRivacase 8065 Laptop Backpack 15 Black\nდამატება\n259 ₾\n\nთვეში: 7 ₾ -დან\n\nLogitech Gaming Mouse G502 X L910-006138 Black\nდამატება\n69 ₾\n\nთვეში: 1 ₾ -დან\n\nRivacase 8065 Laptop Backpack 15 Dark Blue\nდამატება\n259 ₾\n\nთვეში: 7 ₾ -დან\n\nLogitech Gaming Mouse G502 X L910-006138 White\nდამატება\n79 ₾\n\nთვეში: 2 ₾ -დან\n\nRivacase 8335 Laptop Bag 15 Purple\nდამატება\n19 ₾\n\nHavit Gaming Mouse HV-MS626GT Black/Red\nდამატება\n19 ₾\n\nHavit Gaming Mouse HV-MS626GT Black/Blue\nდამატება\n349 ₾\n\nთვეში: 9 ₾ -დან\n\nLogitech Gaming Mouse G703 LIGHTSPEED WL L910-005640 ...\nდამატება\n89 ₾\n\nთვეში: 2 ₾ -დან\n\nLogitech Gaming Mouse G102 LIGHTSYNC L910-005823 Blac ...\nდამატება\n89 ₾\n\nთვეში: 2 ₾ -დან\n\nLogitech Gaming Mouse G102 LIGHTSYNC L910-005824 Whit ...\nდამატება\n89 ₾\n\nთვეში: 2 ₾ -დან\n\nLogitech Gaming Mouse G102 LIGHTSYNC L910-005801 Blue\nდამატება\n239 ₾\n\nთვეში: 6 ₾ -დან\n\nLogitech Gaming Mouse G502 HERO L910-005470 Black\nდამატება\n199 ₾\n\nთვეში: 5 ₾ -დან\n\nHyperX Pulsefire Haste 2 core Wireless Black\nდამატება\n199 ₾\n\nთვეში: 5 ₾ -დან\n\nHyperX Pulsefire Haste 2 core Wireless White\nდამატება\n59 ₾\n\nთვეში: 1 ₾ -დან\n\nHavit Gaming Mouse HV-MS954 Black\nდამატება\n39 ₾\n\nთვეში: 1 ₾ -დან\n\nHavit Gaming Mouse HV-MS1033 White\nდამატება\n39 ₾\n\nთვეში: 1 ₾ -დან\n\nHavit Gaming Mouse HV-MS1029 Pink\nდამატება\n59 ₾\n\nთვეში: 1 ₾ -დან\n\nHavit Gaming Mouse HV-MS966 Black/Green\nდამატება\n49 ₾\n\nთვეში: 1 ₾ -დან\n\nHavit Wireless Mouse HV-MS1039W Black/White\nდამატება\n79 ₾\n\nთვეში: 2 ₾ -დან\n\nHavit Wireless Mouse HV-MS970WB Pro Black\nდამატება\n79 ₾\n\nთვეში: 2 ₾ -დან\n\nHavit Wireless Mouse HV-MS970WB Pro Transparent White\nდამატება\n219 ₾\n\nთვეში: 6 ₾ -დან\n\nRazer Gaming Mouse Orochi V2 WL Pink\nდამატება\nპროდუქტის შესახებ\n\nთუ ეძებთ ლეპტოპს, რომელიც მარტივად გაუმკლავდება ყველაზე მოთხოვნად თამაშებს — MSI Thin A15 B7UC 9S7-16RK11-601 Black შექმნილია სწორედ თქვენთვის. ეს მოდელი აერთიანებს მაღალ წარმადობას, გამძლე კონსტრუქ...\n\nმეტის ნახვა\nმსგავსი პროდუქტები\n2599 ₾\n2999 ₾\n\nთვეში: 72 ₾ -დან\n\nMSI Thin A15 B7UC 9S7-16RK11-211, AMD Ryzen 7, Nvidia ...\nდამატება\n5599 ₾\n5999 ₾\n\nთვეში: 155 ₾ -დან\n\nMSI Sword 16 HX B14VGKG 9S7-15P214-262, Intel core i7 ...\nდამატება\n3299 ₾\n3499 ₾\n\nთვეში: 91 ₾ -დან\n\nMSI Thin 15 9S7-16R831-2003 Black\nდამატება\n4499 ₾\n5199 ₾\n\nთვეში: 124 ₾ -დან\n\nMSI Sword 16 HX B14VFKG 9S7-15P214-669, Intel Core i7 ...\nდამატება\n5199 ₾\n5499 ₾\n\nთვეში: 144 ₾ -დან\n\nMSI Crosshair 16 HX D14VFKG 9S7-15P231-670, Intel Cor ...\nდამატება\n2449 ₾\n2549 ₾\n\nთვეში: 68 ₾ -დან\n\nMSI Thin 15 9S7-16R831-2681, Intel Core i5-12450H, Nv ...\nდამატება\n3399 ₾\n3699 ₾\n\nთვეში: 94 ₾ -დან\n\nMSI Katana 15 9S7-158571-2222, Intel Core i5-13420H, ...\nდამატება\n5399 ₾\n5999 ₾\n\nთვეში: 149 ₾ -დან\n\nMSI Crosshair 17 9S7-17T223-270, Intel Core i7-14700H ...\nდამატება\n3999 ₾\n4299 ₾\n\nთვეში: 111 ₾ -დან\n\nMSI Katana 15 9S7-158571-2279, Intel Core i7-13620H, ...\nდამატება\n4499 ₾\n4899 ₾\n\nთვეში: 124 ₾ -დან\n\nMSI Sword 16 9S7-15P214-886, Intel Core i7-14650HX, N ...\nდამატება\n2599 ₾\n2799 ₾\n\nთვეში: 72 ₾ -დან\n\nMSI Thin A15 B7UC 9S7-16RK11-602 Black\nდამატება\n2999 ₾\n3199 ₾\n\nთვეში: 83 ₾ -დან\n\nMSI Thin A15 B7VE 9S7-16RK11-603 Black\nდამატება\n3399 ₾\n\nთვეში: 94 ₾ -დან\n\nMSI Thin A15 B7VE 9S7-16RK11-604 Black\nდამატება\nდამატებითი მახასიათებლები\nბრენდი\nბრენდი:\n\t\nMSI\nმოდელი\nმოდელი:\n\t\nThin\nტექნიკური მახასიათებლები\nცენტრალური პროცესორი:\n\t\nAMD Ryzen 5-7535HS\n\n\nპროცესორის თაობა:\n\t\nRyzen 5 7000 Series\n\n\nპროცესორის სიხშირე:\n\t\n3.3 GHz ~ 4.55 GHz\n\n\nბირთვების რაოდენობა:\n\t\n6\n\n\nნაკადების რაოდენობა:\n\t\n12\n\n\nგრაფიკული პროცესორი:\n\t\nNvidia GeForce RTX 3050\n\n\nგრაფიკული პროცესორის მეხსიერება:\n\t\n4 GB\n\n\nგრაფიკული პროცესორის ტიპი:\n\t\nარა ინტეგრირებული\n\n\nოპერაციული სისტემა:\n\t\nNo\n\n\nBluetooth:\n\t\n5.3\nეკრანი\nეკრანის ზომა:\n\t\n15.6 Inches\n\n\nრეზოლუცია:\n\t\nFull HD\n\n\nეკრანის ტიპი:\n\t\nIPS\n\n\nსენსორული ეკრანი:\n\t\nNo\n\n\nგანახლების სიხშირე:\n\t\n144 Hz\nდამატებითი მახასიათებლები\nკლავიატურის განათება:\n\t\nYes\n\n\nNumpad:\n\t\nNo\n\n\nდისკის წამკითხველი:\n\t\nNo\n\n\nვებ კამერა:\n\t\nYes\n\n\nლეპტოპის ტიპი:\n\t\nგეიმინგი\nმეხსიერება\nშიდა მეხსიერება:\n\t\n512 GB\n\n\nშიდა მეხსიერების ტიპი:\n\t\nSSD\n\n\nშიდა მეხსიერების ინტერფეისი:\n\t\nM.2\n\n\nოპერატიული მეხსიერება:\n\t\n16 GB\n\n\nოპერატიული მეხსიერების ტიპი:\n\t\nDDR5\n\n\nოპერატიული მეხსიერების სიხშირე:\n\t\n-\nპორტები\nUSB:\n\t\n3 x USB-A\n\n\nType-C:\n\t\n1x\n\n\nType-C პორტით დამუხტვა:\n\t\nNo\n\n\nHDMI:\n\t\nYes\n\n\nლან პორტი:\n\t\nYes\n\n\n3.5mm:\n\t\nYes\nზომა/წონა\nწონა:\n\t\n1.86 kg\nფერი\nფერი:\n\t\nBlack\nმეტის ნახვა\nგაეცანი საგარანტიო პირობებს\nსაგარანტიო პირობები\nფილიალები\nმარაგშია\nშეკვეთიდან 2-5 დღეში\nზუმერის წერეთლის ფილიალი\n\nთბილისი - წერეთლის გამზირი, N1.\n\nმარაგშია\n+995 591 967 601\nორშ-შაბ: 10:00:00 - 20:00:00\nკვირა: 10:00:00 - 19:00:00\nზუმერის \"თბილისი ცენტრალის\" ფილიალი\n\nთბილისი - \"თბილისი ცენტრალი\"- lll სართული\n\nმარაგშია\n+995 599 862 449\nორშ-შაბ: 10:00:00 - 20:00:00\nკვირა: 10:00:00 - 19:00:00\nზუმერის City Mall საბურთალო-ს ფილიალი\n\nთბილისი - \"სითი მოლი\" - პეტრე ქავთარაძის N1\n\nმარაგშია\n+995 591 971 962\nორშ-შაბ: 10:00:00 - 22:00:00\nკვირა: 10:00:00 - 22:00:00\nზუმერის თბილისი მოლის ფილიალი\n\nთბილისი - „თბილისი მოლი\" - I სართული. აღმაშენებლის ხეივანი მე-16 კმ\n\nმარაგშია\n+995 591 967 608\nორშ-შაბ: 10:00:00 - 22:00:00\nკვირა: 10:00:00 - 22:00:00\nზუმერის \"გლდანი მოლის\" ფილიალი\n\nთბილისი - \"გლდანი მოლი\" - I სართული, M-ახმეტელის მიმდებარე\n\nმარაგშია\n+995 591 967 673\nორშ-შაბ: 10:00:00 - 21:00:00\nკვირა: 10:00:00 - 21:00:00\nბათუმი ჭავჭავაძის ფილიალი\n\nბათუმი - ბათუმი, ჭავჭავაძის N21\n\nმარაგშია\n+995 591 967 606\nორშ-შაბ: 10:00:00 - 20:00:00\nკვირა: 10:00:00 - 19:00:00\nბათუმის \"Black Sea Mall\"-ის ფილიალი\n\nბათუმი - \"Black Sea Mall\" - ტბელ აბუსერიძის N22\n\nმარაგშია\n+995 591 310 257\nორშ-შაბ: 10:00:00 - 21:00:00\nკვირა: 10:00:00 - 21:00:00\nბათუმის გრანდ მოლის ფილიალი\n\nბათუმი - \"გრანდ მოლი\" - შერიფ ხიმშიაშვილის 29\n\nმარაგშია\n+995 591 022 872\nორშ-შაბ: 10:00:00 - 22:00:00\nკვირა: 10:00:00 - 22:00:00\nგორი მოლის ფილიალი\n\nგორი - გორი, ცხინვალის გზატკეცილი 14-14ამ, გორი მოლი\n\nმარაგშია\n+995 591 198 248\nორშ-შაბ: 10:00:00 - 22:00:00\nკვირა: 10:00:00 - 22:00:00\nმეტის ნახვა\n2599 ₾\n\nთვეში: 72.2 ₾ -დან\n\nმარაგი ფილიალებში\nფასის დაზღვევა\nფასის კონტროლი\nფასის დაჯავშნა\nყიდვა\nშედარება\nდამატება\nნავიგაცია\n\nპერსონალურ მონაცემთა დაცვის პოლიტიკა\n\nჩვენ შესახებ\n\nწესები და პირობები\n\nმიწოდების სერვისი\n\nკარიერა\n\nგადახდები\n\nSetanta Sports\n\nგადახდის მეთოდები\n\nგარანტია\n\nგანვადება\n\nნივთის დაბრუნება\n\nნივთის ონლაინ ყიდვის ინსტრუქცია\n\nგამოგვყევი\n\nFacebook\n\nYoutube\n\nInstagram\n\nTik Tok\n\nკონტაქტი\n\nInfo@zoommer.ge\n\n+995 (32) 2 60 30 60 / *7007\n\nფილიალები\n\nკორპორატიული გაყიდვები\n\nZoommer App\n\nCopyright © 2023 Zoommer.ge. All rights reserved.\n\nCookie პოლიტიკა\n\nსაიტით სარგებლობის გაგრძელებით, შენ ეთანხმები Cookie ჩანაწერების გამოყენებას. მეტი ინფორმაცისათვის იხილეთ კონფიდენციალურობის პოლიტიკა\n\nგასაგებია",
    "specs": {
      "ბრენდი:": "MSI",
      "მოდელი:": "Thin",
      "ცენტრალური პროცესორი:": "AMD Ryzen 5-7535HS",
      "პროცესორის თაობა:": "Ryzen 5 7000 Series",
      "პროცესორის სიხშირე:": "3.3 GHz ~ 4.55 GHz",
      "ბირთვების რაოდენობა:": "6",
      "ნაკადების რაოდენობა:": "12",
      "გრაფიკული პროცესორი:": "Nvidia GeForce RTX 3050",
      "გრაფიკული პროცესორის მეხსიერება:": "4 GB",
      "გრაფიკული პროცესორის ტიპი:": "არა ინტეგრირებული",
      "ოპერაციული სისტემა:": "No",
      "Bluetooth:": "5.3",
      "ეკრანის ზომა:": "15.6 Inches",
      "რეზოლუცია:": "Full HD",
      "ეკრანის ტიპი:": "IPS",
      "სენსორული ეკრანი:": "No",
      "განახლების სიხშირე:": "144 Hz",
      "კლავიატურის განათება:": "Yes",
      "Numpad:": "No",
      "დისკის წამკითხველი:": "No",
      "ვებ კამერა:": "Yes",
      "ლეპტოპის ტიპი:": "გეიმინგი",
      "შიდა მეხსიერება:": "512 GB",
      "შიდა მეხსიერების ტიპი:": "SSD",
      "შიდა მეხსიერების ინტერფეისი:": "M.2",
      "ოპერატიული მეხსიერება:": "16 GB",
      "ოპერატიული მეხსიერების ტიპი:": "DDR5",
      "ოპერატიული მეხსიერების სიხშირე:": "-",
      "USB:": "3 x USB-A",
      "Type-C:": "1x",
      "Type-C პორტით დამუხტვა:": "No",
      "HDMI:": "Yes",
      "ლან პორტი:": "Yes",
      "3.5mm:": "Yes",
      "წონა:": "1.86 kg",
      "ფერი:": "Black"
    }
  },
  {
    "category": "Gaming ლეპტოპები",
    "title": "Lenovo LOQ 15 83JE002DRK Grey",
    "price": 3799.0,
    "link": "https://zoommer.ge/leptopebi/lenovo-loq-15-83je002drk-grey-p48509",
    "image": "/_next/image?url=https%3A%2F%2Fs3.zoommer.ge%2Fsite%2F00131573-1409-443a-aad4-23b86ddac71a_Thumb.jpeg&w=384&q=50",
    "product_title_detail": "Lenovo LOQ 15 83JE002DRK Grey",
    "description": "*7007 / +995 (32) 2 60 30 60\nსავაჭრო პოლიტიკა\nგანვადება\nკარიერა\nTrade In\nფილიალები\nნავიგაცია\nკალათა\nშესვლა\n%\nმთავარი\nლეპტოპები\nLenovo\n#ZOOM-036779\nLenovo LOQ 15 83JE002DRK Grey\nეკრანის ზომა\n15.6 Inches\nრეზოლუცია\nFull HD\nეკრანის ტიპი\nIPS\nგანახლების სიხშირე\n144 Hz\nშიდა მეხსიერება\n512 GB\nBluetooth\n5.2\nType-C\n1x\nოპერატიული მეხსიერება\n24 GB\nერთად იაფია\nდაამატე ნივთი\nLenovo LOQ 15 83JE002DRK Grey\n3799 ₾\nRivacase 7562 Anti-Theft Laptop Backpack 15 Grey/Dark blue\n67.15 ₾\n79 ₾\nRazer Gaming Mouse DeathAdder Essential USB White\n52 ₾\n65 ₾\nHavit Gaming Cooling Pad HV-F2083 Black\n75.65 ₾\n89 ₾\nჯამური ფასი (3)\n3993.8 ₾\n4032 ₾\nყიდვა\nაქსესუარები\nაღწერა\nმსგავსი\nმახასიათებლები\nფილიალები\nაქსესუარები\nაღწერა\nმსგავსი\nმახასიათებლები\nფილიალები\n89 ₾\n\nთვეში: 2 ₾ -დან\n\nHavit Gaming Cooling Pad HV-F2083 Black\nდამატება\n39 ₾\n\nთვეში: 1 ₾ -დან\n\nLenovo Casual Backpack B210 Green\nდამატება\n219 ₾\n\nთვეში: 6 ₾ -დან\n\nRazer Gaming Mouse Orochi V2 WL Black\nდამატება\n69 ₾\n\nთვეში: 1 ₾ -დან\n\nXiaomi Mi Router 4A DVB4230GL White\nდამატება\n129 ₾\n\nთვეში: 3 ₾ -დან\n\nRivacase 7930 Pro 16\nდამატება\n219 ₾\n\nთვეში: 6 ₾ -დან\n\nRazer Gaming Mouse Orochi V2 WL White\nდამატება\n85 ₾\n\nთვეში: 2 ₾ -დან\n\nTP-Link Archer C50 AC1200 White\nდამატება\n59 ₾\n\nთვეში: 1 ₾ -დან\n\nRivacese 8035 Laptop Shoulder Bag 15 Black\nდამატება\n209 ₾\n\nთვეში: 5 ₾ -დან\n\nRazer Gaming Mouse DeathAdder V2 X Hyperspeed WL/BT/U ...\nდამატება\n119 ₾\n\nთვეში: 3 ₾ -დან\n\nTP-Link Archer C6 AC1200 Black\nდამატება\n59 ₾\n\nთვეში: 1 ₾ -დან\n\nRivacase 8037 Laptop Bag 15 Black\nდამატება\n139 ₾\n\nთვეში: 3 ₾ -დან\n\nLogitech Gaming Mouse G402 Hyperion Fury black\nდამატება\n159 ₾\n\nთვეში: 4 ₾ -დან\n\nXiaomi Router AX1500 White\nდამატება\n79 ₾\n\nთვეში: 2 ₾ -დან\n\nRivacase 7562 Anti-Theft Laptop Backpack 15 Black\nდამატება\n29 ₾\n\nHavit Gaming Mouse HV-MS1010 Black\nდამატება\n179 ₾\n\nთვეში: 4 ₾ -დან\n\nXiaomi Mesh System AX3000 NE 1 pack White\nდამატება\n79 ₾\n\nთვეში: 2 ₾ -დან\n\nRivacase 7562 Anti-Theft Laptop Backpack 15 Dark grey\nდამატება\n79 ₾\n\nთვეში: 2 ₾ -დან\n\nRazer Gaming Mouse DeathAdder Essential USB Black\nდამატება\n299 ₾\n\nთვეში: 8 ₾ -დან\n\nXiaomi Mesh System AX3000 NE 2 pack White\nდამატება\n79 ₾\n\nთვეში: 2 ₾ -დან\n\nRivacase 7562 Anti-Theft Laptop Backpack 15 Grey/Dark ...\nდამატება\n119 ₾\n\nთვეში: 3 ₾ -დან\n\nHyperX Pulsefire Surge Mouse Black\nდამატება\n249 ₾\n\nთვეში: 6 ₾ -დან\n\nXiaomi Router BE3600 White\nდამატება\n69 ₾\n\nთვეში: 1 ₾ -დან\n\nRivacase 7532 Anti-Theft Laptop Bag 15 Dark Grey\nდამატება\n469 ₾\n\nთვეში: 13 ₾ -დან\n\nHP OMEN PHOTON Wireless Mouse 6CL96AA Black\nდამატება\n69 ₾\n\nთვეში: 1 ₾ -დან\n\nRivacase 7532 Anti-Theft Laptop Bag 15 Grey/Dark Blue ...\nდამატება\n65 ₾\n\nთვეში: 1 ₾ -დან\n\nRazer Gaming Mouse DeathAdder Essential USB White\nდამატება\n79 ₾\n\nთვეში: 2 ₾ -დან\n\nRivacase 8231 Laptop Bag 15 Black\nდამატება\n239 ₾\n\nთვეში: 6 ₾ -დან\n\nRazer Gaming Mouse Basilisk V3 Black\nდამატება\n79 ₾\n\nთვეში: 2 ₾ -დან\n\nRivacase 8231 Laptop Bag 15 Star blue\nდამატება\n299 ₾\n\nთვეში: 8 ₾ -დან\n\nRazer Gaming Mouse Naga V2 HyperSpeed WL Black\nდამატება\n79 ₾\n\nთვეში: 2 ₾ -დან\n\nRivacase 8335 Laptop Bag 15 Black\nდამატება\n229 ₾\n\nთვეში: 6 ₾ -დან\n\nRazer Gaming Mouse Basilisk V3 X HyperSpeed WL Black\nდამატება\n79 ₾\n\nთვეში: 2 ₾ -დან\n\nRivacase 8335 Laptop Bag 15 Star blue\nდამატება\n129 ₾\n\nთვეში: 3 ₾ -დან\n\nRazer Gaming Mouse Cobra Black\nდამატება\n69 ₾\n\nთვეში: 1 ₾ -დან\n\nRivacase 7730 Eco Laptop Shoulder Bag 15 Black\nდამატება\n19 ₾\n\nHavit Gaming Mouse HV-MS989GT Black/Red\nდამატება\n59 ₾\n\nთვეში: 1 ₾ -დან\n\nRivacase 8035 Laptop Shoulder Bag 15\nდამატება\n19 ₾\n\nHavit Gaming Mouse HV-MS626GT Black\nდამატება\n79 ₾\n\nთვეში: 2 ₾ -დან\n\nTomtoc Defender A13 Laptop Sleeve 15 A13E3D1 Black\nდამატება\n19 ₾\n\nHavit Gaming Mouse HV-MS66GT White/Blue\nდამატება\n119 ₾\n\nთვეში: 3 ₾ -დან\n\nTomtoc Defender A42 Laptop Briefcase 15 A42E1D1 Black\nდამატება\n149 ₾\n\nთვეში: 4 ₾ -დან\n\nHyperX Gaming Mouse Pulsefire Haste 2 Black\nდამატება\n119 ₾\n\nთვეში: 3 ₾ -დან\n\nTomtoc Defender A42 Laptop Briefcase 15 A42E1B1 Navy ...\nდამატება\n19 ₾\n\nHavit Wireless Mouse HV-MS66GT Black\nდამატება\n79 ₾\n\nთვეში: 2 ₾ -დან\n\nHP Campus backpack 15.6 7J595AA Green\nდამატება\n179 ₾\n\nთვეში: 4 ₾ -დან\n\nLogitech Gaming Mouse G305 LIGHTSPEED WL L910-005282 ...\nდამატება\n79 ₾\n\nთვეში: 2 ₾ -დან\n\nHP Campus backpack 15.6 7J597AA Lavender\nდამატება\n259 ₾\n\nთვეში: 7 ₾ -დან\n\nLogitech Gaming Mouse G502 X L910-006138 Black\nდამატება\n69 ₾\n\nთვეში: 1 ₾ -დან\n\nRivacase 8065 Laptop Backpack 15 Black\nდამატება\n259 ₾\n\nთვეში: 7 ₾ -დან\n\nLogitech Gaming Mouse G502 X L910-006138 White\nდამატება\n69 ₾\n\nთვეში: 1 ₾ -დან\n\nRivacase 8065 Laptop Backpack 15 Dark Blue\nდამატება\n19 ₾\n\nHavit Gaming Mouse HV-MS626GT Black/Red\nდამატება\n79 ₾\n\nთვეში: 2 ₾ -დან\n\nTomtoc Defender A13 Laptop Sleeve 15 A13E3P1 Pink\nდამატება\n19 ₾\n\nHavit Gaming Mouse HV-MS626GT Black/Blue\nდამატება\n79 ₾\n\nთვეში: 2 ₾ -დან\n\nTomtoc Defender A13 Laptop Sleeve 15 A13E3T1 Green\nდამატება\n349 ₾\n\nთვეში: 9 ₾ -დან\n\nLogitech Gaming Mouse G703 LIGHTSPEED WL L910-005640 ...\nდამატება\n79 ₾\n\nთვეში: 2 ₾ -დან\n\nTomtoc Defender A13 Laptop Sleeve Kit 15 A13E3GV Grey\nდამატება\n89 ₾\n\nთვეში: 2 ₾ -დან\n\nLogitech Gaming Mouse G102 LIGHTSYNC L910-005823 Blac ...\nდამატება\n79 ₾\n\nთვეში: 2 ₾ -დან\n\nRivacase 8335 Laptop Bag 15 Purple\nდამატება\n89 ₾\n\nთვეში: 2 ₾ -დან\n\nLogitech Gaming Mouse G102 LIGHTSYNC L910-005824 Whit ...\nდამატება\n89 ₾\n\nთვეში: 2 ₾ -დან\n\nLogitech Gaming Mouse G102 LIGHTSYNC L910-005801 Blue\nდამატება\n239 ₾\n\nთვეში: 6 ₾ -დან\n\nLogitech Gaming Mouse G502 HERO L910-005470 Black\nდამატება\n199 ₾\n\nთვეში: 5 ₾ -დან\n\nHyperX Pulsefire Haste 2 core Wireless Black\nდამატება\n199 ₾\n\nთვეში: 5 ₾ -დან\n\nHyperX Pulsefire Haste 2 core Wireless White\nდამატება\n59 ₾\n\nთვეში: 1 ₾ -დან\n\nHavit Gaming Mouse HV-MS954 Black\nდამატება\n39 ₾\n\nთვეში: 1 ₾ -დან\n\nHavit Gaming Mouse HV-MS1033 White\nდამატება\n39 ₾\n\nთვეში: 1 ₾ -დან\n\nHavit Gaming Mouse HV-MS1029 Pink\nდამატება\n59 ₾\n\nთვეში: 1 ₾ -დან\n\nHavit Gaming Mouse HV-MS966 Black/Green\nდამატება\n49 ₾\n\nთვეში: 1 ₾ -დან\n\nHavit Wireless Mouse HV-MS1039W Black/White\nდამატება\n79 ₾\n\nთვეში: 2 ₾ -დან\n\nHavit Wireless Mouse HV-MS970WB Pro Black\nდამატება\n79 ₾\n\nთვეში: 2 ₾ -დან\n\nHavit Wireless Mouse HV-MS970WB Pro Transparent White\nდამატება\n219 ₾\n\nთვეში: 6 ₾ -დან\n\nRazer Gaming Mouse Orochi V2 WL Pink\nდამატება\nპროდუქტის შესახებ\n\nთუ ეძებთ ლეპტოპს, რომელიც მარტივად გაუმკლავდება ყველაზე მოთხოვნად თამაშებს — Lenovo LOQ 15 83JE002DRK Grey შექმნილია სწორედ თქვენთვის. ეს მოდელი აერთიანებს მაღალ წარმადობას, გამძლე კონსტრუქციასა და ...\n\nმეტის ნახვა\nმსგავსი პროდუქტები\n2999 ₾\n3199 ₾\n\nთვეში: 83 ₾ -დან\n\nLenovo LOQ 15 83DV00MPRK Luna Grey\nდამატება\n7999 ₾\n8799 ₾\n\nთვეში: 222 ₾ -დან\n\nLenovo Legion Pro 7 83F50026RK, Intel Core Ultra 9 27 ...\nდამატება\n4299 ₾\n\nთვეში: 119 ₾ -დან\n\nLenovo Legion 5 83LY008MRK Black\nდამატება\n5999 ₾\n6199 ₾\n\nთვეში: 166 ₾ -დან\n\nLenovo Legion 5 Pro 83F3000XRK Black\nდამატება\n6999 ₾\n\nთვეში: 194 ₾ -დან\n\nLenovo Legion 5 Pro 83F30012RK Black\nდამატება\nდამატებითი მახასიათებლები\nბრენდი\nბრენდი:\n\t\nLenovo\nმოდელი\nმოდელი:\n\t\nLOQ\nტექნიკური მახასიათებლები\nცენტრალური პროცესორი:\n\t\nIntel Core i7-13650HX\n\n\nპროცესორის თაობა:\n\t\nIntel i7 13th Gen\n\n\nპროცესორის სიხშირე:\n\t\n3.6 GHz ~ 4.9 GHz\n\n\nბირთვების რაოდენობა:\n\t\n14\n\n\nნაკადების რაოდენობა:\n\t\n20\n\n\nგრაფიკული პროცესორი:\n\t\nNvidia GeForce RTX 5060\n\n\nგრაფიკული პროცესორის მეხსიერება:\n\t\n8 GB\n\n\nგრაფიკული პროცესორის ტიპი:\n\t\nარა ინტეგრირებული\n\n\nოპერაციული სისტემა:\n\t\nNo\n\n\nBluetooth:\n\t\n5.2\nეკრანი\nეკრანის ზომა:\n\t\n15.6 Inches\n\n\nრეზოლუცია:\n\t\nFull HD\n\n\nეკრანის ტიპი:\n\t\nIPS\n\n\nსენსორული ეკრანი:\n\t\nNo\n\n\nგანახლების სიხშირე:\n\t\n144 Hz\nდამატებითი მახასიათებლები\nკლავიატურის განათება:\n\t\nYes\n\n\nNumpad:\n\t\nYes\n\n\nდისკის წამკითხველი:\n\t\nNo\n\n\nვებ კამერა:\n\t\nYes\n\n\nლეპტოპის ტიპი:\n\t\nგეიმინგი\nმეხსიერება\nშიდა მეხსიერება:\n\t\n512 GB\n\n\nშიდა მეხსიერების ტიპი:\n\t\nSSD\n\n\nშიდა მეხსიერების ინტერფეისი:\n\t\nM.2\n\n\nოპერატიული მეხსიერება:\n\t\n24 GB\n\n\nოპერატიული მეხსიერების ტიპი:\n\t\nDDR5\n\n\nოპერატიული მეხსიერების სიხშირე:\n\t\n4800 MHz\nპორტები\nUSB:\n\t\n3 x USB-A\n\n\nType-C:\n\t\n1x\n\n\nType-C პორტით დამუხტვა:\n\t\nNo\n\n\nHDMI:\n\t\nYes\n\n\nლან პორტი:\n\t\nYes\n\n\n3.5mm:\n\t\nYes\nზომა/წონა\nწონა:\n\t\n2.4 kg\nმეტის ნახვა\nგაეცანი საგარანტიო პირობებს\nსაგარანტიო პირობები\nფილიალები\nმარაგშია\nშეკვეთიდან 2-5 დღეში\nბათუმი ჭავჭავაძის ფილიალი\n\nბათუმი - ბათუმი, ჭავჭავაძის N21\n\nმარაგშია\n+995 591 967 606\nორშ-შაბ: 10:00:00 - 20:00:00\nკვირა: 10:00:00 - 19:00:00\n3799 ₾\n\nთვეში: 105.5 ₾ -დან\n\nმარაგი ფილიალებში\nფასის დაზღვევა\nფასის კონტროლი\nფასის დაჯავშნა\nყიდვა\nშედარება\nდამატება\nნავიგაცია\n\nპერსონალურ მონაცემთა დაცვის პოლიტიკა\n\nჩვენ შესახებ\n\nწესები და პირობები\n\nმიწოდების სერვისი\n\nკარიერა\n\nგადახდები\n\nSetanta Sports\n\nგადახდის მეთოდები\n\nგარანტია\n\nგანვადება\n\nნივთის დაბრუნება\n\nნივთის ონლაინ ყიდვის ინსტრუქცია\n\nგამოგვყევი\n\nFacebook\n\nYoutube\n\nInstagram\n\nTik Tok\n\nკონტაქტი\n\nInfo@zoommer.ge\n\n+995 (32) 2 60 30 60 / *7007\n\nფილიალები\n\nკორპორატიული გაყიდვები\n\nZoommer App\n\nCopyright © 2023 Zoommer.ge. All rights reserved.\n\nCookie პოლიტიკა\n\nსაიტით სარგებლობის გაგრძელებით, შენ ეთანხმები Cookie ჩანაწერების გამოყენებას. მეტი ინფორმაცისათვის იხილეთ კონფიდენციალურობის პოლიტიკა\n\nგასაგებია",
    "specs": {
      "ბრენდი:": "Lenovo",
      "მოდელი:": "LOQ",
      "ცენტრალური პროცესორი:": "Intel Core i7-13650HX",
      "პროცესორის თაობა:": "Intel i7 13th Gen",
      "პროცესორის სიხშირე:": "3.6 GHz ~ 4.9 GHz",
      "ბირთვების რაოდენობა:": "14",
      "ნაკადების რაოდენობა:": "20",
      "გრაფიკული პროცესორი:": "Nvidia GeForce RTX 5060",
      "გრაფიკული პროცესორის მეხსიერება:": "8 GB",
      "გრაფიკული პროცესორის ტიპი:": "არა ინტეგრირებული",
      "ოპერაციული სისტემა:": "No",
      "Bluetooth:": "5.2",
      "ეკრანის ზომა:": "15.6 Inches",
      "რეზოლუცია:": "Full HD",
      "ეკრანის ტიპი:": "IPS",
      "სენსორული ეკრანი:": "No",
      "განახლების სიხშირე:": "144 Hz",
      "კლავიატურის განათება:": "Yes",
      "Numpad:": "Yes",
      "დისკის წამკითხველი:": "No",
      "ვებ კამერა:": "Yes",
      "ლეპტოპის ტიპი:": "გეიმინგი",
      "შიდა მეხსიერება:": "512 GB",
      "შიდა მეხსიერების ტიპი:": "SSD",
      "შიდა მეხსიერების ინტერფეისი:": "M.2",
      "ოპერატიული მეხსიერება:": "24 GB",
      "ოპერატიული მეხსიერების ტიპი:": "DDR5",
      "ოპერატიული მეხსიერების სიხშირე:": "4800 MHz",
      "USB:": "3 x USB-A",
      "Type-C:": "1x",
      "Type-C პორტით დამუხტვა:": "No",
      "HDMI:": "Yes",
      "ლან პორტი:": "Yes",
      "3.5mm:": "Yes",
      "წონა:": "2.4 kg"
    }
  },
  {
    "category": "Gaming ლეპტოპები",
    "title": "Lenovo Legion 5 83LY008MRK Black",
    "price": 4299.0,
    "link": "https://zoommer.ge/leptopebi/lenovo-legion-5-83ly008mrk-black-p48508",
    "image": "/_next/image?url=https%3A%2F%2Fs3.zoommer.ge%2Fsite%2F32493cf2-467a-4c6c-935d-9ab4f043b840_Thumb.jpeg&w=384&q=50",
    "product_title_detail": "Lenovo Legion 5 83LY008MRK Black",
    "description": "*7007 / +995 (32) 2 60 30 60\nსავაჭრო პოლიტიკა\nგანვადება\nკარიერა\nTrade In\nფილიალები\nნავიგაცია\nკალათა\nშესვლა\n%\nმთავარი\nლეპტოპები\nLenovo\n#ZOOM-036778\nLenovo Legion 5 83LY008MRK Black\nეკრანის ზომა\n15.3 Inches\nრეზოლუცია\nWQXGA\nეკრანის ტიპი\nIPS\nგანახლების სიხშირე\n165 Hz\nშიდა მეხსიერება\n1 TB\nBluetooth\n5.2\nType-C\n2x\nოპერატიული მეხსიერება\n24 GB\nერთად იაფია\nდაამატე ნივთი\nLenovo Legion 5 83LY008MRK Black\n4299 ₾\nRivacase 7562 Anti-Theft Laptop Backpack 15 Grey/Dark blue\n67.15 ₾\n79 ₾\nRazer Gaming Mouse DeathAdder Essential USB White\n52 ₾\n65 ₾\nHavit Gaming Cooling Pad HV-F2083 Black\n75.65 ₾\n89 ₾\nჯამური ფასი (3)\n4493.8 ₾\n4532 ₾\nყიდვა\nაქსესუარები\nაღწერა\nმსგავსი\nმახასიათებლები\nფილიალები\nაქსესუარები\nაღწერა\nმსგავსი\nმახასიათებლები\nფილიალები\n89 ₾\n\nთვეში: 2 ₾ -დან\n\nHavit Gaming Cooling Pad HV-F2083 Black\nდამატება\n39 ₾\n\nთვეში: 1 ₾ -დან\n\nLenovo Casual Backpack B210 Green\nდამატება\n219 ₾\n\nთვეში: 6 ₾ -დან\n\nRazer Gaming Mouse Orochi V2 WL Black\nდამატება\n59 ₾\n\nთვეში: 1 ₾ -დან\n\nHavit Gaming mouse Pad HV-MP901\nდამატება\n69 ₾\n\nთვეში: 1 ₾ -დან\n\nXiaomi Mi Router 4A DVB4230GL White\nდამატება\n129 ₾\n\nთვეში: 3 ₾ -დან\n\nRivacase 7930 Pro 16\nდამატება\n219 ₾\n\nთვეში: 6 ₾ -დან\n\nRazer Gaming Mouse Orochi V2 WL White\nდამატება\n9 ₾\n\nHavit Gaming mouse Pad HV-MP838\nდამატება\n85 ₾\n\nთვეში: 2 ₾ -დან\n\nTP-Link Archer C50 AC1200 White\nდამატება\n59 ₾\n\nთვეში: 1 ₾ -დან\n\nRivacese 8035 Laptop Shoulder Bag 15 Black\nდამატება\n209 ₾\n\nთვეში: 5 ₾ -დან\n\nRazer Gaming Mouse DeathAdder V2 X Hyperspeed WL/BT/U ...\nდამატება\n9 ₾\n\nHavit Gaming mouse Pad HV-MP843 Black\nდამატება\n119 ₾\n\nთვეში: 3 ₾ -დან\n\nTP-Link Archer C6 AC1200 Black\nდამატება\n59 ₾\n\nთვეში: 1 ₾ -დან\n\nRivacase 8037 Laptop Bag 15 Black\nდამატება\n139 ₾\n\nთვეში: 3 ₾ -დან\n\nLogitech Gaming Mouse G402 Hyperion Fury black\nდამატება\n149 ₾\n\nთვეში: 4 ₾ -დან\n\nRazer Mouse Pad Firefly V2 RGB M Black\nდამატება\n159 ₾\n\nთვეში: 4 ₾ -დან\n\nXiaomi Router AX1500 White\nდამატება\n79 ₾\n\nთვეში: 2 ₾ -დან\n\nRivacase 7562 Anti-Theft Laptop Backpack 15 Black\nდამატება\n29 ₾\n\nHavit Gaming Mouse HV-MS1010 Black\nდამატება\n199 ₾\n\nთვეში: 5 ₾ -დან\n\nRazer Mouse Pad Goliathus Extended Chroma XXL Black\nდამატება\n179 ₾\n\nთვეში: 4 ₾ -დან\n\nXiaomi Mesh System AX3000 NE 1 pack White\nდამატება\n79 ₾\n\nთვეში: 2 ₾ -დან\n\nRivacase 7562 Anti-Theft Laptop Backpack 15 Dark grey\nდამატება\n79 ₾\n\nთვეში: 2 ₾ -დან\n\nRazer Gaming Mouse DeathAdder Essential USB Black\nდამატება\n149 ₾\n\nთვეში: 4 ₾ -დან\n\nHyperX Pulsefire Mat RGB Black\nდამატება\n299 ₾\n\nთვეში: 8 ₾ -დან\n\nXiaomi Mesh System AX3000 NE 2 pack White\nდამატება\n79 ₾\n\nთვეში: 2 ₾ -დან\n\nRivacase 7562 Anti-Theft Laptop Backpack 15 Grey/Dark ...\nდამატება\n119 ₾\n\nთვეში: 3 ₾ -დან\n\nHyperX Pulsefire Surge Mouse Black\nდამატება\n29 ₾\n\nHavit Gaming Mouse Pad HV-MP845 Black\nდამატება\n249 ₾\n\nთვეში: 6 ₾ -დან\n\nXiaomi Router BE3600 White\nდამატება\n69 ₾\n\nთვეში: 1 ₾ -დან\n\nRivacase 7532 Anti-Theft Laptop Bag 15 Dark Grey\nდამატება\n469 ₾\n\nთვეში: 13 ₾ -დან\n\nHP OMEN PHOTON Wireless Mouse 6CL96AA Black\nდამატება\n29 ₾\n\nHavit Gaming Mouse Pad HV-MP847 Pink\nდამატება\n69 ₾\n\nთვეში: 1 ₾ -დან\n\nRivacase 7532 Anti-Theft Laptop Bag 15 Grey/Dark Blue ...\nდამატება\n65 ₾\n\nთვეში: 1 ₾ -დან\n\nRazer Gaming Mouse DeathAdder Essential USB White\nდამატება\n29 ₾\n\nHavit Gaming Mouse Pad HV-MP849 Black\nდამატება\n79 ₾\n\nთვეში: 2 ₾ -დან\n\nRivacase 8231 Laptop Bag 15 Black\nდამატება\n239 ₾\n\nთვეში: 6 ₾ -დან\n\nRazer Gaming Mouse Basilisk V3 Black\nდამატება\n49 ₾\n\nთვეში: 1 ₾ -დან\n\nHyperX Pulsefire Mat M Black\nდამატება\n79 ₾\n\nთვეში: 2 ₾ -დან\n\nRivacase 8231 Laptop Bag 15 Star blue\nდამატება\n299 ₾\n\nთვეში: 8 ₾ -დან\n\nRazer Gaming Mouse Naga V2 HyperSpeed WL Black\nდამატება\n59 ₾\n\nთვეში: 1 ₾ -დან\n\nHyperX Pulsefire Mat L Black\nდამატება\n79 ₾\n\nთვეში: 2 ₾ -დან\n\nRivacase 8335 Laptop Bag 15 Black\nდამატება\n229 ₾\n\nთვეში: 6 ₾ -დან\n\nRazer Gaming Mouse Basilisk V3 X HyperSpeed WL Black\nდამატება\n39 ₾\n\nთვეში: 1 ₾ -დან\n\nRazer Mouse Pad Sphex V3 S Black\nდამატება\n79 ₾\n\nთვეში: 2 ₾ -დან\n\nRivacase 8335 Laptop Bag 15 Star blue\nდამატება\n129 ₾\n\nთვეში: 3 ₾ -დან\n\nRazer Gaming Mouse Cobra Black\nდამატება\n89 ₾\n\nთვეში: 2 ₾ -დან\n\nRazer Mouse Pad Sphex V3 L Black\nდამატება\n69 ₾\n\nთვეში: 1 ₾ -დან\n\nRivacase 7730 Eco Laptop Shoulder Bag 15 Black\nდამატება\n19 ₾\n\nHavit Gaming Mouse HV-MS989GT Black/Red\nდამატება\n29 ₾\n\nHavit Gaming mouse Pad HV-MP860\nდამატება\n59 ₾\n\nთვეში: 1 ₾ -დან\n\nRivacase 8035 Laptop Shoulder Bag 15\nდამატება\n19 ₾\n\nHavit Gaming Mouse HV-MS626GT Black\nდამატება\n79 ₾\n\nთვეში: 2 ₾ -დან\n\nTomtoc Defender A13 Laptop Sleeve 15 A13E3D1 Black\nდამატება\n19 ₾\n\nHavit Gaming Mouse HV-MS66GT White/Blue\nდამატება\n119 ₾\n\nთვეში: 3 ₾ -დან\n\nTomtoc Defender A42 Laptop Briefcase 15 A42E1D1 Black\nდამატება\n149 ₾\n\nთვეში: 4 ₾ -დან\n\nHyperX Gaming Mouse Pulsefire Haste 2 Black\nდამატება\n119 ₾\n\nთვეში: 3 ₾ -დან\n\nTomtoc Defender A42 Laptop Briefcase 15 A42E1B1 Navy ...\nდამატება\n19 ₾\n\nHavit Wireless Mouse HV-MS66GT Black\nდამატება\n79 ₾\n\nთვეში: 2 ₾ -დან\n\nHP Campus backpack 15.6 7J595AA Green\nდამატება\n179 ₾\n\nთვეში: 4 ₾ -დან\n\nLogitech Gaming Mouse G305 LIGHTSPEED WL L910-005282 ...\nდამატება\n79 ₾\n\nთვეში: 2 ₾ -დან\n\nHP Campus backpack 15.6 7J597AA Lavender\nდამატება\n259 ₾\n\nთვეში: 7 ₾ -დან\n\nLogitech Gaming Mouse G502 X L910-006138 Black\nდამატება\n69 ₾\n\nთვეში: 1 ₾ -დან\n\nRivacase 8065 Laptop Backpack 15 Black\nდამატება\n259 ₾\n\nთვეში: 7 ₾ -დან\n\nLogitech Gaming Mouse G502 X L910-006138 White\nდამატება\n69 ₾\n\nთვეში: 1 ₾ -დან\n\nRivacase 8065 Laptop Backpack 15 Dark Blue\nდამატება\n19 ₾\n\nHavit Gaming Mouse HV-MS626GT Black/Red\nდამატება\n79 ₾\n\nთვეში: 2 ₾ -დან\n\nTomtoc Defender A13 Laptop Sleeve 15 A13E3P1 Pink\nდამატება\n19 ₾\n\nHavit Gaming Mouse HV-MS626GT Black/Blue\nდამატება\n79 ₾\n\nთვეში: 2 ₾ -დან\n\nTomtoc Defender A13 Laptop Sleeve 15 A13E3T1 Green\nდამატება\n349 ₾\n\nთვეში: 9 ₾ -დან\n\nLogitech Gaming Mouse G703 LIGHTSPEED WL L910-005640 ...\nდამატება\n79 ₾\n\nთვეში: 2 ₾ -დან\n\nTomtoc Defender A13 Laptop Sleeve Kit 15 A13E3GV Grey\nდამატება\n89 ₾\n\nთვეში: 2 ₾ -დან\n\nLogitech Gaming Mouse G102 LIGHTSYNC L910-005823 Blac ...\nდამატება\n79 ₾\n\nთვეში: 2 ₾ -დან\n\nRivacase 8335 Laptop Bag 15 Purple\nდამატება\n89 ₾\n\nთვეში: 2 ₾ -დან\n\nLogitech Gaming Mouse G102 LIGHTSYNC L910-005824 Whit ...\nდამატება\n89 ₾\n\nთვეში: 2 ₾ -დან\n\nLogitech Gaming Mouse G102 LIGHTSYNC L910-005801 Blue\nდამატება\n239 ₾\n\nთვეში: 6 ₾ -დან\n\nLogitech Gaming Mouse G502 HERO L910-005470 Black\nდამატება\n199 ₾\n\nთვეში: 5 ₾ -დან\n\nHyperX Pulsefire Haste 2 core Wireless Black\nდამატება\n199 ₾\n\nთვეში: 5 ₾ -დან\n\nHyperX Pulsefire Haste 2 core Wireless White\nდამატება\n59 ₾\n\nთვეში: 1 ₾ -დან\n\nHavit Gaming Mouse HV-MS954 Black\nდამატება\n39 ₾\n\nთვეში: 1 ₾ -დან\n\nHavit Gaming Mouse HV-MS1033 White\nდამატება\n39 ₾\n\nთვეში: 1 ₾ -დან\n\nHavit Gaming Mouse HV-MS1029 Pink\nდამატება\n59 ₾\n\nთვეში: 1 ₾ -დან\n\nHavit Gaming Mouse HV-MS966 Black/Green\nდამატება\n49 ₾\n\nთვეში: 1 ₾ -დან\n\nHavit Wireless Mouse HV-MS1039W Black/White\nდამატება\n79 ₾\n\nთვეში: 2 ₾ -დან\n\nHavit Wireless Mouse HV-MS970WB Pro Black\nდამატება\n79 ₾\n\nთვეში: 2 ₾ -დან\n\nHavit Wireless Mouse HV-MS970WB Pro Transparent White\nდამატება\n219 ₾\n\nთვეში: 6 ₾ -დან\n\nRazer Gaming Mouse Orochi V2 WL Pink\nდამატება\nპროდუქტის შესახებ\n\nთუ ეძებთ ლეპტოპს, რომელიც მარტივად გაუმკლავდება ყველაზე მოთხოვნად თამაშებს — Lenovo Legion 5 83LY008MRK Black შექმნილია სწორედ თქვენთვის. ეს მოდელი აერთიანებს მაღალ წარმადობას, გამძლე კონსტრუქციასა ...\n\nმეტის ნახვა\nმსგავსი პროდუქტები\n2999 ₾\n3199 ₾\n\nთვეში: 83 ₾ -დან\n\nLenovo LOQ 15 83DV00MPRK Luna Grey\nდამატება\n7999 ₾\n8799 ₾\n\nთვეში: 222 ₾ -დან\n\nLenovo Legion Pro 7 83F50026RK, Intel Core Ultra 9 27 ...\nდამატება\n3799 ₾\n\nთვეში: 105 ₾ -დან\n\nLenovo LOQ 15 83JE002DRK Grey\nდამატება\n5999 ₾\n6199 ₾\n\nთვეში: 166 ₾ -დან\n\nLenovo Legion 5 Pro 83F3000XRK Black\nდამატება\n6999 ₾\n\nთვეში: 194 ₾ -დან\n\nLenovo Legion 5 Pro 83F30012RK Black\nდამატება\nდამატებითი მახასიათებლები\nბრენდი\nბრენდი:\n\t\nLenovo\nმოდელი\nმოდელი:\n\t\nLegion\nტექნიკური მახასიათებლები\nცენტრალური პროცესორი:\n\t\nIntel Core i7-13650HX\n\n\nპროცესორის თაობა:\n\t\nIntel i7 13th Gen\n\n\nპროცესორის სიხშირე:\n\t\n3.6 GHz ~ 4.9 GHz\n\n\nბირთვების რაოდენობა:\n\t\n14\n\n\nნაკადების რაოდენობა:\n\t\n20\n\n\nგრაფიკული პროცესორი:\n\t\nNvidia GeForce RTX 5060\n\n\nგრაფიკული პროცესორის მეხსიერება:\n\t\n8 GB\n\n\nგრაფიკული პროცესორის ტიპი:\n\t\nარა ინტეგრირებული\n\n\nოპერაციული სისტემა:\n\t\n-\n\n\nBluetooth:\n\t\n5.2\nეკრანი\nეკრანის ზომა:\n\t\n15.3 Inches\n\n\nრეზოლუცია:\n\t\nWQXGA\n\n\nეკრანის ტიპი:\n\t\nIPS\n\n\nსენსორული ეკრანი:\n\t\nNo\n\n\nგანახლების სიხშირე:\n\t\n165 Hz\nდამატებითი მახასიათებლები\nკლავიატურის განათება:\n\t\nYes\n\n\nNumpad:\n\t\nYes\n\n\nდისკის წამკითხველი:\n\t\nNo\n\n\nვებ კამერა:\n\t\nYes\n\n\nლეპტოპის ტიპი:\n\t\nგეიმინგი\nმეხსიერება\nშიდა მეხსიერება:\n\t\n1 TB\n\n\nშიდა მეხსიერების ტიპი:\n\t\nSSD\n\n\nშიდა მეხსიერების ინტერფეისი:\n\t\nM.2\n\n\nოპერატიული მეხსიერება:\n\t\n24 GB\n\n\nოპერატიული მეხსიერების ტიპი:\n\t\nDDR5\n\n\nოპერატიული მეხსიერების სიხშირე:\n\t\n4800 MHz\nპორტები\nUSB:\n\t\n3 x USB-A\n\n\nType-C:\n\t\n2x\n\n\nType-C პორტით დამუხტვა:\n\t\nNo\n\n\nHDMI:\n\t\nYes\n\n\nლან პორტი:\n\t\nYes\n\n\n3.5mm:\n\t\nYes\nზომა/წონა\nწონა:\n\t\n2.1 kg\nფერი\nფერი:\n\t\nBlack\nმეტის ნახვა\nგაეცანი საგარანტიო პირობებს\nსაგარანტიო პირობები\nფილიალები\nმარაგშია\nშეკვეთიდან 2-5 დღეში\nზუმერის \"თბილისი ცენტრალის\" ფილიალი\n\nთბილისი - \"თბილისი ცენტრალი\"- lll სართული\n\nმარაგშია\n+995 599 862 449\nორშ-შაბ: 10:00:00 - 20:00:00\nკვირა: 10:00:00 - 19:00:00\nზუმერის City Mall საბურთალო-ს ფილიალი\n\nთბილისი - \"სითი მოლი\" - პეტრე ქავთარაძის N1\n\nმარაგშია\n+995 591 971 962\nორშ-შაბ: 10:00:00 - 22:00:00\nკვირა: 10:00:00 - 22:00:00\nზუმერის ისთ ფოინთის ფილიალი\n\nთბილისი - \"ისთ ფოინთი\" - ალ. თვალჭრელიძე N2\n\nმარაგშია\n+995 591 340 476\nორშ-შაბ: 10:00:00 - 22:00:00\nკვირა: 10:00:00 - 22:00:00\nბათუმის გრანდ მოლის ფილიალი\n\nბათუმი - \"გრანდ მოლი\" - შერიფ ხიმშიაშვილის 29\n\nმარაგშია\n+995 591 022 872\nორშ-შაბ: 10:00:00 - 22:00:00\nკვირა: 10:00:00 - 22:00:00\n4299 ₾\n\nთვეში: 119.4 ₾ -დან\n\nმარაგი ფილიალებში\nფასის დაზღვევა\nფასის კონტროლი\nფასის დაჯავშნა\nყიდვა\nშედარება\nდამატება\nნავიგაცია\n\nპერსონალურ მონაცემთა დაცვის პოლიტიკა\n\nჩვენ შესახებ\n\nწესები და პირობები\n\nმიწოდების სერვისი\n\nკარიერა\n\nგადახდები\n\nSetanta Sports\n\nგადახდის მეთოდები\n\nგარანტია\n\nგანვადება\n\nნივთის დაბრუნება\n\nნივთის ონლაინ ყიდვის ინსტრუქცია\n\nგამოგვყევი\n\nFacebook\n\nYoutube\n\nInstagram\n\nTik Tok\n\nკონტაქტი\n\nInfo@zoommer.ge\n\n+995 (32) 2 60 30 60 / *7007\n\nფილიალები\n\nკორპორატიული გაყიდვები\n\nZoommer App\n\nCopyright © 2023 Zoommer.ge. All rights reserved.\n\nCookie პოლიტიკა\n\nსაიტით სარგებლობის გაგრძელებით, შენ ეთანხმები Cookie ჩანაწერების გამოყენებას. მეტი ინფორმაცისათვის იხილეთ კონფიდენციალურობის პოლიტიკა\n\nგასაგებია",
    "specs": {
      "ბრენდი:": "Lenovo",
      "მოდელი:": "Legion",
      "ცენტრალური პროცესორი:": "Intel Core i7-13650HX",
      "პროცესორის თაობა:": "Intel i7 13th Gen",
      "პროცესორის სიხშირე:": "3.6 GHz ~ 4.9 GHz",
      "ბირთვების რაოდენობა:": "14",
      "ნაკადების რაოდენობა:": "20",
      "გრაფიკული პროცესორი:": "Nvidia GeForce RTX 5060",
      "გრაფიკული პროცესორის მეხსიერება:": "8 GB",
      "გრაფიკული პროცესორის ტიპი:": "არა ინტეგრირებული",
      "ოპერაციული სისტემა:": "-",
      "Bluetooth:": "5.2",
      "ეკრანის ზომა:": "15.3 Inches",
      "რეზოლუცია:": "WQXGA",
      "ეკრანის ტიპი:": "IPS",
      "სენსორული ეკრანი:": "No",
      "განახლების სიხშირე:": "165 Hz",
      "კლავიატურის განათება:": "Yes",
      "Numpad:": "Yes",
      "დისკის წამკითხველი:": "No",
      "ვებ კამერა:": "Yes",
      "ლეპტოპის ტიპი:": "გეიმინგი",
      "შიდა მეხსიერება:": "1 TB",
      "შიდა მეხსიერების ტიპი:": "SSD",
      "შიდა მეხსიერების ინტერფეისი:": "M.2",
      "ოპერატიული მეხსიერება:": "24 GB",
      "ოპერატიული მეხსიერების ტიპი:": "DDR5",
      "ოპერატიული მეხსიერების სიხშირე:": "4800 MHz",
      "USB:": "3 x USB-A",
      "Type-C:": "2x",
      "Type-C პორტით დამუხტვა:": "No",
      "HDMI:": "Yes",
      "ლან პორტი:": "Yes",
      "3.5mm:": "Yes",
      "წონა:": "2.1 kg",
      "ფერი:": "Black"
    }
  },
  {
    "category": "Gaming ლეპტოპები",
    "title": "Lenovo Legion Pro 7 83F50026RK, Intel Core Ultra 9 27 ...",
    "price": 7999.0,
    "link": "https://zoommer.ge/leptopebi/lenovo-legion-pro-7-83f50026rk-intel-core-ultra-9-275hx-24c-nvidia-geforce-rt-p48317",
    "image": "/_next/image?url=https%3A%2F%2Fs3.zoommer.ge%2Fsite%2F7c74a086-27a1-4285-9837-8d12b4396e1e_Thumb.jpeg&w=384&q=50",
    "product_title_detail": "Lenovo Legion Pro 7 83F50026RK, Intel Core Ultra 9 275HX - 24c, NVIDIA GeForce RTX 5070 Ti 12GB, 32GB RAM SSD 1TB, Free Dos, ლეპტოპი",
    "description": "*7007 / +995 (32) 2 60 30 60\nსავაჭრო პოლიტიკა\nგანვადება\nკარიერა\nTrade In\nფილიალები\nნავიგაცია\nკალათა\nშესვლა\n%\nმთავარი\nლეპტოპები\nLenovo\n#ZOOM-036670\nLenovo Legion Pro 7 83F50026RK, Intel Core Ultra 9 275HX - 24c, NVIDIA GeForce RTX 5070 Ti 12GB, 32GB RAM SSD 1TB, Free Dos, ლეპტოპი\nეკრანის ზომა\n16 Inches\nრეზოლუცია\nWQXGA\nეკრანის ტიპი\nOled\nგანახლების სიხშირე\n240 Hz\nშიდა მეხსიერება\n1 TB\nBluetooth\nYes\nType-C\n2x\nოპერატიული მეხსიერება\n32 GB\nერთად იაფია\nდაამატე ნივთი\nLenovo Legion Pro 7 83F50026RK, Intel Core Ultra 9 275HX - 24c, NVIDIA GeForce RTX 5070 Ti 12GB, 32GB RAM SSD 1TB, Free Dos, ლეპტოპი\n7999 ₾\nRivacase 8057 Laptop Bag 16 Black\n58.65 ₾\n69 ₾\nRazer Gaming Mouse DeathAdder Essential USB White\n52 ₾\n65 ₾\nHavit Gaming Cooling Pad HV-F2083 Black\n75.65 ₾\n89 ₾\nჯამური ფასი (3)\n8185.3 ₾\n8222 ₾\nყიდვა\nაქსესუარები\nაღწერა\nმსგავსი\nმახასიათებლები\nფილიალები\nაქსესუარები\nაღწერა\nმსგავსი\nმახასიათებლები\nფილიალები\n89 ₾\n\nთვეში: 2 ₾ -დან\n\nHavit Gaming Cooling Pad HV-F2083 Black\nდამატება\n69 ₾\n\nთვეში: 1 ₾ -დან\n\nRivacase 8057 Laptop Bag 16 Black\nდამატება\n219 ₾\n\nთვეში: 6 ₾ -დან\n\nRazer Gaming Mouse Orochi V2 WL Black\nდამატება\n59 ₾\n\nთვეში: 1 ₾ -დან\n\nHavit Gaming mouse Pad HV-MP901\nდამატება\n69 ₾\n\nთვეში: 1 ₾ -დან\n\nXiaomi Mi Router 4A DVB4230GL White\nდამატება\n79 ₾\n\nთვეში: 2 ₾ -დან\n\nRivacase 7531 Eco Laptop Bag 15 Black\nდამატება\n219 ₾\n\nთვეში: 6 ₾ -დან\n\nRazer Gaming Mouse Orochi V2 WL White\nდამატება\n9 ₾\n\nHavit Gaming mouse Pad HV-MP838\nდამატება\n85 ₾\n\nთვეში: 2 ₾ -დან\n\nTP-Link Archer C50 AC1200 White\nდამატება\n89 ₾\n\nთვეში: 2 ₾ -დან\n\nTomtoc Defender A13 Laptop Sleeve Kit 16 A13F2DV Blac ...\nდამატება\n209 ₾\n\nთვეში: 5 ₾ -დან\n\nRazer Gaming Mouse DeathAdder V2 X Hyperspeed WL/BT/U ...\nდამატება\n9 ₾\n\nHavit Gaming mouse Pad HV-MP843 Black\nდამატება\n119 ₾\n\nთვეში: 3 ₾ -დან\n\nTP-Link Archer C6 AC1200 Black\nდამატება\n119 ₾\n\nთვეში: 3 ₾ -დან\n\nTomtoc Defender A42 Laptop Briefcase 16 A42F2B1 Navy ...\nდამატება\n139 ₾\n\nთვეში: 3 ₾ -დან\n\nLogitech Gaming Mouse G402 Hyperion Fury black\nდამატება\n149 ₾\n\nთვეში: 4 ₾ -დან\n\nRazer Mouse Pad Firefly V2 RGB M Black\nდამატება\n159 ₾\n\nთვეში: 4 ₾ -დან\n\nXiaomi Router AX1500 White\nდამატება\n119 ₾\n\nთვეში: 3 ₾ -დან\n\nTomtoc Defender A42 Laptop Briefcase 16 A42F2D1 Black\nდამატება\n29 ₾\n\nHavit Gaming Mouse HV-MS1010 Black\nდამატება\n199 ₾\n\nთვეში: 5 ₾ -დან\n\nRazer Mouse Pad Goliathus Extended Chroma XXL Black\nდამატება\n179 ₾\n\nთვეში: 4 ₾ -დან\n\nXiaomi Mesh System AX3000 NE 1 pack White\nდამატება\n89 ₾\n\nთვეში: 2 ₾ -დან\n\nUniq Dfender Tough Laptop Sleeve 16 Inch Marl Grey\nდამატება\n79 ₾\n\nთვეში: 2 ₾ -დან\n\nRazer Gaming Mouse DeathAdder Essential USB Black\nდამატება\n149 ₾\n\nთვეში: 4 ₾ -დან\n\nHyperX Pulsefire Mat RGB Black\nდამატება\n299 ₾\n\nთვეში: 8 ₾ -დან\n\nXiaomi Mesh System AX3000 NE 2 pack White\nდამატება\n89 ₾\n\nთვეში: 2 ₾ -დან\n\nUniq Dfender Tough Laptop Sleeve 16 Inch Black\nდამატება\n119 ₾\n\nთვეში: 3 ₾ -დან\n\nHyperX Pulsefire Surge Mouse Black\nდამატება\n29 ₾\n\nHavit Gaming Mouse Pad HV-MP845 Black\nდამატება\n249 ₾\n\nთვეში: 6 ₾ -დან\n\nXiaomi Router BE3600 White\nდამატება\n99 ₾\n\nთვეში: 2 ₾ -დან\n\nDell EcoLoop Essential Backpack 14-16 460-BDSS Black\nდამატება\n469 ₾\n\nთვეში: 13 ₾ -დან\n\nHP OMEN PHOTON Wireless Mouse 6CL96AA Black\nდამატება\n29 ₾\n\nHavit Gaming Mouse Pad HV-MP847 Pink\nდამატება\n79 ₾\n\nთვეში: 2 ₾ -დან\n\nTomtoc Defender A13 Laptop Sleeve 16 A13F2D1 Black\nდამატება\n65 ₾\n\nთვეში: 1 ₾ -დან\n\nRazer Gaming Mouse DeathAdder Essential USB White\nდამატება\n29 ₾\n\nHavit Gaming Mouse Pad HV-MP849 Black\nდამატება\n89 ₾\n\nთვეში: 2 ₾ -დან\n\nTomtoc Defender A14 Laptop Briefcase 16 A14F2D1 Black\nდამატება\n239 ₾\n\nთვეში: 6 ₾ -დან\n\nRazer Gaming Mouse Basilisk V3 Black\nდამატება\n49 ₾\n\nთვეში: 1 ₾ -დან\n\nHyperX Pulsefire Mat M Black\nდამატება\n299 ₾\n\nთვეში: 8 ₾ -დან\n\nRazer Gaming Mouse Naga V2 HyperSpeed WL Black\nდამატება\n59 ₾\n\nთვეში: 1 ₾ -დან\n\nHyperX Pulsefire Mat L Black\nდამატება\n229 ₾\n\nთვეში: 6 ₾ -დან\n\nRazer Gaming Mouse Basilisk V3 X HyperSpeed WL Black\nდამატება\n39 ₾\n\nთვეში: 1 ₾ -დან\n\nRazer Mouse Pad Sphex V3 S Black\nდამატება\n129 ₾\n\nთვეში: 3 ₾ -დან\n\nRazer Gaming Mouse Cobra Black\nდამატება\n89 ₾\n\nთვეში: 2 ₾ -დან\n\nRazer Mouse Pad Sphex V3 L Black\nდამატება\n19 ₾\n\nHavit Gaming Mouse HV-MS989GT Black/Red\nდამატება\n29 ₾\n\nHavit Gaming mouse Pad HV-MP860\nდამატება\n19 ₾\n\nHavit Gaming Mouse HV-MS626GT Black\nდამატება\n19 ₾\n\nHavit Gaming Mouse HV-MS66GT White/Blue\nდამატება\n149 ₾\n\nთვეში: 4 ₾ -დან\n\nHyperX Gaming Mouse Pulsefire Haste 2 Black\nდამატება\n19 ₾\n\nHavit Wireless Mouse HV-MS66GT Black\nდამატება\n179 ₾\n\nთვეში: 4 ₾ -დან\n\nLogitech Gaming Mouse G305 LIGHTSPEED WL L910-005282 ...\nდამატება\n259 ₾\n\nთვეში: 7 ₾ -დან\n\nLogitech Gaming Mouse G502 X L910-006138 Black\nდამატება\n259 ₾\n\nთვეში: 7 ₾ -დან\n\nLogitech Gaming Mouse G502 X L910-006138 White\nდამატება\n19 ₾\n\nHavit Gaming Mouse HV-MS626GT Black/Red\nდამატება\n19 ₾\n\nHavit Gaming Mouse HV-MS626GT Black/Blue\nდამატება\n349 ₾\n\nთვეში: 9 ₾ -დან\n\nLogitech Gaming Mouse G703 LIGHTSPEED WL L910-005640 ...\nდამატება\n89 ₾\n\nთვეში: 2 ₾ -დან\n\nLogitech Gaming Mouse G102 LIGHTSYNC L910-005823 Blac ...\nდამატება\n89 ₾\n\nთვეში: 2 ₾ -დან\n\nLogitech Gaming Mouse G102 LIGHTSYNC L910-005824 Whit ...\nდამატება\n89 ₾\n\nთვეში: 2 ₾ -დან\n\nLogitech Gaming Mouse G102 LIGHTSYNC L910-005801 Blue\nდამატება\n239 ₾\n\nთვეში: 6 ₾ -დან\n\nLogitech Gaming Mouse G502 HERO L910-005470 Black\nდამატება\n199 ₾\n\nთვეში: 5 ₾ -დან\n\nHyperX Pulsefire Haste 2 core Wireless Black\nდამატება\n199 ₾\n\nთვეში: 5 ₾ -დან\n\nHyperX Pulsefire Haste 2 core Wireless White\nდამატება\n59 ₾\n\nთვეში: 1 ₾ -დან\n\nHavit Gaming Mouse HV-MS954 Black\nდამატება\n39 ₾\n\nთვეში: 1 ₾ -დან\n\nHavit Gaming Mouse HV-MS1033 White\nდამატება\n39 ₾\n\nთვეში: 1 ₾ -დან\n\nHavit Gaming Mouse HV-MS1029 Pink\nდამატება\n59 ₾\n\nთვეში: 1 ₾ -დან\n\nHavit Gaming Mouse HV-MS966 Black/Green\nდამატება\n49 ₾\n\nთვეში: 1 ₾ -დან\n\nHavit Wireless Mouse HV-MS1039W Black/White\nდამატება\n79 ₾\n\nთვეში: 2 ₾ -დან\n\nHavit Wireless Mouse HV-MS970WB Pro Black\nდამატება\n79 ₾\n\nთვეში: 2 ₾ -დან\n\nHavit Wireless Mouse HV-MS970WB Pro Transparent White\nდამატება\n219 ₾\n\nთვეში: 6 ₾ -დან\n\nRazer Gaming Mouse Orochi V2 WL Pink\nდამატება\nპროდუქტის შესახებ\n\nთუ ეძებთ ლეპტოპს, რომელიც მარტივად გაუმკლავდება ყველაზე მოთხოვნად თამაშებს — Lenovo Legion Pro 7 83F50026RK შექმნილია სწორედ თქვენთვის. ეს მოდელი აერთიანებს მაღალ წარმადობას, გამძლე კონსტრუქციასა და...\n\nმეტის ნახვა\nმსგავსი პროდუქტები\n2999 ₾\n3199 ₾\n\nთვეში: 83 ₾ -დან\n\nLenovo LOQ 15 83DV00MPRK Luna Grey\nდამატება\n4299 ₾\n\nთვეში: 119 ₾ -დან\n\nLenovo Legion 5 83LY008MRK Black\nდამატება\n3799 ₾\n\nთვეში: 105 ₾ -დან\n\nLenovo LOQ 15 83JE002DRK Grey\nდამატება\n5999 ₾\n6199 ₾\n\nთვეში: 166 ₾ -დან\n\nLenovo Legion 5 Pro 83F3000XRK Black\nდამატება\n6999 ₾\n\nთვეში: 194 ₾ -დან\n\nLenovo Legion 5 Pro 83F30012RK Black\nდამატება\nდამატებითი მახასიათებლები\nბრენდი\nბრენდი:\n\t\nLenovo\nმოდელი\nმოდელი:\n\t\nLegion\nტექნიკური მახასიათებლები\nცენტრალური პროცესორი:\n\t\nIntel Core Ultra 9-275HX\n\n\nპროცესორის თაობა:\n\t\nIntel Ultra 9 Series 2\n\n\nპროცესორის სიხშირე:\n\t\n2.1 GHz ~ 5.4 GHz\n\n\nბირთვების რაოდენობა:\n\t\n24\n\n\nნაკადების რაოდენობა:\n\t\n24\n\n\nგრაფიკული პროცესორი:\n\t\nNvidia GeForce RTX 5070 TI\n\n\nგრაფიკული პროცესორის მეხსიერება:\n\t\n12 GB\n\n\nგრაფიკული პროცესორის ტიპი:\n\t\nარა ინტეგრირებული\n\n\nოპერაციული სისტემა:\n\t\nNo\n\n\nBluetooth:\n\t\nYes\nეკრანი\nეკრანის ზომა:\n\t\n16 Inches\n\n\nრეზოლუცია:\n\t\nWQXGA\n\n\nეკრანის ტიპი:\n\t\nOled\n\n\nსენსორული ეკრანი:\n\t\nNo\n\n\nგანახლების სიხშირე:\n\t\n240 Hz\nდამატებითი მახასიათებლები\nკლავიატურის განათება:\n\t\nYes\n\n\nNumpad:\n\t\nYes\n\n\nდისკის წამკითხველი:\n\t\nNo\n\n\nვებ კამერა:\n\t\nYes\n\n\nლეპტოპის ტიპი:\n\t\nგეიმინგი\nმეხსიერება\nშიდა მეხსიერება:\n\t\n1 TB\n\n\nშიდა მეხსიერების ტიპი:\n\t\nSSD\n\n\nშიდა მეხსიერების ინტერფეისი:\n\t\nM.2\n\n\nოპერატიული მეხსიერება:\n\t\n32 GB\n\n\nოპერატიული მეხსიერების ტიპი:\n\t\nDDR5\n\n\nოპერატიული მეხსიერების სიხშირე:\n\t\n6400 MHz\nპორტები\nUSB:\n\t\n3 x USB-A\n\n\nType-C:\n\t\n2x\n\n\nType-C პორტით დამუხტვა:\n\t\nYes\n\n\nHDMI:\n\t\nYes\n\n\nლან პორტი:\n\t\nYes\n\n\n3.5mm:\n\t\nYes\nზომა/წონა\nწონა:\n\t\n2.57 kg\nფერი\nფერი:\n\t\nBlack\nმეტის ნახვა\nგაეცანი საგარანტიო პირობებს\nსაგარანტიო პირობები\nგაეცანი პროდუქტის სახელმძღვანელოს\nპროდუქტის სახელმძღვანელო\nფილიალები\nმარაგშია\nშეკვეთიდან 2-5 დღეში\nზუმერის ისთ ფოინთის ფილიალი\n\nთბილისი - \"ისთ ფოინთი\" - ალ. თვალჭრელიძე N2\n\nმარაგშია\n+995 591 340 476\nორშ-შაბ: 10:00:00 - 22:00:00\nკვირა: 10:00:00 - 22:00:00\n7999 ₾\n8799 ₾\n\nთვეში: 222.2 ₾ -დან\n\nმარაგი ფილიალებში\nფასის დაზღვევა\nფასის კონტროლი\nფასის დაჯავშნა\nყიდვა\nშედარება\nდამატება\nნავიგაცია\n\nპერსონალურ მონაცემთა დაცვის პოლიტიკა\n\nჩვენ შესახებ\n\nწესები და პირობები\n\nმიწოდების სერვისი\n\nკარიერა\n\nგადახდები\n\nSetanta Sports\n\nგადახდის მეთოდები\n\nგარანტია\n\nგანვადება\n\nნივთის დაბრუნება\n\nნივთის ონლაინ ყიდვის ინსტრუქცია\n\nგამოგვყევი\n\nFacebook\n\nYoutube\n\nInstagram\n\nTik Tok\n\nკონტაქტი\n\nInfo@zoommer.ge\n\n+995 (32) 2 60 30 60 / *7007\n\nფილიალები\n\nკორპორატიული გაყიდვები\n\nZoommer App\n\nCopyright © 2023 Zoommer.ge. All rights reserved.\n\nCookie პოლიტიკა\n\nსაიტით სარგებლობის გაგრძელებით, შენ ეთანხმები Cookie ჩანაწერების გამოყენებას. მეტი ინფორმაცისათვის იხილეთ კონფიდენციალურობის პოლიტიკა\n\nგასაგებია",
    "specs": {
      "ბრენდი:": "Lenovo",
      "მოდელი:": "Legion",
      "ცენტრალური პროცესორი:": "Intel Core Ultra 9-275HX",
      "პროცესორის თაობა:": "Intel Ultra 9 Series 2",
      "პროცესორის სიხშირე:": "2.1 GHz ~ 5.4 GHz",
      "ბირთვების რაოდენობა:": "24",
      "ნაკადების რაოდენობა:": "24",
      "გრაფიკული პროცესორი:": "Nvidia GeForce RTX 5070 TI",
      "გრაფიკული პროცესორის მეხსიერება:": "12 GB",
      "გრაფიკული პროცესორის ტიპი:": "არა ინტეგრირებული",
      "ოპერაციული სისტემა:": "No",
      "Bluetooth:": "Yes",
      "ეკრანის ზომა:": "16 Inches",
      "რეზოლუცია:": "WQXGA",
      "ეკრანის ტიპი:": "Oled",
      "სენსორული ეკრანი:": "No",
      "განახლების სიხშირე:": "240 Hz",
      "კლავიატურის განათება:": "Yes",
      "Numpad:": "Yes",
      "დისკის წამკითხველი:": "No",
      "ვებ კამერა:": "Yes",
      "ლეპტოპის ტიპი:": "გეიმინგი",
      "შიდა მეხსიერება:": "1 TB",
      "შიდა მეხსიერების ტიპი:": "SSD",
      "შიდა მეხსიერების ინტერფეისი:": "M.2",
      "ოპერატიული მეხსიერება:": "32 GB",
      "ოპერატიული მეხსიერების ტიპი:": "DDR5",
      "ოპერატიული მეხსიერების სიხშირე:": "6400 MHz",
      "USB:": "3 x USB-A",
      "Type-C:": "2x",
      "Type-C პორტით დამუხტვა:": "Yes",
      "HDMI:": "Yes",
      "ლან პორტი:": "Yes",
      "3.5mm:": "Yes",
      "წონა:": "2.57 kg",
      "ფერი:": "Black"
    }
  },
  {
    "category": "Gaming ლეპტოპები",
    "title": "HP Victus 15 B84VTEA Silver",
    "price": 2799.0,
    "link": "https://zoommer.ge/leptopebi/hp-victus-15-b84vtea-silver-p48100",
    "image": "/_next/image?url=https%3A%2F%2Fs3.zoommer.ge%2Fsite%2F8de8838e-d4b8-42d2-bfb4-d1f21019fb21_Thumb.jpeg&w=384&q=50",
    "product_title_detail": "HP Victus 15 B84VTEA Silver",
    "description": "*7007 / +995 (32) 2 60 30 60\nფილიალები\nნავიგაცია\nკალათა\nშესვლა\n%\nმთავარი\nლეპტოპები\nHP\n#ZOOM-036606\nHP Victus 15 B84VTEA Silver\nეკრანის ზომა\n15.6 Inches\nრეზოლუცია\nFull HD\nეკრანის ტიპი\nIPS\nგანახლების სიხშირე\n144 Hz\nშიდა მეხსიერება\n512 GB\nBluetooth\nYes\nType-C\n1x\nოპერატიული მეხსიერება\n16 GB\nპროდუქტს მოყვება საჩუქარი\nGift Card - 200 ₾\n200 ₾\nერთად იაფია\nდაამატე ნივთი\nHP Victus 15 B84VTEA Silver\n2799 ₾\nRivacase 7562 Anti-Theft Laptop Backpack 15 Grey/Dark blue\n67.15 ₾\n79 ₾\nRazer Gaming Mouse DeathAdder Essential USB White\n52 ₾\n65 ₾\nHavit Gaming Cooling Pad HV-F2035 Black\n41.65 ₾\n49 ₾\nჯამური ფასი (3)\n2959.8 ₾\n2992 ₾\nყიდვა\nაქსესუარები\nაღწერა\nმსგავსი\nმახასიათებლები\nფილიალები\nაქსესუარები\nაღწერა\nმსგავსი\nმახასიათებლები\nფილიალები\n89 ₾\n\nთვეში: 2 ₾ -დან\n\nHavit Gaming Cooling Pad HV-F2083 Black\nდამატება\n39 ₾\n\nთვეში: 1 ₾ -დან\n\nLenovo Casual Backpack B210 Green\nდამატება\n219 ₾\n\nთვეში: 6 ₾ -დან\n\nRazer Gaming Mouse Orochi V2 WL Black\nდამატება\n59 ₾\n\nთვეში: 1 ₾ -დან\n\nHavit Gaming mouse Pad HV-MP901\nდამატება\n69 ₾\n\nთვეში: 1 ₾ -დან\n\nXiaomi Mi Router 4A DVB4230GL White\nდამატება\n129 ₾\n\nთვეში: 3 ₾ -დან\n\nRivacase 7930 Pro 16\nდამატება\n219 ₾\n\nთვეში: 6 ₾ -დან\n\nRazer Gaming Mouse Orochi V2 WL White\nდამატება\n9 ₾\n\nHavit Gaming mouse Pad HV-MP838\nდამატება\n85 ₾\n\nთვეში: 2 ₾ -დან\n\nTP-Link Archer C50 AC1200 White\nდამატება\n59 ₾\n\nთვეში: 1 ₾ -დან\n\nRivacese 8035 Laptop Shoulder Bag 15 Black\nდამატება\n209 ₾\n\nთვეში: 5 ₾ -დან\n\nRazer Gaming Mouse DeathAdder V2 X Hyperspeed WL/BT/U ...\nდამატება\n9 ₾\n\nHavit Gaming mouse Pad HV-MP843 Black\nდამატება\n119 ₾\n\nთვეში: 3 ₾ -დან\n\nTP-Link Archer C6 AC1200 Black\nდამატება\n59 ₾\n\nთვეში: 1 ₾ -დან\n\nRivacase 8037 Laptop Bag 15 Black\nდამატება\n139 ₾\n\nთვეში: 3 ₾ -დან\n\nLogitech Gaming Mouse G402 Hyperion Fury black\nდამატება\n149 ₾\n\nთვეში: 4 ₾ -დან\n\nRazer Mouse Pad Firefly V2 RGB M Black\nდამატება\n159 ₾\n\nთვეში: 4 ₾ -დან\n\nXiaomi Router AX1500 White\nდამატება\n79 ₾\n\nთვეში: 2 ₾ -დან\n\nRivacase 7562 Anti-Theft Laptop Backpack 15 Black\nდამატება\n29 ₾\n\nHavit Gaming Mouse HV-MS1010 Black\nდამატება\n199 ₾\n\nთვეში: 5 ₾ -დან\n\nRazer Mouse Pad Goliathus Extended Chroma XXL Black\nდამატება\n179 ₾\n\nთვეში: 4 ₾ -დან\n\nXiaomi Mesh System AX3000 NE 1 pack White\nდამატება\n79 ₾\n\nთვეში: 2 ₾ -დან\n\nRivacase 7562 Anti-Theft Laptop Backpack 15 Dark grey\nდამატება\n79 ₾\n\nთვეში: 2 ₾ -დან\n\nRazer Gaming Mouse DeathAdder Essential USB Black\nდამატება\n149 ₾\n\nთვეში: 4 ₾ -დან\n\nHyperX Pulsefire Mat RGB Black\nდამატება\n299 ₾\n\nთვეში: 8 ₾ -დან\n\nXiaomi Mesh System AX3000 NE 2 pack White\nდამატება\n79 ₾\n\nთვეში: 2 ₾ -დან\n\nRivacase 7562 Anti-Theft Laptop Backpack 15 Grey/Dark ...\nდამატება\n119 ₾\n\nთვეში: 3 ₾ -დან\n\nHyperX Pulsefire Surge Mouse Black\nდამატება\n29 ₾\n\nHavit Gaming Mouse Pad HV-MP845 Black\nდამატება\n249 ₾\n\nთვეში: 6 ₾ -დან\n\nXiaomi Router BE3600 White\nდამატება\n69 ₾\n\nთვეში: 1 ₾ -დან\n\nRivacase 7532 Anti-Theft Laptop Bag 15 Dark Grey\nდამატება\n469 ₾\n\nთვეში: 13 ₾ -დან\n\nHP OMEN PHOTON Wireless Mouse 6CL96AA Black\nდამატება\n29 ₾\n\nHavit Gaming Mouse Pad HV-MP847 Pink\nდამატება\n69 ₾\n\nთვეში: 1 ₾ -დან\n\nRivacase 7532 Anti-Theft Laptop Bag 15 Grey/Dark Blue ...\nდამატება\n65 ₾\n\nთვეში: 1 ₾ -დან\n\nRazer Gaming Mouse DeathAdder Essential USB White\nდამატება\n29 ₾\n\nHavit Gaming Mouse Pad HV-MP849 Black\nდამატება\n79 ₾\n\nთვეში: 2 ₾ -დან\n\nRivacase 8231 Laptop Bag 15 Black\nდამატება\n239 ₾\n\nთვეში: 6 ₾ -დან\n\nRazer Gaming Mouse Basilisk V3 Black\nდამატება\n49 ₾\n\nთვეში: 1 ₾ -დან\n\nHyperX Pulsefire Mat M Black\nდამატება\n79 ₾\n\nთვეში: 2 ₾ -დან\n\nRivacase 8231 Laptop Bag 15 Star blue\nდამატება\n299 ₾\n\nთვეში: 8 ₾ -დან\n\nRazer Gaming Mouse Naga V2 HyperSpeed WL Black\nდამატება\n59 ₾\n\nთვეში: 1 ₾ -დან\n\nHyperX Pulsefire Mat L Black\nდამატება\n79 ₾\n\nთვეში: 2 ₾ -დან\n\nRivacase 8335 Laptop Bag 15 Black\nდამატება\n229 ₾\n\nთვეში: 6 ₾ -დან\n\nRazer Gaming Mouse Basilisk V3 X HyperSpeed WL Black\nდამატება\n39 ₾\n\nთვეში: 1 ₾ -დან\n\nRazer Mouse Pad Sphex V3 S Black\nდამატება\n79 ₾\n\nთვეში: 2 ₾ -დან\n\nRivacase 8335 Laptop Bag 15 Star blue\nდამატება\n129 ₾\n\nთვეში: 3 ₾ -დან\n\nRazer Gaming Mouse Cobra Black\nდამატება\n89 ₾\n\nთვეში: 2 ₾ -დან\n\nRazer Mouse Pad Sphex V3 L Black\nდამატება\n69 ₾\n\nთვეში: 1 ₾ -დან\n\nRivacase 7730 Eco Laptop Shoulder Bag 15 Black\nდამატება\n19 ₾\n\nHavit Gaming Mouse HV-MS989GT Black/Red\nდამატება\n29 ₾\n\nHavit Gaming mouse Pad HV-MP860\nდამატება\n59 ₾\n\nთვეში: 1 ₾ -დან\n\nRivacase 8035 Laptop Shoulder Bag 15\nდამატება\n19 ₾\n\nHavit Gaming Mouse HV-MS626GT Black\nდამატება\n79 ₾\n\nთვეში: 2 ₾ -დან\n\nTomtoc Defender A13 Laptop Sleeve 15 A13E3D1 Black\nდამატება\n19 ₾\n\nHavit Gaming Mouse HV-MS66GT White/Blue\nდამატება\n119 ₾\n\nთვეში: 3 ₾ -დან\n\nTomtoc Defender A42 Laptop Briefcase 15 A42E1D1 Black\nდამატება\n149 ₾\n\nთვეში: 4 ₾ -დან\n\nHyperX Gaming Mouse Pulsefire Haste 2 Black\nდამატება\n79 ₾\n\nთვეში: 2 ₾ -დან\n\nHP Campus backpack 15.6 7J595AA Green\nდამატება\n19 ₾\n\nHavit Wireless Mouse HV-MS66GT Black\nდამატება\n79 ₾\n\nთვეში: 2 ₾ -დან\n\nHP Campus backpack 15.6 7J597AA Lavender\nდამატება\n179 ₾\n\nთვეში: 4 ₾ -დან\n\nLogitech Gaming Mouse G305 LIGHTSPEED WL L910-005282 ...\nდამატება\n69 ₾\n\nთვეში: 1 ₾ -დან\n\nRivacase 8065 Laptop Backpack 15 Black\nდამატება\n259 ₾\n\nთვეში: 7 ₾ -დან\n\nLogitech Gaming Mouse G502 X L910-006138 Black\nდამატება\n69 ₾\n\nთვეში: 1 ₾ -დან\n\nRivacase 8065 Laptop Backpack 15 Dark Blue\nდამატება\n259 ₾\n\nთვეში: 7 ₾ -დან\n\nLogitech Gaming Mouse G502 X L910-006138 White\nდამატება\n79 ₾\n\nთვეში: 2 ₾ -დან\n\nRivacase 8335 Laptop Bag 15 Purple\nდამატება\n19 ₾\n\nHavit Gaming Mouse HV-MS626GT Black/Red\nდამატება\n19 ₾\n\nHavit Gaming Mouse HV-MS626GT Black/Blue\nდამატება\n349 ₾\n\nთვეში: 9 ₾ -დან\n\nLogitech Gaming Mouse G703 LIGHTSPEED WL L910-005640 ...\nდამატება\n89 ₾\n\nთვეში: 2 ₾ -დან\n\nLogitech Gaming Mouse G102 LIGHTSYNC L910-005823 Blac ...\nდამატება\n89 ₾\n\nთვეში: 2 ₾ -დან\n\nLogitech Gaming Mouse G102 LIGHTSYNC L910-005824 Whit ...\nდამატება\n89 ₾\n\nთვეში: 2 ₾ -დან\n\nLogitech Gaming Mouse G102 LIGHTSYNC L910-005801 Blue\nდამატება\n239 ₾\n\nთვეში: 6 ₾ -დან\n\nLogitech Gaming Mouse G502 HERO L910-005470 Black\nდამატება\n199 ₾\n\nთვეში: 5 ₾ -დან\n\nHyperX Pulsefire Haste 2 core Wireless Black\nდამატება\n199 ₾\n\nთვეში: 5 ₾ -დან\n\nHyperX Pulsefire Haste 2 core Wireless White\nდამატება\n59 ₾\n\nთვეში: 1 ₾ -დან\n\nHavit Gaming Mouse HV-MS954 Black\nდამატება\n39 ₾\n\nთვეში: 1 ₾ -დან\n\nHavit Gaming Mouse HV-MS1033 White\nდამატება\n39 ₾\n\nთვეში: 1 ₾ -დან\n\nHavit Gaming Mouse HV-MS1029 Pink\nდამატება\n59 ₾\n\nთვეში: 1 ₾ -დან\n\nHavit Gaming Mouse HV-MS966 Black/Green\nდამატება\n49 ₾\n\nთვეში: 1 ₾ -დან\n\nHavit Wireless Mouse HV-MS1039W Black/White\nდამატება\n79 ₾\n\nთვეში: 2 ₾ -დან\n\nHavit Wireless Mouse HV-MS970WB Pro Black\nდამატება\n79 ₾\n\nთვეში: 2 ₾ -დან\n\nHavit Wireless Mouse HV-MS970WB Pro Transparent White\nდამატება\n219 ₾\n\nთვეში: 6 ₾ -დან\n\nRazer Gaming Mouse Orochi V2 WL Pink\nდამატება\nპროდუქტის შესახებ\n\nთუ ეძებთ ლეპტოპს, რომელიც მარტივად გაუმკლავდება ყველაზე მოთხოვნად თამაშებს — HP Victus 15 B84VTEA Silver შექმნილია სწორედ თქვენთვის. ეს მოდელი აერთიანებს მაღალ წარმადობას, გამძლე კონსტრუქციასა და თვ...\n\nმეტის ნახვა\nმსგავსი პროდუქტები\n2999 ₾\n\nთვეში: 83 ₾ -დან\n\nHP Victus 15 84J97EA, Intel core i5-13500H, Nvidia Ge ...\nდამატება\n2499 ₾\n\nთვეში: 69 ₾ -დან\n\nHP Victus 15 84J98EA, Intel Core i5-13420H Octa 4.6 G ...\nდამატება\n2499 ₾\n\nთვეში: 69 ₾ -დან\n\nHP Victus 15 84J99EA, Intel Core i5-13420H Octa 4.6 G ...\nდამატება\n3199 ₾\n3399 ₾\n\nთვეში: 88 ₾ -დან\n\nHP Victus 15 8F5J3EA Mica Silver\nდამატება\n3499 ₾\n3699 ₾\n\nთვეში: 97 ₾ -დან\n\nHP Omen 16 A1WF1EA, Intel Core i5-14500HX, Nvidia GeF ...\nდამატება\n2799 ₾\n2999 ₾\n\nთვეში: 77 ₾ -დან\n\nHP Victus 15 A1WD6EA, AMD Ryzen 5-8645HS, NVIDIA GeFo ...\nდამატება\n3379 ₾\n\nთვეში: 93 ₾ -დან\n\nHP Victus 16 A1WE4EA, Intel Core i5-14450HX, Nvidia G ...\nდამატება\n2899 ₾\n2999 ₾\n\nთვეში: 80 ₾ -დან\n\nHP Victus 15 A1WD5EA Mica Silver\nდამატება\n3999 ₾\n5599 ₾\n\nთვეში: 111 ₾ -დან\n\nHP Omen 14 A1AA7EA Black\nდამატება\n2999 ₾\n3099 ₾\n\nთვეში: 83 ₾ -დან\n\nHP Victus 16 A1AB6EA Mica Silver\nდამატება\n2899 ₾\n2999 ₾\n\nთვეში: 80 ₾ -დან\n\nHP Victus 16 A1AB7EA Mica Silver\nდამატება\n3999 ₾\n4199 ₾\n\nთვეში: 111 ₾ -დან\n\nHP Victus 16 B09JXEA Mica Silver\nდამატება\n2499 ₾\n2599 ₾\n\nთვეში: 69 ₾ -დან\n\nHP Victus 15 B08XKEA Mica Silver\nდამატება\n3299 ₾\n3499 ₾\n\nთვეში: 91 ₾ -დან\n\nHP Victus 15 A74LKEA Blue\nდამატება\n2799 ₾\n3199 ₾\n\nთვეში: 77 ₾ -დან\n\nHP Victus 15 B09J6EA Blue\nდამატება\n5699 ₾\n\nთვეში: 158 ₾ -დან\n\nHP Omen Max 16 BG7J7EA, Intel Core Ultra 7-255HX 20c, ...\nდამატება\nდამატებითი მახასიათებლები\nბრენდი\nბრენდი:\n\t\nHP\nმოდელი\nმოდელი:\n\t\nVictus\nტექნიკური მახასიათებლები\nცენტრალური პროცესორი:\n\t\nAMD Ryzen 5-8645HS\n\n\nპროცესორის თაობა:\n\t\nRyzen 5 8000 Series\n\n\nპროცესორის სიხშირე:\n\t\n4.3 GHz ~ 5.0 GHz\n\n\nბირთვების რაოდენობა:\n\t\n6\n\n\nნაკადების რაოდენობა:\n\t\n12\n\n\nგრაფიკული პროცესორი:\n\t\nNvidia GeForce RTX 3050\n\n\nგრაფიკული პროცესორის მეხსიერება:\n\t\n6 GB\n\n\nგრაფიკული პროცესორის ტიპი:\n\t\nარა ინტეგრირებული\n\n\nოპერაციული სისტემა:\n\t\nNo\n\n\nBluetooth:\n\t\nYes\nეკრანი\nეკრანის ზომა:\n\t\n15.6 Inches\n\n\nრეზოლუცია:\n\t\nFull HD\n\n\nეკრანის ტიპი:\n\t\nIPS\n\n\nსენსორული ეკრანი:\n\t\nNo\n\n\nგანახლების სიხშირე:\n\t\n144 Hz\nდამატებითი მახასიათებლები\nკლავიატურის განათება:\n\t\nYes\n\n\nNumpad:\n\t\nYes\n\n\nდისკის წამკითხველი:\n\t\nNo\n\n\nვებ კამერა:\n\t\nYes\n\n\nლეპტოპის ტიპი:\n\t\nგეიმინგი\nმეხსიერება\nშიდა მეხსიერება:\n\t\n512 GB\n\n\nშიდა მეხსიერების ტიპი:\n\t\nSSD\n\n\nშიდა მეხსიერების ინტერფეისი:\n\t\nM.2\n\n\nოპერატიული მეხსიერება:\n\t\n16 GB\n\n\nოპერატიული მეხსიერების ტიპი:\n\t\n-\n\n\nოპერატიული მეხსიერების სიხშირე:\n\t\n-\nპორტები\nUSB:\n\t\n2 x USB-A\n\n\nType-C:\n\t\n1x\n\n\nType-C პორტით დამუხტვა:\n\t\n-\n\n\nHDMI:\n\t\nYes\n\n\nლან პორტი:\n\t\nYes\n\n\n3.5mm:\n\t\nYes\nზომა/წონა\nწონა:\n\t\n2.5 kg\nფერი\nფერი:\n\t\nsilver\nმეტის ნახვა\nგაეცანი საგარანტიო პირობებს\nსაგარანტიო პირობები\nფილიალები\nმარაგშია\nშეკვეთიდან 2-5 დღეში\nზუმერის წერეთლის ფილიალი\n\nთბილისი - წერეთლის გამზირი, N1.\n\nმარაგშია\n+995 591 967 601\nორშ-შაბ: 10:00:00 - 20:00:00\nკვირა: 10:00:00 - 19:00:00\nზუმერის თბილისი მოლის ფილიალი\n\nთბილისი - „თბილისი მოლი\" - I სართული. აღმაშენებლის ხეივანი მე-16 კმ\n\nმარაგშია\n+995 591 967 608\nორშ-შაბ: 10:00:00 - 22:00:00\nკვირა: 10:00:00 - 22:00:00\nზუმერის ისთ ფოინთის ფილიალი\n\nთბილისი - \"ისთ ფოინთი\" - ალ. თვალჭრელიძე N2\n\nმარაგშია\n+995 591 340 476\nორშ-შაბ: 10:00:00 - 22:00:00\nკვირა: 10:00:00 - 22:00:00\nზუმერი რუსთავი მოლის ფილიალი\n\nრუსთავი - შარტავას და ლომოურის კვეთა\n\nმარაგშია\n+995 591 441 082\nორშ-შაბ: 10:00:00 - 22:00:00\nკვირა: 10:00:00 - 22:00:00\nბათუმის \"Black Sea Mall\"-ის ფილიალი\n\nბათუმი - \"Black Sea Mall\" - ტბელ აბუსერიძის N22\n\nმარაგშია\n+995 591 310 257\nორშ-შაბ: 10:00:00 - 21:00:00\nკვირა: 10:00:00 - 21:00:00\nქუთაისი ვესთ მოლი\n\nქუთაისი - \"ვესთ მოლი\" - შარტავას N2\n\nმარაგშია\n+995 595 306 765\nორშ-შაბ: 10:00:00 - 22:00:00\nკვირა: 10:00:00 - 22:00:00\nმეტის ნახვა\n2799 ₾\n2999 ₾\n\nთვეში: 77.8 ₾ -დან\n\nმარაგი ფილიალებში\nფასის დაზღვევა\nფასის კონტროლი\nფასის დაჯავშნა\nყიდვა\nშედარება\nდამატება\nნავიგაცია\nგადახდები\nგამოგვყევი\n\nFacebook\n\nYoutube\n\nInstagram\n\nTik Tok\n\nკონტაქტი\n\nInfo@zoommer.ge\n\n+995 (32) 2 60 30 60 / *7007\n\nფილიალები\n\nკორპორატიული გაყიდვები\n\nZoommer App\n\nCopyright © 2023 Zoommer.ge. All rights reserved.\n\nCookie პოლიტიკა\n\nსაიტით სარგებლობის გაგრძელებით, შენ ეთანხმები Cookie ჩანაწერების გამოყენებას. მეტი ინფორმაცისათვის იხილეთ კონფიდენციალურობის პოლიტიკა\n\nგასაგებია",
    "specs": {
      "ბრენდი:": "HP",
      "მოდელი:": "Victus",
      "ცენტრალური პროცესორი:": "AMD Ryzen 5-8645HS",
      "პროცესორის თაობა:": "Ryzen 5 8000 Series",
      "პროცესორის სიხშირე:": "4.3 GHz ~ 5.0 GHz",
      "ბირთვების რაოდენობა:": "6",
      "ნაკადების რაოდენობა:": "12",
      "გრაფიკული პროცესორი:": "Nvidia GeForce RTX 3050",
      "გრაფიკული პროცესორის მეხსიერება:": "6 GB",
      "გრაფიკული პროცესორის ტიპი:": "არა ინტეგრირებული",
      "ოპერაციული სისტემა:": "No",
      "Bluetooth:": "Yes",
      "ეკრანის ზომა:": "15.6 Inches",
      "რეზოლუცია:": "Full HD",
      "ეკრანის ტიპი:": "IPS",
      "სენსორული ეკრანი:": "No",
      "განახლების სიხშირე:": "144 Hz",
      "კლავიატურის განათება:": "Yes",
      "Numpad:": "Yes",
      "დისკის წამკითხველი:": "No",
      "ვებ კამერა:": "Yes",
      "ლეპტოპის ტიპი:": "გეიმინგი",
      "შიდა მეხსიერება:": "512 GB",
      "შიდა მეხსიერების ტიპი:": "SSD",
      "შიდა მეხსიერების ინტერფეისი:": "M.2",
      "ოპერატიული მეხსიერება:": "16 GB",
      "ოპერატიული მეხსიერების ტიპი:": "-",
      "ოპერატიული მეხსიერების სიხშირე:": "-",
      "USB:": "2 x USB-A",
      "Type-C:": "1x",
      "Type-C პორტით დამუხტვა:": "-",
      "HDMI:": "Yes",
      "ლან პორტი:": "Yes",
      "3.5mm:": "Yes",
      "წონა:": "2.5 kg",
      "ფერი:": "silver"
    }
  },
  {
    "category": "Gaming ლეპტოპები",
    "title": "MSI Sword 16 9S7-15P214-886, Intel Core i7-14650HX, N ...",
    "price": 4499.0,
    "link": "https://zoommer.ge/leptopebi/msi-sword-16-9s7-15p214-886-intel-core-i7-14650hx-nvidia-geforce-rtx-4060-8gb-p46013",
    "image": "/_next/image?url=https%3A%2F%2Fs3.zoommer.ge%2Fsite%2Fdc94addd-3eac-4ade-8fd5-d1933c8cb362_Thumb.jpeg&w=384&q=50",
    "product_title_detail": "MSI Sword 16 9S7-15P214-886, Intel Core i7-14650HX, Nvidia GeForce RTX 4060 8GB, 16GB RAM SSD 1TB, Free Dos, ლეპტოპი",
    "description": "*7007 / +995 (32) 2 60 30 60\nსავაჭრო პოლიტიკა\nგანვადება\nკარიერა\nTrade In\nფილიალები\nნავიგაცია\nკალათა\nშესვლა\n%\nმთავარი\nლეპტოპები\nMSI\n#ZOOM-035610\nMSI Sword 16 9S7-15P214-886, Intel Core i7-14650HX, Nvidia GeForce RTX 4060 8GB, 16GB RAM SSD 1TB, Free Dos, ლეპტოპი\nეკრანის ზომა\n16 Inches\nრეზოლუცია\nFull HD\nეკრანის ტიპი\nIPS\nგანახლების სიხშირე\n144 Hz\nშიდა მეხსიერება\n1 TB\nBluetooth\nYes\nType-C\n1x\nოპერატიული მეხსიერება\n16 GB\nერთად იაფია\nდაამატე ნივთი\nMSI Sword 16 9S7-15P214-886, Intel Core i7-14650HX, Nvidia GeForce RTX 4060 8GB, 16GB RAM SSD 1TB, Free Dos, ლეპტოპი\n4499 ₾\nRivacase 7562 Anti-Theft Laptop Backpack 15 Grey/Dark blue\n67.15 ₾\n79 ₾\nRazer Gaming Mouse DeathAdder Essential USB White\n52 ₾\n65 ₾\nHavit Gaming Cooling Pad HV-F2083 Black\n75.65 ₾\n89 ₾\nჯამური ფასი (3)\n4693.8 ₾\n4732 ₾\nყიდვა\nაქსესუარები\nაღწერა\nმსგავსი\nმახასიათებლები\nფილიალები\nაქსესუარები\nაღწერა\nმსგავსი\nმახასიათებლები\nფილიალები\n89 ₾\n\nთვეში: 2 ₾ -დან\n\nHavit Gaming Cooling Pad HV-F2083 Black\nდამატება\n39 ₾\n\nთვეში: 1 ₾ -დან\n\nLenovo Casual Backpack B210 Green\nდამატება\n219 ₾\n\nთვეში: 6 ₾ -დან\n\nRazer Gaming Mouse Orochi V2 WL Black\nდამატება\n59 ₾\n\nთვეში: 1 ₾ -დან\n\nHavit Gaming mouse Pad HV-MP901\nდამატება\n69 ₾\n\nთვეში: 1 ₾ -დან\n\nXiaomi Mi Router 4A DVB4230GL White\nდამატება\n129 ₾\n\nთვეში: 3 ₾ -დან\n\nRivacase 7930 Pro 16\nდამატება\n219 ₾\n\nთვეში: 6 ₾ -დან\n\nRazer Gaming Mouse Orochi V2 WL White\nდამატება\n9 ₾\n\nHavit Gaming mouse Pad HV-MP838\nდამატება\n85 ₾\n\nთვეში: 2 ₾ -დან\n\nTP-Link Archer C50 AC1200 White\nდამატება\n59 ₾\n\nთვეში: 1 ₾ -დან\n\nRivacese 8035 Laptop Shoulder Bag 15 Black\nდამატება\n209 ₾\n\nთვეში: 5 ₾ -დან\n\nRazer Gaming Mouse DeathAdder V2 X Hyperspeed WL/BT/U ...\nდამატება\n9 ₾\n\nHavit Gaming mouse Pad HV-MP843 Black\nდამატება\n119 ₾\n\nთვეში: 3 ₾ -დან\n\nTP-Link Archer C6 AC1200 Black\nდამატება\n59 ₾\n\nთვეში: 1 ₾ -დან\n\nRivacase 8037 Laptop Bag 15 Black\nდამატება\n139 ₾\n\nთვეში: 3 ₾ -დან\n\nLogitech Gaming Mouse G402 Hyperion Fury black\nდამატება\n149 ₾\n\nთვეში: 4 ₾ -დან\n\nRazer Mouse Pad Firefly V2 RGB M Black\nდამატება\n159 ₾\n\nთვეში: 4 ₾ -დან\n\nXiaomi Router AX1500 White\nდამატება\n79 ₾\n\nთვეში: 2 ₾ -დან\n\nRivacase 7562 Anti-Theft Laptop Backpack 15 Black\nდამატება\n29 ₾\n\nHavit Gaming Mouse HV-MS1010 Black\nდამატება\n199 ₾\n\nთვეში: 5 ₾ -დან\n\nRazer Mouse Pad Goliathus Extended Chroma XXL Black\nდამატება\n179 ₾\n\nთვეში: 4 ₾ -დან\n\nXiaomi Mesh System AX3000 NE 1 pack White\nდამატება\n79 ₾\n\nთვეში: 2 ₾ -დან\n\nRivacase 7562 Anti-Theft Laptop Backpack 15 Dark grey\nდამატება\n79 ₾\n\nთვეში: 2 ₾ -დან\n\nRazer Gaming Mouse DeathAdder Essential USB Black\nდამატება\n149 ₾\n\nთვეში: 4 ₾ -დან\n\nHyperX Pulsefire Mat RGB Black\nდამატება\n299 ₾\n\nთვეში: 8 ₾ -დან\n\nXiaomi Mesh System AX3000 NE 2 pack White\nდამატება\n79 ₾\n\nთვეში: 2 ₾ -დან\n\nRivacase 7562 Anti-Theft Laptop Backpack 15 Grey/Dark ...\nდამატება\n119 ₾\n\nთვეში: 3 ₾ -დან\n\nHyperX Pulsefire Surge Mouse Black\nდამატება\n29 ₾\n\nHavit Gaming Mouse Pad HV-MP845 Black\nდამატება\n249 ₾\n\nთვეში: 6 ₾ -დან\n\nXiaomi Router BE3600 White\nდამატება\n69 ₾\n\nთვეში: 1 ₾ -დან\n\nRivacase 7532 Anti-Theft Laptop Bag 15 Dark Grey\nდამატება\n469 ₾\n\nთვეში: 13 ₾ -დან\n\nHP OMEN PHOTON Wireless Mouse 6CL96AA Black\nდამატება\n29 ₾\n\nHavit Gaming Mouse Pad HV-MP847 Pink\nდამატება\n69 ₾\n\nთვეში: 1 ₾ -დან\n\nRivacase 7532 Anti-Theft Laptop Bag 15 Grey/Dark Blue ...\nდამატება\n65 ₾\n\nთვეში: 1 ₾ -დან\n\nRazer Gaming Mouse DeathAdder Essential USB White\nდამატება\n29 ₾\n\nHavit Gaming Mouse Pad HV-MP849 Black\nდამატება\n79 ₾\n\nთვეში: 2 ₾ -დან\n\nRivacase 8231 Laptop Bag 15 Black\nდამატება\n239 ₾\n\nთვეში: 6 ₾ -დან\n\nRazer Gaming Mouse Basilisk V3 Black\nდამატება\n49 ₾\n\nთვეში: 1 ₾ -დან\n\nHyperX Pulsefire Mat M Black\nდამატება\n79 ₾\n\nთვეში: 2 ₾ -დან\n\nRivacase 8231 Laptop Bag 15 Star blue\nდამატება\n299 ₾\n\nთვეში: 8 ₾ -დან\n\nRazer Gaming Mouse Naga V2 HyperSpeed WL Black\nდამატება\n59 ₾\n\nთვეში: 1 ₾ -დან\n\nHyperX Pulsefire Mat L Black\nდამატება\n79 ₾\n\nთვეში: 2 ₾ -დან\n\nRivacase 8335 Laptop Bag 15 Black\nდამატება\n229 ₾\n\nთვეში: 6 ₾ -დან\n\nRazer Gaming Mouse Basilisk V3 X HyperSpeed WL Black\nდამატება\n39 ₾\n\nთვეში: 1 ₾ -დან\n\nRazer Mouse Pad Sphex V3 S Black\nდამატება\n79 ₾\n\nთვეში: 2 ₾ -დან\n\nRivacase 8335 Laptop Bag 15 Star blue\nდამატება\n129 ₾\n\nთვეში: 3 ₾ -დან\n\nRazer Gaming Mouse Cobra Black\nდამატება\n89 ₾\n\nთვეში: 2 ₾ -დან\n\nRazer Mouse Pad Sphex V3 L Black\nდამატება\n69 ₾\n\nთვეში: 1 ₾ -დან\n\nRivacase 7730 Eco Laptop Shoulder Bag 15 Black\nდამატება\n19 ₾\n\nHavit Gaming Mouse HV-MS989GT Black/Red\nდამატება\n29 ₾\n\nHavit Gaming mouse Pad HV-MP860\nდამატება\n59 ₾\n\nთვეში: 1 ₾ -დან\n\nRivacase 8035 Laptop Shoulder Bag 15\nდამატება\n19 ₾\n\nHavit Gaming Mouse HV-MS626GT Black\nდამატება\n79 ₾\n\nთვეში: 2 ₾ -დან\n\nTomtoc Defender A13 Laptop Sleeve 15 A13E3D1 Black\nდამატება\n19 ₾\n\nHavit Gaming Mouse HV-MS66GT White/Blue\nდამატება\n119 ₾\n\nთვეში: 3 ₾ -დან\n\nTomtoc Defender A42 Laptop Briefcase 15 A42E1D1 Black\nდამატება\n149 ₾\n\nთვეში: 4 ₾ -დან\n\nHyperX Gaming Mouse Pulsefire Haste 2 Black\nდამატება\n119 ₾\n\nთვეში: 3 ₾ -დან\n\nTomtoc Defender A42 Laptop Briefcase 15 A42E1B1 Navy ...\nდამატება\n19 ₾\n\nHavit Wireless Mouse HV-MS66GT Black\nდამატება\n79 ₾\n\nთვეში: 2 ₾ -დან\n\nHP Campus backpack 15.6 7J595AA Green\nდამატება\n179 ₾\n\nთვეში: 4 ₾ -დან\n\nLogitech Gaming Mouse G305 LIGHTSPEED WL L910-005282 ...\nდამატება\n79 ₾\n\nთვეში: 2 ₾ -დან\n\nHP Campus backpack 15.6 7J597AA Lavender\nდამატება\n259 ₾\n\nთვეში: 7 ₾ -დან\n\nLogitech Gaming Mouse G502 X L910-006138 Black\nდამატება\n69 ₾\n\nთვეში: 1 ₾ -დან\n\nRivacase 8065 Laptop Backpack 15 Black\nდამატება\n259 ₾\n\nთვეში: 7 ₾ -დან\n\nLogitech Gaming Mouse G502 X L910-006138 White\nდამატება\n69 ₾\n\nთვეში: 1 ₾ -დან\n\nRivacase 8065 Laptop Backpack 15 Dark Blue\nდამატება\n19 ₾\n\nHavit Gaming Mouse HV-MS626GT Black/Red\nდამატება\n79 ₾\n\nთვეში: 2 ₾ -დან\n\nTomtoc Defender A13 Laptop Sleeve 15 A13E3P1 Pink\nდამატება\n19 ₾\n\nHavit Gaming Mouse HV-MS626GT Black/Blue\nდამატება\n79 ₾\n\nთვეში: 2 ₾ -დან\n\nTomtoc Defender A13 Laptop Sleeve 15 A13E3T1 Green\nდამატება\n349 ₾\n\nთვეში: 9 ₾ -დან\n\nLogitech Gaming Mouse G703 LIGHTSPEED WL L910-005640 ...\nდამატება\n79 ₾\n\nთვეში: 2 ₾ -დან\n\nTomtoc Defender A13 Laptop Sleeve Kit 15 A13E3GV Grey\nდამატება\n89 ₾\n\nთვეში: 2 ₾ -დან\n\nLogitech Gaming Mouse G102 LIGHTSYNC L910-005823 Blac ...\nდამატება\n79 ₾\n\nთვეში: 2 ₾ -დან\n\nRivacase 8335 Laptop Bag 15 Purple\nდამატება\n89 ₾\n\nთვეში: 2 ₾ -დან\n\nLogitech Gaming Mouse G102 LIGHTSYNC L910-005824 Whit ...\nდამატება\n89 ₾\n\nთვეში: 2 ₾ -დან\n\nLogitech Gaming Mouse G102 LIGHTSYNC L910-005801 Blue\nდამატება\n239 ₾\n\nთვეში: 6 ₾ -დან\n\nLogitech Gaming Mouse G502 HERO L910-005470 Black\nდამატება\n199 ₾\n\nთვეში: 5 ₾ -დან\n\nHyperX Pulsefire Haste 2 core Wireless Black\nდამატება\n199 ₾\n\nთვეში: 5 ₾ -დან\n\nHyperX Pulsefire Haste 2 core Wireless White\nდამატება\n59 ₾\n\nთვეში: 1 ₾ -დან\n\nHavit Gaming Mouse HV-MS954 Black\nდამატება\n39 ₾\n\nთვეში: 1 ₾ -დან\n\nHavit Gaming Mouse HV-MS1033 White\nდამატება\n39 ₾\n\nთვეში: 1 ₾ -დან\n\nHavit Gaming Mouse HV-MS1029 Pink\nდამატება\n59 ₾\n\nთვეში: 1 ₾ -დან\n\nHavit Gaming Mouse HV-MS966 Black/Green\nდამატება\n49 ₾\n\nთვეში: 1 ₾ -დან\n\nHavit Wireless Mouse HV-MS1039W Black/White\nდამატება\n79 ₾\n\nთვეში: 2 ₾ -დან\n\nHavit Wireless Mouse HV-MS970WB Pro Black\nდამატება\n79 ₾\n\nთვეში: 2 ₾ -დან\n\nHavit Wireless Mouse HV-MS970WB Pro Transparent White\nდამატება\n219 ₾\n\nთვეში: 6 ₾ -დან\n\nRazer Gaming Mouse Orochi V2 WL Pink\nდამატება\nპროდუქტის შესახებ\n\nთუ ეძებთ ლეპტოპს, რომელიც მარტივად გაუმკლავდება ყველაზე მოთხოვნად თამაშებს — MSI Sword 16 9S7-15P214-886 შექმნილია სწორედ თქვენთვის. ეს მოდელი აერთიანებს მაღალ წარმადობას, გამძლე კონსტრუქციასა და თვ...\n\nმეტის ნახვა\nმსგავსი პროდუქტები\n2599 ₾\n2999 ₾\n\nთვეში: 72 ₾ -დან\n\nMSI Thin A15 B7UC 9S7-16RK11-211, AMD Ryzen 7, Nvidia ...\nდამატება\n5599 ₾\n5999 ₾\n\nთვეში: 155 ₾ -დან\n\nMSI Sword 16 HX B14VGKG 9S7-15P214-262, Intel core i7 ...\nდამატება\n3299 ₾\n3499 ₾\n\nთვეში: 91 ₾ -დან\n\nMSI Thin 15 9S7-16R831-2003 Black\nდამატება\n4499 ₾\n5199 ₾\n\nთვეში: 124 ₾ -დან\n\nMSI Sword 16 HX B14VFKG 9S7-15P214-669, Intel Core i7 ...\nდამატება\n5199 ₾\n5499 ₾\n\nთვეში: 144 ₾ -დან\n\nMSI Crosshair 16 HX D14VFKG 9S7-15P231-670, Intel Cor ...\nდამატება\n2449 ₾\n2549 ₾\n\nთვეში: 68 ₾ -დან\n\nMSI Thin 15 9S7-16R831-2681, Intel Core i5-12450H, Nv ...\nდამატება\n3399 ₾\n3699 ₾\n\nთვეში: 94 ₾ -დან\n\nMSI Katana 15 9S7-158571-2222, Intel Core i5-13420H, ...\nდამატება\n5399 ₾\n5999 ₾\n\nთვეში: 149 ₾ -დან\n\nMSI Crosshair 17 9S7-17T223-270, Intel Core i7-14700H ...\nდამატება\n3999 ₾\n4299 ₾\n\nთვეში: 111 ₾ -დან\n\nMSI Katana 15 9S7-158571-2279, Intel Core i7-13620H, ...\nდამატება\n2599 ₾\n\nთვეში: 72 ₾ -დან\n\nMSI Thin A15 B7UC 9S7-16RK11-601 Black\nდამატება\n2599 ₾\n2799 ₾\n\nთვეში: 72 ₾ -დან\n\nMSI Thin A15 B7UC 9S7-16RK11-602 Black\nდამატება\n2999 ₾\n3199 ₾\n\nთვეში: 83 ₾ -დან\n\nMSI Thin A15 B7VE 9S7-16RK11-603 Black\nდამატება\n3399 ₾\n\nთვეში: 94 ₾ -დან\n\nMSI Thin A15 B7VE 9S7-16RK11-604 Black\nდამატება\nდამატებითი მახასიათებლები\nბრენდი\nბრენდი:\n\t\nMSI\nმოდელი\nმოდელი:\n\t\nSword\nტექნიკური მახასიათებლები\nცენტრალური პროცესორი:\n\t\nIntel Core i7-14650HX\n\n\nპროცესორის თაობა:\n\t\nIntel i7 14th Gen\n\n\nპროცესორის სიხშირე:\n\t\n3.7 GHz ~ 5.2 GHz\n\n\nბირთვების რაოდენობა:\n\t\n16\n\n\nნაკადების რაოდენობა:\n\t\n24\n\n\nგრაფიკული პროცესორი:\n\t\nNvidia GeForce RTX 4060\n\n\nგრაფიკული პროცესორის მეხსიერება:\n\t\n8 GB\n\n\nგრაფიკული პროცესორის ტიპი:\n\t\nარა ინტეგრირებული\n\n\nოპერაციული სისტემა:\n\t\nNo\n\n\nBluetooth:\n\t\nYes\nეკრანი\nეკრანის ზომა:\n\t\n16 Inches\n\n\nრეზოლუცია:\n\t\nFull HD\n\n\nეკრანის ტიპი:\n\t\nIPS\n\n\nსენსორული ეკრანი:\n\t\nNo\n\n\nგანახლების სიხშირე:\n\t\n144 Hz\nდამატებითი მახასიათებლები\nკლავიატურის განათება:\n\t\nYes\n\n\nNumpad:\n\t\nYes\n\n\nდისკის წამკითხველი:\n\t\nNo\n\n\nვებ კამერა:\n\t\nYes\n\n\nლეპტოპის ტიპი:\n\t\nგეიმინგი\nმეხსიერება\nშიდა მეხსიერება:\n\t\n1 TB\n\n\nშიდა მეხსიერების ტიპი:\n\t\nSSD\n\n\nშიდა მეხსიერების ინტერფეისი:\n\t\nM.2\n\n\nოპერატიული მეხსიერება:\n\t\n16 GB\n\n\nოპერატიული მეხსიერების ტიპი:\n\t\nDDR5\n\n\nოპერატიული მეხსიერების სიხშირე:\n\t\n-\nპორტები\nUSB:\n\t\n3 x USB-A\n\n\nType-C:\n\t\n1x\n\n\nType-C პორტით დამუხტვა:\n\t\nNo\n\n\nHDMI:\n\t\nYes\n\n\nლან პორტი:\n\t\nYes\n\n\n3.5mm:\n\t\nYes\nზომა/წონა\nწონა:\n\t\n2.6 kg\nფერი\nფერი:\n\t\nBlack\nმეტის ნახვა\nგაეცანი საგარანტიო პირობებს\nსაგარანტიო პირობები\nფილიალები\nმარაგშია\nშეკვეთიდან 2-5 დღეში\nზუმერის წერეთლის ფილიალი\n\nთბილისი - წერეთლის გამზირი, N1.\n\nმარაგშია\n+995 591 967 601\nორშ-შაბ: 10:00:00 - 20:00:00\nკვირა: 10:00:00 - 19:00:00\nზუმერის City Mall საბურთალო-ს ფილიალი\n\nთბილისი - \"სითი მოლი\" - პეტრე ქავთარაძის N1\n\nმარაგშია\n+995 591 971 962\nორშ-შაბ: 10:00:00 - 22:00:00\nკვირა: 10:00:00 - 22:00:00\n4499 ₾\n4899 ₾\n\nთვეში: 125.0 ₾ -დან\n\nმარაგი ფილიალებში\nფასის დაზღვევა\nფასის კონტროლი\nფასის დაჯავშნა\nყიდვა\nშედარება\nდამატება\nნავიგაცია\n\nპერსონალურ მონაცემთა დაცვის პოლიტიკა\n\nჩვენ შესახებ\n\nწესები და პირობები\n\nმიწოდების სერვისი\n\nკარიერა\n\nგადახდები\n\nSetanta Sports\n\nგადახდის მეთოდები\n\nგარანტია\n\nგანვადება\n\nნივთის დაბრუნება\n\nნივთის ონლაინ ყიდვის ინსტრუქცია\n\nგამოგვყევი\n\nFacebook\n\nYoutube\n\nInstagram\n\nTik Tok\n\nკონტაქტი\n\nInfo@zoommer.ge\n\n+995 (32) 2 60 30 60 / *7007\n\nფილიალები\n\nკორპორატიული გაყიდვები\n\nZoommer App\n\nCopyright © 2023 Zoommer.ge. All rights reserved.\n\nCookie პოლიტიკა\n\nსაიტით სარგებლობის გაგრძელებით, შენ ეთანხმები Cookie ჩანაწერების გამოყენებას. მეტი ინფორმაცისათვის იხილეთ კონფიდენციალურობის პოლიტიკა\n\nგასაგებია",
    "specs": {
      "ბრენდი:": "MSI",
      "მოდელი:": "Sword",
      "ცენტრალური პროცესორი:": "Intel Core i7-14650HX",
      "პროცესორის თაობა:": "Intel i7 14th Gen",
      "პროცესორის სიხშირე:": "3.7 GHz ~ 5.2 GHz",
      "ბირთვების რაოდენობა:": "16",
      "ნაკადების რაოდენობა:": "24",
      "გრაფიკული პროცესორი:": "Nvidia GeForce RTX 4060",
      "გრაფიკული პროცესორის მეხსიერება:": "8 GB",
      "გრაფიკული პროცესორის ტიპი:": "არა ინტეგრირებული",
      "ოპერაციული სისტემა:": "No",
      "Bluetooth:": "Yes",
      "ეკრანის ზომა:": "16 Inches",
      "რეზოლუცია:": "Full HD",
      "ეკრანის ტიპი:": "IPS",
      "სენსორული ეკრანი:": "No",
      "განახლების სიხშირე:": "144 Hz",
      "კლავიატურის განათება:": "Yes",
      "Numpad:": "Yes",
      "დისკის წამკითხველი:": "No",
      "ვებ კამერა:": "Yes",
      "ლეპტოპის ტიპი:": "გეიმინგი",
      "შიდა მეხსიერება:": "1 TB",
      "შიდა მეხსიერების ტიპი:": "SSD",
      "შიდა მეხსიერების ინტერფეისი:": "M.2",
      "ოპერატიული მეხსიერება:": "16 GB",
      "ოპერატიული მეხსიერების ტიპი:": "DDR5",
      "ოპერატიული მეხსიერების სიხშირე:": "-",
      "USB:": "3 x USB-A",
      "Type-C:": "1x",
      "Type-C პორტით დამუხტვა:": "No",
      "HDMI:": "Yes",
      "ლან პორტი:": "Yes",
      "3.5mm:": "Yes",
      "წონა:": "2.6 kg",
      "ფერი:": "Black"
    }
  },
  {
    "category": "Gaming ლეპტოპები",
    "title": "MSI Katana 15 9S7-158571-2279, Intel Core i7-13620H, ...",
    "price": 3999.0,
    "link": "https://zoommer.ge/leptopebi/msi-katana-15-9s7-158571-2279-intel-core-i7-13620h-nvidia-geforce-rtx-4060-8gb-p46012",
    "image": "/_next/image?url=https%3A%2F%2Fs3.zoommer.ge%2Fsite%2F6e3acd24-94ef-4fa3-85cc-3164dce8f284_Thumb.jpeg&w=384&q=50",
    "product_title_detail": "MSI Katana 15 9S7-158571-2279, Intel Core i7-13620H, Nvidia GeForce RTX 4060 8GB, 16GB RAM SSD 1TB, Free Dos, ლეპტოპი",
    "description": "*7007 / +995 (32) 2 60 30 60\nფილიალები\nნავიგაცია\nკალათა\nშესვლა\n%\nმთავარი\nლეპტოპები\nMSI\n#ZOOM-035609\nMSI Katana 15 9S7-158571-2279, Intel Core i7-13620H, Nvidia GeForce RTX 4060 8GB, 16GB RAM SSD 1TB, Free Dos, ლეპტოპი\nეკრანის ზომა\n15.6 Inches\nრეზოლუცია\nFull HD\nეკრანის ტიპი\nIPS\nგანახლების სიხშირე\n144 Hz\nშიდა მეხსიერება\n1 TB\nBluetooth\nYes\nType-C\n1x\nოპერატიული მეხსიერება\n16 GB\nერთად იაფია\nდაამატე ნივთი\nMSI Katana 15 9S7-158571-2279, Intel Core i7-13620H, Nvidia GeForce RTX 4060 8GB, 16GB RAM SSD 1TB, Free Dos, ლეპტოპი\n3999 ₾\nRivacase 7562 Anti-Theft Laptop Backpack 15 Grey/Dark blue\n67.15 ₾\n79 ₾\nRazer Gaming Mouse DeathAdder Essential USB White\n52 ₾\n65 ₾\nHavit Gaming Cooling Pad HV-F2083 Black\n75.65 ₾\n89 ₾\nჯამური ფასი (3)\n4193.8 ₾\n4232 ₾\nყიდვა\nაქსესუარები\nაღწერა\nმსგავსი\nმახასიათებლები\nფილიალები\nაქსესუარები\nაღწერა\nმსგავსი\nმახასიათებლები\nფილიალები\n89 ₾\n\nთვეში: 2 ₾ -დან\n\nHavit Gaming Cooling Pad HV-F2083 Black\nდამატება\n39 ₾\n\nთვეში: 1 ₾ -დან\n\nLenovo Casual Backpack B210 Green\nდამატება\n219 ₾\n\nთვეში: 6 ₾ -დან\n\nRazer Gaming Mouse Orochi V2 WL Black\nდამატება\n69 ₾\n\nთვეში: 1 ₾ -დან\n\nXiaomi Mi Router 4A DVB4230GL White\nდამატება\n129 ₾\n\nთვეში: 3 ₾ -დან\n\nRivacase 7930 Pro 16\nდამატება\n219 ₾\n\nთვეში: 6 ₾ -დან\n\nRazer Gaming Mouse Orochi V2 WL White\nდამატება\n85 ₾\n\nთვეში: 2 ₾ -დან\n\nTP-Link Archer C50 AC1200 White\nდამატება\n59 ₾\n\nთვეში: 1 ₾ -დან\n\nRivacese 8035 Laptop Shoulder Bag 15 Black\nდამატება\n209 ₾\n\nთვეში: 5 ₾ -დან\n\nRazer Gaming Mouse DeathAdder V2 X Hyperspeed WL/BT/U ...\nდამატება\n119 ₾\n\nთვეში: 3 ₾ -დან\n\nTP-Link Archer C6 AC1200 Black\nდამატება\n59 ₾\n\nთვეში: 1 ₾ -დან\n\nRivacase 8037 Laptop Bag 15 Black\nდამატება\n139 ₾\n\nთვეში: 3 ₾ -დან\n\nLogitech Gaming Mouse G402 Hyperion Fury black\nდამატება\n159 ₾\n\nთვეში: 4 ₾ -დან\n\nXiaomi Router AX1500 White\nდამატება\n79 ₾\n\nთვეში: 2 ₾ -დან\n\nRivacase 7562 Anti-Theft Laptop Backpack 15 Black\nდამატება\n29 ₾\n\nHavit Gaming Mouse HV-MS1010 Black\nდამატება\n179 ₾\n\nთვეში: 4 ₾ -დან\n\nXiaomi Mesh System AX3000 NE 1 pack White\nდამატება\n79 ₾\n\nთვეში: 2 ₾ -დან\n\nRivacase 7562 Anti-Theft Laptop Backpack 15 Dark grey\nდამატება\n79 ₾\n\nთვეში: 2 ₾ -დან\n\nRazer Gaming Mouse DeathAdder Essential USB Black\nდამატება\n299 ₾\n\nთვეში: 8 ₾ -დან\n\nXiaomi Mesh System AX3000 NE 2 pack White\nდამატება\n79 ₾\n\nთვეში: 2 ₾ -დან\n\nRivacase 7562 Anti-Theft Laptop Backpack 15 Grey/Dark ...\nდამატება\n119 ₾\n\nთვეში: 3 ₾ -დან\n\nHyperX Pulsefire Surge Mouse Black\nდამატება\n249 ₾\n\nთვეში: 6 ₾ -დან\n\nXiaomi Router BE3600 White\nდამატება\n69 ₾\n\nთვეში: 1 ₾ -დან\n\nRivacase 7532 Anti-Theft Laptop Bag 15 Dark Grey\nდამატება\n469 ₾\n\nთვეში: 13 ₾ -დან\n\nHP OMEN PHOTON Wireless Mouse 6CL96AA Black\nდამატება\n69 ₾\n\nთვეში: 1 ₾ -დან\n\nRivacase 7532 Anti-Theft Laptop Bag 15 Grey/Dark Blue ...\nდამატება\n65 ₾\n\nთვეში: 1 ₾ -დან\n\nRazer Gaming Mouse DeathAdder Essential USB White\nდამატება\n79 ₾\n\nთვეში: 2 ₾ -დან\n\nRivacase 8231 Laptop Bag 15 Black\nდამატება\n239 ₾\n\nთვეში: 6 ₾ -დან\n\nRazer Gaming Mouse Basilisk V3 Black\nდამატება\n79 ₾\n\nთვეში: 2 ₾ -დან\n\nRivacase 8231 Laptop Bag 15 Star blue\nდამატება\n299 ₾\n\nთვეში: 8 ₾ -დან\n\nRazer Gaming Mouse Naga V2 HyperSpeed WL Black\nდამატება\n79 ₾\n\nთვეში: 2 ₾ -დან\n\nRivacase 8335 Laptop Bag 15 Black\nდამატება\n229 ₾\n\nთვეში: 6 ₾ -დან\n\nRazer Gaming Mouse Basilisk V3 X HyperSpeed WL Black\nდამატება\n79 ₾\n\nთვეში: 2 ₾ -დან\n\nRivacase 8335 Laptop Bag 15 Star blue\nდამატება\n129 ₾\n\nთვეში: 3 ₾ -დან\n\nRazer Gaming Mouse Cobra Black\nდამატება\n69 ₾\n\nთვეში: 1 ₾ -დან\n\nRivacase 7730 Eco Laptop Shoulder Bag 15 Black\nდამატება\n19 ₾\n\nHavit Gaming Mouse HV-MS989GT Black/Red\nდამატება\n59 ₾\n\nთვეში: 1 ₾ -დან\n\nRivacase 8035 Laptop Shoulder Bag 15\nდამატება\n19 ₾\n\nHavit Gaming Mouse HV-MS626GT Black\nდამატება\n79 ₾\n\nთვეში: 2 ₾ -დან\n\nTomtoc Defender A13 Laptop Sleeve 15 A13E3D1 Black\nდამატება\n19 ₾\n\nHavit Gaming Mouse HV-MS66GT White/Blue\nდამატება\n119 ₾\n\nთვეში: 3 ₾ -დან\n\nTomtoc Defender A42 Laptop Briefcase 15 A42E1D1 Black\nდამატება\n149 ₾\n\nთვეში: 4 ₾ -დან\n\nHyperX Gaming Mouse Pulsefire Haste 2 Black\nდამატება\n79 ₾\n\nთვეში: 2 ₾ -დან\n\nHP Campus backpack 15.6 7J595AA Green\nდამატება\n19 ₾\n\nHavit Wireless Mouse HV-MS66GT Black\nდამატება\n79 ₾\n\nთვეში: 2 ₾ -დან\n\nHP Campus backpack 15.6 7J597AA Lavender\nდამატება\n179 ₾\n\nთვეში: 4 ₾ -დან\n\nLogitech Gaming Mouse G305 LIGHTSPEED WL L910-005282 ...\nდამატება\n69 ₾\n\nთვეში: 1 ₾ -დან\n\nRivacase 8065 Laptop Backpack 15 Black\nდამატება\n259 ₾\n\nთვეში: 7 ₾ -დან\n\nLogitech Gaming Mouse G502 X L910-006138 Black\nდამატება\n69 ₾\n\nთვეში: 1 ₾ -დან\n\nRivacase 8065 Laptop Backpack 15 Dark Blue\nდამატება\n259 ₾\n\nთვეში: 7 ₾ -დან\n\nLogitech Gaming Mouse G502 X L910-006138 White\nდამატება\n79 ₾\n\nთვეში: 2 ₾ -დან\n\nRivacase 8335 Laptop Bag 15 Purple\nდამატება\n19 ₾\n\nHavit Gaming Mouse HV-MS626GT Black/Red\nდამატება\n19 ₾\n\nHavit Gaming Mouse HV-MS626GT Black/Blue\nდამატება\n349 ₾\n\nთვეში: 9 ₾ -დან\n\nLogitech Gaming Mouse G703 LIGHTSPEED WL L910-005640 ...\nდამატება\n89 ₾\n\nთვეში: 2 ₾ -დან\n\nLogitech Gaming Mouse G102 LIGHTSYNC L910-005823 Blac ...\nდამატება\n89 ₾\n\nთვეში: 2 ₾ -დან\n\nLogitech Gaming Mouse G102 LIGHTSYNC L910-005824 Whit ...\nდამატება\n89 ₾\n\nთვეში: 2 ₾ -დან\n\nLogitech Gaming Mouse G102 LIGHTSYNC L910-005801 Blue\nდამატება\n239 ₾\n\nთვეში: 6 ₾ -დან\n\nLogitech Gaming Mouse G502 HERO L910-005470 Black\nდამატება\n199 ₾\n\nთვეში: 5 ₾ -დან\n\nHyperX Pulsefire Haste 2 core Wireless Black\nდამატება\n199 ₾\n\nთვეში: 5 ₾ -დან\n\nHyperX Pulsefire Haste 2 core Wireless White\nდამატება\n59 ₾\n\nთვეში: 1 ₾ -დან\n\nHavit Gaming Mouse HV-MS954 Black\nდამატება\n39 ₾\n\nთვეში: 1 ₾ -დან\n\nHavit Gaming Mouse HV-MS1033 White\nდამატება\n39 ₾\n\nთვეში: 1 ₾ -დან\n\nHavit Gaming Mouse HV-MS1029 Pink\nდამატება\n59 ₾\n\nთვეში: 1 ₾ -დან\n\nHavit Gaming Mouse HV-MS966 Black/Green\nდამატება\n49 ₾\n\nთვეში: 1 ₾ -დან\n\nHavit Wireless Mouse HV-MS1039W Black/White\nდამატება\n79 ₾\n\nთვეში: 2 ₾ -დან\n\nHavit Wireless Mouse HV-MS970WB Pro Black\nდამატება\n79 ₾\n\nთვეში: 2 ₾ -დან\n\nHavit Wireless Mouse HV-MS970WB Pro Transparent White\nდამატება\n219 ₾\n\nთვეში: 6 ₾ -დან\n\nRazer Gaming Mouse Orochi V2 WL Pink\nდამატება\nპროდუქტის შესახებ\n\nთუ ეძებთ ლეპტოპს, რომელიც მარტივად გაუმკლავდება ყველაზე მოთხოვნად თამაშებს — MSI Katana 15 9S7-158571-2279 შექმნილია სწორედ თქვენთვის. ეს მოდელი აერთიანებს მაღალ წარმადობას, გამძლე კონსტრუქციასა და ...\n\nმეტის ნახვა\nმსგავსი პროდუქტები\n2599 ₾\n2999 ₾\n\nთვეში: 72 ₾ -დან\n\nMSI Thin A15 B7UC 9S7-16RK11-211, AMD Ryzen 7, Nvidia ...\nდამატება\n5599 ₾\n5999 ₾\n\nთვეში: 155 ₾ -დან\n\nMSI Sword 16 HX B14VGKG 9S7-15P214-262, Intel core i7 ...\nდამატება\n3299 ₾\n3499 ₾\n\nთვეში: 91 ₾ -დან\n\nMSI Thin 15 9S7-16R831-2003 Black\nდამატება\n4499 ₾\n5199 ₾\n\nთვეში: 124 ₾ -დან\n\nMSI Sword 16 HX B14VFKG 9S7-15P214-669, Intel Core i7 ...\nდამატება\n5199 ₾\n5499 ₾\n\nთვეში: 144 ₾ -დან\n\nMSI Crosshair 16 HX D14VFKG 9S7-15P231-670, Intel Cor ...\nდამატება\n2449 ₾\n2549 ₾\n\nთვეში: 68 ₾ -დან\n\nMSI Thin 15 9S7-16R831-2681, Intel Core i5-12450H, Nv ...\nდამატება\n3399 ₾\n3699 ₾\n\nთვეში: 94 ₾ -დან\n\nMSI Katana 15 9S7-158571-2222, Intel Core i5-13420H, ...\nდამატება\n5399 ₾\n5999 ₾\n\nთვეში: 149 ₾ -დან\n\nMSI Crosshair 17 9S7-17T223-270, Intel Core i7-14700H ...\nდამატება\n4499 ₾\n4899 ₾\n\nთვეში: 124 ₾ -დან\n\nMSI Sword 16 9S7-15P214-886, Intel Core i7-14650HX, N ...\nდამატება\n2599 ₾\n\nთვეში: 72 ₾ -დან\n\nMSI Thin A15 B7UC 9S7-16RK11-601 Black\nდამატება\n2599 ₾\n2799 ₾\n\nთვეში: 72 ₾ -დან\n\nMSI Thin A15 B7UC 9S7-16RK11-602 Black\nდამატება\n2999 ₾\n3199 ₾\n\nთვეში: 83 ₾ -დან\n\nMSI Thin A15 B7VE 9S7-16RK11-603 Black\nდამატება\n3399 ₾\n\nთვეში: 94 ₾ -დან\n\nMSI Thin A15 B7VE 9S7-16RK11-604 Black\nდამატება\nდამატებითი მახასიათებლები\nბრენდი\nბრენდი:\n\t\nMSI\nმოდელი\nმოდელი:\n\t\nKatana\nტექნიკური მახასიათებლები\nცენტრალური პროცესორი:\n\t\nIntel Core i7-13620H\n\n\nპროცესორის თაობა:\n\t\nIntel i7 13th Gen\n\n\nპროცესორის სიხშირე:\n\t\n3.6 GHz ~ 4.9 GHz\n\n\nბირთვების რაოდენობა:\n\t\n10\n\n\nნაკადების რაოდენობა:\n\t\n16\n\n\nგრაფიკული პროცესორი:\n\t\nNvidia GeForce RTX 4060\n\n\nგრაფიკული პროცესორის მეხსიერება:\n\t\n8 GB\n\n\nგრაფიკული პროცესორის ტიპი:\n\t\nარა ინტეგრირებული\n\n\nოპერაციული სისტემა:\n\t\nNo\n\n\nBluetooth:\n\t\nYes\nეკრანი\nეკრანის ზომა:\n\t\n15.6 Inches\n\n\nრეზოლუცია:\n\t\nFull HD\n\n\nეკრანის ტიპი:\n\t\nIPS\n\n\nსენსორული ეკრანი:\n\t\nNo\n\n\nგანახლების სიხშირე:\n\t\n144 Hz\nდამატებითი მახასიათებლები\nკლავიატურის განათება:\n\t\nYes\n\n\nNumpad:\n\t\nYes\n\n\nდისკის წამკითხველი:\n\t\nNo\n\n\nვებ კამერა:\n\t\nYes\n\n\nლეპტოპის ტიპი:\n\t\nგეიმინგი\nმეხსიერება\nშიდა მეხსიერება:\n\t\n1 TB\n\n\nშიდა მეხსიერების ტიპი:\n\t\nSSD\n\n\nშიდა მეხსიერების ინტერფეისი:\n\t\nM.2\n\n\nოპერატიული მეხსიერება:\n\t\n16 GB\n\n\nოპერატიული მეხსიერების ტიპი:\n\t\nDDR5\n\n\nოპერატიული მეხსიერების სიხშირე:\n\t\n-\nპორტები\nUSB:\n\t\n3 x USB-A\n\n\nType-C:\n\t\n1x\n\n\nType-C პორტით დამუხტვა:\n\t\nNo\n\n\nHDMI:\n\t\nYes\n\n\nლან პორტი:\n\t\nYes\n\n\n3.5mm:\n\t\nYes\nზომა/წონა\nწონა:\n\t\n2.5 kg\nფერი\nფერი:\n\t\nBlack\nმეტის ნახვა\nგაეცანი საგარანტიო პირობებს\nსაგარანტიო პირობები\nფილიალები\nმარაგშია\nშეკვეთიდან 2-5 დღეში\nზუმერის თბილისი მოლის ფილიალი\n\nთბილისი - „თბილისი მოლი\" - I სართული. აღმაშენებლის ხეივანი მე-16 კმ\n\nმარაგშია\n+995 591 967 608\nორშ-შაბ: 10:00:00 - 22:00:00\nკვირა: 10:00:00 - 22:00:00\n3999 ₾\n4299 ₾\n\nთვეში: 111.1 ₾ -დან\n\nმარაგი ფილიალებში\nფასის დაზღვევა\nფასის კონტროლი\nფასის დაჯავშნა\nყიდვა\nშედარება\nდამატება\nნავიგაცია\nგადახდები\nგამოგვყევი\n\nFacebook\n\nYoutube\n\nInstagram\n\nTik Tok\n\nკონტაქტი\n\nInfo@zoommer.ge\n\n+995 (32) 2 60 30 60 / *7007\n\nფილიალები\n\nკორპორატიული გაყიდვები\n\nZoommer App\n\nCopyright © 2023 Zoommer.ge. All rights reserved.\n\nCookie პოლიტიკა\n\nსაიტით სარგებლობის გაგრძელებით, შენ ეთანხმები Cookie ჩანაწერების გამოყენებას. მეტი ინფორმაცისათვის იხილეთ კონფიდენციალურობის პოლიტიკა\n\nგასაგებია",
    "specs": {
      "ბრენდი:": "MSI",
      "მოდელი:": "Katana",
      "ცენტრალური პროცესორი:": "Intel Core i7-13620H",
      "პროცესორის თაობა:": "Intel i7 13th Gen",
      "პროცესორის სიხშირე:": "3.6 GHz ~ 4.9 GHz",
      "ბირთვების რაოდენობა:": "10",
      "ნაკადების რაოდენობა:": "16",
      "გრაფიკული პროცესორი:": "Nvidia GeForce RTX 4060",
      "გრაფიკული პროცესორის მეხსიერება:": "8 GB",
      "გრაფიკული პროცესორის ტიპი:": "არა ინტეგრირებული",
      "ოპერაციული სისტემა:": "No",
      "Bluetooth:": "Yes",
      "ეკრანის ზომა:": "15.6 Inches",
      "რეზოლუცია:": "Full HD",
      "ეკრანის ტიპი:": "IPS",
      "სენსორული ეკრანი:": "No",
      "განახლების სიხშირე:": "144 Hz",
      "კლავიატურის განათება:": "Yes",
      "Numpad:": "Yes",
      "დისკის წამკითხველი:": "No",
      "ვებ კამერა:": "Yes",
      "ლეპტოპის ტიპი:": "გეიმინგი",
      "შიდა მეხსიერება:": "1 TB",
      "შიდა მეხსიერების ტიპი:": "SSD",
      "შიდა მეხსიერების ინტერფეისი:": "M.2",
      "ოპერატიული მეხსიერება:": "16 GB",
      "ოპერატიული მეხსიერების ტიპი:": "DDR5",
      "ოპერატიული მეხსიერების სიხშირე:": "-",
      "USB:": "3 x USB-A",
      "Type-C:": "1x",
      "Type-C პორტით დამუხტვა:": "No",
      "HDMI:": "Yes",
      "ლან პორტი:": "Yes",
      "3.5mm:": "Yes",
      "წონა:": "2.5 kg",
      "ფერი:": "Black"
    }
  },
  {
    "category": "Gaming ლეპტოპები",
    "title": "HP Victus 15 B09J6EA Blue",
    "price": 2799.0,
    "link": "https://zoommer.ge/leptopebi/hp-victus-15-b09j6ea-blue-p45793",
    "image": "/_next/image?url=https%3A%2F%2Fs3.zoommer.ge%2Fsite%2Fc19b29ac-0ee0-4ebd-8c93-58a597fc8072_Thumb.jpeg&w=384&q=50",
    "product_title_detail": "HP Victus 15 B09J6EA Blue",
    "description": "*7007 / +995 (32) 2 60 30 60\nსავაჭრო პოლიტიკა\nგანვადება\nკარიერა\nTrade In\nფილიალები\nნავიგაცია\nკალათა\nშესვლა\n%\nმთავარი\nლეპტოპები\nHP\n#ZOOM-035463\nHP Victus 15 B09J6EA Blue\nეკრანის ზომა\n15.6 inches\nრეზოლუცია\nFull HD\nეკრანის ტიპი\nIPS\nგანახლების სიხშირე\n144 Hz\nშიდა მეხსიერება\n512 GB\nBluetooth\nYes\nType-C\n-\nოპერატიული მეხსიერება\n16 GB\nერთად იაფია\nდაამატე ნივთი\nHP Victus 15 B09J6EA Blue\n2799 ₾\nRivacase 7562 Anti-Theft Laptop Backpack 15 Grey/Dark blue\n67.15 ₾\n79 ₾\nRazer Gaming Mouse DeathAdder Essential USB White\n52 ₾\n65 ₾\nHavit Gaming Cooling Pad HV-F2083 Black\n75.65 ₾\n89 ₾\nჯამური ფასი (3)\n2993.8 ₾\n3032 ₾\nყიდვა\nაქსესუარები\nაღწერა\nმსგავსი\nმახასიათებლები\nფილიალები\nაქსესუარები\nაღწერა\nმსგავსი\nმახასიათებლები\nფილიალები\n89 ₾\n\nთვეში: 2 ₾ -დან\n\nHavit Gaming Cooling Pad HV-F2083 Black\nდამატება\n79 ₾\n\nთვეში: 2 ₾ -დან\n\nLenovo 15.6 Laptop Backpack B510\nდამატება\n219 ₾\n\nთვეში: 6 ₾ -დან\n\nRazer Gaming Mouse Orochi V2 WL Black\nდამატება\n69 ₾\n\nთვეში: 1 ₾ -დან\n\nXiaomi Mi Router 4A DVB4230GL White\nდამატება\n39 ₾\n\nთვეში: 1 ₾ -დან\n\nLenovo T210 Casual Toploader 15.6 Black\nდამატება\n219 ₾\n\nთვეში: 6 ₾ -დან\n\nRazer Gaming Mouse Orochi V2 WL White\nდამატება\n85 ₾\n\nთვეში: 2 ₾ -დან\n\nTP-Link Archer C50 AC1200 White\nდამატება\n39 ₾\n\nთვეში: 1 ₾ -დან\n\nLenovo T210 Casual Toploader 15.6 Grey\nდამატება\n209 ₾\n\nთვეში: 5 ₾ -დან\n\nRazer Gaming Mouse DeathAdder V2 X Hyperspeed WL/BT/U ...\nდამატება\n119 ₾\n\nთვეში: 3 ₾ -დან\n\nTP-Link Archer C6 AC1200 Black\nდამატება\n89 ₾\n\nთვეში: 2 ₾ -დან\n\nAcer Starter Kit 15.6 Laptop Bag & Wireless Mouse\nდამატება\n139 ₾\n\nთვეში: 3 ₾ -დან\n\nLogitech Gaming Mouse G402 Hyperion Fury black\nდამატება\n159 ₾\n\nთვეში: 4 ₾ -დან\n\nXiaomi Router AX1500 White\nდამატება\n89 ₾\n\nთვეში: 2 ₾ -დან\n\nHP Prelude Pro 15.6 Backpack 4Z513AA Grey\nდამატება\n29 ₾\n\nHavit Gaming Mouse HV-MS1010 Black\nდამატება\n179 ₾\n\nთვეში: 4 ₾ -დან\n\nXiaomi Mesh System AX3000 NE 1 pack White\nდამატება\n69 ₾\n\nთვეში: 1 ₾ -დან\n\nHP Prelude Pro 15.6 Laptop bag 4Z514AA Grey\nდამატება\n79 ₾\n\nთვეში: 2 ₾ -დან\n\nRazer Gaming Mouse DeathAdder Essential USB Black\nდამატება\n299 ₾\n\nთვეში: 8 ₾ -დან\n\nXiaomi Mesh System AX3000 NE 2 pack White\nდამატება\n129 ₾\n\nთვეში: 3 ₾ -დან\n\nHP Renew Travel Backpack 2Z8A3AA Grey\nდამატება\n119 ₾\n\nთვეში: 3 ₾ -დან\n\nHyperX Pulsefire Surge Mouse Black\nდამატება\n249 ₾\n\nთვეში: 6 ₾ -დან\n\nXiaomi Router BE3600 White\nდამატება\n79 ₾\n\nთვეში: 2 ₾ -დან\n\nHP Travel Backpack 15 6B8U6AA Iron Grey\nდამატება\n469 ₾\n\nთვეში: 13 ₾ -დან\n\nHP OMEN PHOTON Wireless Mouse 6CL96AA Black\nდამატება\n89 ₾\n\nთვეში: 2 ₾ -დან\n\nXiaomi Commuter Backpack Dark Gray\nდამატება\n65 ₾\n\nთვეში: 1 ₾ -დან\n\nRazer Gaming Mouse DeathAdder Essential USB White\nდამატება\n89 ₾\n\nთვეში: 2 ₾ -დან\n\nXiaomi Commuter Backpack Light Blue\nდამატება\n239 ₾\n\nთვეში: 6 ₾ -დან\n\nRazer Gaming Mouse Basilisk V3 Black\nდამატება\n89 ₾\n\nთვეში: 2 ₾ -დან\n\nXiaomi Commuter Backpack Light Gray\nდამატება\n299 ₾\n\nთვეში: 8 ₾ -დან\n\nRazer Gaming Mouse Naga V2 HyperSpeed WL Black\nდამატება\n59 ₾\n\nთვეში: 1 ₾ -დან\n\nHP Prelude 15.6 2Z8P4AA Dark Grey\nდამატება\n229 ₾\n\nთვეში: 6 ₾ -დან\n\nRazer Gaming Mouse Basilisk V3 X HyperSpeed WL Black\nდამატება\n79 ₾\n\nთვეში: 2 ₾ -დან\n\nHP Prelude 15.6 2Z8P3AA Grey\nდამატება\n129 ₾\n\nთვეში: 3 ₾ -დან\n\nRazer Gaming Mouse Cobra Black\nდამატება\n55 ₾\n\nთვეში: 1 ₾ -დან\n\nHP Prelude 15.6 1E7D7AA Grey\nდამატება\n19 ₾\n\nHavit Gaming Mouse HV-MS989GT Black/Red\nდამატება\n59 ₾\n\nთვეში: 1 ₾ -დან\n\nHP 15 Sleeve 14V33AA Black\nდამატება\n19 ₾\n\nHavit Gaming Mouse HV-MS626GT Black\nდამატება\n39 ₾\n\nთვეში: 1 ₾ -დან\n\nLenovo Casual Backpack B210 Black\nდამატება\n19 ₾\n\nHavit Gaming Mouse HV-MS66GT White/Blue\nდამატება\n39 ₾\n\nთვეში: 1 ₾ -დან\n\nLenovo Casual Backpack B210 Blue\nდამატება\n149 ₾\n\nთვეში: 4 ₾ -დან\n\nHyperX Gaming Mouse Pulsefire Haste 2 Black\nდამატება\n39 ₾\n\nთვეში: 1 ₾ -დან\n\nLenovo Casual Backpack B210 Green\nდამატება\n19 ₾\n\nHavit Wireless Mouse HV-MS66GT Black\nდამატება\n39 ₾\n\nთვეში: 1 ₾ -დან\n\nLenovo Casual Backpack B210 Grey\nდამატება\n179 ₾\n\nთვეში: 4 ₾ -დან\n\nLogitech Gaming Mouse G305 LIGHTSPEED WL L910-005282 ...\nდამატება\n89 ₾\n\nთვეში: 2 ₾ -დან\n\nLenovo IdeaPad Gaming Backpack\nდამატება\n259 ₾\n\nთვეში: 7 ₾ -დან\n\nLogitech Gaming Mouse G502 X L910-006138 Black\nდამატება\n79 ₾\n\nთვეში: 2 ₾ -დან\n\nXiaomi Ninetygo Multitasker Commuting Backpack Grey\nდამატება\n259 ₾\n\nთვეში: 7 ₾ -დან\n\nLogitech Gaming Mouse G502 X L910-006138 White\nდამატება\n139 ₾\n\nთვეში: 3 ₾ -დან\n\nXiaomi Ninetygo Urban Daily Backpack Yellow\nდამატება\n19 ₾\n\nHavit Gaming Mouse HV-MS626GT Black/Red\nდამატება\n99 ₾\n\nთვეში: 2 ₾ -დან\n\nXiaomi Mi Business Backpack 2 Black\nდამატება\n19 ₾\n\nHavit Gaming Mouse HV-MS626GT Black/Blue\nდამატება\n99 ₾\n\nთვეში: 2 ₾ -დან\n\nXiaomi Mi Business Backpack 2 Dark Gray\nდამატება\n349 ₾\n\nთვეში: 9 ₾ -დან\n\nLogitech Gaming Mouse G703 LIGHTSPEED WL L910-005640 ...\nდამატება\n69 ₾\n\nთვეში: 1 ₾ -დან\n\nLenovo 15.6 Laptop Backpack B515 Black\nდამატება\n89 ₾\n\nთვეში: 2 ₾ -დან\n\nLogitech Gaming Mouse G102 LIGHTSYNC L910-005823 Blac ...\nდამატება\n69 ₾\n\nთვეში: 1 ₾ -დან\n\nLenovo 15.6 Laptop Backpack B515 Blue\nდამატება\n89 ₾\n\nთვეში: 2 ₾ -დან\n\nLogitech Gaming Mouse G102 LIGHTSYNC L910-005824 Whit ...\nდამატება\n69 ₾\n\nთვეში: 1 ₾ -დან\n\nLenovo 15.6 Laptop Backpack B515 Grey\nდამატება\n89 ₾\n\nთვეში: 2 ₾ -დან\n\nLogitech Gaming Mouse G102 LIGHTSYNC L910-005801 Blue\nდამატება\n69 ₾\n\nთვეში: 1 ₾ -დან\n\nHP Prelude Backpack 15.6 1E7D6AA Grey\nდამატება\n239 ₾\n\nთვეში: 6 ₾ -დან\n\nLogitech Gaming Mouse G502 HERO L910-005470 Black\nდამატება\n39 ₾\n\nთვეში: 1 ₾ -დან\n\nVivo Backpack YL16\nდამატება\n199 ₾\n\nთვეში: 5 ₾ -დან\n\nHyperX Pulsefire Haste 2 core Wireless Black\nდამატება\n89 ₾\n\nთვეში: 2 ₾ -დან\n\nAsus Shoulder Bag 15 Eos 2 Black\nდამატება\n199 ₾\n\nთვეში: 5 ₾ -დან\n\nHyperX Pulsefire Haste 2 core Wireless White\nდამატება\n89 ₾\n\nთვეში: 2 ₾ -დან\n\nAsus Shoulder Bag 15 Eos 2 Grey\nდამატება\n59 ₾\n\nთვეში: 1 ₾ -დან\n\nHavit Gaming Mouse HV-MS954 Black\nდამატება\n59 ₾\n\nთვეში: 1 ₾ -დან\n\nAcer Urban Backpack 15.6 GP.BAG11.034 Grey\nდამატება\n39 ₾\n\nთვეში: 1 ₾ -დან\n\nHavit Gaming Mouse HV-MS1033 White\nდამატება\n59 ₾\n\nთვეში: 1 ₾ -დან\n\nAcer Nitro Gaming Urban Backpack 15.6 GP.BAG11.02E Bl ...\nდამატება\n39 ₾\n\nთვეში: 1 ₾ -დან\n\nHavit Gaming Mouse HV-MS1029 Pink\nდამატება\n129 ₾\n\nთვეში: 3 ₾ -დან\n\nHP Travel Backpack 15 6B8U4AA Iron Grey\nდამატება\n59 ₾\n\nთვეში: 1 ₾ -დან\n\nHavit Gaming Mouse HV-MS966 Black/Green\nდამატება\n179 ₾\n\nთვეში: 4 ₾ -დან\n\nXiaomi Ninetygo Urban E-Using Plus Shoulder Bag Black\nდამატება\n49 ₾\n\nთვეში: 1 ₾ -დან\n\nHavit Wireless Mouse HV-MS1039W Black/White\nდამატება\n139 ₾\n\nთვეში: 3 ₾ -დან\n\nXiaomi Ninetygo Urban Multifunctional commuting backp ...\nდამატება\n79 ₾\n\nთვეში: 2 ₾ -დან\n\nHavit Wireless Mouse HV-MS970WB Pro Black\nდამატება\n179 ₾\n\nთვეში: 4 ₾ -დან\n\nXiaomi Ninetygo Urban E-Using Plus Shoulder Bag White\nდამატება\n79 ₾\n\nთვეში: 2 ₾ -დან\n\nHavit Wireless Mouse HV-MS970WB Pro Transparent White\nდამატება\n129 ₾\n\nთვეში: 3 ₾ -დან\n\nRivacase 7930 Pro 16\nდამატება\n219 ₾\n\nთვეში: 6 ₾ -დან\n\nRazer Gaming Mouse Orochi V2 WL Pink\nდამატება\n59 ₾\n\nთვეში: 1 ₾ -დან\n\nRivacese 8035 Laptop Shoulder Bag 15 Black\nდამატება\n59 ₾\n\nთვეში: 1 ₾ -დან\n\nRivacase 8037 Laptop Bag 15 Black\nდამატება\n79 ₾\n\nთვეში: 2 ₾ -დან\n\nRivacase 7562 Anti-Theft Laptop Backpack 15 Black\nდამატება\n79 ₾\n\nთვეში: 2 ₾ -დან\n\nRivacase 7562 Anti-Theft Laptop Backpack 15 Dark grey\nდამატება\n79 ₾\n\nთვეში: 2 ₾ -დან\n\nRivacase 7562 Anti-Theft Laptop Backpack 15 Grey/Dark ...\nდამატება\n69 ₾\n\nთვეში: 1 ₾ -დან\n\nRivacase 7532 Anti-Theft Laptop Bag 15 Dark Grey\nდამატება\n69 ₾\n\nთვეში: 1 ₾ -დან\n\nRivacase 7532 Anti-Theft Laptop Bag 15 Grey/Dark Blue ...\nდამატება\n79 ₾\n\nთვეში: 2 ₾ -დან\n\nRivacase 8231 Laptop Bag 15 Black\nდამატება\n79 ₾\n\nთვეში: 2 ₾ -დან\n\nRivacase 8231 Laptop Bag 15 Star blue\nდამატება\n79 ₾\n\nთვეში: 2 ₾ -დან\n\nRivacase 8335 Laptop Bag 15 Black\nდამატება\n79 ₾\n\nთვეში: 2 ₾ -დან\n\nRivacase 8335 Laptop Bag 15 Star blue\nდამატება\n69 ₾\n\nთვეში: 1 ₾ -დან\n\nRivacase 7730 Eco Laptop Shoulder Bag 15 Black\nდამატება\n59 ₾\n\nთვეში: 1 ₾ -დან\n\nRivacase 5562 Lite Urban Backpack 15 Blue\nდამატება\n59 ₾\n\nთვეში: 1 ₾ -დან\n\nRivacase 5562 Lite Urban Backpack 15 Grey\nდამატება\n59 ₾\n\nთვეში: 1 ₾ -დან\n\nRivacase 5562 Lite Urban Backpack 15 Red\nდამატება\n59 ₾\n\nთვეში: 1 ₾ -დან\n\nRivacase 8035 Laptop Shoulder Bag 15\nდამატება\n79 ₾\n\nთვეში: 2 ₾ -დან\n\nTomtoc Defender A13 Laptop Sleeve 15 A13E3D1 Black\nდამატება\n119 ₾\n\nთვეში: 3 ₾ -დან\n\nTomtoc Defender A42 Laptop Briefcase 15 A42E1D1 Black\nდამატება\n79 ₾\n\nთვეში: 2 ₾ -დან\n\nHP Campus backpack 15.6 7J595AA Green\nდამატება\n79 ₾\n\nთვეში: 2 ₾ -დან\n\nHP Campus backpack 15.6 7J597AA Lavender\nდამატება\n69 ₾\n\nთვეში: 1 ₾ -დან\n\nRivacase 8065 Laptop Backpack 15 Black\nდამატება\n99 ₾\n\nთვეში: 2 ₾ -დან\n\nSpigen Valentinus S Laptop Sleeve 16 AFA06425 Brown\nდამატება\n99 ₾\n\nთვეში: 2 ₾ -დან\n\nSpigen Valentinus S Laptop Sleeve 16 AFA06426 Green\nდამატება\n99 ₾\n\nთვეში: 2 ₾ -დან\n\nSpigen Valentinus S Laptop Sleeve 16 AFA06424 Grey\nდამატება\n79 ₾\n\nთვეში: 2 ₾ -დან\n\nSpigen Valentinus Laptop Sleeve 16 AFA06418 Grey\nდამატება\n59 ₾\n\nთვეში: 1 ₾ -დან\n\nRivacase 8036 Laptop Briefcase 16 Black\nდამატება\n79 ₾\n\nთვეში: 2 ₾ -დან\n\nRivacase 8062 Laptop Backpack 16 Black\nდამატება\n69 ₾\n\nთვეში: 1 ₾ -დან\n\nRivacase 8065 Laptop Backpack 15 Dark Blue\nდამატება\n69 ₾\n\nთვეში: 1 ₾ -დან\n\nAcer Green Sleeve 15.6 GP.BAG11.02J Grey\nდამატება\n199 ₾\n\nთვეში: 5 ₾ -დან\n\nTomtoc VintPack TA1 Laptop Backpack 15 TA1M1D1 Black\nდამატება\n199 ₾\n\nთვეში: 5 ₾ -დან\n\nTomtoc Navigator T71 Travel Laptop Backpack 15 T71M1D ...\nდამატება\n149 ₾\n\nთვეში: 4 ₾ -დან\n\nTomtoc Explorer T60 Laptop Backpack 16 T60M1D1 Black\nდამატება\n79 ₾\n\nთვეში: 2 ₾ -დან\n\nHP 15 Sleeve 9J4C3AA Mint Green\nდამატება\n79 ₾\n\nთვეში: 2 ₾ -დან\n\nRivacase 5131 Antishock Hard Shell Case 15.6 Black\nდამატება\n39 ₾\n\nთვეში: 1 ₾ -დან\n\nRivacase 5516 ECO Laptop case 15.6 Black\nდამატება\n49 ₾\n\nთვეში: 1 ₾ -დან\n\nRivacase 5563 ECO 18L lite urban backpack Blue\nდამატება\n119 ₾\n\nთვეში: 3 ₾ -დან\n\nRivacase 8262 Laptop backpack 15 Black\nდამატება\n89 ₾\n\nთვეში: 2 ₾ -დან\n\nRivacase 8265 Laptop backpack 15 Black\nდამატება\n79 ₾\n\nთვეში: 2 ₾ -დან\n\nRivacase 8335 Laptop Bag 15 Purple\nდამატება\n89 ₾\n\nთვეში: 2 ₾ -დან\n\nHP Renew Business 15.6 Laptop Bag 3E5F8AA Black\nდამატება\n49 ₾\n\nთვეში: 1 ₾ -დან\n\nLenovo Urban Sleeve Case 15.6 Grey\nდამატება\nპროდუქტის შესახებ\n\nთუ ეძებთ ლეპტოპს, რომელიც მარტივად გაუმკლავდება ყველაზე მოთხოვნად თამაშებს — HP Victus 15 B09J6EA Blue შექმნილია სწორედ თქვენთვის. ეს მოდელი აერთიანებს მაღალ წარმადობას, გამძლე კონსტრუქციასა და თვალ...\n\nმეტის ნახვა\nმსგავსი პროდუქტები\n2999 ₾\n\nთვეში: 83 ₾ -დან\n\nHP Victus 15 84J97EA, Intel core i5-13500H, Nvidia Ge ...\nდამატება\n2499 ₾\n\nთვეში: 69 ₾ -დან\n\nHP Victus 15 84J98EA, Intel Core i5-13420H Octa 4.6 G ...\nდამატება\n2499 ₾\n\nთვეში: 69 ₾ -დან\n\nHP Victus 15 84J99EA, Intel Core i5-13420H Octa 4.6 G ...\nდამატება\n3199 ₾\n3399 ₾\n\nთვეში: 88 ₾ -დან\n\nHP Victus 15 8F5J3EA Mica Silver\nდამატება\n3499 ₾\n3699 ₾\n\nთვეში: 97 ₾ -დან\n\nHP Omen 16 A1WF1EA, Intel Core i5-14500HX, Nvidia GeF ...\nდამატება\n2799 ₾\n2999 ₾\n\nთვეში: 77 ₾ -დან\n\nHP Victus 15 A1WD6EA, AMD Ryzen 5-8645HS, NVIDIA GeFo ...\nდამატება\n3379 ₾\n\nთვეში: 93 ₾ -დან\n\nHP Victus 16 A1WE4EA, Intel Core i5-14450HX, Nvidia G ...\nდამატება\n2899 ₾\n2999 ₾\n\nთვეში: 80 ₾ -დან\n\nHP Victus 15 A1WD5EA Mica Silver\nდამატება\n3999 ₾\n5599 ₾\n\nთვეში: 111 ₾ -დან\n\nHP Omen 14 A1AA7EA Black\nდამატება\n2999 ₾\n3099 ₾\n\nთვეში: 83 ₾ -დან\n\nHP Victus 16 A1AB6EA Mica Silver\nდამატება\n2899 ₾\n2999 ₾\n\nთვეში: 80 ₾ -დან\n\nHP Victus 16 A1AB7EA Mica Silver\nდამატება\n3999 ₾\n4199 ₾\n\nთვეში: 111 ₾ -დან\n\nHP Victus 16 B09JXEA Mica Silver\nდამატება\n2499 ₾\n2599 ₾\n\nთვეში: 69 ₾ -დან\n\nHP Victus 15 B08XKEA Mica Silver\nდამატება\nGIFTS\n3299 ₾\n3499 ₾\n\nთვეში: 91 ₾ -დან\n\nHP Victus 15 A74LKEA Blue\nდამატება\nGIFTS\n2799 ₾\n2999 ₾\n\nთვეში: 77 ₾ -დან\n\nHP Victus 15 B84VTEA Silver\nდამატება\n5699 ₾\n\nთვეში: 158 ₾ -დან\n\nHP Omen Max 16 BG7J7EA, Intel Core Ultra 7-255HX 20c, ...\nდამატება\nდამატებითი მახასიათებლები\nბრენდი\nბრენდი:\n\t\nHP\nმოდელი\nმოდელი:\n\t\nVictus\nტექნიკური მახასიათებლები\nცენტრალური პროცესორი:\n\t\nIntel Core i5-13420H\n\n\nპროცესორის თაობა:\n\t\nIntel i5 13th Gen\n\n\nპროცესორის სიხშირე:\n\t\n3.4 GHz ~ 4.6 GHz\n\n\nბირთვების რაოდენობა:\n\t\n8\n\n\nნაკადების რაოდენობა:\n\t\n16\n\n\nგრაფიკული პროცესორი:\n\t\nNvidia GeForce RTX 3050\n\n\nგრაფიკული პროცესორის მეხსიერება:\n\t\n6 GB\n\n\nგრაფიკული პროცესორის ტიპი:\n\t\nარა ინტეგრირებული\n\n\nოპერაციული სისტემა:\n\t\nNo\n\n\nBluetooth:\n\t\nYes\nეკრანი\nეკრანის ზომა:\n\t\n15.6 inches\n\n\nრეზოლუცია:\n\t\nFull HD\n\n\nეკრანის ტიპი:\n\t\nIPS\n\n\nსენსორული ეკრანი:\n\t\nNo\n\n\nგანახლების სიხშირე:\n\t\n144 Hz\nდამატებითი მახასიათებლები\nკლავიატურის განათება:\n\t\n-\n\n\nNumpad:\n\t\nYes\n\n\nდისკის წამკითხველი:\n\t\nNo\n\n\nვებ კამერა:\n\t\nYes\n\n\nლეპტოპის ტიპი:\n\t\nგეიმინგი\nმეხსიერება\nშიდა მეხსიერება:\n\t\n512 GB\n\n\nშიდა მეხსიერების ტიპი:\n\t\nSSD\n\n\nშიდა მეხსიერების ინტერფეისი:\n\t\nPcle Gen4\n\n\nოპერატიული მეხსიერება:\n\t\n16 GB\n\n\nოპერატიული მეხსიერების ტიპი:\n\t\nDDR4\n\n\nოპერატიული მეხსიერების სიხშირე:\n\t\n3200 MHz\nპორტები\nUSB:\n\t\n-\n\n\nType-C:\n\t\n-\n\n\nType-C პორტით დამუხტვა:\n\t\n-\n\n\nHDMI:\n\t\n-\n\n\nლან პორტი:\n\t\n-\n\n\n3.5mm:\n\t\nYes\nზომა/წონა\nწონა:\n\t\n-\nფერი\nფერი:\n\t\nBlue\nმეტის ნახვა\nგაეცანი საგარანტიო პირობებს\nსაგარანტიო პირობები\nფილიალები\nმარაგშია\nშეკვეთიდან 2-5 დღეში\nზუმერის წერეთლის ფილიალი\n\nთბილისი - წერეთლის გამზირი, N1.\n\nმარაგშია\n+995 591 967 601\nორშ-შაბ: 10:00:00 - 20:00:00\nკვირა: 10:00:00 - 19:00:00\nზუმერის \"თბილისი ცენტრალის\" ფილიალი\n\nთბილისი - \"თბილისი ცენტრალი\"- lll სართული\n\nმარაგშია\n+995 599 862 449\nორშ-შაბ: 10:00:00 - 20:00:00\nკვირა: 10:00:00 - 19:00:00\nზუმერის City Mall საბურთალო-ს ფილიალი\n\nთბილისი - \"სითი მოლი\" - პეტრე ქავთარაძის N1\n\nმარაგშია\n+995 591 971 962\nორშ-შაბ: 10:00:00 - 22:00:00\nკვირა: 10:00:00 - 22:00:00\nზუმერის თბილისი მოლის ფილიალი\n\nთბილისი - „თბილისი მოლი\" - I სართული. აღმაშენებლის ხეივანი მე-16 კმ\n\nმარაგშია\n+995 591 967 608\nორშ-შაბ: 10:00:00 - 22:00:00\nკვირა: 10:00:00 - 22:00:00\nზუმერის \"გლდანი მოლის\" ფილიალი\n\nთბილისი - \"გლდანი მოლი\" - I სართული, M-ახმეტელის მიმდებარე\n\nმარაგშია\n+995 591 967 673\nორშ-შაბ: 10:00:00 - 21:00:00\nკვირა: 10:00:00 - 21:00:00\nზუმერის ისთ ფოინთის ფილიალი\n\nთბილისი - \"ისთ ფოინთი\" - ალ. თვალჭრელიძე N2\n\nმარაგშია\n+995 591 340 476\nორშ-შაბ: 10:00:00 - 22:00:00\nკვირა: 10:00:00 - 22:00:00\nბათუმი ჭავჭავაძის ფილიალი\n\nბათუმი - ბათუმი, ჭავჭავაძის N21\n\nმარაგშია\n+995 591 967 606\nორშ-შაბ: 10:00:00 - 20:00:00\nკვირა: 10:00:00 - 19:00:00\nბათუმის \"Black Sea Mall\"-ის ფილიალი\n\nბათუმი - \"Black Sea Mall\" - ტბელ აბუსერიძის N22\n\nმარაგშია\n+995 591 310 257\nორშ-შაბ: 10:00:00 - 21:00:00\nკვირა: 10:00:00 - 21:00:00\nბათუმის გრანდ მოლის ფილიალი\n\nბათუმი - \"გრანდ მოლი\" - შერიფ ხიმშიაშვილის 29\n\nმარაგშია\n+995 591 022 872\nორშ-შაბ: 10:00:00 - 22:00:00\nკვირა: 10:00:00 - 22:00:00\nქუთაისი ვესთ მოლი\n\nქუთაისი - \"ვესთ მოლი\" - შარტავას N2\n\nმარაგშია\n+995 595 306 765\nორშ-შაბ: 10:00:00 - 22:00:00\nკვირა: 10:00:00 - 22:00:00\nმეტის ნახვა\n2799 ₾\n3199 ₾\n\nთვეში: 77.8 ₾ -დან\n\nმარაგი ფილიალებში\nფასის დაზღვევა\nფასის კონტროლი\nფასის დაჯავშნა\nყიდვა\nშედარება\nდამატება\nნავიგაცია\n\nპერსონალურ მონაცემთა დაცვის პოლიტიკა\n\nჩვენ შესახებ\n\nწესები და პირობები\n\nმიწოდების სერვისი\n\nკარიერა\n\nგადახდები\n\nSetanta Sports\n\nგადახდის მეთოდები\n\nგარანტია\n\nგანვადება\n\nნივთის დაბრუნება\n\nნივთის ონლაინ ყიდვის ინსტრუქცია\n\nგამოგვყევი\n\nFacebook\n\nYoutube\n\nInstagram\n\nTik Tok\n\nკონტაქტი\n\nInfo@zoommer.ge\n\n+995 (32) 2 60 30 60 / *7007\n\nფილიალები\n\nკორპორატიული გაყიდვები\n\nZoommer App\n\nCopyright © 2023 Zoommer.ge. All rights reserved.\n\nCookie პოლიტიკა\n\nსაიტით სარგებლობის გაგრძელებით, შენ ეთანხმები Cookie ჩანაწერების გამოყენებას. მეტი ინფორმაცისათვის იხილეთ კონფიდენციალურობის პოლიტიკა\n\nგასაგებია",
    "specs": {
      "ბრენდი:": "HP",
      "მოდელი:": "Victus",
      "ცენტრალური პროცესორი:": "Intel Core i5-13420H",
      "პროცესორის თაობა:": "Intel i5 13th Gen",
      "პროცესორის სიხშირე:": "3.4 GHz ~ 4.6 GHz",
      "ბირთვების რაოდენობა:": "8",
      "ნაკადების რაოდენობა:": "16",
      "გრაფიკული პროცესორი:": "Nvidia GeForce RTX 3050",
      "გრაფიკული პროცესორის მეხსიერება:": "6 GB",
      "გრაფიკული პროცესორის ტიპი:": "არა ინტეგრირებული",
      "ოპერაციული სისტემა:": "No",
      "Bluetooth:": "Yes",
      "ეკრანის ზომა:": "15.6 inches",
      "რეზოლუცია:": "Full HD",
      "ეკრანის ტიპი:": "IPS",
      "სენსორული ეკრანი:": "No",
      "განახლების სიხშირე:": "144 Hz",
      "კლავიატურის განათება:": "-",
      "Numpad:": "Yes",
      "დისკის წამკითხველი:": "No",
      "ვებ კამერა:": "Yes",
      "ლეპტოპის ტიპი:": "გეიმინგი",
      "შიდა მეხსიერება:": "512 GB",
      "შიდა მეხსიერების ტიპი:": "SSD",
      "შიდა მეხსიერების ინტერფეისი:": "Pcle Gen4",
      "ოპერატიული მეხსიერება:": "16 GB",
      "ოპერატიული მეხსიერების ტიპი:": "DDR4",
      "ოპერატიული მეხსიერების სიხშირე:": "3200 MHz",
      "USB:": "-",
      "Type-C:": "-",
      "Type-C პორტით დამუხტვა:": "-",
      "HDMI:": "-",
      "ლან პორტი:": "-",
      "3.5mm:": "Yes",
      "წონა:": "-",
      "ფერი:": "Blue"
    }
  },
  {
    "category": "Gaming ლეპტოპები",
    "title": "HP Victus 15 A74LKEA Blue",
    "price": 3299.0,
    "link": "https://zoommer.ge/leptopebi/hp-victus-15-a74lkea-blue-p45706",
    "image": "/_next/image?url=https%3A%2F%2Fs3.zoommer.ge%2Fsite%2F72b80d40-38ab-4682-ae42-e3e4a0a9c710_Thumb.jpeg&w=384&q=50",
    "product_title_detail": "HP Victus 15 A74LKEA Blue",
    "description": "*7007 / +995 (32) 2 60 30 60\nსავაჭრო პოლიტიკა\nგანვადება\nკარიერა\nTrade In\nფილიალები\nნავიგაცია\nკალათა\nშესვლა\n%\nმთავარი\nლეპტოპები\nHP\n#ZOOM-035403\nHP Victus 15 A74LKEA Blue\nეკრანის ზომა\n15.6 Inches\nრეზოლუცია\nFull HD\nეკრანის ტიპი\nIPS\nგანახლების სიხშირე\n144 Hz\nშიდა მეხსიერება\n512 GB\nBluetooth\nYes\nType-C\n-\nოპერატიული მეხსიერება\n16 GB\nპროდუქტს მოყვება საჩუქარი\nGift Card - 200 ₾\n200 ₾\nერთად იაფია\nდაამატე ნივთი\nHP Victus 15 A74LKEA Blue\n3299 ₾\nRivacase 7562 Anti-Theft Laptop Backpack 15 Grey/Dark blue\n67.15 ₾\n79 ₾\nRazer Gaming Mouse DeathAdder Essential USB White\n52 ₾\n65 ₾\nHavit Gaming Cooling Pad HV-F2083 Black\n75.65 ₾\n89 ₾\nჯამური ფასი (3)\n3493.8 ₾\n3532 ₾\nყიდვა\nაქსესუარები\nაღწერა\nმსგავსი\nმახასიათებლები\nფილიალები\nაქსესუარები\nაღწერა\nმსგავსი\nმახასიათებლები\nფილიალები\n89 ₾\n\nთვეში: 2 ₾ -დან\n\nHavit Gaming Cooling Pad HV-F2083 Black\nდამატება\n79 ₾\n\nთვეში: 2 ₾ -დან\n\nLenovo 15.6 Laptop Backpack B510\nდამატება\n219 ₾\n\nთვეში: 6 ₾ -დან\n\nRazer Gaming Mouse Orochi V2 WL Black\nდამატება\n59 ₾\n\nთვეში: 1 ₾ -დან\n\nHavit Gaming mouse Pad HV-MP901\nდამატება\n69 ₾\n\nთვეში: 1 ₾ -დან\n\nXiaomi Mi Router 4A DVB4230GL White\nდამატება\n39 ₾\n\nთვეში: 1 ₾ -დან\n\nLenovo T210 Casual Toploader 15.6 Black\nდამატება\n219 ₾\n\nთვეში: 6 ₾ -დან\n\nRazer Gaming Mouse Orochi V2 WL White\nდამატება\n9 ₾\n\nHavit Gaming mouse Pad HV-MP838\nდამატება\n85 ₾\n\nთვეში: 2 ₾ -დან\n\nTP-Link Archer C50 AC1200 White\nდამატება\n39 ₾\n\nთვეში: 1 ₾ -დან\n\nLenovo T210 Casual Toploader 15.6 Grey\nდამატება\n209 ₾\n\nთვეში: 5 ₾ -დან\n\nRazer Gaming Mouse DeathAdder V2 X Hyperspeed WL/BT/U ...\nდამატება\n9 ₾\n\nHavit Gaming mouse Pad HV-MP843 Black\nდამატება\n119 ₾\n\nთვეში: 3 ₾ -დან\n\nTP-Link Archer C6 AC1200 Black\nდამატება\n89 ₾\n\nთვეში: 2 ₾ -დან\n\nAcer Starter Kit 15.6 Laptop Bag & Wireless Mouse\nდამატება\n139 ₾\n\nთვეში: 3 ₾ -დან\n\nLogitech Gaming Mouse G402 Hyperion Fury black\nდამატება\n149 ₾\n\nთვეში: 4 ₾ -დან\n\nRazer Mouse Pad Firefly V2 RGB M Black\nდამატება\n159 ₾\n\nთვეში: 4 ₾ -დან\n\nXiaomi Router AX1500 White\nდამატება\n89 ₾\n\nთვეში: 2 ₾ -დან\n\nHP Prelude Pro 15.6 Backpack 4Z513AA Grey\nდამატება\n29 ₾\n\nHavit Gaming Mouse HV-MS1010 Black\nდამატება\n199 ₾\n\nთვეში: 5 ₾ -დან\n\nRazer Mouse Pad Goliathus Extended Chroma XXL Black\nდამატება\n179 ₾\n\nთვეში: 4 ₾ -დან\n\nXiaomi Mesh System AX3000 NE 1 pack White\nდამატება\n69 ₾\n\nთვეში: 1 ₾ -დან\n\nHP Prelude Pro 15.6 Laptop bag 4Z514AA Grey\nდამატება\n79 ₾\n\nთვეში: 2 ₾ -დან\n\nRazer Gaming Mouse DeathAdder Essential USB Black\nდამატება\n149 ₾\n\nთვეში: 4 ₾ -დან\n\nHyperX Pulsefire Mat RGB Black\nდამატება\n299 ₾\n\nთვეში: 8 ₾ -დან\n\nXiaomi Mesh System AX3000 NE 2 pack White\nდამატება\n129 ₾\n\nთვეში: 3 ₾ -დან\n\nHP Renew Travel Backpack 2Z8A3AA Grey\nდამატება\n119 ₾\n\nთვეში: 3 ₾ -დან\n\nHyperX Pulsefire Surge Mouse Black\nდამატება\n29 ₾\n\nHavit Gaming Mouse Pad HV-MP845 Black\nდამატება\n249 ₾\n\nთვეში: 6 ₾ -დან\n\nXiaomi Router BE3600 White\nდამატება\n79 ₾\n\nთვეში: 2 ₾ -დან\n\nHP Travel Backpack 15 6B8U6AA Iron Grey\nდამატება\n469 ₾\n\nთვეში: 13 ₾ -დან\n\nHP OMEN PHOTON Wireless Mouse 6CL96AA Black\nდამატება\n29 ₾\n\nHavit Gaming Mouse Pad HV-MP847 Pink\nდამატება\n89 ₾\n\nთვეში: 2 ₾ -დან\n\nXiaomi Commuter Backpack Dark Gray\nდამატება\n65 ₾\n\nთვეში: 1 ₾ -დან\n\nRazer Gaming Mouse DeathAdder Essential USB White\nდამატება\n29 ₾\n\nHavit Gaming Mouse Pad HV-MP849 Black\nდამატება\n89 ₾\n\nთვეში: 2 ₾ -დან\n\nXiaomi Commuter Backpack Light Blue\nდამატება\n239 ₾\n\nთვეში: 6 ₾ -დან\n\nRazer Gaming Mouse Basilisk V3 Black\nდამატება\n49 ₾\n\nთვეში: 1 ₾ -დან\n\nHyperX Pulsefire Mat M Black\nდამატება\n89 ₾\n\nთვეში: 2 ₾ -დან\n\nXiaomi Commuter Backpack Light Gray\nდამატება\n299 ₾\n\nთვეში: 8 ₾ -დან\n\nRazer Gaming Mouse Naga V2 HyperSpeed WL Black\nდამატება\n59 ₾\n\nთვეში: 1 ₾ -დან\n\nHyperX Pulsefire Mat L Black\nდამატება\n59 ₾\n\nთვეში: 1 ₾ -დან\n\nHP Prelude 15.6 2Z8P4AA Dark Grey\nდამატება\n229 ₾\n\nთვეში: 6 ₾ -დან\n\nRazer Gaming Mouse Basilisk V3 X HyperSpeed WL Black\nდამატება\n39 ₾\n\nთვეში: 1 ₾ -დან\n\nRazer Mouse Pad Sphex V3 S Black\nდამატება\n79 ₾\n\nთვეში: 2 ₾ -დან\n\nHP Prelude 15.6 2Z8P3AA Grey\nდამატება\n129 ₾\n\nთვეში: 3 ₾ -დან\n\nRazer Gaming Mouse Cobra Black\nდამატება\n89 ₾\n\nთვეში: 2 ₾ -დან\n\nRazer Mouse Pad Sphex V3 L Black\nდამატება\n55 ₾\n\nთვეში: 1 ₾ -დან\n\nHP Prelude 15.6 1E7D7AA Grey\nდამატება\n19 ₾\n\nHavit Gaming Mouse HV-MS989GT Black/Red\nდამატება\n29 ₾\n\nHavit Gaming mouse Pad HV-MP860\nდამატება\n59 ₾\n\nთვეში: 1 ₾ -დან\n\nHP 15 Sleeve 14V33AA Black\nდამატება\n19 ₾\n\nHavit Gaming Mouse HV-MS626GT Black\nდამატება\n39 ₾\n\nთვეში: 1 ₾ -დან\n\nLenovo Casual Backpack B210 Black\nდამატება\n19 ₾\n\nHavit Gaming Mouse HV-MS66GT White/Blue\nდამატება\n39 ₾\n\nთვეში: 1 ₾ -დან\n\nLenovo Casual Backpack B210 Blue\nდამატება\n149 ₾\n\nთვეში: 4 ₾ -დან\n\nHyperX Gaming Mouse Pulsefire Haste 2 Black\nდამატება\n39 ₾\n\nთვეში: 1 ₾ -დან\n\nLenovo Casual Backpack B210 Green\nდამატება\n19 ₾\n\nHavit Wireless Mouse HV-MS66GT Black\nდამატება\n39 ₾\n\nთვეში: 1 ₾ -დან\n\nLenovo Casual Backpack B210 Grey\nდამატება\n179 ₾\n\nთვეში: 4 ₾ -დან\n\nLogitech Gaming Mouse G305 LIGHTSPEED WL L910-005282 ...\nდამატება\n89 ₾\n\nთვეში: 2 ₾ -დან\n\nLenovo IdeaPad Gaming Backpack\nდამატება\n259 ₾\n\nთვეში: 7 ₾ -დან\n\nLogitech Gaming Mouse G502 X L910-006138 Black\nდამატება\n79 ₾\n\nთვეში: 2 ₾ -დან\n\nXiaomi Ninetygo Multitasker Commuting Backpack Grey\nდამატება\n259 ₾\n\nთვეში: 7 ₾ -დან\n\nLogitech Gaming Mouse G502 X L910-006138 White\nდამატება\n139 ₾\n\nთვეში: 3 ₾ -დან\n\nXiaomi Ninetygo Urban Daily Backpack Yellow\nდამატება\n19 ₾\n\nHavit Gaming Mouse HV-MS626GT Black/Red\nდამატება\n99 ₾\n\nთვეში: 2 ₾ -დან\n\nXiaomi Mi Business Backpack 2 Black\nდამატება\n19 ₾\n\nHavit Gaming Mouse HV-MS626GT Black/Blue\nდამატება\n99 ₾\n\nთვეში: 2 ₾ -დან\n\nXiaomi Mi Business Backpack 2 Dark Gray\nდამატება\n349 ₾\n\nთვეში: 9 ₾ -დან\n\nLogitech Gaming Mouse G703 LIGHTSPEED WL L910-005640 ...\nდამატება\n69 ₾\n\nთვეში: 1 ₾ -დან\n\nLenovo 15.6 Laptop Backpack B515 Black\nდამატება\n89 ₾\n\nთვეში: 2 ₾ -დან\n\nLogitech Gaming Mouse G102 LIGHTSYNC L910-005823 Blac ...\nდამატება\n69 ₾\n\nთვეში: 1 ₾ -დან\n\nLenovo 15.6 Laptop Backpack B515 Blue\nდამატება\n89 ₾\n\nთვეში: 2 ₾ -დან\n\nLogitech Gaming Mouse G102 LIGHTSYNC L910-005824 Whit ...\nდამატება\n69 ₾\n\nთვეში: 1 ₾ -დან\n\nLenovo 15.6 Laptop Backpack B515 Grey\nდამატება\n89 ₾\n\nთვეში: 2 ₾ -დან\n\nLogitech Gaming Mouse G102 LIGHTSYNC L910-005801 Blue\nდამატება\n69 ₾\n\nთვეში: 1 ₾ -დან\n\nHP Prelude Backpack 15.6 1E7D6AA Grey\nდამატება\n239 ₾\n\nთვეში: 6 ₾ -დან\n\nLogitech Gaming Mouse G502 HERO L910-005470 Black\nდამატება\n39 ₾\n\nთვეში: 1 ₾ -დან\n\nVivo Backpack YL16\nდამატება\n199 ₾\n\nთვეში: 5 ₾ -დან\n\nHyperX Pulsefire Haste 2 core Wireless Black\nდამატება\n89 ₾\n\nთვეში: 2 ₾ -დან\n\nAsus Shoulder Bag 15 Eos 2 Black\nდამატება\n199 ₾\n\nთვეში: 5 ₾ -დან\n\nHyperX Pulsefire Haste 2 core Wireless White\nდამატება\n89 ₾\n\nთვეში: 2 ₾ -დან\n\nAsus Shoulder Bag 15 Eos 2 Grey\nდამატება\n59 ₾\n\nთვეში: 1 ₾ -დან\n\nHavit Gaming Mouse HV-MS954 Black\nდამატება\n59 ₾\n\nთვეში: 1 ₾ -დან\n\nAcer Urban Backpack 15.6 GP.BAG11.034 Grey\nდამატება\n39 ₾\n\nთვეში: 1 ₾ -დან\n\nHavit Gaming Mouse HV-MS1033 White\nდამატება\n59 ₾\n\nთვეში: 1 ₾ -დან\n\nAcer Nitro Gaming Urban Backpack 15.6 GP.BAG11.02E Bl ...\nდამატება\n39 ₾\n\nთვეში: 1 ₾ -დან\n\nHavit Gaming Mouse HV-MS1029 Pink\nდამატება\n129 ₾\n\nთვეში: 3 ₾ -დან\n\nHP Travel Backpack 15 6B8U4AA Iron Grey\nდამატება\n59 ₾\n\nთვეში: 1 ₾ -დან\n\nHavit Gaming Mouse HV-MS966 Black/Green\nდამატება\n179 ₾\n\nთვეში: 4 ₾ -დან\n\nXiaomi Ninetygo Urban E-Using Plus Shoulder Bag Black\nდამატება\n49 ₾\n\nთვეში: 1 ₾ -დან\n\nHavit Wireless Mouse HV-MS1039W Black/White\nდამატება\n139 ₾\n\nთვეში: 3 ₾ -დან\n\nXiaomi Ninetygo Urban Multifunctional commuting backp ...\nდამატება\n79 ₾\n\nთვეში: 2 ₾ -დან\n\nHavit Wireless Mouse HV-MS970WB Pro Black\nდამატება\n179 ₾\n\nთვეში: 4 ₾ -დან\n\nXiaomi Ninetygo Urban E-Using Plus Shoulder Bag White\nდამატება\n79 ₾\n\nთვეში: 2 ₾ -დან\n\nHavit Wireless Mouse HV-MS970WB Pro Transparent White\nდამატება\n129 ₾\n\nთვეში: 3 ₾ -დან\n\nRivacase 7930 Pro 16\nდამატება\n219 ₾\n\nთვეში: 6 ₾ -დან\n\nRazer Gaming Mouse Orochi V2 WL Pink\nდამატება\n59 ₾\n\nთვეში: 1 ₾ -დან\n\nRivacese 8035 Laptop Shoulder Bag 15 Black\nდამატება\n59 ₾\n\nთვეში: 1 ₾ -დან\n\nRivacase 8037 Laptop Bag 15 Black\nდამატება\n79 ₾\n\nთვეში: 2 ₾ -დან\n\nRivacase 7562 Anti-Theft Laptop Backpack 15 Black\nდამატება\n79 ₾\n\nთვეში: 2 ₾ -დან\n\nRivacase 7562 Anti-Theft Laptop Backpack 15 Dark grey\nდამატება\n79 ₾\n\nთვეში: 2 ₾ -დან\n\nRivacase 7562 Anti-Theft Laptop Backpack 15 Grey/Dark ...\nდამატება\n69 ₾\n\nთვეში: 1 ₾ -დან\n\nRivacase 7532 Anti-Theft Laptop Bag 15 Dark Grey\nდამატება\n69 ₾\n\nთვეში: 1 ₾ -დან\n\nRivacase 7532 Anti-Theft Laptop Bag 15 Grey/Dark Blue ...\nდამატება\n79 ₾\n\nთვეში: 2 ₾ -დან\n\nRivacase 8231 Laptop Bag 15 Black\nდამატება\n79 ₾\n\nთვეში: 2 ₾ -დან\n\nRivacase 8231 Laptop Bag 15 Star blue\nდამატება\n79 ₾\n\nთვეში: 2 ₾ -დან\n\nRivacase 8335 Laptop Bag 15 Black\nდამატება\n79 ₾\n\nთვეში: 2 ₾ -დან\n\nRivacase 8335 Laptop Bag 15 Star blue\nდამატება\n69 ₾\n\nთვეში: 1 ₾ -დან\n\nRivacase 7730 Eco Laptop Shoulder Bag 15 Black\nდამატება\n59 ₾\n\nთვეში: 1 ₾ -დან\n\nRivacase 5562 Lite Urban Backpack 15 Blue\nდამატება\n59 ₾\n\nთვეში: 1 ₾ -დან\n\nRivacase 5562 Lite Urban Backpack 15 Grey\nდამატება\n59 ₾\n\nთვეში: 1 ₾ -დან\n\nRivacase 5562 Lite Urban Backpack 15 Red\nდამატება\n59 ₾\n\nთვეში: 1 ₾ -დან\n\nRivacase 8035 Laptop Shoulder Bag 15\nდამატება\n79 ₾\n\nთვეში: 2 ₾ -დან\n\nTomtoc Defender A13 Laptop Sleeve 15 A13E3D1 Black\nდამატება\n119 ₾\n\nთვეში: 3 ₾ -დან\n\nTomtoc Defender A42 Laptop Briefcase 15 A42E1D1 Black\nდამატება\n79 ₾\n\nთვეში: 2 ₾ -დან\n\nHP Campus backpack 15.6 7J595AA Green\nდამატება\n79 ₾\n\nთვეში: 2 ₾ -დან\n\nHP Campus backpack 15.6 7J597AA Lavender\nდამატება\n69 ₾\n\nთვეში: 1 ₾ -დან\n\nRivacase 8065 Laptop Backpack 15 Black\nდამატება\n99 ₾\n\nთვეში: 2 ₾ -დან\n\nSpigen Valentinus S Laptop Sleeve 16 AFA06425 Brown\nდამატება\n99 ₾\n\nთვეში: 2 ₾ -დან\n\nSpigen Valentinus S Laptop Sleeve 16 AFA06426 Green\nდამატება\n99 ₾\n\nთვეში: 2 ₾ -დან\n\nSpigen Valentinus S Laptop Sleeve 16 AFA06424 Grey\nდამატება\n79 ₾\n\nთვეში: 2 ₾ -დან\n\nSpigen Valentinus Laptop Sleeve 16 AFA06418 Grey\nდამატება\n59 ₾\n\nთვეში: 1 ₾ -დან\n\nRivacase 8036 Laptop Briefcase 16 Black\nდამატება\n79 ₾\n\nთვეში: 2 ₾ -დან\n\nRivacase 8062 Laptop Backpack 16 Black\nდამატება\n69 ₾\n\nთვეში: 1 ₾ -დან\n\nRivacase 8065 Laptop Backpack 15 Dark Blue\nდამატება\n69 ₾\n\nთვეში: 1 ₾ -დან\n\nAcer Green Sleeve 15.6 GP.BAG11.02J Grey\nდამატება\n199 ₾\n\nთვეში: 5 ₾ -დან\n\nTomtoc VintPack TA1 Laptop Backpack 15 TA1M1D1 Black\nდამატება\n199 ₾\n\nთვეში: 5 ₾ -დან\n\nTomtoc Navigator T71 Travel Laptop Backpack 15 T71M1D ...\nდამატება\n149 ₾\n\nთვეში: 4 ₾ -დან\n\nTomtoc Explorer T60 Laptop Backpack 16 T60M1D1 Black\nდამატება\n79 ₾\n\nთვეში: 2 ₾ -დან\n\nHP 15 Sleeve 9J4C3AA Mint Green\nდამატება\n79 ₾\n\nთვეში: 2 ₾ -დან\n\nRivacase 5131 Antishock Hard Shell Case 15.6 Black\nდამატება\n39 ₾\n\nთვეში: 1 ₾ -დან\n\nRivacase 5516 ECO Laptop case 15.6 Black\nდამატება\n49 ₾\n\nთვეში: 1 ₾ -დან\n\nRivacase 5563 ECO 18L lite urban backpack Blue\nდამატება\n119 ₾\n\nთვეში: 3 ₾ -დან\n\nRivacase 8262 Laptop backpack 15 Black\nდამატება\n89 ₾\n\nთვეში: 2 ₾ -დან\n\nRivacase 8265 Laptop backpack 15 Black\nდამატება\n79 ₾\n\nთვეში: 2 ₾ -დან\n\nRivacase 8335 Laptop Bag 15 Purple\nდამატება\n89 ₾\n\nთვეში: 2 ₾ -დან\n\nHP Renew Business 15.6 Laptop Bag 3E5F8AA Black\nდამატება\n49 ₾\n\nთვეში: 1 ₾ -დან\n\nLenovo Urban Sleeve Case 15.6 Grey\nდამატება\nპროდუქტის შესახებ\n\nთუ ეძებთ ლეპტოპს, რომელიც მარტივად გაუმკლავდება ყველაზე მოთხოვნად თამაშებს — HP Victus 15 A74LKEA Blue შექმნილია სწორედ თქვენთვის. ეს მოდელი აერთიანებს მაღალ წარმადობას, გამძლე კონსტრუქციასა და თვალ...\n\nმეტის ნახვა\nმსგავსი პროდუქტები\n2999 ₾\n\nთვეში: 83 ₾ -დან\n\nHP Victus 15 84J97EA, Intel core i5-13500H, Nvidia Ge ...\nდამატება\n2499 ₾\n\nთვეში: 69 ₾ -დან\n\nHP Victus 15 84J98EA, Intel Core i5-13420H Octa 4.6 G ...\nდამატება\n2499 ₾\n\nთვეში: 69 ₾ -დან\n\nHP Victus 15 84J99EA, Intel Core i5-13420H Octa 4.6 G ...\nდამატება\n3199 ₾\n3399 ₾\n\nთვეში: 88 ₾ -დან\n\nHP Victus 15 8F5J3EA Mica Silver\nდამატება\n3499 ₾\n3699 ₾\n\nთვეში: 97 ₾ -დან\n\nHP Omen 16 A1WF1EA, Intel Core i5-14500HX, Nvidia GeF ...\nდამატება\n2799 ₾\n2999 ₾\n\nთვეში: 77 ₾ -დან\n\nHP Victus 15 A1WD6EA, AMD Ryzen 5-8645HS, NVIDIA GeFo ...\nდამატება\n3379 ₾\n\nთვეში: 93 ₾ -დან\n\nHP Victus 16 A1WE4EA, Intel Core i5-14450HX, Nvidia G ...\nდამატება\n2899 ₾\n2999 ₾\n\nთვეში: 80 ₾ -დან\n\nHP Victus 15 A1WD5EA Mica Silver\nდამატება\n3999 ₾\n5599 ₾\n\nთვეში: 111 ₾ -დან\n\nHP Omen 14 A1AA7EA Black\nდამატება\n2999 ₾\n3099 ₾\n\nთვეში: 83 ₾ -დან\n\nHP Victus 16 A1AB6EA Mica Silver\nდამატება\n2899 ₾\n2999 ₾\n\nთვეში: 80 ₾ -დან\n\nHP Victus 16 A1AB7EA Mica Silver\nდამატება\n3999 ₾\n4199 ₾\n\nთვეში: 111 ₾ -დან\n\nHP Victus 16 B09JXEA Mica Silver\nდამატება\nGIFTS\n2499 ₾\n2599 ₾\n\nთვეში: 69 ₾ -დან\n\nHP Victus 15 B08XKEA Mica Silver\nდამატება\n2799 ₾\n3199 ₾\n\nთვეში: 77 ₾ -დან\n\nHP Victus 15 B09J6EA Blue\nდამატება\n2799 ₾\n2999 ₾\n\nთვეში: 77 ₾ -დან\n\nHP Victus 15 B84VTEA Silver\nდამატება\n5699 ₾\n\nთვეში: 158 ₾ -დან\n\nHP Omen Max 16 BG7J7EA, Intel Core Ultra 7-255HX 20c, ...\nდამატება\nდამატებითი მახასიათებლები\nბრენდი\nბრენდი:\n\t\nHP\nმოდელი\nმოდელი:\n\t\nVictus\nტექნიკური მახასიათებლები\nცენტრალური პროცესორი:\n\t\nAMD Ryzen 7-8845HS\n\n\nპროცესორის თაობა:\n\t\nRyzen 7 8000 Series\n\n\nპროცესორის სიხშირე:\n\t\n3.8 GHz ~ 5.1 GHz\n\n\nბირთვების რაოდენობა:\n\t\n8\n\n\nნაკადების რაოდენობა:\n\t\n16\n\n\nგრაფიკული პროცესორი:\n\t\nNvidia GeForce RTX 4050\n\n\nგრაფიკული პროცესორის მეხსიერება:\n\t\n6 GB\n\n\nგრაფიკული პროცესორის ტიპი:\n\t\nარა ინტეგრირებული\n\n\nოპერაციული სისტემა:\n\t\nNo\n\n\nBluetooth:\n\t\nYes\nეკრანი\nეკრანის ზომა:\n\t\n15.6 Inches\n\n\nრეზოლუცია:\n\t\nFull HD\n\n\nეკრანის ტიპი:\n\t\nIPS\n\n\nსენსორული ეკრანი:\n\t\nNo\n\n\nგანახლების სიხშირე:\n\t\n144 Hz\nდამატებითი მახასიათებლები\nკლავიატურის განათება:\n\t\n-\n\n\nNumpad:\n\t\n-\n\n\nდისკის წამკითხველი:\n\t\nNo\n\n\nვებ კამერა:\n\t\nYes\n\n\nლეპტოპის ტიპი:\n\t\nგეიმინგი\nმეხსიერება\nშიდა მეხსიერება:\n\t\n512 GB\n\n\nშიდა მეხსიერების ტიპი:\n\t\nSSD\n\n\nშიდა მეხსიერების ინტერფეისი:\n\t\nM.2\n\n\nოპერატიული მეხსიერება:\n\t\n16 GB\n\n\nოპერატიული მეხსიერების ტიპი:\n\t\nDDR5\n\n\nოპერატიული მეხსიერების სიხშირე:\n\t\n-\nპორტები\nUSB:\n\t\n-\n\n\nType-C:\n\t\n-\n\n\nType-C პორტით დამუხტვა:\n\t\n-\n\n\nHDMI:\n\t\n-\n\n\nლან პორტი:\n\t\n-\n\n\n3.5mm:\n\t\nYes\nზომა/წონა\nწონა:\n\t\n-\nფერი\nფერი:\n\t\nBlue\nმეტის ნახვა\nგაეცანი საგარანტიო პირობებს\nსაგარანტიო პირობები\nფილიალები\nმარაგშია\nშეკვეთიდან 2-5 დღეში\nზუმერის წერეთლის ფილიალი\n\nთბილისი - წერეთლის გამზირი, N1.\n\nმარაგშია\n+995 591 967 601\nორშ-შაბ: 10:00:00 - 20:00:00\nკვირა: 10:00:00 - 19:00:00\nზუმერის \"თბილისი ცენტრალის\" ფილიალი\n\nთბილისი - \"თბილისი ცენტრალი\"- lll სართული\n\nმარაგშია\n+995 599 862 449\nორშ-შაბ: 10:00:00 - 20:00:00\nკვირა: 10:00:00 - 19:00:00\nზუმერის City Mall საბურთალო-ს ფილიალი\n\nთბილისი - \"სითი მოლი\" - პეტრე ქავთარაძის N1\n\nმარაგშია\n+995 591 971 962\nორშ-შაბ: 10:00:00 - 22:00:00\nკვირა: 10:00:00 - 22:00:00\nზუმერის \"გლდანი მოლის\" ფილიალი\n\nთბილისი - \"გლდანი მოლი\" - I სართული, M-ახმეტელის მიმდებარე\n\nმარაგშია\n+995 591 967 673\nორშ-შაბ: 10:00:00 - 21:00:00\nკვირა: 10:00:00 - 21:00:00\n3299 ₾\n3499 ₾\n\nთვეში: 91.6 ₾ -დან\n\nმარაგი ფილიალებში\nფასის დაზღვევა\nფასის კონტროლი\nფასის დაჯავშნა\nყიდვა\nშედარება\nდამატება\nნავიგაცია\n\nპერსონალურ მონაცემთა დაცვის პოლიტიკა\n\nჩვენ შესახებ\n\nწესები და პირობები\n\nმიწოდების სერვისი\n\nკარიერა\n\nგადახდები\n\nSetanta Sports\n\nგადახდის მეთოდები\n\nგარანტია\n\nგანვადება\n\nნივთის დაბრუნება\n\nნივთის ონლაინ ყიდვის ინსტრუქცია\n\nგამოგვყევი\n\nFacebook\n\nYoutube\n\nInstagram\n\nTik Tok\n\nკონტაქტი\n\nInfo@zoommer.ge\n\n+995 (32) 2 60 30 60 / *7007\n\nფილიალები\n\nკორპორატიული გაყიდვები\n\nZoommer App\n\nCopyright © 2023 Zoommer.ge. All rights reserved.\n\nCookie პოლიტიკა\n\nსაიტით სარგებლობის გაგრძელებით, შენ ეთანხმები Cookie ჩანაწერების გამოყენებას. მეტი ინფორმაცისათვის იხილეთ კონფიდენციალურობის პოლიტიკა\n\nგასაგებია",
    "specs": {
      "ბრენდი:": "HP",
      "მოდელი:": "Victus",
      "ცენტრალური პროცესორი:": "AMD Ryzen 7-8845HS",
      "პროცესორის თაობა:": "Ryzen 7 8000 Series",
      "პროცესორის სიხშირე:": "3.8 GHz ~ 5.1 GHz",
      "ბირთვების რაოდენობა:": "8",
      "ნაკადების რაოდენობა:": "16",
      "გრაფიკული პროცესორი:": "Nvidia GeForce RTX 4050",
      "გრაფიკული პროცესორის მეხსიერება:": "6 GB",
      "გრაფიკული პროცესორის ტიპი:": "არა ინტეგრირებული",
      "ოპერაციული სისტემა:": "No",
      "Bluetooth:": "Yes",
      "ეკრანის ზომა:": "15.6 Inches",
      "რეზოლუცია:": "Full HD",
      "ეკრანის ტიპი:": "IPS",
      "სენსორული ეკრანი:": "No",
      "განახლების სიხშირე:": "144 Hz",
      "კლავიატურის განათება:": "-",
      "Numpad:": "-",
      "დისკის წამკითხველი:": "No",
      "ვებ კამერა:": "Yes",
      "ლეპტოპის ტიპი:": "გეიმინგი",
      "შიდა მეხსიერება:": "512 GB",
      "შიდა მეხსიერების ტიპი:": "SSD",
      "შიდა მეხსიერების ინტერფეისი:": "M.2",
      "ოპერატიული მეხსიერება:": "16 GB",
      "ოპერატიული მეხსიერების ტიპი:": "DDR5",
      "ოპერატიული მეხსიერების სიხშირე:": "-",
      "USB:": "-",
      "Type-C:": "-",
      "Type-C პორტით დამუხტვა:": "-",
      "HDMI:": "-",
      "ლან პორტი:": "-",
      "3.5mm:": "Yes",
      "წონა:": "-",
      "ფერი:": "Blue"
    }
  },
  {
    "category": "Gaming ლეპტოპები",
    "title": "HP Victus 15 B08XKEA Mica Silver",
    "price": 2499.0,
    "link": "https://zoommer.ge/leptopebi/hp-victus-15-b08xkea-mica-silver-p45692",
    "image": "/_next/image?url=https%3A%2F%2Fs3.zoommer.ge%2Fsite%2F05015d37-596f-45b1-ae45-c81ee20762f6_Thumb.png&w=384&q=50",
    "product_title_detail": "HP Victus 15 B08XKEA Mica Silver",
    "description": "*7007 / +995 (32) 2 60 30 60\nფილიალები\nნავიგაცია\nკალათა\nშესვლა\n%\nმთავარი\nლეპტოპები\nHP\n#ZOOM-035410\nHP Victus 15 B08XKEA Mica Silver\nეკრანის ზომა\n15.6 Inches\nრეზოლუცია\nFull HD\nეკრანის ტიპი\nIPS\nგანახლების სიხშირე\n144 Hz\nშიდა მეხსიერება\n512 GB\nBluetooth\n5.3\nType-C\n1x\nოპერატიული მეხსიერება\n16 GB\nპროდუქტს მოყვება საჩუქარი\nGift Card - 200 ₾\n200 ₾\nერთად იაფია\nდაამატე ნივთი\nHP Victus 15 B08XKEA Mica Silver\n2499 ₾\nRivacase 7562 Anti-Theft Laptop Backpack 15 Grey/Dark blue\n67.15 ₾\n79 ₾\nRazer Gaming Mouse DeathAdder Essential USB White\n52 ₾\n65 ₾\nHavit Gaming Cooling Pad HV-F2035 Black\n41.65 ₾\n49 ₾\nჯამური ფასი (3)\n2659.8 ₾\n2692 ₾\nყიდვა\nაქსესუარები\nაღწერა\nმსგავსი\nმახასიათებლები\nფილიალები\nაქსესუარები\nაღწერა\nმსგავსი\nმახასიათებლები\nფილიალები\n89 ₾\n\nთვეში: 2 ₾ -დან\n\nHavit Gaming Cooling Pad HV-F2083 Black\nდამატება\n39 ₾\n\nთვეში: 1 ₾ -დან\n\nLenovo Casual Backpack B210 Green\nდამატება\n219 ₾\n\nთვეში: 6 ₾ -დან\n\nRazer Gaming Mouse Orochi V2 WL Black\nდამატება\n59 ₾\n\nთვეში: 1 ₾ -დან\n\nHavit Gaming mouse Pad HV-MP901\nდამატება\n69 ₾\n\nთვეში: 1 ₾ -დან\n\nXiaomi Mi Router 4A DVB4230GL White\nდამატება\n129 ₾\n\nთვეში: 3 ₾ -დან\n\nRivacase 7930 Pro 16\nდამატება\n219 ₾\n\nთვეში: 6 ₾ -დან\n\nRazer Gaming Mouse Orochi V2 WL White\nდამატება\n9 ₾\n\nHavit Gaming mouse Pad HV-MP838\nდამატება\n85 ₾\n\nთვეში: 2 ₾ -დან\n\nTP-Link Archer C50 AC1200 White\nდამატება\n59 ₾\n\nთვეში: 1 ₾ -დან\n\nRivacese 8035 Laptop Shoulder Bag 15 Black\nდამატება\n209 ₾\n\nთვეში: 5 ₾ -დან\n\nRazer Gaming Mouse DeathAdder V2 X Hyperspeed WL/BT/U ...\nდამატება\n9 ₾\n\nHavit Gaming mouse Pad HV-MP843 Black\nდამატება\n119 ₾\n\nთვეში: 3 ₾ -დან\n\nTP-Link Archer C6 AC1200 Black\nდამატება\n59 ₾\n\nთვეში: 1 ₾ -დან\n\nRivacase 8037 Laptop Bag 15 Black\nდამატება\n139 ₾\n\nთვეში: 3 ₾ -დან\n\nLogitech Gaming Mouse G402 Hyperion Fury black\nდამატება\n149 ₾\n\nთვეში: 4 ₾ -დან\n\nRazer Mouse Pad Firefly V2 RGB M Black\nდამატება\n159 ₾\n\nთვეში: 4 ₾ -დან\n\nXiaomi Router AX1500 White\nდამატება\n79 ₾\n\nთვეში: 2 ₾ -დან\n\nRivacase 7562 Anti-Theft Laptop Backpack 15 Black\nდამატება\n29 ₾\n\nHavit Gaming Mouse HV-MS1010 Black\nდამატება\n199 ₾\n\nთვეში: 5 ₾ -დან\n\nRazer Mouse Pad Goliathus Extended Chroma XXL Black\nდამატება\n179 ₾\n\nთვეში: 4 ₾ -დან\n\nXiaomi Mesh System AX3000 NE 1 pack White\nდამატება\n79 ₾\n\nთვეში: 2 ₾ -დან\n\nRivacase 7562 Anti-Theft Laptop Backpack 15 Dark grey\nდამატება\n79 ₾\n\nთვეში: 2 ₾ -დან\n\nRazer Gaming Mouse DeathAdder Essential USB Black\nდამატება\n149 ₾\n\nთვეში: 4 ₾ -დან\n\nHyperX Pulsefire Mat RGB Black\nდამატება\n299 ₾\n\nთვეში: 8 ₾ -დან\n\nXiaomi Mesh System AX3000 NE 2 pack White\nდამატება\n79 ₾\n\nთვეში: 2 ₾ -დან\n\nRivacase 7562 Anti-Theft Laptop Backpack 15 Grey/Dark ...\nდამატება\n119 ₾\n\nთვეში: 3 ₾ -დან\n\nHyperX Pulsefire Surge Mouse Black\nდამატება\n29 ₾\n\nHavit Gaming Mouse Pad HV-MP845 Black\nდამატება\n249 ₾\n\nთვეში: 6 ₾ -დან\n\nXiaomi Router BE3600 White\nდამატება\n69 ₾\n\nთვეში: 1 ₾ -დან\n\nRivacase 7532 Anti-Theft Laptop Bag 15 Dark Grey\nდამატება\n469 ₾\n\nთვეში: 13 ₾ -დან\n\nHP OMEN PHOTON Wireless Mouse 6CL96AA Black\nდამატება\n29 ₾\n\nHavit Gaming Mouse Pad HV-MP847 Pink\nდამატება\n69 ₾\n\nთვეში: 1 ₾ -დან\n\nRivacase 7532 Anti-Theft Laptop Bag 15 Grey/Dark Blue ...\nდამატება\n65 ₾\n\nთვეში: 1 ₾ -დან\n\nRazer Gaming Mouse DeathAdder Essential USB White\nდამატება\n29 ₾\n\nHavit Gaming Mouse Pad HV-MP849 Black\nდამატება\n79 ₾\n\nთვეში: 2 ₾ -დან\n\nRivacase 8231 Laptop Bag 15 Black\nდამატება\n239 ₾\n\nთვეში: 6 ₾ -დან\n\nRazer Gaming Mouse Basilisk V3 Black\nდამატება\n49 ₾\n\nთვეში: 1 ₾ -დან\n\nHyperX Pulsefire Mat M Black\nდამატება\n79 ₾\n\nთვეში: 2 ₾ -დან\n\nRivacase 8231 Laptop Bag 15 Star blue\nდამატება\n299 ₾\n\nთვეში: 8 ₾ -დან\n\nRazer Gaming Mouse Naga V2 HyperSpeed WL Black\nდამატება\n59 ₾\n\nთვეში: 1 ₾ -დან\n\nHyperX Pulsefire Mat L Black\nდამატება\n79 ₾\n\nთვეში: 2 ₾ -დან\n\nRivacase 8335 Laptop Bag 15 Black\nდამატება\n229 ₾\n\nთვეში: 6 ₾ -დან\n\nRazer Gaming Mouse Basilisk V3 X HyperSpeed WL Black\nდამატება\n39 ₾\n\nთვეში: 1 ₾ -დან\n\nRazer Mouse Pad Sphex V3 S Black\nდამატება\n79 ₾\n\nთვეში: 2 ₾ -დან\n\nRivacase 8335 Laptop Bag 15 Star blue\nდამატება\n129 ₾\n\nთვეში: 3 ₾ -დან\n\nRazer Gaming Mouse Cobra Black\nდამატება\n89 ₾\n\nთვეში: 2 ₾ -დან\n\nRazer Mouse Pad Sphex V3 L Black\nდამატება\n69 ₾\n\nთვეში: 1 ₾ -დან\n\nRivacase 7730 Eco Laptop Shoulder Bag 15 Black\nდამატება\n19 ₾\n\nHavit Gaming Mouse HV-MS989GT Black/Red\nდამატება\n29 ₾\n\nHavit Gaming mouse Pad HV-MP860\nდამატება\n59 ₾\n\nთვეში: 1 ₾ -დან\n\nRivacase 8035 Laptop Shoulder Bag 15\nდამატება\n19 ₾\n\nHavit Gaming Mouse HV-MS626GT Black\nდამატება\n79 ₾\n\nთვეში: 2 ₾ -დან\n\nTomtoc Defender A13 Laptop Sleeve 15 A13E3D1 Black\nდამატება\n19 ₾\n\nHavit Gaming Mouse HV-MS66GT White/Blue\nდამატება\n119 ₾\n\nთვეში: 3 ₾ -დან\n\nTomtoc Defender A42 Laptop Briefcase 15 A42E1D1 Black\nდამატება\n149 ₾\n\nთვეში: 4 ₾ -დან\n\nHyperX Gaming Mouse Pulsefire Haste 2 Black\nდამატება\n79 ₾\n\nთვეში: 2 ₾ -დან\n\nHP Campus backpack 15.6 7J595AA Green\nდამატება\n19 ₾\n\nHavit Wireless Mouse HV-MS66GT Black\nდამატება\n79 ₾\n\nთვეში: 2 ₾ -დან\n\nHP Campus backpack 15.6 7J597AA Lavender\nდამატება\n179 ₾\n\nთვეში: 4 ₾ -დან\n\nLogitech Gaming Mouse G305 LIGHTSPEED WL L910-005282 ...\nდამატება\n69 ₾\n\nთვეში: 1 ₾ -დან\n\nRivacase 8065 Laptop Backpack 15 Black\nდამატება\n259 ₾\n\nთვეში: 7 ₾ -დან\n\nLogitech Gaming Mouse G502 X L910-006138 Black\nდამატება\n69 ₾\n\nთვეში: 1 ₾ -დან\n\nRivacase 8065 Laptop Backpack 15 Dark Blue\nდამატება\n259 ₾\n\nთვეში: 7 ₾ -დან\n\nLogitech Gaming Mouse G502 X L910-006138 White\nდამატება\n79 ₾\n\nთვეში: 2 ₾ -დან\n\nRivacase 8335 Laptop Bag 15 Purple\nდამატება\n19 ₾\n\nHavit Gaming Mouse HV-MS626GT Black/Red\nდამატება\n19 ₾\n\nHavit Gaming Mouse HV-MS626GT Black/Blue\nდამატება\n349 ₾\n\nთვეში: 9 ₾ -დან\n\nLogitech Gaming Mouse G703 LIGHTSPEED WL L910-005640 ...\nდამატება\n89 ₾\n\nთვეში: 2 ₾ -დან\n\nLogitech Gaming Mouse G102 LIGHTSYNC L910-005823 Blac ...\nდამატება\n89 ₾\n\nთვეში: 2 ₾ -დან\n\nLogitech Gaming Mouse G102 LIGHTSYNC L910-005824 Whit ...\nდამატება\n89 ₾\n\nთვეში: 2 ₾ -დან\n\nLogitech Gaming Mouse G102 LIGHTSYNC L910-005801 Blue\nდამატება\n239 ₾\n\nთვეში: 6 ₾ -დან\n\nLogitech Gaming Mouse G502 HERO L910-005470 Black\nდამატება\n199 ₾\n\nთვეში: 5 ₾ -დან\n\nHyperX Pulsefire Haste 2 core Wireless Black\nდამატება\n199 ₾\n\nთვეში: 5 ₾ -დან\n\nHyperX Pulsefire Haste 2 core Wireless White\nდამატება\n59 ₾\n\nთვეში: 1 ₾ -დან\n\nHavit Gaming Mouse HV-MS954 Black\nდამატება\n39 ₾\n\nთვეში: 1 ₾ -დან\n\nHavit Gaming Mouse HV-MS1033 White\nდამატება\n39 ₾\n\nთვეში: 1 ₾ -დან\n\nHavit Gaming Mouse HV-MS1029 Pink\nდამატება\n59 ₾\n\nთვეში: 1 ₾ -დან\n\nHavit Gaming Mouse HV-MS966 Black/Green\nდამატება\n49 ₾\n\nთვეში: 1 ₾ -დან\n\nHavit Wireless Mouse HV-MS1039W Black/White\nდამატება\n79 ₾\n\nთვეში: 2 ₾ -დან\n\nHavit Wireless Mouse HV-MS970WB Pro Black\nდამატება\n79 ₾\n\nთვეში: 2 ₾ -დან\n\nHavit Wireless Mouse HV-MS970WB Pro Transparent White\nდამატება\n219 ₾\n\nთვეში: 6 ₾ -დან\n\nRazer Gaming Mouse Orochi V2 WL Pink\nდამატება\nპროდუქტის შესახებ\n\nთუ ეძებთ ლეპტოპს, რომელიც მარტივად გაუმკლავდება ყველაზე მოთხოვნად თამაშებს — HP Victus 15 B08XKEA Mica Silver შექმნილია სწორედ თქვენთვის. ეს მოდელი აერთიანებს მაღალ წარმადობას, გამძლე კონსტრუქციასა ...\n\nმეტის ნახვა\nმსგავსი პროდუქტები\n2999 ₾\n\nთვეში: 83 ₾ -დან\n\nHP Victus 15 84J97EA, Intel core i5-13500H, Nvidia Ge ...\nდამატება\n2499 ₾\n\nთვეში: 69 ₾ -დან\n\nHP Victus 15 84J98EA, Intel Core i5-13420H Octa 4.6 G ...\nდამატება\n2499 ₾\n\nთვეში: 69 ₾ -დან\n\nHP Victus 15 84J99EA, Intel Core i5-13420H Octa 4.6 G ...\nდამატება\n3199 ₾\n3399 ₾\n\nთვეში: 88 ₾ -დან\n\nHP Victus 15 8F5J3EA Mica Silver\nდამატება\n3499 ₾\n3699 ₾\n\nთვეში: 97 ₾ -დან\n\nHP Omen 16 A1WF1EA, Intel Core i5-14500HX, Nvidia GeF ...\nდამატება\n2799 ₾\n2999 ₾\n\nთვეში: 77 ₾ -დან\n\nHP Victus 15 A1WD6EA, AMD Ryzen 5-8645HS, NVIDIA GeFo ...\nდამატება\n3379 ₾\n\nთვეში: 93 ₾ -დან\n\nHP Victus 16 A1WE4EA, Intel Core i5-14450HX, Nvidia G ...\nდამატება\n2899 ₾\n2999 ₾\n\nთვეში: 80 ₾ -დან\n\nHP Victus 15 A1WD5EA Mica Silver\nდამატება\n3999 ₾\n5599 ₾\n\nთვეში: 111 ₾ -დან\n\nHP Omen 14 A1AA7EA Black\nდამატება\n2999 ₾\n3099 ₾\n\nთვეში: 83 ₾ -დან\n\nHP Victus 16 A1AB6EA Mica Silver\nდამატება\n2899 ₾\n2999 ₾\n\nთვეში: 80 ₾ -დან\n\nHP Victus 16 A1AB7EA Mica Silver\nდამატება\n3999 ₾\n4199 ₾\n\nთვეში: 111 ₾ -დან\n\nHP Victus 16 B09JXEA Mica Silver\nდამატება\n3299 ₾\n3499 ₾\n\nთვეში: 91 ₾ -დან\n\nHP Victus 15 A74LKEA Blue\nდამატება\n2799 ₾\n3199 ₾\n\nთვეში: 77 ₾ -დან\n\nHP Victus 15 B09J6EA Blue\nდამატება\nGIFTS\n2799 ₾\n2999 ₾\n\nთვეში: 77 ₾ -დან\n\nHP Victus 15 B84VTEA Silver\nდამატება\n5699 ₾\n\nთვეში: 158 ₾ -დან\n\nHP Omen Max 16 BG7J7EA, Intel Core Ultra 7-255HX 20c, ...\nდამატება\nდამატებითი მახასიათებლები\nბრენდი\nბრენდი:\n\t\nHP\nმოდელი\nმოდელი:\n\t\nVictus\nტექნიკური მახასიათებლები\nცენტრალური პროცესორი:\n\t\nAMD Ryzen 5-8645HS\n\n\nპროცესორის თაობა:\n\t\nRyzen 5 8000 Series\n\n\nპროცესორის სიხშირე:\n\t\n4.3 GHz ~ 5.0 GHz\n\n\nბირთვების რაოდენობა:\n\t\n6\n\n\nნაკადების რაოდენობა:\n\t\n12\n\n\nგრაფიკული პროცესორი:\n\t\nNvidia GeForce RTX 2050\n\n\nგრაფიკული პროცესორის მეხსიერება:\n\t\n4 GB\n\n\nგრაფიკული პროცესორის ტიპი:\n\t\nარა ინტეგრირებული\n\n\nოპერაციული სისტემა:\n\t\nNo\n\n\nBluetooth:\n\t\n5.3\nეკრანი\nეკრანის ზომა:\n\t\n15.6 Inches\n\n\nრეზოლუცია:\n\t\nFull HD\n\n\nეკრანის ტიპი:\n\t\nIPS\n\n\nსენსორული ეკრანი:\n\t\nNo\n\n\nგანახლების სიხშირე:\n\t\n144 Hz\nდამატებითი მახასიათებლები\nკლავიატურის განათება:\n\t\nYes\n\n\nNumpad:\n\t\nYes\n\n\nდისკის წამკითხველი:\n\t\nNo\n\n\nვებ კამერა:\n\t\nYes\n\n\nლეპტოპის ტიპი:\n\t\nგეიმინგი\nმეხსიერება\nშიდა მეხსიერება:\n\t\n512 GB\n\n\nშიდა მეხსიერების ტიპი:\n\t\nSSD\n\n\nშიდა მეხსიერების ინტერფეისი:\n\t\nM.2\n\n\nოპერატიული მეხსიერება:\n\t\n16 GB\n\n\nოპერატიული მეხსიერების ტიპი:\n\t\nDDR5\n\n\nოპერატიული მეხსიერების სიხშირე:\n\t\n5600 MHz\nპორტები\nUSB:\n\t\n2 x USB-A\n\n\nType-C:\n\t\n1x\n\n\nType-C პორტით დამუხტვა:\n\t\nNo\n\n\nHDMI:\n\t\nYes\n\n\nლან პორტი:\n\t\nYes\n\n\n3.5mm:\n\t\nYes\nზომა/წონა\nწონა:\n\t\n2.29 kg\nფერი\nფერი:\n\t\nMica Silver\nმეტის ნახვა\nგაეცანი საგარანტიო პირობებს\nსაგარანტიო პირობები\nფილიალები\nმარაგშია\nშეკვეთიდან 2-5 დღეში\nზუმერის წერეთლის ფილიალი\n\nთბილისი - წერეთლის გამზირი, N1.\n\nმარაგშია\n+995 591 967 601\nორშ-შაბ: 10:00:00 - 20:00:00\nკვირა: 10:00:00 - 19:00:00\nზუმერის \"თბილისი ცენტრალის\" ფილიალი\n\nთბილისი - \"თბილისი ცენტრალი\"- lll სართული\n\nმარაგშია\n+995 599 862 449\nორშ-შაბ: 10:00:00 - 20:00:00\nკვირა: 10:00:00 - 19:00:00\nზუმერის City Mall საბურთალო-ს ფილიალი\n\nთბილისი - \"სითი მოლი\" - პეტრე ქავთარაძის N1\n\nმარაგშია\n+995 591 971 962\nორშ-შაბ: 10:00:00 - 22:00:00\nკვირა: 10:00:00 - 22:00:00\nზუმერის თბილისი მოლის ფილიალი\n\nთბილისი - „თბილისი მოლი\" - I სართული. აღმაშენებლის ხეივანი მე-16 კმ\n\nმარაგშია\n+995 591 967 608\nორშ-შაბ: 10:00:00 - 22:00:00\nკვირა: 10:00:00 - 22:00:00\nზუმერის \"გლდანი მოლის\" ფილიალი\n\nთბილისი - \"გლდანი მოლი\" - I სართული, M-ახმეტელის მიმდებარე\n\nმარაგშია\n+995 591 967 673\nორშ-შაბ: 10:00:00 - 21:00:00\nკვირა: 10:00:00 - 21:00:00\nზუმერის ისთ ფოინთის ფილიალი\n\nთბილისი - \"ისთ ფოინთი\" - ალ. თვალჭრელიძე N2\n\nმარაგშია\n+995 591 340 476\nორშ-შაბ: 10:00:00 - 22:00:00\nკვირა: 10:00:00 - 22:00:00\nზუმერი რუსთავი მოლის ფილიალი\n\nრუსთავი - შარტავას და ლომოურის კვეთა\n\nმარაგშია\n+995 591 441 082\nორშ-შაბ: 10:00:00 - 22:00:00\nკვირა: 10:00:00 - 22:00:00\nბათუმი ჭავჭავაძის ფილიალი\n\nბათუმი - ბათუმი, ჭავჭავაძის N21\n\nმარაგშია\n+995 591 967 606\nორშ-შაბ: 10:00:00 - 20:00:00\nკვირა: 10:00:00 - 19:00:00\nბათუმის \"Black Sea Mall\"-ის ფილიალი\n\nბათუმი - \"Black Sea Mall\" - ტბელ აბუსერიძის N22\n\nმარაგშია\n+995 591 310 257\nორშ-შაბ: 10:00:00 - 21:00:00\nკვირა: 10:00:00 - 21:00:00\nბათუმის გრანდ მოლის ფილიალი\n\nბათუმი - \"გრანდ მოლი\" - შერიფ ხიმშიაშვილის 29\n\nმარაგშია\n+995 591 022 872\nორშ-შაბ: 10:00:00 - 22:00:00\nკვირა: 10:00:00 - 22:00:00\nზუგდიდი მოლის ფილიალი\n\nზუგდიდი - ზუგდიდი მოლი, კოსტავას ქუჩა №28\n\nმარაგშია\n+995 591 676 489\nორშ-შაბ: 10:00:00 - 22:00:00\nკვირა: 10:00:00 - 22:00:00\nგორი მოლის ფილიალი\n\nგორი - გორი, ცხინვალის გზატკეცილი 14-14ამ, გორი მოლი\n\nმარაგშია\n+995 591 198 248\nორშ-შაბ: 10:00:00 - 22:00:00\nკვირა: 10:00:00 - 22:00:00\nთელავი მოლის ფილიალი\n\nთელავი - \"თელავი მოლი\" - ალაზნის ქ.N77\n\nმარაგშია\n+995 595 069 853\nორშ-შაბ: 10:00:00 - 20:00:00\nკვირა: 10:00:00 - 19:00:00\nზუმერის საბითუმო საწყობი\n\nთბილისი - აკაკი წერეთლის გამზირი 1, საბითუმო საწყობი, -1 სართული\n\nმარაგშია\n+995 (32) 2 60 30 60\nორშ-შაბ: 10:00:00 - 19:00:00\nკვირა: 10:00:00 - 19:00:00\nმეტის ნახვა\n2499 ₾\n2599 ₾\n\nთვეში: 69.4 ₾ -დან\n\nმარაგი ფილიალებში\nფასის დაზღვევა\nფასის კონტროლი\nფასის დაჯავშნა\nყიდვა\nშედარება\nდამატება\nნავიგაცია\nგადახდები\nგამოგვყევი\n\nFacebook\n\nYoutube\n\nInstagram\n\nTik Tok\n\nკონტაქტი\n\nInfo@zoommer.ge\n\n+995 (32) 2 60 30 60 / *7007\n\nფილიალები\n\nკორპორატიული გაყიდვები\n\nZoommer App\n\nCopyright © 2023 Zoommer.ge. All rights reserved.\n\nCookie პოლიტიკა\n\nსაიტით სარგებლობის გაგრძელებით, შენ ეთანხმები Cookie ჩანაწერების გამოყენებას. მეტი ინფორმაცისათვის იხილეთ კონფიდენციალურობის პოლიტიკა\n\nგასაგებია",
    "specs": {
      "ბრენდი:": "HP",
      "მოდელი:": "Victus",
      "ცენტრალური პროცესორი:": "AMD Ryzen 5-8645HS",
      "პროცესორის თაობა:": "Ryzen 5 8000 Series",
      "პროცესორის სიხშირე:": "4.3 GHz ~ 5.0 GHz",
      "ბირთვების რაოდენობა:": "6",
      "ნაკადების რაოდენობა:": "12",
      "გრაფიკული პროცესორი:": "Nvidia GeForce RTX 2050",
      "გრაფიკული პროცესორის მეხსიერება:": "4 GB",
      "გრაფიკული პროცესორის ტიპი:": "არა ინტეგრირებული",
      "ოპერაციული სისტემა:": "No",
      "Bluetooth:": "5.3",
      "ეკრანის ზომა:": "15.6 Inches",
      "რეზოლუცია:": "Full HD",
      "ეკრანის ტიპი:": "IPS",
      "სენსორული ეკრანი:": "No",
      "განახლების სიხშირე:": "144 Hz",
      "კლავიატურის განათება:": "Yes",
      "Numpad:": "Yes",
      "დისკის წამკითხველი:": "No",
      "ვებ კამერა:": "Yes",
      "ლეპტოპის ტიპი:": "გეიმინგი",
      "შიდა მეხსიერება:": "512 GB",
      "შიდა მეხსიერების ტიპი:": "SSD",
      "შიდა მეხსიერების ინტერფეისი:": "M.2",
      "ოპერატიული მეხსიერება:": "16 GB",
      "ოპერატიული მეხსიერების ტიპი:": "DDR5",
      "ოპერატიული მეხსიერების სიხშირე:": "5600 MHz",
      "USB:": "2 x USB-A",
      "Type-C:": "1x",
      "Type-C პორტით დამუხტვა:": "No",
      "HDMI:": "Yes",
      "ლან პორტი:": "Yes",
      "3.5mm:": "Yes",
      "წონა:": "2.29 kg",
      "ფერი:": "Mica Silver"
    }
  },
  {
    "category": "Gaming ლეპტოპები",
    "title": "Asus TUF 15 FA506NFR-HN021, AMD Ryzen 7 7435HS, Nvidi ...",
    "price": 2179.0,
    "link": "https://zoommer.ge/leptopebi/asus-tuf-15-fa506nfr-hn021-amd-ryzen-7-7435hs-nvidia-geforce-rtx-2050-16gb-ram-p45472",
    "image": "/_next/image?url=https%3A%2F%2Fs3.zoommer.ge%2Fsite%2F191ee0cc-6d6b-4dfe-806b-d2b89369ee1a_Thumb.jpeg&w=384&q=50",
    "product_title_detail": "Asus TUF 15 FA506NFR-HN021, AMD Ryzen 7 7435HS, Nvidia GeForce RTX 2050, 16GB RAM SSD 512GB, Free Dos, ლეპტოპი",
    "description": "*7007 / +995 (32) 2 60 30 60\nსავაჭრო პოლიტიკა\nგანვადება\nკარიერა\nTrade In\nფილიალები\nნავიგაცია\nკალათა\nშესვლა\n%\nმთავარი\nლეპტოპები\nAsus\n#ZOOM-035294\nAsus TUF 15 FA506NFR-HN021, AMD Ryzen 7 7435HS, Nvidia GeForce RTX 2050, 16GB RAM SSD 512GB, Free Dos, ლეპტოპი\nეკრანის ზომა\n15.6 Inches\nრეზოლუცია\nFull HD\nეკრანის ტიპი\nIPS\nგანახლების სიხშირე\n-\nშიდა მეხსიერება\n512 GB\nBluetooth\nYes\nType-C\n-\nოპერატიული მეხსიერება\n16 GB\nერთად იაფია\nდაამატე ნივთი\nAsus TUF 15 FA506NFR-HN021, AMD Ryzen 7 7435HS, Nvidia GeForce RTX 2050, 16GB RAM SSD 512GB, Free Dos, ლეპტოპი\n2179 ₾\nRivacase 7562 Anti-Theft Laptop Backpack 15 Grey/Dark blue\n67.15 ₾\n79 ₾\nRazer Gaming Mouse DeathAdder Essential USB White\n52 ₾\n65 ₾\nHavit Gaming Cooling Pad HV-F2083 Black\n75.65 ₾\n89 ₾\nჯამური ფასი (3)\n2373.8 ₾\n2412 ₾\nყიდვა\nაქსესუარები\nაღწერა\nმსგავსი\nმახასიათებლები\nფილიალები\nაქსესუარები\nაღწერა\nმსგავსი\nმახასიათებლები\nფილიალები\n89 ₾\n\nთვეში: 2 ₾ -დან\n\nHavit Gaming Cooling Pad HV-F2083 Black\nდამატება\n39 ₾\n\nთვეში: 1 ₾ -დან\n\nLenovo Casual Backpack B210 Green\nდამატება\n219 ₾\n\nთვეში: 6 ₾ -დან\n\nRazer Gaming Mouse Orochi V2 WL Black\nდამატება\n59 ₾\n\nთვეში: 1 ₾ -დან\n\nHavit Gaming mouse Pad HV-MP901\nდამატება\n69 ₾\n\nთვეში: 1 ₾ -დან\n\nXiaomi Mi Router 4A DVB4230GL White\nდამატება\n129 ₾\n\nთვეში: 3 ₾ -დან\n\nRivacase 7930 Pro 16\nდამატება\n219 ₾\n\nთვეში: 6 ₾ -დან\n\nRazer Gaming Mouse Orochi V2 WL White\nდამატება\n9 ₾\n\nHavit Gaming mouse Pad HV-MP838\nდამატება\n85 ₾\n\nთვეში: 2 ₾ -დან\n\nTP-Link Archer C50 AC1200 White\nდამატება\n59 ₾\n\nთვეში: 1 ₾ -დან\n\nRivacese 8035 Laptop Shoulder Bag 15 Black\nდამატება\n209 ₾\n\nთვეში: 5 ₾ -დან\n\nRazer Gaming Mouse DeathAdder V2 X Hyperspeed WL/BT/U ...\nდამატება\n29 ₾\n\nRazer Mouse Pad Goliathus Mobile Black/Green\nდამატება\n119 ₾\n\nთვეში: 3 ₾ -დან\n\nTP-Link Archer C6 AC1200 Black\nდამატება\n59 ₾\n\nთვეში: 1 ₾ -დან\n\nRivacase 8037 Laptop Bag 15 Black\nდამატება\n139 ₾\n\nთვეში: 3 ₾ -დან\n\nLogitech Gaming Mouse G402 Hyperion Fury black\nდამატება\n29 ₾\n\nRazer Mouse Pad Goliathus Mobile Stealth Edition Blac ...\nდამატება\n159 ₾\n\nთვეში: 4 ₾ -დან\n\nXiaomi Router AX1500 White\nდამატება\n79 ₾\n\nთვეში: 2 ₾ -დან\n\nRivacase 7562 Anti-Theft Laptop Backpack 15 Black\nდამატება\n29 ₾\n\nHavit Gaming Mouse HV-MS1010 Black\nდამატება\n59 ₾\n\nთვეში: 1 ₾ -დან\n\nRazer Mouse Pad Gigantus V2 Large Black\nდამატება\n179 ₾\n\nთვეში: 4 ₾ -დან\n\nXiaomi Mesh System AX3000 NE 1 pack White\nდამატება\n79 ₾\n\nთვეში: 2 ₾ -დან\n\nRivacase 7562 Anti-Theft Laptop Backpack 15 Dark grey\nდამატება\n79 ₾\n\nთვეში: 2 ₾ -დან\n\nRazer Gaming Mouse DeathAdder Essential USB Black\nდამატება\n49 ₾\n\nთვეში: 1 ₾ -დან\n\nRazer Mouse Pad Gigantus V2 Medium Black\nდამატება\n299 ₾\n\nთვეში: 8 ₾ -დან\n\nXiaomi Mesh System AX3000 NE 2 pack White\nდამატება\n79 ₾\n\nთვეში: 2 ₾ -დან\n\nRivacase 7562 Anti-Theft Laptop Backpack 15 Grey/Dark ...\nდამატება\n119 ₾\n\nთვეში: 3 ₾ -დან\n\nHyperX Pulsefire Surge Mouse Black\nდამატება\n9 ₾\n\nHavit Gaming mouse Pad HV-MP843 Black\nდამატება\n249 ₾\n\nთვეში: 6 ₾ -დან\n\nXiaomi Router BE3600 White\nდამატება\n69 ₾\n\nთვეში: 1 ₾ -დან\n\nRivacase 7532 Anti-Theft Laptop Bag 15 Dark Grey\nდამატება\n469 ₾\n\nთვეში: 13 ₾ -დან\n\nHP OMEN PHOTON Wireless Mouse 6CL96AA Black\nდამატება\n149 ₾\n\nთვეში: 4 ₾ -დან\n\nRazer Mouse Pad Firefly V2 RGB M Black\nდამატება\n69 ₾\n\nთვეში: 1 ₾ -დან\n\nRivacase 7532 Anti-Theft Laptop Bag 15 Grey/Dark Blue ...\nდამატება\n65 ₾\n\nთვეში: 1 ₾ -დან\n\nRazer Gaming Mouse DeathAdder Essential USB White\nდამატება\n199 ₾\n\nთვეში: 5 ₾ -დან\n\nRazer Mouse Pad Goliathus Extended Chroma XXL Black\nდამატება\n79 ₾\n\nთვეში: 2 ₾ -დან\n\nRivacase 8231 Laptop Bag 15 Black\nდამატება\n239 ₾\n\nთვეში: 6 ₾ -დან\n\nRazer Gaming Mouse Basilisk V3 Black\nდამატება\n149 ₾\n\nთვეში: 4 ₾ -დან\n\nHyperX Pulsefire Mat RGB Black\nდამატება\n79 ₾\n\nთვეში: 2 ₾ -დან\n\nRivacase 8231 Laptop Bag 15 Star blue\nდამატება\n299 ₾\n\nთვეში: 8 ₾ -დან\n\nRazer Gaming Mouse Naga V2 HyperSpeed WL Black\nდამატება\n29 ₾\n\nHavit Gaming Mouse Pad HV-MP845 Black\nდამატება\n79 ₾\n\nთვეში: 2 ₾ -დან\n\nRivacase 8335 Laptop Bag 15 Black\nდამატება\n229 ₾\n\nთვეში: 6 ₾ -დან\n\nRazer Gaming Mouse Basilisk V3 X HyperSpeed WL Black\nდამატება\n29 ₾\n\nHavit Gaming Mouse Pad HV-MP847 Pink\nდამატება\n79 ₾\n\nთვეში: 2 ₾ -დან\n\nRivacase 8335 Laptop Bag 15 Star blue\nდამატება\n129 ₾\n\nთვეში: 3 ₾ -დან\n\nRazer Gaming Mouse Cobra Black\nდამატება\n29 ₾\n\nHavit Gaming Mouse Pad HV-MP849 Black\nდამატება\n69 ₾\n\nთვეში: 1 ₾ -დან\n\nRivacase 7730 Eco Laptop Shoulder Bag 15 Black\nდამატება\n19 ₾\n\nHavit Gaming Mouse HV-MS989GT Black/Red\nდამატება\n49 ₾\n\nთვეში: 1 ₾ -დან\n\nHyperX Pulsefire Mat M Black\nდამატება\n59 ₾\n\nთვეში: 1 ₾ -დან\n\nRivacase 8035 Laptop Shoulder Bag 15\nდამატება\n19 ₾\n\nHavit Gaming Mouse HV-MS626GT Black\nდამატება\n59 ₾\n\nთვეში: 1 ₾ -დან\n\nHyperX Pulsefire Mat L Black\nდამატება\n79 ₾\n\nთვეში: 2 ₾ -დან\n\nTomtoc Defender A13 Laptop Sleeve 15 A13E3D1 Black\nდამატება\n19 ₾\n\nHavit Gaming Mouse HV-MS66GT White/Blue\nდამატება\n39 ₾\n\nთვეში: 1 ₾ -დან\n\nRazer Mouse Pad Sphex V3 S Black\nდამატება\n119 ₾\n\nთვეში: 3 ₾ -დან\n\nTomtoc Defender A42 Laptop Briefcase 15 A42E1D1 Black\nდამატება\n149 ₾\n\nთვეში: 4 ₾ -დან\n\nHyperX Gaming Mouse Pulsefire Haste 2 Black\nდამატება\n89 ₾\n\nთვეში: 2 ₾ -დან\n\nRazer Mouse Pad Sphex V3 L Black\nდამატება\n79 ₾\n\nთვეში: 2 ₾ -დან\n\nHP Campus backpack 15.6 7J595AA Green\nდამატება\n19 ₾\n\nHavit Wireless Mouse HV-MS66GT Black\nდამატება\n29 ₾\n\nHavit Gaming mouse Pad HV-MP860\nდამატება\n79 ₾\n\nთვეში: 2 ₾ -დან\n\nHP Campus backpack 15.6 7J597AA Lavender\nდამატება\n179 ₾\n\nთვეში: 4 ₾ -დან\n\nLogitech Gaming Mouse G305 LIGHTSPEED WL L910-005282 ...\nდამატება\n25 ₾\n\nHavit Gaming mouse Pad HV-MP861\nდამატება\n69 ₾\n\nთვეში: 1 ₾ -დან\n\nRivacase 8065 Laptop Backpack 15 Black\nდამატება\n259 ₾\n\nთვეში: 7 ₾ -დან\n\nLogitech Gaming Mouse G502 X L910-006138 Black\nდამატება\n99 ₾\n\nთვეში: 2 ₾ -დან\n\nSpigen Desk Pad Black with Magnetic Cable Holder LD30 ...\nდამატება\n69 ₾\n\nთვეში: 1 ₾ -დან\n\nRivacase 8065 Laptop Backpack 15 Dark Blue\nდამატება\n259 ₾\n\nთვეში: 7 ₾ -დან\n\nLogitech Gaming Mouse G502 X L910-006138 White\nდამატება\n79 ₾\n\nთვეში: 2 ₾ -დან\n\nRivacase 8335 Laptop Bag 15 Purple\nდამატება\n19 ₾\n\nHavit Gaming Mouse HV-MS626GT Black/Red\nდამატება\n19 ₾\n\nHavit Gaming Mouse HV-MS626GT Black/Blue\nდამატება\n349 ₾\n\nთვეში: 9 ₾ -დან\n\nLogitech Gaming Mouse G703 LIGHTSPEED WL L910-005640 ...\nდამატება\n89 ₾\n\nთვეში: 2 ₾ -დან\n\nLogitech Gaming Mouse G102 LIGHTSYNC L910-005823 Blac ...\nდამატება\n89 ₾\n\nთვეში: 2 ₾ -დან\n\nLogitech Gaming Mouse G102 LIGHTSYNC L910-005824 Whit ...\nდამატება\n89 ₾\n\nთვეში: 2 ₾ -დან\n\nLogitech Gaming Mouse G102 LIGHTSYNC L910-005801 Blue\nდამატება\n239 ₾\n\nთვეში: 6 ₾ -დან\n\nLogitech Gaming Mouse G502 HERO L910-005470 Black\nდამატება\n199 ₾\n\nთვეში: 5 ₾ -დან\n\nHyperX Pulsefire Haste 2 core Wireless Black\nდამატება\n199 ₾\n\nთვეში: 5 ₾ -დან\n\nHyperX Pulsefire Haste 2 core Wireless White\nდამატება\n59 ₾\n\nთვეში: 1 ₾ -დან\n\nHavit Gaming Mouse HV-MS954 Black\nდამატება\n39 ₾\n\nთვეში: 1 ₾ -დან\n\nHavit Gaming Mouse HV-MS1033 White\nდამატება\n39 ₾\n\nთვეში: 1 ₾ -დან\n\nHavit Gaming Mouse HV-MS1029 Pink\nდამატება\n59 ₾\n\nთვეში: 1 ₾ -დან\n\nHavit Gaming Mouse HV-MS966 Black/Green\nდამატება\n49 ₾\n\nთვეში: 1 ₾ -დან\n\nHavit Wireless Mouse HV-MS1039W Black/White\nდამატება\n79 ₾\n\nთვეში: 2 ₾ -დან\n\nHavit Wireless Mouse HV-MS970WB Pro Black\nდამატება\n79 ₾\n\nთვეში: 2 ₾ -დან\n\nHavit Wireless Mouse HV-MS970WB Pro Transparent White\nდამატება\n219 ₾\n\nთვეში: 6 ₾ -დან\n\nRazer Gaming Mouse Orochi V2 WL Pink\nდამატება\nპროდუქტის შესახებ\n\nთუ ეძებთ ლეპტოპს, რომელიც მარტივად გაუმკლავდება ყველაზე მოთხოვნად თამაშებს — Asus TUF 15 FA506NFR-HN021 შექმნილია სწორედ თქვენთვის. ეს მოდელი აერთიანებს მაღალ წარმადობას, გამძლე კონსტრუქციასა და თვა...\n\nმეტის ნახვა\nმსგავსი პროდუქტები\n2599 ₾\n2799 ₾\n\nთვეში: 72 ₾ -დან\n\nAsus TUF 15 FX507ZC4-HN009 Black\nდამატება\n2249 ₾\n2499 ₾\n\nთვეში: 62 ₾ -დან\n\nAsus TUF 15 FA506NF-HN018, AMD Ryzen 5-7535HS, NVIDIA ...\nდამატება\n2999 ₾\n3699 ₾\n\nთვეში: 83 ₾ -დან\n\nAsus TUF 15 FA507NUR-LP044 Mercha Grey\nდამატება\n3299 ₾\n3499 ₾\n\nთვეში: 91 ₾ -დან\n\nAsus TUF 14 FA401UU-RG013 Jaeger Grey\nდამატება\n4179 ₾\n\nთვეში: 116 ₾ -დან\n\nAsus TUF A16 FA608WV-QT053 Grey\nდამატება\n5599 ₾\n5899 ₾\n\nთვეში: 155 ₾ -დან\n\nAsus TUF 18 FA808UP-S8030 Grey\nდამატება\n7299 ₾\n\nთვეში: 202 ₾ -დან\n\nAsus ROG Strix 16 G615JPR-S5101 Grey\nდამატება\n10399 ₾\n10499 ₾\n\nთვეში: 288 ₾ -დან\n\nAsus ROG Strix 18 G835LR-SA005 Black\nდამატება\n15999 ₾\n\nთვეში: 444 ₾ -დან\n\nAsus ROG Strix 18 G835LX-SA034W Black\nდამატება\n6499 ₾\n\nთვეში: 180 ₾ -დან\n\nAsus ROG Strix 16 G614PR-RV007, AMD Ryzen 9-7940HX, N ...\nდამატება\n6699 ₾\n\nთვეში: 186 ₾ -დან\n\nAsus ROG Strix G16 G615JPR-RV113, Intel core i7-14650 ...\nდამატება\n8499 ₾\n\nთვეში: 236 ₾ -დან\n\nAsus ROG Strix G18 G815LR-S9085, Intel Core Ultra 9 2 ...\nდამატება\n4999 ₾\n\nთვეში: 138 ₾ -დან\n\nAsus TUF F16 FX608JMR-RV073, Intel core i7-14650HX 16 ...\nდამატება\n2699 ₾\n\nთვეში: 74 ₾ -დან\n\nAsus TUF 16 FX607VJ-RL005, Intel Core 5-210H, Nvidia ...\nდამატება\n4199 ₾\n\nთვეში: 116 ₾ -დან\n\nAsus TUF F16 FX608JHR-RV035, Intel core i7-14650HX 16 ...\nდამატება\nდამატებითი მახასიათებლები\nბრენდი\nბრენდი:\n\t\nAsus\nმოდელი\nმოდელი:\n\t\nTUF 15\nტექნიკური მახასიათებლები\nცენტრალური პროცესორი:\n\t\nAMD Ryzen 7 7435HS\n\n\nპროცესორის თაობა:\n\t\nRyzen 7 7000 Series\n\n\nპროცესორის სიხშირე:\n\t\n3.1 GHz ~ 4.5 GHz\n\n\nბირთვების რაოდენობა:\n\t\n8\n\n\nნაკადების რაოდენობა:\n\t\n16\n\n\nგრაფიკული პროცესორი:\n\t\nNvidia GeForce RTX 2050\n\n\nგრაფიკული პროცესორის მეხსიერება:\n\t\n-\n\n\nგრაფიკული პროცესორის ტიპი:\n\t\nარა ინტეგრირებული\n\n\nოპერაციული სისტემა:\n\t\nNo\n\n\nBluetooth:\n\t\nYes\nეკრანი\nეკრანის ზომა:\n\t\n15.6 Inches\n\n\nრეზოლუცია:\n\t\nFull HD\n\n\nეკრანის ტიპი:\n\t\nIPS\n\n\nსენსორული ეკრანი:\n\t\nNo\n\n\nგანახლების სიხშირე:\n\t\n-\nდამატებითი მახასიათებლები\nკლავიატურის განათება:\n\t\n-\n\n\nNumpad:\n\t\n-\n\n\nდისკის წამკითხველი:\n\t\nNo\n\n\nვებ კამერა:\n\t\n-\n\n\nლეპტოპის ტიპი:\n\t\nგეიმინგი\nმეხსიერება\nშიდა მეხსიერება:\n\t\n512 GB\n\n\nშიდა მეხსიერების ტიპი:\n\t\nSSD\n\n\nშიდა მეხსიერების ინტერფეისი:\n\t\nM.2\n\n\nოპერატიული მეხსიერება:\n\t\n16 GB\n\n\nოპერატიული მეხსიერების ტიპი:\n\t\n-\n\n\nოპერატიული მეხსიერების სიხშირე:\n\t\n-\nპორტები\nUSB:\n\t\n-\n\n\nType-C:\n\t\n-\n\n\nType-C პორტით დამუხტვა:\n\t\n-\n\n\nHDMI:\n\t\n-\n\n\nლან პორტი:\n\t\n-\n\n\n3.5mm:\n\t\nYes\nზომა/წონა\nწონა:\n\t\n2.55 კგ\nფერი\nფერი:\n\t\nGraphite Black\nმეტის ნახვა\nგაეცანი საგარანტიო პირობებს\nსაგარანტიო პირობები\nფილიალები\nმარაგშია\nშეკვეთიდან 2-5 დღეში\nზუმერის წერეთლის ფილიალი\n\nთბილისი - წერეთლის გამზირი, N1.\n\nმარაგშია\n+995 591 967 601\nორშ-შაბ: 10:00:00 - 20:00:00\nკვირა: 10:00:00 - 19:00:00\nზუმერის პეკინის ფილიალი\n\nთბილისი - კ.გამსახურდიას (პეკინის) გამზირი N14ა\n\nმარაგშია\n+995 591 967 671\nორშ-შაბ: 10:00:00 - 21:00:00\nკვირა: 10:00:00 - 20:00:00\nზუმერის \"თბილისი ცენტრალის\" ფილიალი\n\nთბილისი - \"თბილისი ცენტრალი\"- lll სართული\n\nმარაგშია\n+995 599 862 449\nორშ-შაბ: 10:00:00 - 20:00:00\nკვირა: 10:00:00 - 19:00:00\nზუმერის City Mall საბურთალო-ს ფილიალი\n\nთბილისი - \"სითი მოლი\" - პეტრე ქავთარაძის N1\n\nმარაგშია\n+995 591 971 962\nორშ-შაბ: 10:00:00 - 22:00:00\nკვირა: 10:00:00 - 22:00:00\nზუმერის თბილისი მოლის ფილიალი\n\nთბილისი - „თბილისი მოლი\" - I სართული. აღმაშენებლის ხეივანი მე-16 კმ\n\nმარაგშია\n+995 591 967 608\nორშ-შაბ: 10:00:00 - 22:00:00\nკვირა: 10:00:00 - 22:00:00\nზუმერის \"გლდანი მოლის\" ფილიალი\n\nთბილისი - \"გლდანი მოლი\" - I სართული, M-ახმეტელის მიმდებარე\n\nმარაგშია\n+995 591 967 673\nორშ-შაბ: 10:00:00 - 21:00:00\nკვირა: 10:00:00 - 21:00:00\nზუმერის ისთ ფოინთის ფილიალი\n\nთბილისი - \"ისთ ფოინთი\" - ალ. თვალჭრელიძე N2\n\nმარაგშია\n+995 591 340 476\nორშ-შაბ: 10:00:00 - 22:00:00\nკვირა: 10:00:00 - 22:00:00\nზუმერი რუსთავი მოლის ფილიალი\n\nრუსთავი - შარტავას და ლომოურის კვეთა\n\nმარაგშია\n+995 591 441 082\nორშ-შაბ: 10:00:00 - 22:00:00\nკვირა: 10:00:00 - 22:00:00\nბათუმი ჭავჭავაძის ფილიალი\n\nბათუმი - ბათუმი, ჭავჭავაძის N21\n\nმარაგშია\n+995 591 967 606\nორშ-შაბ: 10:00:00 - 20:00:00\nკვირა: 10:00:00 - 19:00:00\nბათუმის \"Black Sea Mall\"-ის ფილიალი\n\nბათუმი - \"Black Sea Mall\" - ტბელ აბუსერიძის N22\n\nმარაგშია\n+995 591 310 257\nორშ-შაბ: 10:00:00 - 21:00:00\nკვირა: 10:00:00 - 21:00:00\nბათუმის გრანდ მოლის ფილიალი\n\nბათუმი - \"გრანდ მოლი\" - შერიფ ხიმშიაშვილის 29\n\nმარაგშია\n+995 591 022 872\nორშ-შაბ: 10:00:00 - 22:00:00\nკვირა: 10:00:00 - 22:00:00\nქუთაისი ვესთ მოლი\n\nქუთაისი - \"ვესთ მოლი\" - შარტავას N2\n\nმარაგშია\n+995 595 306 765\nორშ-შაბ: 10:00:00 - 22:00:00\nკვირა: 10:00:00 - 22:00:00\nზუგდიდი მოლის ფილიალი\n\nზუგდიდი - ზუგდიდი მოლი, კოსტავას ქუჩა №28\n\nმარაგშია\n+995 591 676 489\nორშ-შაბ: 10:00:00 - 22:00:00\nკვირა: 10:00:00 - 22:00:00\nგორი მოლის ფილიალი\n\nგორი - გორი, ცხინვალის გზატკეცილი 14-14ამ, გორი მოლი\n\nმარაგშია\n+995 591 198 248\nორშ-შაბ: 10:00:00 - 22:00:00\nკვირა: 10:00:00 - 22:00:00\nზუმერის საწყობი\n\nთბილისი - თბილისი\n\nმარაგშია\nორშ-შაბ: 10:00:00 - 19:00:00\nკვირა: 10:00:00 - 19:00:00\nზუმერის საბითუმო საწყობი\n\nთბილისი - აკაკი წერეთლის გამზირი 1, საბითუმო საწყობი, -1 სართული\n\nმარაგშია\n+995 (32) 2 60 30 60\nორშ-შაბ: 10:00:00 - 19:00:00\nკვირა: 10:00:00 - 19:00:00\nმეტის ნახვა\n2179 ₾\n2279 ₾\n\nთვეში: 60.5 ₾ -დან\n\nმარაგი ფილიალებში\nფასის დაზღვევა\nფასის კონტროლი\nფასის დაჯავშნა\nყიდვა\nშედარება\nდამატება\nნავიგაცია\n\nპერსონალურ მონაცემთა დაცვის პოლიტიკა\n\nჩვენ შესახებ\n\nწესები და პირობები\n\nმიწოდების სერვისი\n\nკარიერა\n\nგადახდები\n\nSetanta Sports\n\nგადახდის მეთოდები\n\nგარანტია\n\nგანვადება\n\nნივთის დაბრუნება\n\nნივთის ონლაინ ყიდვის ინსტრუქცია\n\nგამოგვყევი\n\nFacebook\n\nYoutube\n\nInstagram\n\nTik Tok\n\nკონტაქტი\n\nInfo@zoommer.ge\n\n+995 (32) 2 60 30 60 / *7007\n\nფილიალები\n\nკორპორატიული გაყიდვები\n\nZoommer App\n\nCopyright © 2023 Zoommer.ge. All rights reserved.\n\nCookie პოლიტიკა\n\nსაიტით სარგებლობის გაგრძელებით, შენ ეთანხმები Cookie ჩანაწერების გამოყენებას. მეტი ინფორმაცისათვის იხილეთ კონფიდენციალურობის პოლიტიკა\n\nგასაგებია",
    "specs": {
      "ბრენდი:": "Asus",
      "მოდელი:": "TUF 15",
      "ცენტრალური პროცესორი:": "AMD Ryzen 7 7435HS",
      "პროცესორის თაობა:": "Ryzen 7 7000 Series",
      "პროცესორის სიხშირე:": "3.1 GHz ~ 4.5 GHz",
      "ბირთვების რაოდენობა:": "8",
      "ნაკადების რაოდენობა:": "16",
      "გრაფიკული პროცესორი:": "Nvidia GeForce RTX 2050",
      "გრაფიკული პროცესორის მეხსიერება:": "-",
      "გრაფიკული პროცესორის ტიპი:": "არა ინტეგრირებული",
      "ოპერაციული სისტემა:": "No",
      "Bluetooth:": "Yes",
      "ეკრანის ზომა:": "15.6 Inches",
      "რეზოლუცია:": "Full HD",
      "ეკრანის ტიპი:": "IPS",
      "სენსორული ეკრანი:": "No",
      "განახლების სიხშირე:": "-",
      "კლავიატურის განათება:": "-",
      "Numpad:": "-",
      "დისკის წამკითხველი:": "No",
      "ვებ კამერა:": "-",
      "ლეპტოპის ტიპი:": "გეიმინგი",
      "შიდა მეხსიერება:": "512 GB",
      "შიდა მეხსიერების ტიპი:": "SSD",
      "შიდა მეხსიერების ინტერფეისი:": "M.2",
      "ოპერატიული მეხსიერება:": "16 GB",
      "ოპერატიული მეხსიერების ტიპი:": "-",
      "ოპერატიული მეხსიერების სიხშირე:": "-",
      "USB:": "-",
      "Type-C:": "-",
      "Type-C პორტით დამუხტვა:": "-",
      "HDMI:": "-",
      "ლან პორტი:": "-",
      "3.5mm:": "Yes",
      "წონა:": "2.55 კგ",
      "ფერი:": "Graphite Black"
    }
  },
  {
    "category": "Gaming ლეპტოპები",
    "title": "HP Victus 16 B09JXEA Mica Silver",
    "price": 3999.0,
    "link": "https://zoommer.ge/leptopebi/hp-victus-16-b09jxea-mica-silver-p45468",
    "image": "/_next/image?url=https%3A%2F%2Fs3.zoommer.ge%2Fsite%2F8ec92bd1-6e09-4c40-b6f7-3c0ff3f46fb4_Thumb.jpeg&w=384&q=50",
    "product_title_detail": "HP Victus 16 B09JXEA Mica Silver",
    "description": "*7007 / +995 (32) 2 60 30 60\nსავაჭრო პოლიტიკა\nგანვადება\nკარიერა\nTrade In\nფილიალები\nნავიგაცია\nკალათა\nშესვლა\n%\nმთავარი\nლეპტოპები\nHP\n#ZOOM-035290\nHP Victus 16 B09JXEA Mica Silver\nეკრანის ზომა\n16 Inches\nრეზოლუცია\nFull HD\nეკრანის ტიპი\nIPS\nგანახლების სიხშირე\n-\nშიდა მეხსიერება\n512 GB\nBluetooth\nYes\nType-C\n-\nოპერატიული მეხსიერება\n16 GB\nერთად იაფია\nდაამატე ნივთი\nHP Victus 16 B09JXEA Mica Silver\n3999 ₾\nRivacase 8057 Laptop Bag 16 Black\n58.65 ₾\n69 ₾\nRazer Gaming Mouse DeathAdder Essential USB White\n52 ₾\n65 ₾\nHavit Gaming Cooling Pad HV-F2083 Black\n75.65 ₾\n89 ₾\nჯამური ფასი (3)\n4185.3 ₾\n4222 ₾\nყიდვა\nაქსესუარები\nაღწერა\nმსგავსი\nმახასიათებლები\nფილიალები\nაქსესუარები\nაღწერა\nმსგავსი\nმახასიათებლები\nფილიალები\n89 ₾\n\nთვეში: 2 ₾ -დან\n\nHavit Gaming Cooling Pad HV-F2083 Black\nდამატება\n299 ₾\n\nთვეში: 8 ₾ -დან\n\nASUS ROG BP2701 Backpack 17\nდამატება\n219 ₾\n\nთვეში: 6 ₾ -დან\n\nRazer Gaming Mouse Orochi V2 WL Black\nდამატება\n69 ₾\n\nთვეში: 1 ₾ -დან\n\nXiaomi Mi Router 4A DVB4230GL White\nდამატება\n99 ₾\n\nთვეში: 2 ₾ -დან\n\nASUS ROG BP1501G Backpack 15-17\nდამატება\n219 ₾\n\nთვეში: 6 ₾ -დან\n\nRazer Gaming Mouse Orochi V2 WL White\nდამატება\n85 ₾\n\nთვეში: 2 ₾ -დან\n\nTP-Link Archer C50 AC1200 White\nდამატება\n119 ₾\n\nთვეში: 3 ₾ -დან\n\nASUS ROG BP4701 Backpack 15-17\nდამატება\n209 ₾\n\nთვეში: 5 ₾ -დან\n\nRazer Gaming Mouse DeathAdder V2 X Hyperspeed WL/BT/U ...\nდამატება\n119 ₾\n\nთვეში: 3 ₾ -დან\n\nTP-Link Archer C6 AC1200 Black\nდამატება\n89 ₾\n\nთვეში: 2 ₾ -დან\n\nLenovo Gaming Modern Backpack\nდამატება\n139 ₾\n\nთვეში: 3 ₾ -დან\n\nLogitech Gaming Mouse G402 Hyperion Fury black\nდამატება\n159 ₾\n\nთვეში: 4 ₾ -დან\n\nXiaomi Router AX1500 White\nდამატება\n49 ₾\n\nთვეში: 1 ₾ -დან\n\nAsus Nereus Carry Bag 16 Black\nდამატება\n29 ₾\n\nHavit Gaming Mouse HV-MS1010 Black\nდამატება\n179 ₾\n\nთვეში: 4 ₾ -დან\n\nXiaomi Mesh System AX3000 NE 1 pack White\nდამატება\n69 ₾\n\nთვეში: 1 ₾ -დან\n\nAsus Nereus Backpack 16 Black\nდამატება\n79 ₾\n\nთვეში: 2 ₾ -დან\n\nRazer Gaming Mouse DeathAdder Essential USB Black\nდამატება\n299 ₾\n\nთვეში: 8 ₾ -დან\n\nXiaomi Mesh System AX3000 NE 2 pack White\nდამატება\n69 ₾\n\nთვეში: 1 ₾ -დან\n\nRivacase 8057 Laptop Bag 16 Black\nდამატება\n119 ₾\n\nთვეში: 3 ₾ -დან\n\nHyperX Pulsefire Surge Mouse Black\nდამატება\n249 ₾\n\nთვეში: 6 ₾ -დან\n\nXiaomi Router BE3600 White\nდამატება\n79 ₾\n\nთვეში: 2 ₾ -დან\n\nRivacase 7531 Eco Laptop Bag 15 Black\nდამატება\n469 ₾\n\nთვეში: 13 ₾ -დან\n\nHP OMEN PHOTON Wireless Mouse 6CL96AA Black\nდამატება\n89 ₾\n\nთვეში: 2 ₾ -დან\n\nTomtoc Defender A13 Laptop Sleeve Kit 16 A13F2DV Blac ...\nდამატება\n65 ₾\n\nთვეში: 1 ₾ -დან\n\nRazer Gaming Mouse DeathAdder Essential USB White\nდამატება\n119 ₾\n\nთვეში: 3 ₾ -დან\n\nTomtoc Defender A42 Laptop Briefcase 15 A42E1B1 Navy ...\nდამატება\n239 ₾\n\nთვეში: 6 ₾ -დან\n\nRazer Gaming Mouse Basilisk V3 Black\nდამატება\n119 ₾\n\nთვეში: 3 ₾ -დან\n\nTomtoc Defender A42 Laptop Briefcase 16 A42F2B1 Navy ...\nდამატება\n299 ₾\n\nთვეში: 8 ₾ -დან\n\nRazer Gaming Mouse Naga V2 HyperSpeed WL Black\nდამატება\n119 ₾\n\nთვეში: 3 ₾ -დან\n\nTomtoc Defender A42 Laptop Briefcase 16 A42F2D1 Black\nდამატება\n229 ₾\n\nთვეში: 6 ₾ -დან\n\nRazer Gaming Mouse Basilisk V3 X HyperSpeed WL Black\nდამატება\n89 ₾\n\nთვეში: 2 ₾ -დან\n\nUniq Dfender Tough Laptop Sleeve 16 Inch Marl Grey\nდამატება\n129 ₾\n\nთვეში: 3 ₾ -დან\n\nRazer Gaming Mouse Cobra Black\nდამატება\n89 ₾\n\nთვეში: 2 ₾ -დან\n\nUniq Dfender Tough Laptop Sleeve 16 Inch Black\nდამატება\n19 ₾\n\nHavit Gaming Mouse HV-MS989GT Black/Red\nდამატება\n69 ₾\n\nთვეში: 1 ₾ -დან\n\nAsus AP4600 Backpack 16 Grey\nდამატება\n19 ₾\n\nHavit Gaming Mouse HV-MS626GT Black\nდამატება\n99 ₾\n\nთვეში: 2 ₾ -დან\n\nSpigen Valentinus S Laptop Sleeve 16 AFA06425 Brown\nდამატება\n19 ₾\n\nHavit Gaming Mouse HV-MS66GT White/Blue\nდამატება\n99 ₾\n\nთვეში: 2 ₾ -დან\n\nSpigen Valentinus S Laptop Sleeve 16 AFA06426 Green\nდამატება\n149 ₾\n\nთვეში: 4 ₾ -დან\n\nHyperX Gaming Mouse Pulsefire Haste 2 Black\nდამატება\n99 ₾\n\nთვეში: 2 ₾ -დან\n\nSpigen Valentinus S Laptop Sleeve 16 AFA06424 Grey\nდამატება\n19 ₾\n\nHavit Wireless Mouse HV-MS66GT Black\nდამატება\n79 ₾\n\nთვეში: 2 ₾ -დან\n\nSpigen Valentinus Laptop Sleeve 16 AFA06420 Green\nდამატება\n179 ₾\n\nთვეში: 4 ₾ -დან\n\nLogitech Gaming Mouse G305 LIGHTSPEED WL L910-005282 ...\nდამატება\n79 ₾\n\nთვეში: 2 ₾ -დან\n\nSpigen Valentinus Laptop Sleeve 16 AFA06418 Grey\nდამატება\n259 ₾\n\nთვეში: 7 ₾ -დან\n\nLogitech Gaming Mouse G502 X L910-006138 Black\nდამატება\n79 ₾\n\nთვეში: 2 ₾ -დან\n\nSpigen Valentinus Laptop Sleeve 16 AFA06419 Brown\nდამატება\n259 ₾\n\nთვეში: 7 ₾ -დან\n\nLogitech Gaming Mouse G502 X L910-006138 White\nდამატება\n59 ₾\n\nთვეში: 1 ₾ -დან\n\nRivacase 8036 Laptop Briefcase 16 Black\nდამატება\n19 ₾\n\nHavit Gaming Mouse HV-MS626GT Black/Red\nდამატება\n79 ₾\n\nთვეში: 2 ₾ -დან\n\nRivacase 8062 Laptop Backpack 16 Black\nდამატება\n19 ₾\n\nHavit Gaming Mouse HV-MS626GT Black/Blue\nდამატება\n249 ₾\n\nთვეში: 6 ₾ -დან\n\nASUS ROG BP2501 Ranger Backpack 16 Black\nდამატება\n349 ₾\n\nთვეში: 9 ₾ -დან\n\nLogitech Gaming Mouse G703 LIGHTSPEED WL L910-005640 ...\nდამატება\n99 ₾\n\nთვეში: 2 ₾ -დან\n\nDell EcoLoop Essential Backpack 14-16 460-BDSS Black\nდამატება\n89 ₾\n\nთვეში: 2 ₾ -დან\n\nLogitech Gaming Mouse G102 LIGHTSYNC L910-005823 Blac ...\nდამატება\n79 ₾\n\nთვეში: 2 ₾ -დან\n\nTomtoc Defender A13 Laptop Sleeve 16 A13F2D1 Black\nდამატება\n89 ₾\n\nთვეში: 2 ₾ -დან\n\nLogitech Gaming Mouse G102 LIGHTSYNC L910-005824 Whit ...\nდამატება\n149 ₾\n\nთვეში: 4 ₾ -დან\n\nTomtoc Explorer T60 Laptop Backpack 16 T60M1D1 Black\nდამატება\n89 ₾\n\nთვეში: 2 ₾ -დან\n\nLogitech Gaming Mouse G102 LIGHTSYNC L910-005801 Blue\nდამატება\n89 ₾\n\nთვეში: 2 ₾ -დან\n\nTomtoc Defender A14 Laptop Briefcase 16 A14F2D1 Black\nდამატება\n239 ₾\n\nთვეში: 6 ₾ -დან\n\nLogitech Gaming Mouse G502 HERO L910-005470 Black\nდამატება\n119 ₾\n\nთვეში: 3 ₾ -დან\n\nLenovo Legion 16 Gaming Backpack GB400 Grey\nდამატება\n199 ₾\n\nთვეში: 5 ₾ -დან\n\nHyperX Pulsefire Haste 2 core Wireless Black\nდამატება\n199 ₾\n\nთვეში: 5 ₾ -დან\n\nHyperX Pulsefire Haste 2 core Wireless White\nდამატება\n59 ₾\n\nთვეში: 1 ₾ -დან\n\nHavit Gaming Mouse HV-MS954 Black\nდამატება\n39 ₾\n\nთვეში: 1 ₾ -დან\n\nHavit Gaming Mouse HV-MS1033 White\nდამატება\n39 ₾\n\nთვეში: 1 ₾ -დან\n\nHavit Gaming Mouse HV-MS1029 Pink\nდამატება\n59 ₾\n\nთვეში: 1 ₾ -დან\n\nHavit Gaming Mouse HV-MS966 Black/Green\nდამატება\n49 ₾\n\nთვეში: 1 ₾ -დან\n\nHavit Wireless Mouse HV-MS1039W Black/White\nდამატება\n79 ₾\n\nთვეში: 2 ₾ -დან\n\nHavit Wireless Mouse HV-MS970WB Pro Black\nდამატება\n79 ₾\n\nთვეში: 2 ₾ -დან\n\nHavit Wireless Mouse HV-MS970WB Pro Transparent White\nდამატება\n219 ₾\n\nთვეში: 6 ₾ -დან\n\nRazer Gaming Mouse Orochi V2 WL Pink\nდამატება\nპროდუქტის შესახებ\n\nთუ ეძებთ ლეპტოპს, რომელიც მარტივად გაუმკლავდება ყველაზე მოთხოვნად თამაშებს — HP Victus 16 B09JXEA Mica Silver შექმნილია სწორედ თქვენთვის. ეს მოდელი აერთიანებს მაღალ წარმადობას, გამძლე კონსტრუქციასა ...\n\nმეტის ნახვა\nმსგავსი პროდუქტები\n2999 ₾\n\nთვეში: 83 ₾ -დან\n\nHP Victus 15 84J97EA, Intel core i5-13500H, Nvidia Ge ...\nდამატება\n2499 ₾\n\nთვეში: 69 ₾ -დან\n\nHP Victus 15 84J98EA, Intel Core i5-13420H Octa 4.6 G ...\nდამატება\n2499 ₾\n\nთვეში: 69 ₾ -დან\n\nHP Victus 15 84J99EA, Intel Core i5-13420H Octa 4.6 G ...\nდამატება\n3199 ₾\n3399 ₾\n\nთვეში: 88 ₾ -დან\n\nHP Victus 15 8F5J3EA Mica Silver\nდამატება\n3499 ₾\n3699 ₾\n\nთვეში: 97 ₾ -დან\n\nHP Omen 16 A1WF1EA, Intel Core i5-14500HX, Nvidia GeF ...\nდამატება\n2799 ₾\n2999 ₾\n\nთვეში: 77 ₾ -დან\n\nHP Victus 15 A1WD6EA, AMD Ryzen 5-8645HS, NVIDIA GeFo ...\nდამატება\n3379 ₾\n\nთვეში: 93 ₾ -დან\n\nHP Victus 16 A1WE4EA, Intel Core i5-14450HX, Nvidia G ...\nდამატება\n2899 ₾\n2999 ₾\n\nთვეში: 80 ₾ -დან\n\nHP Victus 15 A1WD5EA Mica Silver\nდამატება\n3999 ₾\n5599 ₾\n\nთვეში: 111 ₾ -დან\n\nHP Omen 14 A1AA7EA Black\nდამატება\n2999 ₾\n3099 ₾\n\nთვეში: 83 ₾ -დან\n\nHP Victus 16 A1AB6EA Mica Silver\nდამატება\n2899 ₾\n2999 ₾\n\nთვეში: 80 ₾ -დან\n\nHP Victus 16 A1AB7EA Mica Silver\nდამატება\n2499 ₾\n2599 ₾\n\nთვეში: 69 ₾ -დან\n\nHP Victus 15 B08XKEA Mica Silver\nდამატება\n3299 ₾\n3499 ₾\n\nთვეში: 91 ₾ -დან\n\nHP Victus 15 A74LKEA Blue\nდამატება\n2799 ₾\n3199 ₾\n\nთვეში: 77 ₾ -დან\n\nHP Victus 15 B09J6EA Blue\nდამატება\nGIFTS\n2799 ₾\n2999 ₾\n\nთვეში: 77 ₾ -დან\n\nHP Victus 15 B84VTEA Silver\nდამატება\n5699 ₾\n\nთვეში: 158 ₾ -დან\n\nHP Omen Max 16 BG7J7EA, Intel Core Ultra 7-255HX 20c, ...\nდამატება\nდამატებითი მახასიათებლები\nბრენდი\nბრენდი:\n\t\nHP\nმოდელი\nმოდელი:\n\t\nVictus\nტექნიკური მახასიათებლები\nცენტრალური პროცესორი:\n\t\nIntel Core i7-14650HX\n\n\nპროცესორის თაობა:\n\t\nIntel i7 14th Gen\n\n\nპროცესორის სიხშირე:\n\t\n3.7 GHz ~ 5.2 GHz\n\n\nბირთვების რაოდენობა:\n\t\n16\n\n\nნაკადების რაოდენობა:\n\t\n24\n\n\nგრაფიკული პროცესორი:\n\t\nNvidia GeForce RTX 4060\n\n\nგრაფიკული პროცესორის მეხსიერება:\n\t\n8 GB\n\n\nგრაფიკული პროცესორის ტიპი:\n\t\nარა ინტეგრირებული\n\n\nოპერაციული სისტემა:\n\t\nNo\n\n\nBluetooth:\n\t\nYes\nეკრანი\nეკრანის ზომა:\n\t\n16 Inches\n\n\nრეზოლუცია:\n\t\nFull HD\n\n\nეკრანის ტიპი:\n\t\nIPS\n\n\nსენსორული ეკრანი:\n\t\nNo\n\n\nგანახლების სიხშირე:\n\t\n-\nდამატებითი მახასიათებლები\nკლავიატურის განათება:\n\t\n-\n\n\nNumpad:\n\t\n-\n\n\nდისკის წამკითხველი:\n\t\nNo\n\n\nვებ კამერა:\n\t\n-\n\n\nლეპტოპის ტიპი:\n\t\nგეიმინგი\nმეხსიერება\nშიდა მეხსიერება:\n\t\n512 GB\n\n\nშიდა მეხსიერების ტიპი:\n\t\nSSD\n\n\nშიდა მეხსიერების ინტერფეისი:\n\t\nM.2\n\n\nოპერატიული მეხსიერება:\n\t\n16 GB\n\n\nოპერატიული მეხსიერების ტიპი:\n\t\n-\n\n\nოპერატიული მეხსიერების სიხშირე:\n\t\n-\nპორტები\nUSB:\n\t\n-\n\n\nType-C:\n\t\n-\n\n\nType-C პორტით დამუხტვა:\n\t\n-\n\n\nHDMI:\n\t\n-\n\n\nლან პორტი:\n\t\n-\n\n\n3.5mm:\n\t\nYes\nზომა/წონა\nწონა:\n\t\n2.55 kg\nფერი\nფერი:\n\t\nMica Silver\nმეტის ნახვა\nგაეცანი საგარანტიო პირობებს\nსაგარანტიო პირობები\nფილიალები\nმარაგშია\nშეკვეთიდან 2-5 დღეში\nბათუმი ჭავჭავაძის ფილიალი\n\nბათუმი - ბათუმი, ჭავჭავაძის N21\n\nმარაგშია\n+995 591 967 606\nორშ-შაბ: 10:00:00 - 20:00:00\nკვირა: 10:00:00 - 19:00:00\nქუთაისი ვესთ მოლი\n\nქუთაისი - \"ვესთ მოლი\" - შარტავას N2\n\nმარაგშია\n+995 595 306 765\nორშ-შაბ: 10:00:00 - 22:00:00\nკვირა: 10:00:00 - 22:00:00\n3999 ₾\n4199 ₾\n\nთვეში: 111.1 ₾ -დან\n\nმარაგი ფილიალებში\nფასის დაზღვევა\nფასის კონტროლი\nფასის დაჯავშნა\nყიდვა\nშედარება\nდამატება\nნავიგაცია\n\nპერსონალურ მონაცემთა დაცვის პოლიტიკა\n\nჩვენ შესახებ\n\nწესები და პირობები\n\nმიწოდების სერვისი\n\nკარიერა\n\nგადახდები\n\nSetanta Sports\n\nგადახდის მეთოდები\n\nგარანტია\n\nგანვადება\n\nნივთის დაბრუნება\n\nნივთის ონლაინ ყიდვის ინსტრუქცია\n\nგამოგვყევი\n\nFacebook\n\nYoutube\n\nInstagram\n\nTik Tok\n\nკონტაქტი\n\nInfo@zoommer.ge\n\n+995 (32) 2 60 30 60 / *7007\n\nფილიალები\n\nკორპორატიული გაყიდვები\n\nZoommer App\n\nCopyright © 2023 Zoommer.ge. All rights reserved.\n\nCookie პოლიტიკა\n\nსაიტით სარგებლობის გაგრძელებით, შენ ეთანხმები Cookie ჩანაწერების გამოყენებას. მეტი ინფორმაცისათვის იხილეთ კონფიდენციალურობის პოლიტიკა\n\nგასაგებია",
    "specs": {
      "ბრენდი:": "HP",
      "მოდელი:": "Victus",
      "ცენტრალური პროცესორი:": "Intel Core i7-14650HX",
      "პროცესორის თაობა:": "Intel i7 14th Gen",
      "პროცესორის სიხშირე:": "3.7 GHz ~ 5.2 GHz",
      "ბირთვების რაოდენობა:": "16",
      "ნაკადების რაოდენობა:": "24",
      "გრაფიკული პროცესორი:": "Nvidia GeForce RTX 4060",
      "გრაფიკული პროცესორის მეხსიერება:": "8 GB",
      "გრაფიკული პროცესორის ტიპი:": "არა ინტეგრირებული",
      "ოპერაციული სისტემა:": "No",
      "Bluetooth:": "Yes",
      "ეკრანის ზომა:": "16 Inches",
      "რეზოლუცია:": "Full HD",
      "ეკრანის ტიპი:": "IPS",
      "სენსორული ეკრანი:": "No",
      "განახლების სიხშირე:": "-",
      "კლავიატურის განათება:": "-",
      "Numpad:": "-",
      "დისკის წამკითხველი:": "No",
      "ვებ კამერა:": "-",
      "ლეპტოპის ტიპი:": "გეიმინგი",
      "შიდა მეხსიერება:": "512 GB",
      "შიდა მეხსიერების ტიპი:": "SSD",
      "შიდა მეხსიერების ინტერფეისი:": "M.2",
      "ოპერატიული მეხსიერება:": "16 GB",
      "ოპერატიული მეხსიერების ტიპი:": "-",
      "ოპერატიული მეხსიერების სიხშირე:": "-",
      "USB:": "-",
      "Type-C:": "-",
      "Type-C პორტით დამუხტვა:": "-",
      "HDMI:": "-",
      "ლან პორტი:": "-",
      "3.5mm:": "Yes",
      "წონა:": "2.55 kg",
      "ფერი:": "Mica Silver"
    }
  },
  {
    "category": "დამტენი ადაპტერები",
    "title": "Ugreen Nexode Pro 65W USB Type-C Ultra Slim Travel Ad ...",
    "price": 125.0,
    "link": "https://zoommer.ge/mobiluris-aqsesuarebi/ugreen-nexode-pro-65w-usb-type-c-ultra-slim-travel-adapter-25356-p48673",
    "image": "/_next/image?url=https%3A%2F%2Fs3.zoommer.ge%2Fsite%2F94a91161-7ccb-4f06-90f5-d457e5d5448d_Thumb.jpeg&w=384&q=50",
    "product_title_detail": "Ugreen Nexode Pro 65W USB Type-C Ultra Slim Travel Adapter 25356",
    "description": "",
    "specs": {
      "ბრენდი:": "Ugreen",
      "სწრაფი დამუხტვა:": "Yes",
      "MAX ვატი:": "65 W",
      "პორტი:": "USB-A, 2 x Type-C",
      "პორტების რაოდენობა:": "3",
      "კაბელი:": "No",
      "კაბელის პორტები:": "No",
      "ფერი:": "Healther Grey"
    }
  },
  {
    "category": "დამტენი ადაპტერები",
    "title": "Ugreen Nexode 30W Type-C with Type-c Cable 1m GaN Fas ...",
    "price": 59.0,
    "link": "https://zoommer.ge/mobiluris-aqsesuarebi/ugreen-nexode-30w-type-c-with-type-c-cable-1m-gan-fast-charger-25257-black-p48672",
    "image": "/_next/image?url=https%3A%2F%2Fs3.zoommer.ge%2Fsite%2Fcf7698b4-3b7f-4cb5-90d0-397bf3b19393_Thumb.jpeg&w=384&q=50",
    "product_title_detail": "Ugreen Nexode 30W Type-C with Type-c Cable 1m GaN Fast Charger 25257 Black",
    "description": "",
    "specs": {
      "ბრენდი:": "Ugreen",
      "სწრაფი დამუხტვა:": "Yes",
      "MAX ვატი:": "30 W",
      "პორტი:": "Type-C",
      "პორტების რაოდენობა:": "1",
      "კაბელი:": "Yes",
      "კაბელის პორტები:": "Type-C",
      "ფერი:": "Healther Grey"
    }
  },
  {
    "category": "დამტენი ადაპტერები",
    "title": "Ugreen GaN Fast Charger 3x USB-C USB-A 100W 40747 Bla ...",
    "price": 199.0,
    "link": "https://zoommer.ge/mobiluris-aqsesuarebi/ugreen-gan-fast-charger-3x-usb-c-usb-a-100w-40747-black-p48670",
    "image": "/_next/image?url=https%3A%2F%2Fs3.zoommer.ge%2Fsite%2F7db9a0b4-2230-4558-9231-af7c95e3c78d_Thumb.jpeg&w=384&q=50",
    "product_title_detail": "Ugreen GaN Fast Charger 3x USB-C USB-A 100W 40747 Black",
    "description": "",
    "specs": {
      "ბრენდი:": "Ugreen",
      "სწრაფი დამუხტვა:": "Yes",
      "MAX ვატი:": "100 W",
      "პორტი:": "USB-A, 3 x Type-C",
      "პორტების რაოდენობა:": "4",
      "კაბელი:": "No",
      "კაბელის პორტები:": "No",
      "ფერი:": "Black"
    }
  },
  {
    "category": "დამტენი ადაპტერები",
    "title": "Ugreen Nexode Pro 160W Type-C USB Charger 25877 Black",
    "price": 249.0,
    "link": "https://zoommer.ge/mobiluris-aqsesuarebi/ugreen-nexode-pro-160w-type-c-usb-charger-25877-black-p48669",
    "image": "/_next/image?url=https%3A%2F%2Fs3.zoommer.ge%2Fsite%2F1c952d00-9856-4a71-b8ff-ba06d8744c65_Thumb.jpeg&w=384&q=50",
    "product_title_detail": "Ugreen Nexode Pro 160W Type-C USB Charger 25877 Black",
    "description": "",
    "specs": {
      "ბრენდი:": "Ugreen",
      "სწრაფი დამუხტვა:": "Yes",
      "MAX ვატი:": "160 W",
      "პორტი:": "USB-A, 3 x Type-C",
      "პორტების რაოდენობა:": "4",
      "კაბელი:": "No",
      "კაბელის პორტები:": "No",
      "ფერი:": "Healther Grey"
    }
  },
  {
    "category": "დამტენი ადაპტერები",
    "title": "Xiaomi 45W Turbo Charging Power Adapter Type-A White",
    "price": 39.0,
    "link": "https://zoommer.ge/mobiluris-aqsesuarebi/xiaomi-45w-turbo-charging-power-adapter-type-a-white-p48435",
    "image": "/_next/image?url=https%3A%2F%2Fs3.zoommer.ge%2Fsite%2Fa7b9fc78-282c-46fc-b627-d5b68c6f805d_Thumb.jpeg&w=384&q=50",
    "product_title_detail": "Xiaomi 45W Turbo Charging Power Adapter Type-A White",
    "description": "",
    "specs": {
      "ბრენდი:": "Xiaomi",
      "სწრაფი დამუხტვა:": "Yes",
      "MAX ვატი:": "45 W",
      "პორტი:": "USB-A",
      "პორტების რაოდენობა:": "1",
      "კაბელი:": "No",
      "კაბელის პორტები:": "No",
      "ფერი:": "White"
    }
  },
  {
    "category": "დამტენი ადაპტერები",
    "title": "Belkin 20W USB-C Cube Wall Charger With PPS WCA009kqW ...",
    "price": 39.0,
    "link": "https://zoommer.ge/mobiluris-aqsesuarebi/belkin-20w-usb-c-cube-wall-charger-with-pps-wca009kqwh-white-p47366",
    "image": "/_next/image?url=https%3A%2F%2Fs3.zoommer.ge%2Fsite%2F1579fed9-cf3e-4f5a-98d2-329b9e994653_Thumb.jpeg&w=384&q=50",
    "product_title_detail": "Belkin 20W USB-C Cube Wall Charger With PPS WCA009kqWH White",
    "description": "",
    "specs": {
      "ბრენდი:": "Belkin",
      "სწრაფი დამუხტვა:": "Yes",
      "MAX ვატი:": "20 W",
      "პორტი:": "Type-C",
      "პორტების რაოდენობა:": "1",
      "კაბელი:": "No",
      "კაბელის პორტები:": "No",
      "ფერი:": "White"
    }
  },
  {
    "category": "დამტენი ადაპტერები",
    "title": "Anker Zolo 20W Type C A2699 White",
    "price": 39.0,
    "link": "https://zoommer.ge/mobiluris-aqsesuarebi/anker-zolo-20w-type-c-a2699-white-p47346",
    "image": "/_next/image?url=https%3A%2F%2Fs3.zoommer.ge%2Fsite%2Ff8b5aedc-dabf-4919-a40a-1f57f2457d08_Thumb.jpeg&w=384&q=50",
    "product_title_detail": "Anker Zolo 20W Type C A2699 White",
    "description": "",
    "specs": {
      "ბრენდი:": "Anker",
      "სწრაფი დამუხტვა:": "Yes",
      "MAX ვატი:": "20 W",
      "პორტი:": "Type-C",
      "პორტების რაოდენობა:": "1",
      "კაბელი:": "No",
      "კაბელის პორტები:": "No",
      "ფერი:": "White"
    }
  },
  {
    "category": "დამტენი ადაპტერები",
    "title": "Havit Fast Charger UC142 Black",
    "price": 39.0,
    "link": "https://zoommer.ge/mobiluris-aqsesuarebi/havit-fast-charger-uc142-black-p47159",
    "image": "/_next/image?url=https%3A%2F%2Fs3.zoommer.ge%2Fsite%2F63e9e987-9b4e-4654-b6d6-3eb6225ff33e_Thumb.jpeg&w=384&q=50",
    "product_title_detail": "Havit Fast Charger UC142 Black",
    "description": "",
    "specs": {
      "ბრენდი:": "Havit",
      "სწრაფი დამუხტვა:": "Yes",
      "MAX ვატი:": "30 W",
      "პორტი:": "USB-A",
      "პორტების რაოდენობა:": "3",
      "კაბელი:": "No",
      "კაბელის პორტები:": "No",
      "ფერი:": "Black"
    }
  },
  {
    "category": "დამტენი ადაპტერები",
    "title": "Ugreen Uno RG 65W 3-Port GaN Fast Charger EU 35291 Pu ...",
    "price": 129.0,
    "link": "https://zoommer.ge/mobiluris-aqsesuarebi/ugreen-uno-rg-65w-3-port-gan-fast-charger-eu-35291-purple-p47028",
    "image": "/_next/image?url=https%3A%2F%2Fs3.zoommer.ge%2Fsite%2Fba2f8688-1c6d-483e-9987-11fca8b63ddd_Thumb.jpeg&w=384&q=50",
    "product_title_detail": "Ugreen Uno RG 65W 3-Port GaN Fast Charger EU 35291 Purple",
    "description": "",
    "specs": {
      "ბრენდი:": "Ugreen",
      "სწრაფი დამუხტვა:": "Yes",
      "MAX ვატი:": "65 W",
      "პორტი:": "USB-A",
      "პორტების რაოდენობა:": "3",
      "კაბელი:": "No",
      "კაბელის პორტები:": "No",
      "ფერი:": "Purple/Blue"
    }
  },
  {
    "category": "დამტენი ადაპტერები",
    "title": "Ugreen Nexode 20W USB-C PD GaN Fast Charger 15324 Whi ...",
    "price": 35.0,
    "link": "https://zoommer.ge/mobiluris-aqsesuarebi/ugreen-nexode-20w-usb-c-pd-gan-fast-charger-15324-white-p46454",
    "image": "/_next/image?url=https%3A%2F%2Fs3.zoommer.ge%2Fsite%2F21b45dcf-49cb-4c9c-a87a-d1eaa5a941cc_Thumb.jpeg&w=384&q=50",
    "product_title_detail": "Ugreen Nexode 20W USB-C PD GaN Fast Charger 15324 White",
    "description": "",
    "specs": {
      "ბრენდი:": "Ugreen",
      "სწრაფი დამუხტვა:": "Yes",
      "MAX ვატი:": "20 W",
      "პორტი:": "Type-C",
      "პორტების რაოდენობა:": "1",
      "კაბელი:": "No",
      "კაბელის პორტები:": "No",
      "ფერი:": "White"
    }
  },
  {
    "category": "დამტენი ადაპტერები",
    "title": "Ugreen USB Wall Charger 50459 Black",
    "price": 19.0,
    "link": "https://zoommer.ge/mobiluris-aqsesuarebi/ugreen-usb-wall-charger-50459-black-p46453",
    "image": "/_next/image?url=https%3A%2F%2Fs3.zoommer.ge%2Fsite%2F014d4a90-75fa-4f89-8310-480e1cf9cb96_Thumb.jpeg&w=384&q=50",
    "product_title_detail": "Ugreen USB Wall Charger 50459 Black",
    "description": "",
    "specs": {
      "ბრენდი:": "Ugreen",
      "სწრაფი დამუხტვა:": "No",
      "MAX ვატი:": "10.5 W",
      "პორტი:": "USB-A",
      "პორტების რაოდენობა:": "1",
      "კაბელი:": "No",
      "კაბელის პორტები:": "No",
      "ფერი:": "Black"
    }
  },
  {
    "category": "დამტენი ადაპტერები",
    "title": "Ugreen Nexode Pro 30W USB-C GaN Fast Charger EU 35006 ...",
    "price": 45.0,
    "link": "https://zoommer.ge/mobiluris-aqsesuarebi/ugreen-nexode-pro-30w-usb-c-gan-fast-charger-eu-35006-grey-p46451",
    "image": "/_next/image?url=https%3A%2F%2Fs3.zoommer.ge%2Fsite%2F40d89fe8-fdc1-45e2-b367-f15f4f712c16_Thumb.jpeg&w=384&q=50",
    "product_title_detail": "Ugreen Nexode Pro 30W USB-C GaN Fast Charger EU 35006 Grey",
    "description": "",
    "specs": {
      "ბრენდი:": "Ugreen",
      "სწრაფი დამუხტვა:": "Yes",
      "MAX ვატი:": "30 W",
      "პორტი:": "Type-C",
      "პორტების რაოდენობა:": "1",
      "კაბელი:": "No",
      "კაბელის პორტები:": "No",
      "ფერი:": "Healther Grey"
    }
  },
  {
    "category": "დამტენი ადაპტერები",
    "title": "Ugreen Uno RG 65W 3-Port GaN Fast Charger EU 25685B G ...",
    "price": 129.0,
    "link": "https://zoommer.ge/mobiluris-aqsesuarebi/ugreen-uno-rg-65w-3-port-gan-fast-charger-eu-25685b-grey-p46448",
    "image": "/_next/image?url=https%3A%2F%2Fs3.zoommer.ge%2Fsite%2Fa0e1061b-2a7b-4f66-9b43-dd69cc1a283e_Thumb.jpeg&w=384&q=50",
    "product_title_detail": "Ugreen Uno RG 65W 3-Port GaN Fast Charger EU 25685B Grey",
    "description": "",
    "specs": {
      "ბრენდი:": "Ugreen",
      "სწრაფი დამუხტვა:": "Yes",
      "MAX ვატი:": "65 W",
      "პორტი:": "2 x Type-C",
      "პორტების რაოდენობა:": "3",
      "კაბელი:": "No",
      "კაბელის პორტები:": "No",
      "ფერი:": "Healther Grey"
    }
  },
  {
    "category": "დამტენი ადაპტერები",
    "title": "Ugreen QC3.0 USB Fast Charger EU 70273 Black",
    "price": 25.0,
    "link": "https://zoommer.ge/mobiluris-aqsesuarebi/ugreen-qc3-0-usb-fast-charger-eu-70273-black-p46438",
    "image": "/_next/image?url=https%3A%2F%2Fs3.zoommer.ge%2Fsite%2F2e40a3b5-9b10-4ba6-af45-6092906f1318_Thumb.jpeg&w=384&q=50",
    "product_title_detail": "Ugreen QC3.0 USB Fast Charger EU 70273 Black",
    "description": "",
    "specs": {
      "ბრენდი:": "Ugreen",
      "სწრაფი დამუხტვა:": "Yes",
      "MAX ვატი:": "18 W",
      "პორტი:": "USB-A",
      "პორტების რაოდენობა:": "1",
      "კაბელი:": "No",
      "კაბელის პორტები:": "No",
      "ფერი:": "Black"
    }
  },
  {
    "category": "დამტენი ადაპტერები",
    "title": "Ugreen Fast Charging Power Adapter with PD 20W EU 604 ...",
    "price": 29.0,
    "link": "https://zoommer.ge/mobiluris-aqsesuarebi/ugreen-fast-charging-power-adapter-with-pd-20w-eu-60450-white-p46434",
    "image": "/_next/image?url=https%3A%2F%2Fs3.zoommer.ge%2Fsite%2F4921dd2a-0d7c-4ffa-93bc-3781d253d549_Thumb.jpeg&w=384&q=50",
    "product_title_detail": "Ugreen Fast Charging Power Adapter with PD 20W EU 60450 White",
    "description": "",
    "specs": {
      "ბრენდი:": "Ugreen",
      "სწრაფი დამუხტვა:": "Yes",
      "MAX ვატი:": "20 W",
      "პორტი:": "Type-C",
      "პორტების რაოდენობა:": "1",
      "კაბელი:": "No",
      "კაბელის პორტები:": "No",
      "ფერი:": "White"
    }
  },
  {
    "category": "დამტენი ადაპტერები",
    "title": "Ugreen Nexode mini 20W Charger EU 90664 Grey",
    "price": 39.0,
    "link": "https://zoommer.ge/mobiluris-aqsesuarebi/ugreen-nexode-mini-20w-charger-eu-90664-grey-p46426",
    "image": "/_next/image?url=https%3A%2F%2Fs3.zoommer.ge%2Fsite%2Fb3167b6e-d870-4757-86b1-51d7b6d9fbab_Thumb.jpeg&w=384&q=50",
    "product_title_detail": "Ugreen Nexode mini 20W Charger EU 90664 Grey",
    "description": "",
    "specs": {
      "ბრენდი:": "Ugreen",
      "სწრაფი დამუხტვა:": "Yes",
      "MAX ვატი:": "20 W",
      "პორტი:": "Type-C",
      "პორტების რაოდენობა:": "1",
      "კაბელი:": "No",
      "კაბელის პორტები:": "No",
      "ფერი:": "Healther Grey"
    }
  },
  {
    "category": "დამტენი ადაპტერები",
    "title": "Ugreen Nexode S 65W 3-Port GaN Fast Charger EU 35042 ...",
    "price": 89.0,
    "link": "https://zoommer.ge/mobiluris-aqsesuarebi/ugreen-nexode-s-65w-3-port-gan-fast-charger-eu-35042-grey-p46424",
    "image": "/_next/image?url=https%3A%2F%2Fs3.zoommer.ge%2Fsite%2F8f3b3fc8-4711-4bc5-8522-5147f7f2354a_Thumb.jpeg&w=384&q=50",
    "product_title_detail": "Ugreen Nexode S 65W 3-Port GaN Fast Charger EU 35042 Grey",
    "description": "",
    "specs": {
      "ბრენდი:": "Ugreen",
      "სწრაფი დამუხტვა:": "Yes",
      "MAX ვატი:": "65 W",
      "პორტი:": "2 x Type-C",
      "პორტების რაოდენობა:": "3",
      "კაბელი:": "No",
      "კაბელის პორტები:": "No",
      "ფერი:": "Healther Grey"
    }
  },
  {
    "category": "დამტენი ადაპტერები",
    "title": "Ugreen 30W Outlet Extender EU (2A1C) 90613 Black",
    "price": 49.0,
    "link": "https://zoommer.ge/mobiluris-aqsesuarebi/ugreen-30w-outlet-extender-eu-2a1c-90613-black-p46419",
    "image": "/_next/image?url=https%3A%2F%2Fs3.zoommer.ge%2Fsite%2F2f5e9d16-bada-4b53-af2d-321eb21663af_Thumb.jpeg&w=384&q=50",
    "product_title_detail": "Ugreen 30W Outlet Extender EU (2A1C) 90613 Black",
    "description": "",
    "specs": {
      "ბრენდი:": "Ugreen",
      "სწრაფი დამუხტვა:": "Yes",
      "MAX ვატი:": "30 W",
      "პორტი:": "2 x USB-A",
      "პორტების რაოდენობა:": "3",
      "კაბელი:": "No",
      "კაბელის პორტები:": "No",
      "ფერი:": "Black"
    }
  },
  {
    "category": "დამტენი ადაპტერები",
    "title": "Ugreen Nexode S 30W USB-C GaN Fast Charger EU 35041 G ...",
    "price": 69.0,
    "link": "https://zoommer.ge/mobiluris-aqsesuarebi/ugreen-nexode-s-30w-usb-c-gan-fast-charger-eu-35041-grey-p46411",
    "image": "/_next/image?url=https%3A%2F%2Fs3.zoommer.ge%2Fsite%2F4e4c02ae-d18f-4607-b282-dbc98c3a73a6_Thumb.jpeg&w=384&q=50",
    "product_title_detail": "Ugreen Nexode S 30W USB-C GaN Fast Charger EU 35041 Grey",
    "description": "",
    "specs": {
      "ბრენდი:": "Ugreen",
      "სწრაფი დამუხტვა:": "Yes",
      "MAX ვატი:": "30 W",
      "პორტი:": "Type-C",
      "პორტების რაოდენობა:": "1",
      "კაბელი:": "No",
      "კაბელის პორტები:": "No",
      "ფერი:": "Healther Grey"
    }
  },
  {
    "category": "დამტენი ადაპტერები",
    "title": "Ugreen 20W 2-Port Fast Charger EU 45310 White",
    "price": 39.0,
    "link": "https://zoommer.ge/mobiluris-aqsesuarebi/ugreen-20w-2-port-fast-charger-eu-45310-white-p46408",
    "image": "/_next/image?url=https%3A%2F%2Fs3.zoommer.ge%2Fsite%2Ff13d517d-7bb1-4bc4-ab82-984f761a291d_Thumb.jpeg&w=384&q=50",
    "product_title_detail": "Ugreen 20W 2-Port Fast Charger EU 45310 White",
    "description": "",
    "specs": {
      "ბრენდი:": "Ugreen",
      "სწრაფი დამუხტვა:": "Yes",
      "MAX ვატი:": "20 W",
      "პორტი:": "Type-C",
      "პორტების რაოდენობა:": "2",
      "კაბელი:": "No",
      "კაბელის პორტები:": "No",
      "ფერი:": "White"
    }
  },
  {
    "category": "დამტენი ადაპტერები",
    "title": "Ugreen Fast Charger EU 10191 Black",
    "price": 29.0,
    "link": "https://zoommer.ge/mobiluris-aqsesuarebi/ugreen-fast-charger-eu-10191-black-p46406",
    "image": "/_next/image?url=https%3A%2F%2Fs3.zoommer.ge%2Fsite%2F4d86b08b-33a5-4f8e-a9b9-4b234d2071e3_Thumb.jpeg&w=384&q=50",
    "product_title_detail": "Ugreen Fast Charger EU 10191 Black",
    "description": "",
    "specs": {
      "ბრენდი:": "Ugreen",
      "სწრაფი დამუხტვა:": "Yes",
      "MAX ვატი:": "20 W",
      "პორტი:": "USB-A",
      "პორტების რაოდენობა:": "1",
      "კაბელი:": "No",
      "კაბელის პორტები:": "No",
      "ფერი:": "Black"
    }
  },
  {
    "category": "დამტენი ადაპტერები",
    "title": "Ugreen QC3.0 USB Fast Charger EU 10133 White",
    "price": 39.0,
    "link": "https://zoommer.ge/mobiluris-aqsesuarebi/ugreen-qc3-0-usb-fast-charger-eu-10133-white-p46404",
    "image": "/_next/image?url=https%3A%2F%2Fs3.zoommer.ge%2Fsite%2F1bb56912-8fa2-46ec-8d18-015268f74b5f_Thumb.jpeg&w=384&q=50",
    "product_title_detail": "Ugreen QC3.0 USB Fast Charger EU 10133 White",
    "description": "",
    "specs": {
      "ბრენდი:": "Ugreen",
      "სწრაფი დამუხტვა:": "Yes",
      "MAX ვატი:": "18 W",
      "პორტი:": "USB-A",
      "პორტების რაოდენობა:": "1",
      "კაბელი:": "No",
      "კაბელის პორტები:": "No",
      "ფერი:": "White"
    }
  },
  {
    "category": "დამტენი ადაპტერები",
    "title": "Ugreen GaN 200W Desktop Charger (6-Port) 40914 Grey",
    "price": 259.0,
    "link": "https://zoommer.ge/mobiluris-aqsesuarebi/ugreen-gan-200w-desktop-charger-6-port-40914-grey-p46396",
    "image": "/_next/image?url=https%3A%2F%2Fs3.zoommer.ge%2Fsite%2F7ccb9728-e807-4c5c-ad10-567a4956b8eb_Thumb.jpeg&w=384&q=50",
    "product_title_detail": "Ugreen GaN 200W Desktop Charger (6-Port) 40914 Grey",
    "description": "",
    "specs": {
      "ბრენდი:": "Ugreen",
      "სწრაფი დამუხტვა:": "Yes",
      "MAX ვატი:": "200 W",
      "პორტი:": "2 x USB-A",
      "პორტების რაოდენობა:": "6",
      "კაბელი:": "Yes",
      "კაბელის პორტები:": "Power cord",
      "ფერი:": "Healther Grey"
    }
  },
  {
    "category": "დამტენი ადაპტერები",
    "title": "Ugreen 20W 2-Port Fast Charger EU 45302 Black",
    "price": 39.0,
    "link": "https://zoommer.ge/mobiluris-aqsesuarebi/ugreen-20w-2-port-fast-charger-eu-45302-black-p46391",
    "image": "/_next/image?url=https%3A%2F%2Fs3.zoommer.ge%2Fsite%2F5a9f7d6a-5b54-4b75-82a2-bf68d8c03cc6_Thumb.jpeg&w=384&q=50",
    "product_title_detail": "Ugreen 20W 2-Port Fast Charger EU 45302 Black",
    "description": "",
    "specs": {
      "ბრენდი:": "Ugreen",
      "სწრაფი დამუხტვა:": "Yes",
      "MAX ვატი:": "20 W",
      "პორტი:": "Type-C",
      "პორტების რაოდენობა:": "2",
      "კაბელი:": "No",
      "კაბელის პორტები:": "No",
      "ფერი:": "Black"
    }
  },
  {
    "category": "დამტენი ადაპტერები",
    "title": "Ugreen USB-C GaN Fast Charger 30W EU 90666 Grey",
    "price": 39.0,
    "link": "https://zoommer.ge/mobiluris-aqsesuarebi/ugreen-usb-c-gan-fast-charger-30w-eu-90666-grey-p46390",
    "image": "/_next/image?url=https%3A%2F%2Fs3.zoommer.ge%2Fsite%2Fa3b3ec34-6d88-41dc-b507-447152371806_Thumb.jpeg&w=384&q=50",
    "product_title_detail": "Ugreen USB-C GaN Fast Charger 30W EU 90666 Grey",
    "description": "",
    "specs": {
      "ბრენდი:": "Ugreen",
      "სწრაფი დამუხტვა:": "Yes",
      "MAX ვატი:": "30 W",
      "პორტი:": "Type-C",
      "პორტების რაოდენობა:": "1",
      "კაბელი:": "No",
      "კაბელის პორტები:": "No",
      "ფერი:": "Healther Grey"
    }
  },
  {
    "category": "დამტენი ადაპტერები",
    "title": "Ugreen Nexode 45W Charger EU 90573 Grey",
    "price": 69.0,
    "link": "https://zoommer.ge/mobiluris-aqsesuarebi/ugreen-nexode-45w-charger-eu-90573-grey-p46373",
    "image": "/_next/image?url=https%3A%2F%2Fs3.zoommer.ge%2Fsite%2F9032ec9d-7254-4bcd-87fe-179a40a8f11a_Thumb.jpeg&w=384&q=50",
    "product_title_detail": "Ugreen Nexode 45W Charger EU 90573 Grey",
    "description": "",
    "specs": {
      "ბრენდი:": "Ugreen",
      "სწრაფი დამუხტვა:": "Yes",
      "MAX ვატი:": "45 W",
      "პორტი:": "2 x Type-C",
      "პორტების რაოდენობა:": "2",
      "კაბელი:": "No",
      "კაბელის პორტები:": "No",
      "ფერი:": "Healther Grey"
    }
  },
  {
    "category": "დამტენი ადაპტერები",
    "title": "Xiaomi 22.5W Power Adapter (Type-A) White",
    "price": 29.0,
    "link": "https://zoommer.ge/mobiluris-aqsesuarebi/xiaomi-22-5w-power-adapter-type-a-white-p46351",
    "image": "/_next/image?url=https%3A%2F%2Fs3.zoommer.ge%2Fsite%2F7d6a1a5f-d11a-46a7-8e12-c66aed5a51e7_Thumb.jpeg&w=384&q=50",
    "product_title_detail": "Xiaomi 22.5W Power Adapter (Type-A) White",
    "description": "",
    "specs": {
      "ბრენდი:": "Xiaomi",
      "სწრაფი დამუხტვა:": "Yes",
      "MAX ვატი:": "22.5 W",
      "პორტი:": "USB-A",
      "პორტების რაოდენობა:": "1",
      "კაბელი:": "No",
      "კაბელის პორტები:": "No",
      "ფერი:": "White"
    }
  },
  {
    "category": "დამტენი ადაპტერები",
    "title": "Belkin USB-C Wall Charger 25W + 1M USB-C to USB-C Cab ...",
    "price": 69.0,
    "link": "https://zoommer.ge/mobiluris-aqsesuarebi/belkin-usb-c-wall-charger-25w-1m-usb-c-to-usb-c-cable-wca004vf1mwh-b6-white-p46316",
    "image": "/_next/image?url=https%3A%2F%2Fs3.zoommer.ge%2Fsite%2Fc5ed46f2-9fc0-4d98-b628-881760b3b40b_Thumb.jpeg&w=384&q=50",
    "product_title_detail": "Belkin USB-C Wall Charger 25W + 1M USB-C to USB-C Cable WCA004vf1MWH-B6 White",
    "description": "",
    "specs": {
      "ბრენდი:": "Belkin",
      "სწრაფი დამუხტვა:": "Yes",
      "MAX ვატი:": "25 W",
      "პორტი:": "Type-C",
      "პორტების რაოდენობა:": "1",
      "კაბელი:": "Yes",
      "კაბელის პორტები:": "Type-C",
      "ფერი:": "White"
    }
  },
  {
    "category": "გარე დამტენები",
    "title": "Ugreen 10000mAh USB-C USB Magsafe Wireless Power Bank ...",
    "price": 139.0,
    "link": "https://zoommer.ge/mobiluris-aqsesuarebi/ugreen-10000mah-usb-c-usb-magsafe-wireless-power-bank-15086-grey-p48675",
    "image": "/_next/image?url=https%3A%2F%2Fs3.zoommer.ge%2Fsite%2F1b612a14-a243-4e70-8918-6373f7979871_Thumb.jpeg&w=384&q=50",
    "product_title_detail": "Ugreen 10000mAh USB-C USB Magsafe Wireless Power Bank 15086 Grey",
    "description": "",
    "specs": {
      "ბრენდი:": "Ugreen",
      "MAX სიმძლავრე:": "20 W",
      "სწრაფი დამუხტვა:": "Yes",
      "Magsafe:": "Yes",
      "Output:": "USB-A , Type-C",
      "Input:": "Type-C",
      "Wireless დამუხტვა:": "Yes",
      "მოცულობა mAh:": "10000 mAh"
    }
  },
  {
    "category": "გარე დამტენები",
    "title": "Ugreen Nexode 12000mAh Type-C USB-A Power Bank With S ...",
    "price": 149.0,
    "link": "https://zoommer.ge/mobiluris-aqsesuarebi/ugreen-nexode-12000mah-type-c-usb-a-power-bank-with-smart-digital-display-35526b-p48674",
    "image": "/_next/image?url=https%3A%2F%2Fs3.zoommer.ge%2Fsite%2F4079b2bf-9830-48d0-a02e-9985017770fa_Thumb.jpeg&w=384&q=50",
    "product_title_detail": "Ugreen Nexode 12000mAh Type-C USB-A Power Bank With Smart Digital Display 35526B Grey",
    "description": "",
    "specs": {
      "ბრენდი:": "Ugreen",
      "MAX სიმძლავრე:": "65 W",
      "სწრაფი დამუხტვა:": "Yes",
      "Magsafe:": "No",
      "Output:": "USB-A , 2 x Type-C",
      "Input:": "Type-C",
      "Wireless დამუხტვა:": "No",
      "მოცულობა mAh:": "12000 mAh"
    }
  },
  {
    "category": "გარე დამტენები",
    "title": "Ugreen 10000mAh Magnetic Wireless Power Bank 45763 Bl ...",
    "price": 139.0,
    "link": "https://zoommer.ge/mobiluris-aqsesuarebi/ugreen-10000mah-magnetic-wireless-power-bank-45763-black-p48665",
    "image": "/_next/image?url=https%3A%2F%2Fs3.zoommer.ge%2Fsite%2Faa991f80-ca5b-408c-8006-c6b4781a5798_Thumb.jpeg&w=384&q=50",
    "product_title_detail": "Ugreen 10000mAh Magnetic Wireless Power Bank 45763 Black",
    "description": "",
    "specs": {
      "ბრენდი:": "Ugreen",
      "MAX სიმძლავრე:": "30 W",
      "სწრაფი დამუხტვა:": "Yes",
      "Magsafe:": "No",
      "Output:": "Type-C",
      "Input:": "Type-C",
      "Wireless დამუხტვა:": "Yes",
      "მოცულობა mAh:": "10000 mAh",
      "ფერი:": "Healther Grey"
    }
  },
  {
    "category": "გარე დამტენები",
    "title": "Ugreen 48000mAh USB-A Type-C Power Bank With Smart Di ...",
    "price": 399.0,
    "link": "https://zoommer.ge/mobiluris-aqsesuarebi/ugreen-48000mah-usb-a-type-c-power-bank-with-smart-digital-display-25286-grey-p48664",
    "image": "/_next/image?url=https%3A%2F%2Fs3.zoommer.ge%2Fsite%2Ff2cfd9a1-9bd5-48ad-827f-29945085cb96_Thumb.jpeg&w=384&q=50",
    "product_title_detail": "Ugreen 48000mAh USB-A Type-C Power Bank With Smart Digital Display 25286 Grey",
    "description": "",
    "specs": {
      "ბრენდი:": "Ugreen",
      "MAX სიმძლავრე:": "140 W",
      "სწრაფი დამუხტვა:": "Yes",
      "Magsafe:": "No",
      "Output:": "2 x USB-A, 3 x Type-C",
      "Input:": "Type-C",
      "Wireless დამუხტვა:": "No",
      "მოცულობა mAh:": "48000 mAh"
    }
  },
  {
    "category": "გარე დამტენები",
    "title": "Ugreen Uno 10000mAh Magnetic Wireless Power Bank 4532 ...",
    "price": 169.0,
    "link": "https://zoommer.ge/mobiluris-aqsesuarebi/ugreen-uno-10000mah-magnetic-wireless-power-bank-45327-grey-p48618",
    "image": "/_next/image?url=https%3A%2F%2Fs3.zoommer.ge%2Fsite%2F7428c5de-1029-432c-8f54-7ce8e33b78ea_Thumb.jpeg&w=384&q=50",
    "product_title_detail": "Ugreen Uno 10000mAh Magnetic Wireless Power Bank 45327 Grey",
    "description": "",
    "specs": {
      "ბრენდი:": "Ugreen",
      "MAX სიმძლავრე:": "20 W",
      "სწრაფი დამუხტვა:": "Yes",
      "Magsafe:": "No",
      "Output:": "Type-C",
      "Input:": "Type-C",
      "Wireless დამუხტვა:": "Yes",
      "მოცულობა mAh:": "10000 mAh",
      "ფერი:": "Healther Grey"
    }
  },
  {
    "category": "გარე დამტენები",
    "title": "Anker MagGo PowerBank 10000mAh For Apple Watch A1657 ...",
    "price": 249.0,
    "link": "https://zoommer.ge/mobiluris-aqsesuarebi/anker-maggo-powerbank-10000mah-for-apple-watch-a1657-black-p48440",
    "image": "/_next/image?url=https%3A%2F%2Fs3.zoommer.ge%2Fsite%2Ff81e4cac-ae3f-40b9-84f7-961d41b6d582_Thumb.jpeg&w=384&q=50",
    "product_title_detail": "Anker MagGo PowerBank 10000mAh For Apple Watch A1657 Black",
    "description": "",
    "specs": {
      "ბრენდი:": "Anker",
      "MAX სიმძლავრე:": "35 W",
      "სწრაფი დამუხტვა:": "Yes",
      "Magsafe:": "Yes",
      "Output:": "Type-C",
      "Input:": "Type-C",
      "Wireless დამუხტვა:": "Yes",
      "მოცულობა mAh:": "10000 mAh",
      "ფერი:": "Black"
    }
  },
  {
    "category": "გარე დამტენები",
    "title": "Anker MagGo PowerBank 10000mAh A1654 White",
    "price": 299.0,
    "link": "https://zoommer.ge/mobiluris-aqsesuarebi/anker-maggo-powerbank-10000mah-a1654-white-p48439",
    "image": "/_next/image?url=https%3A%2F%2Fs3.zoommer.ge%2Fsite%2F0d1f783d-f5aa-4b40-8b9f-fdeb70e5478e_Thumb.jpeg&w=384&q=50",
    "product_title_detail": "Anker MagGo PowerBank 10000mAh A1654 White",
    "description": "",
    "specs": {
      "ბრენდი:": "Anker",
      "MAX სიმძლავრე:": "15 W",
      "სწრაფი დამუხტვა:": "Yes",
      "Magsafe:": "Yes",
      "Output:": "Type-C",
      "Input:": "Type-C",
      "Wireless დამუხტვა:": "Yes",
      "მოცულობა mAh:": "10000 mAh",
      "ფერი:": "White"
    }
  },
  {
    "category": "გარე დამტენები",
    "title": "Anker MagGo PowerBank 10000mAh A1654 Black",
    "price": 299.0,
    "link": "https://zoommer.ge/mobiluris-aqsesuarebi/anker-maggo-powerbank-10000mah-a1654-black-p48438",
    "image": "/_next/image?url=https%3A%2F%2Fs3.zoommer.ge%2Fsite%2F8bdd76bf-0e16-4005-9376-acfcc73ee4b0_Thumb.jpeg&w=384&q=50",
    "product_title_detail": "Anker MagGo PowerBank 10000mAh A1654 Black",
    "description": "",
    "specs": {
      "ბრენდი:": "Anker",
      "MAX სიმძლავრე:": "15 W",
      "სწრაფი დამუხტვა:": "Yes",
      "Magsafe:": "Yes",
      "Output:": "Type-C",
      "Input:": "Type-C",
      "Wireless დამუხტვა:": "Yes",
      "მოცულობა mAh:": "10000 mAh",
      "ფერი:": "Black"
    }
  },
  {
    "category": "გარე დამტენები",
    "title": "Ecoflow Rapid Wireless Power Bank 5000mAh Grey",
    "price": 199.0,
    "link": "https://zoommer.ge/mobiluris-aqsesuarebi/ecoflow-rapid-wireless-power-bank-5000mah-grey-p47546",
    "image": "/_next/image?url=https%3A%2F%2Fs3.zoommer.ge%2Fsite%2F2c2e8ca8-48ec-4d1e-9e99-90a1b8f279c3_Thumb.jpeg&w=384&q=50",
    "product_title_detail": "Ecoflow Rapid Wireless Power Bank 5000mAh Grey",
    "description": "",
    "specs": {
      "ბრენდი:": "EcoFlow",
      "MAX სიმძლავრე:": "30 W",
      "სწრაფი დამუხტვა:": "Yes",
      "Magsafe:": "Yes",
      "Output:": "Type-C",
      "Input:": "Type-C",
      "Wireless დამუხტვა:": "Yes",
      "მოცულობა mAh:": "5000 mAh",
      "ფერი:": "Gray"
    }
  },
  {
    "category": "გარე დამტენები",
    "title": "Xiaomi 18W Power Bank 30000mAh BHR9126GL Black",
    "price": 149.0,
    "link": "https://zoommer.ge/mobiluris-aqsesuarebi/xiaomi-18w-power-bank-30000mah-bhr9126gl-black-p47460",
    "image": "/_next/image?url=https%3A%2F%2Fs3.zoommer.ge%2Fsite%2F0a550d0a-0e72-4499-a745-102e1a75ab7c_Thumb.jpeg&w=384&q=50",
    "product_title_detail": "Xiaomi 18W Power Bank 30000mAh BHR9126GL Black",
    "description": "",
    "specs": {
      "ბრენდი:": "Xiaomi",
      "MAX სიმძლავრე:": "18 W",
      "სწრაფი დამუხტვა:": "Yes",
      "Magsafe:": "No",
      "Output:": "Type-C",
      "Input:": "Type-C",
      "Wireless დამუხტვა:": "No",
      "მოცულობა mAh:": "30000 mAh",
      "ფერი:": "Black"
    }
  },
  {
    "category": "გარე დამტენები",
    "title": "Anker Powerbank 20000mAh 30W C-L A1681 Black",
    "price": 219.0,
    "link": "https://zoommer.ge/mobiluris-aqsesuarebi/anker-powerbank-20000mah-30w-c-l-a1681-black-p47342",
    "image": "/_next/image?url=https%3A%2F%2Fs3.zoommer.ge%2Fsite%2F0963e14a-2659-402e-9127-50c29a864db7_Thumb.jpeg&w=384&q=50",
    "product_title_detail": "Anker Powerbank 20000mAh 30W C-L A1681 Black",
    "description": "",
    "specs": {
      "ბრენდი:": "Anker",
      "MAX სიმძლავრე:": "30 W",
      "სწრაფი დამუხტვა:": "Yes",
      "Magsafe:": "No",
      "Output:": "2 x Type-C",
      "Input:": "Type-C",
      "Wireless დამუხტვა:": "No",
      "მოცულობა mAh:": "20000 mAh",
      "ფერი:": "Black"
    }
  },
  {
    "category": "გარე დამტენები",
    "title": "Anker Powerbank 10000mAh 30W USB-C A1688 Black",
    "price": 159.0,
    "link": "https://zoommer.ge/mobiluris-aqsesuarebi/anker-powerbank-10000mah-30w-usb-c-a1688-black-p47341",
    "image": "/_next/image?url=https%3A%2F%2Fs3.zoommer.ge%2Fsite%2F0305e55a-546a-498d-b3ce-5040fb4debfa_Thumb.jpeg&w=384&q=50",
    "product_title_detail": "Anker Powerbank 10000mAh 30W USB-C A1688 Black",
    "description": "",
    "specs": {
      "ბრენდი:": "Anker",
      "MAX სიმძლავრე:": "30 W",
      "სწრაფი დამუხტვა:": "Yes",
      "Magsafe:": "No",
      "Output:": "2 x Type-C",
      "Input:": "Type-C",
      "Wireless დამუხტვა:": "No",
      "მოცულობა mAh:": "10000 mAh",
      "ფერი:": "Black"
    }
  },
  {
    "category": "გარე დამტენები",
    "title": "Anker Powerbank 10000mAh 30W C-L A1680 Black",
    "price": 179.0,
    "link": "https://zoommer.ge/mobiluris-aqsesuarebi/anker-powerbank-10000mah-30w-c-l-a1680-black-p47340",
    "image": "/_next/image?url=https%3A%2F%2Fs3.zoommer.ge%2Fsite%2F0c74e5a0-b90a-4e68-b9f3-7c5d5c17b2b8_Thumb.jpeg&w=384&q=50",
    "product_title_detail": "Anker Powerbank 10000mAh 30W C-L A1680 Black",
    "description": "",
    "specs": {
      "ბრენდი:": "Anker",
      "MAX სიმძლავრე:": "30 W",
      "სწრაფი დამუხტვა:": "Yes",
      "Magsafe:": "No",
      "Output:": "2 x Type-C",
      "Input:": "Type-C",
      "Wireless დამუხტვა:": "No",
      "მოცულობა mAh:": "10000 mAh",
      "ფერი:": "Black"
    }
  },
  {
    "category": "გარე დამტენები",
    "title": "Lenovo Go USB-C Laptop Power Bank 20000 mAh Grey",
    "price": 349.0,
    "link": "https://zoommer.ge/mobiluris-aqsesuarebi/lenovo-go-usb-c-laptop-power-bank-20000-mah-grey-p47232",
    "image": "/_next/image?url=https%3A%2F%2Fs3.zoommer.ge%2Fsite%2F0cf3ddbc-1ddb-4e6a-a54c-869abd990d12_Thumb.jpeg&w=384&q=50",
    "product_title_detail": "Lenovo Go USB-C Laptop Power Bank 20000 mAh Grey",
    "description": "",
    "specs": {
      "ბრენდი:": "Lenovo",
      "MAX სიმძლავრე:": "65 W",
      "სწრაფი დამუხტვა:": "Yes",
      "Magsafe:": "No",
      "Output:": "2 x Type-C",
      "Input:": "2 x Type-C",
      "Wireless დამუხტვა:": "No",
      "მოცულობა mAh:": "20000 mAh",
      "ფერი:": "Healther Grey"
    }
  },
  {
    "category": "გარე დამტენები",
    "title": "Xiaomi 165W Power Bank 10000mAh Integrated Cable Gray",
    "price": 199.0,
    "link": "https://zoommer.ge/mobiluris-aqsesuarebi/xiaomi-165w-power-bank-10000mah-integrated-cable-gray-p47084",
    "image": "/_next/image?url=https%3A%2F%2Fs3.zoommer.ge%2Fsite%2Fa87443c2-a328-47d6-898e-10bb13ccc552_Thumb.jpeg&w=384&q=50",
    "product_title_detail": "Xiaomi 165W Power Bank 10000mAh Integrated Cable Gray",
    "description": "",
    "specs": {
      "ბრენდი:": "Xiaomi",
      "MAX სიმძლავრე:": "165 W",
      "სწრაფი დამუხტვა:": "Yes",
      "Magsafe:": "No",
      "Output:": "USB-C",
      "Input:": "2 x Type-C",
      "Wireless დამუხტვა:": "No",
      "მოცულობა mAh:": "10000 mAh",
      "ფერი:": "Healther Grey"
    }
  },
  {
    "category": "გარე დამტენები",
    "title": "Ugreen Nexode with Smart Digital Display 25000mAh Typ ...",
    "price": 299.0,
    "link": "https://zoommer.ge/mobiluris-aqsesuarebi/ugreen-nexode-with-smart-digital-display-25000mah-type-c-power-bank-35525b-grey-p46510",
    "image": "/_next/image?url=https%3A%2F%2Fs3.zoommer.ge%2Fsite%2F8148a7b5-14ac-4609-a598-af780fcf262c_Thumb.jpeg&w=384&q=50",
    "product_title_detail": "Ugreen Nexode with Smart Digital Display 25000mAh Type-C Power Bank 35525B Grey",
    "description": "",
    "specs": {
      "ბრენდი:": "Ugreen",
      "MAX სიმძლავრე:": "200 W",
      "სწრაფი დამუხტვა:": "Yes",
      "Magsafe:": "No",
      "Output:": "2 x Type-C",
      "Input:": "2 x Type-C",
      "Wireless დამუხტვა:": "No",
      "მოცულობა mAh:": "25000 mAh",
      "ფერი:": "Healther Grey"
    }
  },
  {
    "category": "გარე დამტენები",
    "title": "Ugreen 5000mAh USB Type-C Power Bank 35338 Grey",
    "price": 109.0,
    "link": "https://zoommer.ge/mobiluris-aqsesuarebi/ugreen-5000mah-usb-type-c-power-bank-35338-grey-p46509",
    "image": "/_next/image?url=https%3A%2F%2Fs3.zoommer.ge%2Fsite%2F8c9ee339-856a-46a4-b104-b5e9aedb4cab_Thumb.jpeg&w=384&q=50",
    "product_title_detail": "Ugreen 5000mAh USB Type-C Power Bank 35338 Grey",
    "description": "",
    "specs": {
      "ბრენდი:": "Ugreen",
      "MAX სიმძლავრე:": "20 W",
      "სწრაფი დამუხტვა:": "Yes",
      "Magsafe:": "No",
      "Output:": "Type-C",
      "Input:": "Type-C",
      "Wireless დამუხტვა:": "No",
      "მოცულობა mAh:": "5000 mAh",
      "ფერი:": "Healther Grey"
    }
  },
  {
    "category": "გარე დამტენები",
    "title": "Ugreen 25000mAh Type-C Power Bank 90597A Grey",
    "price": 249.0,
    "link": "https://zoommer.ge/mobiluris-aqsesuarebi/ugreen-25000mah-type-c-power-bank-90597a-grey-p46508",
    "image": "/_next/image?url=https%3A%2F%2Fs3.zoommer.ge%2Fsite%2Fa2c8c9f2-5513-4c02-a60a-8ae475a46e16_Thumb.jpeg&w=384&q=50",
    "product_title_detail": "Ugreen 25000mAh Type-C Power Bank 90597A Grey",
    "description": "",
    "specs": {
      "ბრენდი:": "Ugreen",
      "MAX სიმძლავრე:": "145 W",
      "სწრაფი დამუხტვა:": "Yes",
      "Magsafe:": "No",
      "Output:": "2 x Type-C",
      "Input:": "2 x Type-C",
      "Wireless დამუხტვა:": "No",
      "მოცულობა mAh:": "25000 mAh",
      "ფერი:": "Healther Grey"
    }
  },
  {
    "category": "გარე დამტენები",
    "title": "Ugreen 20000mAh USB Type-C Two-way Power Bank 25683 B ...",
    "price": 129.0,
    "link": "https://zoommer.ge/mobiluris-aqsesuarebi/ugreen-20000mah-usb-type-c-two-way-power-bank-25683-black-p46507",
    "image": "/_next/image?url=https%3A%2F%2Fs3.zoommer.ge%2Fsite%2Fada5a14e-352e-44db-8302-daa21351b035_Thumb.jpeg&w=384&q=50",
    "product_title_detail": "Ugreen 20000mAh USB Type-C Two-way Power Bank 25683 Black",
    "description": "",
    "specs": {
      "ბრენდი:": "Ugreen",
      "MAX სიმძლავრე:": "20 W",
      "სწრაფი დამუხტვა:": "Yes",
      "Magsafe:": "No",
      "Output:": "Type-C",
      "Input:": "Type-C",
      "Wireless დამუხტვა:": "No",
      "მოცულობა mAh:": "20000 mAh",
      "ფერი:": "Black"
    }
  },
  {
    "category": "გარე დამტენები",
    "title": "Ugreen Nexode with Smart Digital Display 20000mAh Typ ...",
    "price": 199.0,
    "link": "https://zoommer.ge/mobiluris-aqsesuarebi/ugreen-nexode-with-smart-digital-display-20000mah-type-c-power-bank-35524b-grey-p46505",
    "image": "/_next/image?url=https%3A%2F%2Fs3.zoommer.ge%2Fsite%2Fade41fc2-8239-4ab8-ad6c-79c36ee7fc94_Thumb.jpeg&w=384&q=50",
    "product_title_detail": "Ugreen Nexode with Smart Digital Display 20000mAh Type-C Power Bank 35524B Grey",
    "description": "",
    "specs": {
      "ბრენდი:": "Ugreen",
      "MAX სიმძლავრე:": "100 W",
      "სწრაფი დამუხტვა:": "Yes",
      "Magsafe:": "No",
      "Output:": "2 x Type-C",
      "Input:": "Type-C",
      "Wireless დამუხტვა:": "No",
      "მოცულობა mAh:": "20000 mAh",
      "ფერი:": "Healther Grey"
    }
  },
  {
    "category": "გარე დამტენები",
    "title": "Ugreen 20000mAh USB Type-C Two-way Power Bank 25188 G ...",
    "price": 199.0,
    "link": "https://zoommer.ge/mobiluris-aqsesuarebi/ugreen-20000mah-usb-type-c-two-way-power-bank-25188-grey-p46504",
    "image": "/_next/image?url=https%3A%2F%2Fs3.zoommer.ge%2Fsite%2F9d4fcb3a-12ff-4f95-8cf5-4edbda56fa85_Thumb.jpeg&w=384&q=50",
    "product_title_detail": "Ugreen 20000mAh USB Type-C Two-way Power Bank 25188 Grey",
    "description": "",
    "specs": {
      "ბრენდი:": "Ugreen",
      "MAX სიმძლავრე:": "100 W",
      "სწრაფი დამუხტვა:": "Yes",
      "Magsafe:": "No",
      "Output:": "2 x Type-C",
      "Input:": "Type-C",
      "Wireless დამუხტვა:": "No",
      "მოცულობა mAh:": "20000 mAh",
      "ფერი:": "Healther Grey"
    }
  },
  {
    "category": "გარე დამტენები",
    "title": "Ugreen 10000mAh USB-C Magnetic Power Bank 25208 Beige",
    "price": 149.0,
    "link": "https://zoommer.ge/mobiluris-aqsesuarebi/ugreen-10000mah-usb-c-magnetic-power-bank-25208-beige-p46503",
    "image": "/_next/image?url=https%3A%2F%2Fs3.zoommer.ge%2Fsite%2Fb432927e-789e-421a-9f5b-36343de7282d_Thumb.jpeg&w=384&q=50",
    "product_title_detail": "Ugreen 10000mAh USB-C Magnetic Power Bank 25208 Beige",
    "description": "",
    "specs": {
      "ბრენდი:": "Ugreen",
      "MAX სიმძლავრე:": "20 W",
      "სწრაფი დამუხტვა:": "Yes",
      "Magsafe:": "Yes",
      "Output:": "Type-C",
      "Input:": "Type-C",
      "Wireless დამუხტვა:": "Yes",
      "მოცულობა mAh:": "10000 mAh",
      "ფერი:": "Beige"
    }
  },
  {
    "category": "გარე დამტენები",
    "title": "Ugreen 10000mAh Type-C Magnetic Power Bank 25919 Grey",
    "price": 129.0,
    "link": "https://zoommer.ge/mobiluris-aqsesuarebi/ugreen-10000mah-type-c-magnetic-power-bank-25919-grey-p46502",
    "image": "/_next/image?url=https%3A%2F%2Fs3.zoommer.ge%2Fsite%2F863a5814-ed99-4ef4-91bf-2c61dfff2758_Thumb.jpeg&w=384&q=50",
    "product_title_detail": "Ugreen 10000mAh Type-C Magnetic Power Bank 25919 Grey",
    "description": "",
    "specs": {
      "ბრენდი:": "Ugreen",
      "MAX სიმძლავრე:": "20 W",
      "სწრაფი დამუხტვა:": "Yes",
      "Magsafe:": "Yes",
      "Output:": "Type-C",
      "Input:": "Type-C",
      "Wireless დამუხტვა:": "Yes",
      "მოცულობა mAh:": "10000 mAh",
      "ფერი:": "Healther Grey"
    }
  },
  {
    "category": "გარე დამტენები",
    "title": "Ugreen Nexode 10000mAh USB Type-C Power Bank 25185 Gr ...",
    "price": 159.0,
    "link": "https://zoommer.ge/mobiluris-aqsesuarebi/ugreen-nexode-10000mah-usb-type-c-power-bank-25185-grey-p46501",
    "image": "/_next/image?url=https%3A%2F%2Fs3.zoommer.ge%2Fsite%2F79cfdd0e-9d3c-4dbc-978b-55a66f75db93_Thumb.jpeg&w=384&q=50",
    "product_title_detail": "Ugreen Nexode 10000mAh USB Type-C Power Bank 25185 Grey",
    "description": "",
    "specs": {
      "ბრენდი:": "Ugreen",
      "MAX სიმძლავრე:": "30 W",
      "სწრაფი დამუხტვა:": "Yes",
      "Magsafe:": "No",
      "Output:": "Type-C",
      "Input:": "Type-C",
      "Wireless დამუხტვა:": "No",
      "მოცულობა mAh:": "10000 mAh",
      "ფერი:": "Healther Grey"
    }
  },
  {
    "category": "გარე დამტენები",
    "title": "Ugreen 10000mAh USB-C Two-way Power Bank 25742 Black",
    "price": 89.0,
    "link": "https://zoommer.ge/mobiluris-aqsesuarebi/ugreen-10000mah-usb-c-two-way-power-bank-25742-black-p46499",
    "image": "/_next/image?url=https%3A%2F%2Fs3.zoommer.ge%2Fsite%2Fb3609b6c-f051-440d-a7b1-90df0e1e5011_Thumb.jpeg&w=384&q=50",
    "product_title_detail": "Ugreen 10000mAh USB-C Two-way Power Bank 25742 Black",
    "description": "",
    "specs": {
      "ბრენდი:": "Ugreen",
      "MAX სიმძლავრე:": "20 W",
      "სწრაფი დამუხტვა:": "Yes",
      "Magsafe:": "No",
      "Output:": "2 x Type-C",
      "Input:": "Type-C",
      "Wireless დამუხტვა:": "No",
      "მოცულობა mAh:": "10000 mAh",
      "ფერი:": "Black"
    }
  },
  {
    "category": "გარე დამტენები",
    "title": "Xiaomi Magnetic Power Bank 6000mAh BHR9074GL White",
    "price": 199.0,
    "link": "https://zoommer.ge/mobiluris-aqsesuarebi/xiaomi-magnetic-power-bank-6000mah-bhr9074gl-white-p46267",
    "image": "/_next/image?url=https%3A%2F%2Fs3.zoommer.ge%2Fsite%2F64bb756e-f2a4-4cb6-a5ef-a980622af503_Thumb.jpeg&w=384&q=50",
    "product_title_detail": "Xiaomi Magnetic Power Bank 6000mAh BHR9074GL White",
    "description": "",
    "specs": {
      "ბრენდი:": "Xiaomi",
      "MAX სიმძლავრე:": "15 W",
      "სწრაფი დამუხტვა:": "Yes",
      "Magsafe:": "No",
      "Output:": "Type-C",
      "Input:": "Type-C",
      "Wireless დამუხტვა:": "Yes",
      "მოცულობა mAh:": "6000 mAh",
      "ფერი:": "White"
    }
  },
  {
    "category": "გარე დამტენები",
    "title": "Xiaomi 33W Integrated Cable Power Bank 20000mAh White",
    "price": 129.0,
    "link": "https://zoommer.ge/mobiluris-aqsesuarebi/xiaomi-33w-integrated-cable-power-bank-20000mah-white-p46265",
    "image": "/_next/image?url=https%3A%2F%2Fs3.zoommer.ge%2Fsite%2F01e58f4d-90c5-4deb-945b-e827d661b791_Thumb.jpeg&w=384&q=50",
    "product_title_detail": "Xiaomi 33W Integrated Cable Power Bank 20000mAh White",
    "description": "",
    "specs": {
      "ბრენდი:": "Xiaomi",
      "MAX სიმძლავრე:": "18 W",
      "სწრაფი დამუხტვა:": "Yes",
      "Magsafe:": "No",
      "Output:": "Type-C",
      "Input:": "Type-C",
      "Wireless დამუხტვა:": "No",
      "მოცულობა mAh:": "20000mAh",
      "ფერი:": "White"
    }
  },
  {
    "category": "გარე დამტენები",
    "title": "Xiaomi 33W Integrated Cable Power Bank 20000mAh Blue",
    "price": 129.0,
    "link": "https://zoommer.ge/mobiluris-aqsesuarebi/xiaomi-33w-integrated-cable-power-bank-20000mah-blue-p46264",
    "image": "/_next/image?url=https%3A%2F%2Fs3.zoommer.ge%2Fsite%2Fd84886fa-18ef-404f-8c57-e18cf78c8b7a_Thumb.jpeg&w=384&q=50",
    "product_title_detail": "Xiaomi 33W Integrated Cable Power Bank 20000mAh Blue",
    "description": "",
    "specs": {
      "ბრენდი:": "Xiaomi",
      "MAX სიმძლავრე:": "18 W",
      "სწრაფი დამუხტვა:": "Yes",
      "Magsafe:": "No",
      "Output:": "Type-C",
      "Input:": "Type-C",
      "Wireless დამუხტვა:": "No",
      "მოცულობა mAh:": "20000mAh",
      "ფერი:": "Blue"
    }
  }
]